Workbook

Sheet Budgeted_Data
A1: Plant Name | B1: Date | C1: Month | D1: Month | E1: Daily_Gen | F1: Daily_GTI | G1: Daily_GHI | H1: Ambt_Temp | I1: PR_% | J1: CUF_% | K1: TArray | L1: TArrWtd | M1: Connected_DC
A2: Devki_Galol | B2: 45747 | M2: 2411
A3: Devki_Galol | B3: 45748 | E3: 13840.923 | F3: 6.912086 | G3: 6.70334 | H3: 26.93375 | I3: 0.83053646 | J3: 0.23919748 | M3: 2411
A4: Devki_Galol | B4: 45749 | E4: 14376.17 | F4: 7.239875 | G4: 7.020655 | H4: 27.329583 | I4: 0.8235973 | J4: 0.24844756 | M4: 2411
A5: Devki_Galol | B5: 45750 | E5: 15037.604 | F5: 7.636371 | G5: 7.409505 | H5: 28.335833 | I5: 0.8167599 | J5: 0.2598784 | M5: 2411
A6: Devki_Galol | B6: 45751 | E6: 15285.896 | F6: 7.804267 | G6: 7.575568 | H6: 28.312083 | I6: 0.81238438 | J6: 0.26416936 | M6: 2411
A7: Devki_Galol | B7: 45752 | E7: 11354.473 | F7: 5.709052 | G7: 5.48408 | H7: 31.057083 | I7: 0.82490847 | J7: 0.19622689 | M7: 2411
A8: Devki_Galol | B8: 45753 | E8: 7535.2082 | F8: 3.73304 | G8: 3.581261 | H8: 30.49625 | I8: 0.83721192 | J8: 0.13022273 | M8: 2411
A9: Devki_Galol | B9: 45754 | E9: 12448.484 | F9: 6.303896 | G9: 6.093292 | H9: 31.315417 | I9: 0.81904961 | J9: 0.21513348 | M9: 2411
A10: Devki_Galol | B10: 45755 | E10: 13600.049 | F10: 6.903413 | G10: 6.681604 | H10: 30.829583 | I10: 0.81710788 | J10: 0.23503472 | M10: 2411
A11: Devki_Galol | B11: 45756 | E11: 14605.407 | F11: 7.448123 | G11: 7.209586 | H11: 30.139167 | I11: 0.81333527 | J11: 0.25240921 | M11: 2411
A12: Devki_Galol | B12: 45757 | E12: 13864.935 | F12: 7.092537 | G12: 6.865894 | H12: 31.866667 | I12: 0.81080984 | J12: 0.23961245 | M12: 2411
A13: Devki_Galol | B13: 45758 | E13: 14736.226 | F13: 7.611165 | G13: 7.370474 | H13: 32.427917 | I13: 0.80304137 | J13: 0.25467002 | M13: 2411
A14: Devki_Galol | B14: 45759 | E14: 14692.529 | F14: 7.4782 | G14: 7.242306 | H14: 29.682917 | I14: 0.81489615 | J14: 0.25391485 | M14: 2411
... A366: Devki_Galol | B366: 46111 | E366: 13702.313 | F366: 6.93729 | G366: 6.724865 | H366: 29.510833 | I366: 0.81923183 | J366: 0.23680203 | M366: 2411
A367: Devki_Galol | B367: 46112 | E367: 14336.751 | F367: 7.350502 | G367: 7.130775 | H367: 30.856667 | I367: 0.80897765 | J367: 0.24776633

Sheet E-Mail_Copy
A1: Plant_Performance_of_Mandapara_GJ
B3: =DATE(YEAR(B4),MONTH(B4),1) -> 46174 | C3: =VLOOKUP(L3,Basic_Data!$A$28:$B$48,2,0) -> 45748 | L3: 25-26
A4: Date | B4: 46181 | C4: AC Capacity: | E4: =Basic_Data!F10 -> 1925 | F4: DC Capacity: | H4: =Basic_Data!G10 -> 2411.08 | I4: D.O.C.: | K4: =Basic_Data!B3 -> 45745
A5: Plant Name | C5: Daily | F5: MTD | I5: YTD
C6: Budgeted | D6: Actual | E6: Variation(%) | F6: Budgeted | G6: Actual | H6: Variation(%) | I6: Budgeted | J6: Actual | K6: Variation(%)
A7: Generation_MW | C7: =SUMIFS(Budgeted_Data!$E:$E,Budgeted_Data!$B:$B,'E-Mail_Copy'!$B$4) -> 0 | D7: =SUMIFS(Data_Entry!$T:$T,Data_Entry!$C:$C,'E-Mail_Copy'!$B$4) -> 12960 | E7: =(D7-C7)/C7 -> #DIV/0! | F7: =SUMIFS(Budgeted_Data!$E:$E,Budgeted_Data!$B:$B,">="&'E-Mail_Copy'!$B$3,Budgeted_Data!$B:$B,"<="&'E-Mail_Copy'!$B$4) -> 0 | G7: =SUMIFS(Data_Entry!$T:$T,Data_Entry!$C:$C,">="&'E-Mail_Copy'!$B$3,Data_Entry!$C:$C,"<="&'E-Mail_Copy'!$B$4) -> 95070 | H7: =(G7-F7)/F7 -> #DIV/0! | I7: =SUMIFS(Budgeted_Data!$E:$E,Budgeted_Data!$B:$B,">="&'E-Mail_Copy'!$C$3,Budgeted_Data!$B:$B,"<="&'E-Mail_Copy'!$B$4) -> 4073422.4 | J7: =SUMIFS(Data_Entry!$T:$T,Data_Entry!$C:$C,">="&'E-Mail_Copy'!$C$3,Data_Entry!$C:$C,"<="&'E-Mail_Copy'!$B$4) -> 4734060 | K7: =(J7-I7)/I7 -> 0.16218245
A8: GTI (Kwh/m2) | C8: =SUMIFS(Budgeted_Data!$F:$F,Budgeted_Data!$B:$B,'E-Mail_Copy'!$B$4) -> 0 | D8: =SUMIFS(Data_Entry!$V:$V,Data_Entry!$C:$C,'E-Mail_Copy'!B4) -> 4.36 | E8: =(D8-C8)/C8 -> #DIV/0! | F8: =SUMIFS(Budgeted_Data!$F:$F,Budgeted_Data!$B:$B,">="&'E-Mail_Copy'!$B$3,Budgeted_Data!$B:$B,"<="&'E-Mail_Copy'!$B$4) -> 0 | G8: =SUMIFS(Data_Entry!$V:$V,Data_Entry!$C:$C,">="&'E-Mail_Copy'!$B$3,Data_Entry!$C:$C,"<="&'E-Mail_Copy'!$B$4) -> 37.95 | H8: =(G8-F8)/F8 -> #DIV/0! | I8: =SUMIFS(Budgeted_Data!$F:$F,Budgeted_Data!$B:$B,">="&'E-Mail_Copy'!$C$3,Budgeted_Data!$B:$B,"<="&'E-Mail_Copy'!$B$4) -> 2079.3683 | J8: =SUMIFS(Data_Entry!$V:$V,Data_Entry!$C:$C,">="&'E-Mail_Copy'!$C$3,Data_Entry!$C:$C,"<="&'E-Mail_Copy'!$B$4) -> 1678.168 | K8: =(J8-I8)/I8 -> -0.19294335
A9: GHI (Kwh/m2) | C9: =SUMIFS(Budgeted_Data!$G:$G,Budgeted_Data!$B:$B,'E-Mail_Copy'!$B$4) -> 0 | D9: =SUMIFS(Data_Entry!$U:$U,Data_Entry!$C:$C,'E-Mail_Copy'!$B$4) -> 0 | E9: =(D9-C9)/C9 -> #DIV/0! | F9: =SUMIFS(Budgeted_Data!$G:$G,Budgeted_Data!$B:$B,">="&'E-Mail_Copy'!$B$3,Budgeted_Data!$B:$B,"<="&'E-Mail_Copy'!$B$4) -> 0 | G9: =SUMIFS(Data_Entry!$U:$U,Data_Entry!$C:$C,">="&'E-Mail_Copy'!$B$3,Data_Entry!$C:$C,"<="&'E-Mail_Copy'!$B$4) -> 0 | H9: =(G9-F9)/F9 -> #DIV/0! | I9: =SUMIFS(Budgeted_Data!$G:$G,Budgeted_Data!$B:$B,">="&'E-Mail_Copy'!$C$3,Budgeted_Data!$B:$B,"<="&'E-Mail_Copy'!$B$4) -> 2005.4308 | J9: =SUMIFS(Data_Entry!$U:$U,Data_Entry!$C:$C,">="&'E-Mail_Copy'!$C$3,Data_Entry!$C:$C,"<="&'E-Mail_Copy'!$B$4) -> 3.9 | K9: =(J9-I9)/I9 -> -0.99805528
A10: PR_(%) | C10: =C7/C8/H4 -> #DIV/0! | D10: =D7/D8/H4 -> 1.2328405 | E10: =(D10-C10)/C10 -> #DIV/0! | F10: =F7/F8/H4/(B4-B3+1) -> #DIV/0! | G10: =G7/G8/H4/(B4-B3+1) -> 0.12987636 | H10: =(G10-F10)/F10 -> #DIV/0! | I10: =I7/I8/H4/(($B$4-$C$3)+1) -> 0.0018720898 | J10: =J7/J8/H4/(($B$4-$C$3)+1) -> 0.0026958577 | K10: =(J10-I10)/I10 -> 0.44002586
A11: CUF_(%) | C11: =C7/E4/24 -> 0 | D11: =D7/24/E4 -> 0.28051948 | E11: =(D11-C11)/C11 -> #DIV/0! | F11: =F7/24/E4/(B4-B3+1) -> 0 | G11: =G7/24/E4/(B4-B3+1) -> 0.25722403 | H11: =(G11-F11)/F11 -> #DIV/0! | I11: =I7/24/$E$4/(($B$4-$C$3)+1) -> 0.2031551 | J11: =J7/24/$E$4/(($B$4-$C$3)+1) -> 0.2361033 | K11: =(J11-I11)/I11 -> 0.16218245
A12: Wtd_Module_Temp | C12: =AVERAGEIFS(Budgeted_Data!$L:$L,Budgeted_Data!$B:$B,'E-Mail_Copy'!$B$4) -> #DIV/0! | D12: =AVERAGEIFS(Data_Entry!$Y:$Y,Data_Entry!$C:$C,'E-Mail_Copy'!$B$4) -> #DIV/0! | E12: =(D12-C12)/C12 -> #DIV/0! | F12: =AVERAGEIFS(Budgeted_Data!$L:$L,Budgeted_Data!$B:$B,">="&'E-Mail_Copy'!$B$3,Budgeted_Data!$B:$B,"<="&'E-Mail_Copy'!$B$4) -> #DIV/0! | G12: =AVERAGEIFS(Data_Entry!$Y:$Y,Data_Entry!$C:$C,">="&'E-Mail_Copy'!$B$3,Data_Entry!$C:$C,"<="&'E-Mail_Copy'!$B$4) -> #DIV/0! | H12: =(G12-F12)/F12 -> #DIV/0! | I12: =AVERAGEIFS(Budgeted_Data!$L:$L,Budgeted_Data!$B:$B,">="&'E-Mail_Copy'!$C$3,Budgeted_Data!$B:$B,"<="&'E-Mail_Copy'!$B$4) -> #DIV/0! | J12: =AVERAGEIFS(Data_Entry!$Y:$Y,Data_Entry!$C:$C,">="&'E-Mail_Copy'!$C$3,Data_Entry!$C:$C,"<="&'E-Mail_Copy'!$B$4) -> #DIV/0! | K12: =(J12-I12)/I12 -> #DIV/0!
A13: Ambt._Temp_(0C) | C13: =AVERAGEIFS(Budgeted_Data!$H:$H,Budgeted_Data!$B:$B,'E-Mail_Copy'!$B$4) -> #DIV/0! | D13: =AVERAGEIFS(Data_Entry!$W:$W,Data_Entry!$C:$C,'E-Mail_Copy'!$B$4) -> 33.41 | E13: =(D13-C13)/C13 -> #DIV/0! | F13: =AVERAGEIFS(Budgeted_Data!$H:$H,Budgeted_Data!$B:$B,">="&'E-Mail_Copy'!$B$3,Budgeted_Data!$B:$B,"<="&'E-Mail_Copy'!$B$4) -> #DIV/0! | G13: =AVERAGEIFS(Data_Entry!$W:$W,Data_Entry!$C:$C,">="&'E-Mail_Copy'!$B$3,Data_Entry!$C:$C,"<="&'E-Mail_Copy'!$B$4) -> 34.145 | H13: =(G13-F13)/F13 -> #DIV/0! | I13: =AVERAGEIFS(Budgeted_Data!$H:$H,Budgeted_Data!$B:$B,">="&'E-Mail_Copy'!$C$3,Budgeted_Data!$B:$B,"<="&'E-Mail_Copy'!$B$4) -> 27.271073 | J13: =AVERAGEIFS(Data_Entry!$W:$W,Data_Entry!$C:$C,">="&'E-Mail_Copy'!$C$3,Data_Entry!$C:$C,"<="&'E-Mail_Copy'!$B$4) -> 30.220854 | K13: =(J13-I13)/I13 -> 0.1081652

Sheet DGR
A1: Daily_Generation_&_Performance_Report
A3: Inverter_No. | B3: ='E-Mail_Copy'!B4 -> 46181 | C3: =B3+1 -> 46182 | D3: =C3+1 -> 46183 | E3: =D3+1 -> 46184 | F3: =E3+1 -> 46185 | G3: =F3+1 -> 46186 | H3: =G3+1 -> 46187 | I3: =H3+1 -> 46188 | J3: =I3+1 -> 46189 | ... AF3: =AE3+1 -> 46211 | AG3: Total/Avg..
A4: Inv_1 | B4: =IFERROR(VLOOKUP(B$3,Data_Entry!$C:$AB,Data_Entry!$A2,0),"") -> 1843.22 | C4: =IFERROR(VLOOKUP(C$3,Data_Entry!$C:$AB,Data_Entry!$A2,0),"") -> 0 | D4: =IFERROR(VLOOKUP(D$3,Data_Entry!$C:$AB,Data_Entry!$A2,0),"") -> 0 | E4: =IFERROR(VLOOKUP(E$3,Data_Entry!$C:$AB,Data_Entry!$A2,0),"") -> 0 | F4: =IFERROR(VLOOKUP(F$3,Data_Entry!$C:$AB,Data_Entry!$A2,0),"") -> 0 | G4: =IFERROR(VLOOKUP(G$3,Data_Entry!$C:$AB,Data_Entry!$A2,0),"") -> 0 | H4: =IFERROR(VLOOKUP(H$3,Data_Entry!$C:$AB,Data_Entry!$A2,0),"") -> 0 | I4: =IFERROR(VLOOKUP(I$3,Data_Entry!$C:$AB,Data_Entry!$A2,0),"") -> 0 | ... AF4: =IFERROR(VLOOKUP(AF$3,Data_Entry!$C:$AB,Data_Entry!$A2,0),"") | AG4: =IFERROR(SUM(B4:AF4),"") -> 1843.22
A5: Inv_2 | B5: =IFERROR(VLOOKUP(B$3,Data_Entry!$C:$AB,Data_Entry!$A3,0),"") -> 1838.4 | C5: =IFERROR(VLOOKUP(C$3,Data_Entry!$C:$AB,Data_Entry!$A3,0),"") -> 0 | D5: =IFERROR(VLOOKUP(D$3,Data_Entry!$C:$AB,Data_Entry!$A3,0),"") -> 0 | E5: =IFERROR(VLOOKUP(E$3,Data_Entry!$C:$AB,Data_Entry!$A3,0),"") -> 0 | F5: =IFERROR(VLOOKUP(F$3,Data_Entry!$C:$AB,Data_Entry!$A3,0),"") -> 0 | G5: =IFERROR(VLOOKUP(G$3,Data_Entry!$C:$AB,Data_Entry!$A3,0),"") -> 0 | H5: =IFERROR(VLOOKUP(H$3,Data_Entry!$C:$AB,Data_Entry!$A3,0),"") -> 0 | I5: =IFERROR(VLOOKUP(I$3,Data_Entry!$C:$AB,Data_Entry!$A3,0),"") -> 0 | ... AF5: =IFERROR(VLOOKUP(AF$3,Data_Entry!$C:$AB,Data_Entry!$A3,0),"") | AG5: =IFERROR(SUM(B5:AF5),"") -> 1838.4
A6: Inv_3 | B6: =IFERROR(VLOOKUP(B$3,Data_Entry!$C:$AB,Data_Entry!$A4,0),"") -> 1835.24 | C6: =IFERROR(VLOOKUP(C$3,Data_Entry!$C:$AB,Data_Entry!$A4,0),"") -> 0 | D6: =IFERROR(VLOOKUP(D$3,Data_Entry!$C:$AB,Data_Entry!$A4,0),"") -> 0 | E6: =IFERROR(VLOOKUP(E$3,Data_Entry!$C:$AB,Data_Entry!$A4,0),"") -> 0 | F6: =IFERROR(VLOOKUP(F$3,Data_Entry!$C:$AB,Data_Entry!$A4,0),"") -> 0 | G6: =IFERROR(VLOOKUP(G$3,Data_Entry!$C:$AB,Data_Entry!$A4,0),"") -> 0 | H6: =IFERROR(VLOOKUP(H$3,Data_Entry!$C:$AB,Data_Entry!$A4,0),"") -> 0 | I6: =IFERROR(VLOOKUP(I$3,Data_Entry!$C:$AB,Data_Entry!$A4,0),"") -> 0 | ... AF6: =IFERROR(VLOOKUP(AF$3,Data_Entry!$C:$AB,Data_Entry!$A4,0),"") | AG6: =IFERROR(SUM(B6:AF6),"") -> 1835.24
A7: Inv_4 | B7: =IFERROR(VLOOKUP(B$3,Data_Entry!$C:$AB,Data_Entry!$A5,0),"") -> 1906.74 | C7: =IFERROR(VLOOKUP(C$3,Data_Entry!$C:$AB,Data_Entry!$A5,0),"") -> 0 | D7: =IFERROR(VLOOKUP(D$3,Data_Entry!$C:$AB,Data_Entry!$A5,0),"") -> 0 | E7: =IFERROR(VLOOKUP(E$3,Data_Entry!$C:$AB,Data_Entry!$A5,0),"") -> 0 | F7: =IFERROR(VLOOKUP(F$3,Data_Entry!$C:$AB,Data_Entry!$A5,0),"") -> 0 | G7: =IFERROR(VLOOKUP(G$3,Data_Entry!$C:$AB,Data_Entry!$A5,0),"") -> 0 | H7: =IFERROR(VLOOKUP(H$3,Data_Entry!$C:$AB,Data_Entry!$A5,0),"") -> 0 | I7: =IFERROR(VLOOKUP(I$3,Data_Entry!$C:$AB,Data_Entry!$A5,0),"") -> 0 | ... AF7: =IFERROR(VLOOKUP(AF$3,Data_Entry!$C:$AB,Data_Entry!$A5,0),"") | AG7: =IFERROR(SUM(B7:AF7),"") -> 1906.74
A8: Inv_5 | B8: =IFERROR(VLOOKUP(B$3,Data_Entry!$C:$AB,Data_Entry!$A6,0),"") -> 1900.18 | C8: =IFERROR(VLOOKUP(C$3,Data_Entry!$C:$AB,Data_Entry!$A6,0),"") -> 0 | D8: =IFERROR(VLOOKUP(D$3,Data_Entry!$C:$AB,Data_Entry!$A6,0),"") -> 0 | E8: =IFERROR(VLOOKUP(E$3,Data_Entry!$C:$AB,Data_Entry!$A6,0),"") -> 0 | F8: =IFERROR(VLOOKUP(F$3,Data_Entry!$C:$AB,Data_Entry!$A6,0),"") -> 0 | G8: =IFERROR(VLOOKUP(G$3,Data_Entry!$C:$AB,Data_Entry!$A6,0),"") -> 0 | H8: =IFERROR(VLOOKUP(H$3,Data_Entry!$C:$AB,Data_Entry!$A6,0),"") -> 0 | I8: =IFERROR(VLOOKUP(I$3,Data_Entry!$C:$AB,Data_Entry!$A6,0),"") -> 0 | ... AF8: =IFERROR(VLOOKUP(AF$3,Data_Entry!$C:$AB,Data_Entry!$A6,0),"") | AG8: =IFERROR(SUM(B8:AF8),"") -> 1900.18
A9: Inv_6 | B9: =IFERROR(VLOOKUP(B$3,Data_Entry!$C:$AB,Data_Entry!$A7,0),"") -> 1902.3 | C9: =IFERROR(VLOOKUP(C$3,Data_Entry!$C:$AB,Data_Entry!$A7,0),"") -> 0 | D9: =IFERROR(VLOOKUP(D$3,Data_Entry!$C:$AB,Data_Entry!$A7,0),"") -> 0 | E9: =IFERROR(VLOOKUP(E$3,Data_Entry!$C:$AB,Data_Entry!$A7,0),"") -> 0 | F9: =IFERROR(VLOOKUP(F$3,Data_Entry!$C:$AB,Data_Entry!$A7,0),"") -> 0 | G9: =IFERROR(VLOOKUP(G$3,Data_Entry!$C:$AB,Data_Entry!$A7,0),"") -> 0 | H9: =IFERROR(VLOOKUP(H$3,Data_Entry!$C:$AB,Data_Entry!$A7,0),"") -> 0 | I9: =IFERROR(VLOOKUP(I$3,Data_Entry!$C:$AB,Data_Entry!$A7,0),"") -> 0 | ... AF9: =IFERROR(VLOOKUP(AF$3,Data_Entry!$C:$AB,Data_Entry!$A7,0),"") | AG9: =IFERROR(SUM(B9:AF9),"") -> 1902.3
A10: Inv_7 | B10: =IFERROR(VLOOKUP(B$3,Data_Entry!$C:$AB,Data_Entry!$A8,0),"") -> 1902.22 | C10: =IFERROR(VLOOKUP(C$3,Data_Entry!$C:$AB,Data_Entry!$A8,0),"") -> 0 | D10: =IFERROR(VLOOKUP(D$3,Data_Entry!$C:$AB,Data_Entry!$A8,0),"") -> 0 | E10: =IFERROR(VLOOKUP(E$3,Data_Entry!$C:$AB,Data_Entry!$A8,0),"") -> 0 | F10: =IFERROR(VLOOKUP(F$3,Data_Entry!$C:$AB,Data_Entry!$A8,0),"") -> 0 | G10: =IFERROR(VLOOKUP(G$3,Data_Entry!$C:$AB,Data_Entry!$A8,0),"") -> 0 | H10: =IFERROR(VLOOKUP(H$3,Data_Entry!$C:$AB,Data_Entry!$A8,0),"") -> 0 | I10: =IFERROR(VLOOKUP(I$3,Data_Entry!$C:$AB,Data_Entry!$A8,0),"") -> 0 | ... AF10: =IFERROR(VLOOKUP(AF$3,Data_Entry!$C:$AB,Data_Entry!$A8,0),"") | AG10: =IFERROR(SUM(B10:AF10),"") -> 1902.22
A11: Total_Inverter_(kWh) | B11: =SUM(B4:B10) -> 13128.3 | C11: =SUM(C4:C10) -> 0 | D11: =SUM(D4:D10) -> 0 | E11: =SUM(E4:E10) -> 0 | F11: =SUM(F4:F10) -> 0 | G11: =SUM(G4:G10) -> 0 | H11: =SUM(H4:H10) -> 0 | I11: =SUM(I4:I10) -> 0 | ... AG11: =SUM(AG4:AG10) -> 13128.3
A12: Total_ABT_Meter_Export_(kWh) | B12: =IFERROR(VLOOKUP(B$3,Data_Entry!$C:$AB,14,0)," ") -> 12990 | C12: =IFERROR(VLOOKUP(C$3,Data_Entry!$C:$AB,14,0)," ") -> 0 | D12: =IFERROR(VLOOKUP(D$3,Data_Entry!$C:$AB,14,0)," ") -> 0 | E12: =IFERROR(VLOOKUP(E$3,Data_Entry!$C:$AB,14,0)," ") -> 0 | F12: =IFERROR(VLOOKUP(F$3,Data_Entry!$C:$AB,14,0)," ") -> 0 | G12: =IFERROR(VLOOKUP(G$3,Data_Entry!$C:$AB,14,0)," ") -> 0 | H12: =IFERROR(VLOOKUP(H$3,Data_Entry!$C:$AB,14,0)," ") -> 0 | I12: =IFERROR(VLOOKUP(I$3,Data_Entry!$C:$AB,14,0)," ") -> 0 | ... AG12: =IFERROR(VLOOKUP(AG$3,Data_Entry!$C:$AB,14,0)," ")
A13: Total_ABT_Meter_Import_(kWh) | B13: =IFERROR(VLOOKUP(B$3,Data_Entry!$C:$AB,17,0)," ") -> 30 | C13: =IFERROR(VLOOKUP(C$3,Data_Entry!$C:$AB,17,0)," ") -> 0 | D13: =IFERROR(VLOOKUP(D$3,Data_Entry!$C:$AB,17,0)," ") -> 0 | E13: =IFERROR(VLOOKUP(E$3,Data_Entry!$C:$AB,17,0)," ") -> 0 | F13: =IFERROR(VLOOKUP(F$3,Data_Entry!$C:$AB,17,0)," ") -> 0 | G13: =IFERROR(VLOOKUP(G$3,Data_Entry!$C:$AB,17,0)," ") -> 0 | H13: =IFERROR(VLOOKUP(H$3,Data_Entry!$C:$AB,17,0)," ") -> 0 | I13: =IFERROR(VLOOKUP(I$3,Data_Entry!$C:$AB,17,0)," ") -> 0 | ... AG13: =IFERROR(VLOOKUP(AG$3,Data_Entry!$C:$AB,17,0)," ")
A14: Total_ABT_Meter_Net_(kWh) | B14: =IFERROR(VLOOKUP(B$3,Data_Entry!$C:$AB,18,0)," ") -> 12960 | C14: =IFERROR(VLOOKUP(C$3,Data_Entry!$C:$AB,18,0)," ") -> 0 | D14: =IFERROR(VLOOKUP(D$3,Data_Entry!$C:$AB,18,0)," ") -> 0 | E14: =IFERROR(VLOOKUP(E$3,Data_Entry!$C:$AB,18,0)," ") -> 0 | F14: =IFERROR(VLOOKUP(F$3,Data_Entry!$C:$AB,18,0)," ") -> 0 | G14: =IFERROR(VLOOKUP(G$3,Data_Entry!$C:$AB,18,0)," ") -> 0 | H14: =IFERROR(VLOOKUP(H$3,Data_Entry!$C:$AB,18,0)," ") -> 0 | I14: =IFERROR(VLOOKUP(I$3,Data_Entry!$C:$AB,18,0)," ") -> 0 | ... AG14: =IFERROR(VLOOKUP(AG$3,Data_Entry!$C:$AB,18,0)," ")
A15: GTI | B15: =IFERROR(VLOOKUP(B$3,Data_Entry!$C:$AB,20,0)," ") -> 4.36 | C15: =IFERROR(VLOOKUP(C$3,Data_Entry!$C:$AB,20,0)," ") -> 0 | D15: =IFERROR(VLOOKUP(D$3,Data_Entry!$C:$AB,20,0)," ") -> 0 | E15: =IFERROR(VLOOKUP(E$3,Data_Entry!$C:$AB,20,0)," ") -> 0 | F15: =IFERROR(VLOOKUP(F$3,Data_Entry!$C:$AB,20,0)," ") -> 0 | G15: =IFERROR(VLOOKUP(G$3,Data_Entry!$C:$AB,20,0)," ") -> 0 | H15: =IFERROR(VLOOKUP(H$3,Data_Entry!$C:$AB,20,0)," ") -> 0 | I15: =IFERROR(VLOOKUP(I$3,Data_Entry!$C:$AB,20,0)," ") -> 0 | ... AF15: =IFERROR(VLOOKUP(AF$3,Data_Entry!$C:$AB,20,0)," ")
A16: GHI | B16: =IFERROR(VLOOKUP(B$3,Data_Entry!$C:$AB,19,0)," ") -> 0 | C16: =IFERROR(VLOOKUP(C$3,Data_Entry!$C:$AB,19,0)," ") -> 0 | D16: =IFERROR(VLOOKUP(D$3,Data_Entry!$C:$AB,19,0)," ") -> 0 | E16: =IFERROR(VLOOKUP(E$3,Data_Entry!$C:$AB,19,0)," ") -> 0 | F16: =IFERROR(VLOOKUP(F$3,Data_Entry!$C:$AB,19,0)," ") -> 0 | G16: =IFERROR(VLOOKUP(G$3,Data_Entry!$C:$AB,19,0)," ") -> 0 | H16: =IFERROR(VLOOKUP(H$3,Data_Entry!$C:$AB,19,0)," ") -> 0 | I16: =IFERROR(VLOOKUP(I$3,Data_Entry!$C:$AB,19,0)," ") -> 0 | ... AF16: =IFERROR(VLOOKUP(AF$3,Data_Entry!$C:$AB,19,0)," ")
A17: Module_Temp. | B17: =IFERROR(VLOOKUP(B$3,Data_Entry!$C:$AB,23,0)," ") -> 0 | C17: =IFERROR(VLOOKUP(C$3,Data_Entry!$C:$AB,23,0)," ") -> 0 | D17: =IFERROR(VLOOKUP(D$3,Data_Entry!$C:$AB,23,0)," ") -> 0 | E17: =IFERROR(VLOOKUP(E$3,Data_Entry!$C:$AB,23,0)," ") -> 0 | F17: =IFERROR(VLOOKUP(F$3,Data_Entry!$C:$AB,23,0)," ") -> 0 | G17: =IFERROR(VLOOKUP(G$3,Data_Entry!$C:$AB,23,0)," ") -> 0 | H17: =IFERROR(VLOOKUP(H$3,Data_Entry!$C:$AB,23,0)," ") -> 0 | I17: =IFERROR(VLOOKUP(I$3,Data_Entry!$C:$AB,23,0)," ") -> 0 | ... AF17: =IFERROR(VLOOKUP(AF$3,Data_Entry!$C:$AB,23,0)," ")
A18: Ambt._Temp. | B18: =IFERROR(VLOOKUP(B$3,Data_Entry!$C:$AB,21,0)," ") -> 33.41 | C18: =IFERROR(VLOOKUP(C$3,Data_Entry!$C:$AB,21,0)," ") -> 0 | D18: =IFERROR(VLOOKUP(D$3,Data_Entry!$C:$AB,21,0)," ") -> 0 | E18: =IFERROR(VLOOKUP(E$3,Data_Entry!$C:$AB,21,0)," ") -> 0 | F18: =IFERROR(VLOOKUP(F$3,Data_Entry!$C:$AB,21,0)," ") -> 0 | G18: =IFERROR(VLOOKUP(G$3,Data_Entry!$C:$AB,21,0)," ") -> 0 | H18: =IFERROR(VLOOKUP(H$3,Data_Entry!$C:$AB,21,0)," ") -> 0 | I18: =IFERROR(VLOOKUP(I$3,Data_Entry!$C:$AB,21,0)," ") -> 0 | ... AF18: =IFERROR(VLOOKUP(AF$3,Data_Entry!$C:$AB,21,0)," ")
A19: Performance_Ratio_(%) | B19: =IFERROR(B12/B15/(Basic_Data!$G$10),"") -> 1.2356943 | C19: =IFERROR(C12/C15/(Basic_Data!$G$10),"") | D19: =IFERROR(D12/D15/(Basic_Data!$G$10),"") | E19: =IFERROR(E12/E15/(Basic_Data!$G$10),"") | F19: =IFERROR(F12/F15/(Basic_Data!$G$10),"") | G19: =IFERROR(G12/G15/(Basic_Data!$G$10),"") | H19: =IFERROR(H12/H15/(Basic_Data!$G$10),"") | I19: =IFERROR(I12/I15/(Basic_Data!$G$10),"") | ... AG19: =IFERROR(AG12/AG15/(Basic_Data!$G$10),"")
A20: Capacity_Utilization_Factor_(%) | B20: =IFERROR(B12/(Basic_Data!$F$10*24),"") -> 0.28116883 | C20: =IFERROR(C12/(Basic_Data!$F$10*24),"") -> 0 | D20: =IFERROR(D12/(Basic_Data!$F$10*24),"") -> 0 | E20: =IFERROR(E12/(Basic_Data!$F$10*24),"") -> 0 | F20: =IFERROR(F12/(Basic_Data!$F$10*24),"") -> 0 | G20: =IFERROR(G12/(Basic_Data!$F$10*24),"") -> 0 | H20: =IFERROR(H12/(Basic_Data!$F$10*24),"") -> 0 | I20: =IFERROR(I12/(Basic_Data!$F$10*24),"") -> 0 | ... AG20: =IFERROR(AG12/(Basic_Data!$F$10*24),"")
A21: Aux_Consumption_Line_Loss_(%) | B21: =IFERROR((B11-B12)/B11,"") -> 0.010534494 | C21: =IFERROR((C11-C12)/C11,"") | D21: =IFERROR((D11-D12)/D11,"") | E21: =IFERROR((E11-E12)/E11,"") | F21: =IFERROR((F11-F12)/F11,"") | G21: =IFERROR((G11-G12)/G11,"") | H21: =IFERROR((H11-H12)/H11,"") | I21: =IFERROR((I11-I12)/I11,"") | ... AG21: =IFERROR((AG11-AG12)/AG11,"")

Sheet Data_Entry
B1: Month | C1: Date | D1: Plant_Up_Time | E1: Plant_Down_Time | F1: Inv_1 | G1: Inv_2 | H1: Inv_3 | I1: Inv_4 | J1: Inv_5 | K1: Inv_6 | L1: Inv_7 | M1: Total Inv Gen kWh | N1: ABT_Initial_Export | O1: ABT_Final_Export | P1: Total_Export | Q1: ABT_Initial_Import | R1: ABT_Final_Import | S1: Total_Import | T1: Net_Gen_kWh | U1: GHI (kwh/m2) | V1: GTI (kwh/m2) | W1: Ambt_Temp_Avg | X1: Module_Temp_Avg | Y1: Wtd_Module_Temp | Z1: Wind Speed | AA1: Rain_Gaug_MM | AB1: Weather_Condition
A2: 4 | B2: 45747 | C2: 45747 | M2: =SUM(F2:L2) -> 0 | P2: =MAX((O2-N2)*3000,0) -> 0 | S2: =MAX((R2-Q2)*3000,0) -> 0 | T2: =P2-S2 -> 0
A3: =A2+1 -> 5 | B3: 45748 | C3: 45748 | F3: 1907.18 | G3: 1939.32 | H3: 1904.51 | I3: 2007.77 | J3: 2023.7 | K3: 2022.23 | L3: 2004.7 | M3: =SUM(F3:L3) -> 13809.41 | N3: 12.12 | O3: 16.58 | P3: =MAX((O3-N3)*3000,0) -> 13380 | Q3: 1.94 | R3: 1.95 | S3: =MAX((R3-Q3)*3000,0) -> 30 | T3: =P3-S3 -> 13350 | V3: 4.70075
A4: =A3+1 -> 6 | B4: 45749 | C4: 45749 | F4: 1946.04 | G4: 1934.35 | H4: 1916.69 | I4: 2016.27 | J4: 1966.31 | K4: 1972.08 | L4: 1940.16 | M4: =SUM(F4:L4) -> 13691.9 | N4: 16.58 | O4: 21.09 | P4: =MAX((O4-N4)*3000,0) -> 13530 | Q4: 1.95 | R4: 1.96 | S4: =MAX((R4-Q4)*3000,0) -> 30 | T4: =P4-S4 -> 13500 | V4: 4.70525
A5: =A4+1 -> 7 | B5: 45750 | C5: 45750 | F5: 1851.77 | G5: 1838.41 | H5: 1826.56 | I5: 1920.42 | J5: 1872.57 | K5: 1880.64 | L5: 1846.67 | M5: =SUM(F5:L5) -> 13037.04 | N5: 21.09 | O5: 25.39 | P5: =MAX((O5-N5)*3000,0) -> 12900 | Q5: 1.96 | R5: 1.97 | S5: =MAX((R5-Q5)*3000,0) -> 30 | T5: =P5-S5 -> 12870 | V5: 4.574
A6: =A5+1 -> 8 | B6: 45751 | C6: 45751 | F6: 1922.67 | G6: 1906.56 | H6: 1894.57 | I6: 1994.46 | J6: 1942.86 | K6: 1954.23 | L6: 1915.01 | M6: =SUM(F6:L6) -> 13530.36 | N6: 25.39 | O6: 29.86 | P6: =MAX((O6-N6)*3000,0) -> 13410 | Q6: 1.97 | R6: 1.98 | S6: =MAX((R6-Q6)*3000,0) -> 30 | T6: =P6-S6 -> 13380 | V6: 4.706
A7: =A6+1 -> 9 | B7: 45752 | C7: 45752 | F7: 1900.72 | G7: 1888.35 | H7: 1873.9 | I7: 1974.18 | J7: 1922.82 | K7: 1934.16 | L7: 1806 | M7: =SUM(F7:L7) -> 13300.13 | N7: 29.86 | O7: 34.28 | P7: =MAX((O7-N7)*3000,0) -> 13260 | Q7: 1.98 | R7: 1.99 | S7: =MAX((R7-Q7)*3000,0) -> 30 | T7: =P7-S7 -> 13230 | V7: 4.71575
A8: =A7+1 -> 10 | B8: 45753 | C8: 45753 | F8: 1910.69 | G8: 1900.96 | H8: 1885.91 | I8: 1990.97 | J8: 1938.67 | K8: 1948.05 | L8: 1914.38 | M8: =SUM(F8:L8) -> 13489.63 | N8: 34.28 | O8: 38.73 | P8: =MAX((O8-N8)*3000,0) -> 13350 | Q8: 1.99 | R8: 2 | S8: =MAX((R8-Q8)*3000,0) -> 30 | T8: =P8-S8 -> 13320 | V8: 4.834
A9: =A8+1 -> 11 | B9: 45754 | C9: 45754 | F9: 1871.95 | G9: 1858.79 | H9: 1843.59 | I9: 1944.86 | J9: 1894.89 | K9: 1905.29 | L9: 1874.6 | M9: =SUM(F9:L9) -> 13193.97 | N9: 38.73 | O9: 43.09 | P9: =MAX((O9-N9)*3000,0) -> 13080 | Q9: 2 | R9: 2.01 | S9: =MAX((R9-Q9)*3000,0) -> 30 | T9: =P9-S9 -> 13050 | V9: 4.746
A10: =A9+1 -> 12 | B10: 45755 | C10: 45755 | F10: 1747.98 | G10: 1739.72 | H10: 1725.16 | I10: 1838.87 | J10: 1774.48 | K10: 1782.44 | L10: 1753.28 | M10: =SUM(F10:L10) -> 12361.93 | N10: 43.09 | O10: 47.17 | P10: =MAX((O10-N10)*3000,0) -> 12240 | Q10: 2.01 | R10: 2.02 | S10: =MAX((R10-Q10)*3000,0) -> 30 | T10: =P10-S10 -> 12210 | V10: 4.6445
A11: =A10+1 -> 13 | B11: 45756 | C11: 45756 | F11: 1795.76 | G11: 1784.89 | H11: 1771.68 | I11: 1904.8 | J11: 1819.83 | K11: 1827.37 | L11: 1798.97 | M11: =SUM(F11:L11) -> 12703.3 | N11: 47.17 | O11: 51.36 | P11: =MAX((O11-N11)*3000,0) -> 12570 | Q11: 2.02 | R11: 2.04 | S11: =MAX((R11-Q11)*3000,0) -> 60 | T11: =P11-S11 -> 12510 | V11: 4.74175
A12: =A11+1 -> 14 | B12: 45757 | C12: 45757 | F12: 1844.1 | G12: 1826.08 | H12: 1814.23 | I12: 1970.73 | J12: 1921.79 | K12: 1944.7 | L12: 1926.7 | M12: =SUM(F12:L12) -> 13248.33 | N12: =O11 -> 51.36 | O12: 55.73 | P12: =MAX((O12-N12)*3000,0) -> 13110 | Q12: =R11 -> 2.04 | R12: 2.05 | S12: =MAX((R12-Q12)*3000,0) -> 30 | T12: =P12-S12 -> 13080 | V12: 4.9
A13: =A12+1 -> 15 | B13: 45758 | C13: 45758 | F13: 1982.14 | G13: 1971.26 | H13: 1966.63 | I13: 2078.11 | J13: 2014.72 | K13: 2013.29 | L13: 2001.59 | M13: =SUM(F13:L13) -> 14027.74 | N13: =O12 -> 55.73 | O13: 60.36 | P13: =MAX((O13-N13)*3000,0) -> 13890 | Q13: =R12 -> 2.05 | R13: 2.06 | S13: =MAX((R13-Q13)*3000,0) -> 30 | T13: =P13-S13 -> 13860 | V13: 4.92 | W13: 60
A14: =A13+1 -> 16 | B14: 45759 | C14: 45759 | F14: 2000.12 | G14: 1989.96 | H14: 2054.8 | I14: 2103.08 | J14: 2033.46 | K14: 2028.7 | L14: 2016.47 | M14: =SUM(F14:L14) -> 14226.59 | N14: =O13 -> 60.36 | O14: 65.05 | P14: =MAX((O14-N14)*3000,0) -> 14070 | Q14: =R13 -> 2.06 | R14: 2.07 | S14: =MAX((R14-Q14)*3000,0) -> 30 | T14: =P14-S14 -> 14040 | V14: 5.08 | AB14: sunny
A15: =A14+1 -> 17 | B15: 45760 | C15: 45760 | F15: 2116.18 | G15: 2112.73 | H15: 2117 | I15: 2195.22 | J15: 2075.64 | K15: 2068.07 | L15: 2053.15 | M15: =SUM(F15:L15) -> 14737.99 | N15: =O14 -> 65.05 | O15: 69.91 | P15: =MAX((O15-N15)*3000,0) -> 14580 | Q15: =R14 -> 2.07 | R15: 2.08 | S15: =MAX((R15-Q15)*3000,0) -> 30 | T15: =P15-S15 -> 14550 | V15: 5.21 | AB15: sunny
A16: =A15+1 -> 18 | B16: 45761 | C16: 45761 | F16: 2102.77 | G16: 2079.13 | H16: 2090.55 | I16: 2200.6 | J16: 2172.37 | K16: 2164.42 | L16: 2154.04 | M16: =SUM(F16:L16) -> 14963.88 | N16: =O15 -> 69.91 | O16: 74.83 | P16: =MAX((O16-N16)*3000,0) -> 14760 | Q16: =R15 -> 2.08 | R16: 2.09 | S16: =MAX((R16-Q16)*3000,0) -> 30 | T16: =P16-S16 -> 14730 | V16: 5.14 | AB16: sunny
A17: =A16+1 -> 19 | B17: 45762 | C17: 45762 | F17: 2085.01 | G17: 2062.99 | H17: 2072.03 | I17: 2177.98 | J17: 2145.8 | K17: 2147.49 | L17: 2160.53 | M17: =SUM(F17:L17) -> 14851.83 | N17: =O16 -> 74.83 | O17: 79.73 | P17: =MAX((O17-N17)*3000,0) -> 14700 | Q17: =R16 -> 2.09 | R17: 2.1 | S17: =MAX((R17-Q17)*3000,0) -> 30 | T17: =P17-S17 -> 14670 | V17: 5.13 | AB17: sunny
A18: =A17+1 -> 20 | B18: 45763 | C18: 45763 | F18: 2045.52 | G18: 2024.81 | H18: 2028.81 | I18: 2132.32 | J18: 2108.15 | K18: 2115.88 | L18: 2127.22 | M18: =SUM(F18:L18) -> 14582.71 | N18: =O17 -> 79.73 | O18: 84.55 | P18: =MAX((O18-N18)*3000,0) -> 14460 | Q18: =R17 -> 2.1 | R18: 2.11 | S18: =MAX((R18-Q18)*3000,0) -> 30 | T18: =P18-S18 -> 14430 | V18: 5.04 | W18: 34.2 | AB18: sunny
A19: =A18+1 -> 21 | B19: 45764 | C19: 45764 | F19: 871.85 | G19: 870 | H19: 872.65 | I19: 911.72 | J19: 906.16 | K19: 901.18 | L19: 905.53 | M19: =SUM(F19:L19) -> 6239.09 | N19: =O18 -> 84.55 | O19: 86.6 | P19: =MAX((O19-N19)*3000,0) -> 6150 | Q19: =R18 -> 2.11 | R19: 2.12 | S19: =MAX((R19-Q19)*3000,0) -> 30 | T19: =P19-S19 -> 6120 | AB19: sunny
A20: =A19+1 -> 22 | B20: 45765 | C20: 45765 | F20: 0 | G20: 0 | H20: 0 | I20: 0 | J20: 0 | K20: 0 | L20: 0 | M20: =SUM(F20:L20) -> 0 | N20: =O19 -> 86.6 | O20: 86.6 | P20: =MAX((O20-N20)*3000,0) -> 0 | Q20: =R19 -> 2.12 | R20: 2.12 | S20: =MAX((R20-Q20)*3000,0) -> 0 | T20: =P20-S20 -> 0 | AB20: sunny
A21: =A20+1 -> 23 | B21: 45766 | C21: 45766 | F21: 0 | G21: 0 | H21: 0 | I21: 0 | J21: 0 | K21: 0 | L21: 0 | M21: =SUM(F21:L21) -> 0 | N21: =O20 -> 86.6 | O21: 86.6 | P21: =MAX((O21-N21)*3000,0) -> 0 | Q21: =R20 -> 2.12 | R21: 2.12 | S21: =MAX((R21-Q21)*3000,0) -> 0 | T21: =P21-S21 -> 0 | AB21: sunny
A22: =A21+1 -> 24 | B22: 45767 | C22: 45767 | F22: 2111.28 | G22: 2109.21 | H22: 2112.3 | I22: 2208.71 | J22: 2198.85 | K22: 2204.77 | L22: 2227.06 | M22: =SUM(F22:L22) -> 15172.18 | N22: =O21 -> 86.6 | O22: 91.6 | P22: =MAX((O22-N22)*3000,0) -> 15000 | Q22: =R21 -> 2.12 | R22: 2.13 | S22: =MAX((R22-Q22)*3000,0) -> 30 | T22: =P22-S22 -> 14970 | V22: 5.33 | W22: 33.9 | AB22: sunny
A23: =A22+1 -> 25 | B23: 45768 | C23: 45768 | F23: 2044.26 | G23: 2043.53 | H23: 2044.57 | I23: 2140.32 | J23: 2132.27 | K23: 2136.15 | L23: 2151.63 | M23: =SUM(F23:L23) -> 14692.73 | N23: =O22 -> 91.6 | O23: 96.45 | P23: =MAX((O23-N23)*3000,0) -> 14550 | Q23: =R22 -> 2.13 | R23: 2.14 | S23: =MAX((R23-Q23)*3000,0) -> 30 | T23: =P23-S23 -> 14520 | V23: 5.25 | W23: 35.25 | AB23: sunny
A24: =A23+1 -> 26 | B24: 45769 | C24: 45769 | F24: 2051.52 | G24: 2068.96 | H24: 2100.98 | I24: 2189.7 | J24: 2136.27 | K24: 2144.32 | L24: 2161.91 | M24: =SUM(F24:L24) -> 14853.66 | N24: =O23 -> 96.45 | O24: 101.35 | P24: =MAX((O24-N24)*3000,0) -> 14700 | Q24: =R23 -> 2.14 | R24: 2.15 | S24: =MAX((R24-Q24)*3000,0) -> 30 | T24: =P24-S24 -> 14670 | V24: 5.28 | W24: 37 | AB24: sunny
A25: =A24+1 -> 27 | B25: 45770 | C25: 45770 | F25: 2036.09 | G25: 2032.74 | H25: 2033.4 | I25: 2127.45 | J25: 2106.96 | K25: 2094.6 | L25: 2083.49 | M25: =SUM(F25:L25) -> 14514.73 | N25: =O24 -> 101.35 | O25: 106.14 | P25: =MAX((O25-N25)*3000,0) -> 14370 | Q25: =R24 -> 2.15 | R25: 2.16 | S25: =MAX((R25-Q25)*3000,0) -> 30 | T25: =P25-S25 -> 14340 | V25: 5.16 | W25: 37.04 | AB25: sunny
A26: =A25+1 -> 28 | B26: 45771 | C26: 45771 | F26: 2087.2 | G26: 2081.03 | H26: 2082.75 | I26: 2178.48 | J26: 2175.08 | K26: 2175.9 | L26: 2196.2 | M26: =SUM(F26:L26) -> 14976.64 | N26: =O25 -> 106.14 | O26: 111.07 | P26: =MAX((O26-N26)*3000,0) -> 14790 | Q26: =R25 -> 2.16 | R26: 2.17 | S26: =MAX((R26-Q26)*3000,0) -> 30 | T26: =P26-S26 -> 14760 | V26: 5.24 | W26: 35.34 | AB26: sunny
A27: =A26+1 -> 29 | B27: 45772 | C27: 45772 | F27: 2102.3 | G27: 2088.6 | H27: 2073 | I27: 2176.04 | J27: 2179.13 | K27: 2188.77 | L27: 2214.35 | M27: =SUM(F27:L27) -> 15022.19 | N27: =O26 -> 111.07 | O27: 116.04 | P27: =MAX((O27-N27)*3000,0) -> 14910 | Q27: =R26 -> 2.17 | R27: 2.18 | S27: =MAX((R27-Q27)*3000,0) -> 30 | T27: =P27-S27 -> 14880 | V27: 5.36 | W27: 31.86 | AB27: sunny
A28: =A27+1 -> 30 | B28: 45773 | C28: 45773 | F28: 2095.09 | G28: 2079.96 | H28: 2062.85 | I28: 2162.06 | J28: 2171.46 | K28: 2181.79 | L28: 2206.55 | M28: =SUM(F28:L28) -> 14959.76 | N28: =O27 -> 116.04 | O28: 120.98 | P28: =MAX((O28-N28)*3000,0) -> 14820 | Q28: =R27 -> 2.18 | R28: 2.19 | S28: =MAX((R28-Q28)*3000,0) -> 30 | T28: =P28-S28 -> 14790 | V28: 5.39 | W28: 34.96 | AB28: sunny
A29: =A28+1 -> 31 | B29: 45774 | C29: 45774 | F29: 2060 | G29: 2046.34 | H29: 2027.3 | I29: 2124.14 | J29: 2134.74 | K29: 2146.57 | L29: 2168.26 | M29: =SUM(F29:L29) -> 14707.35 | N29: =O28 -> 120.98 | O29: 125.84 | P29: =MAX((O29-N29)*3000,0) -> 14580 | Q29: =R28 -> 2.19 | R29: 2.2 | S29: =MAX((R29-Q29)*3000,0) -> 30 | T29: =P29-S29 -> 14550 | V29: 5.39 | W29: 35.68 | AB29: sunny
A30: =A29+1 -> 32 | B30: 45775 | C30: 45775 | D30: 0.28263889 | E30: 0.78125 | F30: 1845.54 | G30: 1806.3 | H30: 1785.4 | I30: 1867.44 | J30: 1876.8 | K30: 1888.4 | L30: 1906.11 | M30: =SUM(F30:L30) -> 12975.99 | N30: =O29 -> 125.84 | O30: 130.13 | P30: =MAX((O30-N30)*3000,0) -> 12870 | Q30: =R29 -> 2.2 | R30: 2.21 | S30: =MAX((R30-Q30)*3000,0) -> 30 | T30: =P30-S30 -> 12840 | V30: 5.28 | W30: 36.36 | AB30: sunny
A31: =A30+1 -> 33 | B31: 45776 | C31: 45776 | D31: 0.28125 | E31: 0.78125 | F31: 2121.64 | G31: 2111 | H31: 2100.88 | I31: 2189.97 | J31: 2155.82 | K31: 2160.51 | L31: 2181.7 | M31: =SUM(F31:L31) -> 15021.52 | N31: =O30 -> 130.13 | O31: 135.09 | P31: =MAX((O31-N31)*3000,0) -> 14880 | Q31: =R30 -> 2.21 | R31: 2.22 | S31: =MAX((R31-Q31)*3000,0) -> 30 | T31: =P31-S31 -> 14850 | V31: 5.55 | W31: 37.01 | AB31: sunny
A32: =A31+1 -> 34 | B32: 45777 | C32: 45777 | D32: 0.28125 | E32: 0.78125 | F32: 2090 | G32: 2081.16 | H32: 2071.47 | I32: 2172.86 | J32: 2165.84 | K32: 2130.54 | L32: 2143.81 | M32: =SUM(F32:L32) -> 14855.68 | N32: =O31 -> 135.09 | O32: 140 | P32: =MAX((O32-N32)*3000,0) -> 14730 | Q32: =R31 -> 2.22 | R32: 2.23 | S32: =MAX((R32-Q32)*3000,0) -> 30 | T32: =P32-S32 -> 14700 | V32: 5.47 | W32: 35.9 | AB32: sunny
A33: =A32+1 -> 35 | B33: 45778 | C33: 45778 | D33: 0.28125 | E33: 0.78194444 | F33: 2080.73 | G33: 2068.31 | H33: 2061.44 | I33: 2161.49 | J33: 2155.99 | K33: 2167.05 | L33: 2195.77 | M33: =SUM(F33:L33) -> 14890.78 | N33: =O32 -> 140 | O33: 144.91 | P33: =MAX((O33-N33)*3000,0) -> 14730 | Q33: =R32 -> 2.23 | R33: 2.24 | S33: =MAX((R33-Q33)*3000,0) -> 30 | T33: =P33-S33 -> 14700 | V33: 5.52 | W33: 35.78 | AB33: sunny
A34: =A33+1 -> 36 | B34: 45779 | C34: 45779 | D34: 0.28125 | E34: 0.78194444 | F34: 2167.71 | G34: 2144.78 | H34: 2138.28 | I34: 2242.8 | J34: 2237.89 | K34: 2250.4 | L34: 2268.68 | M34: =SUM(F34:L34) -> 15450.54 | N34: =O33 -> 144.91 | O34: 150 | P34: =MAX((O34-N34)*3000,0) -> 15270 | Q34: =R33 -> 2.24 | R34: 2.25 | S34: =MAX((R34-Q34)*3000,0) -> 30 | T34: =P34-S34 -> 15240 | V34: 5.85 | W34: 35.96 | AB34: sunny
A35: =A34+1 -> 37 | B35: 45780 | C35: 45780 | D35: 0.28125 | E35: 0.78194444 | F35: 2035.03 | G35: 2022.08 | H35: 2013.82 | I35: 2111.03 | J35: 2106.59 | K35: 2116.26 | L35: 2137.34 | M35: =SUM(F35:L35) -> 14542.15 | N35: =O34 -> 150 | O35: 154.8 | P35: =MAX((O35-N35)*3000,0) -> 14400 | Q35: =R34 -> 2.25 | R35: 2.26 | S35: =MAX((R35-Q35)*3000,0) -> 30 | T35: =P35-S35 -> 14370 | V35: 5.39 | W35: 33.54 | AB35: sunny
A36: =A35+1 -> 38 | B36: 45781 | C36: 45781 | D36: 0.28125 | E36: 0.78125 | F36: 1905.43 | G36: 1894.04 | H36: 1889.89 | I36: 1977.99 | J36: 1976.69 | K36: 1987.41 | L36: 2009.93 | M36: =SUM(F36:L36) -> 13641.38 | N36: =O35 -> 154.8 | O36: 159.31 | P36: =MAX((O36-N36)*3000,0) -> 13530 | Q36: =R35 -> 2.26 | R36: 2.27 | S36: =MAX((R36-Q36)*3000,0) -> 30 | T36: =P36-S36 -> 13500 | V36: 5.04 | W36: 33.37 | AB36: sunny
A37: =A36+1 -> 39 | B37: 45782 | C37: 45782 | D37: 0.28125 | E37: 0.78125 | F37: 1897.04 | G37: 1882.65 | H37: 1874.3 | I37: 1968.13 | J37: 1975.47 | K37: 1991.66 | L37: 2016.33 | M37: =SUM(F37:L37) -> 13605.58 | N37: =O36 -> 159.31 | O37: 163.8 | P37: =MAX((O37-N37)*3000,0) -> 13470 | Q37: =R36 -> 2.27 | R37: 2.28 | S37: =MAX((R37-Q37)*3000,0) -> 30 | T37: =P37-S37 -> 13440 | V37: 4.23 | W37: 31.68 | AB37: mostly cloudy
A38: =A37+1 -> 40 | B38: 45783 | C38: 45783 | D38: 0.29166667 | E38: 0.625 | F38: 1253.46 | G38: 1246.19 | H38: 1241.61 | I38: 1301.63 | J38: 1293.55 | K38: 1293.12 | L38: 1303.87 | M38: =SUM(F38:L38) -> 8933.43 | N38: =O37 -> 163.8 | O38: 166.67 | P38: =MAX((O38-N38)*3000,0) -> 8610 | Q38: =R37 -> 2.28 | R38: 2.29 | S38: =MAX((R38-Q38)*3000,0) -> 30 | T38: =P38-S38 -> 8580 | V38: 3.29 | W38: 30.13 | AB38: cloudy
A39: =A38+1 -> 41 | B39: 45784 | C39: 45784 | D39: 0.28125 | E39: 0.78125 | F39: 1015.68 | G39: 1010.52 | H39: 1004.47 | I39: 1051.98 | J39: 1055.87 | K39: 1060.14 | L39: 1074.74 | M39: =SUM(F39:L39) -> 7273.4 | N39: =O38 -> 166.67 | O39: 169.14 | P39: =MAX((O39-N39)*3000,0) -> 7410 | Q39: =R38 -> 2.29 | R39: 2.3 | S39: =MAX((R39-Q39)*3000,0) -> 30 | T39: =P39-S39 -> 7380 | V39: 2.65 | W39: 27.47 | AB39: rainy
A40: =A39+1 -> 42 | B40: 45785 | C40: 45785 | D40: 0.28125 | E40: 0.78125 | F40: 1953.56 | G40: 1949.73 | H40: 1946.56 | I40: 2033.03 | J40: 2026.38 | K40: 2030.49 | L40: 2049.24 | M40: =SUM(F40:L40) -> 13988.99 | N40: =O39 -> 169.14 | O40: 173.77 | P40: =MAX((O40-N40)*3000,0) -> 13890 | Q40: =R39 -> 2.3 | R40: 2.31 | S40: =MAX((R40-Q40)*3000,0) -> 30 | T40: =P40-S40 -> 13860 | V40: 5.95 | W40: 31.8 | AB40: cloudy
A41: =A40+1 -> 43 | B41: 45786 | C41: 45786 | D41: 0.28125 | E41: 0.73958333 | F41: 1657.28 | G41: 1651.95 | H41: 1648.38 | I41: 1727.45 | J41: 1724.43 | K41: 1725.34 | L41: 1732.77 | M41: =SUM(F41:L41) -> 11867.6 | N41: =O40 -> 173.77 | O41: 177.69 | P41: =MAX((O41-N41)*3000,0) -> 11760 | Q41: =R40 -> 2.31 | R41: 2.32 | S41: =MAX((R41-Q41)*3000,0) -> 30 | T41: =P41-S41 -> 11730 | V41: 5.13 | W41: 31.24 | AB41: cloudy
... A130: =A129+1 -> 132 | B130: 45875 | C130: 45875 | D130: 0.29166667 | E130: 0.79166667 | F130: 1499.52 | G130: 1494.68 | H130: 1492.16 | I130: 1559.55 | J130: 1554.17 | K130: 1553.73 | L130: 1565.3 | M130: =SUM(F130:L130) -> 10719.11 | N130: =O129 -> 438.13 | O130: 441.67 | P130: =MAX((O130-N130)*3000,0) -> 10620 | Q130: =R129 -> 3.2 | R130: 3.21 | S130: =MAX((R130-Q130)*3000,0) -> 30 | T130: =P130-S130 -> 10590 | V130: 4.33 | W130: 29.27 | AB130: cloudy
A131: =A130+1 -> 133 | B131: 45876 | C131: 45876 | D131: 0.28125 | E131: 0.79166667 | F131: 1753.2 | G131: 1744.43 | H131: 1741.57 | I131: 1815.21 | J131: 1804.12 | K131: 1798.37 | L131: 1800.8 | M131: =SUM(F131:L131) -> 12457.7 | N131: =O130 -> 441.67 | O131: 445.78 | P131: =MAX((O131-N131)*3000,0) -> 12330 | Q131: 3.22 | R131: 3.23 | S131: =MAX((R131-Q131)*3000,0) -> 30 | T131: =P131-S131 -> 12300 | V131: 5.09 | W131: 30.02 | AB131: cloudy
A132: =A131+1 -> 134 | B132: 45877 | C132: 45877 | D132: 0.29166667 | E132: 0.79166667 | F132: 1473.07 | G132: 1467.83 | H132: 1464.44 | I132: 1531.56 | J132: 1517.72 | K132: 1510.31 | L132: 1517.77 | M132: =SUM(F132:L132) -> 10482.7 | N132: =O131 -> 445.78 | O132: 449.24 | P132: =MAX((O132-N132)*3000,0) -> 10380 | Q132: =R131 -> 3.23 | R132: 3.23 | S132: =MAX((R132-Q132)*3000,0) -> 0 | T132: =P132-S132 -> 10380 | V132: 4.32 | W132: 30 | AB132: cloudy
A133: =A132+1 -> 135 | B133: 45878 | C133: 45878 | D133: 0.29166667 | E133: 0.79166667 | F133: 1093.92 | G133: 1090.15 | H133: 1088.1 | I133: 1140.24 | J133: 1132.67 | K133: 1128.6 | L133: 1138.69 | M133: =SUM(F133:L133) -> 7812.37 | N133: =O132 -> 449.24 | O133: 451.83 | P133: =MAX((O133-N133)*3000,0) -> 7770 | Q133: =R132 -> 3.23 | R133: 3.24 | S133: =MAX((R133-Q133)*3000,0) -> 30 | T133: =P133-S133 -> 7740 | V133: 3.13 | W133: 28.46 | AB133: cloudy
A134: =A133+1 -> 136 | B134: 45879 | C134: 45879 | D134: 0.30208333 | E134: 0.78125 | F134: 1261.14 | G134: 1257.14 | H134: 1255.85 | I134: 1313.74 | J134: 1306.88 | K134: 1303.9 | L134: 1316.6 | M134: =SUM(F134:L134) -> 9015.25 | N134: =O133 -> 451.83 | O134: 454.83 | P134: =MAX((O134-N134)*3000,0) -> 9000 | Q134: =R133 -> 3.24 | R134: 3.25 | S134: =MAX((R134-Q134)*3000,0) -> 30 | T134: =P134-S134 -> 8970 | V134: 3.41 | W134: 27.68 | AB134: cloudy
A135: =A134+1 -> 137 | B135: 45880 | C135: 45880 | D135: 0.30208333 | E135: 0.78125 | F135: 1381.22 | G135: 1380.25 | H135: 1385.16 | I135: 1450.6 | J135: 1442.46 | K135: 1435.51 | L135: 1445.5 | M135: =SUM(F135:L135) -> 9920.7 | N135: =O134 -> 454.83 | O135: 458.12 | P135: =MAX((O135-N135)*3000,0) -> 9870 | Q135: =R134 -> 3.25 | R135: 3.26 | S135: =MAX((R135-Q135)*3000,0) -> 30 | T135: =P135-S135 -> 9840 | V135: 3.67 | W135: 28.7 | AB135: cloudy
A136: =A135+1 -> 138 | B136: 45881 | C136: 45881 | D136: 0.29166667 | E136: 0.75 | F136: 1127.29 | G136: 1119.79 | H136: 1120.61 | I136: 1168.03 | J136: 1158.76 | K136: 1157.9 | L136: 1169.13 | M136: =SUM(F136:L136) -> 8021.51 | N136: =O135 -> 458.12 | O136: 460.78 | P136: =MAX((O136-N136)*3000,0) -> 7980 | Q136: =R135 -> 3.26 | R136: 3.27 | S136: =MAX((R136-Q136)*3000,0) -> 30 | T136: =P136-S136 -> 7950 | V136: 2.94 | W136: 27.14 | AB136: cloudy
A137: =A136+1 -> 139 | B137: 45882 | C137: 45882 | D137: 0.30208333 | E137: 0.78125 | F137: 1292 | G137: 1283.32 | H137: 1278.84 | I137: 1332.46 | J137: 1320.36 | K137: 1315.12 | L137: 1320.56 | M137: =SUM(F137:L137) -> 9142.66 | N137: =O136 -> 460.78 | O137: 463.81 | P137: =MAX((O137-N137)*3000,0) -> 9090 | Q137: =R136 -> 3.27 | R137: 3.28 | S137: =MAX((R137-Q137)*3000,0) -> 30 | T137: =P137-S137 -> 9060 | V137: 3.69 | W137: 28.87 | AB137: cloudy
A138: =A137+1 -> 140 | B138: 45883 | C138: 45883 | D138: 0.30208333 | E138: 0.78125 | F138: 979.85 | G138: 974.8 | H138: 976.81 | I138: 1023.5 | J138: 1019.58 | K138: 1019.31 | L138: 1028.68 | M138: =SUM(F138:L138) -> 7022.53 | N138: =O137 -> 463.81 | O138: 466.13 | P138: =MAX((O138-N138)*3000,0) -> 6960 | Q138: =R137 -> 3.28 | R138: 3.29 | S138: =MAX((R138-Q138)*3000,0) -> 30 | T138: =P138-S138 -> 6930 | V138: 2.7 | W138: 28.25 | AB138: cloudy
A139: =A138+1 -> 141 | B139: 45884 | C139: 45884 | D139: 0.30208333 | E139: 0.76041667 | F139: 948.13 | G139: 942.53 | H139: 942.43 | I139: 982.52 | J139: 974.51 | K139: 973.05 | L139: 979.34 | M139: =SUM(F139:L139) -> 6742.51 | N139: =O138 -> 466.13 | O139: 468.37 | P139: =MAX((O139-N139)*3000,0) -> 6720 | Q139: =R138 -> 3.29 | R139: 3.3 | S139: =MAX((R139-Q139)*3000,0) -> 30 | T139: =P139-S139 -> 6690 | V139: 3.05 | W139: 29.48 | AB139: cloudy
A140: =A139+1 -> 142 | B140: 45885 | C140: 45885 | D140: 0.30208333 | E140: 0.73958333 | F140: 1303.56 | G140: 1296.93 | H140: 1297.26 | I140: 1357.51 | J140: 1347.83 | K140: 1346.88 | L140: 1362.49 | M140: =SUM(F140:L140) -> 9312.46 | N140: =O139 -> 468.37 | O140: 471.44 | P140: =MAX((O140-N140)*3000,0) -> 9210 | Q140: =R139 -> 3.3 | R140: 3.31 | S140: =MAX((R140-Q140)*3000,0) -> 30 | T140: =P140-S140 -> 9180 | V140: 3.53 | W140: 29.46 | AB140: rainy
A141: =A140+1 -> 143 | B141: 45886 | C141: 45886 | D141: 0.30208333 | E141: 0.77083333 | F141: 1158.58 | G141: 1153 | H141: 1155.21 | I141: 1206.2 | J141: 1201.45 | K141: 1203.14 | L141: 1211.75 | M141: =SUM(F141:L141) -> 8289.33 | N141: =O140 -> 471.44 | O141: 474.18 | P141: =MAX((O141-N141)*3000,0) -> 8220 | Q141: =R140 -> 3.31 | R141: 3.33 | S141: =MAX((R141-Q141)*3000,0) -> 60 | T141: =P141-S141 -> 8160 | V141: 3.05 | W141: 28.69 | AB141: rainy
A142: =A141+1 -> 144 | B142: 45887 | C142: 45887 | D142: 0.29166667 | E142: 0.78125 | F142: 1175.18 | G142: 1167.11 | H142: 1164.37 | I142: 1207.02 | J142: 1194.61 | K142: 1200 | L142: 1202.86 | M142: =SUM(F142:L142) -> 8311.15 | N142: =O141 -> 474.18 | O142: 476.93 | P142: =MAX((O142-N142)*3000,0) -> 8250 | Q142: =R141 -> 3.33 | R142: 3.34 | S142: =MAX((R142-Q142)*3000,0) -> 30 | T142: =P142-S142 -> 8220 | V142: 3.27 | W142: 30 | AB142: rainy
A143: =A142+1 -> 145 | B143: 45888 | C143: 45888 | F143: 1307.97 | G143: 1300 | H143: 1300.63 | I143: 1357.37 | J143: 1352.77 | K143: 1353.43 | L143: 1365.51 | M143: =SUM(F143:L143) -> 9337.68 | N143: =O142 -> 476.93 | O143: 480.01 | P143: =MAX((O143-N143)*3000,0) -> 9240 | Q143: =R142 -> 3.34 | R143: 3.35 | S143: =MAX((R143-Q143)*3000,0) -> 30 | T143: =P143-S143 -> 9210
A144: =A143+1 -> 146 | B144: 45889 | C144: 45889 | F144: 388.75 | G144: 384.46 | H144: 386.3 | I144: 404.7 | J144: 401.4 | K144: 400.51 | L144: 404.25 | M144: =SUM(F144:L144) -> 2770.37 | N144: =O143 -> 480.01 | O144: 480.93 | P144: =MAX((O144-N144)*3000,0) -> 2760 | Q144: =R143 -> 3.35 | R144: 3.36 | S144: =MAX((R144-Q144)*3000,0) -> 30 | T144: =P144-S144 -> 2730
A145: =A144+1 -> 147 | B145: 45890 | C145: 45890 | F145: 1145.52 | G145: 1139.51 | H145: 1138.05 | I145: 1183.51 | J145: 1176.01 | K145: 1172.02 | L145: 1175.76 | M145: =SUM(F145:L145) -> 8130.38 | N145: =O144 -> 480.93 | O145: 483.62 | P145: =MAX((O145-N145)*3000,0) -> 8070 | Q145: =R144 -> 3.36 | R145: 3.37 | S145: =MAX((R145-Q145)*3000,0) -> 30 | T145: =P145-S145 -> 8040
A146: =A145+1 -> 148 | B146: 45891 | C146: 45891 | F146: 1214.63 | G146: 1203.72 | H146: 1196.54 | I146: 1238.2 | J146: 1219.82 | K146: 1211.91 | L146: 1207.31 | M146: =SUM(F146:L146) -> 8492.13 | N146: =O145 -> 483.62 | O146: 486.44 | P146: =MAX((O146-N146)*3000,0) -> 8460 | Q146: =R145 -> 3.37 | R146: 3.38 | S146: =MAX((R146-Q146)*3000,0) -> 30 | T146: =P146-S146 -> 8430
A147: =A146+1 -> 149 | B147: 45892 | C147: 45892 | F147: 825.47 | G147: 820.58 | H147: 819.1 | I147: 853.46 | J147: 845.59 | K147: 843.81 | L147: 847.17 | M147: =SUM(F147:L147) -> 5855.18 | N147: =O146 -> 486.44 | O147: 488.37 | P147: =MAX((O147-N147)*3000,0) -> 5790 | Q147: =R146 -> 3.38 | R147: 3.39 | S147: =MAX((R147-Q147)*3000,0) -> 30 | T147: =P147-S147 -> 5760
A148: =A147+1 -> 150 | B148: 45893 | C148: 45893 | F148: 838.74 | G148: 833.23 | H148: 833.04 | I148: 870.71 | J148: 863.2 | K148: 861.2 | L148: 863.87 | M148: =SUM(F148:L148) -> 5963.99 | N148: =O147 -> 488.37 | O148: 490.35 | P148: =MAX((O148-N148)*3000,0) -> 5940 | Q148: =R147 -> 3.39 | R148: 3.4 | S148: =MAX((R148-Q148)*3000,0) -> 30 | T148: =P148-S148 -> 5910
A149: =A148+1 -> 151 | B149: 45894 | C149: 45894 | F149: 871.67 | G149: 867.02 | H149: 866.28 | I149: 902.84 | J149: 896.48 | K149: 894.44 | L149: 898.22 | M149: =SUM(F149:L149) -> 6196.95 | N149: =O148 -> 490.35 | O149: 492.41 | P149: =MAX((O149-N149)*3000,0) -> 6180 | Q149: =R148 -> 3.4 | R149: 3.41 | S149: =MAX((R149-Q149)*3000,0) -> 30 | T149: =P149-S149 -> 6150
A150: =A149+1 -> 152 | B150: 45895 | C150: 45895 | F150: 1081 | G150: 1076.5 | H150: 1071.15 | I150: 1117 | J150: 11105.55 | K150: 1100 | L150: 1100.6 | M150: =SUM(F150:L150) -> 17651.8 | N150: =O149 -> 492.41 | O150: 494.95 | P150: =MAX((O150-N150)*3000,0) -> 7620 | Q150: =R149 -> 3.41 | R150: 3.42 | S150: =MAX((R150-Q150)*3000,0) -> 30 | T150: =P150-S150 -> 7590
A151: =A150+1 -> 153 | B151: 45896 | C151: 45896 | F151: 1331.35 | G151: 1325.83 | H151: 1326.49 | I151: 1384.51 | J151: 1379.8 | K151: 1379.01 | L151: 1389.6 | M151: =SUM(F151:L151) -> 9516.59 | N151: =O150 -> 494.95 | O151: 498.09 | P151: =MAX((O151-N151)*3000,0) -> 9420 | Q151: =R150 -> 3.42 | R151: 3.43 | S151: =MAX((R151-Q151)*3000,0) -> 30 | T151: =P151-S151 -> 9390
A152: =A151+1 -> 154 | B152: 45897 | C152: 45897 | F152: 1265.24 | G152: 1261.42 | H152: 1263.8 | I152: 1321.09 | J152: 1316.63 | K152: 1316.72 | L152: 1328.81 | M152: =SUM(F152:L152) -> 9073.71 | N152: =O151 -> 498.09 | O152: 501.1 | P152: =MAX((O152-N152)*3000,0) -> 9030 | Q152: =R151 -> 3.43 | R152: 3.44 | S152: =MAX((R152-Q152)*3000,0) -> 30 | T152: =P152-S152 -> 9000
A153: =A152+1 -> 155 | B153: 45898 | C153: 45898 | F153: 994.36 | G153: 991.7 | H153: 9991.71 | I153: 1037.76 | J153: 1030.58 | K153: 1031.01 | L153: 1037.83 | M153: =SUM(F153:L153) -> 16114.95 | N153: =O152 -> 501.1 | O153: 503.47 | P153: =MAX((O153-N153)*3000,0) -> 7110 | Q153: =R152 -> 3.44 | R153: 3.45 | S153: =MAX((R153-Q153)*3000,0) -> 30 | T153: =P153-S153 -> 7080
A154: =A153+1 -> 156 | B154: 45899 | C154: 45899 | F154: 1159.49 | G154: 1155.06 | H154: 1154.37 | I154: 1208.51 | J154: 1203.16 | K154: 1203.9 | L154: 1211.61 | M154: =SUM(F154:L154) -> 8296.1 | N154: =O153 -> 503.47 | O154: 506.22 | P154: =MAX((O154-N154)*3000,0) -> 8250 | Q154: =R153 -> 3.45 | R154: 3.46 | S154: =MAX((R154-Q154)*3000,0) -> 30 | T154: =P154-S154 -> 8220
... A162: =A161+1 -> 164 | B162: 45907 | C162: 45907 | F162: 448.62 | G162: 444.48 | H162: 443.08 | I162: 462.14 | J162: 457.52 | K162: 456.14 | L162: 458.71 | M162: =SUM(F162:L162) -> 3170.69 | N162: =O161 -> 524.61 | O162: 525.65 | P162: =MAX((O162-N162)*3000,0) -> 3120 | Q162: =R161 -> 3.54 | R162: 3.55 | S162: =MAX((R162-Q162)*3000,0) -> 30 | T162: =P162-S162 -> 3090
A163: =A162+1 -> 165 | B163: 45908 | C163: 45908 | F163: 508.95 | G163: 504.81 | H163: 504.24 | I163: 526.56 | J163: 523.39 | K163: 521,28 | L163: 524.29 | M163: =SUM(F163:L163) -> 3092.24 | N163: =O162 -> 525.65 | O163: 526.85 | P163: =MAX((O163-N163)*3000,0) -> 3600 | Q163: =R162 -> 3.55 | R163: 3.56 | S163: =MAX((R163-Q163)*3000,0) -> 30 | T163: =P163-S163 -> 3570
A164: =A163+1 -> 166 | B164: 45909 | C164: 45909 | F164: 1601.66 | G164: 1594 | H164: 1590.41 | I164: 1657.22 | J164: 1645.05 | K164: 1636.44 | L164: 1638.62 | M164: =SUM(F164:L164) -> 11363.4 | N164: =O163 -> 526.85 | O164: 530.6 | P164: =MAX((O164-N164)*3000,0) -> 11250 | Q164: =R163 -> 3.56 | R164: 3.57 | S164: =MAX((R164-Q164)*3000,0) -> 30 | T164: =P164-S164 -> 11220
A165: =A164+1 -> 167 | B165: 45910 | C165: 45910 | F165: 1663.21 | G165: 1444.24 | H165: 1461.53 | I165: 1514.62 | J165: 1521.49 | K165: 1523.09 | L165: 1538.63 | M165: =SUM(F165:L165) -> 10666.81 | N165: =O164 -> 530.6 | O165: 534.05 | P165: =MAX((O165-N165)*3000,0) -> 10350 | Q165: =R164 -> 3.57 | R165: 3.58 | S165: =MAX((R165-Q165)*3000,0) -> 30 | T165: =P165-S165 -> 10320
A166: =A165+1 -> 168 | B166: 45911 | C166: 45911 | F166: 1992.49 | G166: 1984.6 | H166: 1991.23 | I166: 2078.13 | J166: 2071.11 | K166: 2066.35 | L166: 2075.8 | M166: =SUM(F166:L166) -> 14259.71 | N166: =O165 -> 534.05 | O166: 538.74 | P166: =MAX((O166-N166)*3000,0) -> 14070 | Q166: =R165 -> 3.58 | R166: 3.59 | S166: =MAX((R166-Q166)*3000,0) -> 30 | T166: =P166-S166 -> 14040
A167: =A166+1 -> 169 | B167: 45912 | C167: 45912 | F167: 1716.75 | G167: 1713.72 | H167: 17115.09 | I167: 1799.08 | J167: 1797.26 | K167: 1791.73 | L167: 1799.21 | M167: =SUM(F167:L167) -> 27732.84 | N167: =O166 -> 538.74 | O167: 542.81 | P167: =MAX((O167-N167)*3000,0) -> 12210 | Q167: =R166 -> 3.59 | R167: 3.6 | S167: =MAX((R167-Q167)*3000,0) -> 30 | T167: =P167-S167 -> 12180
A168: =A167+1 -> 170 | B168: 45913 | C168: 45913 | F168: 1741.58 | G168: 1741.08 | H168: 1751.6 | I168: 1835.89 | J168: 1834.96 | K168: 1832.84 | L168: 1843.74 | M168: =SUM(F168:L168) -> 12581.69 | N168: =O167 -> 542.81 | O168: 546.96 | P168: =MAX((O168-N168)*3000,0) -> 12450 | Q168: =R167 -> 3.6 | R168: 3.61 | S168: =MAX((R168-Q168)*3000,0) -> 30 | T168: =P168-S168 -> 12420
A169: =A168+1 -> 171 | B169: 45914 | C169: 45914 | F169: 1235.15 | G169: 1230.53 | H169: 1228.22 | I169: 1283.83 | J169: 1281.01 | K169: 1277.74 | L169: 1279.45 | M169: =SUM(F169:L169) -> 8815.93 | N169: =O168 -> 546.96 | O169: 549.88 | P169: =MAX((O169-N169)*3000,0) -> 8760 | Q169: =R168 -> 3.61 | R169: 3.62 | S169: =MAX((R169-Q169)*3000,0) -> 30 | T169: =P169-S169 -> 8730
A170: =A169+1 -> 172 | B170: 45915 | C170: 45915 | F170: 1027.12 | G170: 1026.5 | H170: 1022 | I170: 1065 | J170: 1062.15 | K170: 1062 | L170: 1067.66 | M170: =SUM(F170:L170) -> 7332.43 | N170: =O169 -> 549.88 | O170: 552.31 | P170: =MAX((O170-N170)*3000,0) -> 7290 | Q170: =R169 -> 3.62 | R170: 3.63 | S170: =MAX((R170-Q170)*3000,0) -> 30 | T170: =P170-S170 -> 7260
A171: =A170+1 -> 173 | B171: 45916 | C171: 45916 | F171: 1677.62 | G171: 1675.41 | H171: 1678.42 | I171: 1764.17 | J171: 1764.3 | K171: 1761.75 | L171: 1769.69 | M171: =SUM(F171:L171) -> 12091.36 | N171: =O170 -> 552.31 | O171: 556.69 | P171: =MAX((O171-N171)*3000,0) -> 13140 | Q171: =R170 -> 3.63 | R171: 3.64 | S171: =MAX((R171-Q171)*3000,0) -> 30 | T171: =P171-S171 -> 13110
A172: =A171+1 -> 174 | B172: 45917 | C172: 45917 | F172: 1711.51 | G172: 1707.12 | H172: 1707.63 | I172: 1780.95 | J172: 1778.18 | K172: 1770.12 | L172: 1778.18 | M172: =SUM(F172:L172) -> 12233.69 | N172: =O171 -> 556.69 | O172: 560.32 | P172: =MAX((O172-N172)*3000,0) -> 10890 | Q172: =R171 -> 3.64 | R172: 3.65 | S172: =MAX((R172-Q172)*3000,0) -> 30 | T172: =P172-S172 -> 10860
A173: =A172+1 -> 175 | B173: 45918 | C173: 45918 | F173: 1733.5 | G173: 1727.07 | H173: 1718 | I173: 1802.84 | J173: 1795.86 | K173: 1781.84 | L173: 1791.04 | M173: =SUM(F173:L173) -> 12350.15 | N173: =O172 -> 560.32 | O173: 564.4 | P173: =MAX((O173-N173)*3000,0) -> 12240 | Q173: =R172 -> 3.65 | R173: 3.66 | S173: =MAX((R173-Q173)*3000,0) -> 30 | T173: =P173-S173 -> 12210
A174: =A173+1 -> 176 | B174: 45919 | C174: 45919 | F174: 1371.32 | G174: 1369.54 | H174: 1363.67 | I174: 1426.07 | J174: 1419.12 | K174: 1416.56 | L174: 1427.79 | M174: =SUM(F174:L174) -> 9794.07 | N174: =O173 -> 564.4 | O174: 567.63 | P174: =MAX((O174-N174)*3000,0) -> 9690 | Q174: =R173 -> 3.66 | R174: 3.67 | S174: =MAX((R174-Q174)*3000,0) -> 30 | T174: =P174-S174 -> 9660
A175: =A174+1 -> 177 | B175: 45920 | C175: 45920 | F175: 1040.45 | G175: 1035.4 | H175: 1035.1 | I175: 1084.03 | J175: 1081.95 | K175: 1079.07 | L175: 1085.41 | M175: =SUM(F175:L175) -> 7441.41 | N175: =O174 -> 567.63 | O175: 570.09 | P175: =MAX((O175-N175)*3000,0) -> 7380 | Q175: =R174 -> 3.67 | R175: 3.68 | S175: =MAX((R175-Q175)*3000,0) -> 30 | T175: =P175-S175 -> 7350
A176: =A175+1 -> 178 | B176: 45921 | C176: 45921 | D176: 0.30208333 | E176: 0.73958333 | F176: 1513.35 | G176: 1508.44 | H176: 1511.42 | I176: 1578.83 | J176: 1576.27 | K176: 1573.38 | L176: 1580.35 | M176: =SUM(F176:L176) -> 10842.04 | N176: =O175 -> 570.09 | O176: 573.66 | P176: =MAX((O176-N176)*3000,0) -> 10710 | Q176: =R175 -> 3.68 | R176: 3.7 | S176: =MAX((R176-Q176)*3000,0) -> 60 | T176: =P176-S176 -> 10650 | V176: 3.75 | W176: 29.65 | AB176: cloudy
A177: =A176+1 -> 179 | B177: 45922 | C177: 45922 | D177: 0.30208333 | E177: 0.75 | F177: 1125.25 | G177: 1120.2 | H177: 1120.95 | I177: 1171 | J177: 1171.43 | K177: 1168.5 | L177: 1176.33 | M177: =SUM(F177:L177) -> 8053.66 | N177: =O176 -> 573.66 | O177: 576.32 | P177: =MAX((O177-N177)*3000,0) -> 7980 | Q177: =R176 -> 3.7 | R177: 3.71 | S177: =MAX((R177-Q177)*3000,0) -> 30 | T177: =P177-S177 -> 7950 | V177: 3.24 | W177: 28.38 | AB177: cloudy
A178: =A177+1 -> 180 | B178: 45923 | C178: 45923 | D178: 0.29166667 | E178: 0.76041667 | F178: 1815.15 | G178: 1812.13 | H178: 1819.19 | I178: 1912.84 | J178: 1912.25 | K178: 1908.74 | L178: 1920.53 | M178: =SUM(F178:L178) -> 13100.83 | N178: =O177 -> 576.32 | O178: 580.64 | P178: =MAX((O178-N178)*3000,0) -> 12960 | Q178: =R177 -> 3.71 | R178: 3.72 | S178: =MAX((R178-Q178)*3000,0) -> 30 | T178: =P178-S178 -> 12930 | V178: 3.71 | W178: 29.73 | AB178: sunny
A179: =A178+1 -> 181 | B179: 45924 | C179: 45924 | D179: 0.29166667 | E179: 0.76111111 | F179: 1770.8 | G179: 1763.63 | H179: 1758.58 | I179: 1841.64 | J179: 1837.7 | K179: 1825.18 | L179: 1835 | M179: =SUM(F179:L179) -> 12632.53 | N179: =O178 -> 580.64 | O179: 584.8 | P179: =MAX((O179-N179)*3000,0) -> 12480 | Q179: =R178 -> 3.72 | R179: 3.73 | S179: =MAX((R179-Q179)*3000,0) -> 30 | T179: =P179-S179 -> 12450 | V179: 2.42 | W179: 29.62 | AB179: sunny
A180: =A179+1 -> 182 | B180: 45925 | C180: 45925 | D180: 0.29166667 | E180: 0.78263889 | F180: 1604.76 | G180: 1602 | H180: 1604.01 | I180: 1683.56 | J180: 1688.05 | K180: 1689.13 | L180: 1699.1 | M180: =SUM(F180:L180) -> 11570.61 | N180: =O179 -> 584.8 | O180: 588.61 | P180: =MAX((O180-N180)*3000,0) -> 11430 | Q180: =R179 -> 3.73 | R180: 3.74 | S180: =MAX((R180-Q180)*3000,0) -> 30 | T180: =P180-S180 -> 11400 | V180: 4.09 | W180: 30.91 | AB180: sunny
A181: =A180+1 -> 183 | B181: 45926 | C181: 45926 | D181: 0.68541667 | E181: 0.76041667 | F181: 371.17 | G181: 368.5 | H181: 369.01 | I181: 388.02 | J181: 386.62 | K181: 385.6 | L181: 388.75 | M181: =SUM(F181:L181) -> 2657.67 | N181: =O180 -> 588.61 | O181: 589.5 | P181: =MAX((O181-N181)*3000,0) -> 2670 | Q181: =R180 -> 3.74 | R181: 3.75 | S181: =MAX((R181-Q181)*3000,0) -> 30 | T181: =P181-S181 -> 2640 | V181: 0.37 | W181: 30.3 | AB181: sunny
A182: =A181+1 -> 184 | B182: 45927 | C182: 45927 | D182: 0.29166667 | E182: 0.76041667 | F182: 1531.9 | G182: 1528.1 | H182: 1527.26 | I182: 1603.56 | J182: 1599.56 | K182: 1595.73 | L182: 1608.1 | M182: =SUM(F182:L182) -> 10994.21 | N182: =O181 -> 589.5 | O182: 593.12 | P182: =MAX((O182-N182)*3000,0) -> 10860 | Q182: =R181 -> 3.75 | R182: 3.76 | S182: =MAX((R182-Q182)*3000,0) -> 30 | T182: =P182-S182 -> 10830 | V182: 4.13 | W182: 31.4 | AB182: sunny
A183: =A182+1 -> 185 | B183: 45928 | C183: 45928 | D183: 0.3125 | E183: 0.73958333 | F183: 514.36 | G183: 511.72 | H183: 510.65 | I183: 536.34 | J183: 535.04 | K183: 534.38 | L183: 539.63 | M183: =SUM(F183:L183) -> 3682.12 | N183: =O182 -> 593.12 | O183: 594.34 | P183: =MAX((O183-N183)*3000,0) -> 3660 | Q183: =R182 -> 3.76 | R183: 3.77 | S183: =MAX((R183-Q183)*3000,0) -> 30 | T183: =P183-S183 -> 3630 | V183: 1.72 | W183: 27.54 | AB183: cloudy
A184: =A183+1 -> 186 | B184: 45929 | C184: 45929 | D184: 0.33333333 | E184: 0.75 | F184: 585 | G184: 582.61 | H184: 584 | I184: 615.31 | J184: 614.39 | K184: 614.96 | L184: 620.21 | M184: =SUM(F184:L184) -> 4216.48 | N184: =O183 -> 594.34 | O184: 595.73 | P184: =MAX((O184-N184)*3000,0) -> 4170 | Q184: =R183 -> 3.77 | R184: 3.79 | S184: =MAX((R184-Q184)*3000,0) -> 60 | T184: =P184-S184 -> 4110 | V184: 1.45 | W184: 26.65 | AB184: rainy
A185: =A184+1 -> 187 | B185: 45930 | C185: 45930 | D185: 0.29166667 | E185: 0.70833333 | F185: 520.22 | G185: 517.56 | H185: 519.08 | I185: 545.4 | J185: 545.65 | K185: 546.97 | L185: 553.31 | M185: =SUM(F185:L185) -> 3748.19 | N185: =O184 -> 595.73 | O185: 596.97 | P185: =MAX((O185-N185)*3000,0) -> 3720 | Q185: =R184 -> 3.79 | R185: 3.8 | S185: =MAX((R185-Q185)*3000,0) -> 30 | T185: =P185-S185 -> 3690 | V185: 1.22 | W185: 23.64 | AB185: rainy
A186: =A185+1 -> 188 | B186: 45931 | C186: 45931 | D186: 0.28125 | E186: 0.75 | F186: 784 | G186: 778.87 | H186: 781.45 | I186: 815.95 | J186: 815.85 | K186: 815.18 | L186: 821.54 | M186: =SUM(F186:L186) -> 5612.84 | N186: =O185 -> 596.97 | O186: 598.82 | P186: =MAX((O186-N186)*3000,0) -> 5550 | Q186: =R185 -> 3.8 | R186: 3.81 | S186: =MAX((R186-Q186)*3000,0) -> 30 | T186: =P186-S186 -> 5520 | V186: 1.61 | W186: 25.44 | AB186: rainy
A187: =A186+1 -> 189 | B187: 45932 | C187: 45932 | D187: 0.30208333 | E187: 0.73958333 | F187: 1002.16 | G187: 997.58 | H187: 999.64 | I187: 1046.59 | J187: 1044.14 | K187: 1044.28 | L187: 1050.76 | M187: =SUM(F187:L187) -> 7185.15 | N187: =O186 -> 598.82 | O187: 601.19 | P187: =MAX((O187-N187)*3000,0) -> 7110 | Q187: =R186 -> 3.81 | R187: 3.82 | S187: =MAX((R187-Q187)*3000,0) -> 30 | T187: =P187-S187 -> 7080 | V187: 2.03 | W187: 26.59 | AB187: rainy
... A240: =A239+1 -> 242 | B240: 45985 | C240: 45985 | D240: 0.3125 | E240: 0.73958333 | F240: 1685.43 | G240: 1687.26 | H240: 1699.59 | I240: 1773.87 | J240: 1761.5 | K240: 1758.58 | L240: 1771.89 | M240: =SUM(F240:L240) -> 12138.12 | N240: =O239 -> 782.22 | O240: 786.22 | P240: =MAX((O240-N240)*3000,0) -> 12000 | Q240: =R239 -> 4.42 | R240: 4.43 | S240: =MAX((R240-Q240)*3000,0) -> 30 | T240: =P240-S240 -> 11970 | V240: 4.11 | W240: 27.45 | AB240: sunny
A241: =A240+1 -> 243 | B241: 45986 | C241: 45986 | D241: 0.3125 | E241: 0.73958333 | F241: 1506.43 | G241: 1507.68 | H241: 1519.77 | I241: 1585.7 | J241: 1574.8 | K241: 1574.96 | L241: 1586.26 | M241: =SUM(F241:L241) -> 10855.6 | N241: =O240 -> 786.22 | O241: 789.8 | P241: =MAX((O241-N241)*3000,0) -> 10740 | Q241: =R240 -> 4.43 | R241: 4.45 | S241: =MAX((R241-Q241)*3000,0) -> 60 | T241: =P241-S241 -> 10680 | U241: 3.9 | V241: 3.9 | W241: 27.07 | AB241: sunny
A242: =A241+1 -> 244 | B242: 45987 | C242: 45987 | D242: 0.3125 | E242: 0.72916667 | F242: 1406.6 | G242: 1405.7 | H242: 1420.6 | I242: 1481.18 | J242: 1473.22 | K242: 1473.21 | L242: 1486.81 | M242: =SUM(F242:L242) -> 10147.32 | N242: =O241 -> 789.8 | O242: 793.15 | P242: =MAX((O242-N242)*3000,0) -> 10050 | Q242: =R241 -> 4.45 | R242: 4.46 | S242: =MAX((R242-Q242)*3000,0) -> 30 | T242: =P242-S242 -> 10020 | V242: 3.7 | W242: 27.04 | AB242: sunny
A243: =A242+1 -> 245 | B243: 45988 | C243: 45988 | D243: 0.32291667 | E243: 0.72916667 | F243: 1320.6 | G243: 1321 | H243: 1332.82 | I243: 1389.62 | J243: 1382.04 | K243: 1381.69 | L243: 1393.84 | M243: =SUM(F243:L243) -> 9521.61 | N243: =O242 -> 793.15 | O243: 796.3 | P243: =MAX((O243-N243)*3000,0) -> 9450 | Q243: =R242 -> 4.46 | R243: 4.47 | S243: =MAX((R243-Q243)*3000,0) -> 30 | T243: =P243-S243 -> 9420 | V243: 3.42 | W243: 28.62 | AB243: sunny
A244: =A243+1 -> 246 | B244: 45989 | C244: 45989 | D244: 0.3125 | E244: 0.72916667 | F244: 1183 | G244: 1181.42 | H244: 1193.1 | I244: 1244.25 | J244: 1238.82 | K244: 1238.86 | L244: 1251.09 | M244: =SUM(F244:L244) -> 8530.54 | N244: =O243 -> 796.3 | O244: 799.12 | P244: =MAX((O244-N244)*3000,0) -> 8460 | Q244: =R243 -> 4.47 | R244: 4.48 | S244: =MAX((R244-Q244)*3000,0) -> 30 | T244: =P244-S244 -> 8430 | V244: 3.13 | W244: 28.4 | AB244: sunny
A245: =A244+1 -> 247 | B245: 45990 | C245: 45990 | D245: 0.32291667 | E245: 0.72916667 | F245: 1264.91 | G245: 1263.3 | H245: 1276 | I245: 1333.3 | J245: 1326.65 | K245: 1328.88 | L245: 1343.32 | M245: =SUM(F245:L245) -> 9136.36 | N245: =O244 -> 799.12 | O245: 802.14 | P245: =MAX((O245-N245)*3000,0) -> 9060 | Q245: =R244 -> 4.48 | R245: 4.49 | S245: =MAX((R245-Q245)*3000,0) -> 30 | T245: =P245-S245 -> 9030 | V245: 3.34 | W245: 27.37 | AB245: sunny
A246: =A245+1 -> 248 | B246: 45991 | C246: 45991 | D246: 0.3125 | E246: 0.72916667 | F246: 1431.79 | G246: 1432.27 | H246: 1445.38 | I246: 1506.73 | J246: 1498.62 | K246: 1497.48 | L246: 1508.03 | M246: =SUM(F246:L246) -> 10320.3 | N246: =O245 -> 802.14 | O246: 805.03 | P246: =MAX((O246-N246)*3000,0) -> 8670 | Q246: =R245 -> 4.49 | R246: 4.5 | S246: =MAX((R246-Q246)*3000,0) -> 30 | T246: =P246-S246 -> 8640 | V246: 3.55 | W246: 27.29 | AB246: sunny
A247: =A246+1 -> 249 | B247: 45992 | C247: 45992 | D247: 0.31319444 | E247: 0.72916667 | F247: 1457.4 | G247: 1458.72 | H247: 1471.01 | I247: 1537.5 | J247: 1525.52 | K247: 1524.71 | L247: 1537.8 | M247: =SUM(F247:L247) -> 10512.66 | N247: =O246 -> 805.03 | O247: 809.01 | P247: =MAX((O247-N247)*3000,0) -> 11940 | Q247: =R246 -> 4.5 | R247: 4.52 | S247: =MAX((R247-Q247)*3000,0) -> 60 | T247: =P247-S247 -> 11880 | V247: 3.81 | W247: 26.7 | AB247: sunny
...

Sheet Inverter_PR
A1: Inverter_Availability_Sheet
C2: 335.72 | D2: 335.72 | E2: 335.72 | F2: 350.98 | G2: 350.98 | H2: 350.98 | I2: 350.98
C3: Inv_1 | D3: Inv_2 | E3: Inv_3 | F3: Inv_4 | G3: Inv_5 | H3: Inv_6 | I3: Inv_7
A4: 45747 | B4: 45747
A5: 45748 | B5: 45748 | C5: =IFERROR((Data_Entry!F3/Data_Entry!$V3/C$2),"") -> 1.2085018 | D5: =IFERROR((Data_Entry!G3/Data_Entry!$V3/D$2),"") -> 1.2288676 | E5: =IFERROR((Data_Entry!H3/Data_Entry!$V3/E$2),"") -> 1.20681 | F5: =IFERROR((Data_Entry!I3/Data_Entry!$V3/F$2),"") -> 1.2169267 | G5: =IFERROR((Data_Entry!J3/Data_Entry!$V3/G$2),"") -> 1.2265821 | H5: =IFERROR((Data_Entry!K3/Data_Entry!$V3/H$2),"") -> 1.2256911 | I5: =IFERROR((Data_Entry!L3/Data_Entry!$V3/I$2),"") -> 1.215066
A6: 45749 | B6: 45749 | C6: =IFERROR((Data_Entry!F4/Data_Entry!$V4/C$2),"") -> 1.2319465 | D6: =IFERROR((Data_Entry!G4/Data_Entry!$V4/D$2),"") -> 1.2245461 | E6: =IFERROR((Data_Entry!H4/Data_Entry!$V4/E$2),"") -> 1.2133664 | F6: =IFERROR((Data_Entry!I4/Data_Entry!$V4/F$2),"") -> 1.2209099 | G6: =IFERROR((Data_Entry!J4/Data_Entry!$V4/G$2),"") -> 1.1906577 | H6: =IFERROR((Data_Entry!K4/Data_Entry!$V4/H$2),"") -> 1.1941516 | I6: =IFERROR((Data_Entry!L4/Data_Entry!$V4/I$2),"") -> 1.1748231
A7: 45750 | B7: 45750 | C7: =IFERROR((Data_Entry!F5/Data_Entry!$V5/C$2),"") -> 1.2059066 | D7: =IFERROR((Data_Entry!G5/Data_Entry!$V5/D$2),"") -> 1.1972063 | E7: =IFERROR((Data_Entry!H5/Data_Entry!$V5/E$2),"") -> 1.1894894 | F7: =IFERROR((Data_Entry!I5/Data_Entry!$V5/F$2),"") -> 1.1962383 | G7: =IFERROR((Data_Entry!J5/Data_Entry!$V5/G$2),"") -> 1.1664323 | H7: =IFERROR((Data_Entry!K5/Data_Entry!$V5/H$2),"") -> 1.1714591 | I7: =IFERROR((Data_Entry!L5/Data_Entry!$V5/I$2),"") -> 1.1502991
A8: 45751 | B8: 45751 | C8: =IFERROR((Data_Entry!F6/Data_Entry!$V6/C$2),"") -> 1.2169581 | D8: =IFERROR((Data_Entry!G6/Data_Entry!$V6/D$2),"") -> 1.2067612 | E8: =IFERROR((Data_Entry!H6/Data_Entry!$V6/E$2),"") -> 1.1991721 | F8: =IFERROR((Data_Entry!I6/Data_Entry!$V6/F$2),"") -> 1.2075108 | G8: =IFERROR((Data_Entry!J6/Data_Entry!$V6/G$2),"") -> 1.1762705 | H8: =IFERROR((Data_Entry!K6/Data_Entry!$V6/H$2),"") -> 1.1831543 | I8: =IFERROR((Data_Entry!L6/Data_Entry!$V6/I$2),"") -> 1.1594092
A9: 45752 | B9: 45752 | C9: =IFERROR((Data_Entry!F7/Data_Entry!$V7/C$2),"") -> 1.2005774 | D9: =IFERROR((Data_Entry!G7/Data_Entry!$V7/D$2),"") -> 1.192764 | E9: =IFERROR((Data_Entry!H7/Data_Entry!$V7/E$2),"") -> 1.1836367 | F9: =IFERROR((Data_Entry!I7/Data_Entry!$V7/F$2),"") -> 1.1927615 | G9: =IFERROR((Data_Entry!J7/Data_Entry!$V7/G$2),"") -> 1.1617308 | H9: =IFERROR((Data_Entry!K7/Data_Entry!$V7/H$2),"") -> 1.1685822 | I9: =IFERROR((Data_Entry!L7/Data_Entry!$V7/I$2),"") -> 1.0911504
A10: 45753 | B10: 45753 | C10: =IFERROR((Data_Entry!F8/Data_Entry!$V8/C$2),"") -> 1.1773521 | D10: =IFERROR((Data_Entry!G8/Data_Entry!$V8/D$2),"") -> 1.1713566 | E10: =IFERROR((Data_Entry!H8/Data_Entry!$V8/E$2),"") -> 1.1620829 | F10: =IFERROR((Data_Entry!I8/Data_Entry!$V8/F$2),"") -> 1.17348 | G10: =IFERROR((Data_Entry!J8/Data_Entry!$V8/G$2),"") -> 1.1426543 | H10: =IFERROR((Data_Entry!K8/Data_Entry!$V8/H$2),"") -> 1.1481829 | I10: =IFERROR((Data_Entry!L8/Data_Entry!$V8/I$2),"") -> 1.1283378
A11: 45754 | B11: 45754 | C11: =IFERROR((Data_Entry!F9/Data_Entry!$V9/C$2),"") -> 1.1748686 | D11: =IFERROR((Data_Entry!G9/Data_Entry!$V9/D$2),"") -> 1.1666092 | E11: =IFERROR((Data_Entry!H9/Data_Entry!$V9/E$2),"") -> 1.1570694 | F11: =IFERROR((Data_Entry!I9/Data_Entry!$V9/F$2),"") -> 1.1675574 | G11: =IFERROR((Data_Entry!J9/Data_Entry!$V9/G$2),"") -> 1.1375589 | H11: =IFERROR((Data_Entry!K9/Data_Entry!$V9/H$2),"") -> 1.1438024 | I11: =IFERROR((Data_Entry!L9/Data_Entry!$V9/I$2),"") -> 1.1253782
A12: 45755 | B12: 45755 | C12: =IFERROR((Data_Entry!F10/Data_Entry!$V10/C$2),"") -> 1.1210379 | D12: =IFERROR((Data_Entry!G10/Data_Entry!$V10/D$2),"") -> 1.1157404 | E12: =IFERROR((Data_Entry!H10/Data_Entry!$V10/E$2),"") -> 1.1064026 | F12: =IFERROR((Data_Entry!I10/Data_Entry!$V10/F$2),"") -> 1.1280535 | G12: =IFERROR((Data_Entry!J10/Data_Entry!$V10/G$2),"") -> 1.0885535 | H12: =IFERROR((Data_Entry!K10/Data_Entry!$V10/H$2),"") -> 1.0934365 | I12: =IFERROR((Data_Entry!L10/Data_Entry!$V10/I$2),"") -> 1.0755484
A13: 45756 | B13: 45756 | C13: =IFERROR((Data_Entry!F11/Data_Entry!$V11/C$2),"") -> 1.1280606 | D13: =IFERROR((Data_Entry!G11/Data_Entry!$V11/D$2),"") -> 1.1212323 | E13: =IFERROR((Data_Entry!H11/Data_Entry!$V11/E$2),"") -> 1.112934 | F13: =IFERROR((Data_Entry!I11/Data_Entry!$V11/F$2),"") -> 1.1445331 | G13: =IFERROR((Data_Entry!J11/Data_Entry!$V11/G$2),"") -> 1.0934774 | H13: =IFERROR((Data_Entry!K11/Data_Entry!$V11/H$2),"") -> 1.0980079 | I13: =IFERROR((Data_Entry!L11/Data_Entry!$V11/I$2),"") -> 1.0809433
A14: 45757 | B14: 45757 | C14: =IFERROR((Data_Entry!F12/Data_Entry!$V12/C$2),"") -> 1.1210144 | D14: =IFERROR((Data_Entry!G12/Data_Entry!$V12/D$2),"") -> 1.1100601 | E14: =IFERROR((Data_Entry!H12/Data_Entry!$V12/E$2),"") -> 1.1028566 | F14: =IFERROR((Data_Entry!I12/Data_Entry!$V12/F$2),"") -> 1.1459052 | G14: =IFERROR((Data_Entry!J12/Data_Entry!$V12/G$2),"") -> 1.1174484 | H14: =IFERROR((Data_Entry!K12/Data_Entry!$V12/H$2),"") -> 1.1307697 | I14: =IFERROR((Data_Entry!L12/Data_Entry!$V12/I$2),"") -> 1.1203034
A15: 45758 | B15: 45758 | C15: =IFERROR((Data_Entry!F13/Data_Entry!$V13/C$2),"") -> 1.2000297 | D15: =IFERROR((Data_Entry!G13/Data_Entry!$V13/D$2),"") -> 1.1934428 | E15: =IFERROR((Data_Entry!H13/Data_Entry!$V13/E$2),"") -> 1.1906397 | F15: =IFERROR((Data_Entry!I13/Data_Entry!$V13/F$2),"") -> 1.2034306 | G15: =IFERROR((Data_Entry!J13/Data_Entry!$V13/G$2),"") -> 1.1667216 | H15: =IFERROR((Data_Entry!K13/Data_Entry!$V13/H$2),"") -> 1.1658935 | I15: =IFERROR((Data_Entry!L13/Data_Entry!$V13/I$2),"") -> 1.159118
A16: 45759 | B16: 45759 | C16: =IFERROR((Data_Entry!F14/Data_Entry!$V14/C$2),"") -> 1.1727762 | D16: =IFERROR((Data_Entry!G14/Data_Entry!$V14/D$2),"") -> 1.1668188 | E16: =IFERROR((Data_Entry!H14/Data_Entry!$V14/E$2),"") -> 1.2048379 | F16: =IFERROR((Data_Entry!I14/Data_Entry!$V14/F$2),"") -> 1.179532 | G16: =IFERROR((Data_Entry!J14/Data_Entry!$V14/G$2),"") -> 1.1404849 | H16: =IFERROR((Data_Entry!K14/Data_Entry!$V14/H$2),"") -> 1.1378152 | I16: =IFERROR((Data_Entry!L14/Data_Entry!$V14/I$2),"") -> 1.1309559
... A369: 46112 | B369: 46112 | C369: =IFERROR((Data_Entry!F367/Data_Entry!$V367/C$2),"") -> 0.95835235 | D369: =IFERROR((Data_Entry!G367/Data_Entry!$V367/D$2),"") -> 0.93648217 | E369: =IFERROR((Data_Entry!H367/Data_Entry!$V367/E$2),"") -> 0.94044044 | F369: =IFERROR((Data_Entry!I367/Data_Entry!$V367/F$2),"") -> 0.94154831 | G369: =IFERROR((Data_Entry!J367/Data_Entry!$V367/G$2),"") -> 0.91696269 | H369: =IFERROR((Data_Entry!K367/Data_Entry!$V367/H$2),"") -> 0.92668145 | I369: =IFERROR((Data_Entry!L367/Data_Entry!$V367/I$2),"") -> 0.95530929

Sheet Invt_Analysis_Gen_Per_KW &_PR
A1: Daily_Generation_Per_KW_Performance_Analysis
B2: Inverter_No. | C2: =DGR!B3 -> 46181 | D2: =DGR!C3 -> 46182 | E2: =DGR!D3 -> 46183 | F2: =DGR!E3 -> 46184 | G2: =DGR!F3 -> 46185 | H2: =DGR!G3 -> 46186 | I2: =DGR!H3 -> 46187 | J2: =DGR!I3 -> 46188 | ... AH2: =DGR!AG3 -> Total/Avg..
B3: Inv_1 | C3: =IFERROR(VLOOKUP(C$2,Data_Entry!$C:$L,Data_Entry!$A2,0)/VLOOKUP($B3,Basic_Data!$E$2:$G$10,3,0),"") -> 5.4903491 | D3: =IFERROR(VLOOKUP(D$2,Data_Entry!$C:$L,Data_Entry!$A2,0)/VLOOKUP($B3,Basic_Data!$E$2:$G$10,3,0),"") -> 0 | E3: =IFERROR(VLOOKUP(E$2,Data_Entry!$C:$L,Data_Entry!$A2,0)/VLOOKUP($B3,Basic_Data!$E$2:$G$10,3,0),"") -> 0 | F3: =IFERROR(VLOOKUP(F$2,Data_Entry!$C:$L,Data_Entry!$A2,0)/VLOOKUP($B3,Basic_Data!$E$2:$G$10,3,0),"") -> 0 | G3: =IFERROR(VLOOKUP(G$2,Data_Entry!$C:$L,Data_Entry!$A2,0)/VLOOKUP($B3,Basic_Data!$E$2:$G$10,3,0),"") -> 0 | H3: =IFERROR(VLOOKUP(H$2,Data_Entry!$C:$L,Data_Entry!$A2,0)/VLOOKUP($B3,Basic_Data!$E$2:$G$10,3,0),"") -> 0 | I3: =IFERROR(VLOOKUP(I$2,Data_Entry!$C:$L,Data_Entry!$A2,0)/VLOOKUP($B3,Basic_Data!$E$2:$G$10,3,0),"") -> 0 | J3: =IFERROR(VLOOKUP(J$2,Data_Entry!$C:$L,Data_Entry!$A2,0)/VLOOKUP($B3,Basic_Data!$E$2:$G$10,3,0),"") -> 0 | ... AG3: =IFERROR(VLOOKUP(AG$2,Data_Entry!$C:$L,Data_Entry!$A2,0)/VLOOKUP($B3,Basic_Data!$E$2:$G$10,3,0),"")
B4: Inv_2 | C4: =IFERROR(VLOOKUP(C$2,Data_Entry!$C:$L,Data_Entry!$A3,0)/VLOOKUP($B4,Basic_Data!$E$2:$G$10,3,0),"") -> 5.4759919 | D4: =IFERROR(VLOOKUP(D$2,Data_Entry!$C:$L,Data_Entry!$A3,0)/VLOOKUP($B4,Basic_Data!$E$2:$G$10,3,0),"") -> 0 | E4: =IFERROR(VLOOKUP(E$2,Data_Entry!$C:$L,Data_Entry!$A3,0)/VLOOKUP($B4,Basic_Data!$E$2:$G$10,3,0),"") -> 0 | F4: =IFERROR(VLOOKUP(F$2,Data_Entry!$C:$L,Data_Entry!$A3,0)/VLOOKUP($B4,Basic_Data!$E$2:$G$10,3,0),"") -> 0 | G4: =IFERROR(VLOOKUP(G$2,Data_Entry!$C:$L,Data_Entry!$A3,0)/VLOOKUP($B4,Basic_Data!$E$2:$G$10,3,0),"") -> 0 | H4: =IFERROR(VLOOKUP(H$2,Data_Entry!$C:$L,Data_Entry!$A3,0)/VLOOKUP($B4,Basic_Data!$E$2:$G$10,3,0),"") -> 0 | I4: =IFERROR(VLOOKUP(I$2,Data_Entry!$C:$L,Data_Entry!$A3,0)/VLOOKUP($B4,Basic_Data!$E$2:$G$10,3,0),"") -> 0 | J4: =IFERROR(VLOOKUP(J$2,Data_Entry!$C:$L,Data_Entry!$A3,0)/VLOOKUP($B4,Basic_Data!$E$2:$G$10,3,0),"") -> 0 | ... AG4: =IFERROR(VLOOKUP(AG$2,Data_Entry!$C:$L,Data_Entry!$A3,0)/VLOOKUP($B4,Basic_Data!$E$2:$G$10,3,0),"")
B5: Inv_3 | C5: =IFERROR(VLOOKUP(C$2,Data_Entry!$C:$L,Data_Entry!$A4,0)/VLOOKUP($B5,Basic_Data!$E$2:$G$10,3,0),"") -> 5.4665793 | D5: =IFERROR(VLOOKUP(D$2,Data_Entry!$C:$L,Data_Entry!$A4,0)/VLOOKUP($B5,Basic_Data!$E$2:$G$10,3,0),"") -> 0 | E5: =IFERROR(VLOOKUP(E$2,Data_Entry!$C:$L,Data_Entry!$A4,0)/VLOOKUP($B5,Basic_Data!$E$2:$G$10,3,0),"") -> 0 | F5: =IFERROR(VLOOKUP(F$2,Data_Entry!$C:$L,Data_Entry!$A4,0)/VLOOKUP($B5,Basic_Data!$E$2:$G$10,3,0),"") -> 0 | G5: =IFERROR(VLOOKUP(G$2,Data_Entry!$C:$L,Data_Entry!$A4,0)/VLOOKUP($B5,Basic_Data!$E$2:$G$10,3,0),"") -> 0 | H5: =IFERROR(VLOOKUP(H$2,Data_Entry!$C:$L,Data_Entry!$A4,0)/VLOOKUP($B5,Basic_Data!$E$2:$G$10,3,0),"") -> 0 | I5: =IFERROR(VLOOKUP(I$2,Data_Entry!$C:$L,Data_Entry!$A4,0)/VLOOKUP($B5,Basic_Data!$E$2:$G$10,3,0),"") -> 0 | J5: =IFERROR(VLOOKUP(J$2,Data_Entry!$C:$L,Data_Entry!$A4,0)/VLOOKUP($B5,Basic_Data!$E$2:$G$10,3,0),"") -> 0 | ... AG5: =IFERROR(VLOOKUP(AG$2,Data_Entry!$C:$L,Data_Entry!$A4,0)/VLOOKUP($B5,Basic_Data!$E$2:$G$10,3,0),"")
B6: Inv_4 | C6: =IFERROR(VLOOKUP(C$2,Data_Entry!$C:$L,Data_Entry!$A5,0)/VLOOKUP($B6,Basic_Data!$E$2:$G$10,3,0),"") -> 5.4326172 | D6: =IFERROR(VLOOKUP(D$2,Data_Entry!$C:$L,Data_Entry!$A5,0)/VLOOKUP($B6,Basic_Data!$E$2:$G$10,3,0),"") -> 0 | E6: =IFERROR(VLOOKUP(E$2,Data_Entry!$C:$L,Data_Entry!$A5,0)/VLOOKUP($B6,Basic_Data!$E$2:$G$10,3,0),"") -> 0 | F6: =IFERROR(VLOOKUP(F$2,Data_Entry!$C:$L,Data_Entry!$A5,0)/VLOOKUP($B6,Basic_Data!$E$2:$G$10,3,0),"") -> 0 | G6: =IFERROR(VLOOKUP(G$2,Data_Entry!$C:$L,Data_Entry!$A5,0)/VLOOKUP($B6,Basic_Data!$E$2:$G$10,3,0),"") -> 0 | H6: =IFERROR(VLOOKUP(H$2,Data_Entry!$C:$L,Data_Entry!$A5,0)/VLOOKUP($B6,Basic_Data!$E$2:$G$10,3,0),"") -> 0 | I6: =IFERROR(VLOOKUP(I$2,Data_Entry!$C:$L,Data_Entry!$A5,0)/VLOOKUP($B6,Basic_Data!$E$2:$G$10,3,0),"") -> 0 | J6: =IFERROR(VLOOKUP(J$2,Data_Entry!$C:$L,Data_Entry!$A5,0)/VLOOKUP($B6,Basic_Data!$E$2:$G$10,3,0),"") -> 0 | ... AG6: =IFERROR(VLOOKUP(AG$2,Data_Entry!$C:$L,Data_Entry!$A5,0)/VLOOKUP($B6,Basic_Data!$E$2:$G$10,3,0),"")
B7: Inv_5 | C7: =IFERROR(VLOOKUP(C$2,Data_Entry!$C:$L,Data_Entry!$A6,0)/VLOOKUP($B7,Basic_Data!$E$2:$G$10,3,0),"") -> 5.4139267 | D7: =IFERROR(VLOOKUP(D$2,Data_Entry!$C:$L,Data_Entry!$A6,0)/VLOOKUP($B7,Basic_Data!$E$2:$G$10,3,0),"") -> 0 | E7: =IFERROR(VLOOKUP(E$2,Data_Entry!$C:$L,Data_Entry!$A6,0)/VLOOKUP($B7,Basic_Data!$E$2:$G$10,3,0),"") -> 0 | F7: =IFERROR(VLOOKUP(F$2,Data_Entry!$C:$L,Data_Entry!$A6,0)/VLOOKUP($B7,Basic_Data!$E$2:$G$10,3,0),"") -> 0 | G7: =IFERROR(VLOOKUP(G$2,Data_Entry!$C:$L,Data_Entry!$A6,0)/VLOOKUP($B7,Basic_Data!$E$2:$G$10,3,0),"") -> 0 | H7: =IFERROR(VLOOKUP(H$2,Data_Entry!$C:$L,Data_Entry!$A6,0)/VLOOKUP($B7,Basic_Data!$E$2:$G$10,3,0),"") -> 0 | I7: =IFERROR(VLOOKUP(I$2,Data_Entry!$C:$L,Data_Entry!$A6,0)/VLOOKUP($B7,Basic_Data!$E$2:$G$10,3,0),"") -> 0 | J7: =IFERROR(VLOOKUP(J$2,Data_Entry!$C:$L,Data_Entry!$A6,0)/VLOOKUP($B7,Basic_Data!$E$2:$G$10,3,0),"") -> 0 | ... AG7: =IFERROR(VLOOKUP(AG$2,Data_Entry!$C:$L,Data_Entry!$A6,0)/VLOOKUP($B7,Basic_Data!$E$2:$G$10,3,0),"")
B8: Inv_6 | C8: =IFERROR(VLOOKUP(C$2,Data_Entry!$C:$L,Data_Entry!$A7,0)/VLOOKUP($B8,Basic_Data!$E$2:$G$10,3,0),"") -> 5.4199669 | D8: =IFERROR(VLOOKUP(D$2,Data_Entry!$C:$L,Data_Entry!$A7,0)/VLOOKUP($B8,Basic_Data!$E$2:$G$10,3,0),"") -> 0 | E8: =IFERROR(VLOOKUP(E$2,Data_Entry!$C:$L,Data_Entry!$A7,0)/VLOOKUP($B8,Basic_Data!$E$2:$G$10,3,0),"") -> 0 | F8: =IFERROR(VLOOKUP(F$2,Data_Entry!$C:$L,Data_Entry!$A7,0)/VLOOKUP($B8,Basic_Data!$E$2:$G$10,3,0),"") -> 0 | G8: =IFERROR(VLOOKUP(G$2,Data_Entry!$C:$L,Data_Entry!$A7,0)/VLOOKUP($B8,Basic_Data!$E$2:$G$10,3,0),"") -> 0 | H8: =IFERROR(VLOOKUP(H$2,Data_Entry!$C:$L,Data_Entry!$A7,0)/VLOOKUP($B8,Basic_Data!$E$2:$G$10,3,0),"") -> 0 | I8: =IFERROR(VLOOKUP(I$2,Data_Entry!$C:$L,Data_Entry!$A7,0)/VLOOKUP($B8,Basic_Data!$E$2:$G$10,3,0),"") -> 0 | J8: =IFERROR(VLOOKUP(J$2,Data_Entry!$C:$L,Data_Entry!$A7,0)/VLOOKUP($B8,Basic_Data!$E$2:$G$10,3,0),"") -> 0 | ... AG8: =IFERROR(VLOOKUP(AG$2,Data_Entry!$C:$L,Data_Entry!$A7,0)/VLOOKUP($B8,Basic_Data!$E$2:$G$10,3,0),"")
B9: Inv_7 | C9: =IFERROR(VLOOKUP(C$2,Data_Entry!$C:$L,Data_Entry!$A8,0)/VLOOKUP($B9,Basic_Data!$E$2:$G$10,3,0),"") -> 5.419739 | D9: =IFERROR(VLOOKUP(D$2,Data_Entry!$C:$L,Data_Entry!$A8,0)/VLOOKUP($B9,Basic_Data!$E$2:$G$10,3,0),"") -> 0 | E9: =IFERROR(VLOOKUP(E$2,Data_Entry!$C:$L,Data_Entry!$A8,0)/VLOOKUP($B9,Basic_Data!$E$2:$G$10,3,0),"") -> 0 | F9: =IFERROR(VLOOKUP(F$2,Data_Entry!$C:$L,Data_Entry!$A8,0)/VLOOKUP($B9,Basic_Data!$E$2:$G$10,3,0),"") -> 0 | G9: =IFERROR(VLOOKUP(G$2,Data_Entry!$C:$L,Data_Entry!$A8,0)/VLOOKUP($B9,Basic_Data!$E$2:$G$10,3,0),"") -> 0 | H9: =IFERROR(VLOOKUP(H$2,Data_Entry!$C:$L,Data_Entry!$A8,0)/VLOOKUP($B9,Basic_Data!$E$2:$G$10,3,0),"") -> 0 | I9: =IFERROR(VLOOKUP(I$2,Data_Entry!$C:$L,Data_Entry!$A8,0)/VLOOKUP($B9,Basic_Data!$E$2:$G$10,3,0),"") -> 0 | J9: =IFERROR(VLOOKUP(J$2,Data_Entry!$C:$L,Data_Entry!$A8,0)/VLOOKUP($B9,Basic_Data!$E$2:$G$10,3,0),"") -> 0 | ... AG9: =IFERROR(VLOOKUP(AG$2,Data_Entry!$C:$L,Data_Entry!$A8,0)/VLOOKUP($B9,Basic_Data!$E$2:$G$10,3,0),"")
B10: Avg_per_Kw | C10: =AVERAGE(C3:C9) -> 5.4455957 | D10: =AVERAGE(D3:D9) -> 0 | E10: =AVERAGE(E3:E9) -> 0 | F10: =AVERAGE(F3:F9) -> 0 | G10: =AVERAGE(G3:G9) -> 0 | H10: =AVERAGE(H3:H9) -> 0 | I10: =AVERAGE(I3:I9) -> 0 | J10: =AVERAGE(J3:J9) -> 0 | ... AH10: =AVERAGE(AH3:AH9) -> #DIV/0!
B13: Inverter_No. | C13: =DGR!B3 -> 46181 | D13: =DGR!C3 -> 46182 | E13: =DGR!D3 -> 46183 | F13: =DGR!E3 -> 46184 | G13: =DGR!F3 -> 46185 | H13: =DGR!G3 -> 46186 | I13: =DGR!H3 -> 46187 | J13: =DGR!I3 -> 46188 | ... AH13: =DGR!AG3 -> Total/Avg..
B14: Inv_1 | C14: =IFERROR(VLOOKUP(C$13,Data_Entry!$C:$M,Data_Entry!$A2,0)/VLOOKUP($B14,Basic_Data!$E$2:$G$9,3,0)/VLOOKUP(C$13,Data_Entry!$C:$V,20,0),"") -> 1.2592544 | D14: =IFERROR(VLOOKUP(D$13,Data_Entry!$C:$M,Data_Entry!$A2,0)/VLOOKUP($B14,Basic_Data!$E$2:$G$9,3,0)/VLOOKUP(D$13,Data_Entry!$C:$V,20,0),"") | E14: =IFERROR(VLOOKUP(E$13,Data_Entry!$C:$M,Data_Entry!$A2,0)/VLOOKUP($B14,Basic_Data!$E$2:$G$9,3,0)/VLOOKUP(E$13,Data_Entry!$C:$V,20,0),"") | F14: =IFERROR(VLOOKUP(F$13,Data_Entry!$C:$M,Data_Entry!$A2,0)/VLOOKUP($B14,Basic_Data!$E$2:$G$9,3,0)/VLOOKUP(F$13,Data_Entry!$C:$V,20,0),"") | G14: =IFERROR(VLOOKUP(G$13,Data_Entry!$C:$M,Data_Entry!$A2,0)/VLOOKUP($B14,Basic_Data!$E$2:$G$9,3,0)/VLOOKUP(G$13,Data_Entry!$C:$V,20,0),"") | H14: =IFERROR(VLOOKUP(H$13,Data_Entry!$C:$M,Data_Entry!$A2,0)/VLOOKUP($B14,Basic_Data!$E$2:$G$9,3,0)/VLOOKUP(H$13,Data_Entry!$C:$V,20,0),"") | I14: =IFERROR(VLOOKUP(I$13,Data_Entry!$C:$M,Data_Entry!$A2,0)/VLOOKUP($B14,Basic_Data!$E$2:$G$9,3,0)/VLOOKUP(I$13,Data_Entry!$C:$V,20,0),"") | J14: =IFERROR(VLOOKUP(J$13,Data_Entry!$C:$M,Data_Entry!$A2,0)/VLOOKUP($B14,Basic_Data!$E$2:$G$9,3,0)/VLOOKUP(J$13,Data_Entry!$C:$V,20,0),"") | ... AG14: =IFERROR(VLOOKUP(AG$13,Data_Entry!$C:$M,Data_Entry!$A2,0)/VLOOKUP($B14,Basic_Data!$E$2:$G$9,3,0)/VLOOKUP(AG$13,Data_Entry!$C:$V,20,0),"")
B15: Inv_2 | C15: =IFERROR(VLOOKUP(C$13,Data_Entry!$C:$M,Data_Entry!$A3,0)/VLOOKUP($B15,Basic_Data!$E$2:$G$9,3,0)/VLOOKUP(C$13,Data_Entry!$C:$V,20,0),"") -> 1.2559614 | D15: =IFERROR(VLOOKUP(D$13,Data_Entry!$C:$M,Data_Entry!$A3,0)/VLOOKUP($B15,Basic_Data!$E$2:$G$9,3,0)/VLOOKUP(D$13,Data_Entry!$C:$V,20,0),"") | E15: =IFERROR(VLOOKUP(E$13,Data_Entry!$C:$M,Data_Entry!$A3,0)/VLOOKUP($B15,Basic_Data!$E$2:$G$9,3,0)/VLOOKUP(E$13,Data_Entry!$C:$V,20,0),"") | F15: =IFERROR(VLOOKUP(F$13,Data_Entry!$C:$M,Data_Entry!$A3,0)/VLOOKUP($B15,Basic_Data!$E$2:$G$9,3,0)/VLOOKUP(F$13,Data_Entry!$C:$V,20,0),"") | G15: =IFERROR(VLOOKUP(G$13,Data_Entry!$C:$M,Data_Entry!$A3,0)/VLOOKUP($B15,Basic_Data!$E$2:$G$9,3,0)/VLOOKUP(G$13,Data_Entry!$C:$V,20,0),"") | H15: =IFERROR(VLOOKUP(H$13,Data_Entry!$C:$M,Data_Entry!$A3,0)/VLOOKUP($B15,Basic_Data!$E$2:$G$9,3,0)/VLOOKUP(H$13,Data_Entry!$C:$V,20,0),"") | I15: =IFERROR(VLOOKUP(I$13,Data_Entry!$C:$M,Data_Entry!$A3,0)/VLOOKUP($B15,Basic_Data!$E$2:$G$9,3,0)/VLOOKUP(I$13,Data_Entry!$C:$V,20,0),"") | J15: =IFERROR(VLOOKUP(J$13,Data_Entry!$C:$M,Data_Entry!$A3,0)/VLOOKUP($B15,Basic_Data!$E$2:$G$9,3,0)/VLOOKUP(J$13,Data_Entry!$C:$V,20,0),"") | ... AG15: =IFERROR(VLOOKUP(AG$13,Data_Entry!$C:$M,Data_Entry!$A3,0)/VLOOKUP($B15,Basic_Data!$E$2:$G$9,3,0)/VLOOKUP(AG$13,Data_Entry!$C:$V,20,0),"")
B16: Inv_3 | C16: =IFERROR(VLOOKUP(C$13,Data_Entry!$C:$M,Data_Entry!$A4,0)/VLOOKUP($B16,Basic_Data!$E$2:$G$9,3,0)/VLOOKUP(C$13,Data_Entry!$C:$V,20,0),"") -> 1.2538026 | D16: =IFERROR(VLOOKUP(D$13,Data_Entry!$C:$M,Data_Entry!$A4,0)/VLOOKUP($B16,Basic_Data!$E$2:$G$9,3,0)/VLOOKUP(D$13,Data_Entry!$C:$V,20,0),"") | E16: =IFERROR(VLOOKUP(E$13,Data_Entry!$C:$M,Data_Entry!$A4,0)/VLOOKUP($B16,Basic_Data!$E$2:$G$9,3,0)/VLOOKUP(E$13,Data_Entry!$C:$V,20,0),"") | F16: =IFERROR(VLOOKUP(F$13,Data_Entry!$C:$M,Data_Entry!$A4,0)/VLOOKUP($B16,Basic_Data!$E$2:$G$9,3,0)/VLOOKUP(F$13,Data_Entry!$C:$V,20,0),"") | G16: =IFERROR(VLOOKUP(G$13,Data_Entry!$C:$M,Data_Entry!$A4,0)/VLOOKUP($B16,Basic_Data!$E$2:$G$9,3,0)/VLOOKUP(G$13,Data_Entry!$C:$V,20,0),"") | H16: =IFERROR(VLOOKUP(H$13,Data_Entry!$C:$M,Data_Entry!$A4,0)/VLOOKUP($B16,Basic_Data!$E$2:$G$9,3,0)/VLOOKUP(H$13,Data_Entry!$C:$V,20,0),"") | I16: =IFERROR(VLOOKUP(I$13,Data_Entry!$C:$M,Data_Entry!$A4,0)/VLOOKUP($B16,Basic_Data!$E$2:$G$9,3,0)/VLOOKUP(I$13,Data_Entry!$C:$V,20,0),"") | J16: =IFERROR(VLOOKUP(J$13,Data_Entry!$C:$M,Data_Entry!$A4,0)/VLOOKUP($B16,Basic_Data!$E$2:$G$9,3,0)/VLOOKUP(J$13,Data_Entry!$C:$V,20,0),"") | ... AG16: =IFERROR(VLOOKUP(AG$13,Data_Entry!$C:$M,Data_Entry!$A4,0)/VLOOKUP($B16,Basic_Data!$E$2:$G$9,3,0)/VLOOKUP(AG$13,Data_Entry!$C:$V,20,0),"")
B17: Inv_4 | C17: =IFERROR(VLOOKUP(C$13,Data_Entry!$C:$M,Data_Entry!$A5,0)/VLOOKUP($B17,Basic_Data!$E$2:$G$9,3,0)/VLOOKUP(C$13,Data_Entry!$C:$V,20,0),"") -> 1.2460131 | D17: =IFERROR(VLOOKUP(D$13,Data_Entry!$C:$M,Data_Entry!$A5,0)/VLOOKUP($B17,Basic_Data!$E$2:$G$9,3,0)/VLOOKUP(D$13,Data_Entry!$C:$V,20,0),"") | E17: =IFERROR(VLOOKUP(E$13,Data_Entry!$C:$M,Data_Entry!$A5,0)/VLOOKUP($B17,Basic_Data!$E$2:$G$9,3,0)/VLOOKUP(E$13,Data_Entry!$C:$V,20,0),"") | F17: =IFERROR(VLOOKUP(F$13,Data_Entry!$C:$M,Data_Entry!$A5,0)/VLOOKUP($B17,Basic_Data!$E$2:$G$9,3,0)/VLOOKUP(F$13,Data_Entry!$C:$V,20,0),"") | G17: =IFERROR(VLOOKUP(G$13,Data_Entry!$C:$M,Data_Entry!$A5,0)/VLOOKUP($B17,Basic_Data!$E$2:$G$9,3,0)/VLOOKUP(G$13,Data_Entry!$C:$V,20,0),"") | H17: =IFERROR(VLOOKUP(H$13,Data_Entry!$C:$M,Data_Entry!$A5,0)/VLOOKUP($B17,Basic_Data!$E$2:$G$9,3,0)/VLOOKUP(H$13,Data_Entry!$C:$V,20,0),"") | I17: =IFERROR(VLOOKUP(I$13,Data_Entry!$C:$M,Data_Entry!$A5,0)/VLOOKUP($B17,Basic_Data!$E$2:$G$9,3,0)/VLOOKUP(I$13,Data_Entry!$C:$V,20,0),"") | J17: =IFERROR(VLOOKUP(J$13,Data_Entry!$C:$M,Data_Entry!$A5,0)/VLOOKUP($B17,Basic_Data!$E$2:$G$9,3,0)/VLOOKUP(J$13,Data_Entry!$C:$V,20,0),"") | ... AG17: =IFERROR(VLOOKUP(AG$13,Data_Entry!$C:$M,Data_Entry!$A5,0)/VLOOKUP($B17,Basic_Data!$E$2:$G$9,3,0)/VLOOKUP(AG$13,Data_Entry!$C:$V,20,0),"")
B18: Inv_5 | C18: =IFERROR(VLOOKUP(C$13,Data_Entry!$C:$M,Data_Entry!$A6,0)/VLOOKUP($B18,Basic_Data!$E$2:$G$9,3,0)/VLOOKUP(C$13,Data_Entry!$C:$V,20,0),"") -> 1.2417263 | D18: =IFERROR(VLOOKUP(D$13,Data_Entry!$C:$M,Data_Entry!$A6,0)/VLOOKUP($B18,Basic_Data!$E$2:$G$9,3,0)/VLOOKUP(D$13,Data_Entry!$C:$V,20,0),"") | E18: =IFERROR(VLOOKUP(E$13,Data_Entry!$C:$M,Data_Entry!$A6,0)/VLOOKUP($B18,Basic_Data!$E$2:$G$9,3,0)/VLOOKUP(E$13,Data_Entry!$C:$V,20,0),"") | F18: =IFERROR(VLOOKUP(F$13,Data_Entry!$C:$M,Data_Entry!$A6,0)/VLOOKUP($B18,Basic_Data!$E$2:$G$9,3,0)/VLOOKUP(F$13,Data_Entry!$C:$V,20,0),"") | G18: =IFERROR(VLOOKUP(G$13,Data_Entry!$C:$M,Data_Entry!$A6,0)/VLOOKUP($B18,Basic_Data!$E$2:$G$9,3,0)/VLOOKUP(G$13,Data_Entry!$C:$V,20,0),"") | H18: =IFERROR(VLOOKUP(H$13,Data_Entry!$C:$M,Data_Entry!$A6,0)/VLOOKUP($B18,Basic_Data!$E$2:$G$9,3,0)/VLOOKUP(H$13,Data_Entry!$C:$V,20,0),"") | I18: =IFERROR(VLOOKUP(I$13,Data_Entry!$C:$M,Data_Entry!$A6,0)/VLOOKUP($B18,Basic_Data!$E$2:$G$9,3,0)/VLOOKUP(I$13,Data_Entry!$C:$V,20,0),"") | J18: =IFERROR(VLOOKUP(J$13,Data_Entry!$C:$M,Data_Entry!$A6,0)/VLOOKUP($B18,Basic_Data!$E$2:$G$9,3,0)/VLOOKUP(J$13,Data_Entry!$C:$V,20,0),"") | ... AG18: =IFERROR(VLOOKUP(AG$13,Data_Entry!$C:$M,Data_Entry!$A6,0)/VLOOKUP($B18,Basic_Data!$E$2:$G$9,3,0)/VLOOKUP(AG$13,Data_Entry!$C:$V,20,0),"")
B19: Inv_6 | C19: =IFERROR(VLOOKUP(C$13,Data_Entry!$C:$M,Data_Entry!$A7,0)/VLOOKUP($B19,Basic_Data!$E$2:$G$9,3,0)/VLOOKUP(C$13,Data_Entry!$C:$V,20,0),"") -> 1.2431117 | D19: =IFERROR(VLOOKUP(D$13,Data_Entry!$C:$M,Data_Entry!$A7,0)/VLOOKUP($B19,Basic_Data!$E$2:$G$9,3,0)/VLOOKUP(D$13,Data_Entry!$C:$V,20,0),"") | E19: =IFERROR(VLOOKUP(E$13,Data_Entry!$C:$M,Data_Entry!$A7,0)/VLOOKUP($B19,Basic_Data!$E$2:$G$9,3,0)/VLOOKUP(E$13,Data_Entry!$C:$V,20,0),"") | F19: =IFERROR(VLOOKUP(F$13,Data_Entry!$C:$M,Data_Entry!$A7,0)/VLOOKUP($B19,Basic_Data!$E$2:$G$9,3,0)/VLOOKUP(F$13,Data_Entry!$C:$V,20,0),"") | G19: =IFERROR(VLOOKUP(G$13,Data_Entry!$C:$M,Data_Entry!$A7,0)/VLOOKUP($B19,Basic_Data!$E$2:$G$9,3,0)/VLOOKUP(G$13,Data_Entry!$C:$V,20,0),"") | H19: =IFERROR(VLOOKUP(H$13,Data_Entry!$C:$M,Data_Entry!$A7,0)/VLOOKUP($B19,Basic_Data!$E$2:$G$9,3,0)/VLOOKUP(H$13,Data_Entry!$C:$V,20,0),"") | I19: =IFERROR(VLOOKUP(I$13,Data_Entry!$C:$M,Data_Entry!$A7,0)/VLOOKUP($B19,Basic_Data!$E$2:$G$9,3,0)/VLOOKUP(I$13,Data_Entry!$C:$V,20,0),"") | J19: =IFERROR(VLOOKUP(J$13,Data_Entry!$C:$M,Data_Entry!$A7,0)/VLOOKUP($B19,Basic_Data!$E$2:$G$9,3,0)/VLOOKUP(J$13,Data_Entry!$C:$V,20,0),"") | ... AG19: =IFERROR(VLOOKUP(AG$13,Data_Entry!$C:$M,Data_Entry!$A7,0)/VLOOKUP($B19,Basic_Data!$E$2:$G$9,3,0)/VLOOKUP(AG$13,Data_Entry!$C:$V,20,0),"")
B20: Inv_7 | C20: =IFERROR(VLOOKUP(C$13,Data_Entry!$C:$M,Data_Entry!$A8,0)/VLOOKUP($B20,Basic_Data!$E$2:$G$9,3,0)/VLOOKUP(C$13,Data_Entry!$C:$V,20,0),"") -> 1.2430594 | D20: =IFERROR(VLOOKUP(D$13,Data_Entry!$C:$M,Data_Entry!$A8,0)/VLOOKUP($B20,Basic_Data!$E$2:$G$9,3,0)/VLOOKUP(D$13,Data_Entry!$C:$V,20,0),"") | E20: =IFERROR(VLOOKUP(E$13,Data_Entry!$C:$M,Data_Entry!$A8,0)/VLOOKUP($B20,Basic_Data!$E$2:$G$9,3,0)/VLOOKUP(E$13,Data_Entry!$C:$V,20,0),"") | F20: =IFERROR(VLOOKUP(F$13,Data_Entry!$C:$M,Data_Entry!$A8,0)/VLOOKUP($B20,Basic_Data!$E$2:$G$9,3,0)/VLOOKUP(F$13,Data_Entry!$C:$V,20,0),"") | G20: =IFERROR(VLOOKUP(G$13,Data_Entry!$C:$M,Data_Entry!$A8,0)/VLOOKUP($B20,Basic_Data!$E$2:$G$9,3,0)/VLOOKUP(G$13,Data_Entry!$C:$V,20,0),"") | H20: =IFERROR(VLOOKUP(H$13,Data_Entry!$C:$M,Data_Entry!$A8,0)/VLOOKUP($B20,Basic_Data!$E$2:$G$9,3,0)/VLOOKUP(H$13,Data_Entry!$C:$V,20,0),"") | I20: =IFERROR(VLOOKUP(I$13,Data_Entry!$C:$M,Data_Entry!$A8,0)/VLOOKUP($B20,Basic_Data!$E$2:$G$9,3,0)/VLOOKUP(I$13,Data_Entry!$C:$V,20,0),"") | J20: =IFERROR(VLOOKUP(J$13,Data_Entry!$C:$M,Data_Entry!$A8,0)/VLOOKUP($B20,Basic_Data!$E$2:$G$9,3,0)/VLOOKUP(J$13,Data_Entry!$C:$V,20,0),"") | ... AG20: =IFERROR(VLOOKUP(AG$13,Data_Entry!$C:$M,Data_Entry!$A8,0)/VLOOKUP($B20,Basic_Data!$E$2:$G$9,3,0)/VLOOKUP(AG$13,Data_Entry!$C:$V,20,0),"")
B21: Avg_PR% | C21: =AVERAGE(C14:C20) -> 1.2489898 | D21: =AVERAGE(D14:D20) -> #DIV/0! | E21: =AVERAGE(E14:E20) -> #DIV/0! | F21: =AVERAGE(F14:F20) -> #DIV/0! | G21: =AVERAGE(G14:G20) -> #DIV/0! | H21: =AVERAGE(H14:H20) -> #DIV/0! | I21: =AVERAGE(I14:I20) -> #DIV/0! | J21: =AVERAGE(J14:J20) -> #DIV/0! | ... AH21: =AVERAGE(AH14:AH20) -> #DIV/0!

Sheet Basic_Data
A2: Details_of_Plant | B2: Values | E2: Inverter_Name | F2: AC_Capacity_MW | G2: Connected_DC_MW | H2: No_Of_Module
A3: D.O.C(DD-MMM-YYY) | B3: 45745 | E3: Inv_1 | F3: 275 | G3: 335.72 | H3: =G3/0.545 -> 616 | I3: 2
A4: Plant_Name | B4: Devki Galol | E4: Inv_2 | F4: 275 | G4: 335.72 | H4: =G4/0.545 -> 616 | I4: 3
A5: Longitude_Of_Site | B5: 21.62 °N | E5: Inv_3 | F5: 275 | G5: 335.72 | H5: =G5/0.545 -> 616 | I5: 4
A6: Latitude_Of_Site | B6: 70.69 °E | E6: Inv_4 | F6: 275 | G6: 350.98 | H6: =G6/0.545 -> 644 | I6: 5
A7: DC_Capacity_(kWh) | B7: 2.411 | E7: Inv_5 | F7: 275 | G7: 350.98 | H7: =G7/0.545 -> 644 | I7: 6
A8: AC_Capacity_(kWh) | B8: 1.925 | E8: Inv_6 | F8: 275 | G8: 350.98 | H8: =G8/0.545 -> 644 | I8: 7
A9: Connected_DC_Capacity | B9: =SUM(G3:G94) -> 4822.16 | E9: Inv_7 | F9: 275 | G9: 350.98 | H9: =G9/0.545 -> 644 | I9: 8
A10: Multiplying_Factor_(MF) | B10: 3000 | E10: Total | F10: =SUM(F3:F9) -> 1925 | G10: =SUM(G3:G9) -> 2411.08 | H10: =SUM(H3:H9) -> 4424
A11: No._of_Power_Trafo. | B11: 1
A12: Power_Trafo._Make | B12: Gujrat_Trafo
A13: Inverter_Make | B13: Watt_power
A14: Inverter_Capacity | B14: 0.275
A15: No._of_Inverter | B15: 7
A16: Module_Make | B16: EMMVEE
A17: Module_Rating | B17: 545
A18: No._of_Strings/Table | B18: 158
A19: No._Of_Module_In_Table | B19: 28 for Bifacial
A20: Total_Module | B20: 4424
A21: Switch_Yard_Make_Vendors | B21: ABB
A22: Table_Configuration | B22: 2X28
A23: ABT Meter Make
A27: FY:Name | B27: From_FY | C27: To_FY
A28: 12-13 | B28: 41000 | C28: 41364 | D28: 365
A29: 13-14 | B29: 41365 | C29: 41729 | D29: 365
A30: 14-15 | B30: 41730 | C30: 42094 | D30: 365
A31: 15-16 | B31: 42095 | C31: 42460 | D31: 366
A32: 16-17 | B32: 42461 | C32: 42825 | D32: 365
A33: 17-18 | B33: 42826 | C33: 43190 | D33: 365
A34: 18-19 | B34: 43191 | C34: 43555 | D34: 365
A35: 19-20 | B35: 43556 | C35: 43921 | D35: 366
A36: 20-21 | B36: 43922 | C36: 44286 | D36: 365
A37: 21-22 | B37: 44287 | C37: 44651 | D37: 365
A38: 22-23 | B38: 44652 | C38: 45016 | D38: 365
A39: 23-24 | B39: 45017 | C39: 45382 | D39: 366
... A48: 32-33 | B48: 48305 | C48: 48669 | D48: 365

Sheet Plant_Down_Time Details
A1: Plant_Down_Time Details
A2: Month | B2: Date | C2: Inverter_No | D2: String_No | E2: Down_Time_Start | F2: Down_Time_Stop | G2: Total_Down_Time | H2: Affected DC Capacity (in KW) | I2: Insolation*Capacity | J2: Generation Loss | K2: Revenue | L2: Component Name | M2: Fault Description | N2: Reason_Of_Down | O2: Purposed Action Plan | P2: Material Consumption Description | Q2: UOM | R2: Quantity | S2: Corrective_Action_Taken_By_Site_Team
A3: 45747 | B3: 45747
A4: 45748 | B4: 45748
A5: 45749 | B5: 45749
A6: 45750 | B6: 45750
A7: 45751 | B7: 45751
A8: 45752 | B8: 45752
A9: 45753 | B9: 45753
A10: 45754 | B10: 45754
A11: 45755 | B11: 45755
A12: 45756 | B12: 45756
A13: 45757 | B13: 45757
A14: 45758 | B14: 45758
... A30: 45774 | B30: 45774
A31: 45775 | B31: 45775 | C31: All inverter | D31: All string | E31: 0.45486111 | F31: 0.46527778 | G31: 0.010416667 | H31: 2411.08 | N31: plant manully stopped our solar site for modam replesement work by PGVCL team
A32: 45775 | B32: 45775 | C32: All inverter | D32: All string | E32: 0.52083333 | F32: 0.53819444 | G32: 0.017361111 | H32: 2411.08 | N32: plant manully stopped 66 KV GETCO S/S site for modam replesement work by PGVCL team
A33: 45776 | B33: 45776
A34: 45777 | B34: 45777
A35: 45778 | B35: 45778
A36: 45779 | B36: 45779
A37: 45780 | B37: 45780
A38: 45781 | B38: 45781
A39: 45782 | B39: 45782
A40: 45783 | B40: 45783
A41: 45784 | B41: 45784
A42: 45785 | B42: 45785
A43: 45786 | B43: 45786
A44: 45787 | B44: 45787
... A93: 45836 | B93: 45836
A94: 45837 | B94: 45837 | C94: Inverter_No 5 | D94: 22 | E94: 0.28125 | F94: 0.79166667 | G94: =F94-E94 -> 0.51041667 | H94: 330 | L94: inverter 5 | M94: short circuit pv arry and the ground | N94: arry cable damage | O94: removed fullty arry | S94: check and find faullty arry
A95: 45838 | B95: 45838 | C95: Inverter_No 5 | D95: 23 | E95: 0.28125 | F95: 0.56944444 | G95: =F95-E95 -> 0.28819444 | H95: 330 | L95: inverter 5 | M95: short circuit pv arry and the ground | N95: arry cable damage | O95: removed fullty arry | S95: removed 2 nos faultty arry and inverter start
A96: 45839 | B96: 45839
A97: 45840 | B97: 45840
A98: 45841 | B98: 45841
A99: 45842 | B99: 45842
A100: 45843 | B100: 45843
A101: 45844 | B101: 45844
A102: 45845 | B102: 45845
A103: 45846 | B103: 45846
A104: 45847 | B104: 45847
A105: 45848 | B105: 45848
A106: 45849 | B106: 45849
A107: 45850 | B107: 45850
... A118: 45861 | B118: 45861
A119: 45862 | B119: 45862 | C119: All inverter | D119: All string | E119: 0.28472222 | F119: 0.32291667 | G119: =F119-E119 -> 0.038194444 | H119: 2411 | L119: conductor | M119: Earth fault | N119: crossing line conductor fall down
A120: 45863 | B120: 45863
A121: 45864 | B121: 45864
A122: 45865 | B122: 45865
A123: 45866 | B123: 45866
A124: 45867 | B124: 45867
A125: 45868 | B125: 45868
A126: 45869 | B126: 45869
A127: 45870 | B127: 45870
A128: 45871 | B128: 45871
A129: 45872 | B129: 45872
A130: 45873 | B130: 45873
A131: 45874 | B131: 45874
... A133: 45876 | B133: 45876
A134: 45877 | B134: 45877 | C134: All inverter | D134: All string | E134: 0.38541667 | F134: 0.42708333 | G134: =F134-E134 -> 0.041666667 | H134: 2411 | L134: DO WIRE | M134: DO WIRE BURINING
A135: 45878 | B135: 45878
A136: 45879 | B136: 45879
A137: 45880 | B137: 45880
A138: 45881 | B138: 45881
A139: 45882 | B139: 45882
A140: 45883 | B140: 45883
A141: 45884 | B141: 45884 | C141: All inverter | D141: All string | E141: 0.57291667 | F141: 0.63888889 | G141: =F141-E141 -> 0.065972222 | H141: 2411 | L141: DO WIRE FUSE | M141: DO Wire burining | S141: Replase DO wire by site team
A142: 45885 | B142: 45885
A143: 45886 | B143: 45886
A144: 45887 | B144: 45887
A145: 45888 | B145: 45888
A146: 45889 | B146: 45889
A147: 45890 | B147: 45890
A148: 45891 | B148: 45891
A149: 45892 | B149: 45892
A150: 45893 | B150: 45893
A151: 45894 | B151: 45894
A152: 45895 | B152: 45895
A153: 45896 | B153: 45896
A154: 45897 | B154: 45897 | C154: All inverter | D154: All string | E154: 0.55555556 | F154: 0.57916667 | G154: =F154-E154 -> 0.023611111 | H154: 2411 | L154: DO WIRE | M154: Do wire burning
A155: 45898 | B155: 45898
A156: 45899 | B156: 45899
A157: 45900 | B157: 45900
A158: 45901 | B158: 45901
A159: 45902 | B159: 45902
A160: 45903 | B160: 45903
A161: 45904 | B161: 45904
A162: 45905 | B162: 45905
A163: 45906 | B163: 45906
A164: 45907 | B164: 45907
A165: 45908 | B165: 45908
A166: 45909 | B166: 45909
A167: 45910 | B167: 45910 | C167: All inverter | D167: All string | E167: 0.50625 | F167: 0.53125 | G167: =F167-E167 -> 0.025 | H167: 2411 | L167: DO WIRE | M167: Do wire burning
A168: 45911 | B168: 45911
A169: 45912 | B169: 45912
A170: 45913 | B170: 45913
A171: 45914 | B171: 45914
A172: 45915 | B172: 45915
A173: 45916 | B173: 45916
A174: 45917 | B174: 45917
...

Sheet Plant_Grid_Down_Time_Details
A1: Plant_Grid_Down_Time_Details
A3: Month | B3: Date | C3: Transformer_No. (T-1) | D3: Down_Time_Start | E3: Down_Time_Stop | F3: Total_Down_Time | G3: Comm. Insolation of the Period | H3: Module Temp of the Period | I3: Affected DC Capacity (in KW) | J3: Insolation*Capacity | K3: Generation Loss | L3: Revenue | M3: Remark
A4: april | B4: 17/04/2025 | C4: 1 | D4: 0.50347222 | E4: 0.79166667 | F4: 0.28819444 | I4: 2411.08
A5: april | B5: 18/04/2025 | C5: 1 | D5: 0.25 | E5: 0.79166667 | F5: 0.5 | I5: 2411.08
A6: april | B6: 19/04/2025 | C6: 1 | D6: 0.25 | E6: 0.79166667 | F6: 0.5 | I6: 2411.08
A7: may | B7: 45813 | C7: 1 | D7: 0.63541667 | E7: 0.78472222 | F7: =E7-D7 -> 0.14930556 | I7: 2411.08
A8: MAY | B8: 23/05/2025 | C8: 1 | D8: 0.27083333 | E8: 0.56875 | F8: =E8-D8 -> 0.29791667 | I8: 2411.08
A9: jun | B9: 45694 | C9: 1 | D9: 0.52083333 | E9: 0.57291667 | F9: =E9-D9 -> 0.052083333 | I9: 2411.08
B10: 45862 | C10: 1 | D10: 0.66666667 | E10: 0.78125 | F10: =E10-D10 -> 0.11458333 | I10: 2411.08 | M10: line manully stopped by pgvcl team for line joint work
B11: 45875 | C11: 1 | D11: 0.71388889 | E11: 0.72777778 | F11: =E11-D11 -> 0.013888889 | I11: 2411.08 | M11: grid drop form s/s site
A12: 45926 | B12: 45926 | C12: 1 | D12: 0.30208333 | E12: 0.59375 | F12: =E12-D12 -> 0.29166667 | I12: 2411.08 | M12: getco s/s site outage
B13: 14/01/2026 | C13: 1 | D13: 0.64930556 | E13: 0.76527778 | F13: =E13-D13 -> 0.11597222 | I13: 2411.08 | M13: line crrosing work from getco team
A14: 19/01/2026 | B14: 19/01/2026 | C14: 1 | D14: 0.55138889 | E14: 0.56041667 | F14: =E14-D14 -> 0.0090277778 | I14: 2411.08 | M14: over voltage
B15: 20/01/2026 | C15: 1 | D15: 0.51736111 | E15: 0.55902778 | F15: =E15-D15 -> 0.041666667 | I15: 2411.08 | M15: DO WIRE BURENED
A16: Feb | B16: 27/02/2026 | C16: 1 | D16: 0.51388889 | E16: 0.65972222 | F16: 0.14583333 | I16: 2411.08 | M16: S/s site DO Wire Burened
A17: MAR | B17: 23/03/2026 | C17: 1 | D17: 0.6375 | E17: 0.70694444 | F17: 0.069444444 | I17: 2411.08 | M17: S/s site y phase jumper Burened
A18: May | B18: 17/05/2026 | C18: 1 | D18: 0.57152778 | E18: 0.61319444 | F18: 0.041666667 | I18: 2411.08 | M18: S/s site DO Wire Burened
A19: May | B19: 22/05/2026 | C19: 1 | D19: 0.29166667 | E19: 0.6875 | F19: 0.39583333 | I19: 2411.08 | M19: getco s/s site outage

Sheet WMS
A1: Months | B1: Date | C1: GHI | D1: GTI | E1: Module_Temp | F1: Amb_Temp | G1: Derect_Irr | H1: Diffused_Irr | I1: Wind_Speed | J1: Wind_derection | K1: Rain Gauge
A2: 45747 | B2: 45747
A3: 45748 | B3: 45748
A4: 45749 | B4: 45749
A5: 45750 | B5: 45750
A6: 45751 | B6: 45751
A7: 45752 | B7: 45752
A8: 45753 | B8: 45753
A9: 45754 | B9: 45754
A10: 45755 | B10: 45755
A11: 45756 | B11: 45756
A12: 45757 | B12: 45757 | C12: 4.9 | D12: 4.9
A13: 45758 | B13: 45758 | D13: 4.92
A14: 45759 | B14: 45759 | D14: 5.08
A15: 45760 | B15: 45760
A16: 45761 | B16: 45761 | D16: 5.14
A17: 45762 | B17: 45762 | D17: 5.13
A18: 45763 | B18: 45763 | D18: 5.04 | F18: 34.2
A19: 45764 | B19: 45764 | F19: 0
A20: 45765 | B20: 45765 | F20: 0
A21: 45766 | B21: 45766 | F21: 0
A22: 45767 | B22: 45767 | D22: 5.33 | F22: 33.9
A23: 45768 | B23: 45768 | D23: 5.25 | F23: 35.25
A24: 45769 | B24: 45769 | D24: 5.28 | F24: 37
A25: 45770 | B25: 45770 | D25: 5.16 | F25: 37.04
A26: 45771 | B26: 45771 | D26: 5.24 | F26: 35.34
A27: 45772 | B27: 45772 | D27: 5.36 | F27: 34.27
A28: 45773 | B28: 45773 | D28: 5.39 | F28: 34.96
A29: 45774 | B29: 45774 | D29: 5.39 | F29: 35.68
A30: 45775 | B30: 45775 | D30: 5.28 | F30: 36.36
A31: 45776 | B31: 45776 | D31: 5.55 | F31: 37.01
A32: 45777 | B32: 45777 | D32: 5.47 | F32: 35.9
A33: 45778 | B33: 45778 | D33: 5.52 | F33: 35.78
... A142: 45887 | B142: 45887 | D142: 3.27 | F142: 30
A143: 45888 | B143: 45888
A144: 45889 | B144: 45889
A145: 45890 | B145: 45890
A146: 45891 | B146: 45891
A147: 45892 | B147: 45892
A148: 45893 | B148: 45893
A149: 45894 | B149: 45894
A150: 45895 | B150: 45895
A151: 45896 | B151: 45896
A152: 45897 | B152: 45897
A153: 45898 | B153: 45898
A154: 45899 | B154: 45899
... A175: 45920 | B175: 45920
A176: 45921 | B176: 45921 | D176: 3.75 | F176: 29.65
A177: 45922 | B177: 45922 | D177: 3.24 | F177: 28.38
A178: 45923 | B178: 45923 | D178: 3.71 | F178: 29.73
A179: 45924 | B179: 45924 | D179: 2.42 | F179: 29.62
A180: 45925 | B180: 45925 | D180: 4.09 | F180: 30.91
A181: 45926 | B181: 45926 | D181: 0.37 | F181: 30.3
A182: 45927 | B182: 45927 | D182: 4.13 | F182: 31.4
A183: 45928 | B183: 45928 | D183: 1.72 | F183: 27.54
A184: 45929 | B184: 45929 | D184: 1.45 | F184: 26.65
A185: 45930 | B185: 45930 | D185: 1.22 | F185: 23.64
A186: 45931 | B186: 45931 | D186: 1.61 | F186: 25.44
A187: 45932 | B187: 45932 | D187: 2.03 | F187: 26.79
... A240: 45985 | B240: 45985 | D240: 4.11 | F240: 27.45
A241: 45986 | B241: 45986 | C241: 3.9 | D241: 3.9 | F241: 27.07
A242: 45987 | B242: 45987 | C242: 3.7 | D242: 3.7 | F242: 27.04
A243: 45988 | B243: 45988 | D243: 3.42 | F243: 28.62
A244: 45989 | B244: 45989 | D244: 3.13 | F244: 28.4
A245: 45990 | B245: 45990 | D245: 3.34 | F245: 27.37
A246: 45991 | B246: 45991 | D246: 3.55 | F246: 27.29
A247: 45992 | B247: 45992 | D247: 3.81 | F247: 26.7
A248: 45993 | B248: 45993 | D248: 3.5 | F248: 26.6
A249: 45994 | B249: 45994 | D249: 3.79 | F249: 25.4
A250: 45995 | B250: 45995 | D250: 3.65 | F250: 25.04
A251: 45996 | B251: 45996 | D251: 3.71 | F251: 26.35
A252: 45997 | B252: 45997 | D252: 3.46 | F252: 25.53
A253: 45998 | B253: 45998 | D253: 3.81 | F253: 25.42
A254: 45999 | B254: 45999 | D254: 3.81 | F254: 26.43
... A262: 46007 | B262: 46007 | D262: 3.86 | F262: 24.16
A263: 46008 | B263: 46008 | D263: 3.62
A264: 46009 | B264: 46009 | D264: 3.99
A265: 46010 | B265: 46010 | D265: 3.65
A266: 46011 | B266: 46011 | D266: 4.1
A267: 46012 | B267: 46012 | D267: 3.36
A268: 46013 | B268: 46013 | D268: 3.89
A269: 46014 | B269: 46014 | D269: 3.85
A270: 46015 | B270: 46015 | D270: 3.93 | F270: 26.17
A271: 46016 | B271: 46016 | D271: 3.87 | F271: 26.07
A272: 46017 | B272: 46017 | D272: 3.74 | F272: 25.41
A273: 46018 | B273: 46018 | D273: 3.62 | F273: 25.19
A274: 46019 | B274: 46019 | D274: 3.62 | F274: 27.07
A275: 46020 | B275: 46020 | D275: 3.6 | F275: 25.64
A276: 46021 | B276: 46021 | D276: 3.5 | F276: 24.6
A277: 46022 | B277: 46022 | D277: 3.1 | F277: 24.92
A278: 46023 | B278: 46023 | D278: 3.58 | F278: 24.46
A279: 46024 | B279: 46024 | D279: 3.9 | F279: 23.51
A280: 46025 | B280: 46025 | D280: 2.91 | F280: 22.35
A281: 46026 | B281: 46026 | D281: 4.15 | F281: 23.9
... A436: 46181 | B436: 46181 | D436: 4.36 | F436: 33.41

Sheet Module_Cleaning
C2: Water Consumption
A3: Months | B3: Date | C3: Tanker Qty | D3: Consumption (Capacity(Ltr)* Tanker) | E3: TDS (PPM) | F3: Cycle No. | G3: Invt. No | I3: Module | J3: Cleaned | K3: Before Cleaning PR% | L3: After Cleaning PR% | M3: Balance | N3: Remarks
A4: 45747 | B4: 45747
A5: 45748 | B5: 45748
A6: 45749 | B6: 45749
A7: 45750 | B7: 45750
A8: 45751 | B8: 45751
A9: 45752 | B9: 45752
A10: 45753 | B10: 45753
A11: 45754 | B11: 45754
A12: 45755 | B12: 45755
A13: 45756 | B13: 45756
A14: 45757 | B14: 45757 | C14: 2 | D14: 2000 | F14: 1 | G14: Inv_3 | H14: =IFERROR(VLOOKUP(G14,Basic_Data!$E$2:$I$9,5,0),"") -> 4 | I14: =IFERROR(VLOOKUP($G14,Basic_Data!$E$2:$H$10,4,0),"") -> 616 | J14: 616 | K14: =IFERROR(VLOOKUP($B14-1,Inverter_PR!$B:$I,Module_Cleaning!H14,0),"") -> 1.112934 | L14: =IFERROR(VLOOKUP($B14+1,Inverter_PR!$B:$I,Module_Cleaning!H14,0),"") -> 1.1906397 | M14: =IFERROR(I14-J14,"") -> 0
A16: 45759 | B16: 45759 | H16: =IFERROR(VLOOKUP(G16,Basic_Data!$E$2:$I$9,5,0),"") | I16: =IFERROR(VLOOKUP($G16,Basic_Data!$E$2:$H$10,4,0),"") | K16: =IFERROR(VLOOKUP($B16-1,Inverter_PR!$B:$I,Module_Cleaning!H16,0),"") | L16: =IFERROR(VLOOKUP($B16+1,Inverter_PR!$B:$I,Module_Cleaning!H16,0),"") | M16: =IFERROR(I16-J16,"")
A17: 45760 | B17: 45760 | H17: =IFERROR(VLOOKUP(G17,Basic_Data!$E$2:$I$9,5,0),"") | I17: =IFERROR(VLOOKUP($G17,Basic_Data!$E$2:$H$10,4,0),"") | K17: =IFERROR(VLOOKUP($B17-1,Inverter_PR!$B:$I,Module_Cleaning!H17,0),"") | L17: =IFERROR(VLOOKUP($B17+1,Inverter_PR!$B:$I,Module_Cleaning!H17,0),"") | M17: =IFERROR(I17-J17,"")
A18: 45761 | B18: 45761 | F18: 1 | G18: Inv_6 | H18: =IFERROR(VLOOKUP(G18,Basic_Data!$E$2:$I$9,5,0),"") -> 7 | I18: =IFERROR(VLOOKUP($G18,Basic_Data!$E$2:$H$10,4,0),"") -> 644 | J18: 644 | K18: =IFERROR(VLOOKUP($B18-1,Inverter_PR!$B:$I,Module_Cleaning!H18,0),"") -> 1.1309545 | L18: =IFERROR(VLOOKUP($B18+1,Inverter_PR!$B:$I,Module_Cleaning!H18,0),"") -> 1.1927005 | M18: =IFERROR(I18-J18,"") -> 0 | N18: robat cleanig
F19: 1 | G19: Inv_7 | I19: =IFERROR(VLOOKUP($G19,Basic_Data!$E$2:$H$10,4,0),"") -> 644 | J19: 644 | K19: =IFERROR(VLOOKUP($B19-1,Inverter_PR!$B:$I,Module_Cleaning!H19,0),"") | L19: =IFERROR(VLOOKUP($B19+1,Inverter_PR!$B:$I,Module_Cleaning!H19,0),"") | M19: =IFERROR(I19-J19,"") -> 0 | N19: robat cleanig
A20: 45762 | B20: 45762 | F20: 1 | G20: Inv_1 | H20: =IFERROR(VLOOKUP(G20,Basic_Data!$E$2:$I$9,5,0),"") -> 2 | I20: =IFERROR(VLOOKUP($G20,Basic_Data!$E$2:$H$10,4,0),"") -> 616 | J20: 616 | K20: =IFERROR(VLOOKUP($B20-1,Inverter_PR!$B:$I,Module_Cleaning!H20,0),"") -> 1.2185727 | L20: =IFERROR(VLOOKUP($B20+1,Inverter_PR!$B:$I,Module_Cleaning!H20,0),"") -> 1.2089156 | M20: =IFERROR(I20-J20,"") -> 0
G21: Inv_2 | I21: =IFERROR(VLOOKUP($G21,Basic_Data!$E$2:$H$10,4,0),"") -> 616 | J21: 616 | K21: =IFERROR(VLOOKUP($B21-1,Inverter_PR!$B:$I,Module_Cleaning!H21,0),"")
G22: Inv_3 | I22: =IFERROR(VLOOKUP($G22,Basic_Data!$E$2:$H$10,4,0),"") -> 616 | J22: 616
G23: Inv_4 | I23: =IFERROR(VLOOKUP($G23,Basic_Data!$E$2:$H$10,4,0),"") -> 644 | J23: 644
G24: Inv_5 | I24: =IFERROR(VLOOKUP($G24,Basic_Data!$E$2:$H$10,4,0),"") -> 644 | J24: 644
G25: Inv_6 | I25: =IFERROR(VLOOKUP($G25,Basic_Data!$E$2:$H$10,4,0),"") -> 644 | J25: 644
G26: Inv_7 | I26: =IFERROR(VLOOKUP($G26,Basic_Data!$E$2:$H$10,4,0),"") -> 644 | J26: 644
A27: 45763 | B27: 45763 | C27: 2 | D27: 3000 | F27: 2 | G27: Inv_1 | H27: =IFERROR(VLOOKUP(G27,Basic_Data!$E$2:$I$9,5,0),"") -> 2 | I27: =IFERROR(VLOOKUP($G27,Basic_Data!$E$2:$H$10,4,0),"") -> 616 | J27: 616 | K27: =IFERROR(VLOOKUP($B27-1,Inverter_PR!$B:$I,Module_Cleaning!H27,0),"") -> 1.2106359 | L27: =IFERROR(VLOOKUP($B27+1,Inverter_PR!$B:$I,Module_Cleaning!H27,0),"") | M27: =IFERROR(I27-J27,"") -> 0
G28: Inv_2 | I28: =IFERROR(VLOOKUP($G28,Basic_Data!$E$2:$H$10,4,0),"") -> 616 | J28: 616
G29: Inv_3 | I29: =IFERROR(VLOOKUP($G29,Basic_Data!$E$2:$H$10,4,0),"") -> 616 | J29: 616
A30: 45764 | B30: 45764 | C30: 0 | D30: 0 | E30: 0 | F30: 0 | I30: 0 | J30: 0 | K30: =IFERROR(VLOOKUP($B30-1,Inverter_PR!$B:$I,Module_Cleaning!H30,0),"") | L30: =IFERROR(VLOOKUP($B30+1,Inverter_PR!$B:$I,Module_Cleaning!H30,0),"") | M30: =IFERROR(I30-J30,"") -> 0 | N30: N0 cleaning
A31: 45765 | B31: 45765 | C31: 0 | D31: 0 | E31: 0 | F31: 0 | I31: 0 | J31: 0 | K31: =IFERROR(VLOOKUP($B31-1,Inverter_PR!$B:$I,Module_Cleaning!H31,0),"") | L31: =IFERROR(VLOOKUP($B31+1,Inverter_PR!$B:$I,Module_Cleaning!H31,0),"") | M31: =IFERROR(I31-J31,"") -> 0 | N31: N0 cleaning
A32: 45766 | B32: 45766 | C32: 0 | D32: 0 | E32: 0 | F32: 0 | I32: 0 | J32: 0 | K32: =IFERROR(VLOOKUP($B32-1,Inverter_PR!$B:$I,Module_Cleaning!H32,0),"") | L32: =IFERROR(VLOOKUP($B32+1,Inverter_PR!$B:$I,Module_Cleaning!H32,0),"") | M32: =IFERROR(I32-J32,"") -> 0 | N32: N0 cleaning
A33: 45767 | B33: 45767 | C33: 0 | D33: 0 | E33: 0 | F33: 0 | I33: 0 | J33: 0 | K33: =IFERROR(VLOOKUP($B33-1,Inverter_PR!$B:$I,Module_Cleaning!H33,0),"") | L33: =IFERROR(VLOOKUP($B33+1,Inverter_PR!$B:$I,Module_Cleaning!H33,0),"") | M33: =IFERROR(I33-J33,"") -> 0 | N33: N0 cleaning
A34: 45768 | B34: 45768 | C34: 0 | D34: 0 | E34: 0 | F34: 0 | I34: 0 | J34: 0 | K34: =IFERROR(VLOOKUP($B34-1,Inverter_PR!$B:$I,Module_Cleaning!H34,0),"") | L34: =IFERROR(VLOOKUP($B34+1,Inverter_PR!$B:$I,Module_Cleaning!H34,0),"") | M34: =IFERROR(I34-J34,"") -> 0 | N34: N0 cleaning
A35: 45769 | B35: 45769 | F35: 3 | G35: Inv_1 | I35: 616 | J35: 616 | M35: =IFERROR(I35-J35,"") -> 0 | N35: robat cleanig
F36: 3 | G36: Inv_2 | I36: 616 | J36: 616 | M36: =IFERROR(I36-J36,"") -> 0 | N36: robat cleanig
F37: 3 | G37: Inv_3 | I37: 616 | J37: 616 | M37: =IFERROR(I37-J37,"") -> 0 | N37: robat cleanig
A39: 45770 | B39: 45770 | F39: 3 | G39: Inv_4 | H39: =IFERROR(VLOOKUP(G39,Basic_Data!$E$2:$I$9,5,0),"") -> 5 | I39: =IFERROR(VLOOKUP($G39,Basic_Data!$E$2:$H$10,4,0),"") -> 644 | J39: 644 | K39: =IFERROR(VLOOKUP($B39-1,Inverter_PR!$B:$I,Module_Cleaning!H39,0),"") -> 1.1815941 | L39: =IFERROR(VLOOKUP($B39+1,Inverter_PR!$B:$I,Module_Cleaning!H39,0),"") -> 1.1845132 | M39: =IFERROR(I39-J39,"") -> 0 | N39: robat cleanig
F40: 3 | G40: Inv_5 | I40: 644 | J40: 644 | M40: =IFERROR(I40-J40,"") -> 0 | N40: robat cleanig
F41: 3 | G41: Inv_6 | I41: 644 | J41: 644 | M41: =IFERROR(I41-J41,"") -> 0 | N41: robat cleanig
A42: 45771 | B42: 45771 | F42: 3 | G42: Inv_7 | H42: =IFERROR(VLOOKUP(G42,Basic_Data!$E$2:$I$9,5,0),"") -> 8 | I42: =IFERROR(VLOOKUP($G42,Basic_Data!$E$2:$H$10,4,0),"") -> 644 | J42: 644 | K42: =IFERROR(VLOOKUP($B42-1,Inverter_PR!$B:$I,Module_Cleaning!H42,0),"") -> 1.1504278 | L42: =IFERROR(VLOOKUP($B42+1,Inverter_PR!$B:$I,Module_Cleaning!H42,0),"") -> 1.1770614 | M42: =IFERROR(I42-J42,"") -> 0 | N42: robat cleanig
A43: 45772 | B43: 45772 | C43: 0 | D43: 0 | E43: 0 | F43: 0 | H43: =IFERROR(VLOOKUP(G43,Basic_Data!$E$2:$I$9,5,0),"") | I43: 0 | J43: 0 | K43: =IFERROR(VLOOKUP($B43-1,Inverter_PR!$B:$I,Module_Cleaning!H43,0),"") | L43: =IFERROR(VLOOKUP($B43+1,Inverter_PR!$B:$I,Module_Cleaning!H43,0),"") | M43: =IFERROR(I43-J43,"") -> 0 | N43: N0 cleaning
A44: 45773 | B44: 45773 | C44: 0 | D44: 0 | E44: 0 | F44: 0 | H44: =IFERROR(VLOOKUP(G44,Basic_Data!$E$2:$I$9,5,0),"") | I44: 0 | J44: 0 | K44: =IFERROR(VLOOKUP($B44-1,Inverter_PR!$B:$I,Module_Cleaning!H44,0),"") | L44: =IFERROR(VLOOKUP($B44+1,Inverter_PR!$B:$I,Module_Cleaning!H44,0),"") | M44: =IFERROR(I44-J44,"") -> 0 | N44: N0 cleaning
A45: 45774 | B45: 45774 | C45: 0 | D45: 0 | E45: 0 | F45: 0 | H45: =IFERROR(VLOOKUP(G45,Basic_Data!$E$2:$I$9,5,0),"") | I45: 0 | J45: 0 | K45: =IFERROR(VLOOKUP($B45-1,Inverter_PR!$B:$I,Module_Cleaning!H45,0),"") | L45: =IFERROR(VLOOKUP($B45+1,Inverter_PR!$B:$I,Module_Cleaning!H45,0),"") | M45: =IFERROR(I45-J45,"") -> 0 | N45: N0 cleaning
A46: 45775 | B46: 45775 | F46: 4 | G46: Inv_1 | H46: =IFERROR(VLOOKUP(G46,Basic_Data!$E$2:$I$9,5,0),"") -> 2 | I46: =IFERROR(VLOOKUP($G46,Basic_Data!$E$2:$H$10,4,0),"") -> 616 | J46: 616 | K46: =IFERROR(VLOOKUP($B46-1,Inverter_PR!$B:$I,Module_Cleaning!H46,0),"") -> 1.1384167 | L46: =IFERROR(VLOOKUP($B46+1,Inverter_PR!$B:$I,Module_Cleaning!H46,0),"") -> 1.1386795 | M46: =IFERROR(I46-J46,"") -> 0 | N46: robat cleanig
A47: 45775 | B47: 45775 | F47: 4 | G47: Inv_2 | I47: 616 | J47: 616 | N47: robat cleanig
A48: 45776 | B48: 45776 | F48: 4 | G48: Inv_3 | H48: =IFERROR(VLOOKUP(G48,Basic_Data!$E$2:$I$9,5,0),"") -> 4 | I48: =IFERROR(VLOOKUP($G48,Basic_Data!$E$2:$H$10,4,0),"") -> 616 | J48: 616 | K48: =IFERROR(VLOOKUP($B48-1,Inverter_PR!$B:$I,Module_Cleaning!H48,0),"") -> 1.0072201 | L48: =IFERROR(VLOOKUP($B48+1,Inverter_PR!$B:$I,Module_Cleaning!H48,0),"") -> 1.128013 | M48: =IFERROR(I48-J48,"") -> 0 | N48: robat cleanig
F49: 4 | G49: Inv_4 | I49: 644 | J49: 644 | N49: robat cleanig
A50: 45777 | B50: 45777 | F50: 4 | G50: Inv_5 | H50: =IFERROR(VLOOKUP(G50,Basic_Data!$E$2:$I$9,5,0),"") -> 6 | I50: =IFERROR(VLOOKUP($G50,Basic_Data!$E$2:$H$10,4,0),"") -> 644 | J50: 644 | K50: =IFERROR(VLOOKUP($B50-1,Inverter_PR!$B:$I,Module_Cleaning!H50,0),"") -> 1.1067184 | L50: =IFERROR(VLOOKUP($B50+1,Inverter_PR!$B:$I,Module_Cleaning!H50,0),"") -> 1.112821 | M50: =IFERROR(I50-J50,"") -> 0 | N50: robat cleanig
F51: 4 | G51: Inv_6 | I51: =IFERROR(VLOOKUP($G51,Basic_Data!$E$2:$H$10,4,0),"") -> 644 | J51: 644 | N51: robat cleanig
F52: 4 | G52: Inv_7 | I52: =IFERROR(VLOOKUP($G52,Basic_Data!$E$2:$H$10,4,0),"") -> 644 | J52: 644 | N52: robat cleanig
A53: 45778 | B53: 45778 | C53: 0 | D53: 0 | E53: 0 | F53: 0 | H53: =IFERROR(VLOOKUP(G53,Basic_Data!$E$2:$I$9,5,0),"") | I53: 0 | J53: 0 | K53: =IFERROR(VLOOKUP($B53-1,Inverter_PR!$B:$I,Module_Cleaning!H53,0),"") | L53: =IFERROR(VLOOKUP($B53+1,Inverter_PR!$B:$I,Module_Cleaning!H53,0),"") | M53: =IFERROR(I53-J53,"") -> 0 | N53: N0 cleaning
A54: 45779 | B54: 45779 | C54: 0 | D54: 0 | E54: 0 | F54: 0 | H54: =IFERROR(VLOOKUP(G54,Basic_Data!$E$2:$I$9,5,0),"") | I54: 0 | J54: 0 | K54: =IFERROR(VLOOKUP($B54-1,Inverter_PR!$B:$I,Module_Cleaning!H54,0),"") | L54: =IFERROR(VLOOKUP($B54+1,Inverter_PR!$B:$I,Module_Cleaning!H54,0),"") | M54: =IFERROR(I54-J54,"") -> 0 | N54: N0 cleaning
A55: 45780 | B55: 45780 | C55: 0 | D55: 0 | E55: 0 | F55: 0 | H55: =IFERROR(VLOOKUP(G55,Basic_Data!$E$2:$I$9,5,0),"") | I55: 0 | J55: 0 | K55: =IFERROR(VLOOKUP($B55-1,Inverter_PR!$B:$I,Module_Cleaning!H55,0),"") | L55: =IFERROR(VLOOKUP($B55+1,Inverter_PR!$B:$I,Module_Cleaning!H55,0),"") | M55: =IFERROR(I55-J55,"") -> 0 | N55: N0 cleaning
A56: 45781 | B56: 45781 | C56: 0 | D56: 0 | E56: 0 | F56: 0 | H56: =IFERROR(VLOOKUP(G56,Basic_Data!$E$2:$I$9,5,0),"") | I56: 0 | J56: 0 | L56: =IFERROR(VLOOKUP($B56+1,Inverter_PR!$B:$I,Module_Cleaning!H56,0),"") | M56: =IFERROR(I56-J56,"") -> 0 | N56: N0 cleaning
A57: 45782 | B57: 45782 | C57: 0 | D57: 0 | E57: 0 | F57: 0 | H57: =IFERROR(VLOOKUP(G57,Basic_Data!$E$2:$I$9,5,0),"") | I57: 0 | J57: 0 | K57: =IFERROR(VLOOKUP($B57-1,Inverter_PR!$B:$I,Module_Cleaning!H57,0),"") | L57: =IFERROR(VLOOKUP($B57+1,Inverter_PR!$B:$I,Module_Cleaning!H57,0),"") | M57: =IFERROR(I57-J57,"") -> 0 | N57: N0 cleaning
A58: 45783 | B58: 45783 | C58: 0 | D58: 0 | E58: 0 | F58: 0 | H58: =IFERROR(VLOOKUP(G58,Basic_Data!$E$2:$I$9,5,0),"") | I58: 0 | J58: 0 | K58: =IFERROR(VLOOKUP($B58-1,Inverter_PR!$B:$I,Module_Cleaning!H58,0),"") | L58: =IFERROR(VLOOKUP($B58+1,Inverter_PR!$B:$I,Module_Cleaning!H58,0),"") | M58: =IFERROR(I58-J58,"") -> 0 | N58: N0 cleaning
A59: 45784 | B59: 45784 | H59: =IFERROR(VLOOKUP(G59,Basic_Data!$E$2:$I$9,5,0),"") | I59: =IFERROR(VLOOKUP($G59,Basic_Data!$E$2:$H$10,4,0),"") | K59: =IFERROR(VLOOKUP($B59-1,Inverter_PR!$B:$I,Module_Cleaning!H59,0),"") | L59: =IFERROR(VLOOKUP($B59+1,Inverter_PR!$B:$I,Module_Cleaning!H59,0),"") | M59: =IFERROR(I59-J59,"") | N59: All module cleaned by rain
A60: 45785 | B60: 45785 | C60: 0 | D60: 0 | E60: 0 | F60: 0 | H60: =IFERROR(VLOOKUP(G60,Basic_Data!$E$2:$I$9,5,0),"") | I60: 0 | J60: 0 | K60: =IFERROR(VLOOKUP($B60-1,Inverter_PR!$B:$I,Module_Cleaning!H60,0),"") | L60: =IFERROR(VLOOKUP($B60+1,Inverter_PR!$B:$I,Module_Cleaning!H60,0),"") | M60: =IFERROR(I60-J60,"") -> 0 | N60: N0 cleaning
A61: 45786 | B61: 45786 | H61: =IFERROR(VLOOKUP(G61,Basic_Data!$E$2:$I$9,5,0),"") | I61: =IFERROR(VLOOKUP($G61,Basic_Data!$E$2:$H$10,4,0),"") | K61: =IFERROR(VLOOKUP($B61-1,Inverter_PR!$B:$I,Module_Cleaning!H61,0),"") | L61: =IFERROR(VLOOKUP($B61+1,Inverter_PR!$B:$I,Module_Cleaning!H61,0),"") | M61: =IFERROR(I61-J61,"") | N61: All module cleaned by rain
A62: 45787 | B62: 45787 | H62: =IFERROR(VLOOKUP(G62,Basic_Data!$E$2:$I$9,5,0),"") | I62: =IFERROR(VLOOKUP($G62,Basic_Data!$E$2:$H$10,4,0),"") | K62: =IFERROR(VLOOKUP($B62-1,Inverter_PR!$B:$I,Module_Cleaning!H62,0),"") | L62: =IFERROR(VLOOKUP($B62+1,Inverter_PR!$B:$I,Module_Cleaning!H62,0),"") | M62: =IFERROR(I62-J62,"") | N62: All module cleaned by rain
A63: 45788 | B63: 45788 | H63: =IFERROR(VLOOKUP(G63,Basic_Data!$E$2:$I$9,5,0),"") | I63: =IFERROR(VLOOKUP($G63,Basic_Data!$E$2:$H$10,4,0),"") | K63: =IFERROR(VLOOKUP($B63-1,Inverter_PR!$B:$I,Module_Cleaning!H63,0),"") | L63: =IFERROR(VLOOKUP($B63+1,Inverter_PR!$B:$I,Module_Cleaning!H63,0),"") | M63: =IFERROR(I63-J63,"") | N63: All module cleaned by rain
A64: 45789 | B64: 45789 | C64: 0 | D64: 0 | E64: 0 | F64: 0 | H64: =IFERROR(VLOOKUP(G64,Basic_Data!$E$2:$I$9,5,0),"") | I64: 0 | J64: 0 | K64: =IFERROR(VLOOKUP($B64-1,Inverter_PR!$B:$I,Module_Cleaning!H64,0),"") | L64: =IFERROR(VLOOKUP($B64+1,Inverter_PR!$B:$I,Module_Cleaning!H64,0),"") | M64: =IFERROR(I64-J64,"") -> 0 | N64: N0 cleaning
A65: 45790 | B65: 45790 | C65: 0 | D65: 0 | E65: 0 | F65: 0 | H65: =IFERROR(VLOOKUP(G65,Basic_Data!$E$2:$I$9,5,0),"") | I65: 0 | J65: 0 | K65: =IFERROR(VLOOKUP($B65-1,Inverter_PR!$B:$I,Module_Cleaning!H65,0),"") | L65: =IFERROR(VLOOKUP($B65+1,Inverter_PR!$B:$I,Module_Cleaning!H65,0),"") | M65: =IFERROR(I65-J65,"") -> 0 | N65: N0 cleaning
A66: 45791 | B66: 45791 | C66: 0 | D66: 0 | E66: 0 | F66: 0 | H66: =IFERROR(VLOOKUP(G66,Basic_Data!$E$2:$I$9,5,0),"") | I66: 0 | J66: 0 | K66: =IFERROR(VLOOKUP($B66-1,Inverter_PR!$B:$I,Module_Cleaning!H66,0),"") | L66: =IFERROR(VLOOKUP($B66+1,Inverter_PR!$B:$I,Module_Cleaning!H66,0),"") | M66: =IFERROR(I66-J66,"") -> 0 | N66: N0 cleaning
A67: 45792 | B67: 45792 | C67: 0 | D67: 0 | E67: 0 | F67: 0 | H67: =IFERROR(VLOOKUP(G67,Basic_Data!$E$2:$I$9,5,0),"") | I67: 0 | J67: 0 | K67: =IFERROR(VLOOKUP($B67-1,Inverter_PR!$B:$I,Module_Cleaning!H67,0),"") | L67: =IFERROR(VLOOKUP($B67+1,Inverter_PR!$B:$I,Module_Cleaning!H67,0),"") | M67: =IFERROR(I67-J67,"") -> 0 | N67: N0 cleaning
A68: 45793 | B68: 45793 | F68: 1 | G68: Inv_1 | H68: =IFERROR(VLOOKUP(G68,Basic_Data!$E$2:$I$9,5,0),"") -> 2 | I68: =IFERROR(VLOOKUP($G68,Basic_Data!$E$2:$H$10,4,0),"") -> 616 | J68: 616 | K68: =IFERROR(VLOOKUP($B68-1,Inverter_PR!$B:$I,Module_Cleaning!H68,0),"") -> 0.90583712 | L68: =IFERROR(VLOOKUP($B68+1,Inverter_PR!$B:$I,Module_Cleaning!H68,0),"") -> 0.91621928 | M68: =IFERROR(I68-J68,"") -> 0 | N68: robat cleanig
F69: 1 | G69: Inv_2 | I69: =IFERROR(VLOOKUP($G69,Basic_Data!$E$2:$H$10,4,0),"") -> 616 | J69: 616 | M69: =IFERROR(I69-J69,"") -> 0 | N69: robat cleanig
A70: 45794 | B70: 45794 | C70: 0 | D70: 0 | E70: 0 | F70: 0 | H70: =IFERROR(VLOOKUP(G70,Basic_Data!$E$2:$I$9,5,0),"") | I70: 0 | J70: 0 | K70: =IFERROR(VLOOKUP($B70-1,Inverter_PR!$B:$I,Module_Cleaning!H70,0),"") | L70: =IFERROR(VLOOKUP($B70+1,Inverter_PR!$B:$I,Module_Cleaning!H70,0),"") | M70: =IFERROR(I70-J70,"") -> 0 | N70: N0 cleaning
A71: 45795 | B71: 45795 | C71: 0 | D71: 0 | E71: 0 | F71: 0 | H71: =IFERROR(VLOOKUP(G71,Basic_Data!$E$2:$I$9,5,0),"") | I71: 0 | J71: 0 | K71: =IFERROR(VLOOKUP($B71-1,Inverter_PR!$B:$I,Module_Cleaning!H71,0),"") | L71: =IFERROR(VLOOKUP($B71+1,Inverter_PR!$B:$I,Module_Cleaning!H71,0),"") | M71: =IFERROR(I71-J71,"") -> 0 | N71: N0 cleaning
A72: 45796 | B72: 45796 | C72: 0 | D72: 0 | E72: 0 | F72: 0 | H72: =IFERROR(VLOOKUP(G72,Basic_Data!$E$2:$I$9,5,0),"") | I72: 0 | J72: 0 | K72: =IFERROR(VLOOKUP($B72-1,Inverter_PR!$B:$I,Module_Cleaning!H72,0),"") | L72: =IFERROR(VLOOKUP($B72+1,Inverter_PR!$B:$I,Module_Cleaning!H72,0),"") | M72: =IFERROR(I72-J72,"") -> 0 | N72: N0 cleaning
A73: 45797 | B73: 45797 | C73: 5 | D73: 5000 | F73: 1 | G73: Inv_1 | H73: =IFERROR(VLOOKUP(G73,Basic_Data!$E$2:$I$9,5,0),"") -> 2 | I73: =IFERROR(VLOOKUP($G73,Basic_Data!$E$2:$H$10,4,0),"") -> 616 | J73: 616 | K73: =IFERROR(VLOOKUP($B73-1,Inverter_PR!$B:$I,Module_Cleaning!H73,0),"") -> 0.92399029 | L73: =IFERROR(VLOOKUP($B73+1,Inverter_PR!$B:$I,Module_Cleaning!H73,0),"") -> 0.96171714 | M73: =IFERROR(I73-J73,"") -> 0 | N73: wet cleaning
G74: Inv_2 | N74: wet cleaning
G75: Inv_3 | N75: wet cleaning
G76: Inv_4 | N76: wet cleaning
G77: Inv_5 | N77: wet cleaning
G78: Inv_6 | N78: wet cleaning
G79: Inv_7 | N79: wet cleaning
A80: 45798 | B80: 45798 | C80: 0 | D80: 0 | E80: 0 | F80: 0 | H80: =IFERROR(VLOOKUP(G80,Basic_Data!$E$2:$I$9,5,0),"") | I80: 0 | J80: 0 | K80: =IFERROR(VLOOKUP($B80-1,Inverter_PR!$B:$I,Module_Cleaning!H80,0),"") | L80: =IFERROR(VLOOKUP($B80+1,Inverter_PR!$B:$I,Module_Cleaning!H80,0),"") | M80: =IFERROR(I80-J80,"") -> 0 | N80: N0 cleaning
A81: 45799 | B81: 45799 | C81: 0 | D81: 0 | E81: 0 | F81: 0 | H81: =IFERROR(VLOOKUP(G81,Basic_Data!$E$2:$I$9,5,0),"") | I81: 0 | J81: 0 | K81: =IFERROR(VLOOKUP($B81-1,Inverter_PR!$B:$I,Module_Cleaning!H81,0),"") | L81: =IFERROR(VLOOKUP($B81+1,Inverter_PR!$B:$I,Module_Cleaning!H81,0),"") | M81: =IFERROR(I81-J81,"") -> 0 | N81: N0 cleaning
A82: 45800 | B82: 45800 | C82: 0 | D82: 0 | E82: 0 | F82: 0 | H82: =IFERROR(VLOOKUP(G82,Basic_Data!$E$2:$I$9,5,0),"") | I82: 0 | J82: 0 | K82: =IFERROR(VLOOKUP($B82-1,Inverter_PR!$B:$I,Module_Cleaning!H82,0),"") | L82: =IFERROR(VLOOKUP($B82+1,Inverter_PR!$B:$I,Module_Cleaning!H82,0),"") | M82: =IFERROR(I82-J82,"") -> 0 | N82: N0 cleaning
A83: 45801 | B83: 45801 | C83: 0 | D83: 0 | E83: 0 | F83: 0 | H83: =IFERROR(VLOOKUP(G83,Basic_Data!$E$2:$I$9,5,0),"") | I83: 0 | J83: 0 | K83: =IFERROR(VLOOKUP($B83-1,Inverter_PR!$B:$I,Module_Cleaning!H83,0),"") | L83: =IFERROR(VLOOKUP($B83+1,Inverter_PR!$B:$I,Module_Cleaning!H83,0),"") | M83: =IFERROR(I83-J83,"") -> 0 | N83: N0 cleaning
A84: 45802 | B84: 45802 | C84: 0 | D84: 0 | E84: 0 | F84: 0 | H84: =IFERROR(VLOOKUP(G84,Basic_Data!$E$2:$I$9,5,0),"") | I84: 0 | J84: 0 | K84: =IFERROR(VLOOKUP($B84-1,Inverter_PR!$B:$I,Module_Cleaning!H84,0),"") | L84: =IFERROR(VLOOKUP($B84+1,Inverter_PR!$B:$I,Module_Cleaning!H84,0),"") | M84: =IFERROR(I84-J84,"") -> 0 | N84: N0 cleaning
A85: 45803 | B85: 45803 | C85: 0 | D85: 0 | E85: 0 | F85: 0 | H85: =IFERROR(VLOOKUP(G85,Basic_Data!$E$2:$I$9,5,0),"") | I85: 0 | J85: 0 | K85: =IFERROR(VLOOKUP($B85-1,Inverter_PR!$B:$I,Module_Cleaning!H85,0),"") | L85: =IFERROR(VLOOKUP($B85+1,Inverter_PR!$B:$I,Module_Cleaning!H85,0),"") | M85: =IFERROR(I85-J85,"") -> 0 | N85: N0 cleaning
A86: 45804 | B86: 45804 | C86: 0 | D86: 0 | E86: 0 | F86: 2 | G86: Inv_1 | H86: =IFERROR(VLOOKUP(G86,Basic_Data!$E$2:$I$9,5,0),"") -> 2 | I86: =IFERROR(VLOOKUP($G86,Basic_Data!$E$2:$H$10,4,0),"") -> 616 | J86: 616 | K86: =IFERROR(VLOOKUP($B86-1,Inverter_PR!$B:$I,Module_Cleaning!H86,0),"") -> 0.88966922 | L86: =IFERROR(VLOOKUP($B86+1,Inverter_PR!$B:$I,Module_Cleaning!H86,0),"") -> 0.9610571 | M86: =IFERROR(I86-J86,"") -> 0 | N86: robat cleanig
A87: 45804 | B87: 45804 | C87: 0 | D87: 0 | E87: 0 | F87: 2 | G87: Inv_2 | H87: 3 | I87: 616 | J87: 616 | K87: =IFERROR(VLOOKUP($B87-1,Inverter_PR!$B:$I,Module_Cleaning!H87,0),"") -> 0.89389106 | L87: =IFERROR(VLOOKUP($B87+1,Inverter_PR!$B:$I,Module_Cleaning!H87,0),"") -> 0.9571407 | M87: 0 | N87: robat cleanig
A88: 45805 | B88: 45805 | C88: 0 | D88: 0 | E88: 0 | F88: 2 | G88: Inv_3 | H88: =IFERROR(VLOOKUP(G88,Basic_Data!$E$2:$I$9,5,0),"") -> 4 | I88: =IFERROR(VLOOKUP($G88,Basic_Data!$E$2:$H$10,4,0),"") -> 616 | J88: 616 | K88: =IFERROR(VLOOKUP($B88-1,Inverter_PR!$B:$I,Module_Cleaning!H88,0),"") -> 0.98655739 | L88: =IFERROR(VLOOKUP($B88+1,Inverter_PR!$B:$I,Module_Cleaning!H88,0),"") -> 0.9306581 | M88: =IFERROR(I88-J88,"") -> 0 | N88: robat cleanig
A89: 45805 | B89: 45805 | C89: 0 | D89: 0 | E89: 0 | F89: 2 | G89: Inv_4 | H89: =IFERROR(VLOOKUP(G89,Basic_Data!$E$2:$I$9,5,0),"") -> 5 | I89: =IFERROR(VLOOKUP($G89,Basic_Data!$E$2:$H$10,4,0),"") -> 644 | J89: 644 | K89: =IFERROR(VLOOKUP($B89-1,Inverter_PR!$B:$I,Module_Cleaning!H89,0),"") -> 0.98322557 | L89: =IFERROR(VLOOKUP($B89+1,Inverter_PR!$B:$I,Module_Cleaning!H89,0),"") -> 0.92857014 | M89: =IFERROR(I89-J89,"") -> 0 | N89: robat cleanig
A90: 45805 | B90: 45805 | C90: 0 | D90: 0 | E90: 0 | F90: 2 | G90: Inv_5 | H90: =IFERROR(VLOOKUP(G90,Basic_Data!$E$2:$I$9,5,0),"") -> 6 | I90: =IFERROR(VLOOKUP($G90,Basic_Data!$E$2:$H$10,4,0),"") -> 644 | J90: 644 | K90: =IFERROR(VLOOKUP($B90-1,Inverter_PR!$B:$I,Module_Cleaning!H90,0),"") -> 0.98015048 | L90: =IFERROR(VLOOKUP($B90+1,Inverter_PR!$B:$I,Module_Cleaning!H90,0),"") -> 0.92052853 | M90: =IFERROR(I90-J90,"") -> 0 | N90: robat cleanig
A91: 45806 | B91: 45806 | C91: 0 | D91: 0 | E91: 0 | F91: 2 | G91: Inv_6 | H91: =IFERROR(VLOOKUP(G91,Basic_Data!$E$2:$I$9,5,0),"") -> 7 | I91: =IFERROR(VLOOKUP($G91,Basic_Data!$E$2:$H$10,4,0),"") -> 644 | J91: 644 | K91: =IFERROR(VLOOKUP($B91-1,Inverter_PR!$B:$I,Module_Cleaning!H91,0),"") -> 0.91756603 | L91: =IFERROR(VLOOKUP($B91+1,Inverter_PR!$B:$I,Module_Cleaning!H91,0),"") -> 0.89174507 | M91: =IFERROR(I91-J91,"") -> 0 | N91: robat cleanig
A92: 45806 | B92: 45806 | C92: 0 | D92: 0 | E92: 0 | F92: 2 | G92: Inv_7 | H92: 8 | I92: 644 | J92: 644 | K92: =IFERROR(VLOOKUP($B92-1,Inverter_PR!$B:$I,Module_Cleaning!H92,0),"") -> 0.92290675 | L92: =IFERROR(VLOOKUP($B92+1,Inverter_PR!$B:$I,Module_Cleaning!H92,0),"") -> 0.90024457 | M92: 0 | N92: robat cleanig
A93: 45807 | B93: 45807 | C93: 0 | D93: 0 | E93: 0 | F93: 0 | H93: =IFERROR(VLOOKUP(G93,Basic_Data!$E$2:$I$9,5,0),"") | I93: 0 | J93: 0 | K93: =IFERROR(VLOOKUP($B93-1,Inverter_PR!$B:$I,Module_Cleaning!H93,0),"") | L93: 0 | M93: =IFERROR(I93-J93,"") -> 0 | N93: N0 cleaning
A94: 45808 | B94: 45808 | C94: 0 | D94: 0 | E94: 0 | F94: 0 | H94: =IFERROR(VLOOKUP(G94,Basic_Data!$E$2:$I$9,5,0),"") | I94: 0 | J94: 0 | K94: =IFERROR(VLOOKUP($B94-1,Inverter_PR!$B:$I,Module_Cleaning!H94,0),"") | L94: 0 | M94: =IFERROR(I94-J94,"") -> 0 | N94: N0 cleaning
A95: 45809 | B95: 45809 | C95: 0 | D95: 0 | E95: 0 | F95: 0 | H95: =IFERROR(VLOOKUP(G95,Basic_Data!$E$2:$I$9,5,0),"") | I95: 0 | J95: 0 | K95: =IFERROR(VLOOKUP($B95-1,Inverter_PR!$B:$I,Module_Cleaning!H95,0),"") | L95: =IFERROR(VLOOKUP($B95+1,Inverter_PR!$B:$I,Module_Cleaning!H95,0),"") | M95: =IFERROR(I95-J95,"") -> 0 | N95: N0 cleaning
A96: 45810 | B96: 45810 | C96: 0 | D96: 0 | E96: 0 | F96: 0 | H96: =IFERROR(VLOOKUP(G96,Basic_Data!$E$2:$I$9,5,0),"") | I96: 0 | J96: 0 | K96: 0 | L96: 0 | M96: =IFERROR(I96-J96,"") -> 0 | N96: N0 cleaning
A97: 45811 | B97: 45811 | C97: 0 | D97: 0 | E97: 0 | F97: 0 | H97: =IFERROR(VLOOKUP(G97,Basic_Data!$E$2:$I$9,5,0),"") | I97: 0 | J97: 0 | K97: 0 | L97: 0 | M97: =IFERROR(I97-J97,"") -> 0 | N97: N0 cleaning
A98: 45812 | B98: 45812 | C98: 0 | D98: 0 | E98: 0 | F98: 1 | G98: Inv_1 | H98: =IFERROR(VLOOKUP(G98,Basic_Data!$E$2:$I$9,5,0),"") -> 2 | I98: =IFERROR(VLOOKUP($G98,Basic_Data!$E$2:$H$10,4,0),"") -> 616 | J98: 616 | K98: =IFERROR(VLOOKUP($B98-1,Inverter_PR!$B:$I,Module_Cleaning!H98,0),"") -> 0.68069168 | L98: =IFERROR(VLOOKUP($B98+1,Inverter_PR!$B:$I,Module_Cleaning!H98,0),"") -> 0.98406681 | M98: =IFERROR(I98-J98,"") -> 0 | N98: robat cleanig
A99: 45812 | B99: 45812 | C99: 0 | D99: 0 | E99: 0 | F99: 1 | G99: Inv_2 | H99: =IFERROR(VLOOKUP(G99,Basic_Data!$E$2:$I$9,5,0),"") -> 3 | I99: =IFERROR(VLOOKUP($G99,Basic_Data!$E$2:$H$10,4,0),"") -> 616 | J99: 616 | K99: =IFERROR(VLOOKUP($B99-1,Inverter_PR!$B:$I,Module_Cleaning!H99,0),"") -> 0.67632363 | L99: =IFERROR(VLOOKUP($B99+1,Inverter_PR!$B:$I,Module_Cleaning!H99,0),"") -> 0.9759919 | M99: =IFERROR(I99-J99,"") -> 0 | N99: robat cleanig
A100: 45813 | B100: 45813 | C100: 0 | D100: 0 | E100: 0 | F100: 1 | G100: Inv_3 | H100: =IFERROR(VLOOKUP(G100,Basic_Data!$E$2:$I$9,5,0),"") -> 4 | I100: =IFERROR(VLOOKUP($G100,Basic_Data!$E$2:$H$10,4,0),"") -> 616 | J100: 616 | K100: =IFERROR(VLOOKUP($B100-1,Inverter_PR!$B:$I,Module_Cleaning!H100,0),"") -> 0.93478339 | L100: =IFERROR(VLOOKUP($B100+1,Inverter_PR!$B:$I,Module_Cleaning!H100,0),"") -> 0.91193004 | M100: =IFERROR(I100-J100,"") -> 0 | N100: robat cleanig
A101: 45813 | B101: 45813 | C101: 0 | D101: 0 | E101: 0 | F101: 1 | G101: Inv_4 | H101: =IFERROR(VLOOKUP(G101,Basic_Data!$E$2:$I$9,5,0),"") -> 5 | I101: =IFERROR(VLOOKUP($G101,Basic_Data!$E$2:$H$10,4,0),"") -> 644 | J101: 644 | K101: =IFERROR(VLOOKUP($B101-1,Inverter_PR!$B:$I,Module_Cleaning!H101,0),"") -> 0.93126431 | L101: =IFERROR(VLOOKUP($B101+1,Inverter_PR!$B:$I,Module_Cleaning!H101,0),"") -> 0.91694863 | M101: =IFERROR(I101-J101,"") -> 0 | N101: robat cleanig
A102: 45814 | B102: 45814 | C102: 0 | D102: 0 | E102: 0 | F102: 1 | G102: Inv_5 | H102: =IFERROR(VLOOKUP(G102,Basic_Data!$E$2:$I$9,5,0),"") -> 6 | I102: =IFERROR(VLOOKUP($G102,Basic_Data!$E$2:$H$10,4,0),"") -> 644 | J102: 644 | K102: =IFERROR(VLOOKUP($B102-1,Inverter_PR!$B:$I,Module_Cleaning!H102,0),"") -> 0.965235 | L102: =IFERROR(VLOOKUP($B102+1,Inverter_PR!$B:$I,Module_Cleaning!H102,0),"") -> 0.8938346 | M102: =IFERROR(I102-J102,"") -> 0 | N102: robat cleanig
A103: 45814 | B103: 45814 | C103: 0 | D103: 0 | E103: 0 | F103: 1 | G103: Inv_6 | H103: =IFERROR(VLOOKUP(G103,Basic_Data!$E$2:$I$9,5,0),"") -> 7 | I103: =IFERROR(VLOOKUP($G103,Basic_Data!$E$2:$H$10,4,0),"") -> 644 | J103: 644 | K103: =IFERROR(VLOOKUP($B103-1,Inverter_PR!$B:$I,Module_Cleaning!H103,0),"") -> 0.95957812 | L103: =IFERROR(VLOOKUP($B103+1,Inverter_PR!$B:$I,Module_Cleaning!H103,0),"") -> 0.89425177 | M103: =IFERROR(I103-J103,"") -> 0 | N103: robat cleanig
...

Sheet Plant  Availiblity
A2: Date | B2: ABT Export Gen | C2: Total inevrter off | D2: GHI | E2: CUF% | F2: Out | G2: In | H2: Total Minute | I2: Outage Hrs. | J2: Plant Capacity | K2: Outage Capacity | L2: Plant Capacity Ratio | M2: Outage Ratio | N2: Plant Availiblity | O2: PA.C CUF | P2: total curtailment | Q2: P.A.C Generation | R2: PA Unit Lose
A3: 45839 | B3: =Data_Entry!P94 -> 9120 | C3: 0 | D3: =Data_Entry!V94 -> 4.07 | E3: =B3/(24*J3) -> 0.15761095 | F3: 0 | G3: 0 | H3: =(G3-F3)*24*60 -> 0 | I3: =H3/60 -> 0 | J3: 2411 | L3: =J3*12 -> 28932 | M3: =K3*I3 -> 0 | N3: =(L3-M3)/L3 -> 1 | O3: =E3/N3 -> 0.15761095 | Q3: =O3*J3*24 -> 9120 | R3: =Q3-B3 -> 0
A4: 45840 | B4: =Data_Entry!P95 -> 4620 | C4: 0 | D4: =Data_Entry!V95 -> 1.77 | E4: =B4/(24*J4) -> 0.079842389 | F4: 0 | G4: 0 | H4: =(G4-F4)*24*60 -> 0 | I4: =H4/60 -> 0 | J4: 2411 | L4: =J4*12 -> 28932 | M4: =K4*I4 -> 0 | N4: =(L4-M4)/L4 -> 1 | O4: =E4/N4 -> 0.079842389 | Q4: =O4*J4*24 -> 4620 | R4: =Q4-B4 -> 0
A5: 45841 | B5: =Data_Entry!P96 -> 4050 | C5: 0 | D5: =Data_Entry!V96 -> 1.54 | E5: =B5/(24*J5) -> 0.069991705 | F5: 0 | G5: 0 | H5: =(G5-F5)*24*60 -> 0 | I5: =H5/60 -> 0 | J5: 2411 | L5: =J5*12 -> 28932 | M5: =K5*I5 -> 0 | N5: =(L5-M5)/L5 -> 1 | O5: =E5/N5 -> 0.069991705 | Q5: =O5*J5*24 -> 4050 | R5: =Q5-B5 -> 0
A6: 45842 | B6: =Data_Entry!P97 -> 5580 | C6: 0 | D6: =Data_Entry!V97 -> 2.25 | E6: =B6/(24*J6) -> 0.096433015 | F6: 0 | G6: 0 | H6: =(G6-F6)*24*60 -> 0 | I6: =H6/60 -> 0 | J6: 2411 | L6: =J6*12 -> 28932 | M6: =K6*I6 -> 0 | N6: =(L6-M6)/L6 -> 1 | O6: =E6/N6 -> 0.096433015 | Q6: =O6*J6*24 -> 5580 | R6: =Q6-B6 -> 0
A7: 45843 | B7: =Data_Entry!P98 -> 3210 | C7: 0 | D7: =Data_Entry!V98 -> 1.2 | E7: =B7/(24*J7) -> 0.055474907 | F7: 0 | G7: 0 | H7: =(G7-F7)*24*60 -> 0 | I7: =H7/60 -> 0 | J7: 2411 | L7: =J7*12 -> 28932 | M7: =K7*I7 -> 0 | N7: =(L7-M7)/L7 -> 1 | O7: =E7/N7 -> 0.055474907 | Q7: =O7*J7*24 -> 3210 | R7: =Q7-B7 -> 0
A8: 45844 | B8: =Data_Entry!P99 -> 4980 | C8: 0 | D8: =Data_Entry!V99 -> 1.93 | E8: =B8/(24*J8) -> 0.086063874 | F8: 0 | G8: 0 | H8: =(G8-F8)*24*60 -> 0 | I8: =H8/60 -> 0 | J8: 2411 | L8: =J8*12 -> 28932 | M8: =K8*I8 -> 0 | N8: =(L8-M8)/L8 -> 1 | O8: =E8/N8 -> 0.086063874 | Q8: =O8*J8*24 -> 4980 | R8: =Q8-B8 -> 0
A9: 45845 | B9: =Data_Entry!P100 -> 3690 | C9: 0 | D9: =Data_Entry!V100 -> 1.43 | E9: =B9/(24*J9) -> 0.06377022 | F9: 0 | G9: 0 | H9: =(G9-F9)*24*60 -> 0 | I9: =H9/60 -> 0 | J9: 2411 | L9: =J9*12 -> 28932 | M9: =K9*I9 -> 0 | N9: =(L9-M9)/L9 -> 1 | O9: =E9/N9 -> 0.06377022 | Q9: =O9*J9*24 -> 3690 | R9: =Q9-B9 -> 0
A10: 45846 | B10: =Data_Entry!P101 -> 6990 | C10: 0 | D10: =Data_Entry!V101 -> 2.81 | E10: =B10/(24*J10) -> 0.1208005 | F10: 0 | G10: 0 | H10: =(G10-F10)*24*60 -> 0 | I10: =H10/60 -> 0 | J10: 2411 | L10: =J10*12 -> 28932 | M10: =K10*I10 -> 0 | N10: =(L10-M10)/L10 -> 1 | O10: =E10/N10 -> 0.1208005 | Q10: =O10*J10*24 -> 6990 | R10: =Q10-B10 -> 0
A11: 45847 | B11: =Data_Entry!P102 -> 11880 | C11: 0 | D11: =Data_Entry!V102 -> 5.06 | E11: =B11/(24*J11) -> 0.205309 | F11: 0 | G11: 0 | H11: =(G11-F11)*24*60 -> 0 | I11: =H11/60 -> 0 | J11: 2411 | L11: =J11*12 -> 28932 | M11: =K11*I11 -> 0 | N11: =(L11-M11)/L11 -> 1 | O11: =E11/N11 -> 0.205309 | Q11: =O11*J11*24 -> 11880 | R11: =Q11-B11 -> 0
A12: 45848 | B12: =Data_Entry!P103 -> 4950 | C12: 0 | D12: =Data_Entry!V103 -> 2.01 | E12: =B12/(24*J12) -> 0.085545417 | F12: 0 | G12: 0 | H12: =(G12-F12)*24*60 -> 0 | I12: =H12/60 -> 0 | J12: 2411 | L12: =J12*12 -> 28932 | M12: =K12*I12 -> 0 | N12: =(L12-M12)/L12 -> 1 | O12: =E12/N12 -> 0.085545417 | Q12: =O12*J12*24 -> 4950 | R12: =Q12-B12 -> 0
A13: 45849 | B13: =Data_Entry!P104 -> 3540 | C13: 0 | D13: =Data_Entry!V104 -> 1.32 | E13: =B13/(24*J13) -> 0.061177934 | F13: 0 | G13: 0 | H13: =(G13-F13)*24*60 -> 0 | I13: =H13/60 -> 0 | J13: 2411 | L13: =J13*12 -> 28932 | M13: =K13*I13 -> 0 | N13: =(L13-M13)/L13 -> 1 | O13: =E13/N13 -> 0.061177934 | Q13: =O13*J13*24 -> 3540 | R13: =Q13-B13 -> 0
A14: 45850 | B14: =Data_Entry!P105 -> 10290 | C14: 0 | D14: =Data_Entry!V105 -> 3.95 | E14: =B14/(24*J14) -> 0.17783078 | F14: 0 | G14: 0 | H14: =(G14-F14)*24*60 -> 0 | I14: =H14/60 -> 0 | J14: 2411 | L14: =J14*12 -> 28932 | M14: =K14*I14 -> 0 | N14: =(L14-M14)/L14 -> 1 | O14: =E14/N14 -> 0.17783078 | Q14: =O14*J14*24 -> 10290 | R14: =Q14-B14 -> 0
... A25: 45861 | B25: =Data_Entry!P116 -> 6090 | C25: 0 | D25: =Data_Entry!V116 -> 2.6 | E25: =B25/(24*J25) -> 0.10524679 | F25: 0 | G25: 0 | H25: =(G25-F25)*24*60 -> 0 | I25: =H25/60 -> 0 | J25: 2411 | L25: =J25*12 -> 28932 | M25: =K25*I25 -> 0 | N25: =(L25-M25)/L25 -> 1 | O25: =E25/N25 -> 0.10524679 | Q25: =O25*J25*24 -> 6090 | R25: =Q25-B25 -> 0
A26: 45862 | B26: =Data_Entry!P117 -> 3720 | C26: 7 | D26: =Data_Entry!V117 -> 1.49 | E26: =B26/(24*J26) -> 0.064288677 | F26: 0.28472222 | G26: 0.32291667 | H26: =(G26-F26)*24*60 -> 55 | I26: =H26/60 -> 0.91666667 | J26: 2411 | K26: 2411 | L26: =J26*12 -> 28932 | M26: =K26*I26 -> 2210.0833 | N26: =(L26-M26)/L26 -> 0.92361111 | O26: =E26/N26 -> 0.069605786 | Q26: =O26*J26*24 -> 4027.6692 | R26: =Q26-B26 -> 307.66917
A27: 45863 | B27: =Data_Entry!P118 -> 7800 | C27: 0 | D27: =Data_Entry!V118 -> 3.14 | E27: =B27/(24*J27) -> 0.13479884 | F27: 0 | G27: 0 | H27: =(G27-F27)*24*60 -> 0 | I27: =H27/60 -> 0 | J27: 2411 | L27: =J27*12 -> 28932 | M27: =K27*I27 -> 0 | N27: =(L27-M27)/L27 -> 1 | O27: =E27/N27 -> 0.13479884 | Q27: =O27*J27*24 -> 7800 | R27: =Q27-B27 -> 0
A28: 45864 | B28: =Data_Entry!P119 -> 5550 | C28: 0 | D28: =Data_Entry!V119 -> 2.26 | E28: =B28/(24*J28) -> 0.095914558 | F28: 0 | G28: 0 | H28: =(G28-F28)*24*60 -> 0 | I28: =H28/60 -> 0 | J28: 2411 | L28: =J28*12 -> 28932 | M28: =K28*I28 -> 0 | N28: =(L28-M28)/L28 -> 1 | O28: =E28/N28 -> 0.095914558 | Q28: =O28*J28*24 -> 5550 | R28: =Q28-B28 -> 0
A29: 45865 | B29: =Data_Entry!P120 -> 4260 | C29: 0 | D29: =Data_Entry!V120 -> 1.6 | E29: =B29/(24*J29) -> 0.073620904 | F29: 0 | G29: 0 | H29: =(G29-F29)*24*60 -> 0 | I29: =H29/60 -> 0 | J29: 2411 | L29: =J29*12 -> 28932 | M29: =K29*I29 -> 0 | N29: =(L29-M29)/L29 -> 1 | O29: =E29/N29 -> 0.073620904 | Q29: =O29*J29*24 -> 4260 | R29: =Q29-B29 -> 0
A30: 45866 | B30: =Data_Entry!P121 -> 5520 | C30: 0 | D30: =Data_Entry!V121 -> 2.18 | E30: =B30/(24*J30) -> 0.095396101 | F30: 0 | G30: 0 | H30: =(G30-F30)*24*60 -> 0 | I30: =H30/60 -> 0 | J30: 2411 | L30: =J30*12 -> 28932 | M30: =K30*I30 -> 0 | N30: =(L30-M30)/L30 -> 1 | O30: =E30/N30 -> 0.095396101 | Q30: =O30*J30*24 -> 5520 | R30: =Q30-B30 -> 0
A31: 45867 | B31: =Data_Entry!P122 -> 4830 | C31: 0 | D31: =Data_Entry!V122 -> 1.89 | E31: =B31/(24*J31) -> 0.083471589 | F31: 0 | G31: 0 | H31: =(G31-F31)*24*60 -> 0 | I31: =H31/60 -> 0 | J31: 2411 | L31: =J31*12 -> 28932 | M31: =K31*I31 -> 0 | N31: =(L31-M31)/L31 -> 1 | O31: =E31/N31 -> 0.083471589 | Q31: =O31*J31*24 -> 4830 | R31: =Q31-B31 -> 0
A32: 45868 | B32: =Data_Entry!P123 -> 7440 | C32: 0 | D32: =Data_Entry!V123 -> 3.4 | E32: =B32/(24*J32) -> 0.12857735 | F32: 0 | G32: 0 | H32: =(G32-F32)*24*60 -> 0 | I32: =H32/60 -> 0 | J32: 2411 | L32: =J32*12 -> 28932 | M32: =K32*I32 -> 0 | N32: =(L32-M32)/L32 -> 1 | O32: =E32/N32 -> 0.12857735 | Q32: =O32*J32*24 -> 7440 | R32: =Q32-B32 -> 0
A33: 45869 | B33: =Data_Entry!P124 -> 6030 | C33: 0 | D33: =Data_Entry!V124 -> 2.19 | E33: =B33/(24*J33) -> 0.10420987 | F33: 0 | G33: 0 | H33: =(G33-F33)*24*60 -> 0 | I33: =H33/60 -> 0 | J33: 2411 | L33: =J33*12 -> 28932 | M33: =K33*I33 -> 0 | N33: =(L33-M33)/L33 -> 1 | O33: =E33/N33 -> 0.10420987 | Q33: =O33*J33*24 -> 6030 | R33: =Q33-B33 -> 0
A35: 45870 | B35: =Data_Entry!P126 -> 7380 | C35: 0 | D35: =Data_Entry!V125 -> 2.71 | E35: =B35/(24*J35) -> 0.12754044 | F35: 0 | G35: 0 | H35: =(G35-F35)*24*60 -> 0 | I35: =H35/60 -> 0 | J35: 2411 | L35: =J35*12 -> 28932 | M35: =K35*I35 -> 0 | N35: =(L35-M35)/L35 -> 1 | O35: =E35/N35 -> 0.12754044 | Q35: =O35*J35*24 -> 7380 | R35: =Q35-B35 -> 0
A36: 45871 | B36: =Data_Entry!P127 -> 5280 | C36: 0 | D36: =Data_Entry!V126 -> 3.07 | E36: =B36/(24*J36) -> 0.091248445 | F36: 0 | G36: 0 | H36: =(G36-F36)*24*60 -> 0 | I36: =H36/60 -> 0 | J36: 2411 | L36: =J36*12 -> 28932 | M36: =K36*I36 -> 0 | N36: =(L36-M36)/L36 -> 1 | O36: =E36/N36 -> 0.091248445 | Q36: =O36*J36*24 -> 5280 | R36: =Q36-B36 -> 0
A37: 45872 | B37: =Data_Entry!P128 -> 5190 | C37: 0 | D37: =Data_Entry!V127 -> 2.18 | E37: =B37/(24*J37) -> 0.089693073 | F37: 0 | G37: 0 | H37: =(G37-F37)*24*60 -> 0 | I37: =H37/60 -> 0 | J37: 2411 | L37: =J37*12 -> 28932 | M37: =K37*I37 -> 0 | N37: =(L37-M37)/L37 -> 1 | O37: =E37/N37 -> 0.089693073 | Q37: =O37*J37*24 -> 5190 | R37: =Q37-B37 -> 0
A38: 45873 | B38: =Data_Entry!P129 -> 7080 | C38: 0 | D38: =Data_Entry!V128 -> 1.96 | E38: =B38/(24*J38) -> 0.12235587 | F38: 0 | G38: 0 | H38: =(G38-F38)*24*60 -> 0 | I38: =H38/60 -> 0 | J38: 2411 | L38: =J38*12 -> 28932 | M38: =K38*I38 -> 0 | N38: =(L38-M38)/L38 -> 1 | O38: =E38/N38 -> 0.12235587 | Q38: =O38*J38*24 -> 7080 | R38: =Q38-B38 -> 0
A39: 45874 | B39: =Data_Entry!P130 -> 10620 | C39: 0 | D39: =Data_Entry!V129 -> 3 | E39: =B39/(24*J39) -> 0.1835338 | F39: 0 | G39: 0 | H39: =(G39-F39)*24*60 -> 0 | I39: =H39/60 -> 0 | J39: 2411 | L39: =J39*12 -> 28932 | M39: =K39*I39 -> 0 | N39: =(L39-M39)/L39 -> 1 | O39: =E39/N39 -> 0.1835338 | Q39: =O39*J39*24 -> 10620 | R39: =Q39-B39 -> 0
A40: 45875 | B40: =Data_Entry!P131 -> 12330 | C40: 0 | D40: =Data_Entry!V130 -> 4.33 | E40: =B40/(24*J40) -> 0.21308586 | F40: 0 | G40: 0 | H40: =(G40-F40)*24*60 -> 0 | I40: =H40/60 -> 0 | J40: 2411 | L40: =J40*12 -> 28932 | M40: =K40*I40 -> 0 | N40: =(L40-M40)/L40 -> 1 | O40: =E40/N40 -> 0.21308586 | Q40: =O40*J40*24 -> 12330 | R40: =Q40-B40 -> 0
A41: 45876 | B41: =Data_Entry!P132 -> 10380 | C41: 0 | D41: =Data_Entry!V131 -> 5.09 | E41: =B41/(24*J41) -> 0.17938615 | F41: 0 | G41: 0 | H41: =(G41-F41)*24*60 -> 0 | I41: =H41/60 -> 0 | J41: 2411 | L41: =J41*12 -> 28932 | M41: =K41*I41 -> 0 | N41: =(L41-M41)/L41 -> 1 | O41: =E41/N41 -> 0.17938615 | Q41: =O41*J41*24 -> 10380 | R41: =Q41-B41 -> 0
A42: 45877 | B42: =Data_Entry!P133 -> 7770 | C42: 0 | D42: =Data_Entry!V132 -> 4.32 | E42: =B42/(24*J42) -> 0.13428038 | F42: 0 | G42: 0 | H42: =(G42-F42)*24*60 -> 0 | I42: =H42/60 -> 0 | J42: 2411 | L42: =J42*12 -> 28932 | M42: =K42*I42 -> 0 | N42: =(L42-M42)/L42 -> 1 | O42: =E42/N42 -> 0.13428038 | Q42: =O42*J42*24 -> 7770 | R42: =Q42-B42 -> 0
A43: 45878 | B43: =Data_Entry!P134 -> 9000 | C43: 0 | D43: =Data_Entry!V133 -> 3.13 | E43: =B43/(24*J43) -> 0.15553712 | F43: 0 | G43: 0 | H43: =(G43-F43)*24*60 -> 0 | I43: =H43/60 -> 0 | J43: 2411 | L43: =J43*12 -> 28932 | M43: =K43*I43 -> 0 | N43: =(L43-M43)/L43 -> 1 | O43: =E43/N43 -> 0.15553712 | Q43: =O43*J43*24 -> 9000 | R43: =Q43-B43 -> 0
A44: 45879 | B44: =Data_Entry!P135 -> 9870 | C44: 0 | D44: =Data_Entry!V134 -> 3.41 | E44: =B44/(24*J44) -> 0.17057238 | F44: 0 | G44: 0 | H44: =(G44-F44)*24*60 -> 0 | I44: =H44/60 -> 0 | J44: 2411 | L44: =J44*12 -> 28932 | M44: =K44*I44 -> 0 | N44: =(L44-M44)/L44 -> 1 | O44: =E44/N44 -> 0.17057238 | Q44: =O44*J44*24 -> 9870 | R44: =Q44-B44 -> 0
A45: 45880 | B45: =Data_Entry!P136 -> 7980 | C45: 0 | D45: =Data_Entry!V135 -> 3.67 | E45: =B45/(24*J45) -> 0.13790958 | F45: 0 | G45: 0 | H45: =(G45-F45)*24*60 -> 0 | I45: =H45/60 -> 0 | J45: 2411 | L45: =J45*12 -> 28932 | M45: =K45*I45 -> 0 | N45: =(L45-M45)/L45 -> 1 | O45: =E45/N45 -> 0.13790958 | Q45: =O45*J45*24 -> 7980 | R45: =Q45-B45 -> 0
A46: 45881 | B46: =Data_Entry!P137 -> 9090 | C46: 0 | D46: =Data_Entry!V136 -> 2.94 | E46: =B46/(24*J46) -> 0.15709249 | F46: 0 | G46: 0 | H46: =(G46-F46)*24*60 -> 0 | I46: =H46/60 -> 0 | J46: 2411 | L46: =J46*12 -> 28932 | M46: =K46*I46 -> 0 | N46: =(L46-M46)/L46 -> 1 | O46: =E46/N46 -> 0.15709249 | Q46: =O46*J46*24 -> 9090 | R46: =Q46-B46 -> 0
... A48: 45883 | B48: =Data_Entry!P139 -> 6720 | C48: 0 | D48: =Data_Entry!V138 -> 2.7 | E48: =B48/(24*J48) -> 0.11613438 | F48: 0 | G48: 0 | H48: =(G48-F48)*24*60 -> 0 | I48: =H48/60 -> 0 | J48: 2411 | L48: =J48*12 -> 28932 | M48: =K48*I48 -> 0 | N48: =(L48-M48)/L48 -> 1 | O48: =E48/N48 -> 0.11613438 | Q48: =O48*J48*24 -> 6720 | R48: =Q48-B48 -> 0
A49: 45884 | B49: =Data_Entry!P140 -> 9210 | C49: 7 | D49: =Data_Entry!V139 -> 3.05 | E49: =B49/(24*J49) -> 0.15916632 | F49: 0.57291667 | G49: 0.63888889 | H49: =(G49-F49)*24*60 -> 95 | I49: =H49/60 -> 1.5833333 | J49: 2411 | K49: 2411 | L49: =J49*12 -> 28932 | M49: =K49*I49 -> 3817.4167 | N49: =(L49-M49)/L49 -> 0.86805556 | O49: =E49/N49 -> 0.1833596 | Q49: =O49*J49*24 -> 10609.92 | R49: =Q49-B49 -> 1399.92
A50: 45885 | B50: =Data_Entry!P141 -> 8220 | C50: 0 | D50: =Data_Entry!V140 -> 3.53 | E50: =B50/(24*J50) -> 0.14205724 | F50: 0 | G50: 0 | H50: =(G50-F50)*24*60 -> 0 | I50: =H50/60 -> 0 | J50: 2411 | L50: =J50*12 -> 28932 | M50: =K50*I50 -> 0 | N50: =(L50-M50)/L50 -> 1 | O50: =E50/N50 -> 0.14205724 | Q50: =O50*J50*24 -> 8220 | R50: =Q50-B50 -> 0
A51: 45886 | B51: =Data_Entry!P142 -> 8250 | C51: 0 | D51: =Data_Entry!V141 -> 3.05 | E51: =B51/(24*J51) -> 0.14257569 | F51: 0 | G51: 0 | H51: =(G51-F51)*24*60 -> 0 | I51: =H51/60 -> 0 | J51: 2411 | L51: =J51*12 -> 28932 | M51: =K51*I51 -> 0 | N51: =(L51-M51)/L51 -> 1 | O51: =E51/N51 -> 0.14257569 | Q51: =O51*J51*24 -> 8250 | R51: =Q51-B51 -> 0
A52: 45887 | B52: =Data_Entry!P143 -> 9240 | C52: 0 | D52: =Data_Entry!V142 -> 3.27 | E52: =B52/(24*J52) -> 0.15968478 | F52: 0 | G52: 0 | H52: =(G52-F52)*24*60 -> 0 | I52: =H52/60 -> 0 | J52: 2411 | L52: =J52*12 -> 28932 | M52: =K52*I52 -> 0 | N52: =(L52-M52)/L52 -> 1 | O52: =E52/N52 -> 0.15968478 | Q52: =O52*J52*24 -> 9240 | R52: =Q52-B52 -> 0
A53: 45888 | B53: =Data_Entry!P144 -> 2760 | C53: 0 | D53: =Data_Entry!V143 -> 0 | E53: =B53/(24*J53) -> 0.047698051 | F53: 0 | G53: 0 | H53: =(G53-F53)*24*60 -> 0 | I53: =H53/60 -> 0 | J53: 2411 | L53: =J53*12 -> 28932 | M53: =K53*I53 -> 0 | N53: =(L53-M53)/L53 -> 1 | O53: =E53/N53 -> 0.047698051 | Q53: =O53*J53*24 -> 2760 | R53: =Q53-B53 -> 0
A54: 45889 | B54: =Data_Entry!P145 -> 8070 | C54: 0 | D54: =Data_Entry!V144 -> 0 | E54: =B54/(24*J54) -> 0.13946495 | F54: 0 | G54: 0 | H54: =(G54-F54)*24*60 -> 0 | I54: =H54/60 -> 0 | J54: 2411 | L54: =J54*12 -> 28932 | M54: =K54*I54 -> 0 | N54: =(L54-M54)/L54 -> 1 | O54: =E54/N54 -> 0.13946495 | Q54: =O54*J54*24 -> 8070 | R54: =Q54-B54 -> 0
A55: 45890 | B55: =Data_Entry!P146 -> 8460 | C55: 0 | D55: =Data_Entry!V145 -> 0 | E55: =B55/(24*J55) -> 0.14620489 | F55: 0 | G55: 0 | H55: =(G55-F55)*24*60 -> 0 | I55: =H55/60 -> 0 | J55: 2411 | L55: =J55*12 -> 28932 | M55: =K55*I55 -> 0 | N55: =(L55-M55)/L55 -> 1 | O55: =E55/N55 -> 0.14620489 | Q55: =O55*J55*24 -> 8460 | R55: =Q55-B55 -> 0
A56: 45891 | B56: =Data_Entry!P147 -> 5790 | C56: 0 | D56: =Data_Entry!V146 -> 0 | E56: =B56/(24*J56) -> 0.10006221 | F56: 0 | G56: 0 | H56: =(G56-F56)*24*60 -> 0 | I56: =H56/60 -> 0 | J56: 2411 | L56: =J56*12 -> 28932 | M56: =K56*I56 -> 0 | N56: =(L56-M56)/L56 -> 1 | O56: =E56/N56 -> 0.10006221 | Q56: =O56*J56*24 -> 5790 | R56: =Q56-B56 -> 0
A57: 45892 | B57: =Data_Entry!P148 -> 5940 | C57: 0 | D57: =Data_Entry!V147 -> 0 | E57: =B57/(24*J57) -> 0.1026545 | F57: 0 | G57: 0 | H57: =(G57-F57)*24*60 -> 0 | I57: =H57/60 -> 0 | J57: 2411 | L57: =J57*12 -> 28932 | M57: =K57*I57 -> 0 | N57: =(L57-M57)/L57 -> 1 | O57: =E57/N57 -> 0.1026545 | Q57: =O57*J57*24 -> 5940 | R57: =Q57-B57 -> 0
A58: 45893 | B58: =Data_Entry!P149 -> 6180 | C58: 0 | D58: =Data_Entry!V148 -> 0 | E58: =B58/(24*J58) -> 0.10680216 | F58: 0 | G58: 0 | H58: =(G58-F58)*24*60 -> 0 | I58: =H58/60 -> 0 | J58: 2411 | L58: =J58*12 -> 28932 | M58: =K58*I58 -> 0 | N58: =(L58-M58)/L58 -> 1 | O58: =E58/N58 -> 0.10680216 | Q58: =O58*J58*24 -> 6180 | R58: =Q58-B58 -> 0
A59: 45894 | B59: =Data_Entry!P150 -> 7620 | C59: 0 | D59: =Data_Entry!V149 -> 0 | E59: =B59/(24*J59) -> 0.1316881 | F59: 0 | G59: 0 | H59: =(G59-F59)*24*60 -> 0 | I59: =H59/60 -> 0 | J59: 2411 | L59: =J59*12 -> 28932 | M59: =K59*I59 -> 0 | N59: =(L59-M59)/L59 -> 1 | O59: =E59/N59 -> 0.1316881 | Q59: =O59*J59*24 -> 7620 | R59: =Q59-B59 -> 0
A60: 45895 | B60: =Data_Entry!P151 -> 9420 | C60: 0 | D60: =Data_Entry!V150 -> 0 | E60: =B60/(24*J60) -> 0.16279552 | F60: 0 | G60: 0 | H60: =(G60-F60)*24*60 -> 0 | I60: =H60/60 -> 0 | J60: 2411 | L60: =J60*12 -> 28932 | M60: =K60*I60 -> 0 | N60: =(L60-M60)/L60 -> 1 | O60: =E60/N60 -> 0.16279552 | Q60: =O60*J60*24 -> 9420 | R60: =Q60-B60 -> 0
A61: 45896 | B61: =Data_Entry!P152 -> 9030 | C61: 0 | D61: =Data_Entry!V151 -> 0 | E61: =B61/(24*J61) -> 0.15605558 | F61: 0 | G61: 0 | H61: =(G61-F61)*24*60 -> 0 | I61: =H61/60 -> 0 | J61: 2411 | L61: =J61*12 -> 28932 | M61: =K61*I61 -> 0 | N61: =(L61-M61)/L61 -> 1 | O61: =E61/N61 -> 0.15605558 | Q61: =O61*J61*24 -> 9030 | R61: =Q61-B61 -> 0
... A65: 45900 | B65: =Data_Entry!P156 -> 8520 | C65: 0 | D65: =Data_Entry!V155 -> 0 | E65: =B65/(24*J65) -> 0.14724181 | F65: 0 | G65: 0 | H65: =(G65-F65)*24*60 -> 0 | I65: =H65/60 -> 0 | J65: 2411 | L65: =J65*12 -> 28932 | M65: =K65*I65 -> 0 | N65: =(L65-M65)/L65 -> 1 | O65: =E65/N65 -> 0.14724181 | Q65: =O65*J65*24 -> 8520 | R65: =Q65-B65 -> 0
N66: =AVERAGE(N35:N65) -> 0.99574373
A67: 45901 | B67: =Data_Entry!P157 -> 11910 | C67: 0 | D67: =Data_Entry!V156 -> 0 | E67: =B67/(24*J67) -> 0.20582746 | F67: 0 | G67: 0 | H67: =(G67-F67)*24*60 -> 0 | I67: =H67/60 -> 0 | J67: 2411 | L67: =J67*12 -> 28932 | M67: =K67*I67 -> 0 | N67: =(L67-M67)/L67 -> 1 | O67: =E67/N67 -> 0.20582746 | Q67: =O67*J67*24 -> 11910 | R67: =Q67-B67 -> 0
A68: 45902 | B68: =Data_Entry!P158 -> 12450 | C68: 0 | D68: =Data_Entry!V157 -> 0 | E68: =B68/(24*J68) -> 0.21515968 | F68: 0 | G68: 0 | H68: =(G68-F68)*24*60 -> 0 | I68: =H68/60 -> 0 | J68: 2411 | L68: =J68*12 -> 28932 | M68: =K68*I68 -> 0 | N68: =(L68-M68)/L68 -> 1 | O68: =E68/N68 -> 0.21515968 | Q68: =O68*J68*24 -> 12450 | R68: =Q68-B68 -> 0
A69: 45903 | B69: =Data_Entry!P159 -> 6030 | C69: 0 | D69: =Data_Entry!V158 -> 0 | E69: =B69/(24*J69) -> 0.10420987 | F69: 0 | G69: 0 | H69: =(G69-F69)*24*60 -> 0 | I69: =H69/60 -> 0 | J69: 2411 | L69: =J69*12 -> 28932 | M69: =K69*I69 -> 0 | N69: =(L69-M69)/L69 -> 1 | O69: =E69/N69 -> 0.10420987 | Q69: =O69*J69*24 -> 6030 | R69: =Q69-B69 -> 0
A70: 45904 | B70: =Data_Entry!P160 -> 5430 | C70: 0 | D70: =Data_Entry!V159 -> 0 | E70: =B70/(24*J70) -> 0.09384073 | F70: 0 | G70: 0 | H70: =(G70-F70)*24*60 -> 0 | I70: =H70/60 -> 0 | J70: 2411 | L70: =J70*12 -> 28932 | M70: =K70*I70 -> 0 | N70: =(L70-M70)/L70 -> 1 | O70: =E70/N70 -> 0.09384073 | Q70: =O70*J70*24 -> 5430 | R70: =Q70-B70 -> 0
A71: 45905 | B71: =Data_Entry!P161 -> 3420 | C71: 0 | D71: =Data_Entry!V160 -> 0 | E71: =B71/(24*J71) -> 0.059104106 | F71: 0 | G71: 0 | H71: =(G71-F71)*24*60 -> 0 | I71: =H71/60 -> 0 | J71: 2411 | L71: =J71*12 -> 28932 | M71: =K71*I71 -> 0 | N71: =(L71-M71)/L71 -> 1 | O71: =E71/N71 -> 0.059104106 | Q71: =O71*J71*24 -> 3420 | R71: =Q71-B71 -> 0
A72: 45906 | B72: =Data_Entry!P162 -> 3120 | C72: 0 | D72: =Data_Entry!V161 -> 0 | E72: =B72/(24*J72) -> 0.053919535 | F72: 0 | G72: 0 | H72: =(G72-F72)*24*60 -> 0 | I72: =H72/60 -> 0 | J72: 2411 | L72: =J72*12 -> 28932 | M72: =K72*I72 -> 0 | N72: =(L72-M72)/L72 -> 1 | O72: =E72/N72 -> 0.053919535 | Q72: =O72*J72*24 -> 3120 | R72: =Q72-B72 -> 0
A73: 45907 | B73: =Data_Entry!P163 -> 3600 | C73: 0 | D73: =Data_Entry!V162 -> 0 | E73: =B73/(24*J73) -> 0.062214849 | F73: 0 | G73: 0 | H73: =(G73-F73)*24*60 -> 0 | I73: =H73/60 -> 0 | J73: 2411 | L73: =J73*12 -> 28932 | M73: =K73*I73 -> 0 | N73: =(L73-M73)/L73 -> 1 | O73: =E73/N73 -> 0.062214849 | Q73: =O73*J73*24 -> 3600 | R73: =Q73-B73 -> 0
A74: 45908 | B74: =Data_Entry!P164 -> 11250 | C74: 0 | D74: =Data_Entry!V163 -> 0 | E74: =B74/(24*J74) -> 0.1944214 | F74: 0 | G74: 0 | H74: =(G74-F74)*24*60 -> 0 | I74: =H74/60 -> 0 | J74: 2411 | L74: =J74*12 -> 28932 | M74: =K74*I74 -> 0 | N74: =(L74-M74)/L74 -> 1 | O74: =E74/N74 -> 0.1944214 | Q74: =O74*J74*24 -> 11250 | R74: =Q74-B74 -> 0
A75: 45909 | B75: =Data_Entry!P165 -> 10350 | C75: 0 | D75: =Data_Entry!V164 -> 0 | E75: =B75/(24*J75) -> 0.17886769 | F75: 0 | G75: 0 | H75: =(G75-F75)*24*60 -> 0 | I75: =H75/60 -> 0 | J75: 2411 | L75: =J75*12 -> 28932 | M75: =K75*I75 -> 0 | N75: =(L75-M75)/L75 -> 1 | O75: =E75/N75 -> 0.17886769 | Q75: =O75*J75*24 -> 10350 | R75: =Q75-B75 -> 0
A76: 45910 | B76: =Data_Entry!P166 -> 14070 | C76: 0 | D76: =Data_Entry!V165 -> 0 | E76: =B76/(24*J76) -> 0.24315637 | F76: 0 | G76: 0 | H76: =(G76-F76)*24*60 -> 0 | I76: =H76/60 -> 0 | J76: 2411 | L76: =J76*12 -> 28932 | M76: =K76*I76 -> 0 | N76: =(L76-M76)/L76 -> 1 | O76: =E76/N76 -> 0.24315637 | Q76: =O76*J76*24 -> 14070 | R76: =Q76-B76 -> 0
A77: 45911 | B77: =Data_Entry!P167 -> 12210 | C77: 0 | D77: =Data_Entry!V166 -> 0 | E77: =B77/(24*J77) -> 0.21101203 | F77: 0 | G77: 0 | H77: =(G77-F77)*24*60 -> 0 | I77: =H77/60 -> 0 | J77: 2411 | L77: =J77*12 -> 28932 | M77: =K77*I77 -> 0 | N77: =(L77-M77)/L77 -> 1 | O77: =E77/N77 -> 0.21101203 | Q77: =O77*J77*24 -> 12210 | R77: =Q77-B77 -> 0
A78: 45912 | B78: =Data_Entry!P168 -> 12450 | C78: 0 | D78: =Data_Entry!V167 -> 0 | E78: =B78/(24*J78) -> 0.21515968 | F78: 0 | G78: 0 | H78: =(G78-F78)*24*60 -> 0 | I78: =H78/60 -> 0 | J78: 2411 | L78: =J78*12 -> 28932 | M78: =K78*I78 -> 0 | N78: =(L78-M78)/L78 -> 1 | O78: =E78/N78 -> 0.21515968 | Q78: =O78*J78*24 -> 12450 | R78: =Q78-B78 -> 0
... A96: 45930 | B96: =Data_Entry!P186 -> 5550 | C96: 0 | D96: =Data_Entry!V185 -> 1.22 | E96: =B96/(24*J96) -> 0.095914558 | F96: 0 | G96: 0 | H96: =(G96-F96)*24*60 -> 0 | I96: =H96/60 -> 0 | J96: 2411 | L96: =J96*12 -> 28932 | M96: =K96*I96 -> 0 | N96: =(L96-M96)/L96 -> 1 | O96: =E96/N96 -> 0.095914558 | Q96: =O96*J96*24 -> 5550 | R96: =Q96-B96 -> 0
A97: 45931 | B97: =Data_Entry!P186 -> 5550 | C97: 0 | D97: =Data_Entry!V186 -> 1.61 | E97: =B97/(24*J97) -> 0.095914558 | F97: 0 | G97: 0 | H97: =(G97-F97)*24*60 -> 0 | I97: =H97/60 -> 0 | J97: 2411 | L97: =J97*12 -> 28932 | M97: =K97*I97 -> 0 | N97: =(L97-M97)/L97 -> 1 | O97: =E97/N97 -> 0.095914558 | Q97: =O97*J97*24 -> 5550 | R97: =Q97-B97 -> 0
A98: 45932 | B98: =Data_Entry!P187 -> 7110 | C98: 0 | D98: =Data_Entry!V187 -> 2.03 | E98: =B98/(24*J98) -> 0.12287433 | F98: 0 | G98: 0 | H98: =(G98-F98)*24*60 -> 0 | I98: =H98/60 -> 0 | J98: 2411 | L98: =J98*12 -> 28932 | M98: =K98*I98 -> 0 | N98: =(L98-M98)/L98 -> 1 | O98: =E98/N98 -> 0.12287433 | Q98: =O98*J98*24 -> 7110 | R98: =Q98-B98 -> 0
A99: 45933 | B99: =Data_Entry!P188 -> 9210 | C99: 0 | D99: =Data_Entry!V188 -> 4.45 | E99: =B99/(24*J99) -> 0.15916632 | F99: 0 | G99: 0 | H99: =(G99-F99)*24*60 -> 0 | I99: =H99/60 -> 0 | J99: 2411 | L99: =J99*12 -> 28932 | M99: =K99*I99 -> 0 | N99: =(L99-M99)/L99 -> 1 | O99: =E99/N99 -> 0.15916632 | Q99: =O99*J99*24 -> 9210 | R99: =Q99-B99 -> 0
A100: 45934 | B100: =Data_Entry!P189 -> 13440 | C100: 0 | D100: =Data_Entry!V189 -> 4.57 | E100: =B100/(24*J100) -> 0.23226877 | F100: 0 | G100: 0 | H100: =(G100-F100)*24*60 -> 0 | I100: =H100/60 -> 0 | J100: 2411 | L100: =J100*12 -> 28932 | M100: =K100*I100 -> 0 | N100: =(L100-M100)/L100 -> 1 | O100: =E100/N100 -> 0.23226877 | Q100: =O100*J100*24 -> 13440 | R100: =Q100-B100 -> 0
A101: 45935 | B101: =Data_Entry!P190 -> 9570 | C101: 0 | D101: =Data_Entry!V190 -> 4.59 | E101: =B101/(24*J101) -> 0.16538781 | F101: 0 | G101: 0 | H101: =(G101-F101)*24*60 -> 0 | I101: =H101/60 -> 0 | J101: 2411 | L101: =J101*12 -> 28932 | M101: =K101*I101 -> 0 | N101: =(L101-M101)/L101 -> 1 | O101: =E101/N101 -> 0.16538781 | Q101: =O101*J101*24 -> 9570 | R101: =Q101-B101 -> 0
A102: 45936 | B102: =Data_Entry!P191 -> 11700 | C102: 0 | D102: =Data_Entry!V191 -> 4.79 | E102: =B102/(24*J102) -> 0.20219826 | F102: 0 | G102: 0 | H102: =(G102-F102)*24*60 -> 0 | I102: =H102/60 -> 0 | J102: 2411 | L102: =J102*12 -> 28932 | M102: =K102*I102 -> 0 | N102: =(L102-M102)/L102 -> 1 | O102: =E102/N102 -> 0.20219826 | Q102: =O102*J102*24 -> 11700 | R102: =Q102-B102 -> 0
A103: 45937 | B103: =Data_Entry!P192 -> 12240 | C103: 0 | D103: =Data_Entry!V192 -> 4.85 | E103: =B103/(24*J103) -> 0.21153049 | F103: 0 | G103: 0 | H103: =(G103-F103)*24*60 -> 0 | I103: =H103/60 -> 0 | J103: 2411 | L103: =J103*12 -> 28932 | M103: =K103*I103 -> 0 | N103: =(L103-M103)/L103 -> 1 | O103: =E103/N103 -> 0.21153049 | Q103: =O103*J103*24 -> 12240 | R103: =Q103-B103 -> 0
A104: 45938 | B104: =Data_Entry!P193 -> 12420 | C104: 7 | D104: =Data_Entry!V193 -> 4.32 | E104: =B104/(24*J104) -> 0.21464123 | F104: 0.38541667 | G104: 0.41666667 | H104: =(G104-F104)*24*60 -> 45 | I104: =H104/60 -> 0.75 | J104: 2411 | K104: 2411 | L104: =J104*12 -> 28932 | M104: =K104*I104 -> 1808.25 | N104: =(L104-M104)/L104 -> 0.9375 | O104: =E104/N104 -> 0.22895064 | Q104: =O104*J104*24 -> 13248 | R104: =Q104-B104 -> 828
A105: 45939 | B105: =Data_Entry!P194 -> 9270 | C105: 0 | D105: =Data_Entry!V194 -> 4.69 | E105: =B105/(24*J105) -> 0.16020324 | F105: 0 | G105: 0 | H105: =(G105-F105)*24*60 -> 0 | I105: =H105/60 -> 0 | J105: 2411 | L105: =J105*12 -> 28932 | M105: =K105*I105 -> 0 | N105: =(L105-M105)/L105 -> 1 | O105: =E105/N105 -> 0.16020324 | Q105: =O105*J105*24 -> 9270 | R105: =Q105-B105 -> 0
A106: 45940 | B106: =Data_Entry!P195 -> 12450 | C106: 0 | D106: =Data_Entry!V195 -> 3.91 | E106: =B106/(24*J106) -> 0.21515968 | F106: 0 | G106: 0 | H106: =(G106-F106)*24*60 -> 0 | I106: =H106/60 -> 0 | J106: 2411 | L106: =J106*12 -> 28932 | M106: =K106*I106 -> 0 | N106: =(L106-M106)/L106 -> 1 | O106: =E106/N106 -> 0.21515968 | Q106: =O106*J106*24 -> 12450 | R106: =Q106-B106 -> 0
A107: 45941 | B107: =Data_Entry!P196 -> 12240 | C107: 0 | D107: =Data_Entry!V196 -> 3.48 | E107: =B107/(24*J107) -> 0.21153049 | F107: 0 | G107: 0 | H107: =(G107-F107)*24*60 -> 0 | I107: =H107/60 -> 0 | J107: 2411 | L107: =J107*12 -> 28932 | M107: =K107*I107 -> 0 | N107: =(L107-M107)/L107 -> 1 | O107: =E107/N107 -> 0.21153049 | Q107: =O107*J107*24 -> 12240 | R107: =Q107-B107 -> 0
A108: 45942 | B108: =Data_Entry!P197 -> 13140 | C108: 0 | D108: =Data_Entry!V197 -> 3.55 | E108: =B108/(24*J108) -> 0.2270842 | F108: 0 | G108: 0 | H108: =(G108-F108)*24*60 -> 0 | I108: =H108/60 -> 0 | J108: 2411 | L108: =J108*12 -> 28932 | M108: =K108*I108 -> 0 | N108: =(L108-M108)/L108 -> 1 | O108: =E108/N108 -> 0.2270842 | Q108: =O108*J108*24 -> 13140 | R108: =Q108-B108 -> 0
A109: 45943 | B109: =Data_Entry!P198 -> 12630 | C109: 0 | D109: =Data_Entry!V198 -> 3.54 | E109: =B109/(24*J109) -> 0.21827043 | F109: 0 | G109: 0 | H109: =(G109-F109)*24*60 -> 0 | I109: =H109/60 -> 0 | J109: 2411 | L109: =J109*12 -> 28932 | M109: =K109*I109 -> 0 | N109: =(L109-M109)/L109 -> 1 | O109: =E109/N109 -> 0.21827043 | Q109: =O109*J109*24 -> 12630 | R109: =Q109-B109 -> 0
A110: 45944 | B110: =Data_Entry!P199 -> 12630 | C110: 0 | D110: =Data_Entry!V199 -> 3.44 | E110: =B110/(24*J110) -> 0.21827043 | F110: 0 | G110: 0 | H110: =(G110-F110)*24*60 -> 0 | I110: =H110/60 -> 0 | J110: 2411 | L110: =J110*12 -> 28932 | M110: =K110*I110 -> 0 | N110: =(L110-M110)/L110 -> 1 | O110: =E110/N110 -> 0.21827043 | Q110: =O110*J110*24 -> 12630 | R110: =Q110-B110 -> 0
A111: 45945 | B111: =Data_Entry!P200 -> 12990 | C111: 0 | D111: =Data_Entry!V200 -> 3.55 | E111: =B111/(24*J111) -> 0.22449191 | F111: 0 | G111: 0 | H111: =(G111-F111)*24*60 -> 0 | I111: =H111/60 -> 0 | J111: 2411 | L111: =J111*12 -> 28932 | M111: =K111*I111 -> 0 | N111: =(L111-M111)/L111 -> 1 | O111: =E111/N111 -> 0.22449191 | Q111: =O111*J111*24 -> 12990 | R111: =Q111-B111 -> 0
A112: 45946 | B112: =Data_Entry!P201 -> 10800 | C112: 0 | D112: =Data_Entry!V201 -> 3.36 | E112: =B112/(24*J112) -> 0.18664455 | F112: 0 | G112: 0 | H112: =(G112-F112)*24*60 -> 0 | I112: =H112/60 -> 0 | J112: 2411 | L112: =J112*12 -> 28932 | M112: =K112*I112 -> 0 | N112: =(L112-M112)/L112 -> 1 | O112: =E112/N112 -> 0.18664455 | Q112: =O112*J112*24 -> 10800 | R112: =Q112-B112 -> 0
A113: 45947 | B113: =Data_Entry!P202 -> 11040 | C113: 0 | D113: =Data_Entry!V202 -> 3.23 | E113: =B113/(24*J113) -> 0.1907922 | F113: 0 | G113: 0 | H113: =(G113-F113)*24*60 -> 0 | I113: =H113/60 -> 0 | J113: 2411 | L113: =J113*12 -> 28932 | M113: =K113*I113 -> 0 | N113: =(L113-M113)/L113 -> 1 | O113: =E113/N113 -> 0.1907922 | Q113: =O113*J113*24 -> 11040 | R113: =Q113-B113 -> 0
A114: 45948 | B114: =Data_Entry!P203 -> 12840 | C114: 0 | D114: =Data_Entry!V203 -> 3.93 | E114: =B114/(24*J114) -> 0.22189963 | F114: 0 | G114: 0 | H114: =(G114-F114)*24*60 -> 0 | I114: =H114/60 -> 0 | J114: 2411 | L114: =J114*12 -> 28932 | M114: =K114*I114 -> 0 | N114: =(L114-M114)/L114 -> 1 | O114: =E114/N114 -> 0.22189963 | Q114: =O114*J114*24 -> 12840 | R114: =Q114-B114 -> 0
A115: 45949 | B115: =Data_Entry!P204 -> 12000 | C115: 0 | D115: =Data_Entry!V204 -> 4.46 | E115: =B115/(24*J115) -> 0.20738283 | F115: 0 | G115: 0 | H115: =(G115-F115)*24*60 -> 0 | I115: =H115/60 -> 0 | J115: 2411 | L115: =J115*12 -> 28932 | M115: =K115*I115 -> 0 | N115: =(L115-M115)/L115 -> 1 | O115: =E115/N115 -> 0.20738283 | Q115: =O115*J115*24 -> 12000 | R115: =Q115-B115 -> 0
A116: 45950 | B116: =Data_Entry!P205 -> 11760 | C116: 0 | D116: =Data_Entry!V205 -> 3.96 | E116: =B116/(24*J116) -> 0.20323517 | F116: 0 | G116: 0 | H116: =(G116-F116)*24*60 -> 0 | I116: =H116/60 -> 0 | J116: 2411 | L116: =J116*12 -> 28932 | M116: =K116*I116 -> 0 | N116: =(L116-M116)/L116 -> 1 | O116: =E116/N116 -> 0.20323517 | Q116: =O116*J116*24 -> 11760 | R116: =Q116-B116 -> 0
... A147: 45981 | B147: =Data_Entry!P236 -> 11160 | C147: 0 | D147: =Data_Entry!V236 -> 3.97 | E147: =B147/(24*J147) -> 0.19286603 | F147: 0 | G147: 0 | H147: =(G147-F147)*24*60 -> 0 | I147: =H147/60 -> 0 | J147: 2411 | L147: =J147*12 -> 28932 | M147: =K147*I147 -> 0 | N147: =(L147-M147)/L147 -> 1 | O147: =E147/N147 -> 0.19286603 | Q147: =O147*J147*24 -> 11160 | R147: =Q147-B147 -> 0
A148: 45982 | B148: =Data_Entry!P237 -> 10110 | C148: 7 | D148: =Data_Entry!V237 -> 3.66 | E148: =B148/(24*J148) -> 0.17472003 | F148: 0.66666667 | G148: 0.71527778 | H148: =(G148-F148)*24*60 -> 70 | I148: =H148/60 -> 1.1666667 | J148: 2411 | K148: 2411 | L148: =J148*12 -> 28932 | M148: =K148*I148 -> 2812.8333 | N148: =(L148-M148)/L148 -> 0.90277778 | O148: =E148/N148 -> 0.19353604 | Q148: =O148*J148*24 -> 11198.769 | R148: =Q148-B148 -> 1088.7692
A149: 45983 | B149: =Data_Entry!P238 -> 11100 | C149: 0 | D149: =Data_Entry!V238 -> 3.92 | E149: =B149/(24*J149) -> 0.19182912 | F149: 0 | G149: 0 | H149: =(G149-F149)*24*60 -> 0 | I149: =H149/60 -> 0 | J149: 2411 | L149: =J149*12 -> 28932 | M149: =K149*I149 -> 0 | N149: =(L149-M149)/L149 -> 1 | O149: =E149/N149 -> 0.19182912 | Q149: =O149*J149*24 -> 11100 | R149: =Q149-B149 -> 0
A150: 45984 | B150: =Data_Entry!P239 -> 11370 | C150: 0 | D150: =Data_Entry!V239 -> 4.02 | E150: =B150/(24*J150) -> 0.19649523 | F150: 0 | G150: 0 | H150: =(G150-F150)*24*60 -> 0 | I150: =H150/60 -> 0 | J150: 2411 | L150: =J150*12 -> 28932 | M150: =K150*I150 -> 0 | N150: =(L150-M150)/L150 -> 1 | O150: =E150/N150 -> 0.19649523 | Q150: =O150*J150*24 -> 11370 | R150: =Q150-B150 -> 0
A151: 45985 | B151: =Data_Entry!P240 -> 12000 | C151: 0 | D151: =Data_Entry!V240 -> 4.11 | E151: =B151/(24*J151) -> 0.20738283 | F151: 0 | G151: 0 | H151: =(G151-F151)*24*60 -> 0 | I151: =H151/60 -> 0 | J151: 2411 | L151: =J151*12 -> 28932 | M151: =K151*I151 -> 0 | N151: =(L151-M151)/L151 -> 1 | O151: =E151/N151 -> 0.20738283 | Q151: =O151*J151*24 -> 12000 | R151: =Q151-B151 -> 0
A152: 45986 | B152: =Data_Entry!P241 -> 10740 | C152: 0 | D152: =Data_Entry!V241 -> 3.9 | E152: =B152/(24*J152) -> 0.18560763 | F152: 0 | G152: 0 | H152: =(G152-F152)*24*60 -> 0 | I152: =H152/60 -> 0 | J152: 2411 | L152: =J152*12 -> 28932 | M152: =K152*I152 -> 0 | N152: =(L152-M152)/L152 -> 1 | O152: =E152/N152 -> 0.18560763 | Q152: =O152*J152*24 -> 10740 | R152: =Q152-B152 -> 0
A153: 45987 | B153: =Data_Entry!P242 -> 10050 | C153: 0 | D153: =Data_Entry!V242 -> 3.7 | E153: =B153/(24*J153) -> 0.17368312 | F153: 0 | G153: 0 | H153: =(G153-F153)*24*60 -> 0 | I153: =H153/60 -> 0 | J153: 2411 | L153: =J153*12 -> 28932 | M153: =K153*I153 -> 0 | N153: =(L153-M153)/L153 -> 1 | O153: =E153/N153 -> 0.17368312 | Q153: =O153*J153*24 -> 10050 | R153: =Q153-B153 -> 0
A154: 45988 | B154: =Data_Entry!P243 -> 9450 | C154: 0 | D154: =Data_Entry!V243 -> 3.42 | E154: =B154/(24*J154) -> 0.16331398 | F154: 0 | G154: 0 | H154: =(G154-F154)*24*60 -> 0 | I154: =H154/60 -> 0 | J154: 2411 | L154: =J154*12 -> 28932 | M154: =K154*I154 -> 0 | N154: =(L154-M154)/L154 -> 1 | O154: =E154/N154 -> 0.16331398 | Q154: =O154*J154*24 -> 9450 | R154: =Q154-B154 -> 0
A155: 45989 | B155: =Data_Entry!P244 -> 8460 | C155: 0 | D155: =Data_Entry!V244 -> 3.13 | E155: =B155/(24*J155) -> 0.14620489 | F155: 0 | G155: 0 | H155: =(G155-F155)*24*60 -> 0 | I155: =H155/60 -> 0 | J155: 2411 | L155: =J155*12 -> 28932 | M155: =K155*I155 -> 0 | N155: =(L155-M155)/L155 -> 1 | O155: =E155/N155 -> 0.14620489 | Q155: =O155*J155*24 -> 8460 | R155: =Q155-B155 -> 0
A156: 45990 | B156: =Data_Entry!P245 -> 9060 | C156: 0 | D156: =Data_Entry!V245 -> 3.34 | E156: =B156/(24*J156) -> 0.15657404 | F156: 0 | G156: 0 | H156: =(G156-F156)*24*60 -> 0 | I156: =H156/60 -> 0 | J156: 2411 | L156: =J156*12 -> 28932 | M156: =K156*I156 -> 0 | N156: =(L156-M156)/L156 -> 1 | O156: =E156/N156 -> 0.15657404 | Q156: =O156*J156*24 -> 9060 | R156: =Q156-B156 -> 0
A157: 45991 | B157: =Data_Entry!P246 -> 8670 | C157: 0 | D157: =Data_Entry!V246 -> 3.55 | E157: =B157/(24*J157) -> 0.14983409 | F157: 0 | G157: 0 | H157: =(G157-F157)*24*60 -> 0 | I157: =H157/60 -> 0 | J157: 2411 | L157: =J157*12 -> 28932 | M157: =K157*I157 -> 0 | N157: =(L157-M157)/L157 -> 1 | O157: =E157/N157 -> 0.14983409 | Q157: =O157*J157*24 -> 8670 | R157: =Q157-B157 -> 0
A158: 45992 | B158: =Data_Entry!P247 -> 11940 | C158: 0 | D158: =Data_Entry!V247 -> 3.81 | E158: =B158/(24*J158) -> 0.20634591 | F158: 0 | G158: 0 | H158: =(G158-F158)*24*60 -> 0 | I158: =H158/60 -> 0 | J158: 2411 | L158: =J158*12 -> 28932 | M158: =K158*I158 -> 0 | N158: =(L158-M158)/L158 -> 1 | O158: =E158/N158 -> 0.20634591 | Q158: =O158*J158*24 -> 11940 | R158: =Q158-B158 -> 0
A159: 45993 | B159: =Data_Entry!P248 -> 9390 | C159: 0 | D159: =Data_Entry!V248 -> 3.5 | E159: =B159/(24*J159) -> 0.16227706 | F159: 0 | G159: 0 | H159: =(G159-F159)*24*60 -> 0 | I159: =H159/60 -> 0 | J159: 2411 | L159: =J159*12 -> 28932 | M159: =K159*I159 -> 0 | N159: =(L159-M159)/L159 -> 1 | O159: =E159/N159 -> 0.16227706 | Q159: =O159*J159*24 -> 9390 | R159: =Q159-B159 -> 0
A160: 45994 | B160: =Data_Entry!P249 -> 10560 | C160: 0 | D160: =Data_Entry!V249 -> 3.79 | E160: =B160/(24*J160) -> 0.18249689 | F160: 0 | G160: 0 | H160: =(G160-F160)*24*60 -> 0 | I160: =H160/60 -> 0 | J160: 2411 | L160: =J160*12 -> 28932 | M160: =K160*I160 -> 0 | N160: =(L160-M160)/L160 -> 1 | O160: =E160/N160 -> 0.18249689 | Q160: =O160*J160*24 -> 10560 | R160: =Q160-B160 -> 0
... A175: 46009 | B175: =Data_Entry!P264 -> 10200 | C175: 0 | D175: =Data_Entry!V264 -> 3.99 | E175: =B175/(24*J175) -> 0.1762754 | F175: 0 | G175: 0 | H175: =(G175-F175)*24*60 -> 0 | I175: =H175/60 -> 0 | J175: 2411 | L175: =J175*12 -> 28932 | M175: =K175*I175 -> 0 | N175: =(L175-M175)/L175 -> 1 | O175: =E175/N175 -> 0.1762754 | Q175: =O175*J175*24 -> 10200 | R175: =Q175-B175 -> 0
A176: 46010 | B176: =Data_Entry!P265 -> 11640 | C176: 7 | D176: =Data_Entry!V265 -> 3.65 | E176: =B176/(24*J176) -> 0.20116134 | F176: 0.45138889 | G176: 0.47916667 | H176: =(G176-F176)*24*60 -> 40 | I176: =H176/60 -> 0.66666667 | J176: 2411 | K176: 2411 | L176: =J176*12 -> 28932 | M176: =K176*I176 -> 1607.3333 | N176: =(L176-M176)/L176 -> 0.94444444 | O176: =E176/N176 -> 0.21299436 | Q176: =O176*J176*24 -> 12324.706 | R176: =Q176-B176 -> 684.70588
A177: 46011 | B177: =Data_Entry!P266 -> 11940 | C177: 0 | D177: =Data_Entry!V266 -> 4.1 | E177: =B177/(24*J177) -> 0.20634591 | F177: 0 | G177: 0 | H177: =(G177-F177)*24*60 -> 0 | I177: =H177/60 -> 0 | J177: 2411 | L177: =J177*12 -> 28932 | M177: =K177*I177 -> 0 | N177: =(L177-M177)/L177 -> 1 | O177: =E177/N177 -> 0.20634591 | Q177: =O177*J177*24 -> 11940 | R177: =Q177-B177 -> 0
...

Sheet Grid Availiblity
A1: Date | B1: ABT Export Gen | C1: GHI | D1: CUF% | E1: Out | F1: In | G1: Total Minute | H1: Outage Hrs. | I1: Plant Capacity | J1: Outage Capacity | K1: Plant Capacity Ratio | L1: Outage Ratio | M1: Grid Availiblity | N1: G.C CUF | O1: G.C Generation | P1: Grid Unit Lose
A2: 45839 | B2: =Data_Entry!P94 -> 9120 | C2: =Data_Entry!V94 -> 4.07 | D2: =B2/(24*I2) -> 0.15761095 | E2: 0 | F2: 0 | G2: =(F2-E2)*24*60 -> 0 | H2: =G2/60 -> 0 | I2: 2411 | K2: =I2*12 -> 28932 | L2: =J2*H2 -> 0 | M2: =(K2-L2)/K2 -> 1 | N2: =D2/M2 -> 0.15761095 | O2: =N2*I2*24 -> 9120 | P2: =O2-B2 -> 0
A3: 45840 | B3: =Data_Entry!P95 -> 4620 | C3: =Data_Entry!V95 -> 1.77 | D3: =B3/(24*I3) -> 0.079842389 | E3: 0 | F3: 0 | G3: =(F3-E3)*24*60 -> 0 | H3: =G3/60 -> 0 | I3: 2411 | K3: =I3*12 -> 28932 | L3: =J3*H3 -> 0 | M3: =(K3-L3)/K3 -> 1 | N3: =D3/M3 -> 0.079842389 | O3: =N3*I3*24 -> 4620 | P3: =O3-B3 -> 0
A4: 45841 | B4: =Data_Entry!P96 -> 4050 | C4: =Data_Entry!V96 -> 1.54 | D4: =B4/(24*I4) -> 0.069991705 | E4: 0 | F4: 0 | G4: =(F4-E4)*24*60 -> 0 | H4: =G4/60 -> 0 | I4: 2411 | K4: =I4*12 -> 28932 | L4: =J4*H4 -> 0 | M4: =(K4-L4)/K4 -> 1 | N4: =D4/M4 -> 0.069991705 | O4: =N4*I4*24 -> 4050 | P4: =O4-B4 -> 0
A5: 45842 | B5: =Data_Entry!P97 -> 5580 | C5: =Data_Entry!V97 -> 2.25 | D5: =B5/(24*I5) -> 0.096433015 | E5: 0 | F5: 0 | G5: =(F5-E5)*24*60 -> 0 | H5: =G5/60 -> 0 | I5: 2411 | K5: =I5*12 -> 28932 | L5: =J5*H5 -> 0 | M5: =(K5-L5)/K5 -> 1 | N5: =D5/M5 -> 0.096433015 | O5: =N5*I5*24 -> 5580 | P5: =O5-B5 -> 0
A6: 45843 | B6: =Data_Entry!P98 -> 3210 | C6: =Data_Entry!V98 -> 1.2 | D6: =B6/(24*I6) -> 0.055474907 | E6: 0 | F6: 0 | G6: =(F6-E6)*24*60 -> 0 | H6: =G6/60 -> 0 | I6: 2411 | K6: =I6*12 -> 28932 | L6: =J6*H6 -> 0 | M6: =(K6-L6)/K6 -> 1 | N6: =D6/M6 -> 0.055474907 | O6: =N6*I6*24 -> 3210 | P6: =O6-B6 -> 0
A7: 45844 | B7: =Data_Entry!P99 -> 4980 | C7: =Data_Entry!V99 -> 1.93 | D7: =B7/(24*I7) -> 0.086063874 | E7: 0 | F7: 0 | G7: =(F7-E7)*24*60 -> 0 | H7: =G7/60 -> 0 | I7: 2411 | K7: =I7*12 -> 28932 | L7: =J7*H7 -> 0 | M7: =(K7-L7)/K7 -> 1 | N7: =D7/M7 -> 0.086063874 | O7: =N7*I7*24 -> 4980 | P7: =O7-B7 -> 0
A8: 45845 | B8: =Data_Entry!P100 -> 3690 | C8: =Data_Entry!V100 -> 1.43 | D8: =B8/(24*I8) -> 0.06377022 | E8: 0 | F8: 0 | G8: =(F8-E8)*24*60 -> 0 | H8: =G8/60 -> 0 | I8: 2411 | K8: =I8*12 -> 28932 | L8: =J8*H8 -> 0 | M8: =(K8-L8)/K8 -> 1 | N8: =D8/M8 -> 0.06377022 | O8: =N8*I8*24 -> 3690 | P8: =O8-B8 -> 0
A9: 45846 | B9: =Data_Entry!P101 -> 6990 | C9: =Data_Entry!V101 -> 2.81 | D9: =B9/(24*I9) -> 0.1208005 | E9: 0 | F9: 0 | G9: =(F9-E9)*24*60 -> 0 | H9: =G9/60 -> 0 | I9: 2411 | K9: =I9*12 -> 28932 | L9: =J9*H9 -> 0 | M9: =(K9-L9)/K9 -> 1 | N9: =D9/M9 -> 0.1208005 | O9: =N9*I9*24 -> 6990 | P9: =O9-B9 -> 0
A10: 45847 | B10: =Data_Entry!P102 -> 11880 | C10: =Data_Entry!V102 -> 5.06 | D10: =B10/(24*I10) -> 0.205309 | E10: 0 | F10: 0 | G10: =(F10-E10)*24*60 -> 0 | H10: =G10/60 -> 0 | I10: 2411 | K10: =I10*12 -> 28932 | L10: =J10*H10 -> 0 | M10: =(K10-L10)/K10 -> 1 | N10: =D10/M10 -> 0.205309 | O10: =N10*I10*24 -> 11880 | P10: =O10-B10 -> 0
A11: 45848 | B11: =Data_Entry!P103 -> 4950 | C11: =Data_Entry!V103 -> 2.01 | D11: =B11/(24*I11) -> 0.085545417 | E11: 0 | F11: 0 | G11: =(F11-E11)*24*60 -> 0 | H11: =G11/60 -> 0 | I11: 2411 | K11: =I11*12 -> 28932 | L11: =J11*H11 -> 0 | M11: =(K11-L11)/K11 -> 1 | N11: =D11/M11 -> 0.085545417 | O11: =N11*I11*24 -> 4950 | P11: =O11-B11 -> 0
A12: 45849 | B12: =Data_Entry!P104 -> 3540 | C12: =Data_Entry!V104 -> 1.32 | D12: =B12/(24*I12) -> 0.061177934 | E12: 0 | F12: 0 | G12: =(F12-E12)*24*60 -> 0 | H12: =G12/60 -> 0 | I12: 2411 | K12: =I12*12 -> 28932 | L12: =J12*H12 -> 0 | M12: =(K12-L12)/K12 -> 1 | N12: =D12/M12 -> 0.061177934 | O12: =N12*I12*24 -> 3540 | P12: =O12-B12 -> 0
A13: 45850 | B13: =Data_Entry!P105 -> 10290 | C13: =Data_Entry!V105 -> 3.95 | D13: =B13/(24*I13) -> 0.17783078 | E13: 0 | F13: 0 | G13: =(F13-E13)*24*60 -> 0 | H13: =G13/60 -> 0 | I13: 2411 | K13: =I13*12 -> 28932 | L13: =J13*H13 -> 0 | M13: =(K13-L13)/K13 -> 1 | N13: =D13/M13 -> 0.17783078 | O13: =N13*I13*24 -> 10290 | P13: =O13-B13 -> 0
... A24: 45861 | B24: =Data_Entry!P116 -> 6090 | C24: =Data_Entry!V116 -> 2.6 | D24: =B24/(24*I24) -> 0.10524679 | E24: 0 | F24: 0 | G24: =(F24-E24)*24*60 -> 0 | H24: =G24/60 -> 0 | I24: 2411 | K24: =I24*12 -> 28932 | L24: =J24*H24 -> 0 | M24: =(K24-L24)/K24 -> 1 | N24: =D24/M24 -> 0.10524679 | O24: =N24*I24*24 -> 6090 | P24: =O24-B24 -> 0
A25: 45862 | B25: =Data_Entry!P117 -> 3720 | C25: =Data_Entry!V117 -> 1.49 | D25: =B25/(24*I25) -> 0.064288677 | E25: 0.66666667 | F25: 0.78125 | G25: =(F25-E25)*24*60 -> 165 | H25: =G25/60 -> 2.75 | I25: 2411 | J25: 2411 | K25: =I25*12 -> 28932 | L25: =J25*H25 -> 6630.25 | M25: =(K25-L25)/K25 -> 0.77083333 | N25: =D25/M25 -> 0.083401527 | O25: =N25*I25*24 -> 4825.9459 | P25: =O25-B25 -> 1105.9459
A26: 45863 | B26: =Data_Entry!P118 -> 7800 | C26: =Data_Entry!V118 -> 3.14 | D26: =B26/(24*I26) -> 0.13479884 | E26: 0 | F26: 0 | G26: =(F26-E26)*24*60 -> 0 | H26: =G26/60 -> 0 | I26: 2411 | K26: =I26*12 -> 28932 | L26: =J26*H26 -> 0 | M26: =(K26-L26)/K26 -> 1 | N26: =D26/M26 -> 0.13479884 | O26: =N26*I26*24 -> 7800 | P26: =O26-B26 -> 0
A27: 45864 | B27: =Data_Entry!P119 -> 5550 | C27: =Data_Entry!V119 -> 2.26 | D27: =B27/(24*I27) -> 0.095914558 | E27: 0 | F27: 0 | G27: =(F27-E27)*24*60 -> 0 | H27: =G27/60 -> 0 | I27: 2411 | K27: =I27*12 -> 28932 | L27: =J27*H27 -> 0 | M27: =(K27-L27)/K27 -> 1 | N27: =D27/M27 -> 0.095914558 | O27: =N27*I27*24 -> 5550 | P27: =O27-B27 -> 0
A28: 45865 | B28: =Data_Entry!P120 -> 4260 | C28: =Data_Entry!V120 -> 1.6 | D28: =B28/(24*I28) -> 0.073620904 | E28: 0 | F28: 0 | G28: =(F28-E28)*24*60 -> 0 | H28: =G28/60 -> 0 | I28: 2411 | K28: =I28*12 -> 28932 | L28: =J28*H28 -> 0 | M28: =(K28-L28)/K28 -> 1 | N28: =D28/M28 -> 0.073620904 | O28: =N28*I28*24 -> 4260 | P28: =O28-B28 -> 0
A29: 45866 | B29: =Data_Entry!P121 -> 5520 | C29: =Data_Entry!V121 -> 2.18 | D29: =B29/(24*I29) -> 0.095396101 | E29: 0 | F29: 0 | G29: =(F29-E29)*24*60 -> 0 | H29: =G29/60 -> 0 | I29: 2411 | K29: =I29*12 -> 28932 | L29: =J29*H29 -> 0 | M29: =(K29-L29)/K29 -> 1 | N29: =D29/M29 -> 0.095396101 | O29: =N29*I29*24 -> 5520 | P29: =O29-B29 -> 0
A30: 45867 | B30: =Data_Entry!P122 -> 4830 | C30: =Data_Entry!V122 -> 1.89 | D30: =B30/(24*I30) -> 0.083471589 | E30: 0 | F30: 0 | G30: =(F30-E30)*24*60 -> 0 | H30: =G30/60 -> 0 | I30: 2411 | K30: =I30*12 -> 28932 | L30: =J30*H30 -> 0 | M30: =(K30-L30)/K30 -> 1 | N30: =D30/M30 -> 0.083471589 | O30: =N30*I30*24 -> 4830 | P30: =O30-B30 -> 0
A31: 45868 | B31: =Data_Entry!P123 -> 7440 | C31: =Data_Entry!V123 -> 3.4 | D31: =B31/(24*I31) -> 0.12857735 | E31: 0 | F31: 0 | G31: =(F31-E31)*24*60 -> 0 | H31: =G31/60 -> 0 | I31: 2411 | K31: =I31*12 -> 28932 | L31: =J31*H31 -> 0 | M31: =(K31-L31)/K31 -> 1 | N31: =D31/M31 -> 0.12857735 | O31: =N31*I31*24 -> 7440 | P31: =O31-B31 -> 0
A32: 45869 | B32: =Data_Entry!P124 -> 6030 | C32: =Data_Entry!V124 -> 2.19 | D32: =B32/(24*I32) -> 0.10420987 | E32: 0 | F32: 0 | G32: =(F32-E32)*24*60 -> 0 | H32: =G32/60 -> 0 | I32: 2411 | K32: =I32*12 -> 28932 | L32: =J32*H32 -> 0 | M32: =(K32-L32)/K32 -> 1 | N32: =D32/M32 -> 0.10420987 | O32: =N32*I32*24 -> 6030 | P32: =O32-B32 -> 0
A34: 45870 | B34: =Data_Entry!P125 -> 6450 | C34: =Data_Entry!V125 -> 2.71 | D34: =B34/(24*I34) -> 0.11146827 | E34: 0 | F34: 0 | G34: =(F34-E34)*24*60 -> 0 | H34: =G34/60 -> 0 | I34: 2411 | K34: =I34*12 -> 28932 | L34: =J34*H34 -> 0 | M34: =(K34-L34)/K34 -> 1 | N34: =D34/M34 -> 0.11146827 | O34: =N34*I34*24 -> 6450 | P34: =O34-B34 -> 0
A35: 45871 | B35: =Data_Entry!P126 -> 7380 | C35: =Data_Entry!V126 -> 3.07 | D35: =B35/(24*I35) -> 0.12754044 | E35: 0 | F35: 0 | G35: =(F35-E35)*24*60 -> 0 | H35: =G35/60 -> 0 | I35: 2411 | K35: =I35*12 -> 28932 | L35: =J35*H35 -> 0 | M35: =(K35-L35)/K35 -> 1 | N35: =D35/M35 -> 0.12754044 | O35: =N35*I35*24 -> 7380 | P35: =O35-B35 -> 0
A36: 45872 | B36: =Data_Entry!P127 -> 5280 | C36: =Data_Entry!V127 -> 2.18 | D36: =B36/(24*I36) -> 0.091248445 | E36: 0 | F36: 0 | G36: =(F36-E36)*24*60 -> 0 | H36: =G36/60 -> 0 | I36: 2411 | K36: =I36*12 -> 28932 | L36: =J36*H36 -> 0 | M36: =(K36-L36)/K36 -> 1 | N36: =D36/M36 -> 0.091248445 | O36: =N36*I36*24 -> 5280 | P36: =O36-B36 -> 0
A37: 45873 | B37: =Data_Entry!P128 -> 5190 | C37: =Data_Entry!V128 -> 1.96 | D37: =B37/(24*I37) -> 0.089693073 | E37: 0 | F37: 0 | G37: =(F37-E37)*24*60 -> 0 | H37: =G37/60 -> 0 | I37: 2411 | K37: =I37*12 -> 28932 | L37: =J37*H37 -> 0 | M37: =(K37-L37)/K37 -> 1 | N37: =D37/M37 -> 0.089693073 | O37: =N37*I37*24 -> 5190 | P37: =O37-B37 -> 0
A38: 45874 | B38: =Data_Entry!P129 -> 7080 | C38: =Data_Entry!V129 -> 3 | D38: =B38/(24*I38) -> 0.12235587 | E38: 0.71388889 | F38: 0.72777778 | G38: =(F38-E38)*24*60 -> 20 | H38: =G38/60 -> 0.33333333 | I38: 2411 | J38: 2411 | K38: =I38*12 -> 28932 | L38: =J38*H38 -> 803.66667 | M38: =(K38-L38)/K38 -> 0.97222222 | N38: =D38/M38 -> 0.12585175 | O38: =N38*I38*24 -> 7282.2857 | P38: =O38-B38 -> 202.28571
A39: 45875 | B39: =Data_Entry!P130 -> 10620 | C39: =Data_Entry!V130 -> 4.33 | D39: =B39/(24*I39) -> 0.1835338 | E39: 0 | F39: 0 | G39: =(F39-E39)*24*60 -> 0 | H39: =G39/60 -> 0 | I39: 2411 | K39: =I39*12 -> 28932 | L39: =J39*H39 -> 0 | M39: =(K39-L39)/K39 -> 1 | N39: =D39/M39 -> 0.1835338 | O39: =N39*I39*24 -> 10620 | P39: =O39-B39 -> 0
A40: 45876 | B40: =Data_Entry!P131 -> 12330 | C40: =Data_Entry!V131 -> 5.09 | D40: =B40/(24*I40) -> 0.21308586 | E40: 0 | F40: 0 | G40: =(F40-E40)*24*60 -> 0 | H40: =G40/60 -> 0 | I40: 2411 | K40: =I40*12 -> 28932 | L40: =J40*H40 -> 0 | M40: =(K40-L40)/K40 -> 1 | N40: =D40/M40 -> 0.21308586 | O40: =N40*I40*24 -> 12330 | P40: =O40-B40 -> 0
A41: 45877 | B41: =Data_Entry!P132 -> 10380 | C41: =Data_Entry!V132 -> 4.32 | D41: =B41/(24*I41) -> 0.17938615 | E41: 0 | F41: 0 | G41: =(F41-E41)*24*60 -> 0 | H41: =G41/60 -> 0 | I41: 2411 | K41: =I41*12 -> 28932 | L41: =J41*H41 -> 0 | M41: =(K41-L41)/K41 -> 1 | N41: =D41/M41 -> 0.17938615 | O41: =N41*I41*24 -> 10380 | P41: =O41-B41 -> 0
A42: 45878 | B42: =Data_Entry!P133 -> 7770 | C42: =Data_Entry!V133 -> 3.13 | D42: =B42/(24*I42) -> 0.13428038 | E42: 0 | F42: 0 | G42: =(F42-E42)*24*60 -> 0 | H42: =G42/60 -> 0 | I42: 2411 | K42: =I42*12 -> 28932 | L42: =J42*H42 -> 0 | M42: =(K42-L42)/K42 -> 1 | N42: =D42/M42 -> 0.13428038 | O42: =N42*I42*24 -> 7770 | P42: =O42-B42 -> 0
A43: 45879 | B43: =Data_Entry!P134 -> 9000 | C43: =Data_Entry!V134 -> 3.41 | D43: =B43/(24*I43) -> 0.15553712 | E43: 0 | F43: 0 | G43: =(F43-E43)*24*60 -> 0 | H43: =G43/60 -> 0 | I43: 2411 | K43: =I43*12 -> 28932 | L43: =J43*H43 -> 0 | M43: =(K43-L43)/K43 -> 1 | N43: =D43/M43 -> 0.15553712 | O43: =N43*I43*24 -> 9000 | P43: =O43-B43 -> 0
A44: 45880 | B44: =Data_Entry!P135 -> 9870 | C44: =Data_Entry!V135 -> 3.67 | D44: =B44/(24*I44) -> 0.17057238 | E44: 0 | F44: 0 | G44: =(F44-E44)*24*60 -> 0 | H44: =G44/60 -> 0 | I44: 2411 | K44: =I44*12 -> 28932 | L44: =J44*H44 -> 0 | M44: =(K44-L44)/K44 -> 1 | N44: =D44/M44 -> 0.17057238 | O44: =N44*I44*24 -> 9870 | P44: =O44-B44 -> 0
A45: 45881 | B45: =Data_Entry!P136 -> 7980 | C45: =Data_Entry!V136 -> 2.94 | D45: =B45/(24*I45) -> 0.13790958 | E45: 0 | F45: 0 | G45: =(F45-E45)*24*60 -> 0 | H45: =G45/60 -> 0 | I45: 2411 | K45: =I45*12 -> 28932 | L45: =J45*H45 -> 0 | M45: =(K45-L45)/K45 -> 1 | N45: =D45/M45 -> 0.13790958 | O45: =N45*I45*24 -> 7980 | P45: =O45-B45 -> 0
A46: 45882 | B46: =Data_Entry!P137 -> 9090 | C46: =Data_Entry!V137 -> 3.69 | D46: =B46/(24*I46) -> 0.15709249 | E46: 0 | F46: 0 | G46: =(F46-E46)*24*60 -> 0 | H46: =G46/60 -> 0 | I46: 2411 | K46: =I46*12 -> 28932 | L46: =J46*H46 -> 0 | M46: =(K46-L46)/K46 -> 1 | N46: =D46/M46 -> 0.15709249 | O46: =N46*I46*24 -> 9090 | P46: =O46-B46 -> 0
A47: 45883 | B47: =Data_Entry!P138 -> 6960 | C47: =Data_Entry!V138 -> 2.7 | D47: =B47/(24*I47) -> 0.12028204 | E47: 0 | F47: 0 | G47: =(F47-E47)*24*60 -> 0 | H47: =G47/60 -> 0 | I47: 2411 | K47: =I47*12 -> 28932 | L47: =J47*H47 -> 0 | M47: =(K47-L47)/K47 -> 1 | N47: =D47/M47 -> 0.12028204 | O47: =N47*I47*24 -> 6960 | P47: =O47-B47 -> 0
A48: 45884 | B48: =Data_Entry!P139 -> 6720 | C48: =Data_Entry!V139 -> 3.05 | D48: =B48/(24*I48) -> 0.11613438 | E48: 0 | F48: 0 | G48: =(F48-E48)*24*60 -> 0 | H48: =G48/60 -> 0 | I48: 2411 | K48: =I48*12 -> 28932 | L48: =J48*H48 -> 0 | M48: =(K48-L48)/K48 -> 1 | N48: =D48/M48 -> 0.11613438 | O48: =N48*I48*24 -> 6720 | P48: =O48-B48 -> 0
A49: 45885 | B49: =Data_Entry!P140 -> 9210 | C49: =Data_Entry!V140 -> 3.53 | D49: =B49/(24*I49) -> 0.15916632 | E49: 0 | F49: 0 | G49: =(F49-E49)*24*60 -> 0 | H49: =G49/60 -> 0 | I49: 2411 | K49: =I49*12 -> 28932 | L49: =J49*H49 -> 0 | M49: =(K49-L49)/K49 -> 1 | N49: =D49/M49 -> 0.15916632 | O49: =N49*I49*24 -> 9210 | P49: =O49-B49 -> 0
A50: 45886 | B50: =Data_Entry!P141 -> 8220 | C50: =Data_Entry!V141 -> 3.05 | D50: =B50/(24*I50) -> 0.14205724 | E50: 0 | F50: 0 | G50: =(F50-E50)*24*60 -> 0 | H50: =G50/60 -> 0 | I50: 2411 | K50: =I50*12 -> 28932 | L50: =J50*H50 -> 0 | M50: =(K50-L50)/K50 -> 1 | N50: =D50/M50 -> 0.14205724 | O50: =N50*I50*24 -> 8220 | P50: =O50-B50 -> 0
... A64: 45900 | B64: =Data_Entry!P155 -> 7410 | C64: =Data_Entry!V155 -> 0 | D64: =B64/(24*I64) -> 0.1280589 | E64: 0 | F64: 0 | G64: =(F64-E64)*24*60 -> 0 | H64: =G64/60 -> 0 | I64: 2411 | K64: =I64*12 -> 28932 | L64: =J64*H64 -> 0 | M64: =(K64-L64)/K64 -> 1 | N64: =D64/M64 -> 0.1280589 | O64: =N64*I64*24 -> 7410 | P64: =O64-B64 -> 0
M65: =AVERAGE(M34:M64) -> 0.99910394
A66: 45901 | B66: =Data_Entry!P156 -> 8520 | C66: =Data_Entry!V156 -> 0 | D66: =B66/(24*I66) -> 0.14724181 | E66: 0 | F66: 0 | G66: =(F66-E66)*24*60 -> 0 | H66: =G66/60 -> 0 | I66: 2411 | K66: =I66*12 -> 28932 | L66: =J66*H66 -> 0 | M66: =(K66-L66)/K66 -> 1 | N66: =D66/M66 -> 0.14724181 | O66: =N66*I66*24 -> 8520 | P66: =O66-B66 -> 0
A67: 45902 | B67: =Data_Entry!P157 -> 11910 | C67: =Data_Entry!V157 -> 0 | D67: =B67/(24*I67) -> 0.20582746 | E67: 0 | F67: 0 | G67: =(F67-E67)*24*60 -> 0 | H67: =G67/60 -> 0 | I67: 2411 | K67: =I67*12 -> 28932 | L67: =J67*H67 -> 0 | M67: =(K67-L67)/K67 -> 1 | N67: =D67/M67 -> 0.20582746 | O67: =N67*I67*24 -> 11910 | P67: =O67-B67 -> 0
A68: 45903 | B68: =Data_Entry!P158 -> 12450 | C68: =Data_Entry!V158 -> 0 | D68: =B68/(24*I68) -> 0.21515968 | E68: 0 | F68: 0 | G68: =(F68-E68)*24*60 -> 0 | H68: =G68/60 -> 0 | I68: 2411 | K68: =I68*12 -> 28932 | L68: =J68*H68 -> 0 | M68: =(K68-L68)/K68 -> 1 | N68: =D68/M68 -> 0.21515968 | O68: =N68*I68*24 -> 12450 | P68: =O68-B68 -> 0
A69: 45904 | B69: =Data_Entry!P159 -> 6030 | C69: =Data_Entry!V159 -> 0 | D69: =B69/(24*I69) -> 0.10420987 | E69: 0 | F69: 0 | G69: =(F69-E69)*24*60 -> 0 | H69: =G69/60 -> 0 | I69: 2411 | K69: =I69*12 -> 28932 | L69: =J69*H69 -> 0 | M69: =(K69-L69)/K69 -> 1 | N69: =D69/M69 -> 0.10420987 | O69: =N69*I69*24 -> 6030 | P69: =O69-B69 -> 0
A70: 45905 | B70: =Data_Entry!P160 -> 5430 | C70: =Data_Entry!V160 -> 0 | D70: =B70/(24*I70) -> 0.09384073 | E70: 0 | F70: 0 | G70: =(F70-E70)*24*60 -> 0 | H70: =G70/60 -> 0 | I70: 2411 | K70: =I70*12 -> 28932 | L70: =J70*H70 -> 0 | M70: =(K70-L70)/K70 -> 1 | N70: =D70/M70 -> 0.09384073 | O70: =N70*I70*24 -> 5430 | P70: =O70-B70 -> 0
A71: 45906 | B71: =Data_Entry!P161 -> 3420 | C71: =Data_Entry!V161 -> 0 | D71: =B71/(24*I71) -> 0.059104106 | E71: 0 | F71: 0 | G71: =(F71-E71)*24*60 -> 0 | H71: =G71/60 -> 0 | I71: 2411 | K71: =I71*12 -> 28932 | L71: =J71*H71 -> 0 | M71: =(K71-L71)/K71 -> 1 | N71: =D71/M71 -> 0.059104106 | O71: =N71*I71*24 -> 3420 | P71: =O71-B71 -> 0
A72: 45907 | B72: =Data_Entry!P162 -> 3120 | C72: =Data_Entry!V162 -> 0 | D72: =B72/(24*I72) -> 0.053919535 | E72: 0 | F72: 0 | G72: =(F72-E72)*24*60 -> 0 | H72: =G72/60 -> 0 | I72: 2411 | K72: =I72*12 -> 28932 | L72: =J72*H72 -> 0 | M72: =(K72-L72)/K72 -> 1 | N72: =D72/M72 -> 0.053919535 | O72: =N72*I72*24 -> 3120 | P72: =O72-B72 -> 0
A73: 45908 | B73: =Data_Entry!P163 -> 3600 | C73: =Data_Entry!V163 -> 0 | D73: =B73/(24*I73) -> 0.062214849 | E73: 0 | F73: 0 | G73: =(F73-E73)*24*60 -> 0 | H73: =G73/60 -> 0 | I73: 2411 | K73: =I73*12 -> 28932 | L73: =J73*H73 -> 0 | M73: =(K73-L73)/K73 -> 1 | N73: =D73/M73 -> 0.062214849 | O73: =N73*I73*24 -> 3600 | P73: =O73-B73 -> 0
A74: 45909 | B74: =Data_Entry!P164 -> 11250 | C74: =Data_Entry!V164 -> 0 | D74: =B74/(24*I74) -> 0.1944214 | E74: 0 | F74: 0 | G74: =(F74-E74)*24*60 -> 0 | H74: =G74/60 -> 0 | I74: 2411 | K74: =I74*12 -> 28932 | L74: =J74*H74 -> 0 | M74: =(K74-L74)/K74 -> 1 | N74: =D74/M74 -> 0.1944214 | O74: =N74*I74*24 -> 11250 | P74: =O74-B74 -> 0
A75: 45910 | B75: =Data_Entry!P165 -> 10350 | C75: =Data_Entry!V165 -> 0 | D75: =B75/(24*I75) -> 0.17886769 | E75: 0 | F75: 0 | G75: =(F75-E75)*24*60 -> 0 | H75: =G75/60 -> 0 | I75: 2411 | K75: =I75*12 -> 28932 | L75: =J75*H75 -> 0 | M75: =(K75-L75)/K75 -> 1 | N75: =D75/M75 -> 0.17886769 | O75: =N75*I75*24 -> 10350 | P75: =O75-B75 -> 0
A76: 45911 | B76: =Data_Entry!P166 -> 14070 | C76: =Data_Entry!V166 -> 0 | D76: =B76/(24*I76) -> 0.24315637 | E76: 0 | F76: 0 | G76: =(F76-E76)*24*60 -> 0 | H76: =G76/60 -> 0 | I76: 2411 | K76: =I76*12 -> 28932 | L76: =J76*H76 -> 0 | M76: =(K76-L76)/K76 -> 1 | N76: =D76/M76 -> 0.24315637 | O76: =N76*I76*24 -> 14070 | P76: =O76-B76 -> 0
A77: 45912 | B77: =Data_Entry!P167 -> 12210 | C77: =Data_Entry!V167 -> 0 | D77: =B77/(24*I77) -> 0.21101203 | E77: 0 | F77: 0 | G77: =(F77-E77)*24*60 -> 0 | H77: =G77/60 -> 0 | I77: 2411 | K77: =I77*12 -> 28932 | L77: =J77*H77 -> 0 | M77: =(K77-L77)/K77 -> 1 | N77: =D77/M77 -> 0.21101203 | O77: =N77*I77*24 -> 12210 | P77: =O77-B77 -> 0
... A90: 45925 | B90: =Data_Entry!P180 -> 11430 | C90: =Data_Entry!V180 -> 4.09 | D90: =B90/(24*I90) -> 0.19753214 | E90: 0 | F90: 0 | G90: =(F90-E90)*24*60 -> 0 | H90: =G90/60 -> 0 | I90: 2411 | K90: =I90*12 -> 28932 | L90: =J90*H90 -> 0 | M90: =(K90-L90)/K90 -> 1 | N90: =D90/M90 -> 0.19753214 | O90: =N90*I90*24 -> 11430 | P90: =O90-B90 -> 0
A91: 45926 | B91: =Data_Entry!P181 -> 2670 | C91: =Data_Entry!V181 -> 0.37 | D91: =B91/(24*I91) -> 0.046142679 | E91: 0.30208333 | F91: 0.59375 | G91: =(F91-E91)*24*60 -> 420 | H91: =G91/60 -> 7 | I91: 2411 | J91: 2411.08 | K91: =I91*12 -> 28932 | L91: =J91*H91 -> 16877.56 | M91: =(K91-L91)/K91 -> 0.41664731 | N91: =D91/M91 -> 0.11074758 | O91: =N91*I91*24 -> 6408.2977 | P91: =O91-B91 -> 3738.2977
A92: 45927 | B92: =Data_Entry!P182 -> 10860 | C92: =Data_Entry!V182 -> 4.13 | D92: =B92/(24*I92) -> 0.18768146 | E92: 0 | F92: 0 | G92: =(F92-E92)*24*60 -> 0 | H92: =G92/60 -> 0 | I92: 2411 | K92: =I92*12 -> 28932 | L92: =J92*H92 -> 0 | M92: =(K92-L92)/K92 -> 1 | N92: =D92/M92 -> 0.18768146 | O92: =N92*I92*24 -> 10860 | P92: =O92-B92 -> 0
A93: 45928 | B93: =Data_Entry!P183 -> 3660 | C93: =Data_Entry!V183 -> 1.72 | D93: =B93/(24*I93) -> 0.063251763 | E93: 0 | F93: 0 | G93: =(F93-E93)*24*60 -> 0 | H93: =G93/60 -> 0 | I93: 2411 | K93: =I93*12 -> 28932 | L93: =J93*H93 -> 0 | M93: =(K93-L93)/K93 -> 1 | N93: =D93/M93 -> 0.063251763 | O93: =N93*I93*24 -> 3660 | P93: =O93-B93 -> 0
A94: 45929 | B94: =Data_Entry!P184 -> 4170 | C94: =Data_Entry!V184 -> 1.45 | D94: =B94/(24*I94) -> 0.072065533 | E94: 0 | F94: 0 | G94: =(F94-E94)*24*60 -> 0 | H94: =G94/60 -> 0 | I94: 2411 | K94: =I94*12 -> 28932 | L94: =J94*H94 -> 0 | M94: =(K94-L94)/K94 -> 1 | N94: =D94/M94 -> 0.072065533 | O94: =N94*I94*24 -> 4170 | P94: =O94-B94 -> 0
A95: 45930 | B95: =Data_Entry!P185 -> 3720 | C95: =Data_Entry!V185 -> 1.22 | D95: =B95/(24*I95) -> 0.064288677 | E95: 0 | F95: 0 | G95: =(F95-E95)*24*60 -> 0 | H95: =G95/60 -> 0 | I95: 2411 | K95: =I95*12 -> 28932 | L95: =J95*H95 -> 0 | M95: =(K95-L95)/K95 -> 1 | N95: =D95/M95 -> 0.064288677 | O95: =N95*I95*24 -> 3720 | P95: =O95-B95 -> 0
A96: 45931 | B96: =Data_Entry!P186 -> 5550 | C96: =Data_Entry!V186 -> 1.61 | D96: =B96/(24*I96) -> 0.095914558 | E96: 0 | F96: 0 | G96: =(F96-E96)*24*60 -> 0 | H96: =G96/60 -> 0 | I96: 2411 | K96: =I96*12 -> 28932 | L96: =J96*H96 -> 0 | M96: =(K96-L96)/K96 -> 1 | N96: =D96/M96 -> 0.095914558 | O96: =N96*I96*24 -> 5550 | P96: =O96-B96 -> 0
A97: 45932 | B97: =Data_Entry!P187 -> 7110 | C97: =Data_Entry!V187 -> 2.03 | D97: =B97/(24*I97) -> 0.12287433 | E97: 0 | F97: 0 | G97: =(F97-E97)*24*60 -> 0 | H97: =G97/60 -> 0 | I97: 2411 | K97: =I97*12 -> 28932 | L97: =J97*H97 -> 0 | M97: =(K97-L97)/K97 -> 1 | N97: =D97/M97 -> 0.12287433 | O97: =N97*I97*24 -> 7110 | P97: =O97-B97 -> 0
A98: 45933 | B98: =Data_Entry!P188 -> 9210 | C98: =Data_Entry!V188 -> 4.45 | D98: =B98/(24*I98) -> 0.15916632 | E98: 0 | F98: 0 | G98: =(F98-E98)*24*60 -> 0 | H98: =G98/60 -> 0 | I98: 2411 | K98: =I98*12 -> 28932 | L98: =J98*H98 -> 0 | M98: =(K98-L98)/K98 -> 1 | N98: =D98/M98 -> 0.15916632 | O98: =N98*I98*24 -> 9210 | P98: =O98-B98 -> 0
A99: 45934 | B99: =Data_Entry!P189 -> 13440 | C99: =Data_Entry!V189 -> 4.57 | D99: =B99/(24*I99) -> 0.23226877 | E99: 0 | F99: 0 | G99: =(F99-E99)*24*60 -> 0 | H99: =G99/60 -> 0 | I99: 2411 | K99: =I99*12 -> 28932 | L99: =J99*H99 -> 0 | M99: =(K99-L99)/K99 -> 1 | N99: =D99/M99 -> 0.23226877 | O99: =N99*I99*24 -> 13440 | P99: =O99-B99 -> 0
A100: 45935 | B100: =Data_Entry!P190 -> 9570 | C100: =Data_Entry!V190 -> 4.59 | D100: =B100/(24*I100) -> 0.16538781 | E100: 0 | F100: 0 | G100: =(F100-E100)*24*60 -> 0 | H100: =G100/60 -> 0 | I100: 2411 | K100: =I100*12 -> 28932 | L100: =J100*H100 -> 0 | M100: =(K100-L100)/K100 -> 1 | N100: =D100/M100 -> 0.16538781 | O100: =N100*I100*24 -> 9570 | P100: =O100-B100 -> 0
A101: 45936 | B101: =Data_Entry!P191 -> 11700 | C101: =Data_Entry!V191 -> 4.79 | D101: =B101/(24*I101) -> 0.20219826 | E101: 0 | F101: 0 | G101: =(F101-E101)*24*60 -> 0 | H101: =G101/60 -> 0 | I101: 2411 | K101: =I101*12 -> 28932 | L101: =J101*H101 -> 0 | M101: =(K101-L101)/K101 -> 1 | N101: =D101/M101 -> 0.20219826 | O101: =N101*I101*24 -> 11700 | P101: =O101-B101 -> 0
A102: 45937 | B102: =Data_Entry!P192 -> 12240 | C102: =Data_Entry!V192 -> 4.85 | D102: =B102/(24*I102) -> 0.21153049 | E102: 0 | F102: 0 | G102: =(F102-E102)*24*60 -> 0 | H102: =G102/60 -> 0 | I102: 2411 | K102: =I102*12 -> 28932 | L102: =J102*H102 -> 0 | M102: =(K102-L102)/K102 -> 1 | N102: =D102/M102 -> 0.21153049 | O102: =N102*I102*24 -> 12240 | P102: =O102-B102 -> 0
A103: 45938 | B103: =Data_Entry!P193 -> 12420 | C103: =Data_Entry!V193 -> 4.32 | D103: =B103/(24*I103) -> 0.21464123 | E103: 0 | F103: 0 | G103: =(F103-E103)*24*60 -> 0 | H103: =G103/60 -> 0 | I103: 2411 | K103: =I103*12 -> 28932 | L103: =J103*H103 -> 0 | M103: =(K103-L103)/K103 -> 1 | N103: =D103/M103 -> 0.21464123 | O103: =N103*I103*24 -> 12420 | P103: =O103-B103 -> 0
... A200: 46035 | B200: =Data_Entry!P290 -> 11160 | C200: =Data_Entry!V290 -> 3.88 | D200: =B200/(24*I200) -> 0.19286603 | E200: 0 | F200: 0 | G200: =(F200-E200)*24*60 -> 0 | H200: =G200/60 -> 0 | I200: 2411 | K200: =I200*12 -> 28932 | L200: =J200*H200 -> 0 | M200: =(K200-L200)/K200 -> 1 | N200: =D200/M200 -> 0.19286603 | O200: =N200*I200*24 -> 11160 | P200: =O200-B200 -> 0
A201: 46036 | B201: =Data_Entry!P291 -> 10920 | C201: =Data_Entry!V291 -> 3.65 | D201: =B201/(24*I201) -> 0.18871837 | E201: 0.64930556 | F201: 0.76527778 | G201: =(F201-E201)*24*60 -> 167 | H201: =G201/60 -> 2.7833333 | I201: 2411 | J201: 2411 | K201: =I201*12 -> 28932 | L201: =J201*H201 -> 6710.6167 | M201: =(K201-L201)/K201 -> 0.76805556 | N201: =D201/M201 -> 0.24570928 | O201: =N201*I201*24 -> 14217.722 | P201: =O201-B201 -> 3297.7215
A202: 46037 | B202: =Data_Entry!P292 -> 13080 | C202: =Data_Entry!V292 -> 4.38 | D202: =B202/(24*I202) -> 0.22604728 | E202: 0 | F202: 0 | G202: =(F202-E202)*24*60 -> 0 | H202: =G202/60 -> 0 | I202: 2411 | K202: =I202*12 -> 28932 | L202: =J202*H202 -> 0 | M202: =(K202-L202)/K202 -> 1 | N202: =D202/M202 -> 0.22604728 | O202: =N202*I202*24 -> 13080 | P202: =O202-B202 -> 0
A203: 46038 | B203: =Data_Entry!P293 -> 12270 | C203: =Data_Entry!V293 -> 4.28 | D203: =B203/(24*I203) -> 0.21204894 | E203: 0 | F203: 0 | G203: =(F203-E203)*24*60 -> 0 | H203: =G203/60 -> 0 | I203: 2411 | K203: =I203*12 -> 28932 | L203: =J203*H203 -> 0 | M203: =(K203-L203)/K203 -> 1 | N203: =D203/M203 -> 0.21204894 | O203: =N203*I203*24 -> 12270 | P203: =O203-B203 -> 0
A204: 46039 | B204: =Data_Entry!P294 -> 12300 | C204: =Data_Entry!V294 -> 4.08 | D204: =B204/(24*I204) -> 0.2125674 | E204: 0 | F204: 0 | G204: =(F204-E204)*24*60 -> 0 | H204: =G204/60 -> 0 | I204: 2411 | K204: =I204*12 -> 28932 | L204: =J204*H204 -> 0 | M204: =(K204-L204)/K204 -> 1 | N204: =D204/M204 -> 0.2125674 | O204: =N204*I204*24 -> 12300 | P204: =O204-B204 -> 0
A205: 46040 | B205: =Data_Entry!P295 -> 12600 | C205: =Data_Entry!V295 -> 3.94 | D205: =B205/(24*I205) -> 0.21775197 | E205: 0 | F205: 0 | G205: =(F205-E205)*24*60 -> 0 | H205: =G205/60 -> 0 | I205: 2411 | K205: =I205*12 -> 28932 | L205: =J205*H205 -> 0 | M205: =(K205-L205)/K205 -> 1 | N205: =D205/M205 -> 0.21775197 | O205: =N205*I205*24 -> 12600 | P205: =O205-B205 -> 0
A206: 46041 | B206: =Data_Entry!P296 -> 12810 | C206: =Data_Entry!V296 -> 4.16 | D206: =B206/(24*I206) -> 0.22138117 | E206: 0.55138889 | F206: 0.56041667 | G206: =(F206-E206)*24*60 -> 13 | H206: =G206/60 -> 0.21666667 | I206: 2411 | J206: 2411 | K206: =I206*12 -> 28932 | L206: =J206*H206 -> 522.38333 | M206: =(K206-L206)/K206 -> 0.98194444 | N206: =D206/M206 -> 0.22545183 | O206: =N206*I206*24 -> 13045.545 | P206: =O206-B206 -> 235.54455
A207: 46042 | B207: =Data_Entry!P297 -> 10410 | C207: =Data_Entry!V297 -> 3.75 | D207: =B207/(24*I207) -> 0.1799046 | E207: 0.51736111 | F207: 0.55902778 | G207: =(F207-E207)*24*60 -> 60 | H207: =G207/60 -> 1 | I207: 2411 | J207: 2411 | K207: =I207*12 -> 28932 | L207: =J207*H207 -> 2411 | M207: =(K207-L207)/K207 -> 0.91666667 | N207: =D207/M207 -> 0.19625957 | O207: =N207*I207*24 -> 11356.364 | P207: =O207-B207 -> 946.36364
A208: 46043 | B208: =Data_Entry!P298 -> 11370 | C208: =Data_Entry!V298 -> 3.85 | D208: =B208/(24*I208) -> 0.19649523 | E208: 0 | F208: 0 | G208: =(F208-E208)*24*60 -> 0 | H208: =G208/60 -> 0 | I208: 2411 | K208: =I208*12 -> 28932 | L208: =J208*H208 -> 0 | M208: =(K208-L208)/K208 -> 1 | N208: =D208/M208 -> 0.19649523 | O208: =N208*I208*24 -> 11370 | P208: =O208-B208 -> 0
A209: 46044 | B209: =Data_Entry!P299 -> 10320 | C209: =Data_Entry!V299 -> 3.81 | D209: =B209/(24*I209) -> 0.17834923 | E209: 0 | F209: 0 | G209: =(F209-E209)*24*60 -> 0 | H209: =G209/60 -> 0 | I209: 2411 | K209: =I209*12 -> 28932 | L209: =J209*H209 -> 0 | M209: =(K209-L209)/K209 -> 1 | N209: =D209/M209 -> 0.17834923 | O209: =N209*I209*24 -> 10320 | P209: =O209-B209 -> 0
A210: 46045 | B210: =Data_Entry!P300 -> 9960 | C210: =Data_Entry!V300 -> 3.62 | D210: =B210/(24*I210) -> 0.17212775 | E210: 0 | F210: 0 | G210: =(F210-E210)*24*60 -> 0 | H210: =G210/60 -> 0 | I210: 2411 | K210: =I210*12 -> 28932 | L210: =J210*H210 -> 0 | M210: =(K210-L210)/K210 -> 1 | N210: =D210/M210 -> 0.17212775 | O210: =N210*I210*24 -> 9960 | P210: =O210-B210 -> 0
A211: 46046 | B211: =Data_Entry!P301 -> 12210 | C211: =Data_Entry!V301 -> 4.03 | D211: =B211/(24*I211) -> 0.21101203 | E211: 0 | F211: 0 | G211: =(F211-E211)*24*60 -> 0 | H211: =G211/60 -> 0 | I211: 2411 | K211: =I211*12 -> 28932 | L211: =J211*H211 -> 0 | M211: =(K211-L211)/K211 -> 1 | N211: =D211/M211 -> 0.21101203 | O211: =N211*I211*24 -> 12210 | P211: =O211-B211 -> 0
A212: 46047 | B212: =Data_Entry!P302 -> 11790 | C212: =Data_Entry!V302 -> 3.63 | D212: =B212/(24*I212) -> 0.20375363 | E212: 0 | F212: 0 | G212: =(F212-E212)*24*60 -> 0 | H212: =G212/60 -> 0 | I212: 2411 | K212: =I212*12 -> 28932 | L212: =J212*H212 -> 0 | M212: =(K212-L212)/K212 -> 1 | N212: =D212/M212 -> 0.20375363 | O212: =N212*I212*24 -> 11790 | P212: =O212-B212 -> 0
A213: 46048 | B213: =Data_Entry!P303 -> 11640 | C213: =Data_Entry!V303 -> 3.89 | D213: =B213/(24*I213) -> 0.20116134 | E213: 0 | F213: 0 | G213: =(F213-E213)*24*60 -> 0 | H213: =G213/60 -> 0 | I213: 2411 | K213: =I213*12 -> 28932 | L213: =J213*H213 -> 0 | M213: =(K213-L213)/K213 -> 1 | N213: =D213/M213 -> 0.20116134 | O213: =N213*I213*24 -> 11640 | P213: =O213-B213 -> 0
A214: 46049 | B214: =Data_Entry!P304 -> 12660 | C214: =Data_Entry!V304 -> 5.95 | D214: =B214/(24*I214) -> 0.21878888 | E214: 0 | F214: 0 | G214: =(F214-E214)*24*60 -> 0 | H214: =G214/60 -> 0 | I214: 2411 | K214: =I214*12 -> 28932 | L214: =J214*H214 -> 0 | M214: =(K214-L214)/K214 -> 1 | N214: =D214/M214 -> 0.21878888 | O214: =N214*I214*24 -> 12660 | P214: =O214-B214 -> 0
A215: 46050 | B215: =Data_Entry!P305 -> 13560 | C215: =Data_Entry!V305 -> 4.46 | D215: =B215/(24*I215) -> 0.2343426 | E215: 0 | F215: 0 | G215: =(F215-E215)*24*60 -> 0 | H215: =G215/60 -> 0 | I215: 2411 | K215: =I215*12 -> 28932 | L215: =J215*H215 -> 0 | M215: =(K215-L215)/K215 -> 1 | N215: =D215/M215 -> 0.2343426 | O215: =N215*I215*24 -> 13560 | P215: =O215-B215 -> 0
A216: 46051 | B216: =Data_Entry!P306 -> 12450 | C216: =Data_Entry!V306 -> 4.28 | D216: =B216/(24*I216) -> 0.21515968 | E216: 0 | F216: 0 | G216: =(F216-E216)*24*60 -> 0 | H216: =G216/60 -> 0 | I216: 2411 | K216: =I216*12 -> 28932 | L216: =J216*H216 -> 0 | M216: =(K216-L216)/K216 -> 1 | N216: =D216/M216 -> 0.21515968 | O216: =N216*I216*24 -> 12450 | P216: =O216-B216 -> 0
A217: 46052 | B217: =Data_Entry!P307 -> 10350 | C217: =Data_Entry!V307 -> 3.58 | D217: =B217/(24*I217) -> 0.17886769 | E217: 0 | F217: 0 | G217: =(F217-E217)*24*60 -> 0 | H217: =G217/60 -> 0 | I217: 2411 | K217: =I217*12 -> 28932 | L217: =J217*H217 -> 0 | M217: =(K217-L217)/K217 -> 1 | N217: =D217/M217 -> 0.17886769 | O217: =N217*I217*24 -> 10350 | P217: =O217-B217 -> 0
A218: 46053 | B218: =Data_Entry!P308 -> 8100 | C218: =Data_Entry!V308 -> 2.95 | D218: =B218/(24*I218) -> 0.13998341 | E218: 0 | F218: 0 | G218: =(F218-E218)*24*60 -> 0 | H218: =G218/60 -> 0 | I218: 2411 | K218: =I218*12 -> 28932 | L218: =J218*H218 -> 0 | M218: =(K218-L218)/K218 -> 1 | N218: =D218/M218 -> 0.13998341 | O218: =N218*I218*24 -> 8100 | P218: =O218-B218 -> 0
A219: 46054 | B219: =Data_Entry!P309 -> 9720 | C219: =Data_Entry!V309 -> 3.54 | D219: =B219/(24*I219) -> 0.16798009 | E219: 0 | F219: 0 | G219: =(F219-E219)*24*60 -> 0 | H219: =G219/60 -> 0 | I219: 2411 | K219: =I219*12 -> 28932 | L219: =J219*H219 -> 0 | M219: =(K219-L219)/K219 -> 1 | N219: =D219/M219 -> 0.16798009 | O219: =N219*I219*24 -> 9720 | P219: =O219-B219 -> 0
... A323: 46158 | B323: =Data_Entry!P413 -> 14280 | C323: =Data_Entry!V413 -> 5.72 | D323: =B323/(24*I323) -> 0.24678557 | E323: 0 | F323: 0 | G323: =(F323-E323)*24*60 -> 0 | H323: =G323/60 -> 0 | I323: 2411 | K323: =I323*12 -> 28932 | L323: =J323*H323 -> 0 | M323: =(K323-L323)/K323 -> 1 | N323: =D323/M323 -> 0.24678557 | O323: =N323*I323*24 -> 14280 | P323: =O323-B323 -> 0
A324: 46159 | B324: =Data_Entry!P414 -> 12390 | C324: =Data_Entry!V414 -> 5.2 | D324: =B324/(24*I324) -> 0.21412277 | E324: 0.57152778 | F324: 0.61319444 | G324: =(F324-E324)*24*60 -> 60 | H324: =G324/60 -> 1 | I324: 2411 | J324: 2411 | K324: =I324*12 -> 28932 | L324: =J324*H324 -> 2411 | M324: =(K324-L324)/K324 -> 0.91666667 | N324: =D324/M324 -> 0.23358848 | O324: =N324*I324*24 -> 13516.364 | P324: =O324-B324 -> 1126.3636
A325: 46160 | B325: =Data_Entry!P415 -> 13770 | C325: =Data_Entry!V415 -> 5.51 | D325: =B325/(24*I325) -> 0.2379718 | E325: 0 | F325: 0 | G325: =(F325-E325)*24*60 -> 0 | H325: =G325/60 -> 0 | I325: 2411 | K325: =I325*12 -> 28932 | L325: =J325*H325 -> 0 | M325: =(K325-L325)/K325 -> 1 | N325: =D325/M325 -> 0.2379718 | O325: =N325*I325*24 -> 13770 | P325: =O325-B325 -> 0
A326: 46161 | B326: =Data_Entry!P416 -> 14220 | C326: =Data_Entry!V416 -> 2.95 | D326: =B326/(24*I326) -> 0.24574865 | E326: 0 | F326: 0 | G326: =(F326-E326)*24*60 -> 0 | H326: =G326/60 -> 0 | I326: 2411 | K326: =I326*12 -> 28932 | L326: =J326*H326 -> 0 | M326: =(K326-L326)/K326 -> 1 | N326: =D326/M326 -> 0.24574865 | O326: =N326*I326*24 -> 14220 | P326: =O326-B326 -> 0
A327: 46162 | B327: =Data_Entry!P417 -> 13800 | C327: =Data_Entry!V417 -> 5.83 | D327: =B327/(24*I327) -> 0.23849025 | E327: 0 | F327: 0 | G327: =(F327-E327)*24*60 -> 0 | H327: =G327/60 -> 0 | I327: 2411 | K327: =I327*12 -> 28932 | L327: =J327*H327 -> 0 | M327: =(K327-L327)/K327 -> 1 | N327: =D327/M327 -> 0.23849025 | O327: =N327*I327*24 -> 13800 | P327: =O327-B327 -> 0
A328: 46163 | B328: =Data_Entry!P418 -> 13230 | C328: =Data_Entry!V418 -> 5.68 | D328: =B328/(24*I328) -> 0.22863957 | E328: 0 | F328: 0 | G328: =(F328-E328)*24*60 -> 0 | H328: =G328/60 -> 0 | I328: 2411 | K328: =I328*12 -> 28932 | L328: =J328*H328 -> 0 | M328: =(K328-L328)/K328 -> 1 | N328: =D328/M328 -> 0.22863957 | O328: =N328*I328*24 -> 13230 | P328: =O328-B328 -> 0
A329: 46164 | B329: =Data_Entry!P419 -> 1050 | C329: =Data_Entry!V419 -> 0.67 | D329: =B329/(24*I329) -> 0.018145998 | E329: 0.29166667 | F329: 0.6875 | G329: =(F329-E329)*24*60 -> 570 | H329: =G329/60 -> 9.5 | I329: 2411 | J329: 2411 | K329: =I329*12 -> 28932 | L329: =J329*H329 -> 22904.5 | M329: =(K329-L329)/K329 -> 0.20833333 | N329: =D329/M329 -> 0.087100788 | O329: =N329*I329*24 -> 5040 | P329: =O329-B329 -> 3990
A330: 46165 | B330: =Data_Entry!P420 -> 12930 | C330: =Data_Entry!V420 -> 5.83 | D330: =B330/(24*I330) -> 0.223455 | E330: 0 | F330: 0 | G330: =(F330-E330)*24*60 -> 0 | H330: =G330/60 -> 0 | I330: 2411 | K330: =I330*12 -> 28932 | L330: =J330*H330 -> 0 | M330: =(K330-L330)/K330 -> 1 | N330: =D330/M330 -> 0.223455 | O330: =N330*I330*24 -> 12930 | P330: =O330-B330 -> 0
A331: 46166 | B331: =Data_Entry!P421 -> 11490 | C331: =Data_Entry!V421 -> 5.1 | D331: =B331/(24*I331) -> 0.19856906 | E331: 0 | F331: 0 | G331: =(F331-E331)*24*60 -> 0 | H331: =G331/60 -> 0 | I331: 2411 | K331: =I331*12 -> 28932 | L331: =J331*H331 -> 0 | M331: =(K331-L331)/K331 -> 1 | N331: =D331/M331 -> 0.19856906 | O331: =N331*I331*24 -> 11490 | P331: =O331-B331 -> 0
A332: 46167 | B332: =Data_Entry!P422 -> 13260 | C332: =Data_Entry!V422 -> 4.78 | D332: =B332/(24*I332) -> 0.22915803 | E332: 0 | F332: 0 | G332: =(F332-E332)*24*60 -> 0 | H332: =G332/60 -> 0 | I332: 2411 | K332: =I332*12 -> 28932 | L332: =J332*H332 -> 0 | M332: =(K332-L332)/K332 -> 1 | N332: =D332/M332 -> 0.22915803 | O332: =N332*I332*24 -> 13260 | P332: =O332-B332 -> 0
A333: 46168 | B333: =Data_Entry!P423 -> 13320 | C333: =Data_Entry!V423 -> 5.74 | D333: =B333/(24*I333) -> 0.23019494 | E333: 0 | F333: 0 | G333: =(F333-E333)*24*60 -> 0 | H333: =G333/60 -> 0 | I333: 2411 | K333: =I333*12 -> 28932 | L333: =J333*H333 -> 0 | M333: =(K333-L333)/K333 -> 1 | N333: =D333/M333 -> 0.23019494 | O333: =N333*I333*24 -> 13320 | P333: =O333-B333 -> 0
A334: 46169 | B334: =Data_Entry!P424 -> 13200 | C334: =Data_Entry!V424 -> 5.74 | D334: =B334/(24*I334) -> 0.22812111 | E334: 0 | F334: 0 | G334: =(F334-E334)*24*60 -> 0 | H334: =G334/60 -> 0 | I334: 2411 | K334: =I334*12 -> 28932 | L334: =J334*H334 -> 0 | M334: =(K334-L334)/K334 -> 1 | N334: =D334/M334 -> 0.22812111 | O334: =N334*I334*24 -> 13200 | P334: =O334-B334 -> 0
A335: 46170 | B335: =Data_Entry!P425 -> 13380 | C335: =Data_Entry!V425 -> 5.79 | D335: =B335/(24*I335) -> 0.23123185 | E335: 0 | F335: 0 | G335: =(F335-E335)*24*60 -> 0 | H335: =G335/60 -> 0 | I335: 2411 | K335: =I335*12 -> 28932 | L335: =J335*H335 -> 0 | M335: =(K335-L335)/K335 -> 1 | N335: =D335/M335 -> 0.23123185 | O335: =N335*I335*24 -> 13380 | P335: =O335-B335 -> 0
...
