Workbook

Sheet Budgeted_Data
A1: Plant Name | B1: Date | C1: Month | D1: Month | E1: Daily_Gen | F1: Daily_GTI | G1: Daily_GHI | H1: Ambt_Temp | I1: PR_% | J1: CUF_% | K1: TArray | L1: TArrWtd | M1: Connected_DC
A2: Devki_Galol | B2: 45747 | M2: 2411
A3: Devki_Galol | B3: 45748 | E3: 13793.656 | F3: 6.91332 | G3: 6.706944 | H3: 27.415 | I3: 0.82755242 | J3: 0.23838061 | K3: 21.811375 | L3: 21.811375 | M3: 2411
A4: Devki_Galol | B4: 45749 | E4: 14382.297 | F4: 7.241431 | G4: 7.024582 | H4: 26.8775 | I4: 0.82377127 | J4: 0.24855345 | K4: 22.152292 | L4: 22.152292 | M4: 2411
A5: Devki_Galol | B5: 45750 | E5: 15006.04 | F5: 7.635258 | G5: 7.41063 | H5: 28.30125 | I5: 0.81516433 | J5: 0.25933292 | K5: 23.397417 | L5: 23.397417 | M5: 2411
A6: Devki_Galol | B6: 45751 | E6: 15318.708 | F6: 7.804122 | G6: 7.577929 | H6: 28.33 | I6: 0.81414333 | J6: 0.26473641 | K6: 23.414333 | L6: 23.414333 | M6: 2411
A7: Devki_Galol | B7: 45752 | E7: 11372.591 | F7: 5.715388 | G7: 5.502656 | H7: 31.082917 | I7: 0.82530882 | J7: 0.19654 | K7: 22.630083 | L7: 22.630083 | M7: 2411
A8: Devki_Galol | B8: 45753 | E8: 7534.1062 | F8: 3.734185 | G8: 3.585435 | H8: 30.53375 | I8: 0.83683281 | J8: 0.13020369 | K8: 18.428792 | L8: 18.428792 | M8: 2411
A9: Devki_Galol | B9: 45754 | E9: 12437.248 | F9: 6.305604 | G9: 6.098628 | H9: 31.335 | I9: 0.81808868 | J9: 0.2149393 | K9: 23.464417 | L9: 23.464417 | M9: 2411
A10: Devki_Galol | B10: 45755 | E10: 13584.717 | F10: 6.904297 | G10: 6.68637 | H10: 30.85375 | I10: 0.81608222 | J10: 0.23476975 | K10: 23.794542 | L10: 23.794542 | M10: 2411
A11: Devki_Galol | B11: 45756 | E11: 14586.557 | F11: 7.448638 | G11: 7.214318 | H11: 30.165833 | I11: 0.81222941 | J11: 0.25208345 | K11: 24.040792 | L11: 24.040792 | M11: 2411
A12: Devki_Galol | B12: 45757 | E12: 13848.104 | F12: 7.092072 | G12: 6.869304 | H12: 31.859167 | I12: 0.80987868 | J12: 0.23932158 | K12: 24.644167 | L12: 24.644167 | M12: 2411
A13: Devki_Galol | B13: 45758 | E13: 14722.199 | F13: 7.611885 | G13: 7.374694 | H13: 32.392917 | I13: 0.80220109 | J13: 0.2544276 | K13: 25.622083 | L13: 25.622083 | M13: 2411
A14: Devki_Galol | B14: 45759 | E14: 14667.795 | F14: 7.477686 | G14: 7.244865 | H14: 29.71 | I14: 0.81358024 | J14: 0.2534874 | K14: 23.866417 | L14: 23.866417 | M14: 2411
... A367: Devki_Galol | B367: 46112 | E367: 14312.664 | F367: 7.348117 | G367: 7.129453 | H367: 30.895833 | I367: 0.80788063 | J367: 0.24735006 | K367: 24.667167 | L367: 24.667167 | M367: 2411

Sheet E-Mail_Copy
A1: Plant_Performance_of_Devki_Galol_GJ
B3: =DATE(YEAR(B4),MONTH(B4),1) -> 46174 | C3: =VLOOKUP(L3,Basic_Data!$A$28:$B$48,2,0) -> 45748 | L3: 25-26
A4: Date | B4: 46178 | C4: AC Capacity: | E4: =Basic_Data!F10 -> 1925 | F4: DC Capacity: | H4: =Basic_Data!G10 -> 2411.08 | I4: D.O.C.: | K4: =Basic_Data!B3 -> 45720
A5: Plant Name | C5: Daily | F5: MTD | I5: YTD
C6: Budgeted | D6: Actual | E6: Variation(%) | F6: Budgeted | G6: Actual | H6: Variation(%) | I6: Budgeted | J6: Actual | K6: Variation(%)
A7: Generation_MW | C7: =SUMIFS(Budgeted_Data!$E:$E,Budgeted_Data!$B:$B,'E-Mail_Copy'!$B$4) -> 0 | D7: =SUMIFS(Data_Entry!$T:$T,Data_Entry!$C:$C,'E-Mail_Copy'!$B$4) -> 10350 | E7: =(D7-C7)/C7 -> #DIV/0! | F7: =SUMIFS(Budgeted_Data!$E:$E,Budgeted_Data!$B:$B,">="&'E-Mail_Copy'!$B$3,Budgeted_Data!$B:$B,"<="&'E-Mail_Copy'!$B$4) -> 0 | G7: =SUMIFS(Data_Entry!$T:$T,Data_Entry!$C:$C,">="&'E-Mail_Copy'!$B$3,Data_Entry!$C:$C,"<="&'E-Mail_Copy'!$B$4) -> 56010 | H7: =(G7-F7)/F7 -> #DIV/0! | I7: =SUMIFS(Budgeted_Data!$E:$E,Budgeted_Data!$B:$B,">="&'E-Mail_Copy'!$C$3,Budgeted_Data!$B:$B,"<="&'E-Mail_Copy'!$B$4) -> 4129749.1 | J7: =SUMIFS(Data_Entry!$T:$T,Data_Entry!$C:$C,">="&'E-Mail_Copy'!$C$3,Data_Entry!$C:$C,"<="&'E-Mail_Copy'!$B$4) -> 4625010 | K7: =(J7-I7)/I7 -> 0.11992518
A8: GTI (Kwh/m2) | C8: =SUMIFS(Budgeted_Data!$F:$F,Budgeted_Data!$B:$B,'E-Mail_Copy'!$B$4) -> 0 | D8: =SUMIFS(Data_Entry!$V:$V,Data_Entry!$C:$C,'E-Mail_Copy'!B4) -> 3.66 | E8: =(D8-C8)/C8 -> #DIV/0! | F8: =SUMIFS(Budgeted_Data!$F:$F,Budgeted_Data!$B:$B,">="&'E-Mail_Copy'!$B$3,Budgeted_Data!$B:$B,"<="&'E-Mail_Copy'!$B$4) -> 0 | G8: =SUMIFS(Data_Entry!$V:$V,Data_Entry!$C:$C,">="&'E-Mail_Copy'!$B$3,Data_Entry!$C:$C,"<="&'E-Mail_Copy'!$B$4) -> 23.67 | H8: =(G8-F8)/F8 -> #DIV/0! | I8: =SUMIFS(Budgeted_Data!$F:$F,Budgeted_Data!$B:$B,">="&'E-Mail_Copy'!$C$3,Budgeted_Data!$B:$B,"<="&'E-Mail_Copy'!$B$4) -> 2080.1765 | J8: =SUMIFS(Data_Entry!$V:$V,Data_Entry!$C:$C,">="&'E-Mail_Copy'!$C$3,Data_Entry!$C:$C,"<="&'E-Mail_Copy'!$B$4) -> 1555.6445 | K8: =(J8-I8)/I8 -> -0.25215744
A9: GHI (Kwh/m2) | C9: =SUMIFS(Budgeted_Data!$G:$G,Budgeted_Data!$B:$B,'E-Mail_Copy'!$B$4) -> 0 | D9: =SUMIFS(Data_Entry!$U:$U,Data_Entry!$C:$C,'E-Mail_Copy'!$B$4) -> 0 | E9: =(D9-C9)/C9 -> #DIV/0! | F9: =SUMIFS(Budgeted_Data!$G:$G,Budgeted_Data!$B:$B,">="&'E-Mail_Copy'!$B$3,Budgeted_Data!$B:$B,"<="&'E-Mail_Copy'!$B$4) -> 0 | G9: =SUMIFS(Data_Entry!$U:$U,Data_Entry!$C:$C,">="&'E-Mail_Copy'!$B$3,Data_Entry!$C:$C,"<="&'E-Mail_Copy'!$B$4) -> 0 | H9: =(G9-F9)/F9 -> #DIV/0! | I9: =SUMIFS(Budgeted_Data!$G:$G,Budgeted_Data!$B:$B,">="&'E-Mail_Copy'!$C$3,Budgeted_Data!$B:$B,"<="&'E-Mail_Copy'!$B$4) -> 2008.1028 | J9: =SUMIFS(Data_Entry!$U:$U,Data_Entry!$C:$C,">="&'E-Mail_Copy'!$C$3,Data_Entry!$C:$C,"<="&'E-Mail_Copy'!$B$4) -> 0 | K9: =(J9-I9)/I9 -> -1
A10: PR_(%) | C10: =C7/C8/H4 -> #DIV/0! | D10: =D7/D8/H4 -> 1.172864 | E10: =(D10-C10)/C10 -> #DIV/0! | F10: =F7/F8/H4/(B4-B3+1) -> #DIV/0! | G10: =G7/G8/H4/(B4-B3+1) -> 0.19628436 | H10: =(G10-F10)/F10 -> #DIV/0! | I10: =I7/I8/H4/(($B$4-$C$3)+1) -> 0.0019104453 | J10: =J7/J8/H4/(($B$4-$C$3)+1) -> 0.0028609708 | K10: =(J10-I10)/I10 -> 0.49754138
A11: CUF_(%) | C11: =C7/E4/24 -> 0 | D11: =D7/24/E4 -> 0.22402597 | E11: =(D11-C11)/C11 -> #DIV/0! | F11: =F7/24/E4/(B4-B3+1) -> 0 | G11: =G7/24/E4/(B4-B3+1) -> 0.24246753 | H11: =(G11-F11)/F11 -> #DIV/0! | I11: =I7/24/$E$4/(($B$4-$C$3)+1) -> 0.20739793 | J11: =J7/24/$E$4/(($B$4-$C$3)+1) -> 0.23227017 | K11: =(J11-I11)/I11 -> 0.11992518
A12: Wtd_Module_Temp | C12: =AVERAGEIFS(Budgeted_Data!$L:$L,Budgeted_Data!$B:$B,'E-Mail_Copy'!$B$4) -> #DIV/0! | D12: =AVERAGEIFS(Data_Entry!$Y:$Y,Data_Entry!$C:$C,'E-Mail_Copy'!$B$4) -> #DIV/0! | E12: =(D12-C12)/C12 -> #DIV/0! | F12: =AVERAGEIFS(Budgeted_Data!$L:$L,Budgeted_Data!$B:$B,">="&'E-Mail_Copy'!$B$3,Budgeted_Data!$B:$B,"<="&'E-Mail_Copy'!$B$4) -> #DIV/0! | G12: =AVERAGEIFS(Data_Entry!$Y:$Y,Data_Entry!$C:$C,">="&'E-Mail_Copy'!$B$3,Data_Entry!$C:$C,"<="&'E-Mail_Copy'!$B$4) -> #DIV/0! | H12: =(G12-F12)/F12 -> #DIV/0! | I12: =AVERAGEIFS(Budgeted_Data!$L:$L,Budgeted_Data!$B:$B,">="&'E-Mail_Copy'!$C$3,Budgeted_Data!$B:$B,"<="&'E-Mail_Copy'!$B$4) -> 20.137807 | J12: =AVERAGEIFS(Data_Entry!$Y:$Y,Data_Entry!$C:$C,">="&'E-Mail_Copy'!$C$3,Data_Entry!$C:$C,"<="&'E-Mail_Copy'!$B$4) -> #DIV/0! | K12: =(J12-I12)/I12 -> #DIV/0!
A13: Ambt._Temp_(0C) | C13: =AVERAGEIFS(Budgeted_Data!$H:$H,Budgeted_Data!$B:$B,'E-Mail_Copy'!$B$4) -> #DIV/0! | D13: =AVERAGEIFS(Data_Entry!$W:$W,Data_Entry!$C:$C,'E-Mail_Copy'!$B$4) -> 34.09 | E13: =(D13-C13)/C13 -> #DIV/0! | F13: =AVERAGEIFS(Budgeted_Data!$H:$H,Budgeted_Data!$B:$B,">="&'E-Mail_Copy'!$B$3,Budgeted_Data!$B:$B,"<="&'E-Mail_Copy'!$B$4) -> #DIV/0! | G13: =AVERAGEIFS(Data_Entry!$W:$W,Data_Entry!$C:$C,">="&'E-Mail_Copy'!$B$3,Data_Entry!$C:$C,"<="&'E-Mail_Copy'!$B$4) -> 34.292 | H13: =(G13-F13)/F13 -> #DIV/0! | I13: =AVERAGEIFS(Budgeted_Data!$H:$H,Budgeted_Data!$B:$B,">="&'E-Mail_Copy'!$C$3,Budgeted_Data!$B:$B,"<="&'E-Mail_Copy'!$B$4) -> 27.271039 | J13: =AVERAGEIFS(Data_Entry!$W:$W,Data_Entry!$C:$C,">="&'E-Mail_Copy'!$C$3,Data_Entry!$C:$C,"<="&'E-Mail_Copy'!$B$4) -> 28.886026 | K13: =(J13-I13)/I13 -> 0.059219875

Sheet DGR
A1: Daily_Generation_&_Performance_Report
A3: Inverter_No. | B3: ='E-Mail_Copy'!B4 -> 46178 | C3: =B3+1 -> 46179 | D3: =C3+1 -> 46180 | E3: =D3+1 -> 46181 | F3: =E3+1 -> 46182 | G3: =F3+1 -> 46183 | H3: =G3+1 -> 46184 | I3: =H3+1 -> 46185 | J3: =I3+1 -> 46186 | ... AF3: =AE3+1 -> 46208 | AG3: Total/Avg..
A4: Inv_1 | B4: =IFERROR(VLOOKUP(B$3,Data_Entry!$C:$AB,Data_Entry!$A2,0),"") -> 1463.28 | C4: =IFERROR(VLOOKUP(C$3,Data_Entry!$C:$AB,Data_Entry!$A2,0),"") -> 0 | D4: =IFERROR(VLOOKUP(D$3,Data_Entry!$C:$AB,Data_Entry!$A2,0),"") -> 0 | E4: =IFERROR(VLOOKUP(E$3,Data_Entry!$C:$AB,Data_Entry!$A2,0),"") -> 0 | F4: =IFERROR(VLOOKUP(F$3,Data_Entry!$C:$AB,Data_Entry!$A2,0),"") -> 0 | G4: =IFERROR(VLOOKUP(G$3,Data_Entry!$C:$AB,Data_Entry!$A2,0),"") -> 0 | H4: =IFERROR(VLOOKUP(H$3,Data_Entry!$C:$AB,Data_Entry!$A2,0),"") -> 0 | I4: =IFERROR(VLOOKUP(I$3,Data_Entry!$C:$AB,Data_Entry!$A2,0),"") -> 0 | ... AF4: =IFERROR(VLOOKUP(AF$3,Data_Entry!$C:$AB,Data_Entry!$A2,0),"") -> 0 | AG4: =IFERROR(SUM(B4:AF4),"") -> 1463.28
A5: Inv_2 | B5: =IFERROR(VLOOKUP(B$3,Data_Entry!$C:$AB,Data_Entry!$A3,0),"") -> 1456.63 | C5: =IFERROR(VLOOKUP(C$3,Data_Entry!$C:$AB,Data_Entry!$A3,0),"") -> 0 | D5: =IFERROR(VLOOKUP(D$3,Data_Entry!$C:$AB,Data_Entry!$A3,0),"") -> 0 | E5: =IFERROR(VLOOKUP(E$3,Data_Entry!$C:$AB,Data_Entry!$A3,0),"") -> 0 | F5: =IFERROR(VLOOKUP(F$3,Data_Entry!$C:$AB,Data_Entry!$A3,0),"") -> 0 | G5: =IFERROR(VLOOKUP(G$3,Data_Entry!$C:$AB,Data_Entry!$A3,0),"") -> 0 | H5: =IFERROR(VLOOKUP(H$3,Data_Entry!$C:$AB,Data_Entry!$A3,0),"") -> 0 | I5: =IFERROR(VLOOKUP(I$3,Data_Entry!$C:$AB,Data_Entry!$A3,0),"") -> 0 | ... AF5: =IFERROR(VLOOKUP(AF$3,Data_Entry!$C:$AB,Data_Entry!$A3,0),"") -> 0 | AG5: =IFERROR(SUM(B5:AF5),"") -> 1456.63
A6: Inv_3 | B6: =IFERROR(VLOOKUP(B$3,Data_Entry!$C:$AB,Data_Entry!$A4,0),"") -> 1461.19 | C6: =IFERROR(VLOOKUP(C$3,Data_Entry!$C:$AB,Data_Entry!$A4,0),"") -> 0 | D6: =IFERROR(VLOOKUP(D$3,Data_Entry!$C:$AB,Data_Entry!$A4,0),"") -> 0 | E6: =IFERROR(VLOOKUP(E$3,Data_Entry!$C:$AB,Data_Entry!$A4,0),"") -> 0 | F6: =IFERROR(VLOOKUP(F$3,Data_Entry!$C:$AB,Data_Entry!$A4,0),"") -> 0 | G6: =IFERROR(VLOOKUP(G$3,Data_Entry!$C:$AB,Data_Entry!$A4,0),"") -> 0 | H6: =IFERROR(VLOOKUP(H$3,Data_Entry!$C:$AB,Data_Entry!$A4,0),"") -> 0 | I6: =IFERROR(VLOOKUP(I$3,Data_Entry!$C:$AB,Data_Entry!$A4,0),"") -> 0 | ... AF6: =IFERROR(VLOOKUP(AF$3,Data_Entry!$C:$AB,Data_Entry!$A4,0),"") -> 0 | AG6: =IFERROR(SUM(B6:AF6),"") -> 1461.19
A7: Inv_4 | B7: =IFERROR(VLOOKUP(B$3,Data_Entry!$C:$AB,Data_Entry!$A5,0),"") -> 1520.01 | C7: =IFERROR(VLOOKUP(C$3,Data_Entry!$C:$AB,Data_Entry!$A5,0),"") -> 0 | D7: =IFERROR(VLOOKUP(D$3,Data_Entry!$C:$AB,Data_Entry!$A5,0),"") -> 0 | E7: =IFERROR(VLOOKUP(E$3,Data_Entry!$C:$AB,Data_Entry!$A5,0),"") -> 0 | F7: =IFERROR(VLOOKUP(F$3,Data_Entry!$C:$AB,Data_Entry!$A5,0),"") -> 0 | G7: =IFERROR(VLOOKUP(G$3,Data_Entry!$C:$AB,Data_Entry!$A5,0),"") -> 0 | H7: =IFERROR(VLOOKUP(H$3,Data_Entry!$C:$AB,Data_Entry!$A5,0),"") -> 0 | I7: =IFERROR(VLOOKUP(I$3,Data_Entry!$C:$AB,Data_Entry!$A5,0),"") -> 0 | ... AF7: =IFERROR(VLOOKUP(AF$3,Data_Entry!$C:$AB,Data_Entry!$A5,0),"") -> 0 | AG7: =IFERROR(SUM(B7:AF7),"") -> 1520.01
A8: Inv_5 | B8: =IFERROR(VLOOKUP(B$3,Data_Entry!$C:$AB,Data_Entry!$A6,0),"") -> 1507.08 | C8: =IFERROR(VLOOKUP(C$3,Data_Entry!$C:$AB,Data_Entry!$A6,0),"") -> 0 | D8: =IFERROR(VLOOKUP(D$3,Data_Entry!$C:$AB,Data_Entry!$A6,0),"") -> 0 | E8: =IFERROR(VLOOKUP(E$3,Data_Entry!$C:$AB,Data_Entry!$A6,0),"") -> 0 | F8: =IFERROR(VLOOKUP(F$3,Data_Entry!$C:$AB,Data_Entry!$A6,0),"") -> 0 | G8: =IFERROR(VLOOKUP(G$3,Data_Entry!$C:$AB,Data_Entry!$A6,0),"") -> 0 | H8: =IFERROR(VLOOKUP(H$3,Data_Entry!$C:$AB,Data_Entry!$A6,0),"") -> 0 | I8: =IFERROR(VLOOKUP(I$3,Data_Entry!$C:$AB,Data_Entry!$A6,0),"") -> 0 | ... AF8: =IFERROR(VLOOKUP(AF$3,Data_Entry!$C:$AB,Data_Entry!$A6,0),"") -> 0 | AG8: =IFERROR(SUM(B8:AF8),"") -> 1507.08
A9: Inv_6 | B9: =IFERROR(VLOOKUP(B$3,Data_Entry!$C:$AB,Data_Entry!$A7,0),"") -> 1500.1 | C9: =IFERROR(VLOOKUP(C$3,Data_Entry!$C:$AB,Data_Entry!$A7,0),"") -> 0 | D9: =IFERROR(VLOOKUP(D$3,Data_Entry!$C:$AB,Data_Entry!$A7,0),"") -> 0 | E9: =IFERROR(VLOOKUP(E$3,Data_Entry!$C:$AB,Data_Entry!$A7,0),"") -> 0 | F9: =IFERROR(VLOOKUP(F$3,Data_Entry!$C:$AB,Data_Entry!$A7,0),"") -> 0 | G9: =IFERROR(VLOOKUP(G$3,Data_Entry!$C:$AB,Data_Entry!$A7,0),"") -> 0 | H9: =IFERROR(VLOOKUP(H$3,Data_Entry!$C:$AB,Data_Entry!$A7,0),"") -> 0 | I9: =IFERROR(VLOOKUP(I$3,Data_Entry!$C:$AB,Data_Entry!$A7,0),"") -> 0 | ... AF9: =IFERROR(VLOOKUP(AF$3,Data_Entry!$C:$AB,Data_Entry!$A7,0),"") -> 0 | AG9: =IFERROR(SUM(B9:AF9),"") -> 1500.1
A10: Inv_7 | B10: =IFERROR(VLOOKUP(B$3,Data_Entry!$C:$AB,Data_Entry!$A8,0),"") -> 1455.77 | C10: =IFERROR(VLOOKUP(C$3,Data_Entry!$C:$AB,Data_Entry!$A8,0),"") -> 0 | D10: =IFERROR(VLOOKUP(D$3,Data_Entry!$C:$AB,Data_Entry!$A8,0),"") -> 0 | E10: =IFERROR(VLOOKUP(E$3,Data_Entry!$C:$AB,Data_Entry!$A8,0),"") -> 0 | F10: =IFERROR(VLOOKUP(F$3,Data_Entry!$C:$AB,Data_Entry!$A8,0),"") -> 0 | G10: =IFERROR(VLOOKUP(G$3,Data_Entry!$C:$AB,Data_Entry!$A8,0),"") -> 0 | H10: =IFERROR(VLOOKUP(H$3,Data_Entry!$C:$AB,Data_Entry!$A8,0),"") -> 0 | I10: =IFERROR(VLOOKUP(I$3,Data_Entry!$C:$AB,Data_Entry!$A8,0),"") -> 0 | ... AF10: =IFERROR(VLOOKUP(AF$3,Data_Entry!$C:$AB,Data_Entry!$A8,0),"") -> 0 | AG10: =IFERROR(SUM(B10:AF10),"") -> 1455.77
A11: Total_Inverter_(kWh) | B11: =SUM(B4:B10) -> 10364.06 | C11: =SUM(C4:C10) -> 0 | D11: =SUM(D4:D10) -> 0 | E11: =SUM(E4:E10) -> 0 | F11: =SUM(F4:F10) -> 0 | G11: =SUM(G4:G10) -> 0 | H11: =SUM(H4:H10) -> 0 | I11: =SUM(I4:I10) -> 0 | ... AG11: =SUM(AG4:AG10) -> 10364.06
A12: Total_ABT_Meter_Export_(kWh) | B12: =IFERROR(VLOOKUP(B$3,Data_Entry!$C:$AB,14,0)," ") -> 10410 | C12: =IFERROR(VLOOKUP(C$3,Data_Entry!$C:$AB,14,0)," ") -> 0 | D12: =IFERROR(VLOOKUP(D$3,Data_Entry!$C:$AB,14,0)," ") -> 0 | E12: =IFERROR(VLOOKUP(E$3,Data_Entry!$C:$AB,14,0)," ") -> 0 | F12: =IFERROR(VLOOKUP(F$3,Data_Entry!$C:$AB,14,0)," ") -> 0 | G12: =IFERROR(VLOOKUP(G$3,Data_Entry!$C:$AB,14,0)," ") -> 0 | H12: =IFERROR(VLOOKUP(H$3,Data_Entry!$C:$AB,14,0)," ") -> 0 | I12: =IFERROR(VLOOKUP(I$3,Data_Entry!$C:$AB,14,0)," ") -> 0 | ... AG12: =IFERROR(VLOOKUP(AG$3,Data_Entry!$C:$AB,14,0)," ")
A13: Total_ABT_Meter_Import_(kWh) | B13: =IFERROR(VLOOKUP(B$3,Data_Entry!$C:$AB,17,0)," ") -> 60 | C13: =IFERROR(VLOOKUP(C$3,Data_Entry!$C:$AB,17,0)," ") -> 0 | D13: =IFERROR(VLOOKUP(D$3,Data_Entry!$C:$AB,17,0)," ") -> 0 | E13: =IFERROR(VLOOKUP(E$3,Data_Entry!$C:$AB,17,0)," ") -> 0 | F13: =IFERROR(VLOOKUP(F$3,Data_Entry!$C:$AB,17,0)," ") -> 0 | G13: =IFERROR(VLOOKUP(G$3,Data_Entry!$C:$AB,17,0)," ") -> 0 | H13: =IFERROR(VLOOKUP(H$3,Data_Entry!$C:$AB,17,0)," ") -> 0 | I13: =IFERROR(VLOOKUP(I$3,Data_Entry!$C:$AB,17,0)," ") -> 0 | ... AG13: =IFERROR(VLOOKUP(AG$3,Data_Entry!$C:$AB,17,0)," ")
A14: Total_ABT_Meter_Net_(kWh) | B14: =IFERROR(VLOOKUP(B$3,Data_Entry!$C:$AB,18,0)," ") -> 10350 | C14: =IFERROR(VLOOKUP(C$3,Data_Entry!$C:$AB,18,0)," ") -> 0 | D14: =IFERROR(VLOOKUP(D$3,Data_Entry!$C:$AB,18,0)," ") -> 0 | E14: =IFERROR(VLOOKUP(E$3,Data_Entry!$C:$AB,18,0)," ") -> 0 | F14: =IFERROR(VLOOKUP(F$3,Data_Entry!$C:$AB,18,0)," ") -> 0 | G14: =IFERROR(VLOOKUP(G$3,Data_Entry!$C:$AB,18,0)," ") -> 0 | H14: =IFERROR(VLOOKUP(H$3,Data_Entry!$C:$AB,18,0)," ") -> 0 | I14: =IFERROR(VLOOKUP(I$3,Data_Entry!$C:$AB,18,0)," ") -> 0 | ... AG14: =IFERROR(VLOOKUP(AG$3,Data_Entry!$C:$AB,18,0)," ")
A15: GTI | B15: =IFERROR(VLOOKUP(B$3,Data_Entry!$C:$AB,20,0)," ") -> 3.66 | C15: =IFERROR(VLOOKUP(C$3,Data_Entry!$C:$AB,20,0)," ") -> 0 | D15: =IFERROR(VLOOKUP(D$3,Data_Entry!$C:$AB,20,0)," ") -> 0 | E15: =IFERROR(VLOOKUP(E$3,Data_Entry!$C:$AB,20,0)," ") -> 0 | F15: =IFERROR(VLOOKUP(F$3,Data_Entry!$C:$AB,20,0)," ") -> 0 | G15: =IFERROR(VLOOKUP(G$3,Data_Entry!$C:$AB,20,0)," ") -> 0 | H15: =IFERROR(VLOOKUP(H$3,Data_Entry!$C:$AB,20,0)," ") -> 0 | I15: =IFERROR(VLOOKUP(I$3,Data_Entry!$C:$AB,20,0)," ") -> 0 | ... AF15: =IFERROR(VLOOKUP(AF$3,Data_Entry!$C:$AB,20,0)," ") -> 0
A16: GHI | B16: =IFERROR(VLOOKUP(B$3,Data_Entry!$C:$AB,19,0)," ") -> 0 | C16: =IFERROR(VLOOKUP(C$3,Data_Entry!$C:$AB,19,0)," ") -> 0 | D16: =IFERROR(VLOOKUP(D$3,Data_Entry!$C:$AB,19,0)," ") -> 0 | E16: =IFERROR(VLOOKUP(E$3,Data_Entry!$C:$AB,19,0)," ") -> 0 | F16: =IFERROR(VLOOKUP(F$3,Data_Entry!$C:$AB,19,0)," ") -> 0 | G16: =IFERROR(VLOOKUP(G$3,Data_Entry!$C:$AB,19,0)," ") -> 0 | H16: =IFERROR(VLOOKUP(H$3,Data_Entry!$C:$AB,19,0)," ") -> 0 | I16: =IFERROR(VLOOKUP(I$3,Data_Entry!$C:$AB,19,0)," ") -> 0 | ... AF16: =IFERROR(VLOOKUP(AF$3,Data_Entry!$C:$AB,19,0)," ") -> 0
A17: Module_Temp. | B17: =IFERROR(VLOOKUP(B$3,Data_Entry!$C:$AB,23,0)," ") -> 0 | C17: =IFERROR(VLOOKUP(C$3,Data_Entry!$C:$AB,23,0)," ") -> 0 | D17: =IFERROR(VLOOKUP(D$3,Data_Entry!$C:$AB,23,0)," ") -> 0 | E17: =IFERROR(VLOOKUP(E$3,Data_Entry!$C:$AB,23,0)," ") -> 0 | F17: =IFERROR(VLOOKUP(F$3,Data_Entry!$C:$AB,23,0)," ") -> 0 | G17: =IFERROR(VLOOKUP(G$3,Data_Entry!$C:$AB,23,0)," ") -> 0 | H17: =IFERROR(VLOOKUP(H$3,Data_Entry!$C:$AB,23,0)," ") -> 0 | I17: =IFERROR(VLOOKUP(I$3,Data_Entry!$C:$AB,23,0)," ") -> 0 | ... AF17: =IFERROR(VLOOKUP(AF$3,Data_Entry!$C:$AB,23,0)," ") -> 0
A18: Ambt._Temp. | B18: =IFERROR(VLOOKUP(B$3,Data_Entry!$C:$AB,21,0)," ") -> 34.09 | C18: =IFERROR(VLOOKUP(C$3,Data_Entry!$C:$AB,21,0)," ") -> 0 | D18: =IFERROR(VLOOKUP(D$3,Data_Entry!$C:$AB,21,0)," ") -> 0 | E18: =IFERROR(VLOOKUP(E$3,Data_Entry!$C:$AB,21,0)," ") -> 0 | F18: =IFERROR(VLOOKUP(F$3,Data_Entry!$C:$AB,21,0)," ") -> 0 | G18: =IFERROR(VLOOKUP(G$3,Data_Entry!$C:$AB,21,0)," ") -> 0 | H18: =IFERROR(VLOOKUP(H$3,Data_Entry!$C:$AB,21,0)," ") -> 0 | I18: =IFERROR(VLOOKUP(I$3,Data_Entry!$C:$AB,21,0)," ") -> 0 | ... AF18: =IFERROR(VLOOKUP(AF$3,Data_Entry!$C:$AB,21,0)," ") -> 0
A19: Performance_Ratio_(%) | B19: =IFERROR(B12/B15/(Basic_Data!$G$10),"") -> 1.1796632 | C19: =IFERROR(C12/C15/(Basic_Data!$G$10),"") | D19: =IFERROR(D12/D15/(Basic_Data!$G$10),"") | E19: =IFERROR(E12/E15/(Basic_Data!$G$10),"") | F19: =IFERROR(F12/F15/(Basic_Data!$G$10),"") | G19: =IFERROR(G12/G15/(Basic_Data!$G$10),"") | H19: =IFERROR(H12/H15/(Basic_Data!$G$10),"") | I19: =IFERROR(I12/I15/(Basic_Data!$G$10),"") | ... AG19: =IFERROR(AG12/AG15/(Basic_Data!$G$10),"")
A20: Capacity_Utilization_Factor_(%) | B20: =IFERROR(B12/(Basic_Data!$F$10*24),"") -> 0.22532468 | C20: =IFERROR(C12/(Basic_Data!$F$10*24),"") -> 0 | D20: =IFERROR(D12/(Basic_Data!$F$10*24),"") -> 0 | E20: =IFERROR(E12/(Basic_Data!$F$10*24),"") -> 0 | F20: =IFERROR(F12/(Basic_Data!$F$10*24),"") -> 0 | G20: =IFERROR(G12/(Basic_Data!$F$10*24),"") -> 0 | H20: =IFERROR(H12/(Basic_Data!$F$10*24),"") -> 0 | I20: =IFERROR(I12/(Basic_Data!$F$10*24),"") -> 0 | ... AG20: =IFERROR(AG12/(Basic_Data!$F$10*24),"")
A21: Aux_Consumption_Line_Loss_(%) | B21: =IFERROR((B11-B12)/B11,"") -> -0.0044326258 | C21: =IFERROR((C11-C12)/C11,"") | D21: =IFERROR((D11-D12)/D11,"") | E21: =IFERROR((E11-E12)/E11,"") | F21: =IFERROR((F11-F12)/F11,"") | G21: =IFERROR((G11-G12)/G11,"") | H21: =IFERROR((H11-H12)/H11,"") | I21: =IFERROR((I11-I12)/I11,"") | ... AG21: =IFERROR((AG11-AG12)/AG11,"")

Sheet Data_Entry
B1: Month | C1: Date | D1: Plant_Up_Time | E1: Plant_Down_Time | F1: Inv_1 | G1: Inv_2 | H1: Inv_3 | I1: Inv_4 | J1: Inv_5 | K1: Inv_6 | L1: Inv_7 | M1: Total Inv Gen kWh | N1: ABT_Initial_Export | O1: ABT_Final_Export | P1: Total_Export | Q1: ABT_Initial_Import | R1: ABT_Final_Import | S1: Total_Import | T1: Net_Gen_kWh | U1: GHI (kwh/m2) | V1: GTI (kwh/m2) | W1: Ambt_Temp_Avg | X1: Module_Temp_Avg | Y1: Wtd_Module_Temp | Z1: Wind Speed | AA1: Rain_Gaug_MM | AB1: Weather_Condition
A2: 4 | B2: 45747 | C2: 45747 | M2: =SUM(F2:L2) -> 0 | P2: =MAX((O2-N2)*3000,0) -> 0 | S2: =MAX((R2-Q2)*3000,0) -> 0 | T2: =P2-S2 -> 0
A3: =A2+1 -> 5 | B3: 45748 | C3: 45748 | F3: 1835.13 | G3: 1870.19 | H3: 1924.81 | I3: 2024.97 | J3: 2015.38 | K3: 1981.68 | L3: 1940.1 | M3: =SUM(F3:L3) -> 13592.26 | N3: 115.74 | O3: 120.23 | P3: =MAX((O3-N3)*3000,0) -> 13470 | Q3: 2.22 | R3: 2.23 | S3: =MAX((R3-Q3)*3000,0) -> 30 | T3: =P3-S3 -> 13440 | V3: 5.62675
A4: =A3+1 -> 6 | B4: 45749 | C4: 45749 | F4: 2030.21 | G4: 2070.38 | H4: 2050.23 | I4: 2090.84 | J4: 1976.97 | K4: 1954.77 | L4: 1964.11 | M4: =SUM(F4:L4) -> 14137.51 | N4: 120.23 | O4: 124.9 | P4: =MAX((O4-N4)*3000,0) -> 14010 | Q4: 2.23 | R4: 2.24 | S4: =MAX((R4-Q4)*3000,0) -> 30 | T4: =P4-S4 -> 13980 | V4: 5.84225
A5: =A4+1 -> 7 | B5: 45750 | C5: 45750 | F5: 1839.07 | G5: 1835.52 | H5: 1842.65 | I5: 1952.53 | J5: 1926.93 | K5: 1892.93 | L5: 1877.62 | M5: =SUM(F5:L5) -> 13167.25 | N5: 124.9 | O5: 129.26 | P5: =MAX((O5-N5)*3000,0) -> 13080 | Q5: 2.24 | R5: 2.25 | S5: =MAX((R5-Q5)*3000,0) -> 30 | T5: =P5-S5 -> 13050 | V5: 5.57625
A6: =A5+1 -> 8 | B6: 45751 | C6: 45751 | F6: 1204.78 | G6: 1204.82 | H6: 1209.34 | I6: 1280.18 | J6: 1263.44 | K6: 1261.51 | L6: 1215.94 | M6: =SUM(F6:L6) -> 8640.01 | N6: 129.26 | O6: 132.13 | P6: =MAX((O6-N6)*3000,0) -> 8610 | Q6: 2.25 | R6: 2.26 | S6: =MAX((R6-Q6)*3000,0) -> 30 | T6: =P6-S6 -> 8580 | V6: 3.7295
A7: =A6+1 -> 9 | B7: 45752 | C7: 45752 | F7: 1901.4 | G7: 1902.92 | H7: 1912.27 | I7: 2020.94 | J7: 2001.33 | K7: 2001.08 | L7: 1996.49 | M7: =SUM(F7:L7) -> 13736.43 | N7: 132.13 | O7: 136.67 | P7: =MAX((O7-N7)*3000,0) -> 13620 | Q7: 2.26 | R7: 2.27 | S7: =MAX((R7-Q7)*3000,0) -> 30 | T7: =P7-S7 -> 13590 | V7: 5.72925
A8: =A7+1 -> 10 | B8: 45753 | C8: 45753 | F8: 1512.52 | G8: 1506.96 | H8: 1516.89 | I8: 1599.98 | J8: 1580.61 | K8: 1529.11 | L8: 1521.58 | M8: =SUM(F8:L8) -> 10767.65 | N8: 136.67 | O8: 140.24 | P8: =MAX((O8-N8)*3000,0) -> 10710 | Q8: 2.27 | R8: 2.28 | S8: =MAX((R8-Q8)*3000,0) -> 30 | T8: =P8-S8 -> 10680 | V8: 4.59325
A9: =A8+1 -> 11 | B9: 45754 | C9: 45754 | F9: 1924.03 | G9: 1913.17 | H9: 1908.55 | I9: 2018.33 | J9: 1998.44 | K9: 1967.54 | L9: 1961.47 | M9: =SUM(F9:L9) -> 13691.53 | N9: 140.24 | O9: 144.77 | P9: =MAX((O9-N9)*3000,0) -> 13590 | Q9: 2.28 | R9: 2.29 | S9: =MAX((R9-Q9)*3000,0) -> 30 | T9: =P9-S9 -> 13560 | V9: 5.81075
A10: =A9+1 -> 12 | B10: 45755 | C10: 45755 | F10: 1848.32 | G10: 1867.75 | H10: 1875.25 | I10: 1959.29 | J10: 1935.92 | K10: 1903.02 | L10: 1896.16 | M10: =SUM(F10:L10) -> 13285.71 | N10: 144.77 | O10: 149.18 | P10: =MAX((O10-N10)*3000,0) -> 13230 | Q10: 2.29 | R10: 2.3 | S10: =MAX((R10-Q10)*3000,0) -> 30 | T10: =P10-S10 -> 13200 | V10: 5.62575
A11: =A10+1 -> 13 | B11: 45756 | C11: 45756 | F11: 1821.74 | G11: 1815.37 | H11: 1854.46 | I11: 1962.77 | J11: 1919.49 | K11: 1822.93 | L11: 1816.06 | M11: =SUM(F11:L11) -> 13012.82 | N11: 149.18 | O11: 153.49 | P11: =MAX((O11-N11)*3000,0) -> 12930 | Q11: 2.3 | R11: 2.31 | S11: =MAX((R11-Q11)*3000,0) -> 30 | T11: =P11-S11 -> 12900 | V11: 5.58175
A12: =A11+1 -> 14 | B12: 45757 | C12: 45757 | F12: 1842.03 | G12: 1834.36 | H12: 1847.15 | I12: 1960.9 | J12: 1944.94 | K12: 1833.69 | L12: 1833.3 | M12: =SUM(F12:L12) -> 13096.37 | N12: =O11 -> 153.49 | O12: 157.83 | P12: =MAX((O12-N12)*3000,0) -> 13020 | Q12: =R11 -> 2.31 | R12: 2.32 | S12: =MAX((R12-Q12)*3000,0) -> 30 | T12: =P12-S12 -> 12990 | V12: 5.5 | AB12: sunny
A13: =A12+1 -> 15 | B13: 45758 | C13: 45758 | F13: 1963.34 | G13: 1954.17 | H13: 1964.66 | I13: 2086.81 | J13: 2068.93 | K13: 1968.66 | L13: 1945.98 | M13: =SUM(F13:L13) -> 13952.55 | N13: =O12 -> 157.83 | O13: 162.47 | P13: =MAX((O13-N13)*3000,0) -> 13920 | Q13: =R12 -> 2.32 | R13: 2.33 | S13: =MAX((R13-Q13)*3000,0) -> 30 | T13: =P13-S13 -> 13890 | V13: 5.84
A14: =A13+1 -> 16 | B14: 45759 | C14: 45759 | F14: 1842.4 | G14: 1918.81 | H14: 1928.86 | I14: 2067.29 | J14: 2060.71 | K14: 1961.26 | L14: 1889.97 | M14: =SUM(F14:L14) -> 13669.3 | N14: =O13 -> 162.47 | O14: 167 | P14: =MAX((O14-N14)*3000,0) -> 13590 | Q14: =R13 -> 2.33 | R14: 2.34 | S14: =MAX((R14-Q14)*3000,0) -> 30 | T14: =P14-S14 -> 13560 | V14: 5.8 | AB14: sunny
A15: =A14+1 -> 17 | B15: 45760 | C15: 45760 | F15: 1673.29 | G15: 1672.24 | H15: 1680.55 | I15: 1774.79 | J15: 1766.34 | K15: 1756.63 | L15: 1707.53 | M15: =SUM(F15:L15) -> 12031.37 | N15: =O14 -> 167 | O15: 171 | P15: =MAX((O15-N15)*3000,0) -> 12000 | Q15: =R14 -> 2.34 | R15: 2.35 | S15: =MAX((R15-Q15)*3000,0) -> 30 | T15: =P15-S15 -> 11970 | V15: 5.18 | AB15: sunny
A16: =A15+1 -> 18 | B16: 45761 | C16: 45761 | F16: 1952.59 | G16: 1988.01 | H16: 2002.92 | I16: 2108.16 | J16: 2100.86 | K16: 2029.73 | L16: 1974.38 | M16: =SUM(F16:L16) -> 14156.65 | N16: =O15 -> 171 | O16: 175.69 | P16: =MAX((O16-N16)*3000,0) -> 14070 | Q16: =R15 -> 2.35 | R16: 2.36 | S16: =MAX((R16-Q16)*3000,0) -> 30 | T16: =P16-S16 -> 14040 | V16: 6 | AB16: sunny
A17: =A16+1 -> 19 | B17: 45762 | C17: 45762 | F17: 1974.76 | G17: 1993.71 | H17: 1977.81 | I17: 2076.65 | J17: 2065.61 | K17: 2004.68 | L17: 2001.35 | M17: =SUM(F17:L17) -> 14094.57 | N17: =O16 -> 175.69 | O17: 180.36 | P17: =MAX((O17-N17)*3000,0) -> 14010 | Q17: =R16 -> 2.36 | R17: 2.37 | S17: =MAX((R17-Q17)*3000,0) -> 30 | T17: =P17-S17 -> 13980 | V17: 5.85 | AB17: sunny
A18: =A17+1 -> 20 | B18: 45763 | C18: 45763 | F18: 788.49 | G18: 785.73 | H18: 787.52 | I18: 828.68 | J18: 830.1 | K18: 827.23 | L18: 811.94 | M18: =SUM(F18:L18) -> 5659.69 | N18: =O17 -> 180.36 | O18: 182.25 | P18: =MAX((O18-N18)*3000,0) -> 5670 | Q18: =R17 -> 2.37 | R18: 2.38 | S18: =MAX((R18-Q18)*3000,0) -> 30 | T18: =P18-S18 -> 5640 | V18: 2.29 | W18: 35.67 | AB18: sunny
A19: =A18+1 -> 21 | B19: 45764 | C19: 45764 | F19: 1977.99 | G19: 2035.23 | H19: 2039.84 | I19: 2145.76 | J19: 2143.04 | K19: 2103.82 | L19: 2056.41 | M19: =SUM(F19:L19) -> 14502.09 | N19: =O18 -> 182.25 | O19: 187.05 | P19: =MAX((O19-N19)*3000,0) -> 14400 | Q19: =R18 -> 2.38 | R19: 2.39 | S19: =MAX((R19-Q19)*3000,0) -> 30 | T19: =P19-S19 -> 14370 | V19: 6.08 | AB19: sunny
A20: =A19+1 -> 22 | B20: 45765 | C20: 45765 | F20: 2025.69 | G20: 2028.78 | H20: 2034.75 | I20: 2034.88 | J20: 2139.47 | K20: 2088.99 | L20: 2045.64 | M20: =SUM(F20:L20) -> 14398.2 | N20: =O19 -> 187.05 | O20: 191.86 | P20: =MAX((O20-N20)*3000,0) -> 14430 | Q20: =R19 -> 2.39 | R20: 2.4 | S20: =MAX((R20-Q20)*3000,0) -> 30 | T20: =P20-S20 -> 14400 | V20: 6.08 | W20: 35.57 | AB20: sunny
A21: =A20+1 -> 23 | B21: 45766 | C21: 45766 | F21: 1951.34 | G21: 2008.08 | H21: 2010.19 | I21: 2138.15 | J21: 2148.49 | K21: 2018.81 | L21: 1290.67 | M21: =SUM(F21:L21) -> 13565.73 | N21: =O20 -> 191.86 | O21: 196.36 | P21: =MAX((O21-N21)*3000,0) -> 13500 | Q21: =R20 -> 2.4 | R21: 2.41 | S21: =MAX((R21-Q21)*3000,0) -> 30 | T21: =P21-S21 -> 13470 | V21: 6.04 | W21: 33.8 | AB21: sunny
A22: =A21+1 -> 24 | B22: 45767 | C22: 45767 | F22: 1975.37 | G22: 2007.14 | H22: 2040.76 | I22: 2160.72 | J22: 2156.02 | K22: 2057.98 | L22: 1189.68 | M22: =SUM(F22:L22) -> 13587.67 | N22: =O21 -> 196.36 | O22: 200.87 | P22: =MAX((O22-N22)*3000,0) -> 13530 | Q22: =R21 -> 2.41 | R22: 2.42 | S22: =MAX((R22-Q22)*3000,0) -> 30 | T22: =P22-S22 -> 13500 | V22: 6.13 | W22: 34.14 | AB22: sunny
A23: =A22+1 -> 25 | B23: 45768 | C23: 45768 | F23: 1788.16 | G23: 1896.38 | H23: 1951.13 | I23: 2079.83 | J23: 2062.5 | K23: 1839.86 | L23: 1795.23 | M23: =SUM(F23:L23) -> 13413.09 | N23: =O22 -> 200.87 | O23: 205.32 | P23: =MAX((O23-N23)*3000,0) -> 13350 | Q23: =R22 -> 2.42 | R23: 2.43 | S23: =MAX((R23-Q23)*3000,0) -> 30 | T23: =P23-S23 -> 13320 | V23: 6.1 | W23: 34.98 | AB23: sunny
A24: =A23+1 -> 26 | B24: 45769 | C24: 45769 | F24: 1901.85 | G24: 1985.07 | H24: 2029.06 | I24: 2114.2 | J24: 2117.29 | K24: 2022.86 | L24: 1985.33 | M24: =SUM(F24:L24) -> 14155.66 | N24: =O23 -> 205.32 | O24: 210 | P24: =MAX((O24-N24)*3000,0) -> 14040 | Q24: =R23 -> 2.43 | R24: 2.44 | S24: =MAX((R24-Q24)*3000,0) -> 30 | T24: =P24-S24 -> 14010 | V24: 6.18 | W24: 36.39 | AB24: sunny
A25: =A24+1 -> 27 | B25: 45770 | C25: 45770 | F25: 1878.4 | G25: 1882.51 | H25: 1884.98 | I25: 1996.83 | J25: 1975.88 | K25: 1966.1 | L25: 1934.02 | M25: =SUM(F25:L25) -> 13518.72 | N25: =O24 -> 210 | O25: 214.47 | P25: =MAX((O25-N25)*3000,0) -> 13410 | Q25: =R24 -> 2.44 | R25: 2.45 | S25: =MAX((R25-Q25)*3000,0) -> 30 | T25: =P25-S25 -> 13380 | V25: 6 | W25: 36.39 | AB25: sunny
A26: =A25+1 -> 28 | B26: 45771 | C26: 45771 | F26: 1995.4 | G26: 1987.48 | H26: 1989.32 | I26: 2083.5 | J26: 2094.35 | K26: 2090.27 | L26: 2077.18 | M26: =SUM(F26:L26) -> 14317.5 | N26: =O25 -> 214.47 | O26: 219.22 | P26: =MAX((O26-N26)*3000,0) -> 14250 | Q26: =R25 -> 2.45 | R26: 2.46 | S26: =MAX((R26-Q26)*3000,0) -> 30 | T26: =P26-S26 -> 14220 | V26: 6.14 | W26: 35.07 | AB26: sunny
A27: =A26+1 -> 29 | B27: 45772 | C27: 45772 | F27: 2028.14 | G27: 2036.48 | H27: 2041.13 | I27: 2130.61 | J27: 2116.63 | K27: 2114.42 | L27: 2089.69 | M27: =SUM(F27:L27) -> 14557.1 | N27: =O26 -> 219.22 | O27: 224.05 | P27: =MAX((O27-N27)*3000,0) -> 14490 | Q27: =R26 -> 2.46 | R27: 2.47 | S27: =MAX((R27-Q27)*3000,0) -> 30 | T27: =P27-S27 -> 14460 | V27: 6.26 | W27: 34.21 | AB27: sunny
A28: =A27+1 -> 30 | B28: 45773 | C28: 45773 | F28: 2029.62 | G28: 2024.87 | H28: 2030.4 | I28: 2126.02 | J28: 2110.91 | K28: 2111.38 | L28: 2085.91 | M28: =SUM(F28:L28) -> 14519.11 | N28: =O27 -> 224.05 | O28: 228.86 | P28: =MAX((O28-N28)*3000,0) -> 14430 | Q28: =R27 -> 2.47 | R28: 2.48 | S28: =MAX((R28-Q28)*3000,0) -> 30 | T28: =P28-S28 -> 14400 | V28: 4.79 | W28: 34.5 | AB28: sunny
A29: =A28+1 -> 31 | B29: 45774 | C29: 45774 | F29: 1994.33 | G29: 1989.53 | H29: 1995.49 | I29: 2088.54 | J29: 2074.3 | K29: 2077.1 | L29: 2048.8 | M29: =SUM(F29:L29) -> 14268.09 | N29: =O28 -> 228.86 | O29: 233.6 | P29: =MAX((O29-N29)*3000,0) -> 14220 | Q29: =R28 -> 2.48 | R29: 2.49 | S29: =MAX((R29-Q29)*3000,0) -> 30 | T29: =P29-S29 -> 14190 | V29: 5.39 | W29: 35.93 | AB29: sunny
A30: =A29+1 -> 32 | B30: 45775 | C30: 45775 | D30: 0.28125 | E30: 0.78125 | F30: 1996.71 | G30: 1984.21 | H30: 1988.57 | I30: 2088.69 | J30: 2073.65 | K30: 2076.25 | L30: 2045.55 | M30: =SUM(F30:L30) -> 14253.63 | N30: =O29 -> 233.6 | O30: 238.33 | P30: =MAX((O30-N30)*3000,0) -> 14190 | Q30: =R29 -> 2.49 | R30: 2.5 | S30: =MAX((R30-Q30)*3000,0) -> 30 | T30: =P30-S30 -> 14160 | V30: 6.19 | W30: 36.38 | AB30: sunny
A31: =A30+1 -> 33 | B31: 45776 | C31: 45776 | D31: 0.28125 | E31: 0.78125 | F31: 2044.76 | G31: 2019.81 | H31: 2026.65 | I31: 2130.06 | J31: 2115.2 | K31: 2112.2 | L31: 2083.24 | M31: =SUM(F31:L31) -> 14531.92 | N31: =O30 -> 238.33 | O31: 243.15 | P31: =MAX((O31-N31)*3000,0) -> 14460 | Q31: =R30 -> 2.5 | R31: 2.51 | S31: =MAX((R31-Q31)*3000,0) -> 30 | T31: =P31-S31 -> 14430 | V31: 6.29 | W31: 36.86 | AB31: sunny
A32: =A31+1 -> 34 | B32: 45777 | C32: 45777 | D32: 0.28125 | E32: 0.78125 | F32: 1996.33 | G32: 1970.12 | H32: 1975.8 | I32: 2077.24 | J32: 2057.78 | K32: 2054.03 | L32: 2030.39 | M32: =SUM(F32:L32) -> 14161.69 | N32: =O31 -> 243.15 | O32: 247.85 | P32: =MAX((O32-N32)*3000,0) -> 14100 | Q32: =R31 -> 2.51 | R32: 2.52 | S32: =MAX((R32-Q32)*3000,0) -> 30 | T32: =P32-S32 -> 14070 | V32: 6.11 | W32: 35.7 | AB32: sunny
A33: =A32+1 -> 35 | B33: 45778 | C33: 45778 | D33: 0.28125 | E33: 0.78125 | F33: 2026.21 | G33: 2013.32 | H33: 1985.18 | I33: 2083.83 | J33: 2062.34 | K33: 2062.25 | L33: 2033.98 | M33: =SUM(F33:L33) -> 14267.11 | N33: =O32 -> 247.85 | O33: 252.57 | P33: =MAX((O33-N33)*3000,0) -> 14160 | Q33: =R32 -> 2.52 | R33: 2.54 | S33: =MAX((R33-Q33)*3000,0) -> 60 | T33: =P33-S33 -> 14100 | V33: 6.15 | W33: 35.41 | AB33: sunny
A34: =A33+1 -> 36 | B34: 45779 | C34: 45779 | D34: 0.28125 | E34: 0.78125 | F34: 2090.6 | G34: 2100.55 | H34: 2084.02 | I34: 2136.4 | J34: 2108.4 | K34: 2077.87 | L34: 2059.08 | M34: =SUM(F34:L34) -> 14656.92 | N34: =O33 -> 252.57 | O34: 257.43 | P34: =MAX((O34-N34)*3000,0) -> 14580 | Q34: =R33 -> 2.54 | R34: 2.55 | S34: =MAX((R34-Q34)*3000,0) -> 30 | T34: =P34-S34 -> 14550 | V34: 6.37 | W34: 35.15 | AB34: sunny
A35: =A34+1 -> 37 | B35: 45780 | C35: 45780 | D35: 0.28125 | E35: 0.78125 | F35: 2017.9 | G35: 2001.08 | H35: 1998.29 | I35: 2107.24 | J35: 2090.08 | K35: 2072.24 | L35: 2064.53 | M35: =SUM(F35:L35) -> 14351.36 | N35: =O34 -> 257.43 | O35: 262.19 | P35: =MAX((O35-N35)*3000,0) -> 14280 | Q35: =R34 -> 2.55 | R35: 2.56 | S35: =MAX((R35-Q35)*3000,0) -> 30 | T35: =P35-S35 -> 14250 | V35: 6.04 | W35: 33.5 | AB35: sunny
A36: =A35+1 -> 38 | B36: 45781 | C36: 45781 | D36: 0.28125 | E36: 0.78125 | F36: 1834.03 | G36: 1817.55 | H36: 1818.25 | I36: 1922.44 | J36: 1908 | K36: 1891.53 | L36: 1895.28 | M36: =SUM(F36:L36) -> 13087.08 | N36: =O35 -> 262.19 | O36: 266.54 | P36: =MAX((O36-N36)*3000,0) -> 13050 | Q36: =R35 -> 2.56 | R36: 2.57 | S36: =MAX((R36-Q36)*3000,0) -> 30 | T36: =P36-S36 -> 13020 | V36: 5.46 | W36: 33.43 | AB36: sunny
A37: =A36+1 -> 39 | B37: 45782 | C37: 45782 | D37: 0.28125 | E37: 0.78125 | F37: 1806.97 | G37: 1791.49 | H37: 1791.72 | I37: 1888.35 | J37: 1876.54 | K37: 1858.44 | L37: 1859.93 | M37: =SUM(F37:L37) -> 12873.44 | N37: =O36 -> 266.54 | O37: 270.82 | P37: =MAX((O37-N37)*3000,0) -> 12840 | Q37: =R36 -> 2.57 | R37: 2.58 | S37: =MAX((R37-Q37)*3000,0) -> 30 | T37: =P37-S37 -> 12810 | V37: 5.35 | W37: 33.26 | AB37: mostly cloudy
A38: =A37+1 -> 40 | B38: 45783 | C38: 45783 | D38: 0.34583333 | E38: 0.6875 | F38: 1317.3 | G38: 1309.2 | H38: 1313.71 | I38: 1373.91 | J38: 1370.27 | K38: 1376.01 | L38: 1363.9 | M38: =SUM(F38:L38) -> 9424.3 | N38: =O37 -> 270.82 | O38: 273.96 | P38: =MAX((O38-N38)*3000,0) -> 9420 | Q38: =R37 -> 2.58 | R38: 2.59 | S38: =MAX((R38-Q38)*3000,0) -> 30 | T38: =P38-S38 -> 9390 | V38: 3.55 | W38: 31.94 | AB38: cloudy
A39: =A38+1 -> 41 | B39: 45784 | C39: 45784 | D39: 0.28125 | E39: 0.77083333 | F39: 929.05 | G39: 925.15 | H39: 927.51 | I39: 966.02 | J39: 956.79 | K39: 959.16 | L39: 951.02 | M39: =SUM(F39:L39) -> 6614.7 | N39: =O38 -> 273.96 | O39: 276.14 | P39: =MAX((O39-N39)*3000,0) -> 6540 | Q39: =R38 -> 2.59 | R39: 2.6 | S39: =MAX((R39-Q39)*3000,0) -> 30 | T39: =P39-S39 -> 6510 | V39: 3.33 | W39: 26.75 | AB39: rainy
A40: =A39+1 -> 42 | B40: 45785 | C40: 45785 | D40: 0.28125 | E40: 0.77083333 | F40: 1838.54 | G40: 1835.84 | H40: 1842.84 | I40: 1939.87 | J40: 1933.94 | K40: 1918.22 | L40: 1889.83 | M40: =SUM(F40:L40) -> 13199.08 | N40: =O39 -> 276.14 | O40: 280.55 | P40: =MAX((O40-N40)*3000,0) -> 13230 | Q40: =R39 -> 2.6 | R40: 2.61 | S40: =MAX((R40-Q40)*3000,0) -> 30 | T40: =P40-S40 -> 13200 | V40: 5.53 | W40: 31.24 | AB40: cloudy
A41: =A40+1 -> 43 | B41: 45786 | C41: 45786 | D41: 0.28125 | E41: 0.73958333 | F41: 1515.61 | G41: 1500.45 | H41: 1500.77 | I41: 1568.9 | J41: 1558.6 | K41: 1563.39 | L41: 1554.15 | M41: =SUM(F41:L41) -> 10761.87 | N41: =O40 -> 280.55 | O41: 284.12 | P41: =MAX((O41-N41)*3000,0) -> 10710 | Q41: =R40 -> 2.61 | R41: 2.62 | S41: =MAX((R41-Q41)*3000,0) -> 30 | T41: =P41-S41 -> 10680 | V41: 4.81 | W41: 31.95 | AB41: cloudy
... A59: =A58+1 -> 61 | B59: 45804 | C59: 45804 | D59: 0.27083333 | E59: 0.79166667 | F59: 827.84 | G59: 821.25 | H59: 825.93 | I59: 865.98 | J59: 856.99 | K59: 856.8 | L59: 848.15 | M59: =SUM(F59:L59) -> 5902.94 | N59: =O58 -> 355.56 | O59: 357.56 | P59: =MAX((O59-N59)*3000,0) -> 6000 | Q59: =R58 -> 2.8 | R59: 2.81 | S59: =MAX((R59-Q59)*3000,0) -> 30 | T59: =P59-S59 -> 5970 | V59: 2.35 | W59: 29.7 | AB59: cloudy
A60: =A59+1 -> 62 | B60: 45805 | C60: 45805 | F60: 1574.84 | G60: 1559.58 | H60: 1561.93 | I60: 1642.12 | J60: 1626.16 | K60: 1626.36 | L60: 1604.87 | M60: =SUM(F60:L60) -> 11195.86 | N60: =O59 -> 357.56 | O60: 361.3 | P60: =MAX((O60-N60)*3000,0) -> 11220 | Q60: =R59 -> 2.81 | R60: 2.82 | S60: =MAX((R60-Q60)*3000,0) -> 30 | T60: =P60-S60 -> 11190 | V60: 2.26 | W60: 34.42 | AB60: cloudy
A61: =A60+1 -> 63 | B61: 45806 | C61: 45806 | D61: 0.28125 | E61: 0.79166667 | F61: 1807.57 | G61: 1792.63 | H61: 1793.85 | I61: 1884.19 | J61: 1864.4 | K61: 1867.79 | L61: 1849.54 | M61: =SUM(F61:L61) -> 12859.97 | N61: =O60 -> 361.3 | O61: 365.59 | P61: =MAX((O61-N61)*3000,0) -> 12870 | Q61: =R60 -> 2.82 | R61: 2.83 | S61: =MAX((R61-Q61)*3000,0) -> 30 | T61: =P61-S61 -> 12840 | V61: 5.53 | W61: 33.5 | AB61: cloudy
A62: =A61+1 -> 64 | B62: 45807 | C62: 45807 | D62: 0.28125 | E62: 0.79166667 | F62: 1857.08 | G62: 1842.7 | H62: 1841.87 | I62: 1944.52 | J62: 1909.74 | K62: 1918.93 | L62: 1903.89 | M62: =SUM(F62:L62) -> 13218.73 | N62: =O61 -> 365.59 | O62: 369.99 | P62: =MAX((O62-N62)*3000,0) -> 13200 | Q62: =R61 -> 2.83 | R62: 2.84 | S62: =MAX((R62-Q62)*3000,0) -> 30 | T62: =P62-S62 -> 13170 | V62: 5.86 | W62: 33.58 | AB62: sunny
A63: =A62+1 -> 65 | B63: 45808 | C63: 45808 | D63: 0.27083333 | E63: 0.73958333 | F63: 1770 | G63: 1769.16 | H63: 1767.12 | I63: 1865.51 | J63: 1837.57 | K63: 1842.54 | L63: 1827.67 | M63: =SUM(F63:L63) -> 12679.57 | N63: =O62 -> 369.99 | O63: 374.21 | P63: =MAX((O63-N63)*3000,0) -> 12660 | Q63: =R62 -> 2.84 | R63: 2.85 | S63: =MAX((R63-Q63)*3000,0) -> 30 | T63: =P63-S63 -> 12630 | V63: 5.61 | W63: 33.52 | AB63: sunny
A64: =A63+1 -> 66 | B64: 45809 | C64: 45809 | D64: 0.27083333 | E64: 0.79166667 | F64: 1773.5 | G64: 1761.98 | H64: 1760.35 | I64: 1869.64 | J64: 1829.73 | K64: 1837.29 | L64: 1818.85 | M64: =SUM(F64:L64) -> 12651.34 | N64: =O63 -> 374.21 | O64: 378.43 | P64: =MAX((O64-N64)*3000,0) -> 12660 | Q64: =R63 -> 2.85 | R64: 2.86 | S64: =MAX((R64-Q64)*3000,0) -> 30 | T64: =P64-S64 -> 12630 | V64: 5.54 | W64: 33.07 | AB64: sunny
A65: =A64+1 -> 67 | B65: 45810 | C65: 45810 | D65: 0.27083333 | E65: 0.79166667 | F65: 1367.97 | G65: 1360.37 | H65: 1361 | I65: 1447.41 | J65: 1409.67 | K65: 1413.02 | L65: 1398.23 | M65: =SUM(F65:L65) -> 9757.67 | N65: =O64 -> 378.43 | O65: 381.7 | P65: =MAX((O65-N65)*3000,0) -> 9810 | Q65: =R64 -> 2.86 | R65: 2.87 | S65: =MAX((R65-Q65)*3000,0) -> 30 | T65: =P65-S65 -> 9780 | V65: 4.52 | W65: 32.8 | AB65: cloudy
A66: =A65+1 -> 68 | B66: 45811 | C66: 45811 | D66: 0.27083333 | E66: 0.79166667 | F66: 1552.72 | G66: 1540.87 | H66: 1541.72 | I66: 1638.23 | J66: 1597.22 | K66: 1601.28 | L66: 1581.09 | M66: =SUM(F66:L66) -> 11053.13 | N66: =O65 -> 381.7 | O66: 385.39 | P66: =MAX((O66-N66)*3000,0) -> 11070 | Q66: =R65 -> 2.87 | R66: 2.88 | S66: =MAX((R66-Q66)*3000,0) -> 30 | T66: =P66-S66 -> 11040 | V66: 5.16 | W66: 33.29 | AB66: sunny
A67: =A66+1 -> 69 | B67: 45812 | C67: 45812 | D67: 0.27083333 | E67: 0.79166667 | F67: 1709.77 | G67: 1680.12 | H67: 1676.06 | I67: 1781.82 | J67: 1736.74 | K67: 1744.86 | L67: 1724.58 | M67: =SUM(F67:L67) -> 12053.95 | N67: =O66 -> 385.39 | O67: 389.41 | P67: =MAX((O67-N67)*3000,0) -> 12060 | Q67: =R66 -> 2.88 | R67: 2.89 | S67: =MAX((R67-Q67)*3000,0) -> 30 | T67: =P67-S67 -> 12030 | V67: 5.56 | W67: 33.27 | AB67: sunny
A68: =A67+1 -> 70 | B68: 45813 | C68: 45813 | D68: 0.27083333 | E68: 0.77083333 | F68: 1817.04 | G68: 1802.13 | H68: 1785.68 | I68: 1857.58 | J68: 1863.28 | K68: 1852.36 | L68: 1849.01 | M68: =SUM(F68:L68) -> 12827.08 | N68: =O67 -> 389.41 | O68: 393.47 | P68: =MAX((O68-N68)*3000,0) -> 12180 | Q68: =R67 -> 2.89 | R68: 2.9 | S68: =MAX((R68-Q68)*3000,0) -> 30 | T68: =P68-S68 -> 12150 | V68: 5.51 | W68: 34.65 | AB68: sunny
A69: =A68+1 -> 71 | B69: 45814 | C69: 45814 | D69: 0.28125 | E69: 0.79166667 | F69: 1720.18 | G69: 1717.79 | H69: 1734.11 | I69: 1820.47 | J69: 1781.23 | K69: 1779.1 | L69: 1758.79 | M69: =SUM(F69:L69) -> 12311.67 | N69: =O68 -> 393.47 | O69: 397.56 | P69: =MAX((O69-N69)*3000,0) -> 12270 | Q69: =R68 -> 2.9 | R69: 2.91 | S69: =MAX((R69-Q69)*3000,0) -> 30 | T69: =P69-S69 -> 12240 | V69: 5.48 | W69: 33.93 | AB69: sunny
A70: =A69+1 -> 72 | B70: 45815 | C70: 45815 | D70: 0.28125 | E70: 0.80208333 | F70: 1735.11 | G70: 1728.55 | H70: 1735.17 | I70: 1822.7 | J70: 1807.37 | K70: 1820.5 | L70: 1804.01 | M70: =SUM(F70:L70) -> 12453.41 | N70: =O69 -> 397.56 | O70: 401.69 | P70: =MAX((O70-N70)*3000,0) -> 12390 | Q70: =R69 -> 2.91 | R70: 2.92 | S70: =MAX((R70-Q70)*3000,0) -> 30 | T70: =P70-S70 -> 12360 | V70: 5.62 | W70: 34.2 | AB70: sunny
A71: =A70+1 -> 73 | B71: 45816 | C71: 45816 | D71: 0.27083333 | E71: 0.79166667 | F71: 1765.45 | G71: 1755.82 | H71: 1768.66 | I71: 1865.19 | J71: 1849.68 | K71: 1866.61 | L71: 1850.79 | M71: =SUM(F71:L71) -> 12722.2 | N71: =O70 -> 401.69 | O71: 405.93 | P71: =MAX((O71-N71)*3000,0) -> 12720 | Q71: =R70 -> 2.92 | R71: 2.93 | S71: =MAX((R71-Q71)*3000,0) -> 30 | T71: =P71-S71 -> 12690 | V71: 5.5 | W71: 33.5 | AB71: sunny
A72: =A71+1 -> 74 | B72: 45817 | C72: 45817 | D72: 0.27083333 | E72: 0.79166667 | F72: 1883.11 | G72: 1868.94 | H72: 1874.49 | I72: 1970.16 | J72: 1951.11 | K72: 1955.21 | L72: 1945.17 | M72: =SUM(F72:L72) -> 13448.19 | N72: =O71 -> 405.93 | O72: 410.4 | P72: =MAX((O72-N72)*3000,0) -> 13410 | Q72: =R71 -> 2.93 | R72: 2.94 | S72: =MAX((R72-Q72)*3000,0) -> 30 | T72: =P72-S72 -> 13380 | V72: 5.91 | W72: 33.52 | AB72: sunny
... A142: =A141+1 -> 144 | B142: 45887 | C142: 45887 | D142: 0.29166667 | E142: 0.78125 | F142: 1145.57 | G142: 1139.07 | H142: 1140.12 | I142: 1180.83 | J142: 1181.56 | K142: 1183.7 | L142: 1163.79 | M142: =SUM(F142:L142) -> 8134.64 | N142: =O141 -> 577.79 | O142: 580.49 | P142: =MAX((O142-N142)*3000,0) -> 8100 | Q142: =R141 -> 4.13 | R142: 4.14 | S142: =MAX((R142-Q142)*3000,0) -> 30 | T142: =P142-S142 -> 8070 | V142: 2.69 | W142: 30.29 | AB142: rainy
A143: =A142+1 -> 145 | B143: 45888 | C143: 45888 | F143: 1380.2 | G143: 1388.46 | H143: 1406.82 | I143: 1457.52 | J143: 1474.51 | K143: 1480.19 | L143: 1456.63 | M143: =SUM(F143:L143) -> 10044.33 | N143: =O142 -> 580.49 | O143: 583.79 | P143: =MAX((O143-N143)*3000,0) -> 9900 | Q143: =R142 -> 4.14 | R143: 4.16 | S143: =MAX((R143-Q143)*3000,0) -> 60 | T143: =P143-S143 -> 9840
A144: =A143+1 -> 146 | B144: 45889 | C144: 45889 | F144: 399.9 | G144: 397.14 | H144: 401.71 | I144: 417.4 | J144: 413.01 | K144: 412.18 | L144: 406.96 | M144: =SUM(F144:L144) -> 2848.3 | N144: =O143 -> 583.79 | O144: 584.76 | P144: =MAX((O144-N144)*3000,0) -> 2910 | Q144: =R143 -> 4.16 | R144: 4.19 | S144: =MAX((R144-Q144)*3000,0) -> 90 | T144: =P144-S144 -> 2820
A145: =A144+1 -> 147 | B145: 45890 | C145: 45890 | F145: 1149.89 | G145: 1145.08 | H145: 1145.36 | I145: 1177.09 | J145: 1195.32 | K145: 1180.98 | L145: 1150.25 | M145: =SUM(F145:L145) -> 8143.97 | N145: =O144 -> 584.76 | O145: 587.47 | P145: =MAX((O145-N145)*3000,0) -> 8130 | Q145: =R144 -> 4.19 | R145: 4.21 | S145: =MAX((R145-Q145)*3000,0) -> 60 | T145: =P145-S145 -> 8070
A146: =A145+1 -> 148 | B146: 45891 | C146: 45891 | F146: 1374.57 | G146: 1371.43 | H146: 1366.61 | I146: 1389.93 | J146: 1400.25 | K146: 1396.29 | L146: 1364.1 | M146: =SUM(F146:L146) -> 9663.18 | N146: =O145 -> 587.47 | O146: 590.68 | P146: =MAX((O146-N146)*3000,0) -> 9630 | Q146: =R145 -> 4.21 | R146: 4.23 | S146: =MAX((R146-Q146)*3000,0) -> 60 | T146: =P146-S146 -> 9570
A147: =A146+1 -> 149 | B147: 45892 | C147: 45892 | F147: 762.34 | G147: 754.83 | H147: 754.33 | I147: 776.25 | J147: 776.6 | K147: 774.16 | L147: 759.27 | M147: =SUM(F147:L147) -> 5357.78 | N147: =O146 -> 590.68 | O147: 592.46 | P147: =MAX((O147-N147)*3000,0) -> 5340 | Q147: =R146 -> 4.23 | R147: 4.25 | S147: =MAX((R147-Q147)*3000,0) -> 60 | T147: =P147-S147 -> 5280
A148: =A147+1 -> 150 | B148: 45893 | C148: 45893 | F148: 533.22 | G148: 526.64 | H148: 527.54 | I148: 544.76 | J148: 583.75 | K148: 535.63 | L148: 525.21 | M148: =SUM(F148:L148) -> 3776.75 | N148: =O147 -> 592.46 | O148: 593.7 | P148: =MAX((O148-N148)*3000,0) -> 3720 | Q148: =R147 -> 4.25 | R148: 4.27 | S148: =MAX((R148-Q148)*3000,0) -> 60 | T148: =P148-S148 -> 3660
A149: =A148+1 -> 151 | B149: 45894 | C149: 45894 | F149: 935.02 | G149: 929.56 | H149: 931.54 | I149: 966.11 | J149: 965.56 | K149: 966.12 | L149: 948.72 | M149: =SUM(F149:L149) -> 6642.63 | N149: =O148 -> 593.7 | O149: 595.9 | P149: =MAX((O149-N149)*3000,0) -> 6600 | Q149: =R148 -> 4.27 | R149: 4.29 | S149: =MAX((R149-Q149)*3000,0) -> 60 | T149: =P149-S149 -> 6540
A150: =A149+1 -> 152 | B150: 45895 | C150: 45895 | F150: 1076.69 | G150: 1068.86 | H150: 1070.9 | I150: 1107.13 | J150: 1115.43 | K150: 1114.69 | L150: 1090.97 | M150: =SUM(F150:L150) -> 7644.67 | N150: =O149 -> 595.9 | O150: 598.46 | P150: =MAX((O150-N150)*3000,0) -> 7680 | Q150: =R149 -> 4.29 | R150: 4.31 | S150: =MAX((R150-Q150)*3000,0) -> 60 | T150: =P150-S150 -> 7620
A151: =A150+1 -> 153 | B151: 45896 | C151: 45896 | F151: 1127.38 | G151: 1124.91 | H151: 1127.66 | I151: 1167.77 | J151: 1175.87 | K151: 1173.46 | L151: 1149.73 | M151: =SUM(F151:L151) -> 8046.78 | N151: =O150 -> 598.46 | O151: 601.16 | P151: =MAX((O151-N151)*3000,0) -> 8100 | Q151: =R150 -> 4.31 | R151: 4.33 | S151: =MAX((R151-Q151)*3000,0) -> 60 | T151: =P151-S151 -> 8040
A152: =A151+1 -> 154 | B152: 45897 | C152: 45897 | F152: 1295.42 | G152: 1291.65 | H152: 1299.83 | I152: 1341.19 | J152: 1355.54 | K152: 1359.43 | L152: 1341.46 | M152: =SUM(F152:L152) -> 9284.52 | N152: =O151 -> 601.16 | O152: 604.26 | P152: =MAX((O152-N152)*3000,0) -> 9300 | Q152: =R151 -> 4.33 | R152: 4.35 | S152: =MAX((R152-Q152)*3000,0) -> 60 | T152: =P152-S152 -> 9240
A153: =A152+1 -> 155 | B153: 45898 | C153: 45898 | F153: 1023.06 | G153: 1020.35 | H153: 1025.9 | I153: 1060.92 | J153: 1068.4 | K153: 1071.03 | L153: 1054.28 | M153: =SUM(F153:L153) -> 7323.94 | N153: =O152 -> 604.26 | O153: 606.7 | P153: =MAX((O153-N153)*3000,0) -> 7320 | Q153: =R152 -> 4.35 | R153: 4.37 | S153: =MAX((R153-Q153)*3000,0) -> 60 | T153: =P153-S153 -> 7260
A154: =A153+1 -> 156 | B154: 45899 | C154: 45899 | F154: 1070.33 | G154: 1064.26 | H154: 1066.65 | I154: 1102.71 | J154: 1109.58 | K154: 1110.57 | L154: 1093.18 | M154: =SUM(F154:L154) -> 7617.28 | N154: =O153 -> 606.7 | O154: 609.23 | P154: =MAX((O154-N154)*3000,0) -> 7590 | Q154: =R153 -> 4.37 | R154: 4.39 | S154: =MAX((R154-Q154)*3000,0) -> 60 | T154: =P154-S154 -> 7530
... A175: =A174+1 -> 177 | B175: 45920 | C175: 45920 | F175: 924.55 | G175: 918.24 | H175: 920.04 | I175: 953.62 | J175: 962.69 | K175: 964.06 | L175: 944.77 | M175: =SUM(F175:L175) -> 6587.97 | N175: =O174 -> 669.38 | O175: 671.51 | P175: =MAX((O175-N175)*3000,0) -> 6390 | Q175: =R174 -> 4.78 | R175: 4.8 | S175: =MAX((R175-Q175)*3000,0) -> 60 | T175: =P175-S175 -> 6330
A176: =A175+1 -> 178 | B176: 45921 | C176: 45921 | D176: 0.30208333 | E176: 0.76041667 | F176: 1384.24 | G176: 1382.32 | H176: 1375.68 | I176: 1424.23 | J176: 1433.01 | K176: 1430.51 | L176: 1387.89 | M176: =SUM(F176:L176) -> 9817.88 | N176: =O175 -> 671.51 | O176: 674.82 | P176: =MAX((O176-N176)*3000,0) -> 9930 | Q176: =R175 -> 4.8 | R176: 4.82 | S176: =MAX((R176-Q176)*3000,0) -> 60 | T176: =P176-S176 -> 9870 | V176: 2.9 | W176: 29.51 | AB176: rainy
A177: =A176+1 -> 179 | B177: 45922 | C177: 45922 | D177: 0.30208333 | E177: 0.76041667 | F177: 1236.11 | G177: 1232 | H177: 1238.91 | I177: 1280.14 | J177: 1304.01 | K177: 1306.95 | L177: 1270.86 | M177: =SUM(F177:L177) -> 8868.98 | N177: =O176 -> 674.82 | O177: 677.76 | P177: =MAX((O177-N177)*3000,0) -> 8820 | Q177: =R176 -> 4.82 | R177: 4.84 | S177: =MAX((R177-Q177)*3000,0) -> 60 | T177: =P177-S177 -> 8760 | V177: 3.72 | W177: 28.93 | AB177: rainy
A178: =A177+1 -> 180 | B178: 45923 | C178: 45923 | D178: 0.29166667 | E178: 0.76041667 | F178: 1953.01 | G178: 1961.73 | H178: 1978.1 | I178: 2009.22 | J178: 2064.14 | K178: 2058.93 | L178: 2012.07 | M178: =SUM(F178:L178) -> 14037.2 | N178: =O177 -> 677.76 | O178: 682.4 | P178: =MAX((O178-N178)*3000,0) -> 13920 | Q178: =R177 -> 4.84 | R178: 4.86 | S178: =MAX((R178-Q178)*3000,0) -> 60 | T178: =P178-S178 -> 13860 | V178: 3.28 | W178: 30.41 | AB178: sunny
A179: =A178+1 -> 181 | B179: 45924 | C179: 45924 | D179: 0.29166667 | E179: 0.76111111 | F179: 1658.9 | G179: 1662.31 | H179: 1668.14 | I179: 1708.21 | J179: 1718.27 | K179: 1697.66 | L179: 1657.79 | M179: =SUM(F179:L179) -> 11771.28 | N179: =O178 -> 682.4 | O179: 686.29 | P179: =MAX((O179-N179)*3000,0) -> 11670 | Q179: =R178 -> 4.86 | R179: 4.88 | S179: =MAX((R179-Q179)*3000,0) -> 60 | T179: =P179-S179 -> 11610 | V179: 2.92 | W179: 29.76 | AB179: sunny
A180: =A179+1 -> 182 | B180: 45925 | C180: 45925 | D180: 0.29166667 | E180: 0.77083333 | F180: 1596.1 | G180: 1594.26 | H180: 1600.26 | I180: 1644.71 | J180: 1660.93 | K180: 1653 | L180: 1598.08 | M180: =SUM(F180:L180) -> 11347.34 | N180: =O179 -> 686.29 | O180: 690.05 | P180: =MAX((O180-N180)*3000,0) -> 11280 | Q180: =R179 -> 4.88 | R180: 4.9 | S180: =MAX((R180-Q180)*3000,0) -> 60 | T180: =P180-S180 -> 11220 | V180: 2.45 | W180: 31.25 | AB180: sunny
A181: =A180+1 -> 183 | B181: 45926 | C181: 45926 | D181: 0.28125 | E181: 0.77083333 | F181: 1474.7 | G181: 1467.77 | H181: 1489.98 | I181: 1529.92 | J181: 1562.47 | K181: 1563.72 | L181: 1532.32 | M181: =SUM(F181:L181) -> 10620.88 | N181: =O180 -> 690.05 | O181: 693.56 | P181: =MAX((O181-N181)*3000,0) -> 10530 | Q181: =R180 -> 4.9 | R181: 4.92 | S181: =MAX((R181-Q181)*3000,0) -> 60 | T181: =P181-S181 -> 10470
A182: =A181+1 -> 184 | B182: 45927 | C182: 45927 | D182: 0.29166667 | E182: 0.77083333 | F182: 1494.29 | G182: 1491.15 | H182: 1506.64 | I182: 1541.29 | J182: 1575.42 | K182: 1577.29 | L182: 1550.98 | M182: =SUM(F182:L182) -> 10737.06 | N182: =O181 -> 693.56 | O182: 697.11 | P182: =MAX((O182-N182)*3000,0) -> 10650 | Q182: =R181 -> 4.92 | R182: 4.94 | S182: =MAX((R182-Q182)*3000,0) -> 60 | T182: =P182-S182 -> 10590
A183: =A182+1 -> 185 | B183: 45928 | C183: 45928 | D183: 0.3125 | E183: 0.73958333 | F183: 493.25 | G183: 490.5 | H183: 498.11 | I183: 521.47 | J183: 518.12 | K183: 517.6 | L183: 515.16 | M183: =SUM(F183:L183) -> 3554.21 | N183: =O182 -> 697.11 | O183: 698.28 | P183: =MAX((O183-N183)*3000,0) -> 3510 | Q183: =R182 -> 4.94 | R183: 4.96 | S183: =MAX((R183-Q183)*3000,0) -> 60 | T183: =P183-S183 -> 3450 | W183: 27.54 | AB183: rainy
A184: =A183+1 -> 186 | B184: 45929 | C184: 45929 | D184: 0.3125 | E184: 0.75 | F184: 520.06 | G184: 515.84 | H184: 525.57 | I184: 551.81 | J184: 546.09 | K184: 545.89 | L184: 540.54 | M184: =SUM(F184:L184) -> 3745.8 | N184: =O183 -> 698.28 | O184: 699.52 | P184: =MAX((O184-N184)*3000,0) -> 3720 | Q184: =R183 -> 4.96 | R184: 4.99 | S184: =MAX((R184-Q184)*3000,0) -> 90 | T184: =P184-S184 -> 3630 | W184: 26.23 | AB184: rainy
A185: =A184+1 -> 187 | B185: 45930 | C185: 45930 | D185: 0.30208333 | E185: 0.73958333 | F185: 667.66 | G185: 665.1 | H185: 678.67 | I185: 709.38 | J185: 709.17 | K185: 710.21 | L185: 702.1 | M185: =SUM(F185:L185) -> 4842.29 | N185: =O184 -> 699.52 | O185: 701.12 | P185: =MAX((O185-N185)*3000,0) -> 4800 | Q185: =R184 -> 4.99 | R185: 5.01 | S185: =MAX((R185-Q185)*3000,0) -> 60 | T185: =P185-S185 -> 4740 | V185: 0.91 | W185: 23.52 | AB185: rainy
A186: =A185+1 -> 188 | B186: 45931 | C186: 45931 | D186: 0.29166667 | E186: 0.73958333 | F186: 827.53 | G186: 819.47 | H186: 835.34 | I186: 866.48 | J186: 867.81 | K186: 864.54 | L186: 852.11 | M186: =SUM(F186:L186) -> 5933.28 | N186: =O185 -> 701.12 | O186: 703.08 | P186: =MAX((O186-N186)*3000,0) -> 5880 | Q186: =R185 -> 5.01 | R186: 5.03 | S186: =MAX((R186-Q186)*3000,0) -> 60 | T186: =P186-S186 -> 5820 | V186: 1.15 | W186: 25.77 | AB186: rainy
A187: =A186+1 -> 189 | B187: 45932 | C187: 45932 | D187: 0.32291667 | E187: 0.75 | F187: 1020.05 | G187: 1012.93 | H187: 1030.72 | I187: 1052.07 | J187: 1070.48 | K187: 1068.81 | L187: 1043.41 | M187: =SUM(F187:L187) -> 7298.47 | N187: =O186 -> 703.08 | O187: 705.49 | P187: =MAX((O187-N187)*3000,0) -> 7230 | Q187: =R186 -> 5.03 | R187: 5.05 | S187: =MAX((R187-Q187)*3000,0) -> 60 | T187: =P187-S187 -> 7170 | V187: 0.94 | W187: 27.16 | AB187: rainy
A188: =A187+1 -> 190 | B188: 45933 | C188: 45933 | D188: 0.29166667 | E188: 0.75 | F188: 1236.64 | G188: 1223.65 | H188: 1252.57 | I188: 1291.37 | J188: 1307.09 | K188: 1301.73 | L188: 1261.04 | M188: =SUM(F188:L188) -> 8874.09 | N188: =O187 -> 705.49 | O188: 708.42 | P188: =MAX((O188-N188)*3000,0) -> 8790 | Q188: =R187 -> 5.05 | R188: 5.07 | S188: =MAX((R188-Q188)*3000,0) -> 60 | T188: =P188-S188 -> 8730 | V188: 4.89 | W188: 31.51 | AB188: sunny
A189: =A188+1 -> 191 | B189: 45934 | C189: 45934 | D189: 0.30208333 | E189: 0.75 | F189: 1746.2 | G189: 1724.83 | H189: 1760.91 | I189: 1798.18 | J189: 1824.1 | K189: 1810.15 | L189: 1757.03 | M189: =SUM(F189:L189) -> 12421.4 | N189: =O188 -> 708.42 | O189: 712.53 | P189: =MAX((O189-N189)*3000,0) -> 12330 | Q189: =R188 -> 5.07 | R189: 5.09 | S189: =MAX((R189-Q189)*3000,0) -> 60 | T189: =P189-S189 -> 12270 | V189: 1.13 | W189: 29.31 | AB189: sunny
A190: =A189+1 -> 192 | B190: 45935 | C190: 45935 | D190: 0.29166667 | E190: 0.75 | F190: 1614.91 | G190: 1599.74 | H190: 1644.89 | I190: 1682.8 | J190: 1721.87 | K190: 1706.87 | L190: 1664.87 | M190: =SUM(F190:L190) -> 11635.95 | N190: =O189 -> 712.53 | O190: 716.37 | P190: =MAX((O190-N190)*3000,0) -> 11520 | Q190: =R189 -> 5.09 | R190: 5.12 | S190: =MAX((R190-Q190)*3000,0) -> 90 | T190: =P190-S190 -> 11430 | V190: 1.13 | W190: 29.55 | AB190: sunny
A191: =A190+1 -> 193 | B191: 45936 | C191: 45936 | D191: 0.29166667 | E191: 0.75 | F191: 1335.64 | G191: 1317.96 | H191: 1358.46 | I191: 1402.46 | J191: 1433.8 | K191: 1431 | L191: 1377.34 | M191: =SUM(F191:L191) -> 9656.66 | N191: =O190 -> 716.37 | O191: 719.56 | P191: =MAX((O191-N191)*3000,0) -> 9570 | Q191: =R190 -> 5.12 | R191: 5.14 | S191: =MAX((R191-Q191)*3000,0) -> 60 | T191: =P191-S191 -> 9510 | V191: 0.84 | W191: 28.6 | AB191: sunny
A192: =A191+1 -> 194 | B192: 45937 | C192: 45937 | D192: 0.29166667 | E192: 0.75 | F192: 1721.19 | G192: 1700.17 | H192: 1774.2 | I192: 1799.1 | J192: 1823.67 | K192: 1786.18 | L192: 1707.54 | M192: =SUM(F192:L192) -> 12312.05 | N192: =O191 -> 719.56 | O192: 723.62 | P192: =MAX((O192-N192)*3000,0) -> 12180 | Q192: =R191 -> 5.14 | R192: 5.16 | S192: =MAX((R192-Q192)*3000,0) -> 60 | T192: =P192-S192 -> 12120 | V192: 0 | W192: 29.77 | AB192: sunny
A193: =A192+1 -> 195 | B193: 45938 | C193: 45938 | D193: 0.30208333 | E193: 0.75 | F193: 1593.35 | G193: 1555.41 | H193: 1605.37 | I193: 1645.99 | J193: 1679.36 | K193: 1677.02 | L193: 1640.95 | M193: =SUM(F193:L193) -> 11397.45 | N193: =O192 -> 723.62 | O193: 727.38 | P193: =MAX((O193-N193)*3000,0) -> 11280 | Q193: =R192 -> 5.16 | R193: 5.18 | S193: =MAX((R193-Q193)*3000,0) -> 60 | T193: =P193-S193 -> 11220 | V193: 0 | W193: 30.47 | AB193: sunny
A194: =A193+1 -> 196 | B194: 45939 | C194: 45939 | D194: 0.29166667 | E194: 0.75 | F194: 1457.06 | G194: 1419.41 | H194: 1468.1 | I194: 1512.94 | J194: 1539.4 | K194: 1536.77 | L194: 1507.13 | M194: =SUM(F194:L194) -> 10440.81 | N194: =O193 -> 727.38 | O194: 730.84 | P194: =MAX((O194-N194)*3000,0) -> 10380 | Q194: =R193 -> 5.18 | R194: 5.2 | S194: =MAX((R194-Q194)*3000,0) -> 60 | T194: =P194-S194 -> 10320 | V194: 0 | W194: 30.88 | AB194: sunny
A195: =A194+1 -> 197 | B195: 45940 | C195: 45940 | D195: 0.29166667 | E195: 0.75 | F195: 1678.93 | G195: 1633.78 | H195: 1696.48 | I195: 1752.69 | J195: 1783.59 | K195: 1776.58 | L195: 1732.54 | M195: =SUM(F195:L195) -> 12054.59 | N195: =O194 -> 730.84 | O195: 734.82 | P195: =MAX((O195-N195)*3000,0) -> 11940 | Q195: =R194 -> 5.2 | R195: 5.22 | S195: =MAX((R195-Q195)*3000,0) -> 60 | T195: =P195-S195 -> 11880 | V195: 0 | W195: 31.35 | AB195: sunny
A196: =A195+1 -> 198 | B196: 45941 | C196: 45941 | D196: 0.30208333 | E196: 0.75 | F196: 1359.85 | G196: 1306.59 | H196: 1351.72 | I196: 1417.81 | J196: 1424.82 | K196: 1416.26 | L196: 1376.61 | M196: =SUM(F196:L196) -> 9653.66 | N196: =O195 -> 734.82 | O196: 738.01 | P196: =MAX((O196-N196)*3000,0) -> 9570 | Q196: =R195 -> 5.22 | R196: 5.24 | S196: =MAX((R196-Q196)*3000,0) -> 60 | T196: =P196-S196 -> 9510 | V196: 0 | W196: 31.55 | AB196: sunny
... A273: =A272+1 -> 275 | B273: 46018 | C273: 46018 | D273: 0.32291667 | E273: 0.73958333 | F273: 1493.86 | G273: 1493.43 | H273: 1501.61 | I273: 1538.74 | J273: 1563.13 | K273: 1586.7 | L273: 1479.08 | M273: =SUM(F273:L273) -> 10656.55 | N273: =O272 -> 1001.31 | O273: 1004.83 | P273: =MAX((O273-N273)*3000,0) -> 10560 | Q273: =R272 -> 6.9 | R273: 6.93 | S273: =MAX((R273-Q273)*3000,0) -> 90 | T273: =P273-S273 -> 10470 | V273: 3.75 | W273: 24.75 | AB273: sunny
A274: =A273+1 -> 276 | B274: 46019 | C274: 46019 | D274: 0.32291667 | E274: 0.73958333 | F274: 1495.68 | G274: 1497.5 | H274: 1505.36 | I274: 1549.24 | J274: 1568.15 | K274: 1583.6 | L274: 1478.56 | M274: =SUM(F274:L274) -> 10678.09 | N274: =O273 -> 1004.83 | O274: 1008.37 | P274: =MAX((O274-N274)*3000,0) -> 10620 | Q274: =R273 -> 6.93 | R274: 6.94 | S274: =MAX((R274-Q274)*3000,0) -> 30 | T274: =P274-S274 -> 10590 | W274: 23.8 | AB274: sunny
A275: =A274+1 -> 277 | B275: 46020 | C275: 46020 | D275: 0.32291667 | E275: 0.73958333 | F275: 1411.57 | G275: 1412.63 | H275: 1419.07 | I275: 1467.11 | J275: 1478.75 | K275: 1495.17 | L275: 1396.9 | M275: =SUM(F275:L275) -> 10081.2 | N275: =O274 -> 1008.37 | O275: 1011.7 | P275: =MAX((O275-N275)*3000,0) -> 9990 | Q275: =R274 -> 6.94 | R275: 6.96 | S275: =MAX((R275-Q275)*3000,0) -> 60 | T275: =P275-S275 -> 9930 | V275: 3.76 | W275: 25.63 | AB275: sunny
A276: =A275+1 -> 278 | B276: 46021 | C276: 46021 | D276: 0.32291667 | E276: 0.73958333 | F276: 1476.15 | G276: 1478.75 | H276: 1487.54 | I276: 1528.73 | J276: 1553.46 | K276: 1546.68 | L276: 1442.35 | M276: =SUM(F276:L276) -> 10513.66 | N276: =O275 -> 1011.7 | O276: 1015.17 | P276: =MAX((O276-N276)*3000,0) -> 10410 | Q276: =R275 -> 6.96 | R276: 6.98 | S276: =MAX((R276-Q276)*3000,0) -> 60 | T276: =P276-S276 -> 10350 | V276: 3.72 | W276: 24.75 | AB276: sunny
A277: =A276+1 -> 279 | B277: 46022 | C277: 46022 | D277: 0.32291667 | E277: 0.72916667 | F277: 1219.06 | G277: 1217.23 | H277: 1222.88 | I277: 1261.28 | J277: 1270.68 | K277: 1283.43 | L277: 1217.53 | M277: =SUM(F277:L277) -> 8692.09 | N277: =O276 -> 1015.17 | O277: 1018.04 | P277: =MAX((O277-N277)*3000,0) -> 8610 | Q277: =R276 -> 6.98 | R277: 7 | S277: =MAX((R277-Q277)*3000,0) -> 60 | T277: =P277-S277 -> 8550 | V277: 3.22 | W277: 25.41 | AB277: sunny
A278: =A277+1 -> 280 | B278: 46023 | C278: 46023 | D278: 0.32291667 | E278: 0.73958333 | F278: 1606.18 | G278: 1611.78 | H278: 1621.58 | I278: 1661.86 | J278: 1689.62 | K278: 1710.49 | L278: 1590.92 | M278: =SUM(F278:L278) -> 11492.43 | N278: =O277 -> 1018.04 | O278: 1021.84 | P278: =MAX((O278-N278)*3000,0) -> 11400 | Q278: =R277 -> 7 | R278: 7.02 | S278: =MAX((R278-Q278)*3000,0) -> 60 | T278: =P278-S278 -> 11340 | V278: 4.03 | W278: 24.46 | AB278: sunny
A279: =A278+1 -> 281 | B279: 46024 | C279: 46024 | D279: 0.32291667 | E279: 0.73958333 | F279: 1630.77 | G279: 1635.01 | H279: 1643.2 | I279: 1687.06 | J279: 1716.41 | K279: 1734.64 | L279: 1610.11 | M279: =SUM(F279:L279) -> 11657.2 | N279: =O278 -> 1021.84 | O279: 1025.69 | P279: =MAX((O279-N279)*3000,0) -> 11550 | Q279: =R278 -> 7.02 | R279: 7.04 | S279: =MAX((R279-Q279)*3000,0) -> 60 | T279: =P279-S279 -> 11490 | V279: 4.05 | W279: 22.95 | AB279: sunny
A280: =A279+1 -> 282 | B280: 46025 | C280: 46025 | D280: 0.32291667 | E280: 0.73958333 | F280: 1719.39 | G280: 1721.45 | H280: 1730.7 | I280: 1776.29 | J280: 1807.53 | K280: 1823 | L280: 1695.07 | M280: =SUM(F280:L280) -> 12273.43 | N280: =O279 -> 1025.69 | O280: 1029.74 | P280: =MAX((O280-N280)*3000,0) -> 12150 | Q280: =R279 -> 7.04 | R280: 7.06 | S280: =MAX((R280-Q280)*3000,0) -> 60 | T280: =P280-S280 -> 12090 | V280: 4.34 | W280: 22.14 | AB280: sunny
A281: =A280+1 -> 283 | B281: 46026 | C281: 46026 | D281: 0.32291667 | E281: 0.6875 | F281: 1639.29 | G281: 1645.03 | H281: 1652.38 | I281: 1704.05 | J281: 1720.22 | K281: 1741.73 | L281: 1610.17 | M281: =SUM(F281:L281) -> 11712.87 | N281: =O280 -> 1029.74 | O281: 1033.6 | P281: =MAX((O281-N281)*3000,0) -> 11580 | Q281: =R280 -> 7.06 | R281: 7.08 | S281: =MAX((R281-Q281)*3000,0) -> 60 | T281: =P281-S281 -> 11520 | V281: 4.1 | W281: 22.57 | AB281: sunny
A282: =A281+1 -> 284 | B282: 46027 | C282: 46027 | D282: 0.32291667 | E282: 0.73958333 | F282: 1606.88 | G282: 1607.81 | H282: 1617.73 | I282: 1664.23 | J282: 1687.19 | K282: 1707.91 | L282: 1587.56 | M282: =SUM(F282:L282) -> 11479.31 | N282: =O281 -> 1033.6 | O282: 1037.39 | P282: =MAX((O282-N282)*3000,0) -> 11370 | Q282: =R281 -> 7.08 | R282: 7.1 | S282: =MAX((R282-Q282)*3000,0) -> 60 | T282: =P282-S282 -> 11310 | V282: 4.03 | W282: 23.17 | AB282: sunny
...

Sheet Inverter_PR
A1: Inverter_Availability_Sheet
C2: 335.72 | D2: 335.72 | E2: 335.72 | F2: 350.98 | G2: 350.98 | H2: 350.98 | I2: 350.98
C3: Inv_1 | D3: Inv_2 | E3: Inv_3 | F3: Inv_4 | G3: Inv_5 | H3: Inv_6 | I3: Inv_7
A4: 45747 | B4: 45747
A5: 45748 | B5: 45748 | C5: =IFERROR((Data_Entry!F3/Data_Entry!$V3/C$2),"") -> 0.97147583 | D5: =IFERROR((Data_Entry!G3/Data_Entry!$V3/D$2),"") -> 0.99003579 | E5: =IFERROR((Data_Entry!H3/Data_Entry!$V3/E$2),"") -> 1.0189504 | F5: =IFERROR((Data_Entry!I3/Data_Entry!$V3/F$2),"") -> 1.0253653 | G5: =IFERROR((Data_Entry!J3/Data_Entry!$V3/G$2),"") -> 1.0205093 | H5: =IFERROR((Data_Entry!K3/Data_Entry!$V3/H$2),"") -> 1.0034449 | I5: =IFERROR((Data_Entry!L3/Data_Entry!$V3/I$2),"") -> 0.98239044
A6: 45749 | B6: 45749 | C6: =IFERROR((Data_Entry!F4/Data_Entry!$V4/C$2),"") -> 1.0351031 | D6: =IFERROR((Data_Entry!G4/Data_Entry!$V4/D$2),"") -> 1.0555838 | E6: =IFERROR((Data_Entry!H4/Data_Entry!$V4/E$2),"") -> 1.0453103 | F6: =IFERROR((Data_Entry!I4/Data_Entry!$V4/F$2),"") -> 1.0196668 | G6: =IFERROR((Data_Entry!J4/Data_Entry!$V4/G$2),"") -> 0.96413439 | H6: =IFERROR((Data_Entry!K4/Data_Entry!$V4/H$2),"") -> 0.95330783 | I6: =IFERROR((Data_Entry!L4/Data_Entry!$V4/I$2),"") -> 0.95786278
A7: 45750 | B7: 45750 | C7: =IFERROR((Data_Entry!F5/Data_Entry!$V5/C$2),"") -> 0.98237841 | D7: =IFERROR((Data_Entry!G5/Data_Entry!$V5/D$2),"") -> 0.9804821 | E7: =IFERROR((Data_Entry!H5/Data_Entry!$V5/E$2),"") -> 0.98429074 | F7: =IFERROR((Data_Entry!I5/Data_Entry!$V5/F$2),"") -> 0.99763829 | G7: =IFERROR((Data_Entry!J5/Data_Entry!$V5/G$2),"") -> 0.98455806 | H7: =IFERROR((Data_Entry!K5/Data_Entry!$V5/H$2),"") -> 0.96718588 | I7: =IFERROR((Data_Entry!L5/Data_Entry!$V5/I$2),"") -> 0.95936329
A8: 45751 | B8: 45751 | C8: =IFERROR((Data_Entry!F6/Data_Entry!$V6/C$2),"") -> 0.96223228 | D8: =IFERROR((Data_Entry!G6/Data_Entry!$V6/D$2),"") -> 0.96226423 | E8: =IFERROR((Data_Entry!H6/Data_Entry!$V6/E$2),"") -> 0.96587426 | F8: =IFERROR((Data_Entry!I6/Data_Entry!$V6/F$2),"") -> 0.9779982 | G8: =IFERROR((Data_Entry!J6/Data_Entry!$V6/G$2),"") -> 0.96520962 | H8: =IFERROR((Data_Entry!K6/Data_Entry!$V6/H$2),"") -> 0.96373519 | I8: =IFERROR((Data_Entry!L6/Data_Entry!$V6/I$2),"") -> 0.92892182
A9: 45752 | B9: 45752 | C9: =IFERROR((Data_Entry!F7/Data_Entry!$V7/C$2),"") -> 0.98854968 | D9: =IFERROR((Data_Entry!G7/Data_Entry!$V7/D$2),"") -> 0.98933994 | E9: =IFERROR((Data_Entry!H7/Data_Entry!$V7/E$2),"") -> 0.99420106 | F9: =IFERROR((Data_Entry!I7/Data_Entry!$V7/F$2),"") -> 1.0050167 | G9: =IFERROR((Data_Entry!J7/Data_Entry!$V7/G$2),"") -> 0.99526461 | H9: =IFERROR((Data_Entry!K7/Data_Entry!$V7/H$2),"") -> 0.99514029 | I9: =IFERROR((Data_Entry!L7/Data_Entry!$V7/I$2),"") -> 0.99285767
A10: 45753 | B10: 45753 | C10: =IFERROR((Data_Entry!F8/Data_Entry!$V8/C$2),"") -> 0.98085278 | D10: =IFERROR((Data_Entry!G8/Data_Entry!$V8/D$2),"") -> 0.97724718 | E10: =IFERROR((Data_Entry!H8/Data_Entry!$V8/E$2),"") -> 0.98368668 | F10: =IFERROR((Data_Entry!I8/Data_Entry!$V8/F$2),"") -> 0.99245792 | G10: =IFERROR((Data_Entry!J8/Data_Entry!$V8/G$2),"") -> 0.98044282 | H10: =IFERROR((Data_Entry!K8/Data_Entry!$V8/H$2),"") -> 0.94849768 | I10: =IFERROR((Data_Entry!L8/Data_Entry!$V8/I$2),"") -> 0.94382687
A11: 45754 | B11: 45754 | C11: =IFERROR((Data_Entry!F9/Data_Entry!$V9/C$2),"") -> 0.98628501 | D11: =IFERROR((Data_Entry!G9/Data_Entry!$V9/D$2),"") -> 0.98071802 | E11: =IFERROR((Data_Entry!H9/Data_Entry!$V9/E$2),"") -> 0.97834975 | F11: =IFERROR((Data_Entry!I9/Data_Entry!$V9/F$2),"") -> 0.98964085 | G11: =IFERROR((Data_Entry!J9/Data_Entry!$V9/G$2),"") -> 0.97988826 | H11: =IFERROR((Data_Entry!K9/Data_Entry!$V9/H$2),"") -> 0.96473717 | I11: =IFERROR((Data_Entry!L9/Data_Entry!$V9/I$2),"") -> 0.96176088
A12: 45755 | B12: 45755 | C12: =IFERROR((Data_Entry!F10/Data_Entry!$V10/C$2),"") -> 0.97863224 | D12: =IFERROR((Data_Entry!G10/Data_Entry!$V10/D$2),"") -> 0.98891987 | E12: =IFERROR((Data_Entry!H10/Data_Entry!$V10/E$2),"") -> 0.9928909 | F12: =IFERROR((Data_Entry!I10/Data_Entry!$V10/F$2),"") -> 0.99228385 | G12: =IFERROR((Data_Entry!J10/Data_Entry!$V10/G$2),"") -> 0.9804481 | H12: =IFERROR((Data_Entry!K10/Data_Entry!$V10/H$2),"") -> 0.96378587 | I12: =IFERROR((Data_Entry!L10/Data_Entry!$V10/I$2),"") -> 0.96031162
A13: 45756 | B13: 45756 | C13: =IFERROR((Data_Entry!F11/Data_Entry!$V11/C$2),"") -> 0.97216235 | D13: =IFERROR((Data_Entry!G11/Data_Entry!$V11/D$2),"") -> 0.96876303 | E13: =IFERROR((Data_Entry!H11/Data_Entry!$V11/E$2),"") -> 0.98962322 | F13: =IFERROR((Data_Entry!I11/Data_Entry!$V11/F$2),"") -> 1.0018822 | G13: =IFERROR((Data_Entry!J11/Data_Entry!$V11/G$2),"") -> 0.97979023 | H13: =IFERROR((Data_Entry!K11/Data_Entry!$V11/H$2),"") -> 0.93050185 | I13: =IFERROR((Data_Entry!L11/Data_Entry!$V11/I$2),"") -> 0.92699511
A14: 45757 | B14: 45757 | C14: =IFERROR((Data_Entry!F12/Data_Entry!$V12/C$2),"") -> 0.99760081 | D14: =IFERROR((Data_Entry!G12/Data_Entry!$V12/D$2),"") -> 0.99344692 | E14: =IFERROR((Data_Entry!H12/Data_Entry!$V12/E$2),"") -> 1.0003737 | F14: =IFERROR((Data_Entry!I12/Data_Entry!$V12/F$2),"") -> 1.0158051 | G14: =IFERROR((Data_Entry!J12/Data_Entry!$V12/G$2),"") -> 1.0075373 | H14: =IFERROR((Data_Entry!K12/Data_Entry!$V12/H$2),"") -> 0.9499065 | I14: =IFERROR((Data_Entry!L12/Data_Entry!$V12/I$2),"") -> 0.94970446
A15: 45758 | B15: 45758 | C15: =IFERROR((Data_Entry!F13/Data_Entry!$V13/C$2),"") -> 1.0013951 | D15: =IFERROR((Data_Entry!G13/Data_Entry!$V13/D$2),"") -> 0.99671795 | E15: =IFERROR((Data_Entry!H13/Data_Entry!$V13/E$2),"") -> 1.0020683 | F15: =IFERROR((Data_Entry!I13/Data_Entry!$V13/F$2),"") -> 1.0180936 | G15: =IFERROR((Data_Entry!J13/Data_Entry!$V13/G$2),"") -> 1.0093704 | H15: =IFERROR((Data_Entry!K13/Data_Entry!$V13/H$2),"") -> 0.96045164 | I15: =IFERROR((Data_Entry!L13/Data_Entry!$V13/I$2),"") -> 0.94938673
A16: 45759 | B16: 45759 | C16: =IFERROR((Data_Entry!F14/Data_Entry!$V14/C$2),"") -> 0.94619079 | D16: =IFERROR((Data_Entry!G14/Data_Entry!$V14/D$2),"") -> 0.98543224 | E16: =IFERROR((Data_Entry!H14/Data_Entry!$V14/E$2),"") -> 0.99059356 | F16: =IFERROR((Data_Entry!I14/Data_Entry!$V14/F$2),"") -> 1.015526 | G16: =IFERROR((Data_Entry!J14/Data_Entry!$V14/G$2),"") -> 1.0122937 | H16: =IFERROR((Data_Entry!K14/Data_Entry!$V14/H$2),"") -> 0.9634403 | I16: =IFERROR((Data_Entry!L14/Data_Entry!$V14/I$2),"") -> 0.92842013
... A21: 45764 | B21: 45764 | C21: =IFERROR((Data_Entry!F19/Data_Entry!$V19/C$2),"") -> 0.96904356 | D21: =IFERROR((Data_Entry!G19/Data_Entry!$V19/D$2),"") -> 0.99708619 | E21: =IFERROR((Data_Entry!H19/Data_Entry!$V19/E$2),"") -> 0.99934469 | F21: =IFERROR((Data_Entry!I19/Data_Entry!$V19/F$2),"") -> 1.0055304 | G21: =IFERROR((Data_Entry!J19/Data_Entry!$V19/G$2),"") -> 1.0042558 | H21: =IFERROR((Data_Entry!K19/Data_Entry!$V19/H$2),"") -> 0.98587676 | I21: =IFERROR((Data_Entry!L19/Data_Entry!$V19/I$2),"") -> 0.96365984
A22: 45765 | B22: 45765 | C22: =IFERROR((Data_Entry!F20/Data_Entry!$V20/C$2),"") -> 0.99241242 | D22: =IFERROR((Data_Entry!G20/Data_Entry!$V20/D$2),"") -> 0.99392625 | E22: =IFERROR((Data_Entry!I20/Data_Entry!$V20/E$2),"") -> 0.99691472 | F22: =IFERROR((Data_Entry!J20/Data_Entry!$V20/F$2),"") -> 1.0025828 | G22: =IFERROR((Data_Entry!K20/Data_Entry!$V20/G$2),"") -> 0.97892724 | H22: =IFERROR((Data_Entry!L20/Data_Entry!$V20/H$2),"") -> 0.95861288 | I22: =IFERROR((Data_Entry!#REF!/Data_Entry!$V20/I$2),"")
A23: 45766 | B23: 45766 | C23: =IFERROR((Data_Entry!F21/Data_Entry!$V21/C$2),"") -> 0.96231841 | D23: =IFERROR((Data_Entry!G21/Data_Entry!$V21/D$2),"") -> 0.99030018 | E23: =IFERROR((Data_Entry!H21/Data_Entry!$V21/E$2),"") -> 0.99134074 | F23: =IFERROR((Data_Entry!I21/Data_Entry!$V21/F$2),"") -> 1.0085998 | G23: =IFERROR((Data_Entry!J21/Data_Entry!$V21/G$2),"") -> 1.0134773 | H23: =IFERROR((Data_Entry!K21/Data_Entry!$V21/H$2),"") -> 0.95230516 | I23: =IFERROR((Data_Entry!L21/Data_Entry!$V21/I$2),"") -> 0.60882981
A24: 45767 | B24: 45767 | C24: =IFERROR((Data_Entry!F22/Data_Entry!$V22/C$2),"") -> 0.95986635 | D24: =IFERROR((Data_Entry!G22/Data_Entry!$V22/D$2),"") -> 0.97530394 | E24: =IFERROR((Data_Entry!H22/Data_Entry!$V22/E$2),"") -> 0.99164047 | F24: =IFERROR((Data_Entry!I22/Data_Entry!$V22/F$2),"") -> 1.0042819 | G24: =IFERROR((Data_Entry!J22/Data_Entry!$V22/G$2),"") -> 1.0020974 | H24: =IFERROR((Data_Entry!K22/Data_Entry!$V22/H$2),"") -> 0.95652936 | I24: =IFERROR((Data_Entry!L22/Data_Entry!$V22/I$2),"") -> 0.55295185
A25: 45768 | B25: 45768 | C25: =IFERROR((Data_Entry!F23/Data_Entry!$V23/C$2),"") -> 0.87317105 | D25: =IFERROR((Data_Entry!G23/Data_Entry!$V23/D$2),"") -> 0.92601563 | E25: =IFERROR((Data_Entry!H23/Data_Entry!$V23/E$2),"") -> 0.95275044 | F25: =IFERROR((Data_Entry!I23/Data_Entry!$V23/F$2),"") -> 0.97143922 | G25: =IFERROR((Data_Entry!J23/Data_Entry!$V23/G$2),"") -> 0.96334479 | H25: =IFERROR((Data_Entry!K23/Data_Entry!$V23/H$2),"") -> 0.85935493 | I25: =IFERROR((Data_Entry!L23/Data_Entry!$V23/I$2),"") -> 0.83850932
A26: 45769 | B26: 45769 | C26: =IFERROR((Data_Entry!F24/Data_Entry!$V24/C$2),"") -> 0.91666484 | D26: =IFERROR((Data_Entry!G24/Data_Entry!$V24/D$2),"") -> 0.9567757 | E26: =IFERROR((Data_Entry!H24/Data_Entry!$V24/E$2),"") -> 0.97797826 | F26: =IFERROR((Data_Entry!I24/Data_Entry!$V24/F$2),"") -> 0.97470956 | G26: =IFERROR((Data_Entry!J24/Data_Entry!$V24/G$2),"") -> 0.97613414 | H26: =IFERROR((Data_Entry!K24/Data_Entry!$V24/H$2),"") -> 0.93259908 | I26: =IFERROR((Data_Entry!L24/Data_Entry!$V24/I$2),"") -> 0.91529662
A27: 45770 | B27: 45770 | C27: =IFERROR((Data_Entry!F25/Data_Entry!$V25/C$2),"") -> 0.93252313 | D27: =IFERROR((Data_Entry!G25/Data_Entry!$V25/D$2),"") -> 0.93456353 | E27: =IFERROR((Data_Entry!H25/Data_Entry!$V25/E$2),"") -> 0.93578975 | F27: =IFERROR((Data_Entry!I25/Data_Entry!$V25/F$2),"") -> 0.94821642 | G27: =IFERROR((Data_Entry!J25/Data_Entry!$V25/G$2),"") -> 0.93826809 | H27: =IFERROR((Data_Entry!K25/Data_Entry!$V25/H$2),"") -> 0.93362395 | I27: =IFERROR((Data_Entry!L25/Data_Entry!$V25/I$2),"") -> 0.91839041
A28: 45771 | B28: 45771 | C28: =IFERROR((Data_Entry!F26/Data_Entry!$V26/C$2),"") -> 0.96802012 | D28: =IFERROR((Data_Entry!G26/Data_Entry!$V26/D$2),"") -> 0.96417792 | E28: =IFERROR((Data_Entry!H26/Data_Entry!$V26/E$2),"") -> 0.96507055 | F28: =IFERROR((Data_Entry!I26/Data_Entry!$V26/F$2),"") -> 0.96681363 | G28: =IFERROR((Data_Entry!J26/Data_Entry!$V26/G$2),"") -> 0.97184839 | H28: =IFERROR((Data_Entry!K26/Data_Entry!$V26/H$2),"") -> 0.96995514 | I28: =IFERROR((Data_Entry!L26/Data_Entry!$V26/I$2),"") -> 0.96388094
A29: 45772 | B29: 45772 | C29: =IFERROR((Data_Entry!F27/Data_Entry!$V27/C$2),"") -> 0.96504237 | D29: =IFERROR((Data_Entry!G27/Data_Entry!$V27/D$2),"") -> 0.96901076 | E29: =IFERROR((Data_Entry!H27/Data_Entry!$V27/E$2),"") -> 0.97122336 | F29: =IFERROR((Data_Entry!I27/Data_Entry!$V27/F$2),"") -> 0.96972202 | G29: =IFERROR((Data_Entry!J27/Data_Entry!$V27/G$2),"") -> 0.96335919 | H29: =IFERROR((Data_Entry!K27/Data_Entry!$V27/H$2),"") -> 0.96235333 | I29: =IFERROR((Data_Entry!L27/Data_Entry!$V27/I$2),"") -> 0.95109777
A30: 45773 | B30: 45773 | C30: =IFERROR((Data_Entry!F28/Data_Entry!$V28/C$2),"") -> 1.2621239 | D30: =IFERROR((Data_Entry!G28/Data_Entry!$V28/D$2),"") -> 1.2591701 | E30: =IFERROR((Data_Entry!H28/Data_Entry!$V28/E$2),"") -> 1.262609 | F30: =IFERROR((Data_Entry!I28/Data_Entry!$V28/F$2),"") -> 1.2645892 | G30: =IFERROR((Data_Entry!J28/Data_Entry!$V28/G$2),"") -> 1.2556015 | H30: =IFERROR((Data_Entry!K28/Data_Entry!$V28/H$2),"") -> 1.2558811 | I30: =IFERROR((Data_Entry!L28/Data_Entry!$V28/I$2),"") -> 1.2407311
A31: 45774 | B31: 45774 | C31: =IFERROR((Data_Entry!F29/Data_Entry!$V29/C$2),"") -> 1.1021255 | D31: =IFERROR((Data_Entry!G29/Data_Entry!$V29/D$2),"") -> 1.0994729 | E31: =IFERROR((Data_Entry!H29/Data_Entry!$V29/E$2),"") -> 1.1027665 | F31: =IFERROR((Data_Entry!I29/Data_Entry!$V29/F$2),"") -> 1.1040066 | G31: =IFERROR((Data_Entry!J29/Data_Entry!$V29/G$2),"") -> 1.0964793 | H31: =IFERROR((Data_Entry!K29/Data_Entry!$V29/H$2),"") -> 1.0979594 | I31: =IFERROR((Data_Entry!L29/Data_Entry!$V29/I$2),"") -> 1.0829999
A32: 45775 | B32: 45775 | C32: =IFERROR((Data_Entry!F30/Data_Entry!$V30/C$2),"") -> 0.96083127 | D32: =IFERROR((Data_Entry!G30/Data_Entry!$V30/D$2),"") -> 0.95481618 | E32: =IFERROR((Data_Entry!H30/Data_Entry!$V30/E$2),"") -> 0.95691425 | F32: =IFERROR((Data_Entry!I30/Data_Entry!$V30/F$2),"") -> 0.96139303 | G32: =IFERROR((Data_Entry!J30/Data_Entry!$V30/G$2),"") -> 0.95447034 | H32: =IFERROR((Data_Entry!K30/Data_Entry!$V30/H$2),"") -> 0.95566708 | I32: =IFERROR((Data_Entry!L30/Data_Entry!$V30/I$2),"") -> 0.94153633
A33: 45776 | B33: 45776 | C33: =IFERROR((Data_Entry!F31/Data_Entry!$V31/C$2),"") -> 0.96831014 | D33: =IFERROR((Data_Entry!G31/Data_Entry!$V31/D$2),"") -> 0.9564949 | E33: =IFERROR((Data_Entry!H31/Data_Entry!$V31/E$2),"") -> 0.95973403 | F33: =IFERROR((Data_Entry!I31/Data_Entry!$V31/F$2),"") -> 0.96484782 | G33: =IFERROR((Data_Entry!J31/Data_Entry!$V31/G$2),"") -> 0.95811673 | H33: =IFERROR((Data_Entry!K31/Data_Entry!$V31/H$2),"") -> 0.95675783 | I33: =IFERROR((Data_Entry!L31/Data_Entry!$V31/I$2),"") -> 0.94363989
A34: 45777 | B34: 45777 | C34: =IFERROR((Data_Entry!F32/Data_Entry!$V32/C$2),"") -> 0.97322646 | D34: =IFERROR((Data_Entry!G32/Data_Entry!$V32/D$2),"") -> 0.96044888 | E34: =IFERROR((Data_Entry!H32/Data_Entry!$V32/E$2),"") -> 0.96321793 | F34: =IFERROR((Data_Entry!I32/Data_Entry!$V32/F$2),"") -> 0.96864156 | G34: =IFERROR((Data_Entry!J32/Data_Entry!$V32/G$2),"") -> 0.95956713 | H34: =IFERROR((Data_Entry!K32/Data_Entry!$V32/H$2),"") -> 0.95781846 | I34: =IFERROR((Data_Entry!L32/Data_Entry!$V32/I$2),"") -> 0.94679485
... A129: 45872 | B129: 45872 | C129: =IFERROR((Data_Entry!F127/Data_Entry!$V127/C$2),"") -> 1.0187168 | D129: =IFERROR((Data_Entry!G127/Data_Entry!$V127/D$2),"") -> 1.0131344 | E129: =IFERROR((Data_Entry!H127/Data_Entry!$V127/E$2),"") -> 1.0181489 | F129: =IFERROR((Data_Entry!I127/Data_Entry!$V127/F$2),"") -> 1.0227581 | G129: =IFERROR((Data_Entry!J127/Data_Entry!$V127/G$2),"") -> 1.0118738 | H129: =IFERROR((Data_Entry!K127/Data_Entry!$V127/H$2),"") -> 1.0142208 | I129: =IFERROR((Data_Entry!L127/Data_Entry!$V127/I$2),"") -> 0.99364124
A130: 45873 | B130: 45873 | C130: =IFERROR((Data_Entry!F128/Data_Entry!$V128/C$2),"") -> 1.146086 | D130: =IFERROR((Data_Entry!G128/Data_Entry!$V128/D$2),"") -> 1.1408555 | E130: =IFERROR((Data_Entry!H128/Data_Entry!$V128/E$2),"") -> 1.1443703 | F130: =IFERROR((Data_Entry!J128/Data_Entry!$V128/F$2),"") -> 1.1404752 | G130: =IFERROR((Data_Entry!K128/Data_Entry!$V128/G$2),"") -> 1.1424013 | H130: =IFERROR((Data_Entry!L128/Data_Entry!$V128/H$2),"") -> 1.1240071 | I130: =IFERROR((Data_Entry!#REF!/Data_Entry!$V128/I$2),"")
A131: 45874 | B131: 45874 | C131: =IFERROR((Data_Entry!F129/Data_Entry!$V129/C$2),"") -> 1.0454351 | D131: =IFERROR((Data_Entry!G129/Data_Entry!$V129/D$2),"") -> 1.0407866 | E131: =IFERROR((Data_Entry!H129/Data_Entry!$V129/E$2),"") -> 1.0461008 | F131: =IFERROR((Data_Entry!I129/Data_Entry!$V129/F$2),"") -> 1.0522917 | G131: =IFERROR((Data_Entry!J129/Data_Entry!$V129/G$2),"") -> 1.0480719 | H131: =IFERROR((Data_Entry!K129/Data_Entry!$V129/H$2),"") -> 1.0515578 | I131: =IFERROR((Data_Entry!L129/Data_Entry!$V129/I$2),"") -> 1.0307395
A132: 45875 | B132: 45875 | C132: =IFERROR((Data_Entry!F130/Data_Entry!$V130/C$2),"") -> 1.0684894 | D132: =IFERROR((Data_Entry!G130/Data_Entry!$V130/D$2),"") -> 1.0637594 | E132: =IFERROR((Data_Entry!H130/Data_Entry!$V130/E$2),"") -> 1.0667955 | F132: =IFERROR((Data_Entry!I130/Data_Entry!$V130/F$2),"") -> 1.0629583 | G132: =IFERROR((Data_Entry!J130/Data_Entry!$V130/G$2),"") -> 1.0546923 | H132: =IFERROR((Data_Entry!K130/Data_Entry!$V130/H$2),"") -> 1.055166 | I132: =IFERROR((Data_Entry!L130/Data_Entry!$V130/I$2),"") -> 1.0391352
A133: 45876 | B133: 45876 | C133: =IFERROR((Data_Entry!F131/Data_Entry!$V131/C$2),"") -> 0.99353907 | D133: =IFERROR((Data_Entry!G131/Data_Entry!$V131/D$2),"") -> 0.99700077 | E133: =IFERROR((Data_Entry!H131/Data_Entry!$V131/E$2),"") -> 0.99441223 | F133: =IFERROR((Data_Entry!I131/Data_Entry!$V131/F$2),"") -> 0.99561442 | G133: =IFERROR((Data_Entry!J131/Data_Entry!$V131/G$2),"") -> 0.98617841 | H133: =IFERROR((Data_Entry!K131/Data_Entry!$V131/H$2),"") -> 0.98285537 | I133: =IFERROR((Data_Entry!L131/Data_Entry!$V131/I$2),"") -> 0.9597955
A134: 45877 | B134: 45877 | C134: =IFERROR((Data_Entry!F132/Data_Entry!$V132/C$2),"") -> 1.0306646 | D134: =IFERROR((Data_Entry!G132/Data_Entry!$V132/D$2),"") -> 1.0271665 | E134: =IFERROR((Data_Entry!H132/Data_Entry!$V132/E$2),"") -> 1.0297196 | F134: =IFERROR((Data_Entry!I132/Data_Entry!$V132/F$2),"") -> 1.0379162 | G134: =IFERROR((Data_Entry!J132/Data_Entry!$V132/G$2),"") -> 1.0343547 | H134: =IFERROR((Data_Entry!K132/Data_Entry!$V132/H$2),"") -> 1.0363479 | I134: =IFERROR((Data_Entry!L132/Data_Entry!$V132/I$2),"") -> 1.0194744
A135: 45878 | B135: 45878 | C135: =IFERROR((Data_Entry!F133/Data_Entry!$V133/C$2),"") -> 0.95481211 | D135: =IFERROR((Data_Entry!G133/Data_Entry!$V133/D$2),"") -> 0.94926397 | E135: =IFERROR((Data_Entry!H133/Data_Entry!$V133/E$2),"") -> 0.95298493 | F135: =IFERROR((Data_Entry!I133/Data_Entry!$V133/F$2),"") -> 0.95588127 | G135: =IFERROR((Data_Entry!J133/Data_Entry!$V133/G$2),"") -> 0.94504898 | H135: =IFERROR((Data_Entry!K133/Data_Entry!$V133/H$2),"") -> 0.94476679 | I135: =IFERROR((Data_Entry!L133/Data_Entry!$V133/I$2),"") -> 0.92648844
A136: 45879 | B136: 45879 | C136: =IFERROR((Data_Entry!F134/Data_Entry!$V134/C$2),"") -> 1.0750911 | D136: =IFERROR((Data_Entry!G134/Data_Entry!$V134/D$2),"") -> 1.0731109 | E136: =IFERROR((Data_Entry!H134/Data_Entry!$V134/E$2),"") -> 1.0775411 | F136: =IFERROR((Data_Entry!I134/Data_Entry!$V134/F$2),"") -> 1.0808208 | G136: =IFERROR((Data_Entry!J134/Data_Entry!$V134/G$2),"") -> 1.0675782 | H136: =IFERROR((Data_Entry!K134/Data_Entry!$V134/H$2),"") -> 1.0654674 | I136: =IFERROR((Data_Entry!L134/Data_Entry!$V134/I$2),"") -> 1.053228
A137: 45880 | B137: 45880 | C137: =IFERROR((Data_Entry!F135/Data_Entry!$V135/C$2),"") -> 0.76255837 | D137: =IFERROR((Data_Entry!G135/Data_Entry!$V135/D$2),"") -> 0.76008826 | E137: =IFERROR((Data_Entry!H135/Data_Entry!$V135/E$2),"") -> 0.7620589 | F137: =IFERROR((Data_Entry!I135/Data_Entry!$V135/F$2),"") -> 0.76652968 | G137: =IFERROR((Data_Entry!J135/Data_Entry!$V135/G$2),"") -> 0.76074448 | H137: =IFERROR((Data_Entry!K135/Data_Entry!$V135/H$2),"") -> 0.76008431 | I137: =IFERROR((Data_Entry!L135/Data_Entry!$V135/I$2),"") -> 0.74426623
A138: 45881 | B138: 45881 | C138: =IFERROR((Data_Entry!F136/Data_Entry!$V136/C$2),"") -> 1.1349243 | D138: =IFERROR((Data_Entry!G136/Data_Entry!$V136/D$2),"") -> 1.1318756 | E138: =IFERROR((Data_Entry!H136/Data_Entry!$V136/E$2),"") -> 1.1352741 | F138: =IFERROR((Data_Entry!I136/Data_Entry!$V136/F$2),"") -> 1.124904 | G138: =IFERROR((Data_Entry!J136/Data_Entry!$V136/G$2),"") -> 1.1258027 | H138: =IFERROR((Data_Entry!K136/Data_Entry!$V136/H$2),"") -> 1.1258409 | I138: =IFERROR((Data_Entry!L136/Data_Entry!$V136/I$2),"") -> 1.106719
A139: 45882 | B139: 45882 | C139: =IFERROR((Data_Entry!F137/Data_Entry!$V137/C$2),"") -> 1.0242852 | D139: =IFERROR((Data_Entry!G137/Data_Entry!$V137/D$2),"") -> 1.0183656 | E139: =IFERROR((Data_Entry!H137/Data_Entry!$V137/E$2),"") -> 1.0195004 | F139: =IFERROR((Data_Entry!I137/Data_Entry!$V137/F$2),"") -> 1.0171067 | G139: =IFERROR((Data_Entry!J137/Data_Entry!$V137/G$2),"") -> 1.0086316 | H139: =IFERROR((Data_Entry!K137/Data_Entry!$V137/H$2),"") -> 1.0078447 | I139: =IFERROR((Data_Entry!L137/Data_Entry!$V137/I$2),"") -> 0.98712268
A140: 45883 | B140: 45883 | C140: =IFERROR((Data_Entry!F138/Data_Entry!$V138/C$2),"") -> 0.97794629 | D140: =IFERROR((Data_Entry!G138/Data_Entry!$V138/D$2),"") -> 0.97694699 | E140: =IFERROR((Data_Entry!H138/Data_Entry!$V138/E$2),"") -> 0.98053101 | F140: =IFERROR((Data_Entry!I138/Data_Entry!$V138/F$2),"") -> 0.98406489 | G140: =IFERROR((Data_Entry!J138/Data_Entry!$V138/G$2),"") -> 0.97420311 | H140: =IFERROR((Data_Entry!K138/Data_Entry!$V138/H$2),"") -> 0.97436854 | I140: =IFERROR((Data_Entry!L138/Data_Entry!$V138/I$2),"") -> 0.95746656
A141: 45884 | B141: 45884 | C141: =IFERROR((Data_Entry!F139/Data_Entry!$V139/C$2),"") -> 1.0264144 | D141: =IFERROR((Data_Entry!G139/Data_Entry!$V139/D$2),"") -> 1.0285478 | E141: =IFERROR((Data_Entry!H139/Data_Entry!$V139/E$2),"") -> 1.038953 | F141: =IFERROR((Data_Entry!I139/Data_Entry!$V139/F$2),"") -> 1.0407153 | G141: =IFERROR((Data_Entry!J139/Data_Entry!$V139/G$2),"") -> 1.0309454 | H141: =IFERROR((Data_Entry!K139/Data_Entry!$V139/H$2),"") -> 1.0325721 | I141: =IFERROR((Data_Entry!L139/Data_Entry!$V139/I$2),"") -> 1.0150151
A142: 45885 | B142: 45885 | C142: =IFERROR((Data_Entry!F140/Data_Entry!$V140/C$2),"") -> 1.0084657 | D142: =IFERROR((Data_Entry!G140/Data_Entry!$V140/D$2),"") -> 1.0082612 | E142: =IFERROR((Data_Entry!H140/Data_Entry!$V140/E$2),"") -> 1.014131 | F142: =IFERROR((Data_Entry!I140/Data_Entry!$V140/F$2),"") -> 1.0173941 | G142: =IFERROR((Data_Entry!J140/Data_Entry!$V140/G$2),"") -> 1.0102432 | H142: =IFERROR((Data_Entry!K140/Data_Entry!$V140/H$2),"") -> 1.0148149 | I142: =IFERROR((Data_Entry!L140/Data_Entry!$V140/I$2),"") -> 1.0023289
... A369: 46112 | B369: 46112 | C369: =IFERROR((Data_Entry!F367/Data_Entry!$V367/C$2),"") -> 1.0274472 | D369: =IFERROR((Data_Entry!G367/Data_Entry!$V367/D$2),"") -> 1.025906 | E369: =IFERROR((Data_Entry!H367/Data_Entry!$V367/E$2),"") -> 1.0238837 | F369: =IFERROR((Data_Entry!I367/Data_Entry!$V367/F$2),"") -> 1.0036345 | G369: =IFERROR((Data_Entry!J367/Data_Entry!$V367/G$2),"") -> 1.0113313 | H369: =IFERROR((Data_Entry!K367/Data_Entry!$V367/H$2),"") -> 1.0050678 | I369: =IFERROR((Data_Entry!L367/Data_Entry!$V367/I$2),"") -> 0.98191322

Sheet Invt_Analysis_Gen_Per_KW &_PR
A1: Daily_Generation_Per_KW_Performance_Analysis
B2: Inverter_No. | C2: =DGR!B3 -> 46178 | D2: =DGR!C3 -> 46179 | E2: =DGR!D3 -> 46180 | F2: =DGR!E3 -> 46181 | G2: =DGR!F3 -> 46182 | H2: =DGR!G3 -> 46183 | I2: =DGR!H3 -> 46184 | J2: =DGR!I3 -> 46185 | ... AH2: =DGR!AG3 -> Total/Avg..
B3: Inv_1 | C3: =IFERROR(VLOOKUP(C$2,Data_Entry!$C:$L,Data_Entry!$A2,0)/VLOOKUP($B3,Basic_Data!$E$2:$G$10,3,0),"") -> 4.3586322 | D3: =IFERROR(VLOOKUP(D$2,Data_Entry!$C:$L,Data_Entry!$A2,0)/VLOOKUP($B3,Basic_Data!$E$2:$G$10,3,0),"") -> 0 | E3: =IFERROR(VLOOKUP(E$2,Data_Entry!$C:$L,Data_Entry!$A2,0)/VLOOKUP($B3,Basic_Data!$E$2:$G$10,3,0),"") -> 0 | F3: =IFERROR(VLOOKUP(F$2,Data_Entry!$C:$L,Data_Entry!$A2,0)/VLOOKUP($B3,Basic_Data!$E$2:$G$10,3,0),"") -> 0 | G3: =IFERROR(VLOOKUP(G$2,Data_Entry!$C:$L,Data_Entry!$A2,0)/VLOOKUP($B3,Basic_Data!$E$2:$G$10,3,0),"") -> 0 | H3: =IFERROR(VLOOKUP(H$2,Data_Entry!$C:$L,Data_Entry!$A2,0)/VLOOKUP($B3,Basic_Data!$E$2:$G$10,3,0),"") -> 0 | I3: =IFERROR(VLOOKUP(I$2,Data_Entry!$C:$L,Data_Entry!$A2,0)/VLOOKUP($B3,Basic_Data!$E$2:$G$10,3,0),"") -> 0 | J3: =IFERROR(VLOOKUP(J$2,Data_Entry!$C:$L,Data_Entry!$A2,0)/VLOOKUP($B3,Basic_Data!$E$2:$G$10,3,0),"") -> 0 | ... AG3: =IFERROR(VLOOKUP(AG$2,Data_Entry!$C:$L,Data_Entry!$A2,0)/VLOOKUP($B3,Basic_Data!$E$2:$G$10,3,0),"") -> 0
B4: Inv_2 | C4: =IFERROR(VLOOKUP(C$2,Data_Entry!$C:$L,Data_Entry!$A3,0)/VLOOKUP($B4,Basic_Data!$E$2:$G$10,3,0),"") -> 4.338824 | D4: =IFERROR(VLOOKUP(D$2,Data_Entry!$C:$L,Data_Entry!$A3,0)/VLOOKUP($B4,Basic_Data!$E$2:$G$10,3,0),"") -> 0 | E4: =IFERROR(VLOOKUP(E$2,Data_Entry!$C:$L,Data_Entry!$A3,0)/VLOOKUP($B4,Basic_Data!$E$2:$G$10,3,0),"") -> 0 | F4: =IFERROR(VLOOKUP(F$2,Data_Entry!$C:$L,Data_Entry!$A3,0)/VLOOKUP($B4,Basic_Data!$E$2:$G$10,3,0),"") -> 0 | G4: =IFERROR(VLOOKUP(G$2,Data_Entry!$C:$L,Data_Entry!$A3,0)/VLOOKUP($B4,Basic_Data!$E$2:$G$10,3,0),"") -> 0 | H4: =IFERROR(VLOOKUP(H$2,Data_Entry!$C:$L,Data_Entry!$A3,0)/VLOOKUP($B4,Basic_Data!$E$2:$G$10,3,0),"") -> 0 | I4: =IFERROR(VLOOKUP(I$2,Data_Entry!$C:$L,Data_Entry!$A3,0)/VLOOKUP($B4,Basic_Data!$E$2:$G$10,3,0),"") -> 0 | J4: =IFERROR(VLOOKUP(J$2,Data_Entry!$C:$L,Data_Entry!$A3,0)/VLOOKUP($B4,Basic_Data!$E$2:$G$10,3,0),"") -> 0 | ... AG4: =IFERROR(VLOOKUP(AG$2,Data_Entry!$C:$L,Data_Entry!$A3,0)/VLOOKUP($B4,Basic_Data!$E$2:$G$10,3,0),"") -> 0
B5: Inv_3 | C5: =IFERROR(VLOOKUP(C$2,Data_Entry!$C:$L,Data_Entry!$A4,0)/VLOOKUP($B5,Basic_Data!$E$2:$G$10,3,0),"") -> 4.3524068 | D5: =IFERROR(VLOOKUP(D$2,Data_Entry!$C:$L,Data_Entry!$A4,0)/VLOOKUP($B5,Basic_Data!$E$2:$G$10,3,0),"") -> 0 | E5: =IFERROR(VLOOKUP(E$2,Data_Entry!$C:$L,Data_Entry!$A4,0)/VLOOKUP($B5,Basic_Data!$E$2:$G$10,3,0),"") -> 0 | F5: =IFERROR(VLOOKUP(F$2,Data_Entry!$C:$L,Data_Entry!$A4,0)/VLOOKUP($B5,Basic_Data!$E$2:$G$10,3,0),"") -> 0 | G5: =IFERROR(VLOOKUP(G$2,Data_Entry!$C:$L,Data_Entry!$A4,0)/VLOOKUP($B5,Basic_Data!$E$2:$G$10,3,0),"") -> 0 | H5: =IFERROR(VLOOKUP(H$2,Data_Entry!$C:$L,Data_Entry!$A4,0)/VLOOKUP($B5,Basic_Data!$E$2:$G$10,3,0),"") -> 0 | I5: =IFERROR(VLOOKUP(I$2,Data_Entry!$C:$L,Data_Entry!$A4,0)/VLOOKUP($B5,Basic_Data!$E$2:$G$10,3,0),"") -> 0 | J5: =IFERROR(VLOOKUP(J$2,Data_Entry!$C:$L,Data_Entry!$A4,0)/VLOOKUP($B5,Basic_Data!$E$2:$G$10,3,0),"") -> 0 | ... AG5: =IFERROR(VLOOKUP(AG$2,Data_Entry!$C:$L,Data_Entry!$A4,0)/VLOOKUP($B5,Basic_Data!$E$2:$G$10,3,0),"") -> 0
B6: Inv_4 | C6: =IFERROR(VLOOKUP(C$2,Data_Entry!$C:$L,Data_Entry!$A5,0)/VLOOKUP($B6,Basic_Data!$E$2:$G$10,3,0),"") -> 4.3307596 | D6: =IFERROR(VLOOKUP(D$2,Data_Entry!$C:$L,Data_Entry!$A5,0)/VLOOKUP($B6,Basic_Data!$E$2:$G$10,3,0),"") -> 0 | E6: =IFERROR(VLOOKUP(E$2,Data_Entry!$C:$L,Data_Entry!$A5,0)/VLOOKUP($B6,Basic_Data!$E$2:$G$10,3,0),"") -> 0 | F6: =IFERROR(VLOOKUP(F$2,Data_Entry!$C:$L,Data_Entry!$A5,0)/VLOOKUP($B6,Basic_Data!$E$2:$G$10,3,0),"") -> 0 | G6: =IFERROR(VLOOKUP(G$2,Data_Entry!$C:$L,Data_Entry!$A5,0)/VLOOKUP($B6,Basic_Data!$E$2:$G$10,3,0),"") -> 0 | H6: =IFERROR(VLOOKUP(H$2,Data_Entry!$C:$L,Data_Entry!$A5,0)/VLOOKUP($B6,Basic_Data!$E$2:$G$10,3,0),"") -> 0 | I6: =IFERROR(VLOOKUP(I$2,Data_Entry!$C:$L,Data_Entry!$A5,0)/VLOOKUP($B6,Basic_Data!$E$2:$G$10,3,0),"") -> 0 | J6: =IFERROR(VLOOKUP(J$2,Data_Entry!$C:$L,Data_Entry!$A5,0)/VLOOKUP($B6,Basic_Data!$E$2:$G$10,3,0),"") -> 0 | ... AG6: =IFERROR(VLOOKUP(AG$2,Data_Entry!$C:$L,Data_Entry!$A5,0)/VLOOKUP($B6,Basic_Data!$E$2:$G$10,3,0),"") -> 0
B7: Inv_5 | C7: =IFERROR(VLOOKUP(C$2,Data_Entry!$C:$L,Data_Entry!$A6,0)/VLOOKUP($B7,Basic_Data!$E$2:$G$10,3,0),"") -> 4.2939199 | D7: =IFERROR(VLOOKUP(D$2,Data_Entry!$C:$L,Data_Entry!$A6,0)/VLOOKUP($B7,Basic_Data!$E$2:$G$10,3,0),"") -> 0 | E7: =IFERROR(VLOOKUP(E$2,Data_Entry!$C:$L,Data_Entry!$A6,0)/VLOOKUP($B7,Basic_Data!$E$2:$G$10,3,0),"") -> 0 | F7: =IFERROR(VLOOKUP(F$2,Data_Entry!$C:$L,Data_Entry!$A6,0)/VLOOKUP($B7,Basic_Data!$E$2:$G$10,3,0),"") -> 0 | G7: =IFERROR(VLOOKUP(G$2,Data_Entry!$C:$L,Data_Entry!$A6,0)/VLOOKUP($B7,Basic_Data!$E$2:$G$10,3,0),"") -> 0 | H7: =IFERROR(VLOOKUP(H$2,Data_Entry!$C:$L,Data_Entry!$A6,0)/VLOOKUP($B7,Basic_Data!$E$2:$G$10,3,0),"") -> 0 | I7: =IFERROR(VLOOKUP(I$2,Data_Entry!$C:$L,Data_Entry!$A6,0)/VLOOKUP($B7,Basic_Data!$E$2:$G$10,3,0),"") -> 0 | J7: =IFERROR(VLOOKUP(J$2,Data_Entry!$C:$L,Data_Entry!$A6,0)/VLOOKUP($B7,Basic_Data!$E$2:$G$10,3,0),"") -> 0 | ... AG7: =IFERROR(VLOOKUP(AG$2,Data_Entry!$C:$L,Data_Entry!$A6,0)/VLOOKUP($B7,Basic_Data!$E$2:$G$10,3,0),"") -> 0
B8: Inv_6 | C8: =IFERROR(VLOOKUP(C$2,Data_Entry!$C:$L,Data_Entry!$A7,0)/VLOOKUP($B8,Basic_Data!$E$2:$G$10,3,0),"") -> 4.2740327 | D8: =IFERROR(VLOOKUP(D$2,Data_Entry!$C:$L,Data_Entry!$A7,0)/VLOOKUP($B8,Basic_Data!$E$2:$G$10,3,0),"") -> 0 | E8: =IFERROR(VLOOKUP(E$2,Data_Entry!$C:$L,Data_Entry!$A7,0)/VLOOKUP($B8,Basic_Data!$E$2:$G$10,3,0),"") -> 0 | F8: =IFERROR(VLOOKUP(F$2,Data_Entry!$C:$L,Data_Entry!$A7,0)/VLOOKUP($B8,Basic_Data!$E$2:$G$10,3,0),"") -> 0 | G8: =IFERROR(VLOOKUP(G$2,Data_Entry!$C:$L,Data_Entry!$A7,0)/VLOOKUP($B8,Basic_Data!$E$2:$G$10,3,0),"") -> 0 | H8: =IFERROR(VLOOKUP(H$2,Data_Entry!$C:$L,Data_Entry!$A7,0)/VLOOKUP($B8,Basic_Data!$E$2:$G$10,3,0),"") -> 0 | I8: =IFERROR(VLOOKUP(I$2,Data_Entry!$C:$L,Data_Entry!$A7,0)/VLOOKUP($B8,Basic_Data!$E$2:$G$10,3,0),"") -> 0 | J8: =IFERROR(VLOOKUP(J$2,Data_Entry!$C:$L,Data_Entry!$A7,0)/VLOOKUP($B8,Basic_Data!$E$2:$G$10,3,0),"") -> 0 | ... AG8: =IFERROR(VLOOKUP(AG$2,Data_Entry!$C:$L,Data_Entry!$A7,0)/VLOOKUP($B8,Basic_Data!$E$2:$G$10,3,0),"") -> 0
B9: Inv_7 | C9: =IFERROR(VLOOKUP(C$2,Data_Entry!$C:$L,Data_Entry!$A8,0)/VLOOKUP($B9,Basic_Data!$E$2:$G$10,3,0),"") -> 4.1477292 | D9: =IFERROR(VLOOKUP(D$2,Data_Entry!$C:$L,Data_Entry!$A8,0)/VLOOKUP($B9,Basic_Data!$E$2:$G$10,3,0),"") -> 0 | E9: =IFERROR(VLOOKUP(E$2,Data_Entry!$C:$L,Data_Entry!$A8,0)/VLOOKUP($B9,Basic_Data!$E$2:$G$10,3,0),"") -> 0 | F9: =IFERROR(VLOOKUP(F$2,Data_Entry!$C:$L,Data_Entry!$A8,0)/VLOOKUP($B9,Basic_Data!$E$2:$G$10,3,0),"") -> 0 | G9: =IFERROR(VLOOKUP(G$2,Data_Entry!$C:$L,Data_Entry!$A8,0)/VLOOKUP($B9,Basic_Data!$E$2:$G$10,3,0),"") -> 0 | H9: =IFERROR(VLOOKUP(H$2,Data_Entry!$C:$L,Data_Entry!$A8,0)/VLOOKUP($B9,Basic_Data!$E$2:$G$10,3,0),"") -> 0 | I9: =IFERROR(VLOOKUP(I$2,Data_Entry!$C:$L,Data_Entry!$A8,0)/VLOOKUP($B9,Basic_Data!$E$2:$G$10,3,0),"") -> 0 | J9: =IFERROR(VLOOKUP(J$2,Data_Entry!$C:$L,Data_Entry!$A8,0)/VLOOKUP($B9,Basic_Data!$E$2:$G$10,3,0),"") -> 0 | ... AG9: =IFERROR(VLOOKUP(AG$2,Data_Entry!$C:$L,Data_Entry!$A8,0)/VLOOKUP($B9,Basic_Data!$E$2:$G$10,3,0),"") -> 0
B10: Avg_per_Kw | C10: =AVERAGE(C3:C9) -> 4.2994721 | D10: =AVERAGE(D3:D9) -> 0 | E10: =AVERAGE(E3:E9) -> 0 | F10: =AVERAGE(F3:F9) -> 0 | G10: =AVERAGE(G3:G9) -> 0 | H10: =AVERAGE(H3:H9) -> 0 | I10: =AVERAGE(I3:I9) -> 0 | J10: =AVERAGE(J3:J9) -> 0 | ... AH10: =AVERAGE(AH3:AH9) -> #DIV/0!
B13: Inverter_No. | C13: =DGR!B3 -> 46178 | D13: =DGR!C3 -> 46179 | E13: =DGR!D3 -> 46180 | F13: =DGR!E3 -> 46181 | G13: =DGR!F3 -> 46182 | H13: =DGR!G3 -> 46183 | I13: =DGR!H3 -> 46184 | J13: =DGR!I3 -> 46185 | ... AH13: =DGR!AG3 -> Total/Avg..
B14: Inv_1 | C14: =IFERROR(VLOOKUP(C$13,Data_Entry!$C:$M,Data_Entry!$A2,0)/VLOOKUP($B14,Basic_Data!$E$2:$G$9,3,0)/VLOOKUP(C$13,Data_Entry!$C:$V,20,0),"") -> 1.1908831 | D14: =IFERROR(VLOOKUP(D$13,Data_Entry!$C:$M,Data_Entry!$A2,0)/VLOOKUP($B14,Basic_Data!$E$2:$G$9,3,0)/VLOOKUP(D$13,Data_Entry!$C:$V,20,0),"") | E14: =IFERROR(VLOOKUP(E$13,Data_Entry!$C:$M,Data_Entry!$A2,0)/VLOOKUP($B14,Basic_Data!$E$2:$G$9,3,0)/VLOOKUP(E$13,Data_Entry!$C:$V,20,0),"") | F14: =IFERROR(VLOOKUP(F$13,Data_Entry!$C:$M,Data_Entry!$A2,0)/VLOOKUP($B14,Basic_Data!$E$2:$G$9,3,0)/VLOOKUP(F$13,Data_Entry!$C:$V,20,0),"") | G14: =IFERROR(VLOOKUP(G$13,Data_Entry!$C:$M,Data_Entry!$A2,0)/VLOOKUP($B14,Basic_Data!$E$2:$G$9,3,0)/VLOOKUP(G$13,Data_Entry!$C:$V,20,0),"") | H14: =IFERROR(VLOOKUP(H$13,Data_Entry!$C:$M,Data_Entry!$A2,0)/VLOOKUP($B14,Basic_Data!$E$2:$G$9,3,0)/VLOOKUP(H$13,Data_Entry!$C:$V,20,0),"") | I14: =IFERROR(VLOOKUP(I$13,Data_Entry!$C:$M,Data_Entry!$A2,0)/VLOOKUP($B14,Basic_Data!$E$2:$G$9,3,0)/VLOOKUP(I$13,Data_Entry!$C:$V,20,0),"") | J14: =IFERROR(VLOOKUP(J$13,Data_Entry!$C:$M,Data_Entry!$A2,0)/VLOOKUP($B14,Basic_Data!$E$2:$G$9,3,0)/VLOOKUP(J$13,Data_Entry!$C:$V,20,0),"") | ... AG14: =IFERROR(VLOOKUP(AG$13,Data_Entry!$C:$M,Data_Entry!$A2,0)/VLOOKUP($B14,Basic_Data!$E$2:$G$9,3,0)/VLOOKUP(AG$13,Data_Entry!$C:$V,20,0),"")
B15: Inv_2 | C15: =IFERROR(VLOOKUP(C$13,Data_Entry!$C:$M,Data_Entry!$A3,0)/VLOOKUP($B15,Basic_Data!$E$2:$G$9,3,0)/VLOOKUP(C$13,Data_Entry!$C:$V,20,0),"") -> 1.185471 | D15: =IFERROR(VLOOKUP(D$13,Data_Entry!$C:$M,Data_Entry!$A3,0)/VLOOKUP($B15,Basic_Data!$E$2:$G$9,3,0)/VLOOKUP(D$13,Data_Entry!$C:$V,20,0),"") | E15: =IFERROR(VLOOKUP(E$13,Data_Entry!$C:$M,Data_Entry!$A3,0)/VLOOKUP($B15,Basic_Data!$E$2:$G$9,3,0)/VLOOKUP(E$13,Data_Entry!$C:$V,20,0),"") | F15: =IFERROR(VLOOKUP(F$13,Data_Entry!$C:$M,Data_Entry!$A3,0)/VLOOKUP($B15,Basic_Data!$E$2:$G$9,3,0)/VLOOKUP(F$13,Data_Entry!$C:$V,20,0),"") | G15: =IFERROR(VLOOKUP(G$13,Data_Entry!$C:$M,Data_Entry!$A3,0)/VLOOKUP($B15,Basic_Data!$E$2:$G$9,3,0)/VLOOKUP(G$13,Data_Entry!$C:$V,20,0),"") | H15: =IFERROR(VLOOKUP(H$13,Data_Entry!$C:$M,Data_Entry!$A3,0)/VLOOKUP($B15,Basic_Data!$E$2:$G$9,3,0)/VLOOKUP(H$13,Data_Entry!$C:$V,20,0),"") | I15: =IFERROR(VLOOKUP(I$13,Data_Entry!$C:$M,Data_Entry!$A3,0)/VLOOKUP($B15,Basic_Data!$E$2:$G$9,3,0)/VLOOKUP(I$13,Data_Entry!$C:$V,20,0),"") | J15: =IFERROR(VLOOKUP(J$13,Data_Entry!$C:$M,Data_Entry!$A3,0)/VLOOKUP($B15,Basic_Data!$E$2:$G$9,3,0)/VLOOKUP(J$13,Data_Entry!$C:$V,20,0),"") | ... AG15: =IFERROR(VLOOKUP(AG$13,Data_Entry!$C:$M,Data_Entry!$A3,0)/VLOOKUP($B15,Basic_Data!$E$2:$G$9,3,0)/VLOOKUP(AG$13,Data_Entry!$C:$V,20,0),"")
B16: Inv_3 | C16: =IFERROR(VLOOKUP(C$13,Data_Entry!$C:$M,Data_Entry!$A4,0)/VLOOKUP($B16,Basic_Data!$E$2:$G$9,3,0)/VLOOKUP(C$13,Data_Entry!$C:$V,20,0),"") -> 1.1891822 | D16: =IFERROR(VLOOKUP(D$13,Data_Entry!$C:$M,Data_Entry!$A4,0)/VLOOKUP($B16,Basic_Data!$E$2:$G$9,3,0)/VLOOKUP(D$13,Data_Entry!$C:$V,20,0),"") | E16: =IFERROR(VLOOKUP(E$13,Data_Entry!$C:$M,Data_Entry!$A4,0)/VLOOKUP($B16,Basic_Data!$E$2:$G$9,3,0)/VLOOKUP(E$13,Data_Entry!$C:$V,20,0),"") | F16: =IFERROR(VLOOKUP(F$13,Data_Entry!$C:$M,Data_Entry!$A4,0)/VLOOKUP($B16,Basic_Data!$E$2:$G$9,3,0)/VLOOKUP(F$13,Data_Entry!$C:$V,20,0),"") | G16: =IFERROR(VLOOKUP(G$13,Data_Entry!$C:$M,Data_Entry!$A4,0)/VLOOKUP($B16,Basic_Data!$E$2:$G$9,3,0)/VLOOKUP(G$13,Data_Entry!$C:$V,20,0),"") | H16: =IFERROR(VLOOKUP(H$13,Data_Entry!$C:$M,Data_Entry!$A4,0)/VLOOKUP($B16,Basic_Data!$E$2:$G$9,3,0)/VLOOKUP(H$13,Data_Entry!$C:$V,20,0),"") | I16: =IFERROR(VLOOKUP(I$13,Data_Entry!$C:$M,Data_Entry!$A4,0)/VLOOKUP($B16,Basic_Data!$E$2:$G$9,3,0)/VLOOKUP(I$13,Data_Entry!$C:$V,20,0),"") | J16: =IFERROR(VLOOKUP(J$13,Data_Entry!$C:$M,Data_Entry!$A4,0)/VLOOKUP($B16,Basic_Data!$E$2:$G$9,3,0)/VLOOKUP(J$13,Data_Entry!$C:$V,20,0),"") | ... AG16: =IFERROR(VLOOKUP(AG$13,Data_Entry!$C:$M,Data_Entry!$A4,0)/VLOOKUP($B16,Basic_Data!$E$2:$G$9,3,0)/VLOOKUP(AG$13,Data_Entry!$C:$V,20,0),"")
B17: Inv_4 | C17: =IFERROR(VLOOKUP(C$13,Data_Entry!$C:$M,Data_Entry!$A5,0)/VLOOKUP($B17,Basic_Data!$E$2:$G$9,3,0)/VLOOKUP(C$13,Data_Entry!$C:$V,20,0),"") -> 1.1832676 | D17: =IFERROR(VLOOKUP(D$13,Data_Entry!$C:$M,Data_Entry!$A5,0)/VLOOKUP($B17,Basic_Data!$E$2:$G$9,3,0)/VLOOKUP(D$13,Data_Entry!$C:$V,20,0),"") | E17: =IFERROR(VLOOKUP(E$13,Data_Entry!$C:$M,Data_Entry!$A5,0)/VLOOKUP($B17,Basic_Data!$E$2:$G$9,3,0)/VLOOKUP(E$13,Data_Entry!$C:$V,20,0),"") | F17: =IFERROR(VLOOKUP(F$13,Data_Entry!$C:$M,Data_Entry!$A5,0)/VLOOKUP($B17,Basic_Data!$E$2:$G$9,3,0)/VLOOKUP(F$13,Data_Entry!$C:$V,20,0),"") | G17: =IFERROR(VLOOKUP(G$13,Data_Entry!$C:$M,Data_Entry!$A5,0)/VLOOKUP($B17,Basic_Data!$E$2:$G$9,3,0)/VLOOKUP(G$13,Data_Entry!$C:$V,20,0),"") | H17: =IFERROR(VLOOKUP(H$13,Data_Entry!$C:$M,Data_Entry!$A5,0)/VLOOKUP($B17,Basic_Data!$E$2:$G$9,3,0)/VLOOKUP(H$13,Data_Entry!$C:$V,20,0),"") | I17: =IFERROR(VLOOKUP(I$13,Data_Entry!$C:$M,Data_Entry!$A5,0)/VLOOKUP($B17,Basic_Data!$E$2:$G$9,3,0)/VLOOKUP(I$13,Data_Entry!$C:$V,20,0),"") | J17: =IFERROR(VLOOKUP(J$13,Data_Entry!$C:$M,Data_Entry!$A5,0)/VLOOKUP($B17,Basic_Data!$E$2:$G$9,3,0)/VLOOKUP(J$13,Data_Entry!$C:$V,20,0),"") | ... AG17: =IFERROR(VLOOKUP(AG$13,Data_Entry!$C:$M,Data_Entry!$A5,0)/VLOOKUP($B17,Basic_Data!$E$2:$G$9,3,0)/VLOOKUP(AG$13,Data_Entry!$C:$V,20,0),"")
B18: Inv_5 | C18: =IFERROR(VLOOKUP(C$13,Data_Entry!$C:$M,Data_Entry!$A6,0)/VLOOKUP($B18,Basic_Data!$E$2:$G$9,3,0)/VLOOKUP(C$13,Data_Entry!$C:$V,20,0),"") -> 1.1732022 | D18: =IFERROR(VLOOKUP(D$13,Data_Entry!$C:$M,Data_Entry!$A6,0)/VLOOKUP($B18,Basic_Data!$E$2:$G$9,3,0)/VLOOKUP(D$13,Data_Entry!$C:$V,20,0),"") | E18: =IFERROR(VLOOKUP(E$13,Data_Entry!$C:$M,Data_Entry!$A6,0)/VLOOKUP($B18,Basic_Data!$E$2:$G$9,3,0)/VLOOKUP(E$13,Data_Entry!$C:$V,20,0),"") | F18: =IFERROR(VLOOKUP(F$13,Data_Entry!$C:$M,Data_Entry!$A6,0)/VLOOKUP($B18,Basic_Data!$E$2:$G$9,3,0)/VLOOKUP(F$13,Data_Entry!$C:$V,20,0),"") | G18: =IFERROR(VLOOKUP(G$13,Data_Entry!$C:$M,Data_Entry!$A6,0)/VLOOKUP($B18,Basic_Data!$E$2:$G$9,3,0)/VLOOKUP(G$13,Data_Entry!$C:$V,20,0),"") | H18: =IFERROR(VLOOKUP(H$13,Data_Entry!$C:$M,Data_Entry!$A6,0)/VLOOKUP($B18,Basic_Data!$E$2:$G$9,3,0)/VLOOKUP(H$13,Data_Entry!$C:$V,20,0),"") | I18: =IFERROR(VLOOKUP(I$13,Data_Entry!$C:$M,Data_Entry!$A6,0)/VLOOKUP($B18,Basic_Data!$E$2:$G$9,3,0)/VLOOKUP(I$13,Data_Entry!$C:$V,20,0),"") | J18: =IFERROR(VLOOKUP(J$13,Data_Entry!$C:$M,Data_Entry!$A6,0)/VLOOKUP($B18,Basic_Data!$E$2:$G$9,3,0)/VLOOKUP(J$13,Data_Entry!$C:$V,20,0),"") | ... AG18: =IFERROR(VLOOKUP(AG$13,Data_Entry!$C:$M,Data_Entry!$A6,0)/VLOOKUP($B18,Basic_Data!$E$2:$G$9,3,0)/VLOOKUP(AG$13,Data_Entry!$C:$V,20,0),"")
B19: Inv_6 | C19: =IFERROR(VLOOKUP(C$13,Data_Entry!$C:$M,Data_Entry!$A7,0)/VLOOKUP($B19,Basic_Data!$E$2:$G$9,3,0)/VLOOKUP(C$13,Data_Entry!$C:$V,20,0),"") -> 1.1677685 | D19: =IFERROR(VLOOKUP(D$13,Data_Entry!$C:$M,Data_Entry!$A7,0)/VLOOKUP($B19,Basic_Data!$E$2:$G$9,3,0)/VLOOKUP(D$13,Data_Entry!$C:$V,20,0),"") | E19: =IFERROR(VLOOKUP(E$13,Data_Entry!$C:$M,Data_Entry!$A7,0)/VLOOKUP($B19,Basic_Data!$E$2:$G$9,3,0)/VLOOKUP(E$13,Data_Entry!$C:$V,20,0),"") | F19: =IFERROR(VLOOKUP(F$13,Data_Entry!$C:$M,Data_Entry!$A7,0)/VLOOKUP($B19,Basic_Data!$E$2:$G$9,3,0)/VLOOKUP(F$13,Data_Entry!$C:$V,20,0),"") | G19: =IFERROR(VLOOKUP(G$13,Data_Entry!$C:$M,Data_Entry!$A7,0)/VLOOKUP($B19,Basic_Data!$E$2:$G$9,3,0)/VLOOKUP(G$13,Data_Entry!$C:$V,20,0),"") | H19: =IFERROR(VLOOKUP(H$13,Data_Entry!$C:$M,Data_Entry!$A7,0)/VLOOKUP($B19,Basic_Data!$E$2:$G$9,3,0)/VLOOKUP(H$13,Data_Entry!$C:$V,20,0),"") | I19: =IFERROR(VLOOKUP(I$13,Data_Entry!$C:$M,Data_Entry!$A7,0)/VLOOKUP($B19,Basic_Data!$E$2:$G$9,3,0)/VLOOKUP(I$13,Data_Entry!$C:$V,20,0),"") | J19: =IFERROR(VLOOKUP(J$13,Data_Entry!$C:$M,Data_Entry!$A7,0)/VLOOKUP($B19,Basic_Data!$E$2:$G$9,3,0)/VLOOKUP(J$13,Data_Entry!$C:$V,20,0),"") | ... AG19: =IFERROR(VLOOKUP(AG$13,Data_Entry!$C:$M,Data_Entry!$A7,0)/VLOOKUP($B19,Basic_Data!$E$2:$G$9,3,0)/VLOOKUP(AG$13,Data_Entry!$C:$V,20,0),"")
B20: Inv_7 | C20: =IFERROR(VLOOKUP(C$13,Data_Entry!$C:$M,Data_Entry!$A8,0)/VLOOKUP($B20,Basic_Data!$E$2:$G$9,3,0)/VLOOKUP(C$13,Data_Entry!$C:$V,20,0),"") -> 1.1332593 | D20: =IFERROR(VLOOKUP(D$13,Data_Entry!$C:$M,Data_Entry!$A8,0)/VLOOKUP($B20,Basic_Data!$E$2:$G$9,3,0)/VLOOKUP(D$13,Data_Entry!$C:$V,20,0),"") | E20: =IFERROR(VLOOKUP(E$13,Data_Entry!$C:$M,Data_Entry!$A8,0)/VLOOKUP($B20,Basic_Data!$E$2:$G$9,3,0)/VLOOKUP(E$13,Data_Entry!$C:$V,20,0),"") | F20: =IFERROR(VLOOKUP(F$13,Data_Entry!$C:$M,Data_Entry!$A8,0)/VLOOKUP($B20,Basic_Data!$E$2:$G$9,3,0)/VLOOKUP(F$13,Data_Entry!$C:$V,20,0),"") | G20: =IFERROR(VLOOKUP(G$13,Data_Entry!$C:$M,Data_Entry!$A8,0)/VLOOKUP($B20,Basic_Data!$E$2:$G$9,3,0)/VLOOKUP(G$13,Data_Entry!$C:$V,20,0),"") | H20: =IFERROR(VLOOKUP(H$13,Data_Entry!$C:$M,Data_Entry!$A8,0)/VLOOKUP($B20,Basic_Data!$E$2:$G$9,3,0)/VLOOKUP(H$13,Data_Entry!$C:$V,20,0),"") | I20: =IFERROR(VLOOKUP(I$13,Data_Entry!$C:$M,Data_Entry!$A8,0)/VLOOKUP($B20,Basic_Data!$E$2:$G$9,3,0)/VLOOKUP(I$13,Data_Entry!$C:$V,20,0),"") | J20: =IFERROR(VLOOKUP(J$13,Data_Entry!$C:$M,Data_Entry!$A8,0)/VLOOKUP($B20,Basic_Data!$E$2:$G$9,3,0)/VLOOKUP(J$13,Data_Entry!$C:$V,20,0),"") | ... AG20: =IFERROR(VLOOKUP(AG$13,Data_Entry!$C:$M,Data_Entry!$A8,0)/VLOOKUP($B20,Basic_Data!$E$2:$G$9,3,0)/VLOOKUP(AG$13,Data_Entry!$C:$V,20,0),"")
B21: Avg_PR% | C21: =AVERAGE(C14:C20) -> 1.1747191 | D21: =AVERAGE(D14:D20) -> #DIV/0! | E21: =AVERAGE(E14:E20) -> #DIV/0! | F21: =AVERAGE(F14:F20) -> #DIV/0! | G21: =AVERAGE(G14:G20) -> #DIV/0! | H21: =AVERAGE(H14:H20) -> #DIV/0! | I21: =AVERAGE(I14:I20) -> #DIV/0! | J21: =AVERAGE(J14:J20) -> #DIV/0! | ... AH21: =AVERAGE(AH14:AH20) -> #DIV/0!

Sheet Basic_Data
A2: Details_of_Plant | B2: Values | E2: Inverter_Name | F2: AC_Capacity_MW | G2: Connected_DC_MW | H2: No_Of_Module
A3: D.O.C(DD-MMM-YYY) | B3: 45720 | E3: Inv_1 | F3: 275 | G3: 335.72 | H3: =G3/0.545 -> 616 | I3: 2
A4: Plant_Name | B4: Devki Galol | E4: Inv_2 | F4: 275 | G4: 335.72 | H4: =G4/0.545 -> 616 | I4: 3
A5: Longitude_Of_Site | B5: 21.62 °N | E5: Inv_3 | F5: 275 | G5: 335.72 | H5: =G5/0.545 -> 616 | I5: 4
A6: Latitude_Of_Site | B6: 70.69 °E | E6: Inv_4 | F6: 275 | G6: 350.98 | H6: =G6/0.545 -> 644 | I6: 5
A7: DC_Capacity_(kWh) | B7: 2.411 | E7: Inv_5 | F7: 275 | G7: 350.98 | H7: =G7/0.545 -> 644 | I7: 6
A8: AC_Capacity_(kWh) | B8: 1.925 | E8: Inv_6 | F8: 275 | G8: 350.98 | H8: =G8/0.545 -> 644 | I8: 7
A9: Connected_DC_Capacity | B9: =SUM(G3:G94) -> 4822.16 | E9: Inv_7 | F9: 275 | G9: 350.98 | H9: =G9/0.545 -> 644 | I9: 8
A10: Multiplying_Factor_(MF) | B10: 3000 | E10: Total | F10: =SUM(F3:F9) -> 1925 | G10: =SUM(G3:G9) -> 2411.08 | H10: =SUM(H3:H9) -> 4424
A11: No._of_Power_Trafo. | B11: 1
A12: Power_Trafo._Make | B12: Gujrat_Trafo
A13: Inverter_Make | B13: Watt_power
A14: Inverter_Capacity | B14: 0.275
A15: No._of_Inverter | B15: 7
A16: Module_Make | B16: EMMVEE
A17: Module_Rating | B17: 545
A18: No._of_Strings/Table | B18: 158
A19: No._Of_Module_In_Table | B19: 28 for Bifacial
A20: Total_Module | B20: 4424
A21: Switch_Yard_Make_Vendors | B21: ABB
A22: Table_Configuration | B22: 2X28
A23: ABT Meter Make
A27: FY:Name | B27: From_FY | C27: To_FY
A28: 12-13 | B28: 41000 | C28: 41364 | D28: 365
A29: 13-14 | B29: 41365 | C29: 41729 | D29: 365
A30: 14-15 | B30: 41730 | C30: 42094 | D30: 365
A31: 15-16 | B31: 42095 | C31: 42460 | D31: 366
A32: 16-17 | B32: 42461 | C32: 42825 | D32: 365
A33: 17-18 | B33: 42826 | C33: 43190 | D33: 365
A34: 18-19 | B34: 43191 | C34: 43555 | D34: 365
A35: 19-20 | B35: 43556 | C35: 43921 | D35: 366
A36: 20-21 | B36: 43922 | C36: 44286 | D36: 365
A37: 21-22 | B37: 44287 | C37: 44651 | D37: 365
A38: 22-23 | B38: 44652 | C38: 45016 | D38: 365
A39: 23-24 | B39: 45017 | C39: 45382 | D39: 366
... A48: 32-33 | B48: 48305 | C48: 48669 | D48: 365

Sheet Plant_Down_Time Details
A1: Plant_Down_Time Details
A2: Month | B2: Date | C2: Inverter_No | D2: String_No | E2: Down_Time_Start | F2: Down_Time_Stop | G2: Total_Down_Time | H2: Affected DC Capacity (in KW) | I2: Insolation*Capacity | J2: Generation Loss | K2: Revenue | L2: Component Name | M2: Fault Description | N2: Reason_Of_Down | O2: Purposed Action Plan | P2: Material Consumption Description | Q2: UOM | R2: Quantity | S2: Corrective_Action_Taken_By_Site_Team
A3: 45747 | B3: 45747
A4: 45748 | B4: 45748
A5: 45749 | B5: 45749
A6: 45750 | B6: 45750
A7: 45751 | B7: 45751 | C7: all inverter | D7: all inverter | E7: 0.51736111 | F7: 0.63194444 | G7: 0.11458333 | H7: 2411 | N7: DO WIRE BURNED
A8: 45752 | B8: 45752
A9: 45753 | B9: 45753 | C9: all inverter | D9: all inverter | E9: 0.52777778 | F9: 0.59375 | G9: 0.065972222 | H9: 2411 | N9: DO WIRE BURNED
A10: 45754 | B10: 45754
A11: 45755 | B11: 45755
A12: 45756 | B12: 45756
A13: 45757 | B13: 45757
A14: 45758 | B14: 45758
A15: 45759 | B15: 45759
A16: 45760 | B16: 45760 | C16: all inverter | D16: - | E16: 0.53333333 | F16: 0.58333333 | G16: 0.05 | H16: 2411 | N16: DO FUSE WIRE BLOWN | R16: 1
A17: 45761 | B17: 45761
A18: 45762 | B18: 45762
A19: 45763 | B19: 45763 | C19: all inverter | D19: all inverter | E19: 0.27083333 | F19: 0.55902778 | G19: 0.28819444 | H19: 2411 | N19: GETCO SUTDOWN
A20: 45764 | B20: 45764
A21: 45765 | B21: 45765
A22: 45766 | B22: 45766 | C22: 7 | D22: All string | E22: 0.28819444 | F22: 0.49166667 | G22: 0.20347222 | H22: 275 | N22: pv array ground | R22: 23 nos
A23: 45767 | B23: 45767 | C23: 7 | D23: All string | E23: 0.28819444 | F23: 0.42083333 | G23: 0.12569444 | H23: 275 | N23: pv array ground | R23: 23 nos
A24: 45768 | B24: 45768
A25: 45769 | B25: 45769
A26: 45770 | B26: 45770 | C26: All inverter | D26: All string | E26: 0.7125 | F26: 0.72916667 | G26: 0.016666667 | H26: 2411 | N26: plant site relay operate in over voltage | S26: After proper relay setting
A27: 45771 | B27: 45771
A28: 45772 | B28: 45772
A29: 45773 | B29: 45773
A30: 45774 | B30: 45774
A31: 45775 | B31: 45775
A32: 45776 | B32: 45776
A33: 45777 | B33: 45777
A34: 45778 | B34: 45778
A35: 45779 | B35: 45779
A36: 45780 | B36: 45780
A37: 45781 | B37: 45781
A38: 45782 | B38: 45782
... A70: 45814 | B70: 45814
A71: 45815 | B71: 45815 | C71: all inverter | D71: all inverter | E71: 0.34375 | F71: 0.39583333 | G71: 0.052083333 | H71: 2411 | L71: TRANSFORMER | M71: BUCHHOLZ RELY ALARM | S71: replace buchholz rely by GT transformer team
A72: 45816 | B72: 45816
A73: 45817 | B73: 45817
A74: 45818 | B74: 45818 | C74: All inverter | D74: All string | E74: 0.63888889 | F74: 0.70138889 | G74: 0.0625 | H74: 2411 | L74: DO FUSE wire | M74: DO Wire burned | N74: DO Wire burned | R74: 1 | S74: Replace DO wire in GETCO s/s side
A75: 45819 | B75: 45819
A76: 45820 | B76: 45820
A77: 45821 | B77: 45821
A78: 45822 | B78: 45822
A79: 45823 | B79: 45823
A80: 45824 | B80: 45824
A81: 45825 | B81: 45825
A82: 45826 | B82: 45826
A83: 45827 | B83: 45827
A84: 45828 | B84: 45828
A85: 45829 | B85: 45829
A86: 45830 | B86: 45830
A87: 45831 | B87: 45831
A88: 45832 | B88: 45832 | C88: All inverter | D88: All inverter | E88: 0.36805556 | F88: 0.38194444 | G88: 0.013888889 | H88: 2411 | L88: GETCO | M88: 66KV GETCO LINE TRIP | N88: 66KV GETCO LINE TRIP
A89: 45833 | B89: 45833
A90: 45834 | B90: 45834
A91: 45835 | B91: 45835
A92: 45836 | B92: 45836
A93: 45837 | B93: 45837
A94: 45838 | B94: 45838 | C94: All inverter | D94: All string | E94: 0.29166667 | F94: 0.47222222 | G94: =F94-E94 -> 0.18055556 | H94: 2411 | L94: DO FUSE wire | M94: DO Wire burned | N94: DO Wire burned | S94: Replace DO wire in GETCO s/s side & also tree cutting done
A95: 45839 | B95: 45839
A96: 45840 | B96: 45840
A97: 45841 | B97: 45841
A98: 45842 | B98: 45842
A99: 45843 | B99: 45843
A100: 45844 | B100: 45844
A101: 45845 | B101: 45845
A102: 45846 | B102: 45846
A103: 45847 | B103: 45847
A104: 45848 | B104: 45848
A105: 45849 | B105: 45849
A106: 45850 | B106: 45850 | C106: All inverter | D106: All string | E106: 0.49305556 | F106: 0.54861111 | G106: =F106-E106 -> 0.055555556 | H106: 2411 | L106: Y phase jumper | M106: burinig jumper | S106: work done by site team
A107: 45851 | B107: 45851 | C107: All inverter | D107: All string | E107: 0.46527778 | F107: 0.57638889 | G107: =F107-E107 -> 0.11111111 | H107: 2411 | L107: Y phase jumper | M107: burinig jumper | S107: work done by site team
A108: 45852 | B108: 45852
A109: 45853 | B109: 45853
A110: 45854 | B110: 45854
A111: 45855 | B111: 45855
A112: 45856 | B112: 45856
A113: 45857 | B113: 45857
A114: 45858 | B114: 45858
A115: 45859 | B115: 45859
A116: 45860 | B116: 45860
A117: 45861 | B117: 45861 | C117: All inverter | D117: All inverter | E117: 0.375 | F117: 0.48263889 | G117: 0.10763889 | H117: 2411 | L117: GETCO | M117: GETCO MAINTANANCE
A118: 45862 | B118: 45862
A119: 45863 | B119: 45863
A120: 45864 | B120: 45864
A121: 45865 | B121: 45865
A122: 45866 | B122: 45866
A123: 45867 | B123: 45867
A124: 45868 | B124: 45868
A125: 45869 | B125: 45869
A126: 45870 | B126: 45870
A127: 45871 | B127: 45871
A128: 45872 | B128: 45872
A129: 45873 | B129: 45873
A130: 45874 | B130: 45874 | C130: All inverter | D130: All string | E130: 0.4375 | F130: 0.52083333 | G130: =F130-E130 -> 0.083333333 | H130: 2411 | L130: Y PHASE DO WIRE | M130: DO WIRE BURINING | S130: Resolve by site team
A131: 45875 | B131: 45875 | G131: =F131-E131 -> 0
...

Sheet Plant_Grid_Down_Time_Details
A1: Plant_Grid_Down_Time_Details
A3: Month | B3: Date | C3: Transformer_No. (T-1) | D3: Down_Time_Start | E3: Down_Time_Stop | F3: Total_Down_Time | G3: Comm. Insolation of the Period | H3: Module Temp of the Period | I3: Affected DC Capacity (in KW) | J3: Insolation*Capacity | K3: Generation Loss | L3: Revenue | M3: REMARK
A4: 45751 | B4: 45751 | C4: 1 | D4: 0.51736111 | E4: 0.63194444 | F4: 0.11458333 | I4: 2411 | M4: Do wire burned
A5: 45751 | B5: 45812 | C5: 1 | D5: 0.52777778 | E5: 0.59375 | F5: 0.065972222 | I5: 2411 | M5: Do wire burned
A6: 45751 | B6: 13/04/2025 | C6: 1 | D6: 0.53333333 | E6: 0.58333333 | F6: 0.05 | I6: 2411 | M6: Do wire burned
A7: 45751 | B7: 16/04/2025 | C7: 1 | D7: 0.27083333 | E7: 0.55902778 | F7: 0.28819444 | I7: 2411 | M7: getco shutdown
A8: 45751 | B8: 23/04/2025 | C8: 1 | D8: 0.7125 | E8: 0.72916667 | F8: 0.016666667 | I8: 2411 | M8: o/v u/v trip getco site
A9: 45811 | B9: 45844 | C9: 1 | D9: 0.34375 | E9: 0.39583333 | F9: 0.052083333 | I9: 2411 | M9: replace buchholz rely by GT transformer team
A10: 45811 | B10: 45936 | C10: 1 | D10: 0.63888889 | E10: 0.70138889 | F10: 0.0625 | I10: 2411 | M10: Do wire burned
A11: 45811 | B11: 24/6/2025 | C11: 1 | D11: 0.36805556 | E11: 0.38194444 | F11: 0.013888889 | I11: 2411 | M11: 66kv getco line trip
A12: 45811 | B12: 30/6/2025 | C12: 1 | D12: 0.29166667 | E12: 0.47222222 | F12: 0.18055556 | I12: 2411 | M12: o/v u/v trip getco site
A13: 45839 | B13: 45998 | C13: 1 | D13: 0.44444444 | E13: 0.49652778 | F13: 0.048611111 | I13: 2411 | M13: y phase jumper burned
A14: 45839 | B14: 13/7/2025 | C14: 1 | D14: 0.46527778 | E14: 0.57638889 | F14: 0.11111111 | I14: 2411 | M14: y phase jumper burned
A15: 45839 | B15: 23/7/2025 | C15: 1 | D15: 0.375 | E15: 0.48263889 | F15: 0.10763889 | I15: 2411 | M15: getco site maintanance
A16: 45926 | B16: 17/9/2025 | C16: 1 | D16: 0.3125 | E16: 0.5 | F16: 0.1875 | I16: 2411 | M16: 66kv shutdown
A17: 45936 | B17: 45971 | C17: 1 | D17: 0.53125 | E17: 0.60416667 | F17: 0.072916667 | I17: 2411 | M17: B phase jumper burned
A18: 45973 | B18: 45972 | C18: 1 | D18: 0.5 | E18: 0.56597222 | F18: 0.065972222 | I18: 2411 | M18: R phase jumper burned
A19: 46012 | B19: 21/12/2025 | C19: 1 | D19: 0.47222222 | E19: 0.53125 | F19: 0.059027778 | I19: 2411 | M19: normal tripping
A20: 46012 | B20: 29/12/2025 | C20: 1 | D20: 0.53472222 | E20: 0.53819444 | F20: 0.0034722222 | I20: 2411 | M20: High voltage ss site
A21: 46034 | B21: 46113 | C21: 1 | D21: 0.49652778 | E21: 0.50902778 | F21: 0.0125 | I21: 2411 | M21: getco main 1 trip
A22: 46034 | B22: 46174 | C22: 1 | D22: 0.61666667 | E22: 0.63194444 | F22: 0.015277778 | I22: 2411 | M22: getco main 1 trip
A23: 46034 | B23: 46266 | C23: 1 | D23: 0.48958333 | E23: 0.52291667 | F23: 0.033333333 | I23: 2411 | M23: gt team visted for transformer oil lekege attend
A24: 46034 | B24: 21/1/2026 | C24: 1 | D24: 0.67708333 | E24: 0.81597222 | F24: 0.13888889 | I24: 2411 | M24: tree cutting work
A25: 46082 | B25: 46107 | C25: 1 | D25: 0.53472222 | E25: 0.54513889 | F25: 0.010416667 | I25: 2411 | M25: getco site maintanance
A26: 46082 | B26: 46111 | C26: 1 | D26: 0.59722222 | E26: 0.60416667 | F26: 0.0069444444 | I26: 2411 | M26: getco side braker testing work
A27: 46113 | B27: 46119 | C27: 1 | D27: 0.47916667 | E27: 0.55555556 | F27: 0.076388889 | I27: 2411 | M27: getco side y phase ctpt lug burned
A28: 46113 | B28: 46119 | C28: 1 | D28: 0.63680556 | E28: 0.64375 | F28: 0.0069444444 | I28: 2411 | M28: getco side 66kv line trip
A29: 46143 | B29: 46155 | C29: 1 | D29: 0.29166667 | E29: 0.72569444 | F29: 0.43402778 | I29: 2411 | M29: 66kv shutdown

Sheet WMS
A1: Months | B1: Date | C1: GHI | D1: GTI | E1: Module_Temp | F1: Amb_Temp | G1: Derect_Irr | H1: Diffused_Irr | I1: Wind_Speed | J1: Wind_derection | K1: Rain Gauge
A2: 45747 | B2: 45747
A3: 45748 | B3: 45748
A4: 45749 | B4: 45749
A5: 45750 | B5: 45750
A6: 45751 | B6: 45751
A7: 45752 | B7: 45752
A8: 45753 | B8: 45753
A9: 45754 | B9: 45754
A10: 45755 | B10: 45755
A11: 45756 | B11: 45756
A12: 45757 | B12: 45757 | D12: 5.5
A13: 45758 | B13: 45758 | D13: 5.84
A14: 45759 | B14: 45759 | D14: 5.8
A15: 45760 | B15: 45760 | D15: 5.18
A16: 45761 | B16: 45761 | D16: 6
A17: 45762 | B17: 45762 | D17: 5.85
A18: 45763 | B18: 45763 | D18: 2.29 | F18: 35.67
A19: 45764 | B19: 45764 | D19: 6.08
A20: 45765 | B20: 45765 | D20: 6.08
A21: 45766 | B21: 45766 | D21: 6.04 | F21: 33.84
A22: 45767 | B22: 45767 | D22: 6.13 | F22: 34.14
A23: 45768 | B23: 45768 | D23: 6.1 | F23: 34.98
A24: 45769 | B24: 45769 | D24: 6.18 | F24: 36.39
A25: 45770 | B25: 45770 | D25: 6 | F25: 36.52
A26: 45771 | B26: 45771 | D26: 6.14 | F26: 35.7
A27: 45772 | B27: 45772 | D27: 6.26 | F27: 34.21
A28: 45773 | B28: 45773 | D28: 4.79 | F28: 34.5
A29: 45774 | B29: 45774 | D29: 5.39 | F29: 35.93
A30: 45775 | B30: 45775 | D30: 6.19 | F30: 36.38
A31: 45776 | B31: 45776 | D31: 6.29 | F31: 36.8
A32: 45777 | B32: 45777 | D32: 6.11 | F32: 35.7
... A142: 45887 | B142: 45887 | D142: 2.69 | F142: 30.29
A143: 45888 | B143: 45888
A144: 45889 | B144: 45889
A145: 45890 | B145: 45890
A146: 45891 | B146: 45891
A147: 45892 | B147: 45892
A148: 45893 | B148: 45893
A149: 45894 | B149: 45894
A150: 45895 | B150: 45895
A151: 45896 | B151: 45896
A152: 45897 | B152: 45897
A153: 45898 | B153: 45898
A154: 45899 | B154: 45899
... A175: 45920 | B175: 45920
A176: 45921 | B176: 45921 | D176: 3.72 | F176: 29.51
A177: 45922 | B177: 45922 | D177: 2.9 | F177: 28.93
A178: 45923 | B178: 45923 | D178: 3.28 | F178: 30.41
A179: 45924 | B179: 45924 | D179: 2.92 | F179: 29.76
A180: 45925 | B180: 45925 | D180: 2.45 | F180: 31.25
A181: 45926 | B181: 45926
A182: 45927 | B182: 45927
A183: 45928 | B183: 45928 | F183: 27.54
A184: 45929 | B184: 45929 | F184: 26.23
A185: 45930 | B185: 45930 | D185: 0.91 | F185: 23.52
A186: 45931 | B186: 45931 | D186: 1.15 | F186: 25.77
A187: 45932 | B187: 45932 | D187: 0.94 | F187: 27.16
A188: 45933 | B188: 45933 | D188: 4.89 | F188: 31.51
A189: 45934 | B189: 45934 | D189: 1.13 | F189: 29.31
A190: 45935 | B190: 45935 | D190: 1.13 | F190: 29.55
A191: 45936 | B191: 45936 | D191: 0.84 | F191: 28.06
A192: 45937 | B192: 45937 | D192: 0 | F192: 29.77
A193: 45938 | B193: 45938 | D193: 0 | F193: 30.47
A194: 45939 | B194: 45939 | D194: 0 | F194: 30.88
A195: 45940 | B195: 45940 | D195: 0 | F195: 31.35
A196: 45941 | B196: 45941 | D196: 0 | F196: 31.55
... A273: 46018 | B273: 46018 | D273: 3.75 | F273: 24.75
A274: 46019 | B274: 46019 | F274: 23.8
A275: 46020 | B275: 46020 | D275: 3.76 | F275: 25.63
A276: 46021 | B276: 46021 | D276: 3.72 | F276: 24.75
A277: 46022 | B277: 46022 | D277: 3.22 | F277: 25.41
A278: 46023 | B278: 46023 | D278: 4.03 | F278: 24.46
A279: 46024 | B279: 46024 | D279: 4.05 | F279: 22.95
A280: 46025 | B280: 46025 | D280: 4.34 | F280: 22.14
A281: 46026 | B281: 46026 | D281: 4.1 | F281: 22.57
A282: 46027 | B282: 46027 | D282: 4.03 | F282: 23.17
A283: 46028 | B283: 46028 | D283: 4.09 | F283: 23.23
A284: 46029 | B284: 46029 | D284: 1.3 | F284: 20.81
A285: 46030 | B285: 46030 | D285: 3.62 | F285: 21.85
A286: 46031 | B286: 46031 | D286: 3.76 | F286: 20.97
... A433: 46178 | B433: 46178 | D433: 3.66 | F433: 34.09
A434: 46179 | B434: 46179
A435: 46180 | B435: 46180
A436: 46181 | B436: 46181
A437: 46182 | B437: 46182
A438: 46183 | B438: 46183
A439: 46184 | B439: 46184
A440: 46185 | B440: 46185
A441: 46186 | B441: 46186
A442: 46187 | B442: 46187
A443: 46188 | B443: 46188
A444: 46189 | B444: 46189
A445: 46190 | B445: 46190
... A489: 46234 | B489: 46234

Sheet Module_Cleaning
C2: Water Consumption
A3: Months | B3: Date | C3: Tanker Qty | D3: Consumption (Capacity(Ltr)* Tanker) | E3: TDS (PPM) | F3: Cycle No. | G3: Invt. No | I3: Module | J3: Cleaned | K3: Before Cleaning PR% | L3: After Cleaning PR% | M3: Balance | N3: Remarks
A4: 45747 | B4: 45747
A5: 45748 | B5: 45748
A6: 45749 | B6: 45749
A7: 45750 | B7: 45750
A8: 45751 | B8: 45751
A9: 45752 | B9: 45752
A10: 45753 | B10: 45753
A11: 45754 | B11: 45754
A12: 45755 | B12: 45755
A13: 45756 | B13: 45756
A14: 45757 | B14: 45757 | H14: =IFERROR(VLOOKUP(G14,Basic_Data!$E$2:$I$9,5,0),"") | I14: =IFERROR(VLOOKUP($G14,Basic_Data!$E$2:$H$10,4,0),"") | K14: =IFERROR(VLOOKUP($B14-1,Inverter_PR!$B:$I,Module_Cleaning!H14,0),"") | L14: =IFERROR(VLOOKUP($B14+1,Inverter_PR!$B:$I,Module_Cleaning!H14,0),"") | M14: =IFERROR(I14-J14,"")
A15: 45758 | B15: 45758 | G15: Inv_4 | H15: =IFERROR(VLOOKUP(G15,Basic_Data!$E$2:$I$9,5,0),"") -> 5 | I15: =IFERROR(VLOOKUP($G15,Basic_Data!$E$2:$H$10,4,0),"") -> 644 | J15: 644 | K15: =IFERROR(VLOOKUP($B15-1,Inverter_PR!$B:$I,Module_Cleaning!H15,0),"") -> 1.0158051 | L15: =IFERROR(VLOOKUP($B15+1,Inverter_PR!$B:$I,Module_Cleaning!H15,0),"") -> 1.015526 | M15: =IFERROR(I15-J15,"") -> 0 | N15: robot cleaning
A16: 45759 | B16: 45759 | G16: Inv_3 | H16: =IFERROR(VLOOKUP(G16,Basic_Data!$E$2:$I$9,5,0),"") -> 4 | I16: =IFERROR(VLOOKUP($G16,Basic_Data!$E$2:$H$10,4,0),"") -> 616 | J16: 616 | K16: =IFERROR(VLOOKUP($B16-1,Inverter_PR!$B:$I,Module_Cleaning!H16,0),"") -> 1.0020683 | L16: =IFERROR(VLOOKUP($B16+1,Inverter_PR!$B:$I,Module_Cleaning!H16,0),"") -> 0.96637228 | M16: =IFERROR(I16-J16,"") -> 0 | N16: robot cleaning
A17: 45760 | B17: 45760 | H17: =IFERROR(VLOOKUP(G17,Basic_Data!$E$2:$I$9,5,0),"") | I17: =IFERROR(VLOOKUP($G17,Basic_Data!$E$2:$H$10,4,0),"") | K17: =IFERROR(VLOOKUP($B17-1,Inverter_PR!$B:$I,Module_Cleaning!H17,0),"") | L17: =IFERROR(VLOOKUP($B17+1,Inverter_PR!$B:$I,Module_Cleaning!H17,0),"") | M17: =IFERROR(I17-J17,"")
A18: 45761 | B18: 45761 | G18: Inv_7 | H18: =IFERROR(VLOOKUP(G18,Basic_Data!$E$2:$I$9,5,0),"") -> 8 | I18: =IFERROR(VLOOKUP($G18,Basic_Data!$E$2:$H$10,4,0),"") -> 644 | J18: 644 | K18: =IFERROR(VLOOKUP($B18-1,Inverter_PR!$B:$I,Module_Cleaning!H18,0),"") -> 0.93919595 | L18: =IFERROR(VLOOKUP($B18+1,Inverter_PR!$B:$I,Module_Cleaning!H18,0),"") -> 0.97473107 | M18: =IFERROR(I18-J18,"") -> 0 | N18: wet cleaning
A19: 45762 | B19: 45762 | C19: 5 | D19: 7500 | F19: 2 | G19: Inv_1 | H19: =IFERROR(VLOOKUP(G19,Basic_Data!$E$2:$I$9,5,0),"") -> 2 | I19: =IFERROR(VLOOKUP($G19,Basic_Data!$E$2:$H$10,4,0),"") -> 616 | J19: 616 | K19: =IFERROR(VLOOKUP($B19-1,Inverter_PR!$B:$I,Module_Cleaning!H19,0),"") -> 0.96935442 | L19: =IFERROR(VLOOKUP($B19+1,Inverter_PR!$B:$I,Module_Cleaning!H19,0),"") -> 1.0256129 | M19: =IFERROR(I19-J19,"") -> 0
G20: Inv_2 | H20: =IFERROR(VLOOKUP(G20,Basic_Data!$E$2:$I$9,5,0),"") -> 3 | I20: =IFERROR(VLOOKUP($G20,Basic_Data!$E$2:$H$10,4,0),"") -> 616 | J20: 616 | K20: =IFERROR(VLOOKUP($B20-1,Inverter_PR!$B:$I,Module_Cleaning!H20,0),"") | L20: =IFERROR(VLOOKUP($B20+1,Inverter_PR!$B:$I,Module_Cleaning!H20,0),"")
G21: Inv_3 | H21: =IFERROR(VLOOKUP(G21,Basic_Data!$E$2:$I$9,5,0),"") -> 4 | I21: =IFERROR(VLOOKUP($G21,Basic_Data!$E$2:$H$10,4,0),"") -> 616 | J21: 616 | K21: =IFERROR(VLOOKUP($B21-1,Inverter_PR!$B:$I,Module_Cleaning!H21,0),"") | L21: =IFERROR(VLOOKUP($B21+1,Inverter_PR!$B:$I,Module_Cleaning!H21,0),"")
G22: Inv_4 | H22: =IFERROR(VLOOKUP(G22,Basic_Data!$E$2:$I$9,5,0),"") -> 5 | I22: =IFERROR(VLOOKUP($G22,Basic_Data!$E$2:$H$10,4,0),"") -> 644 | J22: 644 | K22: =IFERROR(VLOOKUP($B22-1,Inverter_PR!$B:$I,Module_Cleaning!H22,0),"") | L22: =IFERROR(VLOOKUP($B22+1,Inverter_PR!$B:$I,Module_Cleaning!H22,0),"")
G23: Inv_5 | H23: =IFERROR(VLOOKUP(G23,Basic_Data!$E$2:$I$9,5,0),"") -> 6 | I23: =IFERROR(VLOOKUP($G23,Basic_Data!$E$2:$H$10,4,0),"") -> 644 | J23: 644 | K23: =IFERROR(VLOOKUP($B23-1,Inverter_PR!$B:$I,Module_Cleaning!H23,0),"") | L23: =IFERROR(VLOOKUP($B23+1,Inverter_PR!$B:$I,Module_Cleaning!H23,0),"")
A24: 45763 | B24: 45763 | C24: 2 | D24: 3000 | F24: 2 | G24: Inv_6 | H24: =IFERROR(VLOOKUP(G24,Basic_Data!$E$2:$I$9,5,0),"") -> 7 | I24: =IFERROR(VLOOKUP($G24,Basic_Data!$E$2:$H$10,4,0),"") -> 644 | J24: 644 | K24: =IFERROR(VLOOKUP($B24-1,Inverter_PR!$B:$I,Module_Cleaning!H24,0),"") -> 0.9763529 | L24: =IFERROR(VLOOKUP($B24+1,Inverter_PR!$B:$I,Module_Cleaning!H24,0),"") -> 0.98587676 | M24: =IFERROR(I24-J24,"") -> 0
G25: Inv_7 | I25: =IFERROR(VLOOKUP($G25,Basic_Data!$E$2:$H$10,4,0),"") -> 644 | J25: 644
A26: 45764 | B26: 45764 | C26: 0 | D26: 0 | E26: 0 | H26: =IFERROR(VLOOKUP(G26,Basic_Data!$E$2:$I$9,5,0),"") | I26: 0 | J26: 0 | K26: =IFERROR(VLOOKUP($B26-1,Inverter_PR!$B:$I,Module_Cleaning!H26,0),"") | L26: =IFERROR(VLOOKUP($B26+1,Inverter_PR!$B:$I,Module_Cleaning!H26,0),"") | M26: =IFERROR(I26-J26,"") -> 0 | N26: No cleaning
A27: 45765 | B27: 45765 | C27: 0 | D27: 0 | E27: 0 | H27: =IFERROR(VLOOKUP(G27,Basic_Data!$E$2:$I$9,5,0),"") | I27: 0 | J27: 0 | K27: =IFERROR(VLOOKUP($B27-1,Inverter_PR!$B:$I,Module_Cleaning!H27,0),"") | L27: =IFERROR(VLOOKUP($B27+1,Inverter_PR!$B:$I,Module_Cleaning!H27,0),"") | M27: =IFERROR(I27-J27,"") -> 0 | N27: No cleaning
A28: 45766 | B28: 45766 | F28: 3 | G28: Inv_1 | H28: =IFERROR(VLOOKUP(G28,Basic_Data!$E$2:$I$9,5,0),"") -> 2 | I28: =IFERROR(VLOOKUP($G28,Basic_Data!$E$2:$H$10,4,0),"") -> 616 | J28: 616 | K28: =IFERROR(VLOOKUP($B28-1,Inverter_PR!$B:$I,Module_Cleaning!H28,0),"") -> 0.99241242 | L28: =IFERROR(VLOOKUP($B28+1,Inverter_PR!$B:$I,Module_Cleaning!H28,0),"") -> 0.95986635 | M28: =IFERROR(I28-J28,"") -> 0 | N28: robot cleaning
A29: 45766 | B29: 45766 | F29: 3 | G29: Inv_2 | I29: =IFERROR(VLOOKUP($G29,Basic_Data!$E$2:$H$10,4,0),"") -> 616 | J29: 616 | K29: =IFERROR(VLOOKUP($B29-1,Inverter_PR!$B:$I,Module_Cleaning!H29,0),"") | M29: =IFERROR(I29-J29,"") -> 0 | N29: robot cleaning
A30: 45767 | B30: 45767 | F30: 3 | G30: Inv_3 | H30: =IFERROR(VLOOKUP(G30,Basic_Data!$E$2:$I$9,5,0),"") -> 4 | I30: =IFERROR(VLOOKUP($G30,Basic_Data!$E$2:$H$10,4,0),"") -> 616 | J30: 616 | K30: =IFERROR(VLOOKUP($B30-1,Inverter_PR!$B:$I,Module_Cleaning!H30,0),"") -> 0.99134074 | L30: =IFERROR(VLOOKUP($B30+1,Inverter_PR!$B:$I,Module_Cleaning!H30,0),"") -> 0.95275044 | M30: =IFERROR(I30-J30,"") -> 0 | N30: robot cleaning
A31: 45767 | B31: 45767 | F31: 3 | G31: Inv_4 | H31: 5 | I31: 644 | J31: 644 | K31: =IFERROR(VLOOKUP($B31-1,Inverter_PR!$B:$I,Module_Cleaning!H31,0),"") -> 1.0085998 | L31: =IFERROR(VLOOKUP($B31+1,Inverter_PR!$B:$I,Module_Cleaning!H31,0),"") -> 0.97143922 | M31: =IFERROR(I31-J31,"") -> 0 | N31: robot cleaning
A32: 45768 | B32: 45768 | F32: 3 | G32: Inv_5 | H32: =IFERROR(VLOOKUP(G32,Basic_Data!$E$2:$I$9,5,0),"") -> 6 | I32: =IFERROR(VLOOKUP($G32,Basic_Data!$E$2:$H$10,4,0),"") -> 644 | J32: 644 | K32: =IFERROR(VLOOKUP($B32-1,Inverter_PR!$B:$I,Module_Cleaning!H32,0),"") -> 1.0020974 | L32: =IFERROR(VLOOKUP($B32+1,Inverter_PR!$B:$I,Module_Cleaning!H32,0),"") -> 0.97613414 | M32: =IFERROR(I32-J32,"") -> 0 | N32: robot cleaning
A33: 45768 | B33: 45768 | F33: 3 | G33: Inv_6 | H33: 7 | I33: 644 | J33: 644 | K33: =IFERROR(VLOOKUP($B33-1,Inverter_PR!$B:$I,Module_Cleaning!H33,0),"") -> 0.95652936 | L33: =IFERROR(VLOOKUP($B33+1,Inverter_PR!$B:$I,Module_Cleaning!H33,0),"") -> 0.93259908 | M33: =IFERROR(I33-J33,"") -> 0 | N33: robot cleaning
A34: 45768 | B34: 45768 | C34: 0 | D34: 0 | E34: 0 | F34: 0 | I34: 0 | J34: 0 | K34: 0 | L34: 0 | M34: 0 | N34: No cleaning
A35: 45769 | B35: 45769 | F35: 3 | G35: Inv_7 | H35: =IFERROR(VLOOKUP(G35,Basic_Data!$E$2:$I$9,5,0),"") -> 8 | I35: =IFERROR(VLOOKUP($G35,Basic_Data!$E$2:$H$10,4,0),"") -> 644 | J35: 644 | K35: =IFERROR(VLOOKUP($B35-1,Inverter_PR!$B:$I,Module_Cleaning!H35,0),"") -> 0.83850932 | L35: =IFERROR(VLOOKUP($B35+1,Inverter_PR!$B:$I,Module_Cleaning!H35,0),"") -> 0.91839041 | M35: =IFERROR(I35-J35,"") -> 0 | N35: robot cleaning
A36: 45770 | B36: 45770 | C36: 0 | D36: 0 | E36: 0 | H36: =IFERROR(VLOOKUP(G36,Basic_Data!$E$2:$I$9,5,0),"") | I36: 0 | J36: 0 | K36: =IFERROR(VLOOKUP($B36-1,Inverter_PR!$B:$I,Module_Cleaning!H36,0),"") | L36: =IFERROR(VLOOKUP($B36+1,Inverter_PR!$B:$I,Module_Cleaning!H36,0),"") | M36: =IFERROR(I36-J36,"") -> 0 | N36: No cleaning
A37: 45771 | B37: 45771 | F37: 4 | G37: Inv_1 | H37: =IFERROR(VLOOKUP(G37,Basic_Data!$E$2:$I$9,5,0),"") -> 2 | I37: =IFERROR(VLOOKUP($G37,Basic_Data!$E$2:$H$10,4,0),"") -> 616 | J37: 616 | K37: =IFERROR(VLOOKUP($B37-1,Inverter_PR!$B:$I,Module_Cleaning!H37,0),"") -> 0.93252313 | L37: =IFERROR(VLOOKUP($B37+1,Inverter_PR!$B:$I,Module_Cleaning!H37,0),"") -> 0.96504237 | M37: =IFERROR(I37-J37,"") -> 0 | N37: robot cleaning
A38: 45772 | B38: 45772 | F38: 4 | G38: Inv_2 | H38: =IFERROR(VLOOKUP(G38,Basic_Data!$E$2:$I$9,5,0),"") -> 3 | I38: =IFERROR(VLOOKUP($G38,Basic_Data!$E$2:$H$10,4,0),"") -> 616 | J38: 616 | K38: =IFERROR(VLOOKUP($B38-1,Inverter_PR!$B:$I,Module_Cleaning!H38,0),"") -> 0.96417792 | L38: =IFERROR(VLOOKUP($B38+1,Inverter_PR!$B:$I,Module_Cleaning!H38,0),"") -> 1.2591701 | M38: =IFERROR(I38-J38,"") -> 0 | N38: robot cleaning
A39: 45773 | B39: 45773 | F39: 4 | G39: Inv_3 | H39: =IFERROR(VLOOKUP(G39,Basic_Data!$E$2:$I$9,5,0),"") -> 4 | I39: =IFERROR(VLOOKUP($G39,Basic_Data!$E$2:$H$10,4,0),"") -> 616 | J39: 616 | K39: =IFERROR(VLOOKUP($B39-1,Inverter_PR!$B:$I,Module_Cleaning!H39,0),"") -> 0.97122336 | L39: =IFERROR(VLOOKUP($B39+1,Inverter_PR!$B:$I,Module_Cleaning!H39,0),"") -> 1.1027665 | M39: =IFERROR(I39-J39,"") -> 0 | N39: robot cleaning
A40: 45774 | B40: 45774 | C40: 0 | D40: 0 | E40: 0 | F40: 0 | H40: =IFERROR(VLOOKUP(G40,Basic_Data!$E$2:$I$9,5,0),"") | I40: 0 | J40: 0 | K40: =IFERROR(VLOOKUP($B40-1,Inverter_PR!$B:$I,Module_Cleaning!H40,0),"") | L40: =IFERROR(VLOOKUP($B40+1,Inverter_PR!$B:$I,Module_Cleaning!H40,0),"") | M40: =IFERROR(I40-J40,"") -> 0 | N40: No cleaning
A41: 45775 | B41: 45775 | F41: 4 | G41: Inv_4 | H41: =IFERROR(VLOOKUP(G41,Basic_Data!$E$2:$I$9,5,0),"") -> 5 | I41: =IFERROR(VLOOKUP($G41,Basic_Data!$E$2:$H$10,4,0),"") -> 644 | J41: 644 | K41: =IFERROR(VLOOKUP($B41-1,Inverter_PR!$B:$I,Module_Cleaning!H41,0),"") -> 1.1040066 | L41: =IFERROR(VLOOKUP($B41+1,Inverter_PR!$B:$I,Module_Cleaning!H41,0),"") -> 0.96484782 | M41: =IFERROR(I41-J41,"") -> 0 | N41: robot cleaning
A42: 45776 | B42: 45776 | C42: 0 | D42: 0 | E42: 0 | F42: 0 | H42: =IFERROR(VLOOKUP(G42,Basic_Data!$E$2:$I$9,5,0),"") | I42: 0 | J42: 0 | K42: =IFERROR(VLOOKUP($B42-1,Inverter_PR!$B:$I,Module_Cleaning!H42,0),"") | L42: =IFERROR(VLOOKUP($B42+1,Inverter_PR!$B:$I,Module_Cleaning!H42,0),"") | M42: =IFERROR(I42-J42,"") -> 0 | N42: No cleaning
A43: 45777 | B43: 45777 | F43: 4 | G43: Inv_5 | H43: =IFERROR(VLOOKUP(G43,Basic_Data!$E$2:$I$9,5,0),"") -> 6 | I43: =IFERROR(VLOOKUP($G43,Basic_Data!$E$2:$H$10,4,0),"") -> 644 | J43: 644 | K43: =IFERROR(VLOOKUP($B43-1,Inverter_PR!$B:$I,Module_Cleaning!H43,0),"") -> 0.95811673 | L43: =IFERROR(VLOOKUP($B43+1,Inverter_PR!$B:$I,Module_Cleaning!H43,0),"") -> 0.95543859 | M43: =IFERROR(I43-J43,"") -> 0 | N43: robot cleaning
A44: 45778 | B44: 45778 | C44: 1 | D44: 1500 | E44: 1485 | F44: 1 | G44: Inv_1 | H44: =IFERROR(VLOOKUP(G44,Basic_Data!$E$2:$I$9,5,0),"") -> 2 | I44: =IFERROR(VLOOKUP($G44,Basic_Data!$E$2:$H$10,4,0),"") -> 616 | J44: 616 | K44: =IFERROR(VLOOKUP($B44-1,Inverter_PR!$B:$I,Module_Cleaning!H44,0),"") -> 0.97322646 | L44: =IFERROR(VLOOKUP($B44+1,Inverter_PR!$B:$I,Module_Cleaning!H44,0),"") -> 0.97758448 | M44: =IFERROR(I44-J44,"") -> 0 | N44: wet cleaning
A45: 45779 | B45: 45779 | C45: 6 | D45: 9000 | F45: 1 | G45: Inv_2 | H45: =IFERROR(VLOOKUP(G45,Basic_Data!$E$2:$I$9,5,0),"") -> 3 | I45: =IFERROR(VLOOKUP($G45,Basic_Data!$E$2:$H$10,4,0),"") -> 616 | J45: 616 | K45: =IFERROR(VLOOKUP($B45-1,Inverter_PR!$B:$I,Module_Cleaning!H45,0),"") -> 0.97512542 | L45: =IFERROR(VLOOKUP($B45+1,Inverter_PR!$B:$I,Module_Cleaning!H45,0),"") -> 0.98684808 | M45: =IFERROR(I45-J45,"") -> 0 | N45: wet cleaning
F46: 1 | G46: Inv_3 | H46: 4 | I46: =IFERROR(VLOOKUP($G46,Basic_Data!$E$2:$H$10,4,0),"") -> 616 | J46: 616 | K46: =IFERROR(VLOOKUP($B46-1,Inverter_PR!$B:$I,Module_Cleaning!H46,0),"") | N46: wet cleaning
F47: 1 | G47: Inv_4 | H47: 5 | I47: =IFERROR(VLOOKUP($G47,Basic_Data!$E$2:$H$10,4,0),"") -> 644 | J47: 616 | K47: =IFERROR(VLOOKUP($B47-1,Inverter_PR!$B:$I,Module_Cleaning!H47,0),"") | N47: wet cleaning
F48: 1 | G48: Inv_5 | H48: 6 | I48: =IFERROR(VLOOKUP($G48,Basic_Data!$E$2:$H$10,4,0),"") -> 644 | J48: 616 | K48: =IFERROR(VLOOKUP($B48-1,Inverter_PR!$B:$I,Module_Cleaning!H48,0),"") | N48: wet cleaning
F49: 1 | G49: Inv_6 | H49: 7 | I49: =IFERROR(VLOOKUP($G49,Basic_Data!$E$2:$H$10,4,0),"") -> 644 | J49: 616 | K49: =IFERROR(VLOOKUP($B49-1,Inverter_PR!$B:$I,Module_Cleaning!H49,0),"") | N49: wet cleaning
A50: 45780 | B50: 45780 | C50: 1 | D50: 1500 | F50: 1 | G50: Inv_7 | H50: =IFERROR(VLOOKUP(G50,Basic_Data!$E$2:$I$9,5,0),"") -> 8 | I50: =IFERROR(VLOOKUP($G50,Basic_Data!$E$2:$H$10,4,0),"") -> 644 | J50: 644 | K50: =IFERROR(VLOOKUP($B50-1,Inverter_PR!$B:$I,Module_Cleaning!H50,0),"") -> 0.92098259 | L50: =IFERROR(VLOOKUP($B50+1,Inverter_PR!$B:$I,Module_Cleaning!H50,0),"") -> 0.98900473 | M50: =IFERROR(I50-J50,"") -> 0 | N50: wet cleaning
A51: 45781 | B51: 45781 | C51: 0 | D51: 0 | E51: 0 | F51: 0 | H51: =IFERROR(VLOOKUP(G51,Basic_Data!$E$2:$I$9,5,0),"") | I51: 0 | J51: 0 | K51: =IFERROR(VLOOKUP($B51-1,Inverter_PR!$B:$I,Module_Cleaning!H51,0),"") | L51: =IFERROR(VLOOKUP($B51+1,Inverter_PR!$B:$I,Module_Cleaning!H51,0),"") | M51: =IFERROR(I51-J51,"") -> 0 | N51: No cleaning
A52: 45782 | B52: 45782 | C52: 0 | D52: 0 | E52: 0 | F52: 0 | H52: =IFERROR(VLOOKUP(G52,Basic_Data!$E$2:$I$9,5,0),"") | I52: 0 | J52: 0 | K52: =IFERROR(VLOOKUP($B52-1,Inverter_PR!$B:$I,Module_Cleaning!H52,0),"") | L52: =IFERROR(VLOOKUP($B52+1,Inverter_PR!$B:$I,Module_Cleaning!H52,0),"") | M52: =IFERROR(I52-J52,"") -> 0 | N52: No cleaning
A53: 45783 | B53: 45783 | C53: 0 | D53: 0 | E53: 0 | F53: 0 | H53: =IFERROR(VLOOKUP(G53,Basic_Data!$E$2:$I$9,5,0),"") | I53: 0 | J53: 0 | K53: =IFERROR(VLOOKUP($B53-1,Inverter_PR!$B:$I,Module_Cleaning!H53,0),"") | L53: =IFERROR(VLOOKUP($B53+1,Inverter_PR!$B:$I,Module_Cleaning!H53,0),"") | M53: =IFERROR(I53-J53,"") -> 0 | N53: No cleaning
A54: 45784 | B54: 45784 | H54: =IFERROR(VLOOKUP(G54,Basic_Data!$E$2:$I$9,5,0),"") | I54: =IFERROR(VLOOKUP($G54,Basic_Data!$E$2:$H$10,4,0),"") | K54: =IFERROR(VLOOKUP($B54-1,Inverter_PR!$B:$I,Module_Cleaning!H54,0),"") | L54: =IFERROR(VLOOKUP($B54+1,Inverter_PR!$B:$I,Module_Cleaning!H54,0),"") | M54: =IFERROR(I54-J54,"") | N54: All module cleaned by rain
A55: 45785 | B55: 45785 | C55: 0 | E55: 0 | F55: 0 | H55: =IFERROR(VLOOKUP(G55,Basic_Data!$E$2:$I$9,5,0),"") | I55: 0 | J55: 0 | K55: =IFERROR(VLOOKUP($B55-1,Inverter_PR!$B:$I,Module_Cleaning!H55,0),"") | L55: =IFERROR(VLOOKUP($B55+1,Inverter_PR!$B:$I,Module_Cleaning!H55,0),"") | M55: 0 | N55: No cleaning
A56: 45786 | B56: 45786 | H56: =IFERROR(VLOOKUP(G56,Basic_Data!$E$2:$I$9,5,0),"") | I56: =IFERROR(VLOOKUP($G56,Basic_Data!$E$2:$H$10,4,0),"") | K56: =IFERROR(VLOOKUP($B56-1,Inverter_PR!$B:$I,Module_Cleaning!H56,0),"") | L56: =IFERROR(VLOOKUP($B56+1,Inverter_PR!$B:$I,Module_Cleaning!H56,0),"") | M56: =IFERROR(I56-J56,"") | N56: All module cleaned by rain
A57: 45787 | B57: 45787 | H57: =IFERROR(VLOOKUP(G57,Basic_Data!$E$2:$I$9,5,0),"") | I57: =IFERROR(VLOOKUP($G57,Basic_Data!$E$2:$H$10,4,0),"") | K57: =IFERROR(VLOOKUP($B57-1,Inverter_PR!$B:$I,Module_Cleaning!H57,0),"") | L57: =IFERROR(VLOOKUP($B57+1,Inverter_PR!$B:$I,Module_Cleaning!H57,0),"") | M57: =IFERROR(I57-J57,"") | N57: All module cleaned by rain
A58: 45788 | B58: 45788 | C58: 0 | E58: 0 | F58: 0 | H58: =IFERROR(VLOOKUP(G58,Basic_Data!$E$2:$I$9,5,0),"") | I58: 0 | J58: 0 | K58: =IFERROR(VLOOKUP($B58-1,Inverter_PR!$B:$I,Module_Cleaning!H58,0),"") | L58: =IFERROR(VLOOKUP($B58+1,Inverter_PR!$B:$I,Module_Cleaning!H58,0),"") | M58: 0 | N58: No cleaning
A59: 45789 | B59: 45789 | C59: 0 | E59: 0 | F59: 0 | H59: =IFERROR(VLOOKUP(G59,Basic_Data!$E$2:$I$9,5,0),"") | I59: 0 | J59: 0 | K59: =IFERROR(VLOOKUP($B59-1,Inverter_PR!$B:$I,Module_Cleaning!H59,0),"") | L59: =IFERROR(VLOOKUP($B59+1,Inverter_PR!$B:$I,Module_Cleaning!H59,0),"") | M59: 0 | N59: No cleaning
A60: 45790 | B60: 45790 | C60: 0 | E60: 0 | F60: 0 | H60: =IFERROR(VLOOKUP(G60,Basic_Data!$E$2:$I$9,5,0),"") | I60: 0 | J60: 0 | K60: =IFERROR(VLOOKUP($B60-1,Inverter_PR!$B:$I,Module_Cleaning!H60,0),"") | L60: =IFERROR(VLOOKUP($B60+1,Inverter_PR!$B:$I,Module_Cleaning!H60,0),"") | M60: 0 | N60: No cleaning
A61: 45791 | B61: 45791 | C61: 0 | E61: 0 | F61: 0 | H61: =IFERROR(VLOOKUP(G61,Basic_Data!$E$2:$I$9,5,0),"") | I61: 0 | J61: 0 | K61: =IFERROR(VLOOKUP($B61-1,Inverter_PR!$B:$I,Module_Cleaning!H61,0),"") | L61: =IFERROR(VLOOKUP($B61+1,Inverter_PR!$B:$I,Module_Cleaning!H61,0),"") | M61: 0 | N61: No cleaning
A62: 45792 | B62: 45792 | C62: 0 | E62: 0 | F62: 0 | H62: =IFERROR(VLOOKUP(G62,Basic_Data!$E$2:$I$9,5,0),"") | I62: 0 | J62: 0 | K62: =IFERROR(VLOOKUP($B62-1,Inverter_PR!$B:$I,Module_Cleaning!H62,0),"") | L62: =IFERROR(VLOOKUP($B62+1,Inverter_PR!$B:$I,Module_Cleaning!H62,0),"") | M62: 0 | N62: No cleaning
A63: 45793 | B63: 45793 | C63: 0 | E63: 0 | F63: 0 | H63: =IFERROR(VLOOKUP(G63,Basic_Data!$E$2:$I$9,5,0),"") | I63: 0 | J63: 0 | K63: =IFERROR(VLOOKUP($B63-1,Inverter_PR!$B:$I,Module_Cleaning!H63,0),"") | L63: =IFERROR(VLOOKUP($B63+1,Inverter_PR!$B:$I,Module_Cleaning!H63,0),"") | M63: 0 | N63: No cleaning
A64: 45794 | B64: 45794 | C64: 0 | E64: 0 | F64: 0 | H64: =IFERROR(VLOOKUP(G64,Basic_Data!$E$2:$I$9,5,0),"") | I64: 0 | J64: 0 | K64: =IFERROR(VLOOKUP($B64-1,Inverter_PR!$B:$I,Module_Cleaning!H64,0),"") | L64: =IFERROR(VLOOKUP($B64+1,Inverter_PR!$B:$I,Module_Cleaning!H64,0),"") | M64: 0 | N64: No cleaning
A65: 45795 | B65: 45795 | C65: 0 | E65: 0 | F65: 0 | H65: =IFERROR(VLOOKUP(G65,Basic_Data!$E$2:$I$9,5,0),"") | I65: 0 | J65: 0 | K65: =IFERROR(VLOOKUP($B65-1,Inverter_PR!$B:$I,Module_Cleaning!H65,0),"") | L65: =IFERROR(VLOOKUP($B65+1,Inverter_PR!$B:$I,Module_Cleaning!H65,0),"") | M65: 0 | N65: No cleaning
A66: 45796 | B66: 45796 | C66: 0 | E66: 0 | F66: 0 | H66: =IFERROR(VLOOKUP(G66,Basic_Data!$E$2:$I$9,5,0),"") | I66: 0 | J66: 0 | K66: =IFERROR(VLOOKUP($B66-1,Inverter_PR!$B:$I,Module_Cleaning!H66,0),"") | L66: =IFERROR(VLOOKUP($B66+1,Inverter_PR!$B:$I,Module_Cleaning!H66,0),"") | M66: 0 | N66: No cleaning
A67: 45797 | B67: 45797 | C67: 0 | E67: 0 | F67: 0 | H67: =IFERROR(VLOOKUP(G67,Basic_Data!$E$2:$I$9,5,0),"") | I67: 0 | J67: 0 | K67: =IFERROR(VLOOKUP($B67-1,Inverter_PR!$B:$I,Module_Cleaning!H67,0),"") | L67: =IFERROR(VLOOKUP($B67+1,Inverter_PR!$B:$I,Module_Cleaning!H67,0),"") | M67: 0 | N67: All module cleaned by rain
A68: 45798 | B68: 45798 | C68: 0 | E68: 0 | F68: 0 | H68: =IFERROR(VLOOKUP(G68,Basic_Data!$E$2:$I$9,5,0),"") | I68: 0 | J68: 0 | K68: =IFERROR(VLOOKUP($B68-1,Inverter_PR!$B:$I,Module_Cleaning!H68,0),"") | L68: =IFERROR(VLOOKUP($B68+1,Inverter_PR!$B:$I,Module_Cleaning!H68,0),"") | M68: 0 | N68: No cleaning
A69: 45799 | B69: 45799 | C69: 0 | E69: 0 | F69: 0 | H69: =IFERROR(VLOOKUP(G69,Basic_Data!$E$2:$I$9,5,0),"") | I69: 0 | J69: 0 | K69: =IFERROR(VLOOKUP($B69-1,Inverter_PR!$B:$I,Module_Cleaning!H69,0),"") | L69: =IFERROR(VLOOKUP($B69+1,Inverter_PR!$B:$I,Module_Cleaning!H69,0),"") | M69: 0 | N69: No cleaning
... A76: 45806 | B76: 45806 | C76: 0 | E76: 0 | F76: 0 | H76: =IFERROR(VLOOKUP(G76,Basic_Data!$E$2:$I$9,5,0),"") | I76: 0 | J76: 0 | K76: =IFERROR(VLOOKUP($B76-1,Inverter_PR!$B:$I,Module_Cleaning!H76,0),"") | L76: =IFERROR(VLOOKUP($B76+1,Inverter_PR!$B:$I,Module_Cleaning!H76,0),"") | M76: 0 | N76: No cleaning
A77: 45807 | B77: 45807 | C77: 0 | E77: 0 | F77: 1 | G77: Inv_1 | H77: =IFERROR(VLOOKUP(G77,Basic_Data!$E$2:$I$9,5,0),"") -> 2 | I77: =IFERROR(VLOOKUP($G77,Basic_Data!$E$2:$H$10,4,0),"") -> 616 | J77: 616 | K77: =IFERROR(VLOOKUP($B77-1,Inverter_PR!$B:$I,Module_Cleaning!H77,0),"") -> 0.97362738 | L77: =IFERROR(VLOOKUP($B77+1,Inverter_PR!$B:$I,Module_Cleaning!H77,0),"") -> 0.93979513 | M77: =IFERROR(I77-J77,"") -> 0 | N77: robot cleaning
A78: 45807 | B78: 45807 | C78: 0 | E78: 0 | F78: 1 | G78: Inv_2 | H78: 3 | I78: =IFERROR(VLOOKUP($G78,Basic_Data!$E$2:$H$10,4,0),"") -> 616 | J78: 616 | K78: =IFERROR(VLOOKUP($B78-1,Inverter_PR!$B:$I,Module_Cleaning!H78,0),"") -> 0.96558012 | L78: =IFERROR(VLOOKUP($B78+1,Inverter_PR!$B:$I,Module_Cleaning!H78,0),"") -> 0.93934913 | M78: =IFERROR(I78-J78,"") -> 0 | N78: robot cleaning
A79: 45808 | B79: 45808 | C79: 0 | E79: 0 | F79: 1 | G79: Inv_3 | H79: =IFERROR(VLOOKUP(G79,Basic_Data!$E$2:$I$9,5,0),"") -> 4 | I79: =IFERROR(VLOOKUP($G79,Basic_Data!$E$2:$H$10,4,0),"") -> 616 | J79: 616 | K79: =IFERROR(VLOOKUP($B79-1,Inverter_PR!$B:$I,Module_Cleaning!H79,0),"") -> 0.93623343 | L79: =IFERROR(VLOOKUP($B79+1,Inverter_PR!$B:$I,Module_Cleaning!H79,0),"") -> 0.94648132 | M79: =IFERROR(I79-J79,"") -> 0 | N79: robot cleaning
A80: 45808 | B80: 45808 | F80: 1 | G80: Inv_4 | H80: 5 | I80: =IFERROR(VLOOKUP($G80,Basic_Data!$E$2:$H$10,4,0),"") -> 644 | J80: 644 | K80: =IFERROR(VLOOKUP($B80-1,Inverter_PR!$B:$I,Module_Cleaning!H80,0),"") -> 0.94543664 | L80: =IFERROR(VLOOKUP($B80+1,Inverter_PR!$B:$I,Module_Cleaning!H80,0),"") -> 0.96153668 | M80: =IFERROR(I80-J80,"") -> 0 | N80: robot cleaning
A81: 45809 | B81: 45809 | C81: 0 | F81: 1 | G81: Inv_5 | H81: =IFERROR(VLOOKUP(G81,Basic_Data!$E$2:$I$9,5,0),"") -> 6 | I81: =IFERROR(VLOOKUP($G81,Basic_Data!$E$2:$H$10,4,0),"") -> 644 | J81: 644 | K81: =IFERROR(VLOOKUP($B81-1,Inverter_PR!$B:$I,Module_Cleaning!H81,0),"") -> 0.93325142 | L81: =IFERROR(VLOOKUP($B81+1,Inverter_PR!$B:$I,Module_Cleaning!H81,0),"") -> 0.88858024 | M81: =IFERROR(I81-J81,"") -> 0 | N81: robot cleaning
A82: 45809 | B82: 45809 | C82: 0 | E82: 0 | F82: 1 | G82: Inv_6 | H82: 7 | I82: 644 | J82: 644 | K82: =IFERROR(VLOOKUP($B82-1,Inverter_PR!$B:$I,Module_Cleaning!H82,0),"") -> 0.93577555 | L82: =IFERROR(VLOOKUP($B82+1,Inverter_PR!$B:$I,Module_Cleaning!H82,0),"") -> 0.8906919 | N82: robot cleaning
A83: 45809 | B83: 45809 | C83: 0 | E83: 0 | F83: 1 | G83: Inv_7 | H83: 8 | I83: 644 | J83: 644 | K83: =IFERROR(VLOOKUP($B83-1,Inverter_PR!$B:$I,Module_Cleaning!H83,0),"") -> 0.92822349 | L83: =IFERROR(VLOOKUP($B83+1,Inverter_PR!$B:$I,Module_Cleaning!H83,0),"") -> 0.88136908 | N83: robot cleaning
A84: 45810 | B84: 45810 | C84: 0 | E84: 0 | F84: 0 | H84: =IFERROR(VLOOKUP(G84,Basic_Data!$E$2:$I$9,5,0),"") | I84: 0 | J84: 0 | K84: 0 | L84: 0 | M84: =IFERROR(I84-J84,"") -> 0 | N84: No cleaning
A85: 45811 | B85: 45811 | C85: 0 | E85: 0 | F85: 0 | H85: =IFERROR(VLOOKUP(G85,Basic_Data!$E$2:$I$9,5,0),"") | I85: 0 | J85: 0 | K85: 0 | L85: 0 | M85: =IFERROR(I85-J85,"") -> 0 | N85: No cleaning
A86: 45812 | B86: 45812 | C86: 4 | D86: 4000 | F86: 1 | G86: Inv_1 | H86: =IFERROR(VLOOKUP(G86,Basic_Data!$E$2:$I$9,5,0),"") -> 2 | I86: =IFERROR(VLOOKUP($G86,Basic_Data!$E$2:$H$10,4,0),"") -> 616 | J86: 616 | K86: =IFERROR(VLOOKUP($B86-1,Inverter_PR!$B:$I,Module_Cleaning!H86,0),"") -> 0.89632649 | L86: =IFERROR(VLOOKUP($B86+1,Inverter_PR!$B:$I,Module_Cleaning!H86,0),"") -> 0.98228084 | M86: =IFERROR(I86-J86,"") -> 0 | N86: wet cleaning
A87: 45812 | B87: 45812 | F87: 1 | G87: Inv_2 | H87: 3 | I87: 616 | J87: 616 | K87: =IFERROR(VLOOKUP($B87-1,Inverter_PR!$B:$I,Module_Cleaning!H87,0),"") -> 0.88948593 | L87: =IFERROR(VLOOKUP($B87+1,Inverter_PR!$B:$I,Module_Cleaning!H87,0),"") -> 0.97422059 | M87: 0 | N87: wet cleaning
A88: 45812 | B88: 45812 | F88: 1 | G88: Inv_3 | H88: 4 | I88: 616 | J88: 616 | K88: =IFERROR(VLOOKUP($B88-1,Inverter_PR!$B:$I,Module_Cleaning!H88,0),"") -> 0.8899766 | L88: =IFERROR(VLOOKUP($B88+1,Inverter_PR!$B:$I,Module_Cleaning!H88,0),"") -> 0.96532782 | M88: 0 | N88: wet cleaning
A89: 45812 | B89: 45812 | F89: 1 | G89: Inv_4 | H89: 5 | I89: 616 | J89: 616 | K89: =IFERROR(VLOOKUP($B89-1,Inverter_PR!$B:$I,Module_Cleaning!H89,0),"") -> 0.9045713 | L89: =IFERROR(VLOOKUP($B89+1,Inverter_PR!$B:$I,Module_Cleaning!H89,0),"") -> 0.9605358 | M89: 0 | N89: wet cleaning
A90: 45813 | B90: 45813 | C90: 3 | D90: 3000 | F90: 1 | G90: Inv_5 | H90: =IFERROR(VLOOKUP(G90,Basic_Data!$E$2:$I$9,5,0),"") -> 6 | I90: =IFERROR(VLOOKUP($G90,Basic_Data!$E$2:$H$10,4,0),"") -> 644 | J90: 644 | K90: =IFERROR(VLOOKUP($B90-1,Inverter_PR!$B:$I,Module_Cleaning!H90,0),"") -> 0.88997467 | L90: =IFERROR(VLOOKUP($B90+1,Inverter_PR!$B:$I,Module_Cleaning!H90,0),"") -> 0.92609827 | M90: =IFERROR(I90-J90,"") -> 0 | N90: wet cleaning
A91: 45813 | B91: 45813 | F91: 1 | G91: Inv_6 | H91: 7 | I91: =IFERROR(VLOOKUP($G91,Basic_Data!$E$2:$H$10,4,0),"") -> 644 | J91: 644 | K91: =IFERROR(VLOOKUP($B91-1,Inverter_PR!$B:$I,Module_Cleaning!H91,0),"") -> 0.89413568 | L91: =IFERROR(VLOOKUP($B91+1,Inverter_PR!$B:$I,Module_Cleaning!H91,0),"") -> 0.92499084 | M91: =IFERROR(I91-J91,"") -> 0 | N91: wet cleaning
A92: 45813 | B92: 45813 | F92: 1 | G92: Inv_7 | H92: 8 | I92: =IFERROR(VLOOKUP($G92,Basic_Data!$E$2:$H$10,4,0),"") -> 644 | J92: 644 | K92: =IFERROR(VLOOKUP($B92-1,Inverter_PR!$B:$I,Module_Cleaning!H92,0),"") -> 0.8837434 | L92: =IFERROR(VLOOKUP($B92+1,Inverter_PR!$B:$I,Module_Cleaning!H92,0),"") -> 0.91443125 | M92: =IFERROR(I92-J92,"") -> 0 | N92: wet cleaning
A93: 45814 | B93: 45814 | C93: 0 | D93: 0 | E93: 0 | F93: 0 | H93: =IFERROR(VLOOKUP(G93,Basic_Data!$E$2:$I$9,5,0),"") | I93: 0 | J93: 0 | K93: 0 | L93: 0 | M93: =IFERROR(I93-J93,"") -> 0 | N93: No cleaning
A94: 45815 | B94: 45815 | C94: 0 | D94: 0 | E94: 0 | F94: 0 | H94: =IFERROR(VLOOKUP(G94,Basic_Data!$E$2:$I$9,5,0),"") | I94: 0 | J94: 0 | K94: 0 | L94: 0 | M94: =IFERROR(I94-J94,"") -> 0 | N94: No cleaning
A95: 45816 | B95: 45816 | C95: 0 | D95: 0 | E95: 0 | F95: 0 | H95: =IFERROR(VLOOKUP(G95,Basic_Data!$E$2:$I$9,5,0),"") | I95: 0 | J95: 0 | K95: 0 | L95: 0 | M95: =IFERROR(I95-J95,"") -> 0 | N95: No cleaning
A96: 45817 | B96: 45817 | C96: 0 | D96: 0 | E96: 0 | F96: 2 | G96: Inv_1 | H96: =IFERROR(VLOOKUP(G96,Basic_Data!$E$2:$I$9,5,0),"") -> 2 | I96: =IFERROR(VLOOKUP($G96,Basic_Data!$E$2:$H$10,4,0),"") -> 616 | J96: 616 | K96: =IFERROR(VLOOKUP($B96-1,Inverter_PR!$B:$I,Module_Cleaning!H96,0),"") -> 0.95612686 | L96: 0 | M96: =IFERROR(I96-J96,"") -> 0 | N96: robot cleaning
A97: 45817 | B97: 45817 | C97: 0 | D97: 0 | E97: 0 | F97: 2 | G97: Inv_2 | H97: 3 | I97: =IFERROR(VLOOKUP($G97,Basic_Data!$E$2:$H$10,4,0),"") -> 616 | J97: 616 | K97: =IFERROR(VLOOKUP($B97-1,Inverter_PR!$B:$I,Module_Cleaning!H97,0),"") -> 0.95091147 | L97: 0 | M97: 0 | N97: robot cleaning
A98: 45818 | B98: 45818 | C98: 0 | D98: 0 | E98: 0 | F98: 2 | G98: Inv_3 | H98: =IFERROR(VLOOKUP(G98,Basic_Data!$E$2:$I$9,5,0),"") -> 4 | I98: =IFERROR(VLOOKUP($G98,Basic_Data!$E$2:$H$10,4,0),"") -> 616 | J98: 616 | K98: =IFERROR(VLOOKUP($B98-1,Inverter_PR!$B:$I,Module_Cleaning!H98,0),"") -> 0.94475333 | L98: =IFERROR(VLOOKUP($B98+1,Inverter_PR!$B:$I,Module_Cleaning!H98,0),"") -> 0.95298682 | M98: =IFERROR(I98-J98,"") -> 0 | N98: robot cleaning
A99: 45818 | B99: 45818 | C99: 0 | D99: 0 | E99: 0 | F99: 2 | G99: Inv_4 | H99: 5 | I99: 616 | J99: 616 | K99: =IFERROR(VLOOKUP($B99-1,Inverter_PR!$B:$I,Module_Cleaning!H99,0),"") -> 0.94979887 | L99: =IFERROR(VLOOKUP($B99+1,Inverter_PR!$B:$I,Module_Cleaning!H99,0),"") -> 0.96205261 | M99: 0 | N99: robot cleaning
A100: 45819 | B100: 45819 | C100: 0 | D100: 0 | E100: 0 | F100: 2 | G100: Inv_5 | H100: =IFERROR(VLOOKUP(G100,Basic_Data!$E$2:$I$9,5,0),"") -> 6 | I100: =IFERROR(VLOOKUP($G100,Basic_Data!$E$2:$H$10,4,0),"") -> 644 | J100: 644 | K100: =IFERROR(VLOOKUP($B100-1,Inverter_PR!$B:$I,Module_Cleaning!H100,0),"") -> 0.89579034 | L100: =IFERROR(VLOOKUP($B100+1,Inverter_PR!$B:$I,Module_Cleaning!H100,0),"") -> 0.97478516 | M100: =IFERROR(I100-J100,"") -> 0 | N100: robot cleaning
A101: 45812 | B101: 45819 | C101: 0 | D101: 0 | E101: 0 | F101: 2 | G101: Inv_6 | H101: =IFERROR(VLOOKUP(G101,Basic_Data!$E$2:$I$9,5,0),"") -> 7 | I101: =IFERROR(VLOOKUP($G101,Basic_Data!$E$2:$H$10,4,0),"") -> 644 | J101: 644 | K101: =IFERROR(VLOOKUP($B101-1,Inverter_PR!$B:$I,Module_Cleaning!H101,0),"") -> 0.89868219 | L101: =IFERROR(VLOOKUP($B101+1,Inverter_PR!$B:$I,Module_Cleaning!H101,0),"") -> 0.97674915 | M101: =IFERROR(I101-J101,"") -> 0 | N101: robot cleaning
A102: 45842 | B102: 45819 | C102: 0 | D102: 0 | E102: 0 | F102: 2 | G102: Inv_7 | H102: =IFERROR(VLOOKUP(G102,Basic_Data!$E$2:$I$9,5,0),"") -> 8 | I102: =IFERROR(VLOOKUP($G102,Basic_Data!$E$2:$H$10,4,0),"") -> 644 | J102: 644 | K102: =IFERROR(VLOOKUP($B102-1,Inverter_PR!$B:$I,Module_Cleaning!H102,0),"") -> 0.89990936 | L102: =IFERROR(VLOOKUP($B102+1,Inverter_PR!$B:$I,Module_Cleaning!H102,0),"") -> 0.96941878 | M102: =IFERROR(I102-J102,"") -> 0 | N102: robot cleaning
A103: 45820 | B103: 45820 | C103: 0 | D103: 0 | E103: 0 | F103: 0 | H103: =IFERROR(VLOOKUP(G103,Basic_Data!$E$2:$I$9,5,0),"") | I103: 0 | J103: 0 | K103: =IFERROR(VLOOKUP($B103-1,Inverter_PR!$B:$I,Module_Cleaning!H103,0),"") | L103: =IFERROR(VLOOKUP($B103+1,Inverter_PR!$B:$I,Module_Cleaning!H103,0),"") | M103: =IFERROR(I103-J103,"") -> 0 | N103: No cleaning
A104: 45821 | B104: 45821 | C104: 0 | D104: 0 | E104: 0 | F104: 0 | H104: =IFERROR(VLOOKUP(G104,Basic_Data!$E$2:$I$9,5,0),"") | I104: 0 | J104: 0 | K104: =IFERROR(VLOOKUP($B104-1,Inverter_PR!$B:$I,Module_Cleaning!H104,0),"") | L104: =IFERROR(VLOOKUP($B104+1,Inverter_PR!$B:$I,Module_Cleaning!H104,0),"") | M104: =IFERROR(I104-J104,"") -> 0 | N104: No cleaning
A105: 45822 | B105: 45822 | C105: 0 | D105: 0 | E105: 0 | F105: 0 | H105: =IFERROR(VLOOKUP(G105,Basic_Data!$E$2:$I$9,5,0),"") | I105: 0 | J105: 0 | K105: =IFERROR(VLOOKUP($B105-1,Inverter_PR!$B:$I,Module_Cleaning!H105,0),"") | L105: =IFERROR(VLOOKUP($B105+1,Inverter_PR!$B:$I,Module_Cleaning!H105,0),"") | M105: =IFERROR(I105-J105,"") -> 0 | N105: No cleaning
A106: 45823 | B106: 45823 | C106: 0 | D106: 0 | E106: 0 | F106: 0 | H106: =IFERROR(VLOOKUP(G106,Basic_Data!$E$2:$I$9,5,0),"") | I106: 0 | J106: 0 | K106: =IFERROR(VLOOKUP($B106-1,Inverter_PR!$B:$I,Module_Cleaning!H106,0),"") | L106: =IFERROR(VLOOKUP($B106+1,Inverter_PR!$B:$I,Module_Cleaning!H106,0),"") | M106: =IFERROR(I106-J106,"") -> 0 | N106: All module cleaned by rain
A107: 45824 | B107: 45824 | C107: 0 | D107: 0 | E107: 0 | F107: 0 | H107: =IFERROR(VLOOKUP(G107,Basic_Data!$E$2:$I$9,5,0),"") | I107: 0 | J107: 0 | K107: =IFERROR(VLOOKUP($B107-1,Inverter_PR!$B:$I,Module_Cleaning!H107,0),"") | L107: =IFERROR(VLOOKUP($B107+1,Inverter_PR!$B:$I,Module_Cleaning!H107,0),"") | M107: =IFERROR(I107-J107,"") -> 0 | N107: All module cleaned by rain
...

Sheet Plant  Availiblity
A2: Date | B2: ABT Export Gen | C2: Total inevrter off | D2: GHI | E2: CUF% | F2: Out | G2: In | H2: Total Minute | I2: Outage Hrs. | J2: Plant Capacity | K2: Outage Capacity | L2: Plant Capacity Ratio | M2: Outage Ratio | N2: Plant Availiblity | O2: PA.C CUF | P2: total curtailment | Q2: P.A.C Generation | R2: PA Unit Lose
B3: =Data_Entry!P94 -> 8370 | C3: 0 | D3: =Data_Entry!V94 -> 3.18 | E3: =B3/(24*J3) -> 0.14464952 | F3: 0 | G3: 0 | H3: =(G3-F3)*24*60 -> 0 | I3: =H3/60 -> 0 | J3: 2411 | L3: =J3*12 -> 28932 | M3: =K3*I3 -> 0 | N3: =(L3-M3)/L3 -> 1 | O3: =E3/N3 -> 0.14464952 | Q3: =O3*J3*24 -> 8370 | R3: =Q3-B3 -> 0
A4: 45840 | B4: =Data_Entry!P95 -> 4380 | C4: 0 | D4: =Data_Entry!V95 -> 1.61 | E4: =B4/(24*J4) -> 0.075694732 | F4: 0 | G4: 0 | H4: =(G4-F4)*24*60 -> 0 | I4: =H4/60 -> 0 | J4: 2411 | L4: =J4*12 -> 28932 | M4: =K4*I4 -> 0 | N4: =(L4-M4)/L4 -> 1 | O4: =E4/N4 -> 0.075694732 | Q4: =O4*J4*24 -> 4380 | R4: =Q4-B4 -> 0
A5: 45841 | B5: =Data_Entry!P96 -> 3870 | C5: 0 | D5: =Data_Entry!V96 -> 1.11 | E5: =B5/(24*J5) -> 0.066880962 | F5: 0 | G5: 0 | H5: =(G5-F5)*24*60 -> 0 | I5: =H5/60 -> 0 | J5: 2411 | L5: =J5*12 -> 28932 | M5: =K5*I5 -> 0 | N5: =(L5-M5)/L5 -> 1 | O5: =E5/N5 -> 0.066880962 | Q5: =O5*J5*24 -> 3870 | R5: =Q5-B5 -> 0
A6: 45842 | B6: =Data_Entry!P97 -> 6540 | C6: 0 | D6: =Data_Entry!V97 -> 2.7 | E6: =B6/(24*J6) -> 0.11302364 | F6: 0 | G6: 0 | H6: =(G6-F6)*24*60 -> 0 | I6: =H6/60 -> 0 | J6: 2411 | L6: =J6*12 -> 28932 | M6: =K6*I6 -> 0 | N6: =(L6-M6)/L6 -> 1 | O6: =E6/N6 -> 0.11302364 | Q6: =O6*J6*24 -> 6540 | R6: =Q6-B6 -> -2.0008883e-11
A7: 45843 | B7: =Data_Entry!P98 -> 3990 | C7: 0 | D7: =Data_Entry!V98 -> 1.3 | E7: =B7/(24*J7) -> 0.068954791 | F7: 0 | G7: 0 | H7: =(G7-F7)*24*60 -> 0 | I7: =H7/60 -> 0 | J7: 2411 | L7: =J7*12 -> 28932 | M7: =K7*I7 -> 0 | N7: =(L7-M7)/L7 -> 1 | O7: =E7/N7 -> 0.068954791 | Q7: =O7*J7*24 -> 3990 | R7: =Q7-B7 -> 0
A8: 45844 | B8: =Data_Entry!P99 -> 6240 | C8: 0 | D8: =Data_Entry!V99 -> 2.44 | E8: =B8/(24*J8) -> 0.10783907 | F8: 0 | G8: 0 | H8: =(G8-F8)*24*60 -> 0 | I8: =H8/60 -> 0 | J8: 2411 | L8: =J8*12 -> 28932 | M8: =K8*I8 -> 0 | N8: =(L8-M8)/L8 -> 1 | O8: =E8/N8 -> 0.10783907 | Q8: =O8*J8*24 -> 6240 | R8: =Q8-B8 -> 2.6375346e-11
A9: 45845 | B9: =Data_Entry!P100 -> 4860 | C9: 0 | D9: =Data_Entry!V100 -> 1.82 | E9: =B9/(24*J9) -> 0.083990046 | F9: 0 | G9: 0 | H9: =(G9-F9)*24*60 -> 0 | I9: =H9/60 -> 0 | J9: 2411 | L9: =J9*12 -> 28932 | M9: =K9*I9 -> 0 | N9: =(L9-M9)/L9 -> 1 | O9: =E9/N9 -> 0.083990046 | Q9: =O9*J9*24 -> 4860 | R9: =Q9-B9 -> 0
A10: 45846 | B10: =Data_Entry!P101 -> 7590 | C10: 0 | D10: =Data_Entry!V101 -> 3.16 | E10: =B10/(24*J10) -> 0.13116964 | F10: 0 | G10: 0 | H10: =(G10-F10)*24*60 -> 0 | I10: =H10/60 -> 0 | J10: 2411 | L10: =J10*12 -> 28932 | M10: =K10*I10 -> 0 | N10: =(L10-M10)/L10 -> 1 | O10: =E10/N10 -> 0.13116964 | Q10: =O10*J10*24 -> 7590 | R10: =Q10-B10 -> 1.8189894e-11
A11: 45847 | B11: =Data_Entry!P102 -> 11370 | C11: 0 | D11: =Data_Entry!V102 -> 4.7 | E11: =B11/(24*J11) -> 0.19649523 | F11: 0 | G11: 0 | H11: =(G11-F11)*24*60 -> 0 | I11: =H11/60 -> 0 | J11: 2411 | L11: =J11*12 -> 28932 | M11: =K11*I11 -> 0 | N11: =(L11-M11)/L11 -> 1 | O11: =E11/N11 -> 0.19649523 | Q11: =O11*J11*24 -> 11370 | R11: =Q11-B11 -> -3.4560799e-11
A12: 45848 | B12: =Data_Entry!P103 -> 5790 | C12: 0 | D12: =Data_Entry!V103 -> 2.43 | E12: =B12/(24*J12) -> 0.10006221 | F12: 0 | G12: 0 | H12: =(G12-F12)*24*60 -> 0 | I12: =H12/60 -> 0 | J12: 2411 | L12: =J12*12 -> 28932 | M12: =K12*I12 -> 0 | N12: =(L12-M12)/L12 -> 1 | O12: =E12/N12 -> 0.10006221 | Q12: =O12*J12*24 -> 5790 | R12: =Q12-B12 -> 0
A13: 45849 | B13: =Data_Entry!P104 -> 4770 | C13: 0 | D13: =Data_Entry!V104 -> 1.57 | E13: =B13/(24*J13) -> 0.082434674 | F13: 0 | G13: 0 | H13: =(G13-F13)*24*60 -> 0 | I13: =H13/60 -> 0 | J13: 2411 | L13: =J13*12 -> 28932 | M13: =K13*I13 -> 0 | N13: =(L13-M13)/L13 -> 1 | O13: =E13/N13 -> 0.082434674 | Q13: =O13*J13*24 -> 4770 | R13: =Q13-B13 -> -7.2759576e-12
A14: 45850 | B14: =Data_Entry!P105 -> 6930 | C14: 7 | D14: =Data_Entry!V105 -> 3.25 | E14: =B14/(24*J14) -> 0.11976358 | F14: 0.49305556 | G14: 0.54861111 | H14: =(G14-F14)*24*60 -> 80 | I14: =H14/60 -> 1.3333333 | J14: 2411 | K14: 2411 | L14: =J14*12 -> 28932 | M14: =K14*I14 -> 3214.6667 | N14: =(L14-M14)/L14 -> 0.88888889 | O14: =E14/N14 -> 0.13473403 | Q14: =O14*J14*24 -> 7796.25 | R14: =Q14-B14 -> 866.25
A15: 45851 | B15: =Data_Entry!P106 -> 7950 | C15: 7 | D15: =Data_Entry!V106 -> 3.65 | E15: =B15/(24*J15) -> 0.13739112 | F15: 0.46527778 | G15: 0.61111111 | H15: =(G15-F15)*24*60 -> 210 | I15: =H15/60 -> 3.5 | J15: 2411 | K15: 2411 | L15: =J15*12 -> 28932 | M15: =K15*I15 -> 8438.5 | N15: =(L15-M15)/L15 -> 0.70833333 | O15: =E15/N15 -> 0.19396394 | Q15: =O15*J15*24 -> 11223.529 | R15: =Q15-B15 -> 3273.5294
A16: 45852 | B16: =Data_Entry!P107 -> 10020 | C16: 0 | D16: =Data_Entry!V107 -> 4.46 | E16: =B16/(24*J16) -> 0.17316466 | F16: 0 | G16: 0 | H16: =(G16-F16)*24*60 -> 0 | I16: =H16/60 -> 0 | J16: 2411 | L16: =J16*12 -> 28932 | M16: =K16*I16 -> 0 | N16: =(L16-M16)/L16 -> 1 | O16: =E16/N16 -> 0.17316466 | Q16: =O16*J16*24 -> 10020 | R16: =Q16-B16 -> 3.092282e-11
A17: 45853 | B17: =Data_Entry!P108 -> 10470 | C17: 0 | D17: =Data_Entry!V108 -> 4.22 | E17: =B17/(24*J17) -> 0.18094152 | F17: 0 | G17: 0 | H17: =(G17-F17)*24*60 -> 0 | I17: =H17/60 -> 0 | J17: 2411 | L17: =J17*12 -> 28932 | M17: =K17*I17 -> 0 | N17: =(L17-M17)/L17 -> 1 | O17: =E17/N17 -> 0.18094152 | Q17: =O17*J17*24 -> 10470 | R17: =Q17-B17 -> 5.0931703e-11
A18: 45854 | B18: =Data_Entry!P109 -> 10560 | C18: 0 | D18: =Data_Entry!V109 -> 4.6 | E18: =B18/(24*J18) -> 0.18249689 | F18: 0 | G18: 0 | H18: =(G18-F18)*24*60 -> 0 | I18: =H18/60 -> 0 | J18: 2411 | L18: =J18*12 -> 28932 | M18: =K18*I18 -> 0 | N18: =(L18-M18)/L18 -> 1 | O18: =E18/N18 -> 0.18249689 | Q18: =O18*J18*24 -> 10560 | R18: =Q18-B18 -> 7.0940587e-11
A19: 45855 | B19: =Data_Entry!P110 -> 10020 | C19: 0 | D19: =Data_Entry!V110 -> 4.7 | E19: =B19/(24*J19) -> 0.17316466 | F19: 0 | G19: 0 | H19: =(G19-F19)*24*60 -> 0 | I19: =H19/60 -> 0 | J19: 2411 | L19: =J19*12 -> 28932 | M19: =K19*I19 -> 0 | N19: =(L19-M19)/L19 -> 1 | O19: =E19/N19 -> 0.17316466 | Q19: =O19*J19*24 -> 10020 | R19: =Q19-B19 -> 0
A20: 45856 | B20: =Data_Entry!P111 -> 12510 | C20: 0 | D20: =Data_Entry!V111 -> 5.45 | E20: =B20/(24*J20) -> 0.2161966 | F20: 0 | G20: 0 | H20: =(G20-F20)*24*60 -> 0 | I20: =H20/60 -> 0 | J20: 2411 | L20: =J20*12 -> 28932 | M20: =K20*I20 -> 0 | N20: =(L20-M20)/L20 -> 1 | O20: =E20/N20 -> 0.2161966 | Q20: =O20*J20*24 -> 12510 | R20: =Q20-B20 -> -3.4560799e-11
A21: 45857 | B21: =Data_Entry!P112 -> 8700 | C21: 0 | D21: =Data_Entry!V112 -> 3.48 | E21: =B21/(24*J21) -> 0.15035255 | F21: 0 | G21: 0 | H21: =(G21-F21)*24*60 -> 0 | I21: =H21/60 -> 0 | J21: 2411 | L21: =J21*12 -> 28932 | M21: =K21*I21 -> 0 | N21: =(L21-M21)/L21 -> 1 | O21: =E21/N21 -> 0.15035255 | Q21: =O21*J21*24 -> 8700 | R21: =Q21-B21 -> 1.4551915e-11
A22: 45858 | B22: =Data_Entry!P113 -> 9810 | C22: 0 | D22: =Data_Entry!V113 -> 3.3 | E22: =B22/(24*J22) -> 0.16953546 | F22: 0 | G22: 0 | H22: =(G22-F22)*24*60 -> 0 | I22: =H22/60 -> 0 | J22: 2411 | L22: =J22*12 -> 28932 | M22: =K22*I22 -> 0 | N22: =(L22-M22)/L22 -> 1 | O22: =E22/N22 -> 0.16953546 | Q22: =O22*J22*24 -> 9810 | R22: =Q22-B22 -> 0
A23: 45859 | B23: =Data_Entry!P114 -> 7620 | C23: 0 | D23: =Data_Entry!V114 -> 3.27 | E23: =B23/(24*J23) -> 0.1316881 | F23: 0 | G23: 0 | H23: =(G23-F23)*24*60 -> 0 | I23: =H23/60 -> 0 | J23: 2411 | L23: =J23*12 -> 28932 | M23: =K23*I23 -> 0 | N23: =(L23-M23)/L23 -> 1 | O23: =E23/N23 -> 0.1316881 | Q23: =O23*J23*24 -> 7620 | R23: =Q23-B23 -> 2.4556357e-11
A24: 45860 | B24: =Data_Entry!P115 -> 9270 | C24: 0 | D24: =Data_Entry!V115 -> 4.06 | E24: =B24/(24*J24) -> 0.16020324 | F24: 0 | G24: 0 | H24: =(G24-F24)*24*60 -> 0 | I24: =H24/60 -> 0 | J24: 2411 | L24: =J24*12 -> 28932 | M24: =K24*I24 -> 0 | N24: =(L24-M24)/L24 -> 1 | O24: =E24/N24 -> 0.16020324 | Q24: =O24*J24*24 -> 9270 | R24: =Q24-B24 -> -3.2741809e-11
A25: 45861 | B25: =Data_Entry!P116 -> 6210 | C25: 7 | D25: =Data_Entry!V116 -> 2.6 | E25: =B25/(24*J25) -> 0.10732061 | F25: 0.375 | G25: 0.48263889 | H25: =(G25-F25)*24*60 -> 155 | I25: =H25/60 -> 2.5833333 | J25: 2411 | K25: 2411 | L25: =J25*12 -> 28932 | M25: =K25*I25 -> 6228.4167 | N25: =(L25-M25)/L25 -> 0.78472222 | O25: =E25/N25 -> 0.13676255 | Q25: =O25*J25*24 -> 7913.6283 | R25: =Q25-B25 -> 1703.6283
A26: 45862 | B26: =Data_Entry!P117 -> 4800 | C26: 0 | D26: =Data_Entry!V117 -> 1.81 | E26: =B26/(24*J26) -> 0.082953131 | F26: 0 | G26: 0 | H26: =(G26-F26)*24*60 -> 0 | I26: =H26/60 -> 0 | J26: 2411 | L26: =J26*12 -> 28932 | M26: =K26*I26 -> 0 | N26: =(L26-M26)/L26 -> 1 | O26: =E26/N26 -> 0.082953131 | Q26: =O26*J26*24 -> 4800 | R26: =Q26-B26 -> 0
A27: 45863 | B27: =Data_Entry!P118 -> 8040 | C27: 0 | D27: =Data_Entry!V118 -> 2.8 | E27: =B27/(24*J27) -> 0.1389465 | F27: 0 | G27: 0 | H27: =(G27-F27)*24*60 -> 0 | I27: =H27/60 -> 0 | J27: 2411 | L27: =J27*12 -> 28932 | M27: =K27*I27 -> 0 | N27: =(L27-M27)/L27 -> 1 | O27: =E27/N27 -> 0.1389465 | Q27: =O27*J27*24 -> 8040 | R27: =Q27-B27 -> -1.2732926e-11
A28: 45864 | B28: =Data_Entry!P119 -> 4560 | C28: 0 | D28: =Data_Entry!V119 -> 1.61 | E28: =B28/(24*J28) -> 0.078805475 | F28: 0 | G28: 0 | H28: =(G28-F28)*24*60 -> 0 | I28: =H28/60 -> 0 | J28: 2411 | L28: =J28*12 -> 28932 | M28: =K28*I28 -> 0 | N28: =(L28-M28)/L28 -> 1 | O28: =E28/N28 -> 0.078805475 | Q28: =O28*J28*24 -> 4560 | R28: =Q28-B28 -> 0
A29: 45865 | B29: =Data_Entry!P120 -> 4020 | C29: 0 | D29: =Data_Entry!V120 -> 1.55 | E29: =B29/(24*J29) -> 0.069473248 | F29: 0 | G29: 0 | H29: =(G29-F29)*24*60 -> 0 | I29: =H29/60 -> 0 | J29: 2411 | L29: =J29*12 -> 28932 | M29: =K29*I29 -> 0 | N29: =(L29-M29)/L29 -> 1 | O29: =E29/N29 -> 0.069473248 | Q29: =O29*J29*24 -> 4020 | R29: =Q29-B29 -> -5.9117156e-12
A30: 45866 | B30: =Data_Entry!P121 -> 5850 | C30: 0 | D30: =Data_Entry!V121 -> 2.32 | E30: =B30/(24*J30) -> 0.10109913 | F30: 0 | G30: 0 | H30: =(G30-F30)*24*60 -> 0 | I30: =H30/60 -> 0 | J30: 2411 | L30: =J30*12 -> 28932 | M30: =K30*I30 -> 0 | N30: =(L30-M30)/L30 -> 1 | O30: =E30/N30 -> 0.10109913 | Q30: =O30*J30*24 -> 5850 | R30: =Q30-B30 -> 0
A31: 45867 | B31: =Data_Entry!P122 -> 5370 | C31: 0 | D31: =Data_Entry!V122 -> 2.13 | E31: =B31/(24*J31) -> 0.092803816 | F31: 0 | G31: 0 | H31: =(G31-F31)*24*60 -> 0 | I31: =H31/60 -> 0 | J31: 2411 | L31: =J31*12 -> 28932 | M31: =K31*I31 -> 0 | N31: =(L31-M31)/L31 -> 1 | O31: =E31/N31 -> 0.092803816 | Q31: =O31*J31*24 -> 5370 | R31: =Q31-B31 -> 0
A32: 45868 | B32: =Data_Entry!P123 -> 8490 | C32: 0 | D32: =Data_Entry!V123 -> 3.62 | E32: =B32/(24*J32) -> 0.14672335 | F32: 0 | G32: 0 | H32: =(G32-F32)*24*60 -> 0 | I32: =H32/60 -> 0 | J32: 2411 | L32: =J32*12 -> 28932 | M32: =K32*I32 -> 0 | N32: =(L32-M32)/L32 -> 1 | O32: =E32/N32 -> 0.14672335 | Q32: =O32*J32*24 -> 8490 | R32: =Q32-B32 -> 0
A33: 45869 | B33: =Data_Entry!P124 -> 5880 | C33: 0 | D33: =Data_Entry!V124 -> 2.47 | E33: =B33/(24*J33) -> 0.10161759 | F33: 0 | G33: 0 | H33: =(G33-F33)*24*60 -> 0 | I33: =H33/60 -> 0 | J33: 2411 | L33: =J33*12 -> 28932 | M33: =K33*I33 -> 0 | N33: =(L33-M33)/L33 -> 1 | O33: =E33/N33 -> 0.10161759 | Q33: =O33*J33*24 -> 5880 | R33: =Q33-B33 -> 1.0913936e-11
A35: 45870 | B35: =Data_Entry!P125 -> 7320 | C35: 0 | D35: =Data_Entry!V125 -> 3.14 | E35: =B35/(24*J35) -> 0.12650353 | F35: 0 | G35: 0 | H35: =(G35-F35)*24*60 -> 0 | I35: =H35/60 -> 0 | J35: 2411 | L35: =J35*12 -> 28932 | M35: =K35*I35 -> 0 | N35: =(L35-M35)/L35 -> 1 | O35: =E35/N35 -> 0.12650353 | Q35: =O35*J35*24 -> 7320 | R35: =Q35-B35 -> 1.0913936e-11
A36: 45871 | B36: =Data_Entry!P126 -> 7290 | C36: 0 | D36: =Data_Entry!V126 -> 2.91 | E36: =B36/(24*J36) -> 0.12598507 | F36: 0 | G36: 0 | H36: =(G36-F36)*24*60 -> 0 | I36: =H36/60 -> 0 | J36: 2411 | L36: =J36*12 -> 28932 | M36: =K36*I36 -> 0 | N36: =(L36-M36)/L36 -> 1 | O36: =E36/N36 -> 0.12598507 | Q36: =O36*J36*24 -> 7290 | R36: =Q36-B36 -> 1.4551915e-11
A37: 45872 | B37: =Data_Entry!P127 -> 6870 | C37: 0 | D37: =Data_Entry!V127 -> 2.78 | E37: =B37/(24*J37) -> 0.11872667 | F37: 0 | G37: 0 | H37: =(G37-F37)*24*60 -> 0 | I37: =H37/60 -> 0 | J37: 2411 | L37: =J37*12 -> 28932 | M37: =K37*I37 -> 0 | N37: =(L37-M37)/L37 -> 1 | O37: =E37/N37 -> 0.11872667 | Q37: =O37*J37*24 -> 6870 | R37: =Q37-B37 -> -8.1854523e-12
A38: 45873 | B38: =Data_Entry!P128 -> 6900 | C38: 0 | D38: =Data_Entry!V128 -> 2.5 | E38: =B38/(24*J38) -> 0.11924513 | F38: 0 | G38: 0 | H38: =(G38-F38)*24*60 -> 0 | I38: =H38/60 -> 0 | J38: 2411 | L38: =J38*12 -> 28932 | M38: =K38*I38 -> 0 | N38: =(L38-M38)/L38 -> 1 | O38: =E38/N38 -> 0.11924513 | Q38: =O38*J38*24 -> 6900 | R38: =Q38-B38 -> 0
A39: 45874 | B39: =Data_Entry!P129 -> 6690 | C39: 7 | D39: =Data_Entry!V129 -> 2.64 | E39: =B39/(24*J39) -> 0.11561593 | F39: 0.4375 | G39: 0.52083333 | H39: =(G39-F39)*24*60 -> 120 | I39: =H39/60 -> 2 | J39: 2411 | K39: 2411 | L39: =J39*12 -> 28932 | M39: =K39*I39 -> 4822 | N39: =(L39-M39)/L39 -> 0.83333333 | O39: =E39/N39 -> 0.13873911 | Q39: =O39*J39*24 -> 8028 | R39: =Q39-B39 -> 1338
A40: 45875 | B40: =Data_Entry!P130 -> 10530 | C40: 0 | D40: =Data_Entry!V130 -> 4.15 | E40: =B40/(24*J40) -> 0.18197843 | F40: 0 | G40: 0 | H40: =(G40-F40)*24*60 -> 0 | I40: =H40/60 -> 0 | J40: 2411 | L40: =J40*12 -> 28932 | M40: =K40*I40 -> 0 | N40: =(L40-M40)/L40 -> 1 | O40: =E40/N40 -> 0.18197843 | Q40: =O40*J40*24 -> 10530 | R40: =Q40-B40 -> 0
A41: 45876 | B41: =Data_Entry!P131 -> 11430 | C41: 0 | D41: =Data_Entry!V131 -> 4.81 | E41: =B41/(24*J41) -> 0.19753214 | F41: 0 | G41: 0 | H41: =(G41-F41)*24*60 -> 0 | I41: =H41/60 -> 0 | J41: 2411 | L41: =J41*12 -> 28932 | M41: =K41*I41 -> 0 | N41: =(L41-M41)/L41 -> 1 | O41: =E41/N41 -> 0.19753214 | Q41: =O41*J41*24 -> 11430 | R41: =Q41-B41 -> 4.0017767e-11
A42: 45877 | B42: =Data_Entry!P132 -> 11850 | C42: 0 | D42: =Data_Entry!V132 -> 4.76 | E42: =B42/(24*J42) -> 0.20479054 | F42: 0 | G42: 0 | H42: =(G42-F42)*24*60 -> 0 | I42: =H42/60 -> 0 | J42: 2411 | L42: =J42*12 -> 28932 | M42: =K42*I42 -> 0 | N42: =(L42-M42)/L42 -> 1 | O42: =E42/N42 -> 0.20479054 | Q42: =O42*J42*24 -> 11850 | R42: =Q42-B42 -> 6.184564e-11
A43: 45878 | B43: =Data_Entry!P133 -> 7170 | C43: 0 | D43: =Data_Entry!V133 -> 3.13 | E43: =B43/(24*J43) -> 0.12391124 | F43: 0 | G43: 0 | H43: =(G43-F43)*24*60 -> 0 | I43: =H43/60 -> 0 | J43: 2411 | L43: =J43*12 -> 28932 | M43: =K43*I43 -> 0 | N43: =(L43-M43)/L43 -> 1 | O43: =E43/N43 -> 0.12391124 | Q43: =O43*J43*24 -> 7170 | R43: =Q43-B43 -> 0
A44: 45879 | B44: =Data_Entry!P134 -> 9240 | C44: 0 | D44: =Data_Entry!V134 -> 3.55 | E44: =B44/(24*J44) -> 0.15968478 | F44: 0 | G44: 0 | H44: =(G44-F44)*24*60 -> 0 | I44: =H44/60 -> 0 | J44: 2411 | L44: =J44*12 -> 28932 | M44: =K44*I44 -> 0 | N44: =(L44-M44)/L44 -> 1 | O44: =E44/N44 -> 0.15968478 | Q44: =O44*J44*24 -> 9240 | R44: =Q44-B44 -> 2.910383e-11
A45: 45880 | B45: =Data_Entry!P135 -> 6060 | C45: 0 | D45: =Data_Entry!V135 -> 3.28 | E45: =B45/(24*J45) -> 0.10472833 | F45: 0 | G45: 0 | H45: 150 | I45: =H45/60 -> 2.5 | J45: 2411 | K45: 2411 | L45: =J45*12 -> 28932 | M45: =K45*I45 -> 6027.5 | N45: =(L45-M45)/L45 -> 0.79166667 | O45: =E45/N45 -> 0.13228841 | P45: 30% curtailment | Q45: =O45*J45*24 -> 7654.7368 | R45: =Q45-B45 -> 1594.7368
A46: 45881 | B46: =Data_Entry!P136 -> 8100 | C46: 0 | D46: =Data_Entry!V136 -> 2.98 | E46: =B46/(24*J46) -> 0.13998341 | F46: 0 | G46: 0 | H46: =(G46-F46)*24*60 -> 0 | I46: =H46/60 -> 0 | J46: 2411 | L46: =J46*12 -> 28932 | M46: =K46*I46 -> 0 | N46: =(L46-M46)/L46 -> 1 | O46: =E46/N46 -> 0.13998341 | Q46: =O46*J46*24 -> 8100 | R46: =Q46-B46 -> -2.3646862e-11
A47: 45882 | B47: =Data_Entry!P137 -> 7680 | C47: 7 | D47: =Data_Entry!V137 -> 3.15 | E47: =B47/(24*J47) -> 0.13272501 | F47: 0.3125 | G47: 0.33333333 | H47: =(G47-F47)*24*60 -> 30 | I47: =H47/60 -> 0.5 | J47: 2411 | K47: 2411 | L47: =J47*12 -> 28932 | M47: =K47*I47 -> 1205.5 | N47: =(L47-M47)/L47 -> 0.95833333 | O47: =E47/N47 -> 0.13849566 | Q47: =O47*J47*24 -> 8013.913 | R47: =Q47-B47 -> 333.91304
A48: 45883 | B48: =Data_Entry!P138 -> 7320 | C48: 0 | D48: =Data_Entry!V138 -> 3.1 | E48: =B48/(24*J48) -> 0.12650353 | F48: 0 | G48: 0 | H48: =(G48-F48)*24*60 -> 0 | I48: =H48/60 -> 0 | J48: 2411 | L48: =J48*12 -> 28932 | M48: =K48*I48 -> 0 | N48: =(L48-M48)/L48 -> 1 | O48: =E48/N48 -> 0.12650353 | Q48: =O48*J48*24 -> 7320 | R48: =Q48-B48 -> 1.0913936e-11
A49: 45884 | B49: =Data_Entry!P139 -> 7380 | C49: 0 | D49: =Data_Entry!V139 -> 2.96 | E49: =B49/(24*J49) -> 0.12754044 | F49: 0 | G49: 0 | H49: =(G49-F49)*24*60 -> 0 | I49: =H49/60 -> 0 | J49: 2411 | L49: =J49*12 -> 28932 | M49: =K49*I49 -> 0 | N49: =(L49-M49)/L49 -> 1 | O49: =E49/N49 -> 0.12754044 | Q49: =O49*J49*24 -> 7380 | R49: =Q49-B49 -> 1.3642421e-11
A50: 45885 | B50: =Data_Entry!P140 -> 7440 | C50: 0 | D50: =Data_Entry!V140 -> 3.06 | E50: =B50/(24*J50) -> 0.12857735 | F50: 0 | G50: 0 | H50: =(G50-F50)*24*60 -> 0 | I50: =H50/60 -> 0 | J50: 2411 | L50: =J50*12 -> 28932 | M50: =K50*I50 -> 0 | N50: =(L50-M50)/L50 -> 1 | O50: =E50/N50 -> 0.12857735 | Q50: =O50*J50*24 -> 7440 | R50: =Q50-B50 -> 2.2737368e-11
A51: 45886 | B51: =Data_Entry!P141 -> 8490 | C51: 0 | D51: =Data_Entry!V141 -> 2.93 | E51: =B51/(24*J51) -> 0.14672335 | F51: 0 | G51: 0 | H51: =(G51-F51)*24*60 -> 0 | I51: =H51/60 -> 0 | J51: 2411 | L51: =J51*12 -> 28932 | M51: =K51*I51 -> 0 | N51: =(L51-M51)/L51 -> 1 | O51: =E51/N51 -> 0.14672335 | Q51: =O51*J51*24 -> 8490 | R51: =Q51-B51 -> 0
A52: 45887 | B52: =Data_Entry!P142 -> 8100 | C52: 0 | D52: =Data_Entry!V142 -> 2.69 | E52: =B52/(24*J52) -> 0.13998341 | F52: 0 | G52: 0 | H52: =(G52-F52)*24*60 -> 0 | I52: =H52/60 -> 0 | J52: 2411 | L52: =J52*12 -> 28932 | M52: =K52*I52 -> 0 | N52: =(L52-M52)/L52 -> 1 | O52: =E52/N52 -> 0.13998341 | Q52: =O52*J52*24 -> 8100 | R52: =Q52-B52 -> -1.6370905e-11
A53: 45888 | B53: =Data_Entry!P143 -> 9900 | C53: 0 | D53: =Data_Entry!V143 -> 0 | E53: =B53/(24*J53) -> 0.17109083 | F53: 0 | G53: 0 | H53: =(G53-F53)*24*60 -> 0 | I53: =H53/60 -> 0 | J53: 2411 | L53: =J53*12 -> 28932 | M53: =K53*I53 -> 0 | N53: =(L53-M53)/L53 -> 1 | O53: =E53/N53 -> 0.17109083 | Q53: =O53*J53*24 -> 9900 | R53: =Q53-B53 -> 0
A54: 45889 | B54: =Data_Entry!P144 -> 2910 | C54: 0 | D54: =Data_Entry!V144 -> 0 | E54: =B54/(24*J54) -> 0.050290336 | F54: 0 | G54: 0 | H54: =(G54-F54)*24*60 -> 0 | I54: =H54/60 -> 0 | J54: 2411 | L54: =J54*12 -> 28932 | M54: =K54*I54 -> 0 | N54: =(L54-M54)/L54 -> 1 | O54: =E54/N54 -> 0.050290336 | Q54: =O54*J54*24 -> 2910 | R54: =Q54-B54 -> 0
A55: 45890 | B55: =Data_Entry!P145 -> 8130 | C55: 0 | D55: =Data_Entry!V145 -> 0 | E55: =B55/(24*J55) -> 0.14050187 | F55: 0 | G55: 0 | H55: =(G55-F55)*24*60 -> 0 | I55: =H55/60 -> 0 | J55: 2411 | L55: =J55*12 -> 28932 | M55: =K55*I55 -> 0 | N55: =(L55-M55)/L55 -> 1 | O55: =E55/N55 -> 0.14050187 | Q55: =O55*J55*24 -> 8130 | R55: =Q55-B55 -> -1.1823431e-11
A56: 45891 | B56: =Data_Entry!P146 -> 9630 | C56: 0 | D56: =Data_Entry!V146 -> 0 | E56: =B56/(24*J56) -> 0.16642472 | F56: 0 | G56: 0 | H56: =(G56-F56)*24*60 -> 0 | I56: =H56/60 -> 0 | J56: 2411 | L56: =J56*12 -> 28932 | M56: =K56*I56 -> 0 | N56: =(L56-M56)/L56 -> 1 | O56: =E56/N56 -> 0.16642472 | Q56: =O56*J56*24 -> 9630 | R56: =Q56-B56 -> -1.8189894e-11
A57: 45892 | B57: =Data_Entry!P147 -> 5340 | C57: 0 | D57: =Data_Entry!V147 -> 0 | E57: =B57/(24*J57) -> 0.092285359 | F57: 0 | G57: 0 | H57: =(G57-F57)*24*60 -> 0 | I57: =H57/60 -> 0 | J57: 2411 | L57: =J57*12 -> 28932 | M57: =K57*I57 -> 0 | N57: =(L57-M57)/L57 -> 1 | O57: =E57/N57 -> 0.092285359 | Q57: =O57*J57*24 -> 5340 | R57: =Q57-B57 -> 0
A58: 45893 | B58: =Data_Entry!P148 -> 3720 | C58: 0 | D58: =Data_Entry!V148 -> 0 | E58: =B58/(24*J58) -> 0.064288677 | F58: 0 | G58: 0 | H58: =(G58-F58)*24*60 -> 0 | I58: =H58/60 -> 0 | J58: 2411 | L58: =J58*12 -> 28932 | M58: =K58*I58 -> 0 | N58: =(L58-M58)/L58 -> 1 | O58: =E58/N58 -> 0.064288677 | Q58: =O58*J58*24 -> 3720 | R58: =Q58-B58 -> 0
A59: 45894 | B59: =Data_Entry!P149 -> 6600 | C59: 0 | D59: =Data_Entry!V149 -> 0 | E59: =B59/(24*J59) -> 0.11406056 | F59: 0 | G59: 0 | H59: =(G59-F59)*24*60 -> 0 | I59: =H59/60 -> 0 | J59: 2411 | L59: =J59*12 -> 28932 | M59: =K59*I59 -> 0 | N59: =(L59-M59)/L59 -> 1 | O59: =E59/N59 -> 0.11406056 | Q59: =O59*J59*24 -> 6600 | R59: =Q59-B59 -> -2.6375346e-11
... A65: 45900 | B65: =Data_Entry!P155 -> 8460 | C65: 0 | D65: =Data_Entry!V155 -> 0 | E65: =B65/(24*J65) -> 0.14620489 | F65: 0 | G65: 0 | H65: =(G65-F65)*24*60 -> 0 | I65: =H65/60 -> 0 | J65: 2411 | L65: =J65*12 -> 28932 | M65: =K65*I65 -> 0 | N65: =(L65-M65)/L65 -> 1 | O65: =E65/N65 -> 0.14620489 | Q65: =O65*J65*24 -> 8460 | R65: =Q65-B65 -> 0
N66: =AVERAGE(N35:N65) -> 0.98655914
A67: 45901 | B67: =Data_Entry!P156 -> 8310 | C67: 0 | D67: =Data_Entry!V156 -> 0 | E67: =B67/(24*J67) -> 0.14361261 | F67: 0 | G67: 0 | H67: =(G67-F67)*24*60 -> 0 | I67: =H67/60 -> 0 | J67: 2411 | L67: =J67*12 -> 28932 | M67: =K67*I67 -> 0 | N67: =(L67-M67)/L67 -> 1 | O67: =E67/N67 -> 0.14361261 | Q67: =O67*J67*24 -> 8310 | R67: =Q67-B67 -> 0
A68: 45902 | B68: =Data_Entry!P157 -> 11250 | C68: 0 | D68: =Data_Entry!V157 -> 0 | E68: =B68/(24*J68) -> 0.1944214 | F68: 0 | G68: 0 | H68: =(G68-F68)*24*60 -> 0 | I68: =H68/60 -> 0 | J68: 2411 | L68: =J68*12 -> 28932 | M68: =K68*I68 -> 0 | N68: =(L68-M68)/L68 -> 1 | O68: =E68/N68 -> 0.1944214 | Q68: =O68*J68*24 -> 11250 | R68: =Q68-B68 -> 0
A69: 45903 | B69: =Data_Entry!P158 -> 11670 | C69: 0 | D69: =Data_Entry!V158 -> 0 | E69: =B69/(24*J69) -> 0.2016798 | F69: 0 | G69: 0 | H69: =(G69-F69)*24*60 -> 0 | I69: =H69/60 -> 0 | J69: 2411 | L69: =J69*12 -> 28932 | M69: =K69*I69 -> 0 | N69: =(L69-M69)/L69 -> 1 | O69: =E69/N69 -> 0.2016798 | Q69: =O69*J69*24 -> 11670 | R69: =Q69-B69 -> -2.5465852e-11
A70: 45904 | B70: =Data_Entry!P159 -> 5520 | C70: 0 | D70: =Data_Entry!V159 -> 0 | E70: =B70/(24*J70) -> 0.095396101 | F70: 0 | G70: 0 | H70: =(G70-F70)*24*60 -> 0 | I70: =H70/60 -> 0 | J70: 2411 | L70: =J70*12 -> 28932 | M70: =K70*I70 -> 0 | N70: =(L70-M70)/L70 -> 1 | O70: =E70/N70 -> 0.095396101 | Q70: =O70*J70*24 -> 5520 | R70: =Q70-B70 -> 7.2759576e-12
A71: 45905 | B71: =Data_Entry!P160 -> 4890 | C71: 0 | D71: =Data_Entry!V160 -> 0 | E71: =B71/(24*J71) -> 0.084508503 | F71: 0 | G71: 0 | H71: =(G71-F71)*24*60 -> 0 | I71: =H71/60 -> 0 | J71: 2411 | L71: =J71*12 -> 28932 | M71: =K71*I71 -> 0 | N71: =(L71-M71)/L71 -> 1 | O71: =E71/N71 -> 0.084508503 | Q71: =O71*J71*24 -> 4890 | R71: =Q71-B71 -> 0
A72: 45906 | B72: =Data_Entry!P161 -> 3660 | C72: 0 | D72: =Data_Entry!V161 -> 0 | E72: =B72/(24*J72) -> 0.063251763 | F72: 0 | G72: 0 | H72: =(G72-F72)*24*60 -> 0 | I72: =H72/60 -> 0 | J72: 2411 | L72: =J72*12 -> 28932 | M72: =K72*I72 -> 0 | N72: =(L72-M72)/L72 -> 1 | O72: =E72/N72 -> 0.063251763 | Q72: =O72*J72*24 -> 3660 | R72: =Q72-B72 -> 0
A73: 45907 | B73: =Data_Entry!P162 -> 3450 | C73: 0 | D73: =Data_Entry!V162 -> 0 | E73: =B73/(24*J73) -> 0.059622563 | F73: 0 | G73: 0 | H73: =(G73-F73)*24*60 -> 0 | I73: =H73/60 -> 0 | J73: 2411 | L73: =J73*12 -> 28932 | M73: =K73*I73 -> 0 | N73: =(L73-M73)/L73 -> 1 | O73: =E73/N73 -> 0.059622563 | Q73: =O73*J73*24 -> 3450 | R73: =Q73-B73 -> 0
A74: 45908 | B74: =Data_Entry!P163 -> 3960 | C74: 0 | D74: =Data_Entry!V163 -> 0 | E74: =B74/(24*J74) -> 0.068436333 | F74: 0 | G74: 0 | H74: =(G74-F74)*24*60 -> 0 | I74: =H74/60 -> 0 | J74: 2411 | L74: =J74*12 -> 28932 | M74: =K74*I74 -> 0 | N74: =(L74-M74)/L74 -> 1 | O74: =E74/N74 -> 0.068436333 | Q74: =O74*J74*24 -> 3960 | R74: =Q74-B74 -> 0
A75: 45909 | B75: =Data_Entry!P164 -> 10140 | C75: 0 | D75: =Data_Entry!V164 -> 0 | E75: =B75/(24*J75) -> 0.17523849 | F75: 0 | G75: 0 | H75: =(G75-F75)*24*60 -> 0 | I75: =H75/60 -> 0 | J75: 2411 | L75: =J75*12 -> 28932 | M75: =K75*I75 -> 0 | N75: =(L75-M75)/L75 -> 1 | O75: =E75/N75 -> 0.17523849 | Q75: =O75*J75*24 -> 10140 | R75: =Q75-B75 -> 0
A76: 45910 | B76: =Data_Entry!P165 -> 11760 | C76: 0 | D76: =Data_Entry!V165 -> 0 | E76: =B76/(24*J76) -> 0.20323517 | F76: 0 | G76: 0 | H76: =(G76-F76)*24*60 -> 0 | I76: =H76/60 -> 0 | J76: 2411 | L76: =J76*12 -> 28932 | M76: =K76*I76 -> 0 | N76: =(L76-M76)/L76 -> 1 | O76: =E76/N76 -> 0.20323517 | Q76: =O76*J76*24 -> 11760 | R76: =Q76-B76 -> 0
A77: 45911 | B77: =Data_Entry!P166 -> 12690 | C77: 0 | D77: =Data_Entry!V166 -> 0 | E77: =B77/(24*J77) -> 0.21930734 | F77: 0 | G77: 0 | H77: =(G77-F77)*24*60 -> 0 | I77: =H77/60 -> 0 | J77: 2411 | L77: =J77*12 -> 28932 | M77: =K77*I77 -> 0 | N77: =(L77-M77)/L77 -> 1 | O77: =E77/N77 -> 0.21930734 | Q77: =O77*J77*24 -> 12690 | R77: =Q77-B77 -> -4.5474735e-11
A78: 45912 | B78: =Data_Entry!P167 -> 13410 | C78: 0 | D78: =Data_Entry!V167 -> 0 | E78: =B78/(24*J78) -> 0.23175031 | F78: 0 | G78: 0 | H78: =(G78-F78)*24*60 -> 0 | I78: =H78/60 -> 0 | J78: 2411 | L78: =J78*12 -> 28932 | M78: =K78*I78 -> 0 | N78: =(L78-M78)/L78 -> 1 | O78: =E78/N78 -> 0.23175031 | Q78: =O78*J78*24 -> 13410 | R78: =Q78-B78 -> -4.5474735e-11
... A82: 45916 | B82: =Data_Entry!P171 -> 12360 | C82: 0 | D82: =Data_Entry!V171 -> 0 | E82: =B82/(24*J82) -> 0.21360431 | F82: 0 | G82: 0 | H82: =(G82-F82)*24*60 -> 0 | I82: =H82/60 -> 0 | J82: 2411 | L82: =J82*12 -> 28932 | M82: =K82*I82 -> 0 | N82: =(L82-M82)/L82 -> 1 | O82: =E82/N82 -> 0.21360431 | Q82: =O82*J82*24 -> 12360 | R82: =Q82-B82 -> 0
A83: 45917 | B83: =Data_Entry!P172 -> 6330 | C83: 7 | D83: =Data_Entry!V172 -> 0 | E83: =B83/(24*J83) -> 0.10939444 | F83: 0.3125 | G83: 0.5 | H83: =(G83-F83)*24*60 -> 270 | I83: =H83/60 -> 4.5 | J83: 2411 | K83: 2411 | L83: =J83*12 -> 28932 | M83: =K83*I83 -> 10849.5 | N83: =(L83-M83)/L83 -> 0.625 | O83: =E83/N83 -> 0.17503111 | Q83: =O83*J83*24 -> 10128 | R83: =Q83-B83 -> 3798
A84: 45918 | B84: =Data_Entry!P173 -> 13170 | C84: 0 | D84: =Data_Entry!V173 -> 0 | E84: =B84/(24*J84) -> 0.22760265 | F84: 0 | G84: 0 | H84: =(G84-F84)*24*60 -> 0 | I84: =H84/60 -> 0 | J84: 2411 | L84: =J84*12 -> 28932 | M84: =K84*I84 -> 0 | N84: =(L84-M84)/L84 -> 1 | O84: =E84/N84 -> 0.22760265 | Q84: =O84*J84*24 -> 13170 | R84: =Q84-B84 -> -2.1827873e-11
A85: 45919 | B85: =Data_Entry!P174 -> 12060 | C85: 0 | D85: =Data_Entry!V174 -> 0 | E85: =B85/(24*J85) -> 0.20841974 | F85: 0 | G85: 0 | H85: =(G85-F85)*24*60 -> 0 | I85: =H85/60 -> 0 | J85: 2411 | L85: =J85*12 -> 28932 | M85: =K85*I85 -> 0 | N85: =(L85-M85)/L85 -> 1 | O85: =E85/N85 -> 0.20841974 | Q85: =O85*J85*24 -> 12060 | R85: =Q85-B85 -> 1.8189894e-11
A86: 45920 | B86: =Data_Entry!P175 -> 6390 | C86: 0 | D86: =Data_Entry!V175 -> 0 | E86: =B86/(24*J86) -> 0.11043136 | F86: 0 | G86: 0 | H86: =(G86-F86)*24*60 -> 0 | I86: =H86/60 -> 0 | J86: 2411 | L86: =J86*12 -> 28932 | M86: =K86*I86 -> 0 | N86: =(L86-M86)/L86 -> 1 | O86: =E86/N86 -> 0.11043136 | Q86: =O86*J86*24 -> 6390 | R86: =Q86-B86 -> -3.092282e-11
A87: 45921 | B87: =Data_Entry!P176 -> 9930 | C87: 0 | D87: =Data_Entry!V176 -> 2.9 | E87: =B87/(24*J87) -> 0.17160929 | F87: 0 | G87: 0 | H87: =(G87-F87)*24*60 -> 0 | I87: =H87/60 -> 0 | J87: 2411 | L87: =J87*12 -> 28932 | M87: =K87*I87 -> 0 | N87: =(L87-M87)/L87 -> 1 | O87: =E87/N87 -> 0.17160929 | Q87: =O87*J87*24 -> 9930 | R87: =Q87-B87 -> 0
A88: 45922 | B88: =Data_Entry!P177 -> 8820 | C88: 0 | D88: =Data_Entry!V177 -> 3.72 | E88: =B88/(24*J88) -> 0.15242638 | F88: 0 | G88: 0 | H88: =(G88-F88)*24*60 -> 0 | I88: =H88/60 -> 0 | J88: 2411 | L88: =J88*12 -> 28932 | M88: =K88*I88 -> 0 | N88: =(L88-M88)/L88 -> 1 | O88: =E88/N88 -> 0.15242638 | Q88: =O88*J88*24 -> 8820 | R88: =Q88-B88 -> 0
A89: 45923 | B89: =Data_Entry!P178 -> 13920 | C89: 0 | D89: =Data_Entry!V178 -> 3.28 | E89: =B89/(24*J89) -> 0.24056408 | F89: 0 | G89: 0 | H89: =(G89-F89)*24*60 -> 0 | I89: =H89/60 -> 0 | J89: 2411 | L89: =J89*12 -> 28932 | M89: =K89*I89 -> 0 | N89: =(L89-M89)/L89 -> 1 | O89: =E89/N89 -> 0.24056408 | Q89: =O89*J89*24 -> 13920 | R89: =Q89-B89 -> -4.9112714e-11
A90: 45924 | B90: =Data_Entry!P179 -> 11670 | C90: 0 | D90: =Data_Entry!V179 -> 2.92 | E90: =B90/(24*J90) -> 0.2016798 | F90: 0 | G90: 0 | H90: =(G90-F90)*24*60 -> 0 | I90: =H90/60 -> 0 | J90: 2411 | L90: =J90*12 -> 28932 | M90: =K90*I90 -> 0 | N90: =(L90-M90)/L90 -> 1 | O90: =E90/N90 -> 0.2016798 | Q90: =O90*J90*24 -> 11670 | R90: =Q90-B90 -> -2.5465852e-11
A91: 45925 | B91: =Data_Entry!P180 -> 11280 | C91: 0 | D91: =Data_Entry!V180 -> 2.45 | E91: =B91/(24*J91) -> 0.19493986 | F91: 0 | G91: 0 | H91: =(G91-F91)*24*60 -> 0 | I91: =H91/60 -> 0 | J91: 2411 | L91: =J91*12 -> 28932 | M91: =K91*I91 -> 0 | N91: =(L91-M91)/L91 -> 1 | O91: =E91/N91 -> 0.19493986 | Q91: =O91*J91*24 -> 11280 | R91: =Q91-B91 -> -2.7284841e-11
A92: 45926 | B92: =Data_Entry!P181 -> 10530 | C92: 0 | D92: =Data_Entry!V181 -> 0 | E92: =B92/(24*J92) -> 0.18197843 | F92: 0 | G92: 0 | H92: =(G92-F92)*24*60 -> 0 | I92: =H92/60 -> 0 | J92: 2411 | L92: =J92*12 -> 28932 | M92: =K92*I92 -> 0 | N92: =(L92-M92)/L92 -> 1 | O92: =E92/N92 -> 0.18197843 | Q92: =O92*J92*24 -> 10530 | R92: =Q92-B92 -> 0
A93: 45927 | B93: =Data_Entry!P182 -> 10650 | C93: 0 | D93: =Data_Entry!V182 -> 0 | E93: =B93/(24*J93) -> 0.18405226 | F93: 0 | G93: 0 | H93: =(G93-F93)*24*60 -> 0 | I93: =H93/60 -> 0 | J93: 2411 | L93: =J93*12 -> 28932 | M93: =K93*I93 -> 0 | N93: =(L93-M93)/L93 -> 1 | O93: =E93/N93 -> 0.18405226 | Q93: =O93*J93*24 -> 10650 | R93: =Q93-B93 -> -1.8189894e-11
A94: 45928 | B94: =Data_Entry!P183 -> 3510 | C94: 0 | D94: =Data_Entry!V183 -> 0 | E94: =B94/(24*J94) -> 0.060659477 | F94: 0 | G94: 0 | H94: =(G94-F94)*24*60 -> 0 | I94: =H94/60 -> 0 | J94: 2411 | L94: =J94*12 -> 28932 | M94: =K94*I94 -> 0 | N94: =(L94-M94)/L94 -> 1 | O94: =E94/N94 -> 0.060659477 | Q94: =O94*J94*24 -> 3510 | R94: =Q94-B94 -> -5.4569682e-12
A95: 45929 | B95: =Data_Entry!P184 -> 3720 | C95: 0 | D95: =Data_Entry!V184 -> 0 | E95: =B95/(24*J95) -> 0.064288677 | F95: 0 | G95: 0 | H95: =(G95-F95)*24*60 -> 0 | I95: =H95/60 -> 0 | J95: 2411 | L95: =J95*12 -> 28932 | M95: =K95*I95 -> 0 | N95: =(L95-M95)/L95 -> 1 | O95: =E95/N95 -> 0.064288677 | Q95: =O95*J95*24 -> 3720 | R95: =Q95-B95 -> 0
... A106: 45940 | B106: =Data_Entry!P195 -> 11940 | C106: 0 | D106: =Data_Entry!V195 -> 0 | E106: =B106/(24*J106) -> 0.20634591 | F106: 0 | G106: 0 | H106: =(G106-F106)*24*60 -> 0 | I106: =H106/60 -> 0 | J106: 2411 | L106: =J106*12 -> 28932 | M106: =K106*I106 -> 0 | N106: =(L106-M106)/L106 -> 1 | O106: =E106/N106 -> 0.20634591 | Q106: =O106*J106*24 -> 11940 | R106: =Q106-B106 -> -1.8189894e-11
A107: 45941 | B107: =Data_Entry!P196 -> 9570 | C107: 7 | D107: =Data_Entry!V196 -> 0 | E107: =B107/(24*J107) -> 0.16538781 | F107: 0.53125 | G107: 0.60416667 | H107: =(G107-F107)*24*60 -> 105 | I107: =H107/60 -> 1.75 | J107: 2411 | K107: 2411 | L107: =J107*12 -> 28932 | M107: =K107*I107 -> 4219.25 | N107: =(L107-M107)/L107 -> 0.85416667 | O107: =E107/N107 -> 0.19362475 | Q107: =O107*J107*24 -> 11203.902 | R107: =Q107-B107 -> 1633.9024
A108: 45942 | B108: =Data_Entry!P197 -> 12840 | C108: 0 | D108: =Data_Entry!V197 -> 0 | E108: =B108/(24*J108) -> 0.22189963 | F108: 0 | G108: 0 | H108: =(G108-F108)*24*60 -> 0 | I108: =H108/60 -> 0 | J108: 2411 | L108: =J108*12 -> 28932 | M108: =K108*I108 -> 0 | N108: =(L108-M108)/L108 -> 1 | O108: =E108/N108 -> 0.22189963 | Q108: =O108*J108*24 -> 12840 | R108: =Q108-B108 -> 2.0008883e-11
A109: 45943 | B109: =Data_Entry!P198 -> 12360 | C109: 0 | D109: =Data_Entry!V198 -> 0 | E109: =B109/(24*J109) -> 0.21360431 | F109: 0 | G109: 0 | H109: =(G109-F109)*24*60 -> 0 | I109: =H109/60 -> 0 | J109: 2411 | L109: =J109*12 -> 28932 | M109: =K109*I109 -> 0 | N109: =(L109-M109)/L109 -> 1 | O109: =E109/N109 -> 0.21360431 | Q109: =O109*J109*24 -> 12360 | R109: =Q109-B109 -> 0
A110: 45944 | B110: =Data_Entry!P199 -> 12600 | C110: 0 | D110: =Data_Entry!V199 -> 0 | E110: =B110/(24*J110) -> 0.21775197 | F110: 0 | G110: 0 | H110: =(G110-F110)*24*60 -> 0 | I110: =H110/60 -> 0 | J110: 2411 | L110: =J110*12 -> 28932 | M110: =K110*I110 -> 0 | N110: =(L110-M110)/L110 -> 1 | O110: =E110/N110 -> 0.21775197 | Q110: =O110*J110*24 -> 12600 | R110: =Q110-B110 -> 3.4560799e-11
A111: 45945 | B111: =Data_Entry!P200 -> 12750 | C111: 0 | D111: =Data_Entry!V200 -> 0 | E111: =B111/(24*J111) -> 0.22034426 | F111: 0 | G111: 0 | H111: =(G111-F111)*24*60 -> 0 | I111: =H111/60 -> 0 | J111: 2411 | L111: =J111*12 -> 28932 | M111: =K111*I111 -> 0 | N111: =(L111-M111)/L111 -> 1 | O111: =E111/N111 -> 0.22034426 | Q111: =O111*J111*24 -> 12750 | R111: =Q111-B111 -> 0
A112: 45946 | B112: =Data_Entry!P201 -> 10470 | C112: 0 | D112: =Data_Entry!V201 -> 0 | E112: =B112/(24*J112) -> 0.18094152 | F112: 0 | G112: 0 | H112: =(G112-F112)*24*60 -> 0 | I112: =H112/60 -> 0 | J112: 2411 | L112: =J112*12 -> 28932 | M112: =K112*I112 -> 0 | N112: =(L112-M112)/L112 -> 1 | O112: =E112/N112 -> 0.18094152 | Q112: =O112*J112*24 -> 10470 | R112: =Q112-B112 -> 5.0931703e-11
A113: 45947 | B113: =Data_Entry!P202 -> 11550 | C113: 0 | D113: =Data_Entry!V202 -> 0 | E113: =B113/(24*J113) -> 0.19960597 | F113: 0 | G113: 0 | H113: =(G113-F113)*24*60 -> 0 | I113: =H113/60 -> 0 | J113: 2411 | L113: =J113*12 -> 28932 | M113: =K113*I113 -> 0 | N113: =(L113-M113)/L113 -> 1 | O113: =E113/N113 -> 0.19960597 | Q113: =O113*J113*24 -> 11550 | R113: =Q113-B113 -> -2.0008883e-11
A114: 45948 | B114: =Data_Entry!P203 -> 12630 | C114: 0 | D114: =Data_Entry!V203 -> 0 | E114: =B114/(24*J114) -> 0.21827043 | F114: 0 | G114: 0 | H114: =(G114-F114)*24*60 -> 0 | I114: =H114/60 -> 0 | J114: 2411 | L114: =J114*12 -> 28932 | M114: =K114*I114 -> 0 | N114: =(L114-M114)/L114 -> 1 | O114: =E114/N114 -> 0.21827043 | Q114: =O114*J114*24 -> 12630 | R114: =Q114-B114 -> -4.0017767e-11
A115: 45949 | B115: =Data_Entry!P204 -> 11790 | C115: 0 | D115: =Data_Entry!V204 -> 0 | E115: =B115/(24*J115) -> 0.20375363 | F115: 0 | G115: 0 | H115: =(G115-F115)*24*60 -> 0 | I115: =H115/60 -> 0 | J115: 2411 | L115: =J115*12 -> 28932 | M115: =K115*I115 -> 0 | N115: =(L115-M115)/L115 -> 1 | O115: =E115/N115 -> 0.20375363 | Q115: =O115*J115*24 -> 11790 | R115: =Q115-B115 -> 1.4551915e-11
A116: 45950 | B116: =Data_Entry!P205 -> 11700 | C116: 0 | D116: =Data_Entry!V205 -> 0 | E116: =B116/(24*J116) -> 0.20219826 | F116: 0 | G116: 0 | H116: =(G116-F116)*24*60 -> 0 | I116: =H116/60 -> 0 | J116: 2411 | L116: =J116*12 -> 28932 | M116: =K116*I116 -> 0 | N116: =(L116-M116)/L116 -> 1 | O116: =E116/N116 -> 0.20219826 | Q116: =O116*J116*24 -> 11700 | R116: =Q116-B116 -> 4.7293724e-11
A117: 45951 | B117: =Data_Entry!P206 -> 10020 | C117: 0 | D117: =Data_Entry!V206 -> 0 | E117: =B117/(24*J117) -> 0.17316466 | F117: 0 | G117: 0 | H117: =(G117-F117)*24*60 -> 0 | I117: =H117/60 -> 0 | J117: 2411 | L117: =J117*12 -> 28932 | M117: =K117*I117 -> 0 | N117: =(L117-M117)/L117 -> 1 | O117: =E117/N117 -> 0.17316466 | Q117: =O117*J117*24 -> 10020 | R117: =Q117-B117 -> 0
A118: 45952 | B118: =Data_Entry!P207 -> 11100 | C118: 0 | D118: =Data_Entry!V207 -> 0 | E118: =B118/(24*J118) -> 0.19182912 | F118: 0 | G118: 0 | H118: =(G118-F118)*24*60 -> 0 | I118: =H118/60 -> 0 | J118: 2411 | L118: =J118*12 -> 28932 | M118: =K118*I118 -> 0 | N118: =(L118-M118)/L118 -> 1 | O118: =E118/N118 -> 0.19182912 | Q118: =O118*J118*24 -> 11100 | R118: =Q118-B118 -> -1.4551915e-11
A119: 45953 | B119: =Data_Entry!P208 -> 10830 | C119: 0 | D119: =Data_Entry!V208 -> 0 | E119: =B119/(24*J119) -> 0.187163 | F119: 0 | G119: 0 | H119: =(G119-F119)*24*60 -> 0 | I119: =H119/60 -> 0 | J119: 2411 | L119: =J119*12 -> 28932 | M119: =K119*I119 -> 0 | N119: =(L119-M119)/L119 -> 1 | O119: =E119/N119 -> 0.187163 | Q119: =O119*J119*24 -> 10830 | R119: =Q119-B119 -> 2.3646862e-11
... A137: 45971 | B137: =Data_Entry!P226 -> 12150 | C137: 0 | D137: =Data_Entry!V226 -> 3.79 | E137: =B137/(24*J137) -> 0.20997511 | F137: 0 | G137: 0 | H137: =(G137-F137)*24*60 -> 0 | I137: =H137/60 -> 0 | J137: 2411 | L137: =J137*12 -> 28932 | M137: =K137*I137 -> 0 | N137: =(L137-M137)/L137 -> 1 | O137: =E137/N137 -> 0.20997511 | Q137: =O137*J137*24 -> 12150 | R137: =Q137-B137 -> -6.002665e-11
...

Sheet Grid Availiblity
A1: Date | B1: ABT Export Gen | C1: GHI | D1: CUF% | E1: Out | F1: In | G1: Total Minute | H1: Outage Hrs. | I1: Plant Capacity | J1: Outage Capacity | K1: Plant Capacity Ratio | L1: Outage Ratio | M1: Grid Availiblity | N1: G.C CUF | O1: G.C Generation | P1: Grid Unit Lose
A2: 45839 | B2: =Data_Entry!P94 -> 8370 | C2: =Data_Entry!V94 -> 3.18 | D2: =B2/(24*I2) -> 0.14464952 | E2: 0 | F2: 0 | G2: =(F2-E2)*24*60 -> 0 | H2: =G2/60 -> 0 | I2: 2411 | K2: =I2*12 -> 28932 | L2: =J2*H2 -> 0 | M2: =(K2-L2)/K2 -> 1 | N2: =D2/M2 -> 0.14464952 | O2: =N2*I2*24 -> 8370 | P2: =O2-B2 -> 0
A3: 45840 | B3: =Data_Entry!P95 -> 4380 | C3: =Data_Entry!V95 -> 1.61 | D3: =B3/(24*I3) -> 0.075694732 | E3: 0 | F3: 0 | G3: =(F3-E3)*24*60 -> 0 | H3: =G3/60 -> 0 | I3: 2411 | K3: =I3*12 -> 28932 | L3: =J3*H3 -> 0 | M3: =(K3-L3)/K3 -> 1 | N3: =D3/M3 -> 0.075694732 | O3: =N3*I3*24 -> 4380 | P3: =O3-B3 -> 0
A4: 45841 | B4: =Data_Entry!P96 -> 3870 | C4: =Data_Entry!V96 -> 1.11 | D4: =B4/(24*I4) -> 0.066880962 | E4: 0 | F4: 0 | G4: =(F4-E4)*24*60 -> 0 | H4: =G4/60 -> 0 | I4: 2411 | K4: =I4*12 -> 28932 | L4: =J4*H4 -> 0 | M4: =(K4-L4)/K4 -> 1 | N4: =D4/M4 -> 0.066880962 | O4: =N4*I4*24 -> 3870 | P4: =O4-B4 -> 0
A5: 45842 | B5: =Data_Entry!P97 -> 6540 | C5: =Data_Entry!V97 -> 2.7 | D5: =B5/(24*I5) -> 0.11302364 | E5: 0 | F5: 0 | G5: =(F5-E5)*24*60 -> 0 | H5: =G5/60 -> 0 | I5: 2411 | K5: =I5*12 -> 28932 | L5: =J5*H5 -> 0 | M5: =(K5-L5)/K5 -> 1 | N5: =D5/M5 -> 0.11302364 | O5: =N5*I5*24 -> 6540 | P5: =O5-B5 -> 0
A6: 45843 | B6: =Data_Entry!P98 -> 3990 | C6: =Data_Entry!V98 -> 1.3 | D6: =B6/(24*I6) -> 0.068954791 | E6: 0 | F6: 0 | G6: =(F6-E6)*24*60 -> 0 | H6: =G6/60 -> 0 | I6: 2411 | K6: =I6*12 -> 28932 | L6: =J6*H6 -> 0 | M6: =(K6-L6)/K6 -> 1 | N6: =D6/M6 -> 0.068954791 | O6: =N6*I6*24 -> 3990 | P6: =O6-B6 -> 0
A7: 45844 | B7: =Data_Entry!P99 -> 6240 | C7: =Data_Entry!V99 -> 2.44 | D7: =B7/(24*I7) -> 0.10783907 | E7: 0 | F7: 0 | G7: =(F7-E7)*24*60 -> 0 | H7: =G7/60 -> 0 | I7: 2411 | K7: =I7*12 -> 28932 | L7: =J7*H7 -> 0 | M7: =(K7-L7)/K7 -> 1 | N7: =D7/M7 -> 0.10783907 | O7: =N7*I7*24 -> 6240 | P7: =O7-B7 -> 0
A8: 45845 | B8: =Data_Entry!P100 -> 4860 | C8: =Data_Entry!V100 -> 1.82 | D8: =B8/(24*I8) -> 0.083990046 | E8: 0 | F8: 0 | G8: =(F8-E8)*24*60 -> 0 | H8: =G8/60 -> 0 | I8: 2411 | K8: =I8*12 -> 28932 | L8: =J8*H8 -> 0 | M8: =(K8-L8)/K8 -> 1 | N8: =D8/M8 -> 0.083990046 | O8: =N8*I8*24 -> 4860 | P8: =O8-B8 -> 0
A9: 45846 | B9: =Data_Entry!P101 -> 7590 | C9: =Data_Entry!V101 -> 3.16 | D9: =B9/(24*I9) -> 0.13116964 | E9: 0 | F9: 0 | G9: =(F9-E9)*24*60 -> 0 | H9: =G9/60 -> 0 | I9: 2411 | K9: =I9*12 -> 28932 | L9: =J9*H9 -> 0 | M9: =(K9-L9)/K9 -> 1 | N9: =D9/M9 -> 0.13116964 | O9: =N9*I9*24 -> 7590 | P9: =O9-B9 -> 0
A10: 45847 | B10: =Data_Entry!P102 -> 11370 | C10: =Data_Entry!V102 -> 4.7 | D10: =B10/(24*I10) -> 0.19649523 | E10: 0 | F10: 0 | G10: =(F10-E10)*24*60 -> 0 | H10: =G10/60 -> 0 | I10: 2411 | K10: =I10*12 -> 28932 | L10: =J10*H10 -> 0 | M10: =(K10-L10)/K10 -> 1 | N10: =D10/M10 -> 0.19649523 | O10: =N10*I10*24 -> 11370 | P10: =O10-B10 -> 0
A11: 45848 | B11: =Data_Entry!P103 -> 5790 | C11: =Data_Entry!V103 -> 2.43 | D11: =B11/(24*I11) -> 0.10006221 | E11: 0 | F11: 0 | G11: =(F11-E11)*24*60 -> 0 | H11: =G11/60 -> 0 | I11: 2411 | K11: =I11*12 -> 28932 | L11: =J11*H11 -> 0 | M11: =(K11-L11)/K11 -> 1 | N11: =D11/M11 -> 0.10006221 | O11: =N11*I11*24 -> 5790 | P11: =O11-B11 -> 0
A12: 45849 | B12: =Data_Entry!P104 -> 4770 | C12: =Data_Entry!V104 -> 1.57 | D12: =B12/(24*I12) -> 0.082434674 | E12: 0 | F12: 0 | G12: =(F12-E12)*24*60 -> 0 | H12: =G12/60 -> 0 | I12: 2411 | K12: =I12*12 -> 28932 | L12: =J12*H12 -> 0 | M12: =(K12-L12)/K12 -> 1 | N12: =D12/M12 -> 0.082434674 | O12: =N12*I12*24 -> 4770 | P12: =O12-B12 -> 0
A13: 45850 | B13: =Data_Entry!P105 -> 6930 | C13: =Data_Entry!V105 -> 3.25 | D13: =B13/(24*I13) -> 0.11976358 | E13: 0.44444444 | F13: 0.49305556 | G13: =(F13-E13)*24*60 -> 70 | H13: =G13/60 -> 1.1666667 | I13: 2411 | J13: 2411 | K13: =I13*12 -> 28932 | L13: =J13*H13 -> 2812.8333 | M13: =(K13-L13)/K13 -> 0.90277778 | N13: =D13/M13 -> 0.1326612 | O13: =N13*I13*24 -> 7676.3077 | P13: =O13-B13 -> 746.30769
A14: 45851 | B14: =Data_Entry!P106 -> 7950 | C14: =Data_Entry!V106 -> 3.65 | D14: =B14/(24*I14) -> 0.13739112 | E14: 0.46527778 | F14: 0.57638889 | G14: =(F14-E14)*24*60 -> 160 | H14: =G14/60 -> 2.6666667 | I14: 2411 | J14: 2411 | K14: =I14*12 -> 28932 | L14: =J14*H14 -> 6429.3333 | M14: =(K14-L14)/K14 -> 0.77777778 | N14: =D14/M14 -> 0.17664573 | O14: =N14*I14*24 -> 10221.429 | P14: =O14-B14 -> 2271.4286
A15: 45852 | B15: =Data_Entry!P107 -> 10020 | C15: =Data_Entry!V107 -> 4.46 | D15: =B15/(24*I15) -> 0.17316466 | E15: 0 | F15: 0 | G15: =(F15-E15)*24*60 -> 0 | H15: =G15/60 -> 0 | I15: 2411 | K15: =I15*12 -> 28932 | L15: =J15*H15 -> 0 | M15: =(K15-L15)/K15 -> 1 | N15: =D15/M15 -> 0.17316466 | O15: =N15*I15*24 -> 10020 | P15: =O15-B15 -> 0
A16: 45853 | B16: =Data_Entry!P108 -> 10470 | C16: =Data_Entry!V108 -> 4.22 | D16: =B16/(24*I16) -> 0.18094152 | E16: 0 | F16: 0 | G16: =(F16-E16)*24*60 -> 0 | H16: =G16/60 -> 0 | I16: 2411 | K16: =I16*12 -> 28932 | L16: =J16*H16 -> 0 | M16: =(K16-L16)/K16 -> 1 | N16: =D16/M16 -> 0.18094152 | O16: =N16*I16*24 -> 10470 | P16: =O16-B16 -> 0
A17: 45854 | B17: =Data_Entry!P109 -> 10560 | C17: =Data_Entry!V109 -> 4.6 | D17: =B17/(24*I17) -> 0.18249689 | E17: 0 | F17: 0 | G17: =(F17-E17)*24*60 -> 0 | H17: =G17/60 -> 0 | I17: 2411 | K17: =I17*12 -> 28932 | L17: =J17*H17 -> 0 | M17: =(K17-L17)/K17 -> 1 | N17: =D17/M17 -> 0.18249689 | O17: =N17*I17*24 -> 10560 | P17: =O17-B17 -> 0
A18: 45855 | B18: =Data_Entry!P110 -> 10020 | C18: =Data_Entry!V110 -> 4.7 | D18: =B18/(24*I18) -> 0.17316466 | E18: 0 | F18: 0 | G18: =(F18-E18)*24*60 -> 0 | H18: =G18/60 -> 0 | I18: 2411 | K18: =I18*12 -> 28932 | L18: =J18*H18 -> 0 | M18: =(K18-L18)/K18 -> 1 | N18: =D18/M18 -> 0.17316466 | O18: =N18*I18*24 -> 10020 | P18: =O18-B18 -> 0
A19: 45856 | B19: =Data_Entry!P111 -> 12510 | C19: =Data_Entry!V111 -> 5.45 | D19: =B19/(24*I19) -> 0.2161966 | E19: 0 | F19: 0 | G19: =(F19-E19)*24*60 -> 0 | H19: =G19/60 -> 0 | I19: 2411 | K19: =I19*12 -> 28932 | L19: =J19*H19 -> 0 | M19: =(K19-L19)/K19 -> 1 | N19: =D19/M19 -> 0.2161966 | O19: =N19*I19*24 -> 12510 | P19: =O19-B19 -> 0
A20: 45857 | B20: =Data_Entry!P112 -> 8700 | C20: =Data_Entry!V112 -> 3.48 | D20: =B20/(24*I20) -> 0.15035255 | E20: 0 | F20: 0 | G20: =(F20-E20)*24*60 -> 0 | H20: =G20/60 -> 0 | I20: 2411 | K20: =I20*12 -> 28932 | L20: =J20*H20 -> 0 | M20: =(K20-L20)/K20 -> 1 | N20: =D20/M20 -> 0.15035255 | O20: =N20*I20*24 -> 8700 | P20: =O20-B20 -> 0
A21: 45858 | B21: =Data_Entry!P113 -> 9810 | C21: =Data_Entry!V113 -> 3.3 | D21: =B21/(24*I21) -> 0.16953546 | E21: 0 | F21: 0 | G21: =(F21-E21)*24*60 -> 0 | H21: =G21/60 -> 0 | I21: 2411 | K21: =I21*12 -> 28932 | L21: =J21*H21 -> 0 | M21: =(K21-L21)/K21 -> 1 | N21: =D21/M21 -> 0.16953546 | O21: =N21*I21*24 -> 9810 | P21: =O21-B21 -> 0
A22: 45859 | B22: =Data_Entry!P114 -> 7620 | C22: =Data_Entry!V114 -> 3.27 | D22: =B22/(24*I22) -> 0.1316881 | E22: 0 | F22: 0 | G22: =(F22-E22)*24*60 -> 0 | H22: =G22/60 -> 0 | I22: 2411 | K22: =I22*12 -> 28932 | L22: =J22*H22 -> 0 | M22: =(K22-L22)/K22 -> 1 | N22: =D22/M22 -> 0.1316881 | O22: =N22*I22*24 -> 7620 | P22: =O22-B22 -> 0
A23: 45860 | B23: =Data_Entry!P115 -> 9270 | C23: =Data_Entry!V115 -> 4.06 | D23: =B23/(24*I23) -> 0.16020324 | E23: 0 | F23: 0 | G23: =(F23-E23)*24*60 -> 0 | H23: =G23/60 -> 0 | I23: 2411 | K23: =I23*12 -> 28932 | L23: =J23*H23 -> 0 | M23: =(K23-L23)/K23 -> 1 | N23: =D23/M23 -> 0.16020324 | O23: =N23*I23*24 -> 9270 | P23: =O23-B23 -> 0
A24: 45861 | B24: =Data_Entry!P116 -> 6210 | C24: =Data_Entry!V116 -> 2.6 | D24: =B24/(24*I24) -> 0.10732061 | E24: 0.36458333 | F24: 0.47916667 | G24: =(F24-E24)*24*60 -> 165 | H24: =G24/60 -> 2.75 | I24: 2411 | J24: 2411 | K24: =I24*12 -> 28932 | L24: =J24*H24 -> 6630.25 | M24: =(K24-L24)/K24 -> 0.77083333 | N24: =D24/M24 -> 0.13922674 | O24: =N24*I24*24 -> 8056.2162 | P24: =O24-B24 -> 1846.2162
A25: 45862 | B25: =Data_Entry!P117 -> 4800 | C25: =Data_Entry!V117 -> 1.81 | D25: =B25/(24*I25) -> 0.082953131 | E25: 0 | F25: 0 | G25: =(F25-E25)*24*60 -> 0 | H25: =G25/60 -> 0 | I25: 2411 | K25: =I25*12 -> 28932 | L25: =J25*H25 -> 0 | M25: =(K25-L25)/K25 -> 1 | N25: =D25/M25 -> 0.082953131 | O25: =N25*I25*24 -> 4800 | P25: =O25-B25 -> 0
A26: 45863 | B26: =Data_Entry!P118 -> 8040 | C26: =Data_Entry!V118 -> 2.8 | D26: =B26/(24*I26) -> 0.1389465 | E26: 0 | F26: 0 | G26: =(F26-E26)*24*60 -> 0 | H26: =G26/60 -> 0 | I26: 2411 | K26: =I26*12 -> 28932 | L26: =J26*H26 -> 0 | M26: =(K26-L26)/K26 -> 1 | N26: =D26/M26 -> 0.1389465 | O26: =N26*I26*24 -> 8040 | P26: =O26-B26 -> 0
A27: 45864 | B27: =Data_Entry!P119 -> 4560 | C27: =Data_Entry!V119 -> 1.61 | D27: =B27/(24*I27) -> 0.078805475 | E27: 0 | F27: 0 | G27: =(F27-E27)*24*60 -> 0 | H27: =G27/60 -> 0 | I27: 2411 | K27: =I27*12 -> 28932 | L27: =J27*H27 -> 0 | M27: =(K27-L27)/K27 -> 1 | N27: =D27/M27 -> 0.078805475 | O27: =N27*I27*24 -> 4560 | P27: =O27-B27 -> 0
A28: 45865 | B28: =Data_Entry!P120 -> 4020 | C28: =Data_Entry!V120 -> 1.55 | D28: =B28/(24*I28) -> 0.069473248 | E28: 0 | F28: 0 | G28: =(F28-E28)*24*60 -> 0 | H28: =G28/60 -> 0 | I28: 2411 | K28: =I28*12 -> 28932 | L28: =J28*H28 -> 0 | M28: =(K28-L28)/K28 -> 1 | N28: =D28/M28 -> 0.069473248 | O28: =N28*I28*24 -> 4020 | P28: =O28-B28 -> 0
A29: 45866 | B29: =Data_Entry!P121 -> 5850 | C29: =Data_Entry!V121 -> 2.32 | D29: =B29/(24*I29) -> 0.10109913 | E29: 0 | F29: 0 | G29: =(F29-E29)*24*60 -> 0 | H29: =G29/60 -> 0 | I29: 2411 | K29: =I29*12 -> 28932 | L29: =J29*H29 -> 0 | M29: =(K29-L29)/K29 -> 1 | N29: =D29/M29 -> 0.10109913 | O29: =N29*I29*24 -> 5850 | P29: =O29-B29 -> 0
A30: 45867 | B30: =Data_Entry!P122 -> 5370 | C30: =Data_Entry!V122 -> 2.13 | D30: =B30/(24*I30) -> 0.092803816 | E30: 0 | F30: 0 | G30: =(F30-E30)*24*60 -> 0 | H30: =G30/60 -> 0 | I30: 2411 | K30: =I30*12 -> 28932 | L30: =J30*H30 -> 0 | M30: =(K30-L30)/K30 -> 1 | N30: =D30/M30 -> 0.092803816 | O30: =N30*I30*24 -> 5370 | P30: =O30-B30 -> 0
A31: 45868 | B31: =Data_Entry!P123 -> 8490 | C31: =Data_Entry!V123 -> 3.62 | D31: =B31/(24*I31) -> 0.14672335 | E31: 0 | F31: 0 | G31: =(F31-E31)*24*60 -> 0 | H31: =G31/60 -> 0 | I31: 2411 | K31: =I31*12 -> 28932 | L31: =J31*H31 -> 0 | M31: =(K31-L31)/K31 -> 1 | N31: =D31/M31 -> 0.14672335 | O31: =N31*I31*24 -> 8490 | P31: =O31-B31 -> 0
A32: 45869 | B32: =Data_Entry!P124 -> 5880 | C32: =Data_Entry!V124 -> 2.47 | D32: =B32/(24*I32) -> 0.10161759 | E32: 0 | F32: 0 | G32: =(F32-E32)*24*60 -> 0 | H32: =G32/60 -> 0 | I32: 2411 | K32: =I32*12 -> 28932 | L32: =J32*H32 -> 0 | M32: =(K32-L32)/K32 -> 1 | N32: =D32/M32 -> 0.10161759 | O32: =N32*I32*24 -> 5880 | P32: =O32-B32 -> 0
A34: 45870 | B34: =Data_Entry!P125 -> 7320 | C34: =Data_Entry!V125 -> 3.14 | D34: =B34/(24*I34) -> 0.12650353 | E34: 0 | F34: 0 | G34: =(F34-E34)*24*60 -> 0 | H34: =G34/60 -> 0 | I34: 2411 | K34: =I34*12 -> 28932 | L34: =J34*H34 -> 0 | M34: =(K34-L34)/K34 -> 1 | N34: =D34/M34 -> 0.12650353 | O34: =N34*I34*24 -> 7320 | P34: =O34-B34 -> 0
A35: 45871 | B35: =Data_Entry!P126 -> 7290 | C35: =Data_Entry!V126 -> 2.91 | D35: =B35/(24*I35) -> 0.12598507 | E35: 0 | F35: 0 | G35: =(F35-E35)*24*60 -> 0 | H35: =G35/60 -> 0 | I35: 2411 | K35: =I35*12 -> 28932 | L35: =J35*H35 -> 0 | M35: =(K35-L35)/K35 -> 1 | N35: =D35/M35 -> 0.12598507 | O35: =N35*I35*24 -> 7290 | P35: =O35-B35 -> 0
A36: 45872 | B36: =Data_Entry!P127 -> 6870 | C36: =Data_Entry!V127 -> 2.78 | D36: =B36/(24*I36) -> 0.11872667 | E36: 0 | F36: 0 | G36: =(F36-E36)*24*60 -> 0 | H36: =G36/60 -> 0 | I36: 2411 | K36: =I36*12 -> 28932 | L36: =J36*H36 -> 0 | M36: =(K36-L36)/K36 -> 1 | N36: =D36/M36 -> 0.11872667 | O36: =N36*I36*24 -> 6870 | P36: =O36-B36 -> 0
A37: 45873 | B37: =Data_Entry!P128 -> 6900 | C37: =Data_Entry!V128 -> 2.5 | D37: =B37/(24*I37) -> 0.11924513 | E37: 0 | F37: 0 | G37: =(F37-E37)*24*60 -> 0 | H37: =G37/60 -> 0 | I37: 2411 | K37: =I37*12 -> 28932 | L37: =J37*H37 -> 0 | M37: =(K37-L37)/K37 -> 1 | N37: =D37/M37 -> 0.11924513 | O37: =N37*I37*24 -> 6900 | P37: =O37-B37 -> 0
A38: 45874 | B38: =Data_Entry!P129 -> 6690 | C38: =Data_Entry!V129 -> 2.64 | D38: =B38/(24*I38) -> 0.11561593 | E38: 0 | F38: 0 | G38: =(F38-E38)*24*60 -> 0 | H38: =G38/60 -> 0 | I38: 2411 | K38: =I38*12 -> 28932 | L38: =J38*H38 -> 0 | M38: =(K38-L38)/K38 -> 1 | N38: =D38/M38 -> 0.11561593 | O38: =N38*I38*24 -> 6690 | P38: =O38-B38 -> 0
A39: 45875 | B39: =Data_Entry!P130 -> 10530 | C39: =Data_Entry!V130 -> 4.15 | D39: =B39/(24*I39) -> 0.18197843 | E39: 0 | F39: 0 | G39: =(F39-E39)*24*60 -> 0 | H39: =G39/60 -> 0 | I39: 2411 | K39: =I39*12 -> 28932 | L39: =J39*H39 -> 0 | M39: =(K39-L39)/K39 -> 1 | N39: =D39/M39 -> 0.18197843 | O39: =N39*I39*24 -> 10530 | P39: =O39-B39 -> 0
A40: 45876 | B40: =Data_Entry!P131 -> 11430 | C40: =Data_Entry!V131 -> 4.81 | D40: =B40/(24*I40) -> 0.19753214 | E40: 0 | F40: 0 | G40: =(F40-E40)*24*60 -> 0 | H40: =G40/60 -> 0 | I40: 2411 | K40: =I40*12 -> 28932 | L40: =J40*H40 -> 0 | M40: =(K40-L40)/K40 -> 1 | N40: =D40/M40 -> 0.19753214 | O40: =N40*I40*24 -> 11430 | P40: =O40-B40 -> 0
A41: 45877 | B41: =Data_Entry!P132 -> 11850 | C41: =Data_Entry!V132 -> 4.76 | D41: =B41/(24*I41) -> 0.20479054 | E41: 0 | F41: 0 | G41: =(F41-E41)*24*60 -> 0 | H41: =G41/60 -> 0 | I41: 2411 | K41: =I41*12 -> 28932 | L41: =J41*H41 -> 0 | M41: =(K41-L41)/K41 -> 1 | N41: =D41/M41 -> 0.20479054 | O41: =N41*I41*24 -> 11850 | P41: =O41-B41 -> 0
A42: 45878 | B42: =Data_Entry!P133 -> 7170 | C42: =Data_Entry!V133 -> 3.13 | D42: =B42/(24*I42) -> 0.12391124 | E42: 0 | F42: 0 | G42: =(F42-E42)*24*60 -> 0 | H42: =G42/60 -> 0 | I42: 2411 | K42: =I42*12 -> 28932 | L42: =J42*H42 -> 0 | M42: =(K42-L42)/K42 -> 1 | N42: =D42/M42 -> 0.12391124 | O42: =N42*I42*24 -> 7170 | P42: =O42-B42 -> 0
A43: 45879 | B43: =Data_Entry!P134 -> 9240 | C43: =Data_Entry!V134 -> 3.55 | D43: =B43/(24*I43) -> 0.15968478 | E43: 0 | F43: 0 | G43: =(F43-E43)*24*60 -> 0 | H43: =G43/60 -> 0 | I43: 2411 | K43: =I43*12 -> 28932 | L43: =J43*H43 -> 0 | M43: =(K43-L43)/K43 -> 1 | N43: =D43/M43 -> 0.15968478 | O43: =N43*I43*24 -> 9240 | P43: =O43-B43 -> 0
A44: 45880 | B44: =Data_Entry!P135 -> 6060 | C44: =Data_Entry!V135 -> 3.28 | D44: =B44/(24*I44) -> 0.10472833 | E44: 0 | F44: 0 | G44: =(F44-E44)*24*60 -> 0 | H44: =G44/60 -> 0 | I44: 2411 | K44: =I44*12 -> 28932 | L44: =J44*H44 -> 0 | M44: =(K44-L44)/K44 -> 1 | N44: =D44/M44 -> 0.10472833 | O44: =N44*I44*24 -> 6060 | P44: =O44-B44 -> 0
A45: 45881 | B45: =Data_Entry!P136 -> 8100 | C45: =Data_Entry!V136 -> 2.98 | D45: =B45/(24*I45) -> 0.13998341 | E45: 0 | F45: 0 | G45: =(F45-E45)*24*60 -> 0 | H45: =G45/60 -> 0 | I45: 2411 | K45: =I45*12 -> 28932 | L45: =J45*H45 -> 0 | M45: =(K45-L45)/K45 -> 1 | N45: =D45/M45 -> 0.13998341 | O45: =N45*I45*24 -> 8100 | P45: =O45-B45 -> 0
... A64: 45900 | B64: =Data_Entry!P155 -> 8460 | C64: =Data_Entry!V155 -> 0 | D64: =B64/(24*I64) -> 0.14620489 | E64: 0 | F64: 0 | G64: =(F64-E64)*24*60 -> 0 | H64: =G64/60 -> 0 | I64: 2411 | K64: =I64*12 -> 28932 | L64: =J64*H64 -> 0 | M64: =(K64-L64)/K64 -> 1 | N64: =D64/M64 -> 0.14620489 | O64: =N64*I64*24 -> 8460 | P64: =O64-B64 -> 0
M65: =AVERAGE(M34:M64) -> 1
A66: 45901 | B66: =Data_Entry!P156 -> 8310 | C66: =Data_Entry!V156 -> 0 | D66: =B66/(24*I66) -> 0.14361261 | E66: 0 | F66: 0 | G66: =(F66-E66)*24*60 -> 0 | H66: =G66/60 -> 0 | I66: 2411 | K66: =I66*12 -> 28932 | L66: =J66*H66 -> 0 | M66: =(K66-L66)/K66 -> 1 | N66: =D66/M66 -> 0.14361261 | O66: =N66*I66*24 -> 8310 | P66: =O66-B66 -> 0
A67: 45902 | B67: =Data_Entry!P157 -> 11250 | C67: =Data_Entry!V157 -> 0 | D67: =B67/(24*I67) -> 0.1944214 | E67: 0 | F67: 0 | G67: =(F67-E67)*24*60 -> 0 | H67: =G67/60 -> 0 | I67: 2411 | K67: =I67*12 -> 28932 | L67: =J67*H67 -> 0 | M67: =(K67-L67)/K67 -> 1 | N67: =D67/M67 -> 0.1944214 | O67: =N67*I67*24 -> 11250 | P67: =O67-B67 -> 0
A68: 45903 | B68: =Data_Entry!P158 -> 11670 | C68: =Data_Entry!V158 -> 0 | D68: =B68/(24*I68) -> 0.2016798 | E68: 0 | F68: 0 | G68: =(F68-E68)*24*60 -> 0 | H68: =G68/60 -> 0 | I68: 2411 | K68: =I68*12 -> 28932 | L68: =J68*H68 -> 0 | M68: =(K68-L68)/K68 -> 1 | N68: =D68/M68 -> 0.2016798 | O68: =N68*I68*24 -> 11670 | P68: =O68-B68 -> 0
A69: 45904 | B69: =Data_Entry!P159 -> 5520 | C69: =Data_Entry!V159 -> 0 | D69: =B69/(24*I69) -> 0.095396101 | E69: 0 | F69: 0 | G69: =(F69-E69)*24*60 -> 0 | H69: =G69/60 -> 0 | I69: 2411 | K69: =I69*12 -> 28932 | L69: =J69*H69 -> 0 | M69: =(K69-L69)/K69 -> 1 | N69: =D69/M69 -> 0.095396101 | O69: =N69*I69*24 -> 5520 | P69: =O69-B69 -> 0
A70: 45905 | B70: =Data_Entry!P160 -> 4890 | C70: =Data_Entry!V160 -> 0 | D70: =B70/(24*I70) -> 0.084508503 | E70: 0 | F70: 0 | G70: =(F70-E70)*24*60 -> 0 | H70: =G70/60 -> 0 | I70: 2411 | K70: =I70*12 -> 28932 | L70: =J70*H70 -> 0 | M70: =(K70-L70)/K70 -> 1 | N70: =D70/M70 -> 0.084508503 | O70: =N70*I70*24 -> 4890 | P70: =O70-B70 -> 0
A71: 45906 | B71: =Data_Entry!P161 -> 3660 | C71: =Data_Entry!V161 -> 0 | D71: =B71/(24*I71) -> 0.063251763 | E71: 0 | F71: 0 | G71: =(F71-E71)*24*60 -> 0 | H71: =G71/60 -> 0 | I71: 2411 | K71: =I71*12 -> 28932 | L71: =J71*H71 -> 0 | M71: =(K71-L71)/K71 -> 1 | N71: =D71/M71 -> 0.063251763 | O71: =N71*I71*24 -> 3660 | P71: =O71-B71 -> 0
A72: 45907 | B72: =Data_Entry!P162 -> 3450 | C72: =Data_Entry!V162 -> 0 | D72: =B72/(24*I72) -> 0.059622563 | E72: 0 | F72: 0 | G72: =(F72-E72)*24*60 -> 0 | H72: =G72/60 -> 0 | I72: 2411 | K72: =I72*12 -> 28932 | L72: =J72*H72 -> 0 | M72: =(K72-L72)/K72 -> 1 | N72: =D72/M72 -> 0.059622563 | O72: =N72*I72*24 -> 3450 | P72: =O72-B72 -> 0
A73: 45908 | B73: =Data_Entry!P163 -> 3960 | C73: =Data_Entry!V163 -> 0 | D73: =B73/(24*I73) -> 0.068436333 | E73: 0 | F73: 0 | G73: =(F73-E73)*24*60 -> 0 | H73: =G73/60 -> 0 | I73: 2411 | K73: =I73*12 -> 28932 | L73: =J73*H73 -> 0 | M73: =(K73-L73)/K73 -> 1 | N73: =D73/M73 -> 0.068436333 | O73: =N73*I73*24 -> 3960 | P73: =O73-B73 -> 0
A74: 45909 | B74: =Data_Entry!P164 -> 10140 | C74: =Data_Entry!V164 -> 0 | D74: =B74/(24*I74) -> 0.17523849 | E74: 0 | F74: 0 | G74: =(F74-E74)*24*60 -> 0 | H74: =G74/60 -> 0 | I74: 2411 | K74: =I74*12 -> 28932 | L74: =J74*H74 -> 0 | M74: =(K74-L74)/K74 -> 1 | N74: =D74/M74 -> 0.17523849 | O74: =N74*I74*24 -> 10140 | P74: =O74-B74 -> 0
A75: 45910 | B75: =Data_Entry!P165 -> 11760 | C75: =Data_Entry!V165 -> 0 | D75: =B75/(24*I75) -> 0.20323517 | E75: 0 | F75: 0 | G75: =(F75-E75)*24*60 -> 0 | H75: =G75/60 -> 0 | I75: 2411 | K75: =I75*12 -> 28932 | L75: =J75*H75 -> 0 | M75: =(K75-L75)/K75 -> 1 | N75: =D75/M75 -> 0.20323517 | O75: =N75*I75*24 -> 11760 | P75: =O75-B75 -> 0
A76: 45911 | B76: =Data_Entry!P166 -> 12690 | C76: =Data_Entry!V166 -> 0 | D76: =B76/(24*I76) -> 0.21930734 | E76: 0 | F76: 0 | G76: =(F76-E76)*24*60 -> 0 | H76: =G76/60 -> 0 | I76: 2411 | K76: =I76*12 -> 28932 | L76: =J76*H76 -> 0 | M76: =(K76-L76)/K76 -> 1 | N76: =D76/M76 -> 0.21930734 | O76: =N76*I76*24 -> 12690 | P76: =O76-B76 -> 0
A77: 45912 | B77: =Data_Entry!P167 -> 13410 | C77: =Data_Entry!V167 -> 0 | D77: =B77/(24*I77) -> 0.23175031 | E77: 0 | F77: 0 | G77: =(F77-E77)*24*60 -> 0 | H77: =G77/60 -> 0 | I77: 2411 | K77: =I77*12 -> 28932 | L77: =J77*H77 -> 0 | M77: =(K77-L77)/K77 -> 1 | N77: =D77/M77 -> 0.23175031 | O77: =N77*I77*24 -> 13410 | P77: =O77-B77 -> 0
... A81: 45916 | B81: =Data_Entry!P171 -> 12360 | C81: =Data_Entry!V171 -> 0 | D81: =B81/(24*I81) -> 0.21360431 | E81: 0 | F81: 0 | G81: =(F81-E81)*24*60 -> 0 | H81: =G81/60 -> 0 | I81: 2411 | K81: =I81*12 -> 28932 | L81: =J81*H81 -> 0 | M81: =(K81-L81)/K81 -> 1 | N81: =D81/M81 -> 0.21360431 | O81: =N81*I81*24 -> 12360 | P81: =O81-B81 -> 0
A82: 45917 | B82: =Data_Entry!P172 -> 6330 | C82: =Data_Entry!V172 -> 0 | D82: =B82/(24*I82) -> 0.10939444 | E82: 0.3125 | F82: 0.5 | G82: =(F82-E82)*24*60 -> 270 | H82: =G82/60 -> 4.5 | I82: 2411 | J82: 2411 | K82: =I82*12 -> 28932 | L82: =J82*H82 -> 10849.5 | M82: =(K82-L82)/K82 -> 0.625 | N82: =D82/M82 -> 0.17503111 | O82: =N82*I82*24 -> 10128 | P82: =O82-B82 -> 3798
A83: 45918 | B83: =Data_Entry!P173 -> 13170 | C83: =Data_Entry!V173 -> 0 | D83: =B83/(24*I83) -> 0.22760265 | E83: 0 | F83: 0 | G83: =(F83-E83)*24*60 -> 0 | H83: =G83/60 -> 0 | I83: 2411 | K83: =I83*12 -> 28932 | L83: =J83*H83 -> 0 | M83: =(K83-L83)/K83 -> 1 | N83: =D83/M83 -> 0.22760265 | O83: =N83*I83*24 -> 13170 | P83: =O83-B83 -> 0
