Workbook

Sheet Budgeted_data
A1: Plant Name | B1: Date | C1: Month | D1: Month | E1: Daily_Gen | F1: Daily_GTI | G1: Daily_GHI | H1: Ambt_Temp | I1: PR_% | J1: CUF_% | K1: TArray | L1: TArrWtd | M1: Connected_DC
A2: Kanja | B2: 45658 | E2: 21731.502 | F2: 5.47253 | G2: 4.345315 | H2: 27.273333 | I2: 0.8148 | J2: =E2/24/M2 -> 0.18778085 | K2: 43.6059 | L2: 43.6059 | M2: 4822
A3: Kanja | B3: 45659 | E3: 22711.152 | F3: 5.69424 | G3: 4.481942 | H3: 25.555 | I3: 0.8188 | J3: =E3/24/M3 -> 0.19624596 | K3: 42.2575 | L3: 42.2575 | M3: 4822
A4: Kanja | B4: 45660 | E4: 21189.702 | F4: 5.30545 | G4: 4.2633838 | H4: 26.016667 | I4: 0.8209 | J4: =E4/24/M4 -> 0.18309918 | K4: 42.155 | L4: 42.155 | M4: 4822
A5: Kanja | B5: 45661 | E5: 23732.482 | F5: 5.9432 | G5: 4.6643305 | H5: 24.213333 | I5: 0.8208 | J5: =E5/24/M5 -> 0.20507122 | K5: 41.7867 | L5: 41.7867 | M5: 4822
A6: Kanja | B6: 45662 | E6: 23911.322 | F6: 5.98552 | G6: 4.7081898 | H6: 23.605417 | I6: 0.8224 | J6: =E6/24/M6 -> 0.20661657 | K6: 41.5419 | L6: 41.5419 | M6: 4822
A7: Kanja | B7: 45663 | E7: 22558.262 | F7: 5.60885 | G7: 4.4441987 | H7: 23.3175 | I7: 0.8276 | J7: =E7/24/M7 -> 0.19492484 | K7: 40.038 | L7: 40.038 | M7: 4822
A8: Kanja | B8: 45664 | E8: 23693.582 | F8: 5.92036 | G8: 4.6664676 | H8: 23.430833 | I8: 0.8244 | J8: =E8/24/M8 -> 0.20473509 | K8: 41.2841 | L8: 41.2841 | M8: 4822
A9: Kanja | B9: 45665 | E9: 23686.692 | F9: 5.90096 | G9: 4.6665587 | H9: 22.774167 | I9: 0.8276 | J9: =E9/24/M9 -> 0.20467555 | K9: 40.4263 | L9: 40.4263 | M9: 4822
A10: Kanja | B10: 45666 | E10: 23974.132 | F10: 5.97003 | G10: 4.7177087 | H10: 22.23 | I10: 0.8282 | J10: =E10/24/M10 -> 0.2071593 | K10: 40.1721 | L10: 40.1721 | M10: 4822
A11: Kanja | B11: 45667 | E11: 24191.272 | F11: 6.03196 | G11: 4.7673159 | H11: 22.38875 | I11: 0.8274 | J11: =E11/24/M11 -> 0.2090356 | K11: 40.5892 | L11: 40.5892 | M11: 4822
A12: Kanja | B12: 45668 | E12: 24730.552 | F12: 6.19892 | G12: 4.9104998 | H12: 23.040417 | I12: 0.8237 | J12: =E12/24/M12 -> 0.21369549 | K12: 41.8787 | L12: 41.8787 | M12: 4822
A13: Kanja | B13: 45669 | E13: 24236.612 | F13: 5.97777 | G13: 4.749791 | H13: 19.702917 | I13: 0.8372 | J13: =E13/24/M13 -> 0.20942738 | K13: 37.4108 | L13: 37.4108 | M13: 4822
... A366: Kanja | B366: 46022 | E366: 21626.042 | F366: 5.4422333 | G366: 4.2868251 | H366: 25.557083 | I366: 0.8152 | J366: =E366/24/M366 -> 0.18686957 | K366: 40.758727 | L366: 40.758727 | M366: 4822

Sheet E-Mail_Copy
A1: Plant_Performance_of_Kanja_GJ
B3: =DATE(YEAR(B4),MONTH(B4),1) -> 46143 | C3: =VLOOKUP(L3,[1]Basic_Data!$A$28:$B$48,2,0) -> 45748 | L3: 25-26
A4: Date | B4: 46173 | C4: AC Capacity: | E4: =Basic_Data!G18 -> 4125 | F4: DC Capacity: | H4: =Basic_Data!H18 -> 4822.16 | I4: D.O.C.: | K4: =Basic_Data!C3 -> 45818
A5: Plant Name | C5: Daily | F5: MTD | I5: YTD
C6: Budgeted | D6: Actual | E6: Variation(%) | F6: Budgeted | G6: Actual | H6: Variation(%) | I6: Budgeted | J6: Actual | K6: Variation(%)
A7: Generation_MW | C7: =SUMIFS(Budgeted_data!$E:$E,Budgeted_data!$B:$B,'E-Mail_Copy'!$B$4) -> 0 | D7: =SUMIFS(Data_Entry!$AB:$AB,Data_Entry!$C:$C,'E-Mail_Copy'!$B$4) -> 22750 | E7: =(D7-C7)/C7 -> #DIV/0! | F7: =SUMIFS(Budgeted_data!$E:$E,Budgeted_data!$B:$B,">="&'E-Mail_Copy'!$B$3,Budgeted_data!$B:$B,"<="&'E-Mail_Copy'!$B$4) -> 0 | G7: =SUMIFS(Data_Entry!$AB:$AB,Data_Entry!$C:$C,">="&'E-Mail_Copy'!$B$3,Data_Entry!$C:$C,"<="&'E-Mail_Copy'!$B$4) -> 795300 | H7: =(G7-F7)/F7 -> #DIV/0! | I7: =SUMIFS(Budgeted_data!$E:$E,Budgeted_data!$B:$B,">="&'E-Mail_Copy'!$C$3,Budgeted_data!$B:$B,"<="&'E-Mail_Copy'!$B$4) -> 5977312.5 | J7: =SUMIFS(Data_Entry!$AB:$AB,Data_Entry!$C:$C,">="&'E-Mail_Copy'!$C$3,Data_Entry!$C:$C,"<="&'E-Mail_Copy'!$B$4) -> 6866600 | K7: =(J7-I7)/I7 -> 0.14877714
A8: GTI (Kwh/m2) | C8: =SUMIFS(Budgeted_data!$F:$F,Budgeted_data!$B:$B,'E-Mail_Copy'!$B$4) -> 0 | D8: =SUMIFS(Data_Entry!$AD:$AD,Data_Entry!$C:$C,'E-Mail_Copy'!B4) -> 4.77 | E8: =(D8-C8)/C8 -> #DIV/0! | F8: =SUMIFS(Budgeted_data!$F:$F,Budgeted_data!$B:$B,">="&'E-Mail_Copy'!$B$3,Budgeted_data!$B:$B,"<="&'E-Mail_Copy'!$B$4) -> 0 | G8: =SUMIFS(Data_Entry!$AD:$AD,Data_Entry!$C:$C,">="&'E-Mail_Copy'!$B$3,Data_Entry!$C:$C,"<="&'E-Mail_Copy'!$B$4) -> 159.04 | H8: =(G8-F8)/F8 -> #DIV/0! | I8: =SUMIFS(Budgeted_data!$F:$F,Budgeted_data!$B:$B,">="&'E-Mail_Copy'!$C$3,Budgeted_data!$B:$B,"<="&'E-Mail_Copy'!$B$4) -> 1508.825 | J8: =SUMIFS(Data_Entry!$AD:$AD,Data_Entry!$C:$C,">="&'E-Mail_Copy'!$C$3,Data_Entry!$C:$C,"<="&'E-Mail_Copy'!$B$4) -> 1115.72 | K8: =(J8-I8)/I8 -> -0.26053719
A9: GHI (Kwh/m2) | C9: =SUMIFS(Budgeted_data!$G:$G,Budgeted_data!$B:$B,'E-Mail_Copy'!$B$4) -> 0 | D9: =SUMIFS(Data_Entry!$AC:$AC,Data_Entry!$C:$C,'E-Mail_Copy'!$B$4) -> 0 | E9: =(D9-C9)/C9 -> #DIV/0! | F9: =SUMIFS(Budgeted_data!$G:$G,Budgeted_data!$B:$B,">="&'E-Mail_Copy'!$B$3,Budgeted_data!$B:$B,"<="&'E-Mail_Copy'!$B$4) -> 0 | G9: =SUMIFS(Data_Entry!$AC:$AC,Data_Entry!$C:$C,">="&'E-Mail_Copy'!$B$3,Data_Entry!$C:$C,"<="&'E-Mail_Copy'!$B$4) -> 0 | H9: =(G9-F9)/F9 -> #DIV/0! | I9: =SUMIFS(Budgeted_data!$G:$G,Budgeted_data!$B:$B,">="&'E-Mail_Copy'!$C$3,Budgeted_data!$B:$B,"<="&'E-Mail_Copy'!$B$4) -> 1435.8387 | J9: =SUMIFS(Data_Entry!$AC:$AC,Data_Entry!$C:$C,">="&'E-Mail_Copy'!$C$3,Data_Entry!$C:$C,"<="&'E-Mail_Copy'!$B$4) -> 0 | K9: =(J9-I9)/I9 -> -1
A10: PR_(%) | C10: =C7/C8/H4 -> #DIV/0! | D10: =D7/D8/H4 -> 0.98905719 | E10: =(D10-C10)/C10 -> #DIV/0! | F10: =F7/F8/H4/(B4-B3+1) -> #DIV/0! | G10: =G7/G8/H4/(B4-B3+1) -> 0.03345194 | H10: =(G10-F10)/F10 -> #DIV/0! | I10: =I7/I8/H4/(($B$4-$C$3)+1) -> 0.0019284832 | J10: =J7/J8/H4/(($B$4-$C$3)+1) -> 0.0029959552 | K10: =(J10-I10)/I10 -> 0.5535293
A11: CUF_(%) | C11: =C7/E4/24 -> 0 | D11: =D7/24/E4 -> 0.22979798 | E11: =(D11-C11)/C11 -> #DIV/0! | F11: =F7/24/E4/(B4-B3+1) -> 0 | G11: =G7/24/E4/(B4-B3+1) -> 0.25913978 | H11: =(G11-F11)/F11 -> #DIV/0! | I11: =I7/24/$E$4/(($B$4-$C$3)+1) -> 0.1417298 | J11: =J7/24/$E$4/(($B$4-$C$3)+1) -> 0.16281595 | K11: =(J11-I11)/I11 -> 0.14877714
A12: Wtd_Module_Temp | C12: =AVERAGEIFS(Budgeted_data!$L:$L,Budgeted_data!$B:$B,'E-Mail_Copy'!$B$4) -> #DIV/0! | D12: =AVERAGEIFS(Data_Entry!$AG:$AG,Data_Entry!$C:$C,'E-Mail_Copy'!$B$4) -> #DIV/0! | E12: =(D12-C12)/C12 -> #DIV/0! | F12: =AVERAGEIFS(Budgeted_data!$L:$L,Budgeted_data!$B:$B,">="&'E-Mail_Copy'!$B$3,Budgeted_data!$B:$B,"<="&'E-Mail_Copy'!$B$4) -> #DIV/0! | G12: =AVERAGEIFS(Data_Entry!$AG:$AG,Data_Entry!$C:$C,">="&'E-Mail_Copy'!$B$3,Data_Entry!$C:$C,"<="&'E-Mail_Copy'!$B$4) -> #DIV/0! | H12: =(G12-F12)/F12 -> #DIV/0! | I12: =AVERAGEIFS(Budgeted_data!$L:$L,Budgeted_data!$B:$B,">="&'E-Mail_Copy'!$C$3,Budgeted_data!$B:$B,"<="&'E-Mail_Copy'!$B$4) -> 40.987154 | J12: =AVERAGEIFS(Data_Entry!$AG:$AG,Data_Entry!$C:$C,">="&'E-Mail_Copy'!$C$3,Data_Entry!$C:$C,"<="&'E-Mail_Copy'!$B$4) -> #DIV/0! | K12: =(J12-I12)/I12 -> #DIV/0!
A13: Ambt._Temp_(0C) | C13: =AVERAGEIFS(Budgeted_data!$H:$H,Budgeted_data!$B:$B,'E-Mail_Copy'!$B$4) -> #DIV/0! | D13: =AVERAGEIFS(Data_Entry!$AE:$AE,Data_Entry!$C:$C,'E-Mail_Copy'!$B$4) -> 33.34 | E13: =(D13-C13)/C13 -> #DIV/0! | F13: =AVERAGEIFS(Budgeted_data!$H:$H,Budgeted_data!$B:$B,">="&'E-Mail_Copy'!$B$3,Budgeted_data!$B:$B,"<="&'E-Mail_Copy'!$B$4) -> #DIV/0! | G13: =AVERAGEIFS(Data_Entry!$AE:$AE,Data_Entry!$C:$C,">="&'E-Mail_Copy'!$B$3,Data_Entry!$C:$C,"<="&'E-Mail_Copy'!$B$4) -> 34.263226 | H13: =(G13-F13)/F13 -> #DIV/0! | I13: =AVERAGEIFS(Budgeted_data!$H:$H,Budgeted_data!$B:$B,">="&'E-Mail_Copy'!$C$3,Budgeted_data!$B:$B,"<="&'E-Mail_Copy'!$B$4) -> 27.906308 | J13: =AVERAGEIFS(Data_Entry!$AE:$AE,Data_Entry!$C:$C,">="&'E-Mail_Copy'!$C$3,Data_Entry!$C:$C,"<="&'E-Mail_Copy'!$B$4) -> 29.529697 | K13: =(J13-I13)/I13 -> 0.058172844

Sheet DGR
A1: Daily_Generation_&_Performance_Report
A3: Inverter_No. | B3: ='E-Mail_Copy'!B4 -> 46173 | C3: =B3+1 -> 46174 | D3: =C3+1 -> 46175 | E3: =D3+1 -> 46176 | F3: =E3+1 -> 46177 | G3: =F3+1 -> 46178 | H3: =G3+1 -> 46179 | I3: =H3+1 -> 46180 | J3: =I3+1 -> 46181 | ... AF3: =AE3+1 -> 46203 | AG3: Total/Avg..
A4: Inv_1 | B4: =IFERROR(VLOOKUP(B$3,Data_Entry!$C:$AB,Data_Entry!$A2,0),"") -> 1570.81 | C4: =IFERROR(VLOOKUP(C$3,Data_Entry!$C:$AB,Data_Entry!$A2,0),"") -> 1624.57 | D4: =IFERROR(VLOOKUP(D$3,Data_Entry!$C:$AB,Data_Entry!$A2,0),"") -> 1230.72 | E4: =IFERROR(VLOOKUP(E$3,Data_Entry!$C:$AB,Data_Entry!$A2,0),"") -> 1649.4 | F4: =IFERROR(VLOOKUP(F$3,Data_Entry!$C:$AB,Data_Entry!$A2,0),"") -> 1308.79 | G4: =IFERROR(VLOOKUP(G$3,Data_Entry!$C:$AB,Data_Entry!$A2,0),"") -> 1592.87 | H4: =IFERROR(VLOOKUP(H$3,Data_Entry!$C:$AB,Data_Entry!$A2,0),"") -> 0 | I4: =IFERROR(VLOOKUP(I$3,Data_Entry!$C:$AB,Data_Entry!$A2,0),"") -> 0 | ... AF4: =IFERROR(VLOOKUP(AF$3,Data_Entry!$C:$AB,Data_Entry!$A2,0),"") -> 0 | AG4: =IFERROR(SUM(B4:AF4),"") -> 8977.16
A5: Inv_2 | B5: =IFERROR(VLOOKUP(B$3,Data_Entry!$C:$AB,Data_Entry!$A3,0),"") -> 1564.48 | C5: =IFERROR(VLOOKUP(C$3,Data_Entry!$C:$AB,Data_Entry!$A3,0),"") -> 1634.93 | D5: =IFERROR(VLOOKUP(D$3,Data_Entry!$C:$AB,Data_Entry!$A3,0),"") -> 1285.78 | E5: =IFERROR(VLOOKUP(E$3,Data_Entry!$C:$AB,Data_Entry!$A3,0),"") -> 1223.33 | F5: =IFERROR(VLOOKUP(F$3,Data_Entry!$C:$AB,Data_Entry!$A3,0),"") -> 1251.58 | G5: =IFERROR(VLOOKUP(G$3,Data_Entry!$C:$AB,Data_Entry!$A3,0),"") -> 1594.63 | H5: =IFERROR(VLOOKUP(H$3,Data_Entry!$C:$AB,Data_Entry!$A3,0),"") -> 0 | I5: =IFERROR(VLOOKUP(I$3,Data_Entry!$C:$AB,Data_Entry!$A3,0),"") -> 0 | ... AF5: =IFERROR(VLOOKUP(AF$3,Data_Entry!$C:$AB,Data_Entry!$A3,0),"") -> 0 | AG5: =IFERROR(SUM(B5:AF5),"") -> 8554.73
A6: Inv_3 | B6: =IFERROR(VLOOKUP(B$3,Data_Entry!$C:$AB,Data_Entry!$A4,0),"") -> 1575.03 | C6: =IFERROR(VLOOKUP(C$3,Data_Entry!$C:$AB,Data_Entry!$A4,0),"") -> 1630.4 | D6: =IFERROR(VLOOKUP(D$3,Data_Entry!$C:$AB,Data_Entry!$A4,0),"") -> 1457.01 | E6: =IFERROR(VLOOKUP(E$3,Data_Entry!$C:$AB,Data_Entry!$A4,0),"") -> 1685.12 | F6: =IFERROR(VLOOKUP(F$3,Data_Entry!$C:$AB,Data_Entry!$A4,0),"") -> 1567.34 | G6: =IFERROR(VLOOKUP(G$3,Data_Entry!$C:$AB,Data_Entry!$A4,0),"") -> 1600.23 | H6: =IFERROR(VLOOKUP(H$3,Data_Entry!$C:$AB,Data_Entry!$A4,0),"") -> 0 | I6: =IFERROR(VLOOKUP(I$3,Data_Entry!$C:$AB,Data_Entry!$A4,0),"") -> 0 | ... AF6: =IFERROR(VLOOKUP(AF$3,Data_Entry!$C:$AB,Data_Entry!$A4,0),"") -> 0 | AG6: =IFERROR(SUM(B6:AF6),"") -> 9515.13
A7: Inv_4 | B7: =IFERROR(VLOOKUP(B$3,Data_Entry!$C:$AB,Data_Entry!$A5,0),"") -> 1580.77 | C7: =IFERROR(VLOOKUP(C$3,Data_Entry!$C:$AB,Data_Entry!$A5,0),"") -> 1625.51 | D7: =IFERROR(VLOOKUP(D$3,Data_Entry!$C:$AB,Data_Entry!$A5,0),"") -> 1491.58 | E7: =IFERROR(VLOOKUP(E$3,Data_Entry!$C:$AB,Data_Entry!$A5,0),"") -> 1733.43 | F7: =IFERROR(VLOOKUP(F$3,Data_Entry!$C:$AB,Data_Entry!$A5,0),"") -> 1571.79 | G7: =IFERROR(VLOOKUP(G$3,Data_Entry!$C:$AB,Data_Entry!$A5,0),"") -> 1601.66 | H7: =IFERROR(VLOOKUP(H$3,Data_Entry!$C:$AB,Data_Entry!$A5,0),"") -> 0 | I7: =IFERROR(VLOOKUP(I$3,Data_Entry!$C:$AB,Data_Entry!$A5,0),"") -> 0 | ... AF7: =IFERROR(VLOOKUP(AF$3,Data_Entry!$C:$AB,Data_Entry!$A5,0),"") -> 0 | AG7: =IFERROR(SUM(B7:AF7),"") -> 9604.74
A8: Inv_5 | B8: =IFERROR(VLOOKUP(B$3,Data_Entry!$C:$AB,Data_Entry!$A6,0),"") -> 1539.11 | C8: =IFERROR(VLOOKUP(C$3,Data_Entry!$C:$AB,Data_Entry!$A6,0),"") -> 1614.91 | D8: =IFERROR(VLOOKUP(D$3,Data_Entry!$C:$AB,Data_Entry!$A6,0),"") -> 1501.86 | E8: =IFERROR(VLOOKUP(E$3,Data_Entry!$C:$AB,Data_Entry!$A6,0),"") -> 1734.76 | F8: =IFERROR(VLOOKUP(F$3,Data_Entry!$C:$AB,Data_Entry!$A6,0),"") -> 1564.08 | G8: =IFERROR(VLOOKUP(G$3,Data_Entry!$C:$AB,Data_Entry!$A6,0),"") -> 1587.14 | H8: =IFERROR(VLOOKUP(H$3,Data_Entry!$C:$AB,Data_Entry!$A6,0),"") -> 0 | I8: =IFERROR(VLOOKUP(I$3,Data_Entry!$C:$AB,Data_Entry!$A6,0),"") -> 0 | ... AF8: =IFERROR(VLOOKUP(AF$3,Data_Entry!$C:$AB,Data_Entry!$A6,0),"") -> 0 | AG8: =IFERROR(SUM(B8:AF8),"") -> 9541.86
A9: Inv_6 | B9: =IFERROR(VLOOKUP(B$3,Data_Entry!$C:$AB,Data_Entry!$A7,0),"") -> 1575.84 | C9: =IFERROR(VLOOKUP(C$3,Data_Entry!$C:$AB,Data_Entry!$A7,0),"") -> 1622.77 | D9: =IFERROR(VLOOKUP(D$3,Data_Entry!$C:$AB,Data_Entry!$A7,0),"") -> 1460.8 | E9: =IFERROR(VLOOKUP(E$3,Data_Entry!$C:$AB,Data_Entry!$A7,0),"") -> 1688.58 | F9: =IFERROR(VLOOKUP(F$3,Data_Entry!$C:$AB,Data_Entry!$A7,0),"") -> 1573.66 | G9: =IFERROR(VLOOKUP(G$3,Data_Entry!$C:$AB,Data_Entry!$A7,0),"") -> 1602.68 | H9: =IFERROR(VLOOKUP(H$3,Data_Entry!$C:$AB,Data_Entry!$A7,0),"") -> 0 | I9: =IFERROR(VLOOKUP(I$3,Data_Entry!$C:$AB,Data_Entry!$A7,0),"") -> 0 | ... AF9: =IFERROR(VLOOKUP(AF$3,Data_Entry!$C:$AB,Data_Entry!$A7,0),"") -> 0 | AG9: =IFERROR(SUM(B9:AF9),"") -> 9524.33
A10: Inv_7 | B10: =IFERROR(VLOOKUP(B$3,Data_Entry!$C:$AB,Data_Entry!$A8,0),"") -> 1574.55 | C10: =IFERROR(VLOOKUP(C$3,Data_Entry!$C:$AB,Data_Entry!$A8,0),"") -> 1631.91 | D10: =IFERROR(VLOOKUP(D$3,Data_Entry!$C:$AB,Data_Entry!$A8,0),"") -> 1490.55 | E10: =IFERROR(VLOOKUP(E$3,Data_Entry!$C:$AB,Data_Entry!$A8,0),"") -> 1724.34 | F10: =IFERROR(VLOOKUP(F$3,Data_Entry!$C:$AB,Data_Entry!$A8,0),"") -> 1564.87 | G10: =IFERROR(VLOOKUP(G$3,Data_Entry!$C:$AB,Data_Entry!$A8,0),"") -> 1584.38 | H10: =IFERROR(VLOOKUP(H$3,Data_Entry!$C:$AB,Data_Entry!$A8,0),"") -> 0 | I10: =IFERROR(VLOOKUP(I$3,Data_Entry!$C:$AB,Data_Entry!$A8,0),"") -> 0 | ... AF10: =IFERROR(VLOOKUP(AF$3,Data_Entry!$C:$AB,Data_Entry!$A8,0),"") -> 0 | AG10: =IFERROR(SUM(B10:AF10),"") -> 9570.6
A11: Inv_8 | B11: =IFERROR(VLOOKUP(B$3,Data_Entry!$C:$AB,Data_Entry!$A9,0),"") -> 1582.79 | C11: =IFERROR(VLOOKUP(C$3,Data_Entry!$C:$AB,Data_Entry!$A9,0),"") -> 1659.98 | D11: =IFERROR(VLOOKUP(D$3,Data_Entry!$C:$AB,Data_Entry!$A9,0),"") -> 1559.32 | E11: =IFERROR(VLOOKUP(E$3,Data_Entry!$C:$AB,Data_Entry!$A9,0),"") -> 1799.98 | F11: =IFERROR(VLOOKUP(F$3,Data_Entry!$C:$AB,Data_Entry!$A9,0),"") -> 1628.2 | G11: =IFERROR(VLOOKUP(G$3,Data_Entry!$C:$AB,Data_Entry!$A9,0),"") -> 1642.05 | H11: =IFERROR(VLOOKUP(H$3,Data_Entry!$C:$AB,Data_Entry!$A9,0),"") -> 0 | I11: =IFERROR(VLOOKUP(I$3,Data_Entry!$C:$AB,Data_Entry!$A9,0),"") -> 0 | ... AF11: =IFERROR(VLOOKUP(AF$3,Data_Entry!$C:$AB,Data_Entry!$A9,0),"") -> 0 | AG11: =IFERROR(SUM(B11:AF11),"") -> 9872.32
A12: Inv_9 | B12: =IFERROR(VLOOKUP(B$3,Data_Entry!$C:$AB,Data_Entry!$A10,0),"") -> 1493.82 | C12: =IFERROR(VLOOKUP(C$3,Data_Entry!$C:$AB,Data_Entry!$A10,0),"") -> 1564.89 | D12: =IFERROR(VLOOKUP(D$3,Data_Entry!$C:$AB,Data_Entry!$A10,0),"") -> 1458.21 | E12: =IFERROR(VLOOKUP(E$3,Data_Entry!$C:$AB,Data_Entry!$A10,0),"") -> 1683.11 | F12: =IFERROR(VLOOKUP(F$3,Data_Entry!$C:$AB,Data_Entry!$A10,0),"") -> 1537.8 | G12: =IFERROR(VLOOKUP(G$3,Data_Entry!$C:$AB,Data_Entry!$A10,0),"") -> 1555.85 | H12: =IFERROR(VLOOKUP(H$3,Data_Entry!$C:$AB,Data_Entry!$A10,0),"") -> 0 | I12: =IFERROR(VLOOKUP(I$3,Data_Entry!$C:$AB,Data_Entry!$A10,0),"") -> 0 | ... AF12: =IFERROR(VLOOKUP(AF$3,Data_Entry!$C:$AB,Data_Entry!$A10,0),"") -> 0 | AG12: =IFERROR(SUM(B12:AF12),"") -> 9293.68
A13: Inv_10 | B13: =IFERROR(VLOOKUP(B$3,Data_Entry!$C:$AB,Data_Entry!$A11,0),"") -> 1494.13 | C13: =IFERROR(VLOOKUP(C$3,Data_Entry!$C:$AB,Data_Entry!$A11,0),"") -> 1578.12 | D13: =IFERROR(VLOOKUP(D$3,Data_Entry!$C:$AB,Data_Entry!$A11,0),"") -> 1449.12 | E13: =IFERROR(VLOOKUP(E$3,Data_Entry!$C:$AB,Data_Entry!$A11,0),"") -> 1672.37 | F13: =IFERROR(VLOOKUP(F$3,Data_Entry!$C:$AB,Data_Entry!$A11,0),"") -> 1534.23 | G13: =IFERROR(VLOOKUP(G$3,Data_Entry!$C:$AB,Data_Entry!$A11,0),"") -> 1556.26 | H13: =IFERROR(VLOOKUP(H$3,Data_Entry!$C:$AB,Data_Entry!$A11,0),"") -> 0 | I13: =IFERROR(VLOOKUP(I$3,Data_Entry!$C:$AB,Data_Entry!$A11,0),"") -> 0 | ... AF13: =IFERROR(VLOOKUP(AF$3,Data_Entry!$C:$AB,Data_Entry!$A11,0),"") -> 0 | AG13: =IFERROR(SUM(B13:AF13),"") -> 9284.23
A14: Inv_11 | B14: =IFERROR(VLOOKUP(B$3,Data_Entry!$C:$AB,Data_Entry!$A12,0),"") -> 1495.98 | C14: =IFERROR(VLOOKUP(C$3,Data_Entry!$C:$AB,Data_Entry!$A12,0),"") -> 1566.52 | D14: =IFERROR(VLOOKUP(D$3,Data_Entry!$C:$AB,Data_Entry!$A12,0),"") -> 1449.37 | E14: =IFERROR(VLOOKUP(E$3,Data_Entry!$C:$AB,Data_Entry!$A12,0),"") -> 1678.1 | F14: =IFERROR(VLOOKUP(F$3,Data_Entry!$C:$AB,Data_Entry!$A12,0),"") -> 1527 | G14: =IFERROR(VLOOKUP(G$3,Data_Entry!$C:$AB,Data_Entry!$A12,0),"") -> 1561.11 | H14: =IFERROR(VLOOKUP(H$3,Data_Entry!$C:$AB,Data_Entry!$A12,0),"") -> 0 | I14: =IFERROR(VLOOKUP(I$3,Data_Entry!$C:$AB,Data_Entry!$A12,0),"") -> 0 | ... AF14: =IFERROR(VLOOKUP(AF$3,Data_Entry!$C:$AB,Data_Entry!$A12,0),"") -> 0 | AG14: =IFERROR(SUM(B14:AF14),"") -> 9278.08
A15: Inv_12 | B15: =IFERROR(VLOOKUP(B$3,Data_Entry!$C:$AB,Data_Entry!$A13,0),"") -> 1506.82 | C15: =IFERROR(VLOOKUP(C$3,Data_Entry!$C:$AB,Data_Entry!$A13,0),"") -> 1564.44 | D15: =IFERROR(VLOOKUP(D$3,Data_Entry!$C:$AB,Data_Entry!$A13,0),"") -> 1435.62 | E15: =IFERROR(VLOOKUP(E$3,Data_Entry!$C:$AB,Data_Entry!$A13,0),"") -> 1695.73 | F15: =IFERROR(VLOOKUP(F$3,Data_Entry!$C:$AB,Data_Entry!$A13,0),"") -> 1531.11 | G15: =IFERROR(VLOOKUP(G$3,Data_Entry!$C:$AB,Data_Entry!$A13,0),"") -> 1562.41 | H15: =IFERROR(VLOOKUP(H$3,Data_Entry!$C:$AB,Data_Entry!$A13,0),"") -> 0 | I15: =IFERROR(VLOOKUP(I$3,Data_Entry!$C:$AB,Data_Entry!$A13,0),"") -> 0 | ... AF15: =IFERROR(VLOOKUP(AF$3,Data_Entry!$C:$AB,Data_Entry!$A13,0),"") -> 0 | AG15: =IFERROR(SUM(B15:AF15),"") -> 9296.13
... A18: Inv_15 | B18: =IFERROR(VLOOKUP(B$3,Data_Entry!$C:$AB,Data_Entry!$A16,0),"") -> 1501.72 | C18: =IFERROR(VLOOKUP(C$3,Data_Entry!$C:$AB,Data_Entry!$A16,0),"") -> 1563.67 | D18: =IFERROR(VLOOKUP(D$3,Data_Entry!$C:$AB,Data_Entry!$A16,0),"") -> 1391.26 | E18: =IFERROR(VLOOKUP(E$3,Data_Entry!$C:$AB,Data_Entry!$A16,0),"") -> 1651.57 | F18: =IFERROR(VLOOKUP(F$3,Data_Entry!$C:$AB,Data_Entry!$A16,0),"") -> 1520.65 | G18: =IFERROR(VLOOKUP(G$3,Data_Entry!$C:$AB,Data_Entry!$A16,0),"") -> 1557.74 | H18: =IFERROR(VLOOKUP(H$3,Data_Entry!$C:$AB,Data_Entry!$A16,0),"") -> 0 | I18: =IFERROR(VLOOKUP(I$3,Data_Entry!$C:$AB,Data_Entry!$A16,0),"") -> 0 | ... AF18: =IFERROR(VLOOKUP(AF$3,Data_Entry!$C:$AB,Data_Entry!$A16,0),"") -> 0 | AG18: =IFERROR(SUM(B18:AF18),"") -> 9186.61
A19: Total_Inverter_(kWh) | B19: =SUM(B4:B18) -> 23074.17 | C19: =SUM(C4:C18) -> 24007.97 | D19: =SUM(D4:D18) -> 21449.81 | E19: =SUM(E4:E18) -> 24895.9 | F19: =SUM(F4:F18) -> 22732.48 | G19: =SUM(G4:G18) -> 23733.56 | H19: =SUM(H4:H18) -> 0 | I19: =SUM(I4:I18) -> 0 | ... AG19: =SUM(AG4:AG18) -> 139893.89
A20: Total_ABT_Meter_Export_(kWh) | B20: =IFERROR(VLOOKUP(B$3,Data_Entry!$C:$AB,22,0)," ") -> 22800 | C20: =IFERROR(VLOOKUP(C$3,Data_Entry!$C:$AB,22,0)," ") -> 23750 | D20: =IFERROR(VLOOKUP(D$3,Data_Entry!$C:$AB,22,0)," ") -> 21250 | E20: =IFERROR(VLOOKUP(E$3,Data_Entry!$C:$AB,22,0)," ") -> 24600 | F20: =IFERROR(VLOOKUP(F$3,Data_Entry!$C:$AB,22,0)," ") -> 22500 | G20: =IFERROR(VLOOKUP(G$3,Data_Entry!$C:$AB,22,0)," ") -> 23500 | H20: =IFERROR(VLOOKUP(H$3,Data_Entry!$C:$AB,22,0)," ") -> 0 | I20: =IFERROR(VLOOKUP(I$3,Data_Entry!$C:$AB,22,0)," ") -> 0 | ... AF20: =IFERROR(VLOOKUP(AF$3,Data_Entry!$C:$AB,22,0)," ") -> 0 | AG20: =IFERROR(VLOOKUP(AG$3,[1]Data_Entry!$C:$AB,14,0)," ")
A21: Total_ABT_Meter_Import_(kWh) | B21: =IFERROR(VLOOKUP(B$3,Data_Entry!$C:$AB,25,0)," ") -> 50 | C21: =IFERROR(VLOOKUP(C$3,Data_Entry!$C:$AB,25,0)," ") -> 50 | D21: =IFERROR(VLOOKUP(D$3,Data_Entry!$C:$AB,25,0)," ") -> 50 | E21: =IFERROR(VLOOKUP(E$3,Data_Entry!$C:$AB,25,0)," ") -> 50 | F21: =IFERROR(VLOOKUP(F$3,Data_Entry!$C:$AB,25,0)," ") -> 50 | G21: =IFERROR(VLOOKUP(G$3,Data_Entry!$C:$AB,25,0)," ") -> 50 | H21: =IFERROR(VLOOKUP(H$3,Data_Entry!$C:$AB,25,0)," ") -> 0 | I21: =IFERROR(VLOOKUP(I$3,Data_Entry!$C:$AB,25,0)," ") -> 0 | ... AF21: =IFERROR(VLOOKUP(AF$3,Data_Entry!$C:$AB,25,0)," ") -> 0 | AG21: =IFERROR(VLOOKUP(AG$3,[1]Data_Entry!$C:$AB,17,0)," ")
A22: Total_ABT_Meter_Net_(kWh) | B22: =IFERROR(VLOOKUP(B$3,Data_Entry!$C:$AB,26,0)," ") -> 22750 | C22: =IFERROR(VLOOKUP(C$3,Data_Entry!$C:$AB,26,0)," ") -> 23700 | D22: =IFERROR(VLOOKUP(D$3,Data_Entry!$C:$AB,26,0)," ") -> 21200 | E22: =IFERROR(VLOOKUP(E$3,Data_Entry!$C:$AB,26,0)," ") -> 24550 | F22: =IFERROR(VLOOKUP(F$3,Data_Entry!$C:$AB,26,0)," ") -> 22450 | G22: =IFERROR(VLOOKUP(G$3,Data_Entry!$C:$AB,26,0)," ") -> 23450 | H22: =IFERROR(VLOOKUP(H$3,Data_Entry!$C:$AB,26,0)," ") -> 0 | I22: =IFERROR(VLOOKUP(I$3,Data_Entry!$C:$AB,26,0)," ") -> 0 | ... AF22: =IFERROR(VLOOKUP(AF$3,Data_Entry!$C:$AB,26,0)," ") -> 0 | AG22: =IFERROR(VLOOKUP(AG$3,[1]Data_Entry!$C:$AB,18,0)," ")
A23: GTI | B23: =IFERROR(VLOOKUP(B$3,Data_Entry!$C:$AB,28,0)," ") | C23: =IFERROR(VLOOKUP(C$3,Data_Entry!$C:$AB,28,0)," ") | D23: =IFERROR(VLOOKUP(D$3,Data_Entry!$C:$AB,28,0)," ") | E23: =IFERROR(VLOOKUP(E$3,Data_Entry!$C:$AB,28,0)," ") | F23: =IFERROR(VLOOKUP(F$3,Data_Entry!$C:$AB,28,0)," ") | G23: =IFERROR(VLOOKUP(G$3,Data_Entry!$C:$AB,28,0)," ") | H23: =IFERROR(VLOOKUP(H$3,Data_Entry!$C:$AB,28,0)," ") | I23: =IFERROR(VLOOKUP(I$3,Data_Entry!$C:$AB,28,0)," ") | ... AF23: =IFERROR(VLOOKUP(AF$3,Data_Entry!$C:$AB,28,0)," ")
A24: GHI | B24: =IFERROR(VLOOKUP(B$3,Data_Entry!$C:$AB,27,0)," ") | C24: =IFERROR(VLOOKUP(C$3,Data_Entry!$C:$AB,27,0)," ") | D24: =IFERROR(VLOOKUP(D$3,Data_Entry!$C:$AB,27,0)," ") | E24: =IFERROR(VLOOKUP(E$3,Data_Entry!$C:$AB,27,0)," ") | F24: =IFERROR(VLOOKUP(F$3,Data_Entry!$C:$AB,27,0)," ") | G24: =IFERROR(VLOOKUP(G$3,Data_Entry!$C:$AB,27,0)," ") | H24: =IFERROR(VLOOKUP(H$3,Data_Entry!$C:$AB,27,0)," ") | I24: =IFERROR(VLOOKUP(I$3,Data_Entry!$C:$AB,27,0)," ") | ... AF24: =IFERROR(VLOOKUP(AF$3,Data_Entry!$C:$AB,27,0)," ")
A25: Module_Temp. | B25: =IFERROR(VLOOKUP(B$3,Data_Entry!$C:$AB,31,0)," ") | C25: =IFERROR(VLOOKUP(C$3,Data_Entry!$C:$AB,31,0)," ") | D25: =IFERROR(VLOOKUP(D$3,Data_Entry!$C:$AB,31,0)," ") | E25: =IFERROR(VLOOKUP(E$3,Data_Entry!$C:$AB,31,0)," ") | F25: =IFERROR(VLOOKUP(F$3,Data_Entry!$C:$AB,31,0)," ") | G25: =IFERROR(VLOOKUP(G$3,Data_Entry!$C:$AB,31,0)," ") | H25: =IFERROR(VLOOKUP(H$3,Data_Entry!$C:$AB,31,0)," ") | I25: =IFERROR(VLOOKUP(I$3,Data_Entry!$C:$AB,31,0)," ") | ... AF25: =IFERROR(VLOOKUP(AF$3,Data_Entry!$C:$AB,31,0)," ")
A26: Ambt._Temp. | B26: =IFERROR(VLOOKUP(B$3,Data_Entry!$C:$AB,29,0)," ") | C26: =IFERROR(VLOOKUP(C$3,Data_Entry!$C:$AB,29,0)," ") | D26: =IFERROR(VLOOKUP(D$3,Data_Entry!$C:$AB,29,0)," ") | E26: =IFERROR(VLOOKUP(E$3,Data_Entry!$C:$AB,29,0)," ") | F26: =IFERROR(VLOOKUP(F$3,Data_Entry!$C:$AB,29,0)," ") | G26: =IFERROR(VLOOKUP(G$3,Data_Entry!$C:$AB,29,0)," ") | H26: =IFERROR(VLOOKUP(H$3,Data_Entry!$C:$AB,29,0)," ") | I26: =IFERROR(VLOOKUP(I$3,Data_Entry!$C:$AB,29,0)," ") | ... AF26: =IFERROR(VLOOKUP(AF$3,Data_Entry!$C:$AB,29,0)," ")
A27: Performance_Ratio_(%) | B27: =IFERROR(B20/B23/(Basic_Data!$H$18),"") | C27: =IFERROR(C20/C23/(Basic_Data!$H$18),"") | D27: =IFERROR(D20/D23/(Basic_Data!$H$18),"") | E27: =IFERROR(E20/E23/(Basic_Data!$H$18),"") | F27: =IFERROR(F20/F23/(Basic_Data!$H$18),"") | G27: =IFERROR(G20/G23/(Basic_Data!$H$18),"") | H27: =IFERROR(H20/H23/(Basic_Data!$H$18),"") | I27: =IFERROR(I20/I23/(Basic_Data!$H$18),"") | ... AF27: =IFERROR(AF20/AF23/(Basic_Data!$H$18),"") | AG27: =IFERROR(AG20/AG23/([1]Basic_Data!$G$10),"")
A28: Capacity_Utilization_Factor_(%) | B28: =IFERROR(B20/(Basic_Data!$G$18*24),"") -> 0.23030303 | C28: =IFERROR(C20/(Basic_Data!$G$18*24),"") -> 0.23989899 | D28: =IFERROR(D20/(Basic_Data!$G$18*24),"") -> 0.21464646 | E28: =IFERROR(E20/(Basic_Data!$G$18*24),"") -> 0.24848485 | F28: =IFERROR(F20/(Basic_Data!$G$18*24),"") -> 0.22727273 | G28: =IFERROR(G20/(Basic_Data!$G$18*24),"") -> 0.23737374 | H28: =IFERROR(H20/(Basic_Data!$G$18*24),"") -> 0 | I28: =IFERROR(I20/(Basic_Data!$G$18*24),"") -> 0 | ... AF28: =IFERROR(AF20/(Basic_Data!$G$18*24),"") -> 0 | AG28: =IFERROR(AG20/([1]Basic_Data!$F$10*24),"")
A29: Aux_Consumption_Line_Loss_(%) | B29: =IFERROR((B19-B20)/B19,"") -> 0.011882118 | C29: =IFERROR((C19-C20)/C19,"") -> 0.010745182 | D29: =IFERROR((D19-D20)/D19,"") -> 0.009315234 | E29: =IFERROR((E19-E20)/E19,"") -> 0.011885491 | F29: =IFERROR((F19-F20)/F19,"") -> 0.010226777 | G29: =IFERROR((G19-G20)/G19,"") -> 0.0098409172 | H29: =IFERROR((H19-H20)/H19,"") | I29: =IFERROR((I19-I20)/I19,"") | ... AG29: =IFERROR((AG19-AG20)/AG19,"")

Sheet Data_Entry
B1: Month | C1: Date | D1: Plant_Up_Time | E1: Plant_Down_Time | F1: Inv_1 | G1: Inv_2 | H1: Inv_3 | I1: Inv_4 | J1: Inv_5 | K1: Inv_6 | L1: Inv_7 | M1: Inv_8 | N1: Inv_9 | O1: Inv_10 | P1: Inv_11 | Q1: Inv_12 | R1: Inv_13 | S1: Inv_14 | T1: Inv_15 | U1: Total Inv Gen kWh | V1: ABT_Initial_Export | W1: ABT_Final_Export | X1: Total_Export | Y1: ABT_Initial_Import | Z1: ABT_Final_Import | AA1: Total_Import | AB1: Net_Gen_kWh | AC1: GHI (kwh/m2) | AD1: GTI (kwh/m2) | AE1: Ambt_Temp_Avg | AF1: Module_Temp_Avg | AG1: Wtd_Module_Temp | AH1: Wind Speed | AI1: Rain_Gaug_MM | AJ1: Weather_Condition
A2: 4 | B2: 45747 | C2: 45747 | U2: =SUM(F2:T2) -> 0 | X2: =MAX((W2-V2)*5000,0) -> 0 | AA2: =MAX((Z2-Y2)*3000,0) -> 0 | AB2: =X2-AA2 -> 0
A3: =A2+1 -> 5 | B3: 45748 | C3: 45748 | U3: =SUM(F3:T3) -> 0 | X3: =MAX((W3-V3)*5000,0) -> 0 | AA3: =MAX((Z3-Y3)*5000,0) -> 0 | AB3: =X3-AA3 -> 0
A4: =A3+1 -> 6 | B4: 45749 | C4: 45749 | U4: =SUM(F4:T4) -> 0 | X4: =MAX((W4-V4)*5000,0) -> 0 | AA4: =MAX((Z4-Y4)*5000,0) -> 0 | AB4: =X4-AA4 -> 0
A5: =A4+1 -> 7 | B5: 45750 | C5: 45750 | U5: =SUM(F5:T5) -> 0 | X5: =MAX((W5-V5)*5000,0) -> 0 | AA5: =MAX((Z5-Y5)*5000,0) -> 0 | AB5: =X5-AA5 -> 0
A6: =A5+1 -> 8 | B6: 45751 | C6: 45751 | U6: =SUM(F6:T6) -> 0 | X6: =MAX((W6-V6)*5000,0) -> 0 | AA6: =MAX((Z6-Y6)*5000,0) -> 0 | AB6: =X6-AA6 -> 0
A7: =A6+1 -> 9 | B7: 45752 | C7: 45752 | U7: =SUM(F7:T7) -> 0 | X7: =MAX((W7-V7)*5000,0) -> 0 | AA7: =MAX((Z7-Y7)*5000,0) -> 0 | AB7: =X7-AA7 -> 0
A8: =A7+1 -> 10 | B8: 45753 | C8: 45753 | U8: =SUM(F8:T8) -> 0 | X8: =MAX((W8-V8)*5000,0) -> 0 | AA8: =MAX((Z8-Y8)*5000,0) -> 0 | AB8: =X8-AA8 -> 0
A9: =A8+1 -> 11 | B9: 45754 | C9: 45754 | U9: =SUM(F9:T9) -> 0 | X9: =MAX((W9-V9)*5000,0) -> 0 | AA9: =MAX((Z9-Y9)*5000,0) -> 0 | AB9: =X9-AA9 -> 0
A10: =A9+1 -> 12 | B10: 45755 | C10: 45755 | U10: =SUM(F10:T10) -> 0 | X10: =MAX((W10-V10)*5000,0) -> 0 | AA10: =MAX((Z10-Y10)*5000,0) -> 0 | AB10: =X10-AA10 -> 0
A11: =A10+1 -> 13 | B11: 45756 | C11: 45756 | U11: =SUM(F11:T11) -> 0 | X11: =MAX((W11-V11)*5000,0) -> 0 | AA11: =MAX((Z11-Y11)*5000,0) -> 0 | AB11: =X11-AA11 -> 0
A12: =A11+1 -> 14 | B12: 45757 | C12: 45757 | U12: =SUM(F12:T12) -> 0 | X12: =MAX((W12-V12)*5000,0) -> 0 | AA12: =MAX((Z12-Y12)*5000,0) -> 0 | AB12: =X12-AA12 -> 0
A13: =A12+1 -> 15 | B13: 45758 | C13: 45758 | U13: =SUM(F13:T13) -> 0 | X13: =MAX((W13-V13)*5000,0) -> 0 | AA13: =MAX((Z13-Y13)*5000,0) -> 0 | AB13: =X13-AA13 -> 0
A14: =A13+1 -> 16 | B14: 45759 | C14: 45759 | U14: =SUM(F14:T14) -> 0 | X14: =MAX((W14-V14)*5000,0) -> 0 | AA14: =MAX((Z14-Y14)*5000,0) -> 0 | AB14: =X14-AA14 -> 0
... A72: =A71+1 -> 74 | B72: 45817 | C72: 45817 | U72: =SUM(F72:T72) -> 0 | X72: =MAX((W72-V72)*5000,0) -> 0 | AA72: =MAX((Z72-Y72)*5000,0) -> 0 | AB72: =X72-AA72 -> 0
A73: =A72+1 -> 75 | B73: 45818 | C73: 45818 | F73: 479.05 | G73: 479.22 | H73: 475.46 | I73: 477.38 | J73: 473.68 | K73: 464.18 | L73: 473.68 | M73: 499.04 | N73: 480.76 | O73: 426.79 | P73: 461.88 | Q73: 482.59 | R73: 461.76 | S73: 483.65 | T73: 483.48 | U73: =SUM(F73:T73) -> 7102.6 | V73: 2.24 | W73: 2.24 | X73: =MAX((W73-V73)*5000,0) -> 0 | Z73: 1.92 | AA73: =MAX((Z73-Y73)*5000,0) -> 9600 | AB73: =X73-AA73 -> -9600
A74: =A73+1 -> 76 | B74: 45819 | C74: 45819 | F74: 1441.56 | G74: 1431.88 | H74: 1462.99 | I74: 1462.12 | J74: 1466.89 | K74: 1458.42 | L74: 1474.14 | M74: 1550.44 | N74: 1524.27 | O74: 1377.49 | P74: 1452.24 | Q74: 1524.69 | R74: 1447.08 | S74: 1514.83 | T74: 1516.35 | U74: =SUM(F74:T74) -> 22105.39 | V74: =W73 -> 2.24 | W74: 6.64 | X74: =MAX((W74-V74)*5000,0) -> 22000 | Y74: =Z73 -> 1.92 | Z74: 1.93 | AA74: =MAX((Z74-Y74)*5000,0) -> 50 | AB74: =X74-AA74 -> 21950
A75: =A74+1 -> 77 | B75: 45820 | C75: 45820 | F75: 1322.33 | G75: 1316.77 | H75: 1341.61 | I75: 1342.62 | J75: 1349.17 | K75: 1336.15 | L75: 1322.88 | M75: 1373.95 | N75: 1374.49 | O75: 1277.89 | P75: 1338.14 | Q75: 1389.75 | R75: 1340.7 | S75: 1395.84 | T75: 1394.87 | U75: =SUM(F75:T75) -> 20217.16 | V75: =W74 -> 6.64 | W75: 10.69 | X75: =MAX((W75-V75)*5000,0) -> 20250 | Y75: =Z74 -> 1.93 | Z75: 1.94 | AA75: =MAX((Z75-Y75)*5000,0) -> 50 | AB75: =X75-AA75 -> 20200
A76: =A75+1 -> 78 | B76: 45821 | C76: 45821 | F76: 843.05 | G76: 830.8 | H76: 824.39 | I76: 832.77 | J76: 839.85 | K76: 822.59 | L76: 842.08 | M76: 870.5 | N76: 879.66 | O76: 829.56 | P76: 791.82 | Q76: 863.33 | R76: 882.6 | S76: 834.56 | T76: 859.88 | U76: =SUM(F76:T76) -> 12647.44 | V76: =W75 -> 10.69 | W76: 13.23 | X76: =MAX((W76-V76)*5000,0) -> 12700 | Y76: =Z75 -> 1.94 | Z76: 1.95 | AA76: =MAX((Z76-Y76)*5000,0) -> 50 | AB76: =X76-AA76 -> 12650
A77: =A76+1 -> 79 | B77: 45822 | C77: 45822 | F77: 1356.34 | G77: 1348.14 | H77: 1384.25 | I77: 1380.56 | J77: 1383.57 | K77: 1376.78 | L77: 1394.83 | M77: 1466.25 | N77: 1451.11 | O77: 1316.87 | P77: 1380.97 | Q77: 1446.66 | R77: 1392.1 | S77: 1439.97 | T77: 1450.45 | U77: =SUM(F77:T77) -> 20968.85 | V77: =W76 -> 13.23 | W77: 17.4 | X77: =MAX((W77-V77)*5000,0) -> 20850 | Y77: =Z76 -> 1.95 | Z77: 1.96 | AA77: =MAX((Z77-Y77)*5000,0) -> 50 | AB77: =X77-AA77 -> 20800
A78: =A77+1 -> 80 | B78: 45823 | C78: 45823 | F78: 964.05 | G78: 923.78 | H78: 969.84 | I78: 970.07 | J78: 879.48 | K78: 939.9 | L78: 988.86 | M78: 988.86 | N78: 988.86 | O78: 988.86 | P78: 988.86 | Q78: 988.86 | R78: 988.86 | S78: 988.86 | T78: 988.86 | U78: =SUM(F78:T78) -> 14546.86 | V78: =W77 -> 17.4 | W78: 20.24 | X78: =MAX((W78-V78)*5000,0) -> 14200 | Y78: =Z77 -> 1.96 | Z78: 1.97 | AA78: =MAX((Z78-Y78)*5000,0) -> 50 | AB78: =X78-AA78 -> 14150
A79: =A78+1 -> 81 | B79: 45824 | C79: 45824 | F79: 129.9 | G79: 133.38 | H79: 133.24 | I79: 130.06 | J79: 128.28 | K79: 135.57 | L79: 130.8 | M79: 134.59 | N79: 138.72 | O79: 125.8 | P79: 121.1 | Q79: 133.85 | R79: 131.45 | S79: 125.76 | T79: 133.95 | U79: =SUM(F79:T79) -> 1966.45 | V79: =W78 -> 20.24 | W79: 20.6 | X79: =MAX((W79-V79)*5000,0) -> 1800 | Y79: =Z78 -> 1.97 | Z79: 1.98 | AA79: =MAX((Z79-Y79)*5000,0) -> 50 | AB79: =X79-AA79 -> 1750
A80: =A79+1 -> 82 | B80: 45825 | C80: 45825 | F80: 317.24 | G80: 317.17 | H80: 305.49 | I80: 314.32 | J80: 316.05 | K80: 300.88 | L80: 175.97 | M80: 317.4 | N80: 326.46 | O80: 314.7 | P80: 313.48 | Q80: 303.31 | R80: 291.84 | S80: 312.94 | T80: 317.24 | U80: =SUM(F80:T80) -> 4544.49 | V80: =W79 -> 20.6 | W80: 21.49 | X80: =MAX((W80-V80)*5000,0) -> 4450 | Y80: =Z79 -> 1.98 | Z80: 1.99 | AA80: =MAX((Z80-Y80)*5000,0) -> 50 | AB80: =X80-AA80 -> 4400
A81: =A80+1 -> 83 | B81: 45826 | C81: 45826 | F81: 396.53 | G81: 389.64 | H81: 374.53 | I81: 357.85 | J81: 387.9 | K81: 395.1 | L81: 376.3 | M81: 404.41 | N81: 396.55 | O81: 357.85 | P81: 376.3 | Q81: 395.1 | R81: 374.53 | S81: 393.4 | T81: 396.53 | U81: =SUM(F81:T81) -> 5772.52 | V81: =W80 -> 21.49 | W81: 22.65 | X81: =MAX((W81-V81)*5000,0) -> 5800 | Y81: =Z80 -> 1.99 | Z81: 2 | AA81: =MAX((Z81-Y81)*5000,0) -> 50 | AB81: =X81-AA81 -> 5750
A82: =A81+1 -> 84 | B82: 45827 | C82: 45827 | F82: 1210.15 | G82: 1215.19 | H82: 1205.25 | I82: 1280.05 | J82: 1213.54 | K82: 1189.09 | L82: 1146.6 | M82: 1265.7 | N82: 1211.62 | O82: 1097.67 | P82: 1154.76 | Q82: 1210.04 | R82: 1155.69 | S82: 1206.69 | T82: 1211.82 | U82: =SUM(F82:T82) -> 17973.86 | V82: =W81 -> 22.65 | W82: 26.23 | X82: =MAX((W82-V82)*5000,0) -> 17900 | Y82: =Z81 -> 2 | Z82: 2.01 | AA82: =MAX((Z82-Y82)*5000,0) -> 50 | AB82: =X82-AA82 -> 17850
A83: =A82+1 -> 85 | B83: 45828 | C83: 45828 | F83: 1071.73 | G83: 1075.4 | H83: 1066.09 | I83: 1067.53 | J83: 1070.69 | K83: 1053.62 | L83: 1012.46 | M83: 1090.43 | N83: 1082.73 | O83: 986.61 | P83: 1032.76 | Q83: 1083.19 | R83: 1038.32 | S83: 1074.73 | T83: 1082.76 | U83: =SUM(F83:T83) -> 15889.05 | V83: =W82 -> 26.23 | W83: 29.39 | X83: =MAX((W83-V83)*5000,0) -> 15800 | Y83: =Z82 -> 2.01 | Z83: 2.02 | AA83: =MAX((Z83-Y83)*5000,0) -> 50 | AB83: =X83-AA83 -> 15750
A84: =A83+1 -> 86 | B84: 45829 | C84: 45829 | F84: 922.1 | G84: 929.23 | H84: 920 | I84: 922.08 | J84: 927 | K84: 907.8 | L84: 873.21 | M84: 962.65 | N84: 930.76 | O84: 859.14 | P84: 885.84 | Q84: 928.28 | R84: 888.35 | S84: 926.41 | T84: 931.52 | U84: =SUM(F84:T84) -> 13714.37 | V84: =W83 -> 29.39 | W84: 32.12 | X84: =MAX((W84-V84)*5000,0) -> 13650 | Y84: =Z83 -> 2.02 | Z84: 2.03 | AA84: =MAX((Z84-Y84)*5000,0) -> 50 | AB84: =X84-AA84 -> 13600
A85: =A84+1 -> 87 | B85: 45830 | C85: 45830 | F85: 500.55 | G85: 553.25 | H85: 549.76 | I85: 546.57 | J85: 548.96 | K85: 542.52 | L85: 545.16 | M85: 569.69 | N85: 555.99 | O85: 553.13 | P85: 551.36 | Q85: 553.07 | R85: 549.58 | S85: 524.02 | T85: 550.7 | U85: =SUM(F85:T85) -> 8194.31 | V85: =W84 -> 32.12 | W85: 33.6 | X85: =MAX((W85-V85)*5000,0) -> 7400 | Y85: =Z84 -> 2.03 | Z85: 2.04 | AA85: =MAX((Z85-Y85)*5000,0) -> 50 | AB85: =X85-AA85 -> 7350
... A100: =A99+1 -> 102 | B100: 45845 | C100: 45845 | F100: 616.7 | G100: 624.06 | H100: 612.45 | I100: 618.66 | J100: 617.18 | K100: 610.24 | L100: 618.41 | M100: 643.9 | N100: 621.6 | O100: 617.7 | P100: 594.46 | Q100: 624.15 | R100: 622.01 | S100: 622.92 | T100: 621.33 | U100: =SUM(F100:T100) -> 9285.77 | V100: =W99 -> 63.89 | W100: 65.75 | X100: =MAX((W100-V100)*5000,0) -> 9300 | Y100: =Z99 -> 2.19 | Z100: 2.2 | AA100: =MAX((Z100-Y100)*5000,0) -> 50 | AB100: =X100-AA100 -> 9250
A101: =A100+1 -> 103 | B101: 45846 | C101: 45846 | F101: 1032.44 | G101: 1050.25 | H101: 1025.72 | I101: 1043.36 | J101: 1040.1 | K101: 1020.6 | L101: 1044.22 | M101: 1089.32 | N101: 1022.56 | O101: 1032.5 | P101: 995.17 | Q101: 1045.45 | R101: 1040.1 | S101: 1042.8 | T101: 1037.63 | U101: =SUM(F101:T101) -> 15562.22 | V101: =W100 -> 65.75 | W101: 68.86 | X101: =MAX((W101-V101)*5000,0) -> 15550 | Y101: =Z100 -> 2.2 | Z101: 2.21 | AA101: =MAX((Z101-Y101)*5000,0) -> 50 | AB101: =X101-AA101 -> 15500 | AE101: 0
A102: =A101+1 -> 104 | B102: 45847 | C102: 45847 | F102: 1470.45 | G102: 1480.93 | H102: 1450.17 | I102: 1470.58 | J102: 1452.51 | K102: 1438.5 | L102: 1465.27 | M102: 1496.76 | N102: 1458.68 | O102: 1466.52 | P102: 1415.2 | Q102: 1486.31 | R102: 1477.36 | S102: 1482.35 | T102: 1466.02 | U102: =SUM(F102:T102) -> 21977.61 | V102: =W101 -> 68.86 | W102: 73.25 | X102: =MAX((W102-V102)*5000,0) -> 21950 | Y102: =Z101 -> 2.21 | Z102: 2.22 | AA102: =MAX((Z102-Y102)*5000,0) -> 50 | AB102: =X102-AA102 -> 21900 | AE102: 0
A103: =A102+1 -> 105 | B103: 45848 | C103: 45848 | F103: 877.65 | G103: 890.62 | H103: 870.65 | I103: 882.7 | J103: 977.77 | K103: 863.4 | L103: 870.9 | M103: 850.95 | N103: 865.8 | O103: 893.71 | P103: 866.58 | Q103: 908.27 | R103: 897.58 | S103: 905.09 | T103: 891.97 | U103: =SUM(F103:T103) -> 13313.64 | V103: =W102 -> 73.25 | W103: 75.93 | X103: =MAX((W103-V103)*5000,0) -> 13400 | Y103: =Z102 -> 2.22 | Z103: 2.25 | AA103: =MAX((Z103-Y103)*5000,0) -> 150 | AB103: =X103-AA103 -> 13250 | AE103: 0
A104: =A103+1 -> 106 | B104: 45849 | C104: 45849 | F104: 778.85 | G104: 763.71 | H104: 734.18 | I104: 755.9 | J104: 751.54 | K104: 736.6 | L104: 750.73 | M104: 785.68 | N104: 772.89 | O104: 764.65 | P104: 737.99 | Q104: 775.39 | R104: 767.07 | S104: 771.62 | T104: 758.49 | U104: =SUM(F104:T104) -> 11405.29 | V104: =W103 -> 75.93 | W104: 78.25 | X104: =MAX((W104-V104)*5000,0) -> 11600 | Y104: =Z103 -> 2.25 | Z104: 2.26 | AA104: =MAX((Z104-Y104)*5000,0) -> 50 | AB104: =X104-AA104 -> 11550 | AE104: 0
A105: =A104+1 -> 107 | B105: 45850 | C105: 45850 | F105: 1297.6 | G105: 1321.5 | H105: 1276.62 | I105: 1316.5 | J105: 1305.2 | K105: 1261.16 | L105: 1253.37 | M105: 1265.09 | N105: 1239.26 | O105: 1309.19 | P105: 1259.83 | Q105: 1293 | R105: 1318.96 | S105: 1319.55 | T105: 1303.81 | U105: =SUM(F105:T105) -> 19340.64 | V105: =W104 -> 78.25 | W105: 82.12 | X105: =MAX((W105-V105)*5000,0) -> 19350 | Y105: =Z104 -> 2.26 | Z105: 2.27 | AA105: =MAX((Z105-Y105)*5000,0) -> 50 | AB105: =X105-AA105 -> 19300 | AE105: 0
A106: =A105+1 -> 108 | B106: 45851 | C106: 45851 | F106: 1093.8 | G106: 1122.93 | H106: 1071.55 | I106: 1115.6 | J106: 1112.18 | K106: 1088.6 | L106: 1110.61 | M106: 1165.57 | N106: 1114.93 | O106: 1107.28 | P106: 1068.59 | Q106: 1119.27 | R106: 1118.61 | S106: 1119.56 | T106: 1099.48 | U106: =SUM(F106:T106) -> 16628.56 | V106: =W105 -> 82.12 | W106: 85.48 | X106: =MAX((W106-V106)*5000,0) -> 16800 | Y106: =Z105 -> 2.27 | Z106: 2.28 | AA106: =MAX((Z106-Y106)*5000,0) -> 50 | AB106: =X106-AA106 -> 16750 | AE106: 0
A107: =A106+1 -> 109 | B107: 45852 | C107: 45852 | D107: 0.27083333 | E107: 0.80208333 | F107: 1412.43 | G107: 1486.07 | H107: 1417.51 | I107: 1480.09 | J107: 1472.92 | K107: 1400.64 | L107: 1346.68 | M107: 1371.07 | N107: 1343.55 | O107: 1434.97 | P107: 1390.1 | Q107: 1396.3 | R107: 1495.66 | S107: 1497.65 | T107: 1490.6 | U107: =SUM(F107:T107) -> 21436.24 | V107: 85.48 | W107: 89.78 | X107: =MAX((W107-V107)*5000,0) -> 21500 | Y107: =Z106 -> 2.28 | Z107: 2.29 | AA107: =MAX((Z107-Y107)*5000,0) -> 50 | AB107: =X107-AA107 -> 21450 | AD107: 3.44 | AE107: 30.32 | AJ107: cloudy
A108: =A107+1 -> 110 | B108: 45853 | C108: 45853 | D108: 0.27083333 | E108: 0.80208333 | F108: 874.24 | G108: 932.25 | H108: 902.78 | I108: 926.12 | J108: 926.17 | K108: 903.03 | L108: 918.08 | M108: 965.1 | N108: 943.59 | O108: 936.4 | P108: 905.23 | Q108: 946.68 | R108: 945.8 | S108: 944.56 | T108: 940.98 | U108: =SUM(F108:T108) -> 13911.01 | V108: =W107 -> 89.78 | W108: 92.58 | X108: =MAX((W108-V108)*5000,0) -> 14000 | Y108: =Z107 -> 2.29 | Z108: 2.3 | AA108: =MAX((Z108-Y108)*5000,0) -> 50 | AB108: =X108-AA108 -> 13950
A109: =A108+1 -> 111 | B109: 45854 | C109: 45854 | D109: 0.27083333 | E109: 0.80208333 | F109: 1578.35 | G109: 1651.2 | H109: 1599.78 | I109: 1640.62 | J109: 1625.99 | K109: 1567.68 | L109: 1486.43 | M109: 1514.96 | N109: 1509.09 | O109: 1671.42 | P109: 1574.64 | Q109: 1624.86 | R109: 1671.68 | S109: 1686.31 | T109: 1682.43 | U109: =SUM(F109:T109) -> 24085.44 | V109: =W108 -> 92.58 | W109: 97.37 | X109: =MAX((W109-V109)*5000,0) -> 23950 | Y109: =Z108 -> 2.3 | Z109: 2.31 | AA109: =MAX((Z109-Y109)*5000,0) -> 50 | AB109: =X109-AA109 -> 23900 | AD109: 4.4 | AE109: 30.74 | AJ109: cloudy
A110: =A109+1 -> 112 | B110: 45855 | C110: 45855 | D110: 0.27083333 | E110: 0.80208333 | F110: 1385.84 | G110: 1464.96 | H110: 1426.46 | I110: 1455.38 | J110: 1447.7 | K110: 1426.77 | L110: 1426.86 | M110: 1499.26 | N110: 1484.44 | O110: 1480.03 | P110: 1417.2 | Q110: 1483.16 | R110: 1485.23 | S110: 1478.18 | T110: 1480.4 | U110: =SUM(F110:T110) -> 21841.87 | V110: =W109 -> 97.37 | W110: 101.75 | X110: =MAX((W110-V110)*5000,0) -> 21900 | Y110: =Z109 -> 2.31 | Z110: 2.33 | AA110: =MAX((Z110-Y110)*5000,0) -> 100 | AB110: =X110-AA110 -> 21800 | AD110: 3.46 | AE110: 31.17 | AJ110: cloudy
A111: =A110+1 -> 113 | B111: 45856 | C111: 45856 | D111: 0.27083333 | E111: 0.80208333 | F111: 1177.37 | G111: 1243.36 | H111: 1221.3 | I111: 1241.29 | J111: 1233.92 | K111: 1229.02 | L111: 1227.34 | M111: 1290.91 | N111: 1263.85 | O111: 1258.41 | P111: 1213.84 | Q111: 1270.1 | R111: 1266.36 | S111: 1270.21 | T111: 1264.68 | U111: =SUM(F111:T111) -> 18671.96 | V111: =W110 -> 101.75 | W111: 105.5 | X111: =MAX((W111-V111)*5000,0) -> 18750 | Y111: =Z110 -> 2.33 | Z111: 2.34 | AA111: =MAX((Z111-Y111)*5000,0) -> 50 | AB111: =X111-AA111 -> 18700 | AD111: 3.13 | AE111: 30.54 | AJ111: cloudy
A112: =A111+1 -> 114 | B112: 45857 | C112: 45857 | D112: 0.28125 | E112: 0.73958333 | F112: 829.54 | G112: 875.34 | H112: 863.93 | I112: 875.24 | J112: 869.62 | K112: 870.99 | L112: 868.14 | M112: 907.59 | N112: 872.93 | O112: 869.8 | P112: 838.68 | Q112: 874.77 | R112: 876.42 | S112: 876.63 | T112: 880.35 | U112: =SUM(F112:T112) -> 13049.97 | V112: =W111 -> 105.5 | W112: 108.11 | X112: =MAX((W112-V112)*5000,0) -> 13050 | Y112: =Z111 -> 2.34 | Z112: 2.35 | AA112: =MAX((Z112-Y112)*5000,0) -> 50 | AB112: =X112-AA112 -> 13000 | AD112: 1.9 | AE112: 29.14 | AJ112: cloudy
A113: =A112+1 -> 115 | B113: 45858 | C113: 45858 | D113: 0.29166667 | E113: 0.82291667 | F113: 801.29 | G113: 844.26 | H113: 837.95 | I113: 845.94 | J113: 839.81 | K113: 846.11 | L113: 843.25 | M113: 880.71 | N113: 844.19 | O113: 840.11 | P113: 811.77 | Q113: 850.29 | R113: 845.7 | S113: 854.58 | T113: 853.6 | U113: =SUM(F113:T113) -> 12639.56 | V113: =W112 -> 108.11 | W113: 110.59 | X113: =MAX((W113-V113)*5000,0) -> 12400 | Y113: =Z112 -> 2.35 | Z113: 2.36 | AA113: =MAX((Z113-Y113)*5000,0) -> 50 | AB113: =X113-AA113 -> 12350 | AD113: 1.81 | AE113: 28.6 | AJ113: cloudy
A114: =A113+1 -> 116 | B114: 45859 | C114: 45859 | D114: 0.28125 | E114: 0.80208333 | F114: 942.02 | G114: 998.09 | H114: 977.43 | I114: 990.96 | J114: 983.96 | K114: 982.46 | L114: 986.94 | M114: 1023.82 | N114: 999.91 | O114: 1003.81 | P114: 958.47 | Q114: 1009.56 | R114: 1007 | S114: 1005.26 | T114: 1005.89 | U114: =SUM(F114:T114) -> 14875.58 | V114: =W113 -> 110.59 | W114: 113.59 | X114: =MAX((W114-V114)*5000,0) -> 15000 | Y114: =Z113 -> 2.36 | Z114: 2.37 | AA114: =MAX((Z114-Y114)*5000,0) -> 50 | AB114: =X114-AA114 -> 14950 | AD114: 2.13 | AE114: 28.75 | AJ114: cloudy
A115: =A114+1 -> 117 | B115: 45860 | C115: 45860 | D115: 0.27083333 | E115: 0.80208333 | F115: 887.1 | G115: 933.71 | H115: 920.8 | I115: 931.11 | J115: 928.64 | K115: 925.54 | L115: 919.92 | M115: 963.09 | N115: 923.32 | O115: 922.93 | P115: 984.09 | Q115: 933.68 | R115: 926.54 | S115: 930.52 | T115: 925.59 | U115: =SUM(F115:T115) -> 13956.58 | V115: =W114 -> 113.59 | W115: 116.35 | X115: =MAX((W115-V115)*5000,0) -> 13800 | Y115: =Z114 -> 2.37 | Z115: 2.38 | AA115: =MAX((Z115-Y115)*5000,0) -> 50 | AB115: =X115-AA115 -> 13750 | AD115: 2.01 | AE115: 28.55 | AJ115: cloudy
A116: =A115+1 -> 118 | B116: 45861 | C116: 45861 | D116: 0.27083333 | E116: 0.79166667 | F116: 1182.7 | G116: 1240.09 | H116: 1222.71 | I116: 1240.4 | J116: 1228.8 | K116: 1224.93 | L116: 1233.55 | M116: 1276.05 | N116: 1236.4 | O116: 1235.05 | P116: 1190.16 | Q116: 1245.08 | R116: 1242.36 | S116: 1251.68 | T116: 1251.16 | U116: =SUM(F116:T116) -> 18501.12 | V116: =W115 -> 116.35 | W116: 120.06 | X116: =MAX((W116-V116)*5000,0) -> 18550 | Y116: =Z115 -> 2.38 | Z116: 2.39 | AA116: =MAX((Z116-Y116)*5000,0) -> 50 | AB116: =X116-AA116 -> 18500 | AD116: 2.89 | AE116: 28.64 | AJ116: cloudy
A117: =A116+1 -> 119 | B117: 45862 | C117: 45862 | D117: 0.27083333 | E117: 0.79166667 | F117: 945.2 | G117: 1000.45 | H117: 983.55 | I117: 998.8 | J117: 991.61 | K117: 989.6 | L117: 990.11 | M117: 1036.61 | N117: 994.81 | O117: 995.88 | P117: 961.82 | Q117: 1001.61 | R117: 999.16 | S117: 997.63 | T117: 996.94 | U117: =SUM(F117:T117) -> 14883.78 | V117: =W116 -> 120.06 | W117: 123.06 | X117: =MAX((W117-V117)*5000,0) -> 15000 | Y117: =Z116 -> 2.39 | Z117: 2.4 | AA117: =MAX((Z117-Y117)*5000,0) -> 50 | AB117: =X117-AA117 -> 14950 | AD117: 2.28 | AE117: 28.38 | AJ117: rainy
A118: =A117+1 -> 120 | B118: 45863 | C118: 45863 | D118: 0.27083333 | E118: 0.80208333 | F118: 995.32 | G118: 1042.84 | H118: 1030.7 | I118: 1039.9 | J118: 1034.7 | K118: 1009.36 | L118: 984.5 | M118: 1011.1 | N118: 992.98 | O118: 1030.63 | P118: 992.09 | Q118: 1011.26 | R118: 1039.97 | S118: 1035.99 | T118: 1036.77 | U118: =SUM(F118:T118) -> 15288.11 | V118: =W117 -> 123.06 | W118: 126.11 | X118: =MAX((W118-V118)*5000,0) -> 15250 | Y118: =Z117 -> 2.4 | Z118: 2.41 | AA118: =MAX((Z118-Y118)*5000,0) -> 50 | AB118: =X118-AA118 -> 15200 | AD118: 2.52 | AE118: 29.33 | AJ118: cloudy
A119: =A118+1 -> 121 | B119: 45864 | C119: 45864 | D119: 0.28125 | E119: 0.8125 | F119: 892.93 | G119: 846.23 | H119: 834.1 | I119: 842.85 | J119: 838.29 | K119: 832.29 | L119: 834.16 | M119: 895.64 | N119: 830.74 | O119: 833.25 | P119: 798.36 | Q119: 840.89 | R119: 836.32 | S119: 835.93 | T119: 835.11 | U119: =SUM(F119:T119) -> 12627.09 | V119: =W118 -> 126.11 | W119: 128.65 | X119: =MAX((W119-V119)*5000,0) -> 12700 | Y119: =Z118 -> 2.41 | Z119: 2.43 | AA119: =MAX((Z119-Y119)*5000,0) -> 100 | AB119: =X119-AA119 -> 12600 | AD119: 1.79 | AE119: 28.04 | AJ119: cloudy
A120: =A119+1 -> 122 | B120: 45865 | C120: 45865 | D120: 0.28125 | E120: 0.8125 | F120: 495.96 | G120: 524.72 | H120: 520 | I120: 523.79 | J120: 517.73 | K120: 519.45 | L120: 522.92 | M120: 540.97 | N120: 517.44 | O120: 518.96 | P120: 497.18 | Q120: 521.93 | R120: 523.61 | S120: 520.56 | T120: 525.04 | U120: =SUM(F120:T120) -> 7790.26 | V120: =W119 -> 128.65 | W120: 130.2 | X120: =MAX((W120-V120)*5000,0) -> 7750 | Y120: =Z119 -> 2.43 | Z120: 2.44 | AA120: =MAX((Z120-Y120)*5000,0) -> 50 | AB120: =X120-AA120 -> 7700 | AD120: 1.09 | AE120: 26.85 | AJ120: rainy
... A142: =A141+1 -> 144 | B142: 45887 | C142: 45887 | D142: 0.29166667 | E142: 0.79166667 | F142: 998.61 | G142: 1057.82 | H142: 1039.82 | I142: 1058.9 | J142: 1050.44 | K142: 1048.64 | L142: 1058.18 | M142: 1045.2 | N142: 1039.14 | O142: 1029.45 | P142: 1060.34 | Q142: 1055.39 | R142: 1047.39 | S142: 1054.55 | T142: 1053.7 | U142: =SUM(F142:T142) -> 15697.57 | V142: =W141 -> 185.04 | W142: 188.16 | X142: =MAX((W142-V142)*5000,0) -> 15600 | Y142: =Z141 -> 2.67 | Z142: 2.68 | AA142: =MAX((Z142-Y142)*5000,0) -> 50 | AB142: =X142-AA142 -> 15550 | AD142: 3.1 | AE142: 30.9 | AJ142: rainy
A143: =A142+1 -> 145 | B143: 45888 | C143: 45888 | U143: =SUM(F143:T143) -> 0 | V143: =W142 -> 188.16 | W143: 191.13 | X143: =MAX((W143-V143)*5000,0) -> 14850 | Y143: =Z142 -> 2.68 | Z143: 2.69 | AA143: =MAX((Z143-Y143)*5000,0) -> 50 | AB143: =X143-AA143 -> 14800
A144: =A143+1 -> 146 | B144: 45889 | C144: 45889 | J144: PLANT MANULLY STOPPED FOR HAVEY RAIN (PLANT WATER LEVEL INCREASE) | U144: =SUM(F144:T144) -> 0 | V144: =W143 -> 191.13 | W144: 191.13 | X144: =MAX((W144-V144)*5000,0) -> 0 | Y144: =Z143 -> 2.69 | Z144: 2.69 | AA144: =MAX((Z144-Y144)*5000,0) -> 0 | AB144: =X144-AA144 -> 0
A145: =A144+1 -> 147 | B145: 45890 | C145: 45890 | U145: =SUM(F145:T145) -> 0 | V145: =W144 -> 191.13 | W145: 191.13 | X145: =MAX((W145-V145)*5000,0) -> 0 | Y145: =Z144 -> 2.69 | Z145: 2.69 | AA145: =MAX((Z145-Y145)*5000,0) -> 0 | AB145: =X145-AA145 -> 0
A146: =A145+1 -> 148 | B146: 45891 | C146: 45891 | H146: PLANT CONTINUE UNDER BREAK DOWN FOR THE WATTER LEVEL INCREASE IN PLANT | U146: =SUM(F146:T146) -> 0 | V146: =W145 -> 191.13 | W146: 191.13 | X146: =MAX((W146-V146)*5000,0) -> 0 | Y146: =Z145 -> 2.69 | Z146: 2.69 | AA146: =MAX((Z146-Y146)*5000,0) -> 0 | AB146: =X146-AA146 -> 0
A147: =A146+1 -> 149 | B147: 45892 | C147: 45892 | U147: =SUM(F147:T147) -> 0 | V147: =W146 -> 191.13 | W147: 191.13 | X147: =MAX((W147-V147)*5000,0) -> 0 | Y147: =Z146 -> 2.69 | Z147: 2.69 | AA147: =MAX((Z147-Y147)*5000,0) -> 0 | AB147: =X147-AA147 -> 0
A148: =A147+1 -> 150 | B148: 45893 | C148: 45893 | U148: =SUM(F148:T148) -> 0 | V148: =W147 -> 191.13 | W148: 191.13 | X148: =MAX((W148-V148)*5000,0) -> 0 | Y148: =Z147 -> 2.69 | Z148: 2.69 | AA148: =MAX((Z148-Y148)*5000,0) -> 0 | AB148: =X148-AA148 -> 0
A149: =A148+1 -> 151 | B149: 45894 | C149: 45894 | U149: =SUM(F149:T149) -> 0 | V149: =W148 -> 191.13 | W149: 191.13 | X149: =MAX((W149-V149)*5000,0) -> 0 | Y149: =Z148 -> 2.69 | Z149: 2.69 | AA149: =MAX((Z149-Y149)*5000,0) -> 0 | AB149: =X149-AA149 -> 0
A150: =A149+1 -> 152 | B150: 45895 | C150: 45895 | U150: =SUM(F150:T150) -> 0 | V150: =W149 -> 191.13 | W150: 191.13 | X150: =MAX((W150-V150)*5000,0) -> 0 | Y150: =Z149 -> 2.69 | Z150: 2.69 | AA150: =MAX((Z150-Y150)*5000,0) -> 0 | AB150: =X150-AA150 -> 0
A151: =A150+1 -> 153 | B151: 45896 | C151: 45896 | U151: =SUM(F151:T151) -> 0 | V151: =W150 -> 191.13 | W151: 191.13 | X151: =MAX((W151-V151)*5000,0) -> 0 | Y151: =Z150 -> 2.69 | Z151: 2.69 | AA151: =MAX((Z151-Y151)*5000,0) -> 0 | AB151: =X151-AA151 -> 0
A152: =A151+1 -> 154 | B152: 45897 | C152: 45897 | U152: =SUM(F152:T152) -> 0 | V152: =W151 -> 191.13 | W152: 191.13 | X152: =MAX((W152-V152)*5000,0) -> 0 | Y152: =Z151 -> 2.69 | Z152: 2.69 | AA152: =MAX((Z152-Y152)*5000,0) -> 0 | AB152: =X152-AA152 -> 0
A153: =A152+1 -> 155 | B153: 45898 | C153: 45898 | U153: =SUM(F153:T153) -> 0 | V153: =W152 -> 191.13 | W153: 191.13 | X153: =MAX((W153-V153)*5000,0) -> 0 | Y153: =Z152 -> 2.69 | Z153: 2.69 | AA153: =MAX((Z153-Y153)*5000,0) -> 0 | AB153: =X153-AA153 -> 0
A154: =A153+1 -> 156 | B154: 45899 | C154: 45899 | F154: 11.61 | G154: 114.39 | K154: 110.8 | L154: 40.45 | Q154: 109.9 | R154: 106.96 | S154: 109.22 | U154: =SUM(F154:T154) -> 603.33 | V154: =W153 -> 191.13 | W154: 191.34 | X154: =MAX((W154-V154)*5000,0) -> 1050 | Y154: =Z153 -> 2.69 | Z154: 2.76 | AA154: =MAX((Z154-Y154)*5000,0) -> 350 | AB154: =X154-AA154 -> 700
A155: =A154+1 -> 157 | B155: 45900 | C155: 45900 | H155: 11 KV LINE TRIPPED FROM GETCO S/S SITE IN EARTH FAULT | U155: =SUM(F155:T155) -> 0 | V155: =W154 -> 191.34 | W155: 191.34 | X155: =MAX((W155-V155)*5000,0) -> 0 | Y155: =Z154 -> 2.76 | AA155: =MAX((Z155-Y155)*5000,0) -> 0 | AB155: =X155-AA155 -> 0
A156: =A155+1 -> 158 | B156: 45901 | C156: 45901 | H156: CONTINUE PLANT UNDER BREAK DOWN FOR Our 11 KV UNDER GROUND CABLE FAULT | U156: =SUM(F156:T156) -> 0 | V156: =W155 -> 191.34 | W156: 191.34 | X156: =MAX((W156-V156)*5000,0) -> 0 | Y156: =Z155 -> 0 | AA156: =MAX((Z156-Y156)*5000,0) -> 0 | AB156: =X156-AA156 -> 0
A157: =A156+1 -> 159 | B157: 45902 | C157: 45902 | U157: =SUM(F157:T157) -> 0 | V157: =W156 -> 191.34 | W157: 191.34 | X157: =MAX((W157-V157)*5000,0) -> 0 | Y157: =Z156 -> 0 | AA157: =MAX((Z157-Y157)*5000,0) -> 0 | AB157: =X157-AA157 -> 0
A158: =A157+1 -> 160 | B158: 45903 | C158: 45903 | U158: =SUM(F158:T158) -> 0 | V158: =W157 -> 191.34 | W158: 191.34 | X158: =MAX((W158-V158)*5000,0) -> 0 | Y158: =Z157 -> 0 | AA158: =MAX((Z158-Y158)*5000,0) -> 0 | AB158: =X158-AA158 -> 0
A159: =A158+1 -> 161 | B159: 45904 | C159: 45904 | U159: =SUM(F159:T159) -> 0 | V159: =W158 -> 191.34 | W159: 191.34 | X159: =MAX((W159-V159)*5000,0) -> 0 | Y159: =Z158 -> 0 | AA159: =MAX((Z159-Y159)*5000,0) -> 0 | AB159: =X159-AA159 -> 0
A160: =A159+1 -> 162 | B160: 45905 | C160: 45905 | U160: =SUM(F160:T160) -> 0 | V160: =W159 -> 191.34 | W160: 191.34 | X160: =MAX((W160-V160)*5000,0) -> 0 | Y160: =Z159 -> 0 | AA160: =MAX((Z160-Y160)*5000,0) -> 0 | AB160: =X160-AA160 -> 0
A161: =A160+1 -> 163 | B161: 45906 | C161: 45906 | U161: =SUM(F161:T161) -> 0 | V161: =W160 -> 191.34 | W161: 191.34 | X161: =MAX((W161-V161)*5000,0) -> 0 | Y161: =Z160 -> 0 | AA161: =MAX((Z161-Y161)*5000,0) -> 0 | AB161: =X161-AA161 -> 0
A162: =A161+1 -> 164 | B162: 45907 | C162: 45907 | U162: =SUM(F162:T162) -> 0 | V162: =W161 -> 191.34 | W162: 191.34 | X162: =MAX((W162-V162)*5000,0) -> 0 | Y162: =Z161 -> 0 | AA162: =MAX((Z162-Y162)*5000,0) -> 0 | AB162: =X162-AA162 -> 0
A163: =A162+1 -> 165 | B163: 45908 | C163: 45908 | U163: =SUM(F163:T163) -> 0 | V163: =W162 -> 191.34 | W163: 191.34 | X163: =MAX((W163-V163)*5000,0) -> 0 | Y163: =Z162 -> 0 | AA163: =MAX((Z163-Y163)*5000,0) -> 0 | AB163: =X163-AA163 -> 0
A164: =A163+1 -> 166 | B164: 45909 | C164: 45909 | G164: 54.67 | H164: 57.4 | L164: 50.95 | Q164: 43.19 | U164: =SUM(F164:T164) -> 206.21 | V164: =W163 -> 191.34 | W164: 191.42 | X164: =MAX((W164-V164)*5000,0) -> 400 | Y164: 2.69 | Z164: 2.77 | AA164: =MAX((Z164-Y164)*5000,0) -> 400 | AB164: =X164-AA164 -> -7.9921847e-11
A165: =A164+1 -> 167 | B165: 45910 | C165: 45910 | G165: 192.75 | H165: 173.37 | L165: 184.06 | Q165: 161.2 | R165: 169.05 | S165: 158.45 | U165: =SUM(F165:T165) -> 1038.88 | V165: =W164 -> 191.42 | W165: 191.71 | X165: =MAX((W165-V165)*5000,0) -> 1450 | Y165: 2.78 | Z165: =Y166 -> 2.79 | AA165: =MAX((Z165-Y165)*5000,0) -> 50 | AB165: =X165-AA165 -> 1400
A166: =A165+1 -> 168 | B166: 45911 | C166: 45911 | G166: 330.97 | H166: 769.06 | L166: 1213.62 | Q166: 331 | R166: 332.24 | S166: 328.75 | U166: =SUM(F166:T166) -> 3305.64 | V166: =W165 -> 191.71 | W166: 192.64 | X166: =MAX((W166-V166)*5000,0) -> 4650 | Y166: 2.79 | Z166: 2.79 | AA166: =MAX((Z166-Y166)*5000,0) -> 0 | AB166: =X166-AA166 -> 4650
A167: =A166+1 -> 169 | B167: 45912 | C167: 45912 | F167: FIRE | G167: 1530.65 | H167: 1148.43 | L167: 1025.43 | M167: FIRE | Q167: 761.75 | R167: 971.2 | S167: 910.2 | U167: =SUM(F167:T167) -> 6347.66 | V167: =W166 -> 192.64 | W167: 194.62 | X167: =MAX((W167-V167)*5000,0) -> 9900 | Y167: 2.81 | Z167: =Y168 -> 2.82 | AA167: =MAX((Z167-Y167)*5000,0) -> 50 | AB167: =X167-AA167 -> 9850
A168: =A167+1 -> 170 | B168: 45913 | C168: 45913 | F168: 464.26 | G168: 1182.21 | H168: 897.34 | I168: 366.43 | K168: 919.44 | L168: 802.08 | M168: 10.38 | Q168: 954.9 | R168: 1031.28 | S168: 1014.41 | U168: =SUM(F168:T168) -> 7642.73 | V168: =W167 -> 194.62 | W168: 196.58 | X168: =MAX((W168-V168)*5000,0) -> 9800 | Y168: 2.82 | Z168: 2.82 | AA168: =MAX((Z168-Y168)*5000,0) -> 0 | AB168: =X168-AA168 -> 9800
A169: =A168+1 -> 171 | B169: 45914 | C169: 45914 | U169: =SUM(F169:T169) -> 0 | V169: =W168 -> 196.58 | W169: 198.66 | X169: =MAX((W169-V169)*5000,0) -> 10400 | Y169: =Z168 -> 2.82 | Z169: =Y170 -> 2.83 | AA169: =MAX((Z169-Y169)*5000,0) -> 50 | AB169: =X169-AA169 -> 10350
A170: =A169+1 -> 172 | B170: 45915 | C170: 45915 | F170: 1240.23 | G170: 1280.32 | H170: 1116.53 | I170: 1274.74 | K170: 1225.05 | L170: 1266.53 | M170: 1321.81 | Q170: 1187.59 | R170: 1272.08 | S170: 1250.41 | U170: =SUM(F170:T170) -> 12435.29 | V170: =W169 -> 198.66 | W170: 201.59 | X170: =MAX((W170-V170)*5000,0) -> 14650 | Y170: 2.83 | Z170: =Y171 -> 2.85 | AA170: =MAX((Z170-Y170)*5000,0) -> 100 | AB170: =X170-AA170 -> 14550
A171: =A170+1 -> 173 | B171: 45916 | C171: 45916 | F171: 1514.4 | G171: 1507.33 | H171: 1451.06 | I171: 1511.81 | K171: 1471.67 | L171: 1495.76 | M171: 1557.86 | Q171: 1419.85 | R171: 1512.87 | S171: 1483.12 | U171: =SUM(F171:T171) -> 14925.73 | V171: =W170 -> 201.59 | W171: 205.13 | X171: =MAX((W171-V171)*5000,0) -> 17700 | Y171: 2.85 | Z171: =Y172 -> 2.86 | AA171: =MAX((Z171-Y171)*5000,0) -> 50 | AB171: =X171-AA171 -> 17650
A172: =A171+1 -> 174 | B172: 45917 | C172: 45917 | F172: 1435.18 | G172: 1430.15 | H172: 1384.95 | I172: 1254.42 | K172: 1399.02 | L172: 1420.41 | M172: 1478.39 | Q172: 1353.94 | R172: 1445.14 | S172: 1426.56 | U172: =SUM(F172:T172) -> 14028.16 | V172: =W171 -> 205.13 | W172: 208.5 | X172: =MAX((W172-V172)*5000,0) -> 16850 | Y172: 2.86 | Z172: =Y173 -> 2.87 | AA172: =MAX((Z172-Y172)*5000,0) -> 50 | AB172: =X172-AA172 -> 16800
A173: =A172+1 -> 175 | B173: 45918 | C173: 45918 | F173: 1743.32 | G173: 1695.58 | H173: 1639.17 | I173: 1699.63 | K173: 1646.89 | L173: 1664.87 | M173: 1749.58 | Q173: 1629.37 | R173: 1727.1 | S173: 1745.17 | U173: =SUM(F173:T173) -> 16940.68 | V173: =W172 -> 208.5 | W173: 212.53 | X173: =MAX((W173-V173)*5000,0) -> 20150 | Y173: 2.87 | Z173: =Y174 -> 2.89 | AA173: =MAX((Z173-Y173)*5000,0) -> 100 | AB173: =X173-AA173 -> 20050
A174: =A173+1 -> 176 | B174: 45919 | C174: 45919 | F174: 1468.1 | G174: 1462.8 | H174: 1414.8 | I174: 1452.43 | K174: 1407.45 | L174: 1447.49 | M174: 1504.36 | N174: 24.97 | Q174: 1377.59 | R174: 1474.34 | S174: 1472.5 | T174: 4 | U174: =SUM(F174:T174) -> 14510.83 | V174: =W173 -> 212.53 | W174: 215.97 | X174: =MAX((W174-V174)*5000,0) -> 17200 | Y174: 2.89 | Z174: =Y175 -> 2.9 | AA174: =MAX((Z174-Y174)*5000,0) -> 50 | AB174: =X174-AA174 -> 17150
A175: =A174+1 -> 177 | B175: 45920 | C175: 45920 | F175: 1191.11 | G175: 1182.45 | H175: 1160.36 | I175: 1168.63 | K175: 1140.1 | L175: 1106.73 | M175: 1156.14 | N175: 1121.78 | P175: 827.52 | Q175: 1113.58 | R175: 1177.27 | S175: 1174.19 | T175: 1180.26 | U175: =SUM(F175:T175) -> 14700.12 | V175: =W174 -> 215.97 | W175: 219.34 | X175: =MAX((W175-V175)*5000,0) -> 16850 | Y175: 2.9 | Z175: =Y176 -> 2.91 | AA175: =MAX((Z175-Y175)*5000,0) -> 50 | AB175: =X175-AA175 -> 16800
A176: =A175+1 -> 178 | B176: 45921 | C176: 45921 | D176: 0.29166667 | E176: 0.77083333 | F176: 1059.81 | G176: 1058.61 | H176: 1033.27 | I176: 1051.12 | K176: 1039.78 | L176: 980.91 | M176: 1090.06 | N176: 1051.78 | P176: 1040.56 | Q176: 1056.41 | R176: 1050.34 | S176: 1070.75 | T176: 1068.78 | U176: =SUM(F176:T176) -> 13652.18 | V176: =W175 -> 219.34 | W176: 222.45 | X176: =MAX((W176-V176)*5000,0) -> 15550 | Y176: 2.91 | Z176: 2.91 | AA176: =MAX((Z176-Y176)*5000,0) -> 0 | AB176: =X176-AA176 -> 15550 | AD176: 3.75 | AE176: 29.49 | AJ176: rainy
A177: =A176+1 -> 179 | B177: 45922 | C177: 45922 | D177: 0.3125 | E177: 0.78125 | F177: 1015.48 | G177: 923.05 | H177: 897.02 | I177: 917.7 | K177: 902.27 | L177: 895.38 | M177: 942.55 | N177: 912.19 | P177: 925.31 | Q177: 914.41 | R177: 922.83 | S177: 926.26 | T177: 926.96 | U177: =SUM(F177:T177) -> 12021.41 | V177: =W176 -> 222.45 | W177: 225.22 | X177: =MAX((W177-V177)*5000,0) -> 13850 | Y177: =Z176 -> 2.91 | Z177: 2.92 | AA177: =MAX((Z177-Y177)*5000,0) -> 50 | AB177: =X177-AA177 -> 13800 | AD177: 3.24 | AE177: 28.81 | AJ177: rainy
A178: =A177+1 -> 180 | B178: 45923 | C178: 45923 | D178: 0.29861111 | E178: 0.79166667 | F178: 1245.34 | G178: 1245.9 | H178: 1224.16 | I178: 1242.6 | K178: 1217.18 | L178: 1230.41 | M178: 1277.98 | N178: 1237.3 | P178: 1242.92 | Q178: 1240.36 | R178: 1245.45 | S178: 1243.54 | T178: 1252.6 | U178: =SUM(F178:T178) -> 16145.74 | V178: =W177 -> 225.22 | W178: 228.92 | X178: =MAX((W178-V178)*5000,0) -> 18500 | Y178: =Z177 -> 2.92 | Z178: 2.93 | AA178: =MAX((Z178-Y178)*5000,0) -> 50 | AB178: =X178-AA178 -> 18450 | AD178: 3.9 | AE178: 30.8 | AJ178: rainy
A179: =A178+1 -> 181 | B179: 45924 | C179: 45924 | D179: 0.28125 | E179: 0.77083333 | F179: 1495.85 | G179: 1494.16 | H179: 1448.61 | I179: 1434.97 | K179: 1350.96 | L179: 1322.51 | M179: 1357.12 | N179: 1287.77 | P179: 1420.06 | Q179: 1481.74 | R179: 1335.22 | S179: 1491.08 | T179: 1427.01 | U179: =SUM(F179:T179) -> 18347.06 | V179: =W178 -> 228.92 | W179: 233.09 | X179: =MAX((W179-V179)*5000,0) -> 20850 | Y179: =Z178 -> 2.93 | Z179: 2.94 | AA179: =MAX((Z179-Y179)*5000,0) -> 50 | AB179: =X179-AA179 -> 20800 | AD179: 2.18 | AE179: 30.36 | AJ179: Sunny
A180: =A179+1 -> 182 | B180: 45925 | C180: 45925 | D180: 0.28611111 | E180: 0.79166667 | F180: 1296.59 | G180: 1275.34 | H180: 1254.53 | I180: 1250.04 | K180: 1162.8 | L180: 1192.8 | M180: 1242.96 | N180: 1159.3 | P180: 1223.84 | Q180: 1245.95 | R180: 1227.56 | S180: 1271.03 | T180: 1241.16 | U180: =SUM(F180:T180) -> 16043.9 | V180: =W179 -> 233.09 | W180: 236.73 | X180: =MAX((W180-V180)*5000,0) -> 18200 | Y180: =Z179 -> 2.94 | Z180: 2.96 | AA180: =MAX((Z180-Y180)*5000,0) -> 100 | AB180: =X180-AA180 -> 18100 | AD180: 4.09 | AE180: 30.8 | AJ180: Sunny
A181: =A180+1 -> 183 | B181: 45926 | C181: 45926 | D181: 0.28125 | E181: 0.77083333 | F181: 1337.79 | G181: 1319.76 | H181: 1311.14 | I181: 1314.76 | K181: 1257.66 | L181: 1307.11 | M181: 1326.31 | N181: 1345.27 | P181: 1268.16 | Q181: 1344.93 | R181: 1346.8 | S181: 1360.55 | T181: 1350.57 | U181: =SUM(F181:T181) -> 17190.81 | V181: =W180 -> 236.73 | W181: 240.67 | X181: =MAX((W181-V181)*5000,0) -> 19700 | Y181: =Z180 -> 2.96 | Z181: 2.97 | AA181: =MAX((Z181-Y181)*5000,0) -> 50 | AB181: =X181-AA181 -> 19650 | AD181: 4.82 | AE181: 32.98 | AJ181: Sunny
A182: =A181+1 -> 184 | B182: 45927 | C182: 45927 | D182: 0.29166667 | E182: 0.75 | F182: 1385.47 | G182: 1387.63 | H182: 1376.92 | I182: 1386.72 | K182: 1358.42 | L182: 1356.84 | M182: 1408.9 | N182: 1350.32 | P182: 1375.78 | Q182: 1373.66 | R182: 1381.05 | S182: 1381.04 | T182: 1387.37 | U182: =SUM(F182:T182) -> 17910.12 | V182: =W181 -> 240.67 | W182: 244.76 | X182: =MAX((W182-V182)*5000,0) -> 20450 | Y182: =Z181 -> 2.97 | Z182: 2.98 | AA182: =MAX((Z182-Y182)*5000,0) -> 50 | AB182: =X182-AA182 -> 20400 | AD182: 4.02 | AE182: 32.09 | AJ182: Sunny
A183: =A182+1 -> 185 | B183: 45928 | C183: 45928 | D183: 0.29166667 | E183: 0.76041667 | F183: 449.34 | G183: 454.48 | H183: 448.84 | I183: 449.66 | K183: 449.61 | L183: 445.91 | M183: 468.1 | N183: 453.91 | O183: 455.34 | P183: 455.45 | Q183: 459.59 | R183: 455.61 | S183: 459.45 | T183: 455.79 | U183: =SUM(F183:T183) -> 6361.08 | V183: =W182 -> 244.76 | W183: 246.13 | X183: =MAX((W183-V183)*5000,0) -> 6850 | Y183: =Z182 -> 2.98 | Z183: 2.99 | AA183: =MAX((Z183-Y183)*5000,0) -> 50 | AB183: =X183-AA183 -> 6800 | AD183: 1.73 | AE183: 28.04 | AJ183: cloudy
A184: =A183+1 -> 186 | B184: 45929 | C184: 45929 | D184: 0.37291667 | E184: 0.77083333 | F184: 432.46 | G184: 433.6 | H184: 431.72 | I184: 429.45 | K184: 428.54 | L184: 424.8 | M184: 435.78 | N184: 440.53 | O184: 441.27 | P184: 442 | Q184: 435.65 | R184: 439.8 | S184: 439.37 | T184: 438.46 | U184: =SUM(F184:T184) -> 6093.43 | V184: =W183 -> 246.13 | W184: 247.42 | X184: =MAX((W184-V184)*5000,0) -> 6450 | Y184: =Z183 -> 2.99 | Z184: 3 | AA184: =MAX((Z184-Y184)*5000,0) -> 50 | AB184: =X184-AA184 -> 6400 | AD184: 1.43 | AE184: 26.65 | AJ184: rainy
A185: =A184+1 -> 187 | B185: 45930 | C185: 45930 | D185: 0.29166667 | E185: 0.77083333 | F185: 561.78 | G185: 565.97 | H185: 563.32 | I185: 561.41 | K185: 561.82 | L185: 557.78 | M185: 582.15 | N185: 562.06 | P185: 561.79 | Q185: 563.03 | R185: 564.66 | S185: 561.18 | T185: 565.7 | U185: =SUM(F185:T185) -> 7332.65 | V185: =W184 -> 247.42 | W185: 249.09 | X185: =MAX((W185-V185)*5000,0) -> 8350 | Y185: =Z184 -> 3 | Z185: 3.01 | AA185: =MAX((Z185-Y185)*5000,0) -> 50 | AB185: =X185-AA185 -> 8300 | AD185: 1.27 | AE185: 24.44 | AJ185: rainy
A186: =A185+1 -> 188 | B186: 45931 | C186: 45931 | D186: 0.28125 | E186: 0.78125 | F186: 588.44 | G186: 595.55 | H186: 591.32 | I186: 580.78 | K186: 560.5 | L186: 547.33 | M186: 554.19 | N186: 531.98 | P186: 576.17 | Q186: 598.81 | R186: 574.68 | S186: 595.02 | T186: 574.18 | U186: =SUM(F186:T186) -> 7468.95 | V186: =W185 -> 249.09 | W186: 250.8 | X186: =MAX((W186-V186)*5000,0) -> 8550 | Y186: =Z185 -> 3.01 | Z186: 3.02 | AA186: =MAX((Z186-Y186)*5000,0) -> 50 | AB186: =X186-AA186 -> 8500 | AD186: 1.61 | AE186: 25.44 | AJ186: rainy
A187: =A186+1 -> 189 | B187: 45932 | C187: 45932 | F187: 542.23 | G187: 542.13 | H187: 536.83 | I187: 536.7 | K187: 535.09 | L187: 533.36 | M187: 552.29 | N187: 535.94 | P187: 536.94 | Q187: 538.96 | R187: 540.32 | S187: 540.15 | T187: 539.79 | U187: =SUM(F187:T187) -> 7010.73 | V187: =W186 -> 250.8 | W187: 252.4 | X187: =MAX((W187-V187)*5000,0) -> 8000 | Y187: =Z186 -> 3.02 | Z187: 3.03 | AA187: =MAX((Z187-Y187)*5000,0) -> 50 | AB187: =X187-AA187 -> 7950
A188: =A187+1 -> 190 | B188: 45933 | C188: 45933 | D188: 0.41666667 | E188: 0.78125 | F188: 1325.21 | G188: 1253.37 | H188: 1291.75 | I188: 1255.35 | K188: 1261.85 | L188: 1224.94 | M188: 1245.29 | N188: 1000.83 | P188: 1109.26 | Q188: 1132.15 | R188: 1170.27 | S188: 1163.24 | T188: 1172.94 | U188: =SUM(F188:T188) -> 15606.45 | V188: =W187 -> 252.4 | W188: 255.94 | X188: =MAX((W188-V188)*5000,0) -> 17700 | Y188: =Z187 -> 3.03 | Z188: 3.04 | AA188: =MAX((Z188-Y188)*5000,0) -> 50 | AB188: =X188-AA188 -> 17650 | AD188: 4.2 | AE188: 31.51 | AJ188: sunny
A189: =A188+1 -> 191 | B189: 45934 | C189: 45934 | D189: 0.28611111 | E189: 0.78125 | F189: 1386.94 | G189: 1379.71 | H189: 1373.11 | I189: 1388.6 | J189: 1239.19 | K189: 1365.64 | L189: 1359.36 | M189: 1425.2 | N189: 1338.51 | P189: 1363.61 | Q189: 1363.55 | R189: 1370.82 | S189: 1362.28 | T189: 1374.65 | U189: =SUM(F189:T189) -> 19091.17 | V189: =W188 -> 255.94 | W189: 259.97 | X189: =MAX((W189-V189)*5000,0) -> 20150 | Y189: =Z188 -> 3.04 | Z189: 3.05 | AA189: =MAX((Z189-Y189)*5000,0) -> 50 | AB189: =X189-AA189 -> 20100 | AD189: 4.19 | AE189: 30.18 | AJ189: sunny
A190: =A189+1 -> 192 | B190: 45935 | C190: 45935 | D190: 0.28125 | E190: 0.78125 | F190: 1309.78 | G190: 1309.74 | H190: 1288.99 | I190: 1308.57 | J190: 1299.52 | K190: 1289.24 | L190: 1306.95 | M190: 1355.07 | N190: 1299.41 | P190: 1298.18 | Q190: 1294.15 | R190: 1299.48 | S190: 1290.45 | T190: 1295.45 | U190: =SUM(F190:T190) -> 18244.98 | V190: =W189 -> 259.97 | W190: 263.85 | X190: =MAX((W190-V190)*5000,0) -> 19400 | Y190: =Z189 -> 3.05 | Z190: 3.06 | AA190: =MAX((Z190-Y190)*5000,0) -> 50 | AB190: =X190-AA190 -> 19350 | AD190: 4.68 | AE190: 28.59 | AJ190: sunny
A191: =A190+1 -> 193 | B191: 45936 | C191: 45936 | D191: 0.28125 | E191: 0.78125 | F191: 1632.42 | G191: 1632 | H191: 1608.72 | I191: 1575.69 | J191: 1588.11 | K191: 1248.78 | L191: 1557.63 | M191: 1610.05 | N191: 1488.94 | P191: 1591.93 | Q191: 1619.77 | R191: 1618.91 | T191: 1614.47 | U191: =SUM(F191:T191) -> 20387.42 | V191: =W190 -> 263.85 | W191: 268.56 | X191: =MAX((W191-V191)*5000,0) -> 23550 | Y191: =Z190 -> 3.06 | Z191: 3.07 | AA191: =MAX((Z191-Y191)*5000,0) -> 50 | AB191: =X191-AA191 -> 23500 | AD191: 4.79 | AE191: 28.95 | AJ191: sunny
A192: =A191+1 -> 194 | B192: 45937 | C192: 45937 | D192: 0.28125 | E192: 0.78125 | F192: 1657.27 | G192: 1660.5 | H192: 1636.14 | I192: 1654.84 | J192: 1649.03 | K192: 1610.57 | L192: 1616.1 | M192: 1690.19 | N192: 1622.87 | P192: 1642.03 | Q192: 1635.55 | R192: 1638.43 | T192: 1656.15 | U192: =SUM(F192:T192) -> 21369.67 | V192: =W191 -> 268.56 | W192: 273.43 | X192: =MAX((W192-V192)*5000,0) -> 24350 | Y192: =Z191 -> 3.07 | Z192: 3.09 | AA192: =MAX((Z192-Y192)*5000,0) -> 100 | AB192: =X192-AA192 -> 24250 | AD192: 4.87 | AE192: 29.89 | AJ192: sunny
...

Sheet Basic_Data
B2: Details_of_Plant | C2: Values | F2: Inverter_Name | G2: AC_Capacity_MW | H2: Connected_DC_MW
B3: D.O.C(DD-MMM-YYY) | C3: 45818 | F3: Inv-1 | G3: 275
B4: Plant_Name | C4: Kanja | F4: Inv-2 | G4: 275
B5: Longitude_Of_Site | C5: 21.62 °N | F5: Inv-3 | G5: 275
B6: Latitude_Of_Site | C6: 70.69 °E | F6: Inv-4 | G6: 275
B7: DC_Capacity_(kWh) | C7: 4.82216 | F7: Inv-5 | G7: 275
B8: AC_Capacity_(kWh) | C8: 4 | F8: Inv-6 | G8: 275
B9: Connected_DC_Capacity | C9: =SUM(H3:H94) -> 4822.16 | F9: Inv-7 | G9: 275
B10: Multiplying_Factor_(MF) | F10: Inv-8 | G10: 275
B11: No._of_Power_Trafo. | C11: Gujrat_Trafo | F11: Inv-9 | G11: 275
B12: Power_Trafo._Make | C12: 2 | F12: Inv-10 | G12: 275
B13: Inverter_Make | C13: Watt_power | F13: Inv-11 | G13: 275
B14: Inverter_Capacity | C14: 0.275 | F14: Inv-12 | G14: 275
B15: No._of_Inverter | C15: 15 | F15: Inv-13 | G15: 275
B16: Module_Make | C16: EMMVEE | F16: Inv-14 | G16: 275
B17: Module_Rating | C17: 545 | F17: Inv-15 | G17: 275
B18: No._of_Strings/Table | C18: 316 | F18: Total | G18: =SUM(G3:G17) -> 4125 | H18: 4822.16
B19: No._Of_Module_In_Table | C19: 28 for Bifacial
B20: Total_Module | C20: 8848
B21: Switch_Yard_Make_Vendors | C21: ABB
B22: Table_Configuration | C22: 2X28
B23: ABT Meter Make

Sheet Module_Cleaning
C2: Water Consumption
A3: Months | B3: Date | C3: Tanker Qty | D3: Consumption (Capacity(Ltr)* Tanker) | E3: TDS (PPM) | F3: Cycle No. | G3: Invt. No | I3: Module | J3: Cleaned | K3: Before Cleaning PR% | L3: After Cleaning PR% | M3: Balance | N3: Remarks
A4: 45747 | B4: 45747
A5: 45748 | B5: 45748
A6: 45749 | B6: 45749
A7: 45750 | B7: 45750
A8: 45751 | B8: 45751
A9: 45752 | B9: 45752
A10: 45753 | B10: 45753
A11: 45754 | B11: 45754
A12: 45755 | B12: 45755
A13: 45756 | B13: 45756
A14: 45757 | B14: 45757
A15: 45758 | B15: 45758
... A103: 45820 | B103: 45820
A104: 45821 | B104: 45821 | C104: 4 | D104: 4000 | F104: 1 | G104: Inv_1 | H104: =IFERROR(VLOOKUP(G104,[2]Basic_Data!$E$2:$I$9,5,0),"") -> 2 | I104: =IFERROR(VLOOKUP($G104,[2]Basic_Data!$E$2:$H$10,4,0),"") -> 616 | J104: 616 | K104: =IFERROR(VLOOKUP($B104-1,[2]Inverter_PR!$B:$I,[2]Module_Cleaning!H104,0),"") | L104: =IFERROR(VLOOKUP($B104+1,[2]Inverter_PR!$B:$I,[2]Module_Cleaning!H104,0),"") | M104: =IFERROR(I104-J104,"") -> 0 | N104: wet cleaning
A105: 45822 | B105: 45822 | F105: 1 | G105: Inv_2 | H105: 3 | I105: 616 | J105: 616 | K105: =IFERROR(VLOOKUP($B105-1,[2]Inverter_PR!$B:$I,[2]Module_Cleaning!H105,0),"") | L105: =IFERROR(VLOOKUP($B105+1,[2]Inverter_PR!$B:$I,[2]Module_Cleaning!H105,0),"") | M105: 0 | N105: wet cleaning
A106: 45823 | B106: 45823 | F106: 1 | G106: Inv_3 | H106: 4 | I106: 616 | J106: 616 | K106: =IFERROR(VLOOKUP($B106-1,[2]Inverter_PR!$B:$I,[2]Module_Cleaning!H106,0),"") | L106: =IFERROR(VLOOKUP($B106+1,[2]Inverter_PR!$B:$I,[2]Module_Cleaning!H106,0),"") | M106: 0 | N106: wet cleaning
A107: 45824 | B107: 45824 | F107: 1 | G107: Inv_4 | H107: 5 | I107: 616 | J107: 616 | K107: =IFERROR(VLOOKUP($B107-1,[2]Inverter_PR!$B:$I,[2]Module_Cleaning!H107,0),"") | L107: =IFERROR(VLOOKUP($B107+1,[2]Inverter_PR!$B:$I,[2]Module_Cleaning!H107,0),"") | M107: 0 | N107: wet cleaning
A108: 45825 | B108: 45825 | C108: 3 | D108: 3000 | F108: 1 | G108: Inv_5 | H108: =IFERROR(VLOOKUP(G108,[2]Basic_Data!$E$2:$I$9,5,0),"") -> 6 | I108: =IFERROR(VLOOKUP($G108,[2]Basic_Data!$E$2:$H$10,4,0),"") -> 644 | J108: 644 | K108: =IFERROR(VLOOKUP($B108-1,[2]Inverter_PR!$B:$I,[2]Module_Cleaning!H108,0),"") | L108: =IFERROR(VLOOKUP($B108+1,[2]Inverter_PR!$B:$I,[2]Module_Cleaning!H108,0),"") | M108: =IFERROR(I108-J108,"") -> 0 | N108: wet cleaning
A109: 45826 | B109: 45826 | F109: 1 | G109: Inv_6 | H109: 7 | I109: =IFERROR(VLOOKUP($G109,[2]Basic_Data!$E$2:$H$10,4,0),"") -> 644 | J109: 644 | K109: =IFERROR(VLOOKUP($B109-1,[2]Inverter_PR!$B:$I,[2]Module_Cleaning!H109,0),"") | L109: =IFERROR(VLOOKUP($B109+1,[2]Inverter_PR!$B:$I,[2]Module_Cleaning!H109,0),"") | M109: =IFERROR(I109-J109,"") -> 0 | N109: wet cleaning
A110: 45827 | B110: 45827
A111: 45828 | B111: 45828
A112: 45829 | B112: 45829
A113: 45830 | B113: 45830
A114: 45831 | B114: 45831
A115: 45832 | B115: 45832
A116: 45833 | B116: 45833
A117: 45834 | B117: 45834
A118: 45835 | B118: 45835
A119: 45836 | B119: 45836
A120: 45837 | B120: 45837
A121: 45838 | B121: 45838
... A138: 45855 | B138: 45855
A139: 45856 | B139: 45856 | C139: 0 | D139: 0 | E139: 0 | F139: 0 | H139: 0 | I139: 0 | J139: 0 | K139: 0 | L139: 0 | M139: =IFERROR(I139-J139,"") -> 0 | N139: No cleaning
A140: 45857 | B140: 45857 | C140: 0 | D140: 0 | E140: 0 | F140: 0 | H140: 0 | I140: 0 | J140: 0 | K140: 0 | L140: 0 | M140: =IFERROR(I140-J140,"") -> 0 | N140: No cleaning
A141: 45858 | B141: 45858 | C141: 0 | D141: 0 | E141: 0 | F141: 0 | H141: 0 | I141: 0 | J141: 0 | K141: 0 | L141: 0 | M141: =IFERROR(I141-J141,"") -> 0 | N141: All module cleaned by rain
A142: 45859 | B142: 45859 | C142: 0 | D142: 0 | E142: 0 | F142: 0 | H142: 0 | I142: 0 | J142: 0 | K142: 0 | L142: 0 | M142: =IFERROR(I142-J142,"") -> 0 | N142: No cleaning
A143: 45860 | B143: 45860 | C143: 0 | D143: 0 | E143: 0 | F143: 0 | H143: 0 | I143: 0 | J143: 0 | K143: 0 | L143: 0 | M143: =IFERROR(I143-J143,"") -> 0 | N143: No cleaning
A144: 45861 | B144: 45861 | C144: 0 | D144: 0 | E144: 0 | F144: 0 | H144: 0 | I144: 0 | J144: 0 | K144: 0 | L144: 0 | M144: =IFERROR(I144-J144,"") -> 0 | N144: All module cleaned by rain
A145: 45862 | B145: 45862 | C145: 0 | D145: 0 | E145: 0 | F145: 0 | H145: 0 | I145: 0 | J145: 0 | K145: 0 | L145: 0 | M145: =IFERROR(I145-J145,"") -> 0 | N145: All module cleaned by rain
A146: 45863 | B146: 45863 | C146: 0 | D146: 0 | E146: 0 | F146: 0 | H146: 0 | I146: 0 | J146: 0 | K146: 0 | L146: 0 | M146: =IFERROR(I146-J146,"") -> 0 | N146: No cleaning
A147: 45864 | B147: 45864 | C147: 0 | D147: 0 | E147: 0 | F147: 0 | H147: 0 | I147: 0 | J147: 0 | K147: 0 | L147: 0 | M147: =IFERROR(I147-J147,"") -> 0 | N147: No cleaning
A148: 45865 | B148: 45865 | C148: 0 | D148: 0 | E148: 0 | F148: 0 | H148: 0 | I148: 0 | J148: 0 | K148: 0 | L148: 0 | M148: =IFERROR(I148-J148,"") -> 0 | N148: All module cleaned by rain
A149: 45866 | B149: 45866 | C149: 0 | D149: 0 | E149: 0 | F149: 0 | H149: 0 | I149: 0 | J149: 0 | K149: 0 | L149: 0 | M149: =IFERROR(I149-J149,"") -> 0 | N149: No cleaning
A150: 45867 | B150: 45867 | C150: 0 | D150: 0 | E150: 0 | F150: 0 | H150: 0 | I150: 0 | J150: 0 | K150: 0 | L150: 0 | M150: =IFERROR(I150-J150,"") -> 0 | N150: No cleaning
... A170: 45887 | B170: 45887 | C170: 0 | D170: 0 | E170: 0 | F170: 0 | H170: 0 | I170: 0 | J170: 0 | K170: 0 | L170: 0 | M170: =IFERROR(I170-J170,"") -> 0 | N170: All module cleaned by rain
A171: 45888 | B171: 45888 | H171: =IFERROR(VLOOKUP(G171,[2]Basic_Data!$E$2:$I$9,5,0),"") | I171: =IFERROR(VLOOKUP($G171,[2]Basic_Data!$E$2:$H$10,4,0),"") | K171: =IFERROR(VLOOKUP($B171-1,[2]Inverter_PR!$B:$I,[2]Module_Cleaning!H171,0),"") | L171: =IFERROR(VLOOKUP($B171+1,[2]Inverter_PR!$B:$I,[2]Module_Cleaning!H171,0),"") | M171: =IFERROR(I171-J171,"")
A172: 45889 | B172: 45889 | H172: =IFERROR(VLOOKUP(G172,[2]Basic_Data!$E$2:$I$9,5,0),"") | I172: =IFERROR(VLOOKUP($G172,[2]Basic_Data!$E$2:$H$10,4,0),"") | K172: =IFERROR(VLOOKUP($B172-1,[2]Inverter_PR!$B:$I,[2]Module_Cleaning!H172,0),"") | L172: =IFERROR(VLOOKUP($B172+1,[2]Inverter_PR!$B:$I,[2]Module_Cleaning!H172,0),"") | M172: =IFERROR(I172-J172,"")
A173: 45890 | B173: 45890 | H173: =IFERROR(VLOOKUP(G173,[2]Basic_Data!$E$2:$I$9,5,0),"") | I173: =IFERROR(VLOOKUP($G173,[2]Basic_Data!$E$2:$H$10,4,0),"") | K173: =IFERROR(VLOOKUP($B173-1,[2]Inverter_PR!$B:$I,[2]Module_Cleaning!H173,0),"") | L173: =IFERROR(VLOOKUP($B173+1,[2]Inverter_PR!$B:$I,[2]Module_Cleaning!H173,0),"") | M173: =IFERROR(I173-J173,"")
A174: 45891 | B174: 45891 | H174: =IFERROR(VLOOKUP(G174,[2]Basic_Data!$E$2:$I$9,5,0),"") | I174: =IFERROR(VLOOKUP($G174,[2]Basic_Data!$E$2:$H$10,4,0),"") | K174: =IFERROR(VLOOKUP($B174-1,[2]Inverter_PR!$B:$I,[2]Module_Cleaning!H174,0),"") | L174: =IFERROR(VLOOKUP($B174+1,[2]Inverter_PR!$B:$I,[2]Module_Cleaning!H174,0),"") | M174: =IFERROR(I174-J174,"")
A175: 45892 | B175: 45892 | H175: =IFERROR(VLOOKUP(G175,[2]Basic_Data!$E$2:$I$9,5,0),"") | I175: =IFERROR(VLOOKUP($G175,[2]Basic_Data!$E$2:$H$10,4,0),"") | K175: =IFERROR(VLOOKUP($B175-1,[2]Inverter_PR!$B:$I,[2]Module_Cleaning!H175,0),"") | L175: =IFERROR(VLOOKUP($B175+1,[2]Inverter_PR!$B:$I,[2]Module_Cleaning!H175,0),"") | M175: =IFERROR(I175-J175,"")
A176: 45893 | B176: 45893 | H176: =IFERROR(VLOOKUP(G176,[2]Basic_Data!$E$2:$I$9,5,0),"") | I176: =IFERROR(VLOOKUP($G176,[2]Basic_Data!$E$2:$H$10,4,0),"") | K176: =IFERROR(VLOOKUP($B176-1,[2]Inverter_PR!$B:$I,[2]Module_Cleaning!H176,0),"") | L176: =IFERROR(VLOOKUP($B176+1,[2]Inverter_PR!$B:$I,[2]Module_Cleaning!H176,0),"") | M176: =IFERROR(I176-J176,"")
A177: 45894 | B177: 45894 | H177: =IFERROR(VLOOKUP(G177,[2]Basic_Data!$E$2:$I$9,5,0),"") | I177: =IFERROR(VLOOKUP($G177,[2]Basic_Data!$E$2:$H$10,4,0),"") | K177: =IFERROR(VLOOKUP($B177-1,[2]Inverter_PR!$B:$I,[2]Module_Cleaning!H177,0),"") | L177: =IFERROR(VLOOKUP($B177+1,[2]Inverter_PR!$B:$I,[2]Module_Cleaning!H177,0),"") | M177: =IFERROR(I177-J177,"")
A178: 45895 | B178: 45895 | H178: =IFERROR(VLOOKUP(G178,[2]Basic_Data!$E$2:$I$9,5,0),"") | I178: =IFERROR(VLOOKUP($G178,[2]Basic_Data!$E$2:$H$10,4,0),"") | K178: =IFERROR(VLOOKUP($B178-1,[2]Inverter_PR!$B:$I,[2]Module_Cleaning!H178,0),"") | L178: =IFERROR(VLOOKUP($B178+1,[2]Inverter_PR!$B:$I,[2]Module_Cleaning!H178,0),"") | M178: =IFERROR(I178-J178,"")
A179: 45896 | B179: 45896 | H179: =IFERROR(VLOOKUP(G179,[2]Basic_Data!$E$2:$I$9,5,0),"") | I179: =IFERROR(VLOOKUP($G179,[2]Basic_Data!$E$2:$H$10,4,0),"") | K179: =IFERROR(VLOOKUP($B179-1,[2]Inverter_PR!$B:$I,[2]Module_Cleaning!H179,0),"") | L179: =IFERROR(VLOOKUP($B179+1,[2]Inverter_PR!$B:$I,[2]Module_Cleaning!H179,0),"") | M179: =IFERROR(I179-J179,"")
A180: 45897 | B180: 45897 | H180: =IFERROR(VLOOKUP(G180,[2]Basic_Data!$E$2:$I$9,5,0),"") | I180: =IFERROR(VLOOKUP($G180,[2]Basic_Data!$E$2:$H$10,4,0),"") | K180: =IFERROR(VLOOKUP($B180-1,[2]Inverter_PR!$B:$I,[2]Module_Cleaning!H180,0),"") | L180: =IFERROR(VLOOKUP($B180+1,[2]Inverter_PR!$B:$I,[2]Module_Cleaning!H180,0),"") | M180: =IFERROR(I180-J180,"")
A181: 45898 | B181: 45898 | H181: =IFERROR(VLOOKUP(G181,[2]Basic_Data!$E$2:$I$9,5,0),"") | I181: =IFERROR(VLOOKUP($G181,[2]Basic_Data!$E$2:$H$10,4,0),"") | K181: =IFERROR(VLOOKUP($B181-1,[2]Inverter_PR!$B:$I,[2]Module_Cleaning!H181,0),"") | L181: =IFERROR(VLOOKUP($B181+1,[2]Inverter_PR!$B:$I,[2]Module_Cleaning!H181,0),"") | M181: =IFERROR(I181-J181,"")
A182: 45899 | B182: 45899 | H182: =IFERROR(VLOOKUP(G182,[2]Basic_Data!$E$2:$I$9,5,0),"") | I182: =IFERROR(VLOOKUP($G182,[2]Basic_Data!$E$2:$H$10,4,0),"") | K182: =IFERROR(VLOOKUP($B182-1,[2]Inverter_PR!$B:$I,[2]Module_Cleaning!H182,0),"") | L182: =IFERROR(VLOOKUP($B182+1,[2]Inverter_PR!$B:$I,[2]Module_Cleaning!H182,0),"") | M182: =IFERROR(I182-J182,"")
... A205: 45922 | B205: 45922 | H205: =IFERROR(VLOOKUP(G205,[2]Basic_Data!$E$2:$I$9,5,0),"") | I205: =IFERROR(VLOOKUP($G205,[2]Basic_Data!$E$2:$H$10,4,0),"") | K205: =IFERROR(VLOOKUP($B205-1,[2]Inverter_PR!$B:$I,[2]Module_Cleaning!H205,0),"") | L205: =IFERROR(VLOOKUP($B205+1,[2]Inverter_PR!$B:$I,[2]Module_Cleaning!H205,0),"") | M205: =IFERROR(I205-J205,"")
A206: 45923 | B206: 45923 | C206: 0 | D206: 0 | E206: 0 | F206: 0 | H206: 0 | I206: 0 | J206: 0 | K206: 0 | L206: 0 | M206: =IFERROR(I206-J206,"") -> 0 | N206: All module cleaned by rain
A207: 45924 | B207: 45924 | C207: 0 | D207: 0 | E207: 0 | F207: 0 | H207: 0 | I207: 0 | J207: 0 | K207: 0 | L207: 0 | M207: =IFERROR(I207-J207,"") -> 0 | N207: No cleaning
A208: 45925 | B208: 45925 | C208: 0 | D208: 0 | E208: 0 | F208: 0 | H208: 0 | I208: 0 | J208: 0 | K208: 0 | L208: 0 | M208: =IFERROR(I208-J208,"") -> 0 | N208: No cleaning
A209: 45926 | B209: 45926 | C209: 0 | D209: 0 | E209: 0 | F209: 0 | H209: 0 | I209: 0 | J209: 0 | K209: 0 | L209: 0 | M209: =IFERROR(I209-J209,"") -> 0 | N209: No cleaning
A210: 45927 | B210: 45927 | C210: 0 | D210: 0 | E210: 0 | F210: 0 | H210: 0 | I210: 0 | J210: 0 | K210: 0 | L210: 0 | M210: =IFERROR(I210-J210,"") -> 0 | N210: No cleaning
A211: 45928 | B211: 45928 | C211: 0 | D211: 0 | E211: 0 | F211: 0 | H211: 0 | I211: 0 | J211: 0 | K211: 0 | L211: 0 | M211: =IFERROR(I211-J211,"") -> 0 | N211: All module cleaned by rain
A212: 45929 | B212: 45929 | C212: 0 | D212: 0 | E212: 0 | F212: 0 | H212: 0 | I212: 0 | J212: 0 | K212: 0 | L212: 0 | M212: =IFERROR(I212-J212,"") -> 0 | N212: All module cleaned by rain
A213: 45930 | B213: 45930 | C213: 0 | D213: 0 | E213: 0 | F213: 0 | H213: 0 | I213: 0 | J213: 0 | K213: 0 | L213: 0 | M213: =IFERROR(I213-J213,"") -> 0 | N213: No cleaning
A214: 45931 | B214: 45931 | C214: 0 | D214: 0 | E214: 0 | F214: 0 | H214: 0 | I214: 0 | J214: 0 | K214: 0 | L214: 0 | M214: =IFERROR(I214-J214,"") -> 0 | N214: No cleaning
A215: 45932 | B215: 45932 | C215: 0 | D215: 0 | E215: 0 | F215: 0 | H215: 0 | I215: 0 | J215: 0 | K215: 0 | L215: 0 | M215: =IFERROR(I215-J215,"") -> 0 | N215: No cleaning
A216: 45933 | B216: 45933 | C216: 0 | D216: 0 | E216: 0 | F216: 0 | H216: 0 | I216: 0 | J216: 0 | K216: 0 | L216: 0 | M216: =IFERROR(I216-J216,"") -> 0 | N216: No cleaning
A217: 45934 | B217: 45934 | C217: 0 | D217: 0 | E217: 0 | F217: 0 | H217: 0 | I217: 0 | J217: 0 | K217: 0 | L217: 0 | M217: =IFERROR(I217-J217,"") -> 0 | N217: No cleaning
... A229: 45946 | B229: 45946 | C229: 0 | D229: 0 | E229: 0 | F229: 0 | H229: 0 | I229: 0 | J229: 0 | K229: 0 | L229: 0 | M229: =IFERROR(I229-J229,"") -> 0 | N229: No cleaning
A230: 45947 | B230: 45947 | C230: 0 | D230: 0 | F230: 0 | H230: 0 | I230: 0 | J230: 0 | K230: 0 | L230: 0 | M230: =IFERROR(I230-J230,"") -> 0
A231: 45948 | B231: 45948 | C231: 0 | D231: 0 | E231: 0 | F231: 1 | G231: Inv_1 | H231: =IFERROR(VLOOKUP(G231,[2]Basic_Data!$E$2:$I$9,5,0),"") -> 2 | I231: =IFERROR(VLOOKUP($G231,[2]Basic_Data!$E$2:$H$10,4,0),"") -> 616 | J231: 0 | K231: 0 | L231: 0 | M231: =IFERROR(I231-J231,"") -> 616 | N231: robat cleanig
A232: 45949 | B232: 45949 | F232: 1 | G232: Inv_2 | H232: =IFERROR(VLOOKUP(G232,[2]Basic_Data!$E$2:$I$9,5,0),"") -> 3 | I232: =IFERROR(VLOOKUP($G232,[2]Basic_Data!$E$2:$H$10,4,0),"") -> 616 | J232: 0 | K232: 0 | L232: 0 | M232: =IFERROR(I232-J232,"") -> 616 | N232: robat cleanig
A233: 45950 | B233: 45950 | F233: 1 | G233: Inv_3 | H233: =IFERROR(VLOOKUP(G233,[2]Basic_Data!$E$2:$I$9,5,0),"") -> 4 | I233: =IFERROR(VLOOKUP($G233,[2]Basic_Data!$E$2:$H$10,4,0),"") -> 616 | J233: 0 | K233: 0 | L233: 0 | M233: =IFERROR(I233-J233,"") -> 616 | N233: robat cleanig
A234: 45951 | B234: 45951 | F234: 1 | G234: Inv_4 | H234: =IFERROR(VLOOKUP(G234,[2]Basic_Data!$E$2:$I$9,5,0),"") -> 5 | I234: =IFERROR(VLOOKUP($G234,[2]Basic_Data!$E$2:$H$10,4,0),"") -> 644 | J234: 0 | K234: 0 | L234: 0 | M234: =IFERROR(I234-J234,"") -> 644 | N234: robat cleanig
A235: 45952 | B235: 45952 | F235: 1 | G235: Inv_5 | H235: =IFERROR(VLOOKUP(G235,[2]Basic_Data!$E$2:$I$9,5,0),"") -> 6 | I235: =IFERROR(VLOOKUP($G235,[2]Basic_Data!$E$2:$H$10,4,0),"") -> 644 | J235: 0 | K235: 0 | L235: 0 | M235: =IFERROR(I235-J235,"") -> 644 | N235: robat cleanig
A236: 45953 | B236: 45953 | F236: 1 | G236: Inv_6 | H236: =IFERROR(VLOOKUP(G236,[2]Basic_Data!$E$2:$I$9,5,0),"") -> 7 | I236: =IFERROR(VLOOKUP($G236,[2]Basic_Data!$E$2:$H$10,4,0),"") -> 644 | J236: 0 | K236: 0 | L236: 0 | M236: =IFERROR(I236-J236,"") -> 644 | N236: robat cleanig
A237: 45954 | B237: 45954 | F237: 1 | G237: Inv_7 | H237: =IFERROR(VLOOKUP(G237,[2]Basic_Data!$E$2:$I$9,5,0),"") -> 8 | I237: =IFERROR(VLOOKUP($G237,[2]Basic_Data!$E$2:$H$10,4,0),"") -> 644 | J237: 0 | K237: 0 | L237: 0 | M237: =IFERROR(I237-J237,"") -> 644 | N237: robat cleanig
A238: 45955 | B238: 45955 | C238: 0 | D238: 0 | E238: 0 | F238: 0 | H238: 0 | I238: 0 | J238: 0 | K238: 0 | L238: 0 | M238: =IFERROR(I238-J238,"") -> 0 | N238: No cleaning
A239: 45956 | B239: 45956 | C239: 0 | D239: 0 | E239: 0 | F239: 0 | H239: 0 | I239: 0 | J239: 0 | K239: 0 | L239: 0 | M239: =IFERROR(I239-J239,"") -> 0 | N239: No cleaning
A240: 45957 | B240: 45957 | C240: 0 | D240: 0 | E240: 0 | F240: 0 | H240: 0 | I240: 0 | J240: 0 | K240: 0 | L240: 0 | M240: =IFERROR(I240-J240,"") -> 0 | N240: All module cleaned by rain
A241: 45958 | B241: 45958 | C241: 0 | D241: 0 | E241: 0 | F241: 0 | H241: 0 | I241: 0 | J241: 0 | K241: 0 | L241: 0 | M241: =IFERROR(I241-J241,"") -> 0 | N241: All module cleaned by rain
A242: 45959 | B242: 45959 | C242: 0 | D242: 0 | E242: 0 | F242: 0 | H242: 0 | I242: 0 | J242: 0 | K242: 0 | L242: 0 | M242: =IFERROR(I242-J242,"") -> 0 | N242: No cleaning
A243: 45960 | B243: 45960 | C243: 0 | D243: 0 | E243: 0 | F243: 0 | H243: 0 | I243: 0 | J243: 0 | K243: 0 | L243: 0 | M243: =IFERROR(I243-J243,"") -> 0 | N243: All module cleaned by rain
A244: 45961 | B244: 45961 | C244: 0 | D244: 0 | E244: 0 | F244: 0 | H244: 0 | I244: 0 | J244: 0 | K244: 0 | L244: 0 | M244: =IFERROR(I244-J244,"") -> 0 | N244: No cleaning
A245: 45962 | B245: 45962 | C245: 0 | D245: 0 | E245: 0 | F245: 0 | H245: 0 | I245: 0 | J245: 0 | K245: 0 | L245: 0 | M245: =IFERROR(I245-J245,"") -> 0 | N245: No cleaning
A246: 45963 | B246: 45963 | C246: 0 | D246: 0 | E246: 0 | F246: 0 | H246: 0 | I246: 0 | J246: 0 | K246: 0 | L246: 0 | M246: =IFERROR(I246-J246,"") -> 0 | N246: No cleaning
A247: 45964 | B247: 45964 | C247: 0 | D247: 0 | E247: 0 | F247: 0 | H247: 0 | I247: 0 | J247: 0 | K247: 0 | L247: 0 | M247: =IFERROR(I247-J247,"") -> 0 | N247: No cleaning
A248: 45965 | B248: 45965 | C248: 0 | D248: 0 | E248: 0 | F248: 0 | H248: 0 | I248: 0 | J248: 0 | K248: 0 | L248: 0 | M248: =IFERROR(I248-J248,"") -> 0 | N248: No cleaning
A249: 45966 | B249: 45966 | C249: 0 | D249: 0 | E249: 0 | F249: 0 | H249: 0 | I249: 0 | J249: 0 | K249: 0 | L249: 0 | M249: =IFERROR(I249-J249,"") -> 0 | N249: No cleaning
A250: 45967 | B250: 45967 | C250: 0 | D250: 0 | E250: 0 | F250: 1 | G250: Inv_1 | H250: =IFERROR(VLOOKUP(G250,[2]Basic_Data!$E$2:$I$9,5,0),"") -> 2 | I250: 588 | J250: 588 | K250: 0 | L250: 0 | M250: =IFERROR(I250-J250,"") -> 0 | N250: robat cleanig
F251: 1 | G251: Inv_2 | H251: 3 | I251: 588 | J251: 588 | K251: 0 | L251: 0 | M251: =IFERROR(I251-J251,"") -> 0 | N251: robat cleanig
A252: 45968 | B252: 45968 | F252: 1 | G252: Inv_3 | H252: =IFERROR(VLOOKUP(G252,[2]Basic_Data!$E$2:$I$9,5,0),"") -> 4 | I252: 588 | J252: 588 | K252: 0 | L252: 0 | M252: =IFERROR(I252-J252,"") -> 0 | N252: robat cleanig
F253: 1 | G253: Inv_4 | H253: 5 | I253: 588 | J253: 588 | K253: 0 | L253: 0 | M253: =IFERROR(I253-J253,"") -> 0 | N253: robat cleanig
A254: 45969 | B254: 45969 | F254: 1 | G254: Inv_5 | H254: =IFERROR(VLOOKUP(G254,[2]Basic_Data!$E$2:$I$9,5,0),"") -> 6 | I254: 588 | J254: 588 | K254: 0 | L254: 0 | M254: =IFERROR(I254-J254,"") -> 0 | N254: robat cleanig
F255: 1 | G255: Inv_6 | H255: =IFERROR(VLOOKUP(G255,[2]Basic_Data!$E$2:$I$9,5,0),"") -> 7 | I255: 588 | J255: 588 | K255: 0 | L255: 0 | M255: =IFERROR(I255-J255,"") -> 0 | N255: robat cleanig
A256: 45970 | B256: 45970 | F256: 1 | G256: Inv_7 | H256: =IFERROR(VLOOKUP(G256,[2]Basic_Data!$E$2:$I$9,5,0),"") -> 8 | I256: 588 | J256: 588 | K256: 0 | L256: 0 | M256: =IFERROR(I256-J256,"") -> 0 | N256: robat cleanig
...

Sheet WMS
A1: Months | B1: Date | C1: GHI | D1: GTI | E1: Module_Temp | F1: Amb_Temp | G1: Derect_Irr | H1: Diffused_Irr | I1: Wind_Speed | J1: Wind_derection | K1: Rain Gauge

Sheet Plant_Down_Time Details
A1: KANZA Plant_Down_Time Details
A2: Month | B2: Date | C2: Power Trafo | D2: Down_Time_Start | E2: Down_Time_Stop | F2: Total_Down_Time | G2: Affected DC Capacity (in KW) | H2: Component Name | I2: Fault Description | J2: Reason_Of_Down | K2: Purposed Action Plan | L2: Corrective_Action_Taken_By_Site_Team
A3: 45833 | B3: 45827 | C3: 1 | D3: 0.48611111 | E3: 0.52083333 | F3: =E3-D3 -> 0.034722222 | G3: 4 | I3: Earth fault | J3: Do wire burinig | K3: Replace Do wire
A4: 45833 | B4: 45828 | C4: 1 | D4: 0.4875 | E4: 0.51736111 | F4: =E4-D4 -> 0.029861111 | G4: 4 | I4: over current | J4: Do wire burinig | K4: Replace Do wire
A5: 45833 | B5: 45828 | C5: 1 | D5: 0.55555556 | E5: 0.58333333 | F5: =E5-D5 -> 0.027777778 | G5: 4 | I5: over current | J5: Do wire burinig | K5: Replace Do wire | L5: complited work done by site team
A6: 45863 | B6: 15/07/25 | C6: 1 | D6: 0.48611111 | E6: 0.52777778 | F6: =E6-D6 -> 0.041666667 | G6: 4 | I6: over current | J6: R phase jumper burinig | K6: New jumper | L6: getco s/s site new DO work done
A7: 45863 | B7: 15/07/26 | C7: 1 | D7: 0.54027778 | E7: 0.58333333 | F7: =E7-D7 -> 0.043055556 | G7: 4 | I7: over current | J7: Do wire burinig
A8: 45863 | B8: 45856 | C8: 1 | D8: 0.49305556 | E8: 0.53819444 | F8: =E8-D8 -> 0.045138889 | G8: 4 | I8: over current | J8: Do wire burinig
A9: 45863 | B9: 45862 | C9: 1 | D9: 0.45833333 | E9: 0.51388889 | F9: =E9-D9 -> 0.055555556 | G9: 4 | I9: over current | J9: Do wire burinig
A10: 45863 | B10: 45868 | C10: 1 | D10: 0.52083333 | E10: 0.68402778 | F10: =E10-D10 -> 0.16319444 | G10: 4 | H10: 11KV CT/PT | I10: over current | J10: R phase ct/pt lug burinig | K10: replace lug
A11: 45872 | B11: 45872 | C11: 1 | D11: 0.70833333 | E11: 0.72916667 | F11: =E11-D11 -> 0.020833333 | G11: 4 | I11: over/undar voltage | J11: gird voltage high in s/s side
A12: 45876 | B12: 45876 | C12: 1 | D12: 0.50416667 | E12: 0.63541667 | F12: =E12-D12 -> 0.13125 | G12: 4 | H12: R Phase jumpar | I12: over/undar voltage | K12: replace lug
A13: 45878 | B13: 45878 | C13: 1 | D13: 0.29166667 | E13: 0.34722222 | F13: =E13-D13 -> 0.055555556 | G13: 4 | I13: over voltage | J13: gird voltage high in s/s side
A14: 228 | B14: 15/08/25 | C14: 1 | D14: 0.4375 | E14: 0.5625 | F14: =E14-D14 -> 0.125 | G14: 4 | H14: CT/PT LUGS | I14: over voltage | J14: lugs burinig | L14: complited work done by site team
A15: 45929 | B15: 29/09/25 | C15: 1 | D15: 0.29166667 | E15: 0.36805556 | F15: =E15-D15 -> 0.076388889 | G15: 4 | L15: GETCO S/S IN DARK
A16: 45932 | B16: 45698 | C16: 1 | D16: 0.625 | E16: 0.79166667 | F16: =E16-D16 -> 0.16666667 | G16: 4 | L16: again plant manully stopped for havey rain
A17: 45964 | B17: 45964 | C17: 1 | D17: 0.46527778 | E17: 0.48263889 | F17: =E17-D17 -> 0.017361111 | G17: 4 | L17: 11 kv bus maintance in GETCO SS SITE
A18: 45976 | B18: 15/11/2025 | C18: 1 | D18: 0.29166667 | E18: 0.51458333 | F18: =E18-D18 -> 0.22291667 | G18: 4 | H18: no fault | J18: GETCO S/S SITE PLANNED OUTAGE

Sheet Plant_Grid_Down_Time_Details
A1: Plant_Grid_Down_Time_Details
A3: Month | B3: Date | C3: Transformer_No. (T-1) | D3: Down_Time_Start | E3: Down_Time_Stop | F3: Total_Down_Time | G3: Comm. Insolation of the Period | H3: Module Temp of the Period | I3: Affected DC Capacity (in KW) | J3: Insolation*Capacity | K3: Generation Loss | L3: Revenue
A4: 45833 | B4: 17/06/25 | C4: 1 | D4: 0.29166667 | E4: 0.45833333 | F4: 0.16666667
A5: 45833 | B5: 17/06/25 | D5: 0.47916667 | E5: 0.57986111 | F5: =E5-D5 -> 0.10069444
A6: 45955 | B6: 4/10//25 | C6: 1 | D6: 0.5625 | E6: 0.58263889 | F6: =E6-D6 -> 0.020138889
A7: 45964 | B7: 45964 | C7: 1 | D7: 0.46527778 | E7: 0.48263889 | F7: =E7-D7 -> 0.017361111 | M7: plant manully stopped for GETCO ss site 11kv bus maintance
A8: 45986 | B8: 45982 | C8: 1 | D8: 0.40625 | E8: 0.42708333 | F8: =E8-D8 -> 0.020833333 | M8: plant manully stopped for GETCO ss site work getco team,
A9: 45986 | B9: 29/11/2025 | C9: 1 | D9: 0.49444444 | E9: 0.50069444 | F9: =E9-D9 -> 0.00625 | M9: plant undar brackdown from getco ss site tripped in over voltage
A10: 46016 | B10: 46008 | C10: 1 | D10: 0.3125 | E10: 0.35347222 | F10: =E10-D10 -> 0.040972222 | M10: LINE VVOLTAGE high in ss
A11: 46026 | B11: 46026 | C11: 1 | D11: 0.60416667 | E11: 0.60833333 | F11: =E11-D11 -> 0.0041666667 | M11: from getco site gried drop
A12: 46028 | B12: 46029 | C12: 1 | D12: 0.52291667 | E12: 0.525 | F12: =E12-D12 -> 0.0020833333 | M12: getco site grid voltage hige
A13: 46029 | B13: 46030 | C13: 1 | D13: 0.69861111 | E13: 0.69930556 | F13: =E13-D13 -> 0.00069444444
A14: 16/01/2026 | B14: 16/01/2026 | C14: 1 | D14: 0.4125 | E14: 0.41527778 | F14: =E14-D14 -> 0.0027777778 | M14: s/s site grid voltage low
A15: 16/01/2026 | B15: 16/01/2026 | C15: 1 | D15: 0.66805556 | E15: 0.67152778 | F15: =E15-D15 -> 0.0034722222 | M15: s/s site grid voltage low
A16: 24/01/2026 | B16: 24/01/2026 | C16: 1 | D16: 0.49722222 | E16: 0.50069444 | F16: =E16-D16 -> 0.0034722222 | M16: s/s site grid voltage high
A17: 46069 | B17: 46069 | C17: 1 | D17: 0.52638889 | E17: 0.53333333 | F17: =E17-D17 -> 0.0069444444 | M17: s/s site grid voltage high
A18: 46071 | B18: 46071 | C18: 1 | D18: 0.55138889 | E18: 0.55416667 | F18: =E18-D18 -> 0.0027777778 | M18: s/s site grid voltage high
A19: 46075 | B19: 46075 | C19: 1 | D19: 12.27 | E19: 12.31 | F19: =E19-D19 -> 0.04 | M19: s/s site grid voltage high
A20: 46076 | B20: 46076 | C20: 1 | D20: 0.44583333 | E20: 0.50694444 | F20: =E20-D20 -> 0.061111111 | M20: plant site Y pashe jumper burned
A21: 46079 | B21: 46079 | C21: 1 | D21: 0.49097222 | E21: 0.61111111 | F21: =E21-D21 -> 0.12013889 | M21: s/s site Y pashe B pashe jumper burned
A22: 46081 | B22: 46081 | C22: 1 | D22: 0.39652778 | E22: 0.65625 | F22: =E22-D22 -> 0.25972222 | M22: inverter 8 under breakdown 1 string foulty
A23: 46084 | B23: 46084 | C23: 1 | D23: 0.47083333 | E23: 0.53888889 | F23: =E23-D23 -> 0.068055556 | M23: s/s site B pashe jumper burenin
A24: 46085 | B24: 46085 | C24: 1 | D24: 0.51111111 | E24: 0.65694444 | F24: =E24-D24 -> 0.14583333 | M24: plant load shedding inv no 1 stop
A25: 46088 | B25: 46088 | C25: 1 | D25: 0.48888889 | E25: 0.5625 | F25: =E25-D25 -> 0.073611111 | M25: plant site Y pashe jumper burned
A26: 46106 | B26: 46106 | C26: 1 | D26: 0.37152778 | E26: 0.42708333 | F26: =E26-D26 -> 0.055555556 | M26: 8 number inveter 1 string fualty remove
A27: 46123 | B27: 46123 | C27: 1 | D27: 0.67916667 | E27: 0.68263889 | F27: =E27-D27 -> 0.0034722222 | M27: s/s site grid voltage high
A28: 46163 | B28: 46163 | C28: 1 | D28: 0.29166667 | E28: 0.61458333 | F28: =E28-D28 -> 0.32291667 | M28: substation site planned outage
... A30: 46172 | B30: 46172 | C30: 1 | D30: 0.49166667 | E30: 0.59166667 | F30: =E30-D30 -> 0.1 | M30: both site r phase jumper lugs burned

Sheet Plant Aviliblity
A1: Date | B1: ABT Export Gen | C1: Total inevrter off | D1: GHI | E1: CUF% | F1: Out | G1: In | H1: Total Minute | I1: Outage Hrs. | J1: Plant Capacity | K1: Outage Capacity | L1: Plant Capacity Ratio | M1: Outage Ratio | N1: Plant Availiblity | O1: PA.C CUF | P1: total curtailment | Q1: P.A.C Generation | R1: PA Unit Lose
A2: 45839 | B2: =Data_Entry!X94 -> 15900 | C2: 0 | D2: =Data_Entry!AD94 -> 0 | E2: =B2/(24*J2) -> 0.16060606 | F2: 0 | G2: 0 | H2: =(G2-F2)*24*60 -> 0 | I2: =H2/60 -> 0 | J2: 4125 | K2: 0 | L2: =J2*12 -> 49500 | M2: =K2*I2 -> 0 | N2: =(L2-M2)/L2 -> 1 | O2: =E2/N2 -> 0.16060606 | Q2: =O2*J2*24 -> 15900 | R2: =Q2-B2 -> 0
A3: 45840 | B3: =Data_Entry!X95 -> 12000 | C3: 0 | D3: =Data_Entry!AD95 -> 0 | E3: =B3/(24*J3) -> 0.12121212 | F3: 0 | G3: 0 | H3: =(G3-F3)*24*60 -> 0 | I3: =H3/60 -> 0 | J3: 4125 | K3: 0 | L3: =J3*12 -> 49500 | M3: =K3*I3 -> 0 | N3: =(L3-M3)/L3 -> 1 | O3: =E3/N3 -> 0.12121212 | Q3: =O3*J3*24 -> 12000 | R3: =Q3-B3 -> 0
A4: 45841 | B4: =Data_Entry!X96 -> 5150 | C4: 0 | D4: =Data_Entry!AD96 -> 0 | E4: =B4/(24*J4) -> 0.052020202 | F4: 0.041666667 | G4: 0.041666667 | H4: =(G4-F4)*24*60 -> 0 | I4: =H4/60 -> 0 | J4: 4125 | K4: 0 | L4: =J4*12 -> 49500 | M4: =K4*I4 -> 0 | N4: =(L4-M4)/L4 -> 1 | O4: =E4/N4 -> 0.052020202 | Q4: =O4*J4*24 -> 5150 | R4: =Q4-B4 -> 0
A5: 45842 | B5: =Data_Entry!X97 -> 9900 | C5: 0 | D5: =Data_Entry!AD97 -> 0 | E5: =B5/(24*J5) -> 0.1 | F5: 0.083333333 | G5: 0.083333333 | H5: =(G5-F5)*24*60 -> 0 | I5: =H5/60 -> 0 | J5: 4125 | K5: 0 | L5: =J5*12 -> 49500 | M5: =K5*I5 -> 0 | N5: =(L5-M5)/L5 -> 1 | O5: =E5/N5 -> 0.1 | Q5: =O5*J5*24 -> 9900 | R5: =Q5-B5 -> 0
A6: 45843 | B6: =Data_Entry!X98 -> 9450 | C6: 0 | D6: =Data_Entry!AD98 -> 0 | E6: =B6/(24*J6) -> 0.095454545 | F6: 0.41666667 | G6: 0.48958333 | H6: =(G6-F6)*24*60 -> 105 | I6: =H6/60 -> 1.75 | J6: 4125 | K6: 0 | L6: =J6*12 -> 49500 | M6: =K6*I6 -> 0 | N6: =(L6-M6)/L6 -> 1 | O6: =E6/N6 -> 0.095454545 | Q6: =O6*J6*24 -> 9450 | R6: =Q6-B6 -> 0
A7: 45844 | B7: =Data_Entry!X99 -> 13800 | C7: 0 | D7: =Data_Entry!AD99 -> 0 | E7: =B7/(24*J7) -> 0.13939394 | F7: 0 | G7: 0 | H7: =(G7-F7)*24*60 -> 0 | I7: =H7/60 -> 0 | J7: 4125 | K7: 0 | L7: =J7*12 -> 49500 | M7: =K7*I7 -> 0 | N7: =(L7-M7)/L7 -> 1 | O7: =E7/N7 -> 0.13939394 | Q7: =O7*J7*24 -> 13800 | R7: =Q7-B7 -> 0
A8: 45845 | B8: =Data_Entry!X100 -> 9300 | C8: 0 | D8: =Data_Entry!AD100 -> 0 | E8: =B8/(24*J8) -> 0.093939394 | F8: 0 | G8: 0 | H8: =(G8-F8)*24*60 -> 0 | I8: =H8/60 -> 0 | J8: 4125 | K8: 0 | L8: =J8*12 -> 49500 | M8: =K8*I8 -> 0 | N8: =(L8-M8)/L8 -> 1 | O8: =E8/N8 -> 0.093939394 | Q8: =O8*J8*24 -> 9300 | R8: =Q8-B8 -> 0
A9: 45846 | B9: =Data_Entry!X101 -> 15550 | C9: 0 | D9: =Data_Entry!AD101 -> 0 | E9: =B9/(24*J9) -> 0.15707071 | F9: 0 | G9: 0 | H9: =(G9-F9)*24*60 -> 0 | I9: =H9/60 -> 0 | J9: 4125 | K9: 0 | L9: =J9*12 -> 49500 | M9: =K9*I9 -> 0 | N9: =(L9-M9)/L9 -> 1 | O9: =E9/N9 -> 0.15707071 | Q9: =O9*J9*24 -> 15550 | R9: =Q9-B9 -> 0
A10: 45847 | B10: =Data_Entry!X102 -> 21950 | C10: 0 | D10: =Data_Entry!AD102 -> 0 | E10: =B10/(24*J10) -> 0.22171717 | F10: 0 | G10: 0 | H10: =(G10-F10)*24*60 -> 0 | I10: =H10/60 -> 0 | J10: 4125 | K10: 0 | L10: =J10*12 -> 49500 | M10: =K10*I10 -> 0 | N10: =(L10-M10)/L10 -> 1 | O10: =E10/N10 -> 0.22171717 | Q10: =O10*J10*24 -> 21950 | R10: =Q10-B10 -> 0
A11: 45848 | B11: =Data_Entry!X103 -> 13400 | C11: 0 | D11: =Data_Entry!AD103 -> 0 | E11: =B11/(24*J11) -> 0.13535354 | F11: 0 | G11: 0 | H11: =(G11-F11)*24*60 -> 0 | I11: =H11/60 -> 0 | J11: 4125 | K11: 0 | L11: =J11*12 -> 49500 | M11: =K11*I11 -> 0 | N11: =(L11-M11)/L11 -> 1 | O11: =E11/N11 -> 0.13535354 | Q11: =O11*J11*24 -> 13400 | R11: =Q11-B11 -> 0
A12: 45849 | B12: =Data_Entry!X104 -> 11600 | C12: 0 | D12: =Data_Entry!AD104 -> 0 | E12: =B12/(24*J12) -> 0.11717172 | F12: 0 | G12: 0 | H12: =(G12-F12)*24*60 -> 0 | I12: =H12/60 -> 0 | J12: 4125 | K12: 0 | L12: =J12*12 -> 49500 | M12: =K12*I12 -> 0 | N12: =(L12-M12)/L12 -> 1 | O12: =E12/N12 -> 0.11717172 | Q12: =O12*J12*24 -> 11600 | R12: =Q12-B12 -> 0
A13: 45850 | B13: =Data_Entry!X105 -> 19350 | C13: 0 | D13: =Data_Entry!AD105 -> 0 | E13: =B13/(24*J13) -> 0.19545455 | F13: 0 | G13: 0 | H13: =(G13-F13)*24*60 -> 0 | I13: =H13/60 -> 0 | J13: 4125 | K13: 0 | L13: =J13*12 -> 49500 | M13: =K13*I13 -> 0 | N13: =(L13-M13)/L13 -> 1 | O13: =E13/N13 -> 0.19545455 | Q13: =O13*J13*24 -> 19350 | R13: =Q13-B13 -> 0
... A15: 45852 | B15: =Data_Entry!X107 -> 21500 | C15: 0 | D15: =Data_Entry!AD107 -> 3.44 | E15: =B15/(24*J15) -> 0.21717172 | F15: 0 | G15: 0 | H15: =(G15-F15)*24*60 -> 0 | I15: =H15/60 -> 0 | J15: 4125 | K15: 0 | L15: =J15*12 -> 49500 | M15: =K15*I15 -> 0 | N15: =(L15-M15)/L15 -> 1 | O15: =E15/N15 -> 0.21717172 | Q15: =O15*J15*24 -> 21500 | R15: =Q15-B15 -> 0
A16: 45853 | B16: =Data_Entry!X108 -> 14000 | C16: 7 | D16: =Data_Entry!AD108 -> 0 | E16: =B16/(24*J16) -> 0.14141414 | F16: 0.48611111 | G16: 0.52777778 | H16: 125 | I16: =H16/60 -> 2.0833333 | J16: 4125 | K16: 4822.16 | L16: =J16*12 -> 49500 | M16: =K16*I16 -> 10046.167 | N16: =(L16-M16)/L16 -> 0.79704714 | O16: =E16/N16 -> 0.17742256 | Q16: =O16*J16*24 -> 17564.833 | R16: =Q16-B16 -> 3564.8332
A17: 45854 | B17: =Data_Entry!X109 -> 23950 | C17: 0 | D17: =Data_Entry!AD109 -> 4.4 | E17: =B17/(24*J17) -> 0.24191919 | F17: 0 | G17: 0 | H17: =(G17-F17)*24*60 -> 0 | I17: =H17/60 -> 0 | J17: 4125 | K17: 0 | L17: =J17*12 -> 49500 | M17: =K17*I17 -> 0 | N17: =(L17-M17)/L17 -> 1 | O17: =E17/N17 -> 0.24191919 | Q17: =O17*J17*24 -> 23950 | R17: =Q17-B17 -> 0
A18: 45855 | B18: =Data_Entry!X110 -> 21900 | C18: 0 | D18: =Data_Entry!AD110 -> 3.46 | E18: =B18/(24*J18) -> 0.22121212 | F18: 0 | G18: 0 | H18: =(G18-F18)*24*60 -> 0 | I18: =H18/60 -> 0 | J18: 4125 | K18: 0 | L18: =J18*12 -> 49500 | M18: =K18*I18 -> 0 | N18: =(L18-M18)/L18 -> 1 | O18: =E18/N18 -> 0.22121212 | Q18: =O18*J18*24 -> 21900 | R18: =Q18-B18 -> 0
A19: 45856 | B19: =Data_Entry!X111 -> 18750 | C19: 15 | D19: =Data_Entry!AD111 -> 3.13 | E19: =B19/(24*J19) -> 0.18939394 | F19: ='Plant_Down_Time Details'!D8 -> 0.49305556 | G19: ='Plant_Down_Time Details'!E8 -> 0.53819444 | H19: =(G19-F19)*24*60 -> 65 | I19: =H19/60 -> 1.0833333 | J19: 4125 | K19: 4822.16 | L19: =J19*12 -> 49500 | M19: =K19*I19 -> 5224.0067 | N19: =(L19-M19)/L19 -> 0.89446451 | O19: =E19/N19 -> 0.21174003 | Q19: =O19*J19*24 -> 20962.263 | R19: =Q19-B19 -> 2212.2626
A20: 45857 | B20: =Data_Entry!X112 -> 13050 | C20: 0 | D20: =Data_Entry!AD112 -> 1.9 | E20: =B20/(24*J20) -> 0.13181818 | F20: 0 | G20: 0 | H20: =(G20-F20)*24*60 -> 0 | I20: =H20/60 -> 0 | J20: 4125 | K20: 0 | L20: =J20*12 -> 49500 | M20: =K20*I20 -> 0 | N20: =(L20-M20)/L20 -> 1 | O20: =E20/N20 -> 0.13181818 | Q20: =O20*J20*24 -> 13050 | R20: =Q20-B20 -> 0
A21: 45858 | B21: =Data_Entry!X113 -> 12400 | C21: 0 | D21: =Data_Entry!AD113 -> 1.81 | E21: =B21/(24*J21) -> 0.12525253 | F21: 0 | G21: 0 | H21: =(G21-F21)*24*60 -> 0 | I21: =H21/60 -> 0 | J21: 4125 | K21: 0 | L21: =J21*12 -> 49500 | M21: =K21*I21 -> 0 | N21: =(L21-M21)/L21 -> 1 | O21: =E21/N21 -> 0.12525253 | Q21: =O21*J21*24 -> 12400 | R21: =Q21-B21 -> 0
A22: 45859 | B22: =Data_Entry!X114 -> 15000 | C22: 0 | D22: =Data_Entry!AD114 -> 2.13 | E22: =B22/(24*J22) -> 0.15151515 | F22: 0 | G22: 0 | H22: =(G22-F22)*24*60 -> 0 | I22: =H22/60 -> 0 | J22: 4125 | K22: 0 | L22: =J22*12 -> 49500 | M22: =K22*I22 -> 0 | N22: =(L22-M22)/L22 -> 1 | O22: =E22/N22 -> 0.15151515 | Q22: =O22*J22*24 -> 15000 | R22: =Q22-B22 -> 0
A23: 45860 | B23: =Data_Entry!X115 -> 13800 | C23: 0 | D23: =Data_Entry!AD115 -> 2.01 | E23: =B23/(24*J23) -> 0.13939394 | F23: 0 | G23: 0 | H23: =(G23-F23)*24*60 -> 0 | I23: =H23/60 -> 0 | J23: 4125 | K23: 0 | L23: =J23*12 -> 49500 | M23: =K23*I23 -> 0 | N23: =(L23-M23)/L23 -> 1 | O23: =E23/N23 -> 0.13939394 | Q23: =O23*J23*24 -> 13800 | R23: =Q23-B23 -> 0
A24: 45861 | B24: =Data_Entry!X116 -> 18550 | C24: 0 | D24: =Data_Entry!AD116 -> 2.89 | E24: =B24/(24*J24) -> 0.18737374 | F24: 0 | G24: 0 | H24: =(G24-F24)*24*60 -> 0 | I24: =H24/60 -> 0 | J24: 4125 | K24: 0 | L24: =J24*12 -> 49500 | M24: =K24*I24 -> 0 | N24: =(L24-M24)/L24 -> 1 | O24: =E24/N24 -> 0.18737374 | Q24: =O24*J24*24 -> 18550 | R24: =Q24-B24 -> 0
A25: 45862 | B25: =Data_Entry!X117 -> 15000 | C25: 0 | D25: =Data_Entry!AD117 -> 2.28 | E25: =B25/(24*J25) -> 0.15151515 | F25: 0 | G25: 0 | H25: =(G25-F25)*24*60 -> 0 | I25: =H25/60 -> 0 | J25: 4125 | K25: 0 | L25: =J25*12 -> 49500 | M25: =K25*I25 -> 0 | N25: =(L25-M25)/L25 -> 1 | O25: =E25/N25 -> 0.15151515 | Q25: =O25*J25*24 -> 15000 | R25: =Q25-B25 -> 0
A26: 45863 | B26: =Data_Entry!X118 -> 15250 | C26: 15 | D26: =Data_Entry!AD118 -> 2.52 | E26: =B26/(24*J26) -> 0.1540404 | F26: 0.45833333 | G26: 0.51388889 | H26: =(G26-F26)*24*60 -> 80 | I26: =H26/60 -> 1.3333333 | J26: 4125 | K26: 4822.16 | L26: =J26*12 -> 49500 | M26: =K26*I26 -> 6429.5467 | N26: =(L26-M26)/L26 -> 0.87011017 | O26: =E26/N26 -> 0.17703552 | Q26: =O26*J26*24 -> 17526.516 | R26: =Q26-B26 -> 2276.5162
A27: 45864 | B27: =Data_Entry!X119 -> 12700 | C27: 0 | D27: =Data_Entry!AD119 -> 1.79 | E27: =B27/(24*J27) -> 0.12828283 | F27: 0 | G27: 0 | H27: =(G27-F27)*24*60 -> 0 | I27: =H27/60 -> 0 | J27: 4125 | K27: 0 | L27: =J27*12 -> 49500 | M27: =K27*I27 -> 0 | N27: =(L27-M27)/L27 -> 1 | O27: =E27/N27 -> 0.12828283 | Q27: =O27*J27*24 -> 12700 | R27: =Q27-B27 -> 0
A28: 45865 | B28: =Data_Entry!X120 -> 7750 | C28: 0 | D28: =Data_Entry!AD120 -> 1.09 | E28: =B28/(24*J28) -> 0.078282828 | F28: 0 | G28: 0 | H28: =(G28-F28)*24*60 -> 0 | I28: =H28/60 -> 0 | J28: 4125 | K28: 0 | L28: =J28*12 -> 49500 | M28: =K28*I28 -> 0 | N28: =(L28-M28)/L28 -> 1 | O28: =E28/N28 -> 0.078282828 | Q28: =O28*J28*24 -> 7750 | R28: =Q28-B28 -> 0
A29: 45866 | B29: =Data_Entry!X121 -> 9300 | C29: 0 | D29: =Data_Entry!AD121 -> 1.39 | E29: =B29/(24*J29) -> 0.093939394 | F29: 0 | G29: 0 | H29: =(G29-F29)*24*60 -> 0 | I29: =H29/60 -> 0 | J29: 4125 | K29: 0 | L29: =J29*12 -> 49500 | M29: =K29*I29 -> 0 | N29: =(L29-M29)/L29 -> 1 | O29: =E29/N29 -> 0.093939394 | Q29: =O29*J29*24 -> 9300 | R29: =Q29-B29 -> 0
A30: 45867 | B30: =Data_Entry!X122 -> 8250 | C30: 0 | D30: =Data_Entry!AD122 -> 1.13 | E30: =B30/(24*J30) -> 0.083333333 | F30: 0 | G30: 0 | H30: =(G30-F30)*24*60 -> 0 | I30: =H30/60 -> 0 | J30: 4125 | K30: 0 | L30: =J30*12 -> 49500 | M30: =K30*I30 -> 0 | N30: =(L30-M30)/L30 -> 1 | O30: =E30/N30 -> 0.083333333 | Q30: =O30*J30*24 -> 8250 | R30: =Q30-B30 -> 0
A31: 45868 | B31: =Data_Entry!X123 -> 6000 | C31: 0 | D31: =Data_Entry!AD123 -> 0.94 | E31: =B31/(24*J31) -> 0.060606061 | F31: 0.52083333 | G31: 0.68402778 | H31: =(G31-F31)*24*60 -> 235 | I31: =H31/60 -> 3.9166667 | J31: 4125 | K31: 4822.16 | L31: =J31*12 -> 49500 | M31: =K31*I31 -> 18886.793 | N31: =(L31-M31)/L31 -> 0.61844862 | O31: =E31/N31 -> 0.097996921 | Q31: =O31*J31*24 -> 9701.6952 | R31: =Q31-B31 -> 3701.6952
A32: 45869 | B32: =Data_Entry!X124 -> 11950 | C32: 0 | D32: =Data_Entry!AD124 -> 1.81 | E32: =B32/(24*J32) -> 0.12070707 | F32: 0 | G32: 0 | H32: =(G32-F32)*24*60 -> 0 | I32: =H32/60 -> 0 | J32: 4125 | K32: 0 | L32: =J32*12 -> 49500 | M32: =K32*I32 -> 0 | N32: =(L32-M32)/L32 -> 1 | O32: =E32/N32 -> 0.12070707 | Q32: =O32*J32*24 -> 11950 | R32: =Q32-B32 -> 0
A34: 45870 | B34: =Data_Entry!X125 -> 13750 | C34: 0 | D34: =Data_Entry!AD125 -> 1.29 | E34: =B34/(24*J34) -> 0.13888889 | F34: 0 | G34: 0 | H34: =(G34-F34)*24*60 -> 0 | I34: =H34/60 -> 0 | J34: 4125 | K34: 0 | L34: =J34*12 -> 49500 | M34: =K34*I34 -> 0 | N34: =(L34-M34)/L34 -> 1 | O34: =E34/N34 -> 0.13888889 | Q34: =O34*J34*24 -> 13750 | R34: =Q34-B34 -> 0
A35: 45871 | B35: =Data_Entry!X126 -> 15700 | C35: 0 | D35: =Data_Entry!AD126 -> 0.56 | E35: =B35/(24*J35) -> 0.15858586 | F35: 0 | G35: 0 | H35: =(G35-F35)*24*60 -> 0 | I35: =H35/60 -> 0 | J35: 4125 | K35: 0 | L35: =J35*12 -> 49500 | M35: =K35*I35 -> 0 | N35: =(L35-M35)/L35 -> 1 | O35: =E35/N35 -> 0.15858586 | Q35: =O35*J35*24 -> 15700 | R35: =Q35-B35 -> 0
A36: 45872 | B36: =Data_Entry!X127 -> 11600 | C36: 15 | D36: =Data_Entry!AD127 -> 0.45 | E36: =B36/(24*J36) -> 0.11717172 | F36: 0.70833333 | G36: 0.72916667 | H36: =(G36-F36)*24*60 -> 30 | I36: =H36/60 -> 0.5 | J36: 4125 | K36: 4822.16 | L36: =J36*12 -> 49500 | M36: =K36*I36 -> 2411.08 | N36: =(L36-M36)/L36 -> 0.95129131 | O36: =E36/N36 -> 0.12317123 | Q36: =O36*J36*24 -> 12193.951 | R36: =Q36-B36 -> 593.95136
A37: 45873 | B37: =Data_Entry!X128 -> 15300 | C37: 0 | D37: =Data_Entry!AD128 -> 0.54 | E37: =B37/(24*J37) -> 0.15454545 | F37: 0 | G37: 0 | H37: =(G37-F37)*24*60 -> 0 | I37: =H37/60 -> 0 | J37: 4125 | K37: 0 | L37: =J37*12 -> 49500 | M37: =K37*I37 -> 0 | N37: =(L37-M37)/L37 -> 1 | O37: =E37/N37 -> 0.15454545 | Q37: =O37*J37*24 -> 15300 | R37: =Q37-B37 -> 0
A38: 45874 | B38: =Data_Entry!X129 -> 18300 | C38: 0 | D38: =Data_Entry!AD129 -> 0.76 | E38: =B38/(24*J38) -> 0.18484848 | F38: 0 | G38: 0 | H38: =(G38-F38)*24*60 -> 0 | I38: =H38/60 -> 0 | J38: 4125 | K38: 0 | L38: =J38*12 -> 49500 | M38: =K38*I38 -> 0 | N38: =(L38-M38)/L38 -> 1 | O38: =E38/N38 -> 0.18484848 | Q38: =O38*J38*24 -> 18300 | R38: =Q38-B38 -> 0
A39: 45875 | B39: =Data_Entry!X130 -> 16100 | C39: 0 | D39: =Data_Entry!AD130 -> 0.66 | E39: =B39/(24*J39) -> 0.16262626 | F39: 0 | G39: 0 | H39: =(G39-F39)*24*60 -> 0 | I39: =H39/60 -> 0 | J39: 4125 | K39: 0 | L39: =J39*12 -> 49500 | M39: =K39*I39 -> 0 | N39: =(L39-M39)/L39 -> 1 | O39: =E39/N39 -> 0.16262626 | Q39: =O39*J39*24 -> 16100 | R39: =Q39-B39 -> 0
A40: 45876 | B40: =Data_Entry!X131 -> 13450 | C40: 15 | D40: =Data_Entry!AD131 -> 0.51 | E40: =B40/(24*J40) -> 0.13585859 | F40: 0.50416667 | G40: 0.63541667 | H40: =(G40-F40)*24*60 -> 189 | I40: =H40/60 -> 3.15 | J40: 4125 | K40: 4822.16 | L40: =J40*12 -> 49500 | M40: =K40*I40 -> 15189.804 | N40: =(L40-M40)/L40 -> 0.69313527 | O40: =E40/N40 -> 0.19600588 | Q40: =O40*J40*24 -> 19404.582 | R40: =Q40-B40 -> 5954.5817
A41: 45877 | B41: =Data_Entry!X132 -> 20100 | C41: 0 | D41: =Data_Entry!AD132 -> 0.73 | E41: =B41/(24*J41) -> 0.2030303 | F41: 0 | G41: 0 | H41: =(G41-F41)*24*60 -> 0 | I41: =H41/60 -> 0 | J41: 4125 | K41: 0 | L41: =J41*12 -> 49500 | M41: =K41*I41 -> 0 | N41: =(L41-M41)/L41 -> 1 | O41: =E41/N41 -> 0.2030303 | Q41: =O41*J41*24 -> 20100 | R41: =Q41-B41 -> 0
A42: 45878 | B42: =Data_Entry!X133 -> 12550 | C42: 0 | D42: =Data_Entry!AD133 -> 0.41 | E42: =B42/(24*J42) -> 0.12676768 | F42: 0 | G42: 0 | H42: =(G42-F42)*24*60 -> 0 | I42: =H42/60 -> 0 | J42: 4125 | K42: 0 | L42: =J42*12 -> 49500 | M42: =K42*I42 -> 0 | N42: =(L42-M42)/L42 -> 1 | O42: =E42/N42 -> 0.12676768 | Q42: =O42*J42*24 -> 12550 | R42: =Q42-B42 -> 0
A43: 45879 | B43: =Data_Entry!X134 -> 8550 | C43: 0 | D43: =Data_Entry!AD134 -> 0.28 | E43: =B43/(24*J43) -> 0.086363636 | F43: 0 | G43: 0 | H43: =(G43-F43)*24*60 -> 0 | I43: =H43/60 -> 0 | J43: 4125 | K43: 0 | L43: =J43*12 -> 49500 | M43: =K43*I43 -> 0 | N43: =(L43-M43)/L43 -> 1 | O43: =E43/N43 -> 0.086363636 | Q43: =O43*J43*24 -> 8550 | R43: =Q43-B43 -> 0
A44: 45880 | B44: =Data_Entry!X135 -> 19400 | C44: 0 | D44: =Data_Entry!AD135 -> 0.69 | E44: =B44/(24*J44) -> 0.1959596 | F44: 0 | G44: 0 | H44: =(G44-F44)*24*60 -> 0 | I44: =H44/60 -> 0 | J44: 4125 | K44: 0 | L44: =J44*12 -> 49500 | M44: =K44*I44 -> 0 | N44: =(L44-M44)/L44 -> 1 | O44: =E44/N44 -> 0.1959596 | Q44: =O44*J44*24 -> 19400 | R44: =Q44-B44 -> 0
A45: 45881 | B45: =Data_Entry!X136 -> 11450 | C45: 0 | D45: =Data_Entry!AD136 -> 0.44 | E45: =B45/(24*J45) -> 0.11565657 | F45: 0 | G45: 0 | H45: =(G45-F45)*24*60 -> 0 | I45: =H45/60 -> 0 | J45: 4125 | K45: 0 | L45: =J45*12 -> 49500 | M45: =K45*I45 -> 0 | N45: =(L45-M45)/L45 -> 1 | O45: =E45/N45 -> 0.11565657 | Q45: =O45*J45*24 -> 11450 | R45: =Q45-B45 -> 0
... A48: 45884 | B48: =Data_Entry!X139 -> 7000 | C48: 15 | D48: =Data_Entry!AD139 -> 0.23 | E48: =B48/(24*J48) -> 0.070707071 | F48: 0.4375 | G48: 0.5625 | H48: =(G48-F48)*24*60 -> 180 | I48: =H48/60 -> 3 | J48: 4125 | K48: 4822.16 | L48: =J48*12 -> 49500 | M48: =K48*I48 -> 14466.48 | N48: =(L48-M48)/L48 -> 0.70774788 | O48: =E48/N48 -> 0.09990432 | Q48: =O48*J48*24 -> 9890.5277 | R48: =Q48-B48 -> 2890.5277
A49: 45885 | B49: =Data_Entry!X140 -> 14450 | C49: 0 | D49: =Data_Entry!AD140 -> 0.48 | E49: =B49/(24*J49) -> 0.1459596 | F49: 0 | G49: 0 | H49: =(G49-F49)*24*60 -> 0 | I49: =H49/60 -> 0 | J49: 4125 | L49: =J49*12 -> 49500 | M49: =K49*I49 -> 0 | N49: =(L49-M49)/L49 -> 1 | O49: =E49/N49 -> 0.1459596 | Q49: =O49*J49*24 -> 14450 | R49: =Q49-B49 -> 0
A50: 45886 | B50: =Data_Entry!X141 -> 16100 | C50: 0 | D50: =Data_Entry!AD141 -> 0.51 | E50: =B50/(24*J50) -> 0.16262626 | F50: 0 | G50: 0 | H50: =(G50-F50)*24*60 -> 0 | I50: =H50/60 -> 0 | J50: 4125 | L50: =J50*12 -> 49500 | M50: =K50*I50 -> 0 | N50: =(L50-M50)/L50 -> 1 | O50: =E50/N50 -> 0.16262626 | Q50: =O50*J50*24 -> 16100 | R50: =Q50-B50 -> 0
A51: 45887 | B51: =Data_Entry!X142 -> 15600 | C51: 0 | D51: =Data_Entry!AD142 -> 3.1 | E51: =B51/(24*J51) -> 0.15757576 | F51: 0 | G51: 0 | H51: =(G51-F51)*24*60 -> 0 | I51: =H51/60 -> 0 | J51: 4125 | L51: =J51*12 -> 49500 | M51: =K51*I51 -> 0 | N51: =(L51-M51)/L51 -> 1 | O51: =E51/N51 -> 0.15757576 | Q51: =O51*J51*24 -> 15600 | R51: =Q51-B51 -> 0
A52: 45888 | B52: =Data_Entry!X143 -> 14850 | C52: 0 | D52: =Data_Entry!AD143 -> 0 | E52: =B52/(24*J52) -> 0.15 | F52: 0 | G52: 0 | H52: =(G52-F52)*24*60 -> 0 | I52: =H52/60 -> 0 | J52: 4125 | L52: =J52*12 -> 49500 | M52: =K52*I52 -> 0 | N52: =(L52-M52)/L52 -> 1 | O52: =E52/N52 -> 0.15 | Q52: =O52*J52*24 -> 14850 | R52: =Q52-B52 -> 0
A53: 45889 | B53: =Data_Entry!X144 -> 0 | C53: 15 | D53: =Data_Entry!AD144 -> 0 | E53: =B53/(24*J53) -> 0 | F53: 0.29166667 | G53: 0.79166667 | H53: =(G53-F53)*24*60 -> 720 | I53: =H53/60 -> 12 | J53: 4125 | K53: 4822.16 | L53: =J53*12 -> 49500 | M53: =K53*I53 -> 57865.92 | N53: =(L53-M53)/L53 -> -0.16900848 | O53: =E53/N53 -> 0 | Q53: =O53*J53*24 -> 0 | R53: =Q53-B53 -> 0
A54: 45890 | B54: =Data_Entry!X145 -> 0 | C54: 15 | D54: =Data_Entry!AD145 -> 0 | E54: =B54/(24*J54) -> 0 | F54: 0.29166667 | G54: 0.79166667 | H54: =(G54-F54)*24*60 -> 720 | I54: =H54/60 -> 12 | J54: 4125 | K54: 4822.16 | L54: =J54*12 -> 49500 | M54: =K54*I54 -> 57865.92 | N54: =(L54-M54)/L54 -> -0.16900848 | O54: =E54/N54 -> 0 | Q54: =O54*J54*24 -> 0 | R54: =Q54-B54 -> 0
A55: 45891 | B55: =Data_Entry!X146 -> 0 | C55: 15 | D55: =Data_Entry!AD146 -> 0 | E55: =B55/(24*J55) -> 0 | F55: 0.29166667 | G55: 0.79166667 | H55: =(G55-F55)*24*60 -> 720 | I55: =H55/60 -> 12 | J55: 4125 | K55: 4822.16 | L55: =J55*12 -> 49500 | M55: =K55*I55 -> 57865.92 | N55: =(L55-M55)/L55 -> -0.16900848 | O55: =E55/N55 -> 0 | Q55: =O55*J55*24 -> 0 | R55: =Q55-B55 -> 0
A56: 45892 | B56: =Data_Entry!X147 -> 0 | C56: 15 | D56: =Data_Entry!AD147 -> 0 | E56: =B56/(24*J56) -> 0 | F56: 0.29166667 | G56: 0.79166667 | H56: =(G56-F56)*24*60 -> 720 | I56: =H56/60 -> 12 | J56: 4125 | K56: 4822.16 | L56: =J56*12 -> 49500 | M56: =K56*I56 -> 57865.92 | N56: =(L56-M56)/L56 -> -0.16900848 | O56: =E56/N56 -> 0 | Q56: =O56*J56*24 -> 0 | R56: =Q56-B56 -> 0
A57: 45893 | B57: =Data_Entry!X148 -> 0 | C57: 15 | D57: =Data_Entry!AD148 -> 0 | E57: =B57/(24*J57) -> 0 | F57: 0.29166667 | G57: 0.79166667 | H57: =(G57-F57)*24*60 -> 720 | I57: =H57/60 -> 12 | J57: 4125 | K57: 4822.16 | L57: =J57*12 -> 49500 | M57: =K57*I57 -> 57865.92 | N57: =(L57-M57)/L57 -> -0.16900848 | O57: =E57/N57 -> 0 | Q57: =O57*J57*24 -> 0 | R57: =Q57-B57 -> 0
A58: 45894 | B58: =Data_Entry!X149 -> 0 | C58: 15 | D58: =Data_Entry!AD149 -> 0 | E58: =B58/(24*J58) -> 0 | F58: 0.29166667 | G58: 0.79166667 | H58: =(G58-F58)*24*60 -> 720 | I58: =H58/60 -> 12 | J58: 4125 | K58: 4822.16 | L58: =J58*12 -> 49500 | M58: =K58*I58 -> 57865.92 | N58: =(L58-M58)/L58 -> -0.16900848 | O58: =E58/N58 -> 0 | Q58: =O58*J58*24 -> 0 | R58: =Q58-B58 -> 0
A59: 45895 | B59: =Data_Entry!X150 -> 0 | C59: 15 | D59: =Data_Entry!AD150 -> 0 | E59: =B59/(24*J59) -> 0 | F59: 0.29166667 | G59: 0.79166667 | H59: =(G59-F59)*24*60 -> 720 | I59: =H59/60 -> 12 | J59: 4125 | K59: 4822.16 | L59: =J59*12 -> 49500 | M59: =K59*I59 -> 57865.92 | N59: =(L59-M59)/L59 -> -0.16900848 | O59: =E59/N59 -> 0 | Q59: =O59*J59*24 -> 0 | R59: =Q59-B59 -> 0
A60: 45896 | B60: =Data_Entry!X151 -> 0 | C60: 15 | D60: =Data_Entry!AD151 -> 0 | E60: =B60/(24*J60) -> 0 | F60: 0.29166667 | G60: 0.79166667 | H60: =(G60-F60)*24*60 -> 720 | I60: =H60/60 -> 12 | J60: 4125 | K60: 4822.16 | L60: =J60*12 -> 49500 | M60: =K60*I60 -> 57865.92 | N60: =(L60-M60)/L60 -> -0.16900848 | O60: =E60/N60 -> 0 | Q60: =O60*J60*24 -> 0 | R60: =Q60-B60 -> 0
A61: 45897 | B61: =Data_Entry!X152 -> 0 | C61: 15 | D61: =Data_Entry!AD152 -> 0 | E61: =B61/(24*J61) -> 0 | F61: 0.29166667 | G61: 0.79166667 | H61: =(G61-F61)*24*60 -> 720 | I61: =H61/60 -> 12 | J61: 4125 | K61: 4822.16 | L61: =J61*12 -> 49500 | M61: =K61*I61 -> 57865.92 | N61: =(L61-M61)/L61 -> -0.16900848 | O61: =E61/N61 -> 0 | Q61: =O61*J61*24 -> 0 | R61: =Q61-B61 -> 0
A62: 45898 | B62: =Data_Entry!X153 -> 0 | C62: 15 | D62: =Data_Entry!AD153 -> 0 | E62: =B62/(24*J62) -> 0 | F62: 0.29166667 | G62: 0.79166667 | H62: =(G62-F62)*24*60 -> 720 | I62: =H62/60 -> 12 | J62: 4125 | K62: 4822.16 | L62: =J62*12 -> 49500 | M62: =K62*I62 -> 57865.92 | N62: =(L62-M62)/L62 -> -0.16900848 | O62: =E62/N62 -> 0 | Q62: =O62*J62*24 -> 0 | R62: =Q62-B62 -> 0
A63: 45899 | B63: =Data_Entry!X154 -> 1050 | C63: 0 | D63: =Data_Entry!AD154 -> 0 | E63: =B63/(24*J63) -> 0.010606061 | F63: 0 | G63: 0 | H63: =(G63-F63)*24*60 -> 0 | I63: =H63/60 -> 0 | J63: 4125 | K63: 4822.16 | L63: =J63*12 -> 49500 | M63: =K63*I63 -> 0 | N63: =(L63-M63)/L63 -> 1 | O63: =E63/N63 -> 0.010606061 | Q63: =O63*J63*24 -> 1050 | R63: =Q63-B63 -> 0
A64: 45900 | B64: =Data_Entry!X155 -> 0 | C64: 15 | D64: =Data_Entry!AD155 -> 0 | E64: =B64/(24*J64) -> 0 | F64: 0.29166667 | G64: 0.79166667 | H64: =(G64-F64)*24*60 -> 720 | I64: =H64/60 -> 12 | J64: 4125 | K64: 4822.16 | L64: =J64*12 -> 49500 | M64: =K64*I64 -> 57865.92 | N64: =(L64-M64)/L64 -> -0.16900848 | O64: =E64/N64 -> 0 | Q64: =O64*J64*24 -> 0 | R64: =Q64-B64 -> 0
N65: =AVERAGE(N34:N64) -> 0.56429294
A66: 45901 | B66: =Data_Entry!X156 -> 0 | C66: 15 | D66: =Data_Entry!AD156 -> 0 | E66: =B66/(24*J66) -> 0 | F66: 0 | G66: 0 | H66: =(G66-F66)*24*60 -> 0 | I66: =H66/60 -> 0 | J66: 4125 | L66: =J66*12 -> 49500 | M66: =K66*I66 -> 0 | N66: =(L66-M66)/L66 -> 1 | O66: =E66/N66 -> 0 | Q66: =O66*J66*24 -> 0 | R66: =Q66-B66 -> 0
A67: 45902 | B67: =Data_Entry!X157 -> 0 | C67: 15 | D67: =Data_Entry!AD157 -> 0 | E67: =B67/(24*J67) -> 0 | F67: 0 | G67: 0 | H67: =(G67-F67)*24*60 -> 0 | I67: =H67/60 -> 0 | J67: 4125 | L67: =J67*12 -> 49500 | M67: =K67*I67 -> 0 | N67: =(L67-M67)/L67 -> 1 | O67: =E67/N67 -> 0 | Q67: =O67*J67*24 -> 0 | R67: =Q67-B67 -> 0
A68: 45903 | B68: =Data_Entry!X158 -> 0 | C68: 15 | D68: =Data_Entry!AD158 -> 0 | E68: =B68/(24*J68) -> 0 | F68: 0 | G68: 0 | H68: =(G68-F68)*24*60 -> 0 | I68: =H68/60 -> 0 | J68: 4125 | L68: =J68*12 -> 49500 | M68: =K68*I68 -> 0 | N68: =(L68-M68)/L68 -> 1 | O68: =E68/N68 -> 0 | Q68: =O68*J68*24 -> 0 | R68: =Q68-B68 -> 0
A69: 45904 | B69: =Data_Entry!X159 -> 0 | C69: 15 | D69: =Data_Entry!AD159 -> 0 | E69: =B69/(24*J69) -> 0 | F69: 0 | G69: 0 | H69: =(G69-F69)*24*60 -> 0 | I69: =H69/60 -> 0 | J69: 4125 | L69: =J69*12 -> 49500 | M69: =K69*I69 -> 0 | N69: =(L69-M69)/L69 -> 1 | O69: =E69/N69 -> 0 | Q69: =O69*J69*24 -> 0 | R69: =Q69-B69 -> 0
A70: 45905 | B70: =Data_Entry!X160 -> 0 | C70: 15 | D70: =Data_Entry!AD160 -> 0 | E70: =B70/(24*J70) -> 0 | F70: 0 | G70: 0 | H70: =(G70-F70)*24*60 -> 0 | I70: =H70/60 -> 0 | J70: 4125 | L70: =J70*12 -> 49500 | M70: =K70*I70 -> 0 | N70: =(L70-M70)/L70 -> 1 | O70: =E70/N70 -> 0 | Q70: =O70*J70*24 -> 0 | R70: =Q70-B70 -> 0
A71: 45906 | B71: =Data_Entry!X161 -> 0 | C71: 15 | D71: =Data_Entry!AD161 -> 0 | E71: =B71/(24*J71) -> 0 | F71: 0 | G71: 0 | H71: =(G71-F71)*24*60 -> 0 | I71: =H71/60 -> 0 | J71: 4125 | L71: =J71*12 -> 49500 | M71: =K71*I71 -> 0 | N71: =(L71-M71)/L71 -> 1 | O71: =E71/N71 -> 0 | Q71: =O71*J71*24 -> 0 | R71: =Q71-B71 -> 0
A72: 45907 | B72: =Data_Entry!X162 -> 0 | C72: 15 | D72: =Data_Entry!AD162 -> 0 | E72: =B72/(24*J72) -> 0 | F72: 0 | G72: 0 | H72: =(G72-F72)*24*60 -> 0 | I72: =H72/60 -> 0 | J72: 4125 | L72: =J72*12 -> 49500 | M72: =K72*I72 -> 0 | N72: =(L72-M72)/L72 -> 1 | O72: =E72/N72 -> 0 | Q72: =O72*J72*24 -> 0 | R72: =Q72-B72 -> 0
A73: 45908 | B73: =Data_Entry!X163 -> 0 | C73: 15 | D73: =Data_Entry!AD163 -> 0 | E73: =B73/(24*J73) -> 0 | F73: 0 | G73: 0 | H73: =(G73-F73)*24*60 -> 0 | I73: =H73/60 -> 0 | J73: 4125 | L73: =J73*12 -> 49500 | M73: =K73*I73 -> 0 | N73: =(L73-M73)/L73 -> 1 | O73: =E73/N73 -> 0 | Q73: =O73*J73*24 -> 0 | R73: =Q73-B73 -> 0
A74: 45909 | B74: =Data_Entry!X164 -> 400 | C74: 0 | D74: =Data_Entry!AD164 -> 0 | E74: =B74/(24*J74) -> 0.004040404 | F74: 0 | G74: 0 | H74: =(G74-F74)*24*60 -> 0 | I74: =H74/60 -> 0 | J74: 4125 | L74: =J74*12 -> 49500 | M74: =K74*I74 -> 0 | N74: =(L74-M74)/L74 -> 1 | O74: =E74/N74 -> 0.004040404 | Q74: =O74*J74*24 -> 400 | R74: =Q74-B74 -> 0
A75: 45910 | B75: =Data_Entry!X165 -> 1450 | C75: 0 | D75: =Data_Entry!AD165 -> 0 | E75: =B75/(24*J75) -> 0.014646465 | F75: 0 | G75: 0 | H75: =(G75-F75)*24*60 -> 0 | I75: =H75/60 -> 0 | J75: 4125 | L75: =J75*12 -> 49500 | M75: =K75*I75 -> 0 | N75: =(L75-M75)/L75 -> 1 | O75: =E75/N75 -> 0.014646465 | Q75: =O75*J75*24 -> 1450 | R75: =Q75-B75 -> 0
A76: 45911 | B76: =Data_Entry!X166 -> 4650 | C76: 0 | D76: =Data_Entry!AD166 -> 0 | E76: =B76/(24*J76) -> 0.046969697 | F76: 0 | G76: 0 | H76: =(G76-F76)*24*60 -> 0 | I76: =H76/60 -> 0 | J76: 4125 | L76: =J76*12 -> 49500 | M76: =K76*I76 -> 0 | N76: =(L76-M76)/L76 -> 1 | O76: =E76/N76 -> 0.046969697 | Q76: =O76*J76*24 -> 4650 | R76: =Q76-B76 -> 0
A77: 45912 | B77: =Data_Entry!X167 -> 9900 | C77: 0 | D77: =Data_Entry!AD167 -> 0 | E77: =B77/(24*J77) -> 0.1 | F77: 0 | G77: 0 | H77: =(G77-F77)*24*60 -> 0 | I77: =H77/60 -> 0 | J77: 4125 | L77: =J77*12 -> 49500 | M77: =K77*I77 -> 0 | N77: =(L77-M77)/L77 -> 1 | O77: =E77/N77 -> 0.1 | Q77: =O77*J77*24 -> 9900 | R77: =Q77-B77 -> 0
... A93: 45928 | B93: =Data_Entry!X183 -> 6850 | C93: 0 | D93: =Data_Entry!AD183 -> 1.73 | E93: =B93/(24*J93) -> 0.069191919 | F93: 0 | G93: 0 | H93: =(G93-F93)*24*60 -> 0 | I93: =H93/60 -> 0 | J93: 4125 | L93: =J93*12 -> 49500 | M93: =K93*I93 -> 0 | N93: =(L93-M93)/L93 -> 1 | O93: =E93/N93 -> 0.069191919 | Q93: =O93*J93*24 -> 6850 | R93: =Q93-B93 -> 0
A94: 45929 | B94: =Data_Entry!X184 -> 6450 | C94: 15 | D94: =Data_Entry!AD184 -> 1.43 | E94: =B94/(24*J94) -> 0.065151515 | F94: 0.29166667 | G94: 0.36805556 | H94: =(G94-F94)*24*60 -> 110 | I94: =H94/60 -> 1.8333333 | J94: 4125 | K94: 4822.16 | L94: =J94*12 -> 49500 | M94: =K94*I94 -> 8840.6267 | N94: =(L94-M94)/L94 -> 0.82140148 | O94: =E94/N94 -> 0.079317504 | Q94: =O94*J94*24 -> 7852.4329 | R94: =Q94-B94 -> 1402.4329
A95: 45930 | B95: =Data_Entry!X185 -> 8350 | C95: 0 | D95: =Data_Entry!AD185 -> 1.27 | E95: =B95/(24*J95) -> 0.084343434 | F95: 0 | G95: 0 | H95: =(G95-F95)*24*60 -> 0 | I95: =H95/60 -> 0 | J95: 4125 | L95: =J95*12 -> 49500 | M95: =K95*I95 -> 0 | N95: =(L95-M95)/L95 -> 1 | O95: =E95/N95 -> 0.084343434 | Q95: =O95*J95*24 -> 8350 | R95: =Q95-B95 -> 0
A96: 45931 | B96: =Data_Entry!X186 -> 8550 | C96: 0 | D96: =Data_Entry!AD186 -> 1.61 | E96: =B96/(24*J96) -> 0.086363636 | F96: 0 | G96: 0 | H96: =(G96-F96)*24*60 -> 0 | I96: =H96/60 -> 0 | J96: 4125 | L96: =J96*12 -> 49500 | M96: =K96*I96 -> 0 | N96: =(L96-M96)/L96 -> 1 | O96: =E96/N96 -> 0.086363636 | Q96: =O96*J96*24 -> 8550 | R96: =Q96-B96 -> 0
A97: 45932 | B97: =Data_Entry!X187 -> 8000 | C97: 0 | D97: =Data_Entry!AD187 -> 0 | E97: =B97/(24*J97) -> 0.080808081 | F97: 0 | G97: 0 | H97: =(G97-F97)*24*60 -> 0 | I97: =H97/60 -> 0 | J97: 4125 | L97: =J97*12 -> 49500 | M97: =K97*I97 -> 0 | N97: =(L97-M97)/L97 -> 1 | O97: =E97/N97 -> 0.080808081 | Q97: =O97*J97*24 -> 8000 | R97: =Q97-B97 -> 0
A98: 45933 | B98: =Data_Entry!X188 -> 17700 | C98: 0 | D98: =Data_Entry!AD188 -> 4.2 | E98: =B98/(24*J98) -> 0.17878788 | F98: 0 | G98: 0 | H98: =(G98-F98)*24*60 -> 0 | I98: =H98/60 -> 0 | J98: 4125 | L98: =J98*12 -> 49500 | M98: =K98*I98 -> 0 | N98: =(L98-M98)/L98 -> 1 | O98: =E98/N98 -> 0.17878788 | Q98: =O98*J98*24 -> 17700 | R98: =Q98-B98 -> 0
A99: 45934 | B99: =Data_Entry!X189 -> 20150 | C99: 0 | D99: =Data_Entry!AD189 -> 4.19 | E99: =B99/(24*J99) -> 0.20353535 | F99: 0 | G99: 0 | H99: =(G99-F99)*24*60 -> 0 | I99: =H99/60 -> 0 | J99: 4125 | L99: =J99*12 -> 49500 | M99: =K99*I99 -> 0 | N99: =(L99-M99)/L99 -> 1 | O99: =E99/N99 -> 0.20353535 | Q99: =O99*J99*24 -> 20150 | R99: =Q99-B99 -> 0
A100: 45935 | B100: =Data_Entry!X190 -> 19400 | C100: 0 | D100: =Data_Entry!AD190 -> 4.68 | E100: =B100/(24*J100) -> 0.1959596 | F100: 0 | G100: 0 | H100: =(G100-F100)*24*60 -> 0 | I100: =H100/60 -> 0 | J100: 4125 | L100: =J100*12 -> 49500 | M100: =K100*I100 -> 0 | N100: =(L100-M100)/L100 -> 1 | O100: =E100/N100 -> 0.1959596 | Q100: =O100*J100*24 -> 19400 | R100: =Q100-B100 -> 0
A101: 45936 | B101: =Data_Entry!X191 -> 23550 | C101: 0 | D101: =Data_Entry!AD191 -> 4.79 | E101: =B101/(24*J101) -> 0.23787879 | F101: 0 | G101: 0 | H101: =(G101-F101)*24*60 -> 0 | I101: =H101/60 -> 0 | J101: 4125 | L101: =J101*12 -> 49500 | M101: =K101*I101 -> 0 | N101: =(L101-M101)/L101 -> 1 | O101: =E101/N101 -> 0.23787879 | Q101: =O101*J101*24 -> 23550 | R101: =Q101-B101 -> 0
A102: 45937 | B102: =Data_Entry!X192 -> 24350 | C102: 0 | D102: =Data_Entry!AD192 -> 4.87 | E102: =B102/(24*J102) -> 0.2459596 | F102: 0 | G102: 0 | H102: =(G102-F102)*24*60 -> 0 | I102: =H102/60 -> 0 | J102: 4125 | L102: =J102*12 -> 49500 | M102: =K102*I102 -> 0 | N102: =(L102-M102)/L102 -> 1 | O102: =E102/N102 -> 0.2459596 | Q102: =O102*J102*24 -> 24350 | R102: =Q102-B102 -> 0
A103: 45938 | B103: =Data_Entry!X193 -> 26250 | C103: 0 | D103: =Data_Entry!AD193 -> 4.72 | E103: =B103/(24*J103) -> 0.26515152 | F103: 0 | G103: 0 | H103: =(G103-F103)*24*60 -> 0 | I103: =H103/60 -> 0 | J103: 4125 | L103: =J103*12 -> 49500 | M103: =K103*I103 -> 0 | N103: =(L103-M103)/L103 -> 1 | O103: =E103/N103 -> 0.26515152 | Q103: =O103*J103*24 -> 26250 | R103: =Q103-B103 -> 0
A104: 45939 | B104: =Data_Entry!X194 -> 24400 | C104: 0 | D104: =Data_Entry!AD194 -> 4.96 | E104: =B104/(24*J104) -> 0.24646465 | F104: 0 | G104: 0 | H104: =(G104-F104)*24*60 -> 0 | I104: =H104/60 -> 0 | J104: 4125 | L104: =J104*12 -> 49500 | M104: =K104*I104 -> 0 | N104: =(L104-M104)/L104 -> 1 | O104: =E104/N104 -> 0.24646465 | Q104: =O104*J104*24 -> 24400 | R104: =Q104-B104 -> 0
A105: 45940 | B105: =Data_Entry!X195 -> 25650 | C105: 0 | D105: =Data_Entry!AD195 -> 3.9 | E105: =B105/(24*J105) -> 0.25909091 | F105: 0 | G105: 0 | H105: =(G105-F105)*24*60 -> 0 | I105: =H105/60 -> 0 | J105: 4125 | L105: =J105*12 -> 49500 | M105: =K105*I105 -> 0 | N105: =(L105-M105)/L105 -> 1 | O105: =E105/N105 -> 0.25909091 | Q105: =O105*J105*24 -> 25650 | R105: =Q105-B105 -> 0
A106: 45941 | B106: =Data_Entry!X196 -> 25200 | C106: 0 | D106: =Data_Entry!AD196 -> 3.48 | E106: =B106/(24*J106) -> 0.25454545 | F106: 0 | G106: 0 | H106: =(G106-F106)*24*60 -> 0 | I106: =H106/60 -> 0 | J106: 4125 | L106: =J106*12 -> 49500 | M106: =K106*I106 -> 0 | N106: =(L106-M106)/L106 -> 1 | O106: =E106/N106 -> 0.25454545 | Q106: =O106*J106*24 -> 25200 | R106: =Q106-B106 -> 0
... A214: 46049 | B214: =Data_Entry!X304 -> 26150 | C214: 0 | D214: =Data_Entry!AD304 -> 5.94 | E214: =B214/(24*J214) -> 0.26414141 | F214: 0 | G214: 0 | H214: =(G214-F214)*24*60 -> 0 | I214: =H214/60 -> 0 | J214: 4125 | L214: =J214*12 -> 49500 | M214: =K214*I214 -> 0 | N214: =(L214-M214)/L214 -> 1 | O214: =E214/N214 -> 0.26414141 | Q214: =O214*J214*24 -> 26150 | R214: =Q214-B214 -> 0
A215: 46050 | B215: =Data_Entry!X305 -> 27500 | C215: 0 | D215: =Data_Entry!AD305 -> 4.43 | E215: =B215/(24*J215) -> 0.27777778 | F215: 0.54166667 | G215: 0.59722222 | H215: =(G215-F215)*24*60 -> 80 | I215: =H215/60 -> 1.3333333 | J215: 4125 | K215: 137.07 | L215: =J215*12 -> 49500 | M215: =K215*I215 -> 182.76 | N215: =(L215-M215)/L215 -> 0.99630788 | O215: =E215/N215 -> 0.27880717 | P215: curtailment | Q215: =O215*J215*24 -> 27601.91 | R215: =Q215-B215 -> 101.9096
A216: 46051 | B216: =Data_Entry!X306 -> 25100 | C216: 0 | D216: =Data_Entry!AD306 -> 4.28 | E216: =B216/(24*J216) -> 0.25353535 | F216: 0 | G216: 0 | H216: =(G216-F216)*24*60 -> 0 | I216: =H216/60 -> 0 | J216: 4125 | L216: =J216*12 -> 49500 | M216: =K216*I216 -> 0 | N216: =(L216-M216)/L216 -> 1 | O216: =E216/N216 -> 0.25353535 | Q216: =O216*J216*24 -> 25100 | R216: =Q216-B216 -> 0
A217: 46052 | B217: =Data_Entry!X307 -> 20550 | C217: 0 | D217: =Data_Entry!AD307 -> 3.59 | E217: =B217/(24*J217) -> 0.20757576 | F217: 0 | G217: 0 | H217: =(G217-F217)*24*60 -> 0 | I217: =H217/60 -> 0 | J217: 4125 | L217: =J217*12 -> 49500 | M217: =K217*I217 -> 0 | N217: =(L217-M217)/L217 -> 1 | O217: =E217/N217 -> 0.20757576 | Q217: =O217*J217*24 -> 20550 | R217: =Q217-B217 -> 0
A218: 46053 | B218: =Data_Entry!X308 -> 14650 | C218: 0 | D218: =Data_Entry!AD308 -> 2.26 | E218: =B218/(24*J218) -> 0.1479798 | F218: 0 | G218: 0 | H218: =(G218-F218)*24*60 -> 0 | I218: =H218/60 -> 0 | J218: 4125 | L218: =J218*12 -> 49500 | M218: =K218*I218 -> 0 | N218: =(L218-M218)/L218 -> 1 | O218: =E218/N218 -> 0.1479798 | Q218: =O218*J218*24 -> 14650 | R218: =Q218-B218 -> 0
A219: 46054 | B219: =Data_Entry!X309 -> 19600 | C219: 0 | D219: =Data_Entry!AD309 -> 3.4 | E219: =B219/(24*J219) -> 0.1979798 | F219: 0 | G219: 0 | H219: =(G219-F219)*24*60 -> 0 | I219: =H219/60 -> 0 | J219: 4125 | L219: =J219*12 -> 49500 | M219: =K219*I219 -> 0 | N219: =(L219-M219)/L219 -> 1 | O219: =E219/N219 -> 0.1979798 | Q219: =O219*J219*24 -> 19600 | R219: =Q219-B219 -> 0
A220: 46055 | B220: =Data_Entry!X310 -> 19400 | C220: 0 | D220: =Data_Entry!AD310 -> 3.51 | E220: =B220/(24*J220) -> 0.1959596 | F220: 0 | G220: 0 | H220: =(G220-F220)*24*60 -> 0 | I220: =H220/60 -> 0 | J220: 4125 | L220: =J220*12 -> 49500 | M220: =K220*I220 -> 0 | N220: =(L220-M220)/L220 -> 1 | O220: =E220/N220 -> 0.1959596 | Q220: =O220*J220*24 -> 19400 | R220: =Q220-B220 -> 0
A221: 46056 | B221: =Data_Entry!X311 -> 21000 | C221: 0 | D221: =Data_Entry!AD311 -> 3.67 | E221: =B221/(24*J221) -> 0.21212121 | F221: 0 | G221: 0 | H221: =(G221-F221)*24*60 -> 0 | I221: =H221/60 -> 0 | J221: 4125 | L221: =J221*12 -> 49500 | M221: =K221*I221 -> 0 | N221: =(L221-M221)/L221 -> 1 | O221: =E221/N221 -> 0.21212121 | Q221: =O221*J221*24 -> 21000 | R221: =Q221-B221 -> 0
A222: 46057 | B222: =Data_Entry!X312 -> 20900 | C222: 0 | D222: =Data_Entry!AD312 -> 3.73 | E222: =B222/(24*J222) -> 0.21111111 | F222: 0 | G222: 0 | H222: =(G222-F222)*24*60 -> 0 | I222: =H222/60 -> 0 | J222: 4125 | L222: =J222*12 -> 49500 | M222: =K222*I222 -> 0 | N222: =(L222-M222)/L222 -> 1 | O222: =E222/N222 -> 0.21111111 | Q222: =O222*J222*24 -> 20900 | R222: =Q222-B222 -> 0
A223: 46058 | B223: =Data_Entry!X313 -> 23100 | C223: 0 | D223: =Data_Entry!AD313 -> 4.02 | E223: =B223/(24*J223) -> 0.23333333 | F223: 0 | G223: 0 | H223: =(G223-F223)*24*60 -> 0 | I223: =H223/60 -> 0 | J223: 4125 | L223: =J223*12 -> 49500 | M223: =K223*I223 -> 0 | N223: =(L223-M223)/L223 -> 1 | O223: =E223/N223 -> 0.23333333 | Q223: =O223*J223*24 -> 23100 | R223: =Q223-B223 -> 0
A224: 46059 | B224: =Data_Entry!X314 -> 24700 | C224: 0 | D224: =Data_Entry!AD314 -> 4.2 | E224: =B224/(24*J224) -> 0.24949495 | F224: 0 | G224: 0 | H224: =(G224-F224)*24*60 -> 0 | I224: =H224/60 -> 0 | J224: 4125 | L224: =J224*12 -> 49500 | M224: =K224*I224 -> 0 | N224: =(L224-M224)/L224 -> 1 | O224: =E224/N224 -> 0.24949495 | Q224: =O224*J224*24 -> 24700 | R224: =Q224-B224 -> 0
A225: 46060 | B225: =Data_Entry!X315 -> 23150 | C225: 0 | D225: =Data_Entry!AD315 -> 4.08 | E225: =B225/(24*J225) -> 0.23383838 | F225: 0 | G225: 0 | H225: =(G225-F225)*24*60 -> 0 | I225: =H225/60 -> 0 | J225: 4125 | L225: =J225*12 -> 49500 | M225: =K225*I225 -> 0 | N225: =(L225-M225)/L225 -> 1 | O225: =E225/N225 -> 0.23383838 | Q225: =O225*J225*24 -> 23150 | R225: =Q225-B225 -> 0
A226: 46061 | B226: =Data_Entry!X316 -> 21950 | C226: 0 | D226: =Data_Entry!AD316 -> 4.05 | E226: =B226/(24*J226) -> 0.22171717 | F226: 0 | G226: 0 | H226: =(G226-F226)*24*60 -> 0 | I226: =H226/60 -> 0 | J226: 4125 | L226: =J226*12 -> 49500 | M226: =K226*I226 -> 0 | N226: =(L226-M226)/L226 -> 1 | O226: =E226/N226 -> 0.22171717 | Q226: =O226*J226*24 -> 21950 | R226: =Q226-B226 -> 0
...

Sheet Grid Availiblity
A1: Date | B1: ABT Export Gen | C1: GHI | D1: CUF% | E1: Out | F1: In | G1: Total Minute | H1: Outage Hrs. | I1: Plant Capacity | J1: Outage Capacity | K1: Plant Capacity Ratio | L1: Outage Ratio | M1: Grid Availiblity | N1: G.C CUF | O1: G.C Generation | P1: Grid Unit Lose
A2: 45839 | B2: =Data_Entry!X94 -> 15900 | C2: =Data_Entry!AD94 -> 0 | D2: =B2/(24*I2) -> 0.16060606 | E2: 0 | F2: 0 | G2: =(F2-E2)*24*60 -> 0 | H2: =G2/60 -> 0 | I2: 4125 | K2: =I2*12 -> 49500 | L2: =J2*H2 -> 0 | M2: =(K2-L2)/K2 -> 1 | N2: =D2/M2 -> 0.16060606 | O2: =N2*I2*24 -> 15900 | P2: =O2-B2 -> 0
A3: 45840 | B3: =Data_Entry!X95 -> 12000 | C3: =Data_Entry!AD95 -> 0 | D3: =B3/(24*I3) -> 0.12121212 | E3: 0 | F3: 0 | G3: =(F3-E3)*24*60 -> 0 | H3: =G3/60 -> 0 | I3: 4125 | K3: =I3*12 -> 49500 | L3: =J3*H3 -> 0 | M3: =(K3-L3)/K3 -> 1 | N3: =D3/M3 -> 0.12121212 | O3: =N3*I3*24 -> 12000 | P3: =O3-B3 -> 0
A4: 45841 | B4: =Data_Entry!X96 -> 5150 | C4: =Data_Entry!AD96 -> 0 | D4: =B4/(24*I4) -> 0.052020202 | E4: 0 | F4: 0 | G4: =(F4-E4)*24*60 -> 0 | H4: =G4/60 -> 0 | I4: 4125 | K4: =I4*12 -> 49500 | L4: =J4*H4 -> 0 | M4: =(K4-L4)/K4 -> 1 | N4: =D4/M4 -> 0.052020202 | O4: =N4*I4*24 -> 5150 | P4: =O4-B4 -> 0
A5: 45842 | B5: =Data_Entry!X97 -> 9900 | C5: =Data_Entry!AD97 -> 0 | D5: =B5/(24*I5) -> 0.1 | E5: 0 | F5: 0 | G5: =(F5-E5)*24*60 -> 0 | H5: =G5/60 -> 0 | I5: 4125 | K5: =I5*12 -> 49500 | L5: =J5*H5 -> 0 | M5: =(K5-L5)/K5 -> 1 | N5: =D5/M5 -> 0.1 | O5: =N5*I5*24 -> 9900 | P5: =O5-B5 -> 0
A6: 45843 | B6: =Data_Entry!X98 -> 9450 | C6: =Data_Entry!AD98 -> 0 | D6: =B6/(24*I6) -> 0.095454545 | E6: 0 | F6: 0 | G6: =(F6-E6)*24*60 -> 0 | H6: =G6/60 -> 0 | I6: 4125 | K6: =I6*12 -> 49500 | L6: =J6*H6 -> 0 | M6: =(K6-L6)/K6 -> 1 | N6: =D6/M6 -> 0.095454545 | O6: =N6*I6*24 -> 9450 | P6: =O6-B6 -> 0
A7: 45844 | B7: =Data_Entry!X99 -> 13800 | C7: =Data_Entry!AD99 -> 0 | D7: =B7/(24*I7) -> 0.13939394 | E7: 0 | F7: 0 | G7: =(F7-E7)*24*60 -> 0 | H7: =G7/60 -> 0 | I7: 4125 | K7: =I7*12 -> 49500 | L7: =J7*H7 -> 0 | M7: =(K7-L7)/K7 -> 1 | N7: =D7/M7 -> 0.13939394 | O7: =N7*I7*24 -> 13800 | P7: =O7-B7 -> 0
A8: 45845 | B8: =Data_Entry!X100 -> 9300 | C8: =Data_Entry!AD100 -> 0 | D8: =B8/(24*I8) -> 0.093939394 | E8: 0 | F8: 0 | G8: =(F8-E8)*24*60 -> 0 | H8: =G8/60 -> 0 | I8: 4125 | K8: =I8*12 -> 49500 | L8: =J8*H8 -> 0 | M8: =(K8-L8)/K8 -> 1 | N8: =D8/M8 -> 0.093939394 | O8: =N8*I8*24 -> 9300 | P8: =O8-B8 -> 0
A9: 45846 | B9: =Data_Entry!X101 -> 15550 | C9: =Data_Entry!AD101 -> 0 | D9: =B9/(24*I9) -> 0.15707071 | E9: 0 | F9: 0 | G9: =(F9-E9)*24*60 -> 0 | H9: =G9/60 -> 0 | I9: 4125 | K9: =I9*12 -> 49500 | L9: =J9*H9 -> 0 | M9: =(K9-L9)/K9 -> 1 | N9: =D9/M9 -> 0.15707071 | O9: =N9*I9*24 -> 15550 | P9: =O9-B9 -> 0
A10: 45847 | B10: =Data_Entry!X102 -> 21950 | C10: =Data_Entry!AD102 -> 0 | D10: =B10/(24*I10) -> 0.22171717 | E10: 0 | F10: 0 | G10: =(F10-E10)*24*60 -> 0 | H10: =G10/60 -> 0 | I10: 4125 | K10: =I10*12 -> 49500 | L10: =J10*H10 -> 0 | M10: =(K10-L10)/K10 -> 1 | N10: =D10/M10 -> 0.22171717 | O10: =N10*I10*24 -> 21950 | P10: =O10-B10 -> 0
A11: 45848 | B11: =Data_Entry!X103 -> 13400 | C11: =Data_Entry!AD103 -> 0 | D11: =B11/(24*I11) -> 0.13535354 | E11: 0 | F11: 0 | G11: =(F11-E11)*24*60 -> 0 | H11: =G11/60 -> 0 | I11: 4125 | K11: =I11*12 -> 49500 | L11: =J11*H11 -> 0 | M11: =(K11-L11)/K11 -> 1 | N11: =D11/M11 -> 0.13535354 | O11: =N11*I11*24 -> 13400 | P11: =O11-B11 -> 0
A12: 45849 | B12: =Data_Entry!X104 -> 11600 | C12: =Data_Entry!AD104 -> 0 | D12: =B12/(24*I12) -> 0.11717172 | E12: 0 | F12: 0 | G12: =(F12-E12)*24*60 -> 0 | H12: =G12/60 -> 0 | I12: 4125 | K12: =I12*12 -> 49500 | L12: =J12*H12 -> 0 | M12: =(K12-L12)/K12 -> 1 | N12: =D12/M12 -> 0.11717172 | O12: =N12*I12*24 -> 11600 | P12: =O12-B12 -> 0
A13: 45850 | B13: =Data_Entry!X105 -> 19350 | C13: =Data_Entry!AD105 -> 0 | D13: =B13/(24*I13) -> 0.19545455 | E13: 0 | F13: 0 | G13: =(F13-E13)*24*60 -> 0 | H13: =G13/60 -> 0 | I13: 4125 | K13: =I13*12 -> 49500 | L13: =J13*H13 -> 0 | M13: =(K13-L13)/K13 -> 1 | N13: =D13/M13 -> 0.19545455 | O13: =N13*I13*24 -> 19350 | P13: =O13-B13 -> 0
... A32: 45869 | B32: =Data_Entry!X124 -> 11950 | C32: =Data_Entry!AD124 -> 1.81 | D32: =B32/(24*I32) -> 0.12070707 | E32: 0 | F32: 0 | G32: =(F32-E32)*24*60 -> 0 | H32: =G32/60 -> 0 | I32: 4125 | K32: =I32*12 -> 49500 | L32: =J32*H32 -> 0 | M32: =(K32-L32)/K32 -> 1 | N32: =D32/M32 -> 0.12070707 | O32: =N32*I32*24 -> 11950 | P32: =O32-B32 -> 0
A34: 45870 | B34: =Data_Entry!X125 -> 13750 | C34: =Data_Entry!AD125 -> 1.29 | D34: =B34/(24*I34) -> 0.13888889 | E34: 0 | F34: 0 | G34: =(F34-E34)*24*60 -> 0 | H34: =G34/60 -> 0 | I34: 4125 | J34: 13000 | K34: =I34*12 -> 49500 | L34: =J34*H34 -> 0 | M34: =(K34-L34)/K34 -> 1 | N34: =D34/M34 -> 0.13888889 | O34: =N34*I34*24 -> 13750 | P34: =O34-B34 -> 0
A35: 45871 | B35: =Data_Entry!X126 -> 15700 | C35: =Data_Entry!AD126 -> 0.56 | D35: =B35/(24*I35) -> 0.15858586 | G35: =(F35-E35)*24*60 -> 0 | H35: =G35/60 -> 0 | I35: 4125 | K35: =I35*12 -> 49500 | L35: =J35*H35 -> 0 | M35: =(K35-L35)/K35 -> 1 | N35: =D35/M35 -> 0.15858586 | O35: =N35*I35*24 -> 15700 | P35: =O35-B35 -> 0
A36: 45872 | B36: =Data_Entry!X127 -> 11600 | C36: =Data_Entry!AD127 -> 0.45 | D36: =B36/(24*I36) -> 0.11717172 | G36: =(F36-E36)*24*60 -> 0 | H36: =G36/60 -> 0 | I36: 4125 | K36: =I36*12 -> 49500 | L36: =J36*H36 -> 0 | M36: =(K36-L36)/K36 -> 1 | N36: =D36/M36 -> 0.11717172 | O36: =N36*I36*24 -> 11600 | P36: =O36-B36 -> 0
A37: 45873 | B37: =Data_Entry!X128 -> 15300 | C37: =Data_Entry!AD128 -> 0.54 | D37: =B37/(24*I37) -> 0.15454545 | G37: =(F37-E37)*24*60 -> 0 | H37: =G37/60 -> 0 | I37: 4125 | K37: =I37*12 -> 49500 | L37: =J37*H37 -> 0 | M37: =(K37-L37)/K37 -> 1 | N37: =D37/M37 -> 0.15454545 | O37: =N37*I37*24 -> 15300 | P37: =O37-B37 -> 0
A38: 45874 | B38: =Data_Entry!X129 -> 18300 | C38: =Data_Entry!AD129 -> 0.76 | D38: =B38/(24*I38) -> 0.18484848 | G38: =(F38-E38)*24*60 -> 0 | H38: =G38/60 -> 0 | I38: 4125 | K38: =I38*12 -> 49500 | L38: =J38*H38 -> 0 | M38: =(K38-L38)/K38 -> 1 | N38: =D38/M38 -> 0.18484848 | O38: =N38*I38*24 -> 18300 | P38: =O38-B38 -> 0
A39: 45875 | B39: =Data_Entry!X130 -> 16100 | C39: =Data_Entry!AD130 -> 0.66 | D39: =B39/(24*I39) -> 0.16262626 | G39: =(F39-E39)*24*60 -> 0 | H39: =G39/60 -> 0 | I39: 4125 | K39: =I39*12 -> 49500 | L39: =J39*H39 -> 0 | M39: =(K39-L39)/K39 -> 1 | N39: =D39/M39 -> 0.16262626 | O39: =N39*I39*24 -> 16100 | P39: =O39-B39 -> 0
A40: 45876 | B40: =Data_Entry!X131 -> 13450 | C40: =Data_Entry!AD131 -> 0.51 | D40: =B40/(24*I40) -> 0.13585859 | G40: =(F40-E40)*24*60 -> 0 | H40: =G40/60 -> 0 | I40: 4125 | K40: =I40*12 -> 49500 | L40: =J40*H40 -> 0 | M40: =(K40-L40)/K40 -> 1 | N40: =D40/M40 -> 0.13585859 | O40: =N40*I40*24 -> 13450 | P40: =O40-B40 -> 0
A41: 45877 | B41: =Data_Entry!X132 -> 20100 | C41: =Data_Entry!AD132 -> 0.73 | D41: =B41/(24*I41) -> 0.2030303 | G41: =(F41-E41)*24*60 -> 0 | H41: =G41/60 -> 0 | I41: 4125 | K41: =I41*12 -> 49500 | L41: =J41*H41 -> 0 | M41: =(K41-L41)/K41 -> 1 | N41: =D41/M41 -> 0.2030303 | O41: =N41*I41*24 -> 20100 | P41: =O41-B41 -> 0
A42: 45878 | B42: =Data_Entry!X133 -> 12550 | C42: =Data_Entry!AD133 -> 0.41 | D42: =B42/(24*I42) -> 0.12676768 | G42: =(F42-E42)*24*60 -> 0 | H42: =G42/60 -> 0 | I42: 4125 | K42: =I42*12 -> 49500 | L42: =J42*H42 -> 0 | M42: =(K42-L42)/K42 -> 1 | N42: =D42/M42 -> 0.12676768 | O42: =N42*I42*24 -> 12550 | P42: =O42-B42 -> 0
A43: 45879 | B43: =Data_Entry!X134 -> 8550 | C43: =Data_Entry!AD134 -> 0.28 | D43: =B43/(24*I43) -> 0.086363636 | G43: =(F43-E43)*24*60 -> 0 | H43: =G43/60 -> 0 | I43: 4125 | K43: =I43*12 -> 49500 | L43: =J43*H43 -> 0 | M43: =(K43-L43)/K43 -> 1 | N43: =D43/M43 -> 0.086363636 | O43: =N43*I43*24 -> 8550 | P43: =O43-B43 -> 0
A44: 45880 | B44: =Data_Entry!X135 -> 19400 | C44: =Data_Entry!AD135 -> 0.69 | D44: =B44/(24*I44) -> 0.1959596 | G44: =(F44-E44)*24*60 -> 0 | H44: =G44/60 -> 0 | I44: 4125 | K44: =I44*12 -> 49500 | L44: =J44*H44 -> 0 | M44: =(K44-L44)/K44 -> 1 | N44: =D44/M44 -> 0.1959596 | O44: =N44*I44*24 -> 19400 | P44: =O44-B44 -> 0
A45: 45881 | B45: =Data_Entry!X136 -> 11450 | C45: =Data_Entry!AD136 -> 0.44 | D45: =B45/(24*I45) -> 0.11565657 | G45: =(F45-E45)*24*60 -> 0 | H45: =G45/60 -> 0 | I45: 4125 | K45: =I45*12 -> 49500 | L45: =J45*H45 -> 0 | M45: =(K45-L45)/K45 -> 1 | N45: =D45/M45 -> 0.11565657 | O45: =N45*I45*24 -> 11450 | P45: =O45-B45 -> 0
A46: 45882 | B46: =Data_Entry!X137 -> 16350 | C46: =Data_Entry!AD137 -> 0.54 | D46: =B46/(24*I46) -> 0.16515152 | G46: =(F46-E46)*24*60 -> 0 | H46: =G46/60 -> 0 | I46: 4125 | K46: =I46*12 -> 49500 | L46: =J46*H46 -> 0 | M46: =(K46-L46)/K46 -> 1 | N46: =D46/M46 -> 0.16515152 | O46: =N46*I46*24 -> 16350 | P46: =O46-B46 -> 0
A47: 45883 | B47: =Data_Entry!X138 -> 8550 | C47: =Data_Entry!AD138 -> 0.28 | D47: =B47/(24*I47) -> 0.086363636 | E47: 0 | F47: 0 | G47: =(F47-E47)*24*60 -> 0 | H47: =G47/60 -> 0 | I47: 4125 | K47: =I47*12 -> 49500 | L47: =J47*H47 -> 0 | M47: =(K47-L47)/K47 -> 1 | N47: =D47/M47 -> 0.086363636 | O47: =N47*I47*24 -> 8550 | P47: =O47-B47 -> 0
A48: 45884 | B48: =Data_Entry!X139 -> 7000 | C48: =Data_Entry!AD139 -> 0.23 | D48: =B48/(24*I48) -> 0.070707071 | G48: =(F48-E48)*24*60 -> 0 | H48: =G48/60 -> 0 | I48: 4125 | K48: =I48*12 -> 49500 | L48: =J48*H48 -> 0 | M48: =(K48-L48)/K48 -> 1 | N48: =D48/M48 -> 0.070707071 | O48: =N48*I48*24 -> 7000 | P48: =O48-B48 -> 0
A49: 45885 | B49: =Data_Entry!X140 -> 14450 | C49: =Data_Entry!AD140 -> 0.48 | D49: =B49/(24*I49) -> 0.1459596 | G49: =(F49-E49)*24*60 -> 0 | H49: =G49/60 -> 0 | I49: 4125 | K49: =I49*12 -> 49500 | L49: =J49*H49 -> 0 | M49: =(K49-L49)/K49 -> 1 | N49: =D49/M49 -> 0.1459596 | O49: =N49*I49*24 -> 14450 | P49: =O49-B49 -> 0
A50: 45886 | B50: =Data_Entry!X141 -> 16100 | C50: =Data_Entry!AD141 -> 0.51 | D50: =B50/(24*I50) -> 0.16262626 | G50: =(F50-E50)*24*60 -> 0 | H50: =G50/60 -> 0 | I50: 4125 | K50: =I50*12 -> 49500 | L50: =J50*H50 -> 0 | M50: =(K50-L50)/K50 -> 1 | N50: =D50/M50 -> 0.16262626 | O50: =N50*I50*24 -> 16100 | P50: =O50-B50 -> 0
A51: 45887 | B51: =Data_Entry!X142 -> 15600 | C51: =Data_Entry!AD142 -> 3.1 | D51: =B51/(24*I51) -> 0.15757576 | G51: =(F51-E51)*24*60 -> 0 | H51: =G51/60 -> 0 | I51: 4125 | K51: =I51*12 -> 49500 | L51: =J51*H51 -> 0 | M51: =(K51-L51)/K51 -> 1 | N51: =D51/M51 -> 0.15757576 | O51: =N51*I51*24 -> 15600 | P51: =O51-B51 -> 0
A52: 45888 | B52: =Data_Entry!X143 -> 14850 | C52: =Data_Entry!AD143 -> 0 | D52: =B52/(24*I52) -> 0.15 | G52: =(F52-E52)*24*60 -> 0 | H52: =G52/60 -> 0 | I52: 4125 | K52: =I52*12 -> 49500 | L52: =J52*H52 -> 0 | M52: =(K52-L52)/K52 -> 1 | N52: =D52/M52 -> 0.15 | O52: =N52*I52*24 -> 14850 | P52: =O52-B52 -> 0
A53: 45889 | B53: =Data_Entry!X144 -> 0 | C53: =Data_Entry!AD144 -> 0 | D53: =B53/(24*I53) -> 0 | G53: =(F53-E53)*24*60 -> 0 | H53: =G53/60 -> 0 | I53: 4125 | K53: =I53*12 -> 49500 | L53: =J53*H53 -> 0 | M53: =(K53-L53)/K53 -> 1 | N53: =D53/M53 -> 0 | O53: =N53*I53*24 -> 0 | P53: =O53-B53 -> 0
A54: 45890 | B54: =Data_Entry!X145 -> 0 | C54: =Data_Entry!AD145 -> 0 | D54: =B54/(24*I54) -> 0 | G54: =(F54-E54)*24*60 -> 0 | H54: =G54/60 -> 0 | I54: 4125 | K54: =I54*12 -> 49500 | L54: =J54*H54 -> 0 | M54: =(K54-L54)/K54 -> 1 | N54: =D54/M54 -> 0 | O54: =N54*I54*24 -> 0 | P54: =O54-B54 -> 0
A55: 45891 | B55: =Data_Entry!X146 -> 0 | C55: =Data_Entry!AD146 -> 0 | D55: =B55/(24*I55) -> 0 | G55: =(F55-E55)*24*60 -> 0 | H55: =G55/60 -> 0 | I55: 4125 | K55: =I55*12 -> 49500 | L55: =J55*H55 -> 0 | M55: =(K55-L55)/K55 -> 1 | N55: =D55/M55 -> 0 | O55: =N55*I55*24 -> 0 | P55: =O55-B55 -> 0
A56: 45892 | B56: =Data_Entry!X147 -> 0 | C56: =Data_Entry!AD147 -> 0 | D56: =B56/(24*I56) -> 0 | G56: =(F56-E56)*24*60 -> 0 | H56: =G56/60 -> 0 | I56: 4125 | K56: =I56*12 -> 49500 | L56: =J56*H56 -> 0 | M56: =(K56-L56)/K56 -> 1 | N56: =D56/M56 -> 0 | O56: =N56*I56*24 -> 0 | P56: =O56-B56 -> 0
A57: 45893 | B57: =Data_Entry!X148 -> 0 | C57: =Data_Entry!AD148 -> 0 | D57: =B57/(24*I57) -> 0 | G57: =(F57-E57)*24*60 -> 0 | H57: =G57/60 -> 0 | I57: 4125 | K57: =I57*12 -> 49500 | L57: =J57*H57 -> 0 | M57: =(K57-L57)/K57 -> 1 | N57: =D57/M57 -> 0 | O57: =N57*I57*24 -> 0 | P57: =O57-B57 -> 0
A58: 45894 | B58: =Data_Entry!X149 -> 0 | C58: =Data_Entry!AD149 -> 0 | D58: =B58/(24*I58) -> 0 | G58: =(F58-E58)*24*60 -> 0 | H58: =G58/60 -> 0 | I58: 4125 | K58: =I58*12 -> 49500 | L58: =J58*H58 -> 0 | M58: =(K58-L58)/K58 -> 1 | N58: =D58/M58 -> 0 | O58: =N58*I58*24 -> 0 | P58: =O58-B58 -> 0
A59: 45895 | B59: =Data_Entry!X150 -> 0 | C59: =Data_Entry!AD150 -> 0 | D59: =B59/(24*I59) -> 0 | G59: =(F59-E59)*24*60 -> 0 | H59: =G59/60 -> 0 | I59: 4125 | K59: =I59*12 -> 49500 | L59: =J59*H59 -> 0 | M59: =(K59-L59)/K59 -> 1 | N59: =D59/M59 -> 0 | O59: =N59*I59*24 -> 0 | P59: =O59-B59 -> 0
... A64: 45900 | B64: =Data_Entry!X155 -> 0 | C64: =Data_Entry!AD155 -> 0 | D64: =B64/(24*I64) -> 0 | G64: =(F64-E64)*24*60 -> 0 | H64: =G64/60 -> 0 | I64: 4125 | K64: =I64*12 -> 49500 | L64: =J64*H64 -> 0 | M64: =(K64-L64)/K64 -> 1 | N64: =D64/M64 -> 0 | O64: =N64*I64*24 -> 0 | P64: =O64-B64 -> 0
M65: =AVERAGE(M34:M64) -> 1
A66: 45901 | B66: =Data_Entry!X156 -> 0 | C66: =Data_Entry!AD156 -> 0 | D66: =B66/(24*I66) -> 0 | G66: =(F66-E66)*24*60 -> 0 | H66: =G66/60 -> 0 | I66: 4125 | K66: =I66*12 -> 49500 | L66: =J66*H66 -> 0 | M66: =(K66-L66)/K66 -> 1 | N66: =D66/M66 -> 0 | O66: =N66*I66*24 -> 0 | P66: =O66-B66 -> 0
A67: 45902 | B67: =Data_Entry!X157 -> 0 | C67: =Data_Entry!AD157 -> 0 | D67: =B67/(24*I67) -> 0 | G67: =(F67-E67)*24*60 -> 0 | H67: =G67/60 -> 0 | I67: 4125 | K67: =I67*12 -> 49500 | L67: =J67*H67 -> 0 | M67: =(K67-L67)/K67 -> 1 | N67: =D67/M67 -> 0 | O67: =N67*I67*24 -> 0 | P67: =O67-B67 -> 0
A68: 45903 | B68: =Data_Entry!X158 -> 0 | C68: =Data_Entry!AD158 -> 0 | D68: =B68/(24*I68) -> 0 | G68: =(F68-E68)*24*60 -> 0 | H68: =G68/60 -> 0 | I68: 4125 | K68: =I68*12 -> 49500 | L68: =J68*H68 -> 0 | M68: =(K68-L68)/K68 -> 1 | N68: =D68/M68 -> 0 | O68: =N68*I68*24 -> 0 | P68: =O68-B68 -> 0
A69: 45904 | B69: =Data_Entry!X159 -> 0 | C69: =Data_Entry!AD159 -> 0 | D69: =B69/(24*I69) -> 0 | G69: =(F69-E69)*24*60 -> 0 | H69: =G69/60 -> 0 | I69: 4125 | K69: =I69*12 -> 49500 | L69: =J69*H69 -> 0 | M69: =(K69-L69)/K69 -> 1 | N69: =D69/M69 -> 0 | O69: =N69*I69*24 -> 0 | P69: =O69-B69 -> 0
A70: 45905 | B70: =Data_Entry!X160 -> 0 | C70: =Data_Entry!AD160 -> 0 | D70: =B70/(24*I70) -> 0 | G70: =(F70-E70)*24*60 -> 0 | H70: =G70/60 -> 0 | I70: 4125 | K70: =I70*12 -> 49500 | L70: =J70*H70 -> 0 | M70: =(K70-L70)/K70 -> 1 | N70: =D70/M70 -> 0 | O70: =N70*I70*24 -> 0 | P70: =O70-B70 -> 0
A71: 45906 | B71: =Data_Entry!X161 -> 0 | C71: =Data_Entry!AD161 -> 0 | D71: =B71/(24*I71) -> 0 | G71: =(F71-E71)*24*60 -> 0 | H71: =G71/60 -> 0 | I71: 4125 | K71: =I71*12 -> 49500 | L71: =J71*H71 -> 0 | M71: =(K71-L71)/K71 -> 1 | N71: =D71/M71 -> 0 | O71: =N71*I71*24 -> 0 | P71: =O71-B71 -> 0
A72: 45907 | B72: =Data_Entry!X162 -> 0 | C72: =Data_Entry!AD162 -> 0 | D72: =B72/(24*I72) -> 0 | G72: =(F72-E72)*24*60 -> 0 | H72: =G72/60 -> 0 | I72: 4125 | K72: =I72*12 -> 49500 | L72: =J72*H72 -> 0 | M72: =(K72-L72)/K72 -> 1 | N72: =D72/M72 -> 0 | O72: =N72*I72*24 -> 0 | P72: =O72-B72 -> 0
A73: 45908 | B73: =Data_Entry!X163 -> 0 | C73: =Data_Entry!AD163 -> 0 | D73: =B73/(24*I73) -> 0 | G73: =(F73-E73)*24*60 -> 0 | H73: =G73/60 -> 0 | I73: 4125 | K73: =I73*12 -> 49500 | L73: =J73*H73 -> 0 | M73: =(K73-L73)/K73 -> 1 | N73: =D73/M73 -> 0 | O73: =N73*I73*24 -> 0 | P73: =O73-B73 -> 0
A74: 45909 | B74: =Data_Entry!X164 -> 400 | C74: =Data_Entry!AD164 -> 0 | D74: =B74/(24*I74) -> 0.004040404 | G74: =(F74-E74)*24*60 -> 0 | H74: =G74/60 -> 0 | I74: 4125 | K74: =I74*12 -> 49500 | L74: =J74*H74 -> 0 | M74: =(K74-L74)/K74 -> 1 | N74: =D74/M74 -> 0.004040404 | O74: =N74*I74*24 -> 400 | P74: =O74-B74 -> 0
A75: 45910 | B75: =Data_Entry!X165 -> 1450 | C75: =Data_Entry!AD165 -> 0 | D75: =B75/(24*I75) -> 0.014646465 | G75: =(F75-E75)*24*60 -> 0 | H75: =G75/60 -> 0 | I75: 4125 | K75: =I75*12 -> 49500 | L75: =J75*H75 -> 0 | M75: =(K75-L75)/K75 -> 1 | N75: =D75/M75 -> 0.014646465 | O75: =N75*I75*24 -> 1450 | P75: =O75-B75 -> 0
A76: 45911 | B76: =Data_Entry!X166 -> 4650 | C76: =Data_Entry!AD166 -> 0 | D76: =B76/(24*I76) -> 0.046969697 | G76: =(F76-E76)*24*60 -> 0 | H76: =G76/60 -> 0 | I76: 4125 | K76: =I76*12 -> 49500 | L76: =J76*H76 -> 0 | M76: =(K76-L76)/K76 -> 1 | N76: =D76/M76 -> 0.046969697 | O76: =N76*I76*24 -> 4650 | P76: =O76-B76 -> 0
A77: 45912 | B77: =Data_Entry!X167 -> 9900 | C77: =Data_Entry!AD167 -> 0 | D77: =B77/(24*I77) -> 0.1 | G77: =(F77-E77)*24*60 -> 0 | H77: =G77/60 -> 0 | I77: 4125 | K77: =I77*12 -> 49500 | L77: =J77*H77 -> 0 | M77: =(K77-L77)/K77 -> 1 | N77: =D77/M77 -> 0.1 | O77: =N77*I77*24 -> 9900 | P77: =O77-B77 -> 0
... A128: 45963 | B128: =Data_Entry!X218 -> 19350 | C128: =Data_Entry!AD218 -> 2.92 | D128: =B128/(24*I128) -> 0.19545455 | G128: =(F128-E128)*24*60 -> 0 | H128: =G128/60 -> 0 | I128: 4125 | K128: =I128*12 -> 49500 | L128: =J128*H128 -> 0 | M128: =(K128-L128)/K128 -> 1 | N128: =D128/M128 -> 0.19545455 | O128: =N128*I128*24 -> 19350 | P128: =O128-B128 -> 0
A129: 45964 | B129: =Data_Entry!X219 -> 21250 | C129: =Data_Entry!AD219 -> 3.98 | D129: =B129/(24*I129) -> 0.21464646 | E129: 0.46527778 | F129: 0.48263889 | G129: =(F129-E129)*24*60 -> 25 | H129: =G129/60 -> 0.41666667 | I129: 4125 | J129: 4125 | K129: =I129*12 -> 49500 | L129: =J129*H129 -> 1718.75 | M129: =(K129-L129)/K129 -> 0.96527778 | N129: =D129/M129 -> 0.22236756 | O129: =N129*I129*24 -> 22014.388 | P129: =O129-B129 -> 764.38849
A130: 45965 | B130: =Data_Entry!X220 -> 23500 | C130: =Data_Entry!AD220 -> 4 | D130: =B130/(24*I130) -> 0.23737374 | G130: =(F130-E130)*24*60 -> 0 | H130: =G130/60 -> 0 | I130: 4125 | K130: =I130*12 -> 49500 | L130: =J130*H130 -> 0 | M130: =(K130-L130)/K130 -> 1 | N130: =D130/M130 -> 0.23737374 | O130: =N130*I130*24 -> 23500 | P130: =O130-B130 -> 0
A131: 45966 | B131: =Data_Entry!X221 -> 25450 | C131: =Data_Entry!AD221 -> 4.39 | D131: =B131/(24*I131) -> 0.25707071 | G131: =(F131-E131)*24*60 -> 0 | H131: =G131/60 -> 0 | I131: 4125 | K131: =I131*12 -> 49500 | L131: =J131*H131 -> 0 | M131: =(K131-L131)/K131 -> 1 | N131: =D131/M131 -> 0.25707071 | O131: =N131*I131*24 -> 25450 | P131: =O131-B131 -> 0
A132: 45967 | B132: =Data_Entry!X222 -> 24950 | C132: =Data_Entry!AD222 -> 4.39 | D132: =B132/(24*I132) -> 0.2520202 | G132: =(F132-E132)*24*60 -> 0 | H132: =G132/60 -> 0 | I132: 4125 | K132: =I132*12 -> 49500 | L132: =J132*H132 -> 0 | M132: =(K132-L132)/K132 -> 1 | N132: =D132/M132 -> 0.2520202 | O132: =N132*I132*24 -> 24950 | P132: =O132-B132 -> 0
A133: 45968 | B133: =Data_Entry!X223 -> 23800 | C133: =Data_Entry!AD223 -> 4.27 | D133: =B133/(24*I133) -> 0.24040404 | G133: =(F133-E133)*24*60 -> 0 | H133: =G133/60 -> 0 | I133: 4125 | K133: =I133*12 -> 49500 | L133: =J133*H133 -> 0 | M133: =(K133-L133)/K133 -> 1 | N133: =D133/M133 -> 0.24040404 | O133: =N133*I133*24 -> 23800 | P133: =O133-B133 -> 0
A134: 45969 | B134: =Data_Entry!X224 -> 24900 | C134: =Data_Entry!AD224 -> 4.48 | D134: =B134/(24*I134) -> 0.25151515 | G134: =(F134-E134)*24*60 -> 0 | H134: =G134/60 -> 0 | I134: 4125 | K134: =I134*12 -> 49500 | L134: =J134*H134 -> 0 | M134: =(K134-L134)/K134 -> 1 | N134: =D134/M134 -> 0.25151515 | O134: =N134*I134*24 -> 24900 | P134: =O134-B134 -> 0
A135: 45970 | B135: =Data_Entry!X225 -> 24800 | C135: =Data_Entry!AD225 -> 4.46 | D135: =B135/(24*I135) -> 0.25050505 | G135: =(F135-E135)*24*60 -> 0 | H135: =G135/60 -> 0 | I135: 4125 | K135: =I135*12 -> 49500 | L135: =J135*H135 -> 0 | M135: =(K135-L135)/K135 -> 1 | N135: =D135/M135 -> 0.25050505 | O135: =N135*I135*24 -> 24800 | P135: =O135-B135 -> 0
A136: 45971 | B136: =Data_Entry!X226 -> 24050 | C136: =Data_Entry!AD226 -> 2.21 | D136: =B136/(24*I136) -> 0.24292929 | G136: =(F136-E136)*24*60 -> 0 | H136: =G136/60 -> 0 | I136: 4125 | K136: =I136*12 -> 49500 | L136: =J136*H136 -> 0 | M136: =(K136-L136)/K136 -> 1 | N136: =D136/M136 -> 0.24292929 | O136: =N136*I136*24 -> 24050 | P136: =O136-B136 -> 0
A137: 45972 | B137: =Data_Entry!X227 -> 24300 | C137: =Data_Entry!AD227 -> 4.33 | D137: =B137/(24*I137) -> 0.24545455 | G137: =(F137-E137)*24*60 -> 0 | H137: =G137/60 -> 0 | I137: 4125 | K137: =I137*12 -> 49500 | L137: =J137*H137 -> 0 | M137: =(K137-L137)/K137 -> 1 | N137: =D137/M137 -> 0.24545455 | O137: =N137*I137*24 -> 24300 | P137: =O137-B137 -> 0
A138: 45973 | B138: =Data_Entry!X228 -> 23950 | C138: =Data_Entry!AD228 -> 4.3 | D138: =B138/(24*I138) -> 0.24191919 | G138: =(F138-E138)*24*60 -> 0 | H138: =G138/60 -> 0 | I138: 4125 | K138: =I138*12 -> 49500 | L138: =J138*H138 -> 0 | M138: =(K138-L138)/K138 -> 1 | N138: =D138/M138 -> 0.24191919 | O138: =N138*I138*24 -> 23950 | P138: =O138-B138 -> 0
A139: 45974 | B139: =Data_Entry!X229 -> 23450 | C139: =Data_Entry!AD229 -> 4.25 | D139: =B139/(24*I139) -> 0.23686869 | G139: =(F139-E139)*24*60 -> 0 | H139: =G139/60 -> 0 | I139: 4125 | K139: =I139*12 -> 49500 | L139: =J139*H139 -> 0 | M139: =(K139-L139)/K139 -> 1 | N139: =D139/M139 -> 0.23686869 | O139: =N139*I139*24 -> 23450 | P139: =O139-B139 -> 0
A140: 45975 | B140: =Data_Entry!X230 -> 23300 | C140: =Data_Entry!AD230 -> 4.27 | D140: =B140/(24*I140) -> 0.23535354 | G140: =(F140-E140)*24*60 -> 0 | H140: =G140/60 -> 0 | I140: 4125 | K140: =I140*12 -> 49500 | L140: =J140*H140 -> 0 | M140: =(K140-L140)/K140 -> 1 | N140: =D140/M140 -> 0.23535354 | O140: =N140*I140*24 -> 23300 | P140: =O140-B140 -> 0
A141: 45976 | B141: =Data_Entry!X231 -> 11700 | C141: =Data_Entry!AD231 -> 2.41 | D141: =B141/(24*I141) -> 0.11818182 | E141: 0.29166667 | F141: 0.51458333 | G141: =(F141-E141)*24*60 -> 321 | H141: =G141/60 -> 5.35 | I141: 4125 | J141: 4125 | K141: =I141*12 -> 49500 | L141: =J141*H141 -> 22068.75 | M141: =(K141-L141)/K141 -> 0.55416667 | N141: =D141/M141 -> 0.21326042 | O141: =N141*I141*24 -> 21112.782 | P141: =O141-B141 -> 9412.782
A142: 45977 | B142: =Data_Entry!X232 -> 20950 | C142: =Data_Entry!AD232 -> 4.01 | D142: =B142/(24*I142) -> 0.21161616 | G142: =(F142-E142)*24*60 -> 0 | H142: =G142/60 -> 0 | I142: 4125 | K142: =I142*12 -> 49500 | L142: =J142*H142 -> 0 | M142: =(K142-L142)/K142 -> 1 | N142: =D142/M142 -> 0.21161616 | O142: =N142*I142*24 -> 20950 | P142: =O142-B142 -> 0
A143: 45978 | B143: =Data_Entry!X233 -> 22800 | C143: =Data_Entry!AD233 -> 4.21 | D143: =B143/(24*I143) -> 0.23030303 | G143: =(F143-E143)*24*60 -> 0 | H143: =G143/60 -> 0 | I143: 4125 | K143: =I143*12 -> 49500 | L143: =J143*H143 -> 0 | M143: =(K143-L143)/K143 -> 1 | N143: =D143/M143 -> 0.23030303 | O143: =N143*I143*24 -> 22800 | P143: =O143-B143 -> 0
A144: 45979 | B144: =Data_Entry!X234 -> 22500 | C144: =Data_Entry!AD234 -> 4.22 | D144: =B144/(24*I144) -> 0.22727273 | G144: =(F144-E144)*24*60 -> 0 | H144: =G144/60 -> 0 | I144: 4125 | K144: =I144*12 -> 49500 | L144: =J144*H144 -> 0 | M144: =(K144-L144)/K144 -> 1 | N144: =D144/M144 -> 0.22727273 | O144: =N144*I144*24 -> 22500 | P144: =O144-B144 -> 0
A145: 45980 | B145: =Data_Entry!X235 -> 21500 | C145: =Data_Entry!AD235 -> 3.96 | D145: =B145/(24*I145) -> 0.21717172 | G145: =(F145-E145)*24*60 -> 0 | H145: =G145/60 -> 0 | I145: 4125 | K145: =I145*12 -> 49500 | L145: =J145*H145 -> 0 | M145: =(K145-L145)/K145 -> 1 | N145: =D145/M145 -> 0.21717172 | O145: =N145*I145*24 -> 21500 | P145: =O145-B145 -> 0
A146: 45981 | B146: =Data_Entry!X236 -> 21550 | C146: =Data_Entry!AD236 -> 3.94 | D146: =B146/(24*I146) -> 0.21767677 | G146: =(F146-E146)*24*60 -> 0 | H146: =G146/60 -> 0 | I146: 4125 | K146: =I146*12 -> 49500 | L146: =J146*H146 -> 0 | M146: =(K146-L146)/K146 -> 1 | N146: =D146/M146 -> 0.21767677 | O146: =N146*I146*24 -> 21550 | P146: =O146-B146 -> 0
A147: 45982 | B147: =Data_Entry!X237 -> 19350 | C147: =Data_Entry!AD237 -> 3.67 | D147: =B147/(24*I147) -> 0.19545455 | E147: 0.40625 | F147: 0.42708333 | G147: =(F147-E147)*24*60 -> 30 | H147: =G147/60 -> 0.5 | I147: 4125 | J147: 4125 | K147: =I147*12 -> 49500 | L147: =J147*H147 -> 2062.5 | M147: =(K147-L147)/K147 -> 0.95833333 | N147: =D147/M147 -> 0.20395257 | O147: =N147*I147*24 -> 20191.304 | P147: =O147-B147 -> 841.30435
A148: 45983 | B148: =Data_Entry!X238 -> 21300 | C148: =Data_Entry!AD238 -> 3.92 | D148: =B148/(24*I148) -> 0.21515152 | G148: =(F148-E148)*24*60 -> 0 | H148: =G148/60 -> 0 | I148: 4125 | K148: =I148*12 -> 49500 | L148: =J148*H148 -> 0 | M148: =(K148-L148)/K148 -> 1 | N148: =D148/M148 -> 0.21515152 | O148: =N148*I148*24 -> 21300 | P148: =O148-B148 -> 0
A149: 45984 | B149: =Data_Entry!X239 -> 21700 | C149: =Data_Entry!AD239 -> 4.02 | D149: =B149/(24*I149) -> 0.21919192 | G149: =(F149-E149)*24*60 -> 0 | H149: =G149/60 -> 0 | I149: 4125 | K149: =I149*12 -> 49500 | L149: =J149*H149 -> 0 | M149: =(K149-L149)/K149 -> 1 | N149: =D149/M149 -> 0.21919192 | O149: =N149*I149*24 -> 21700 | P149: =O149-B149 -> 0
A150: 45985 | B150: =Data_Entry!X240 -> 23150 | C150: =Data_Entry!AD240 -> 4.16 | D150: =B150/(24*I150) -> 0.23383838 | G150: =(F150-E150)*24*60 -> 0 | H150: =G150/60 -> 0 | I150: 4125 | K150: =I150*12 -> 49500 | L150: =J150*H150 -> 0 | M150: =(K150-L150)/K150 -> 1 | N150: =D150/M150 -> 0.23383838 | O150: =N150*I150*24 -> 23150 | P150: =O150-B150 -> 0
A151: 45986 | B151: =Data_Entry!X241 -> 21650 | C151: =Data_Entry!AD241 -> 3.9 | D151: =B151/(24*I151) -> 0.21868687 | G151: =(F151-E151)*24*60 -> 0 | H151: =G151/60 -> 0 | I151: 4125 | K151: =I151*12 -> 49500 | L151: =J151*H151 -> 0 | M151: =(K151-L151)/K151 -> 1 | N151: =D151/M151 -> 0.21868687 | O151: =N151*I151*24 -> 21650 | P151: =O151-B151 -> 0
A152: 45987 | B152: =Data_Entry!X242 -> 20150 | C152: =Data_Entry!AD242 -> 3.7 | D152: =B152/(24*I152) -> 0.20353535 | G152: =(F152-E152)*24*60 -> 0 | H152: =G152/60 -> 0 | I152: 4125 | K152: =I152*12 -> 49500 | L152: =J152*H152 -> 0 | M152: =(K152-L152)/K152 -> 1 | N152: =D152/M152 -> 0.20353535 | O152: =N152*I152*24 -> 20150 | P152: =O152-B152 -> 0
A153: 45988 | B153: =Data_Entry!X243 -> 18950 | C153: =Data_Entry!AD243 -> 3.43 | D153: =B153/(24*I153) -> 0.19141414 | G153: =(F153-E153)*24*60 -> 0 | H153: =G153/60 -> 0 | I153: 4125 | K153: =I153*12 -> 49500 | L153: =J153*H153 -> 0 | M153: =(K153-L153)/K153 -> 1 | N153: =D153/M153 -> 0.19141414 | O153: =N153*I153*24 -> 18950 | P153: =O153-B153 -> 0
A154: 45989 | B154: =Data_Entry!X244 -> 16650 | C154: =Data_Entry!AD244 -> 3.13 | D154: =B154/(24*I154) -> 0.16818182 | G154: =(F154-E154)*24*60 -> 0 | H154: =G154/60 -> 0 | I154: 4125 | K154: =I154*12 -> 49500 | L154: =J154*H154 -> 0 | M154: =(K154-L154)/K154 -> 1 | N154: =D154/M154 -> 0.16818182 | O154: =N154*I154*24 -> 16650 | P154: =O154-B154 -> 0
A155: 45990 | B155: =Data_Entry!X245 -> 17350 | C155: =Data_Entry!AD245 -> 3.35 | D155: =B155/(24*I155) -> 0.17525253 | E155: 0.49444444 | F155: 0.50069444 | G155: =(F155-E155)*24*60 -> 9 | H155: =G155/60 -> 0.15 | I155: 4125 | J155: 4125 | K155: =I155*12 -> 49500 | L155: =J155*H155 -> 618.75 | M155: =(K155-L155)/K155 -> 0.9875 | N155: =D155/M155 -> 0.17747091 | O155: =N155*I155*24 -> 17569.62 | P155: =O155-B155 -> 219.62025
A156: 45991 | B156: =Data_Entry!X246 -> 20150 | C156: =Data_Entry!AD246 -> 3.71 | D156: =B156/(24*I156) -> 0.20353535 | G156: =(F156-E156)*24*60 -> 0 | H156: =G156/60 -> 0 | I156: 4125 | K156: =I156*12 -> 49500 | L156: =J156*H156 -> 0 | M156: =(K156-L156)/K156 -> 1 | N156: =D156/M156 -> 0.20353535 | O156: =N156*I156*24 -> 20150 | P156: =O156-B156 -> 0
A157: 45992 | B157: =Data_Entry!X247 -> 21350 | C157: =Data_Entry!AD247 -> 3.81 | D157: =B157/(24*I157) -> 0.21565657 | G157: =(F157-E157)*24*60 -> 0 | H157: =G157/60 -> 0 | I157: 4125 | K157: =I157*12 -> 49500 | L157: =J157*H157 -> 0 | M157: =(K157-L157)/K157 -> 1 | N157: =D157/M157 -> 0.21565657 | O157: =N157*I157*24 -> 21350 | P157: =O157-B157 -> 0
A158: 45993 | B158: =Data_Entry!X248 -> 19300 | C158: =Data_Entry!AD248 -> 3.5 | D158: =B158/(24*I158) -> 0.19494949 | G158: =(F158-E158)*24*60 -> 0 | H158: =G158/60 -> 0 | I158: 4125 | K158: =I158*12 -> 49500 | L158: =J158*H158 -> 0 | M158: =(K158-L158)/K158 -> 1 | N158: =D158/M158 -> 0.19494949 | O158: =N158*I158*24 -> 19300 | P158: =O158-B158 -> 0
A159: 45994 | B159: =Data_Entry!X249 -> 21300 | C159: =Data_Entry!AD249 -> 3.8 | D159: =B159/(24*I159) -> 0.21515152 | G159: =(F159-E159)*24*60 -> 0 | H159: =G159/60 -> 0 | I159: 4125 | K159: =I159*12 -> 49500 | L159: =J159*H159 -> 0 | M159: =(K159-L159)/K159 -> 1 | N159: =D159/M159 -> 0.21515152 | O159: =N159*I159*24 -> 21300 | P159: =O159-B159 -> 0
A160: 45995 | B160: =Data_Entry!X250 -> 20000 | C160: =Data_Entry!AD250 -> 3.65 | D160: =B160/(24*I160) -> 0.2020202 | G160: =(F160-E160)*24*60 -> 0 | H160: =G160/60 -> 0 | I160: 4125 | K160: =I160*12 -> 49500 | L160: =J160*H160 -> 0 | M160: =(K160-L160)/K160 -> 1 | N160: =D160/M160 -> 0.2020202 | O160: =N160*I160*24 -> 20000 | P160: =O160-B160 -> 0
A161: 45996 | B161: =Data_Entry!X251 -> 20350 | C161: =Data_Entry!AD251 -> 3.65 | D161: =B161/(24*I161) -> 0.20555556 | G161: =(F161-E161)*24*60 -> 0 | H161: =G161/60 -> 0 | I161: 4125 | K161: =I161*12 -> 49500 | L161: =J161*H161 -> 0 | M161: =(K161-L161)/K161 -> 1 | N161: =D161/M161 -> 0.20555556 | O161: =N161*I161*24 -> 20350 | P161: =O161-B161 -> 0
A162: 45997 | B162: =Data_Entry!X252 -> 19200 | C162: =Data_Entry!AD252 -> 3.45 | D162: =B162/(24*I162) -> 0.19393939 | G162: =(F162-E162)*24*60 -> 0 | H162: =G162/60 -> 0 | I162: 4125 | K162: =I162*12 -> 49500 | L162: =J162*H162 -> 0 | M162: =(K162-L162)/K162 -> 1 | N162: =D162/M162 -> 0.19393939 | O162: =N162*I162*24 -> 19200 | P162: =O162-B162 -> 0
A163: 45998 | B163: =Data_Entry!X253 -> 21450 | C163: =Data_Entry!AD253 -> 3.81 | D163: =B163/(24*I163) -> 0.21666667 | G163: =(F163-E163)*24*60 -> 0 | H163: =G163/60 -> 0 | I163: 4125 | K163: =I163*12 -> 49500 | L163: =J163*H163 -> 0 | M163: =(K163-L163)/K163 -> 1 | N163: =D163/M163 -> 0.21666667 | O163: =N163*I163*24 -> 21450 | P163: =O163-B163 -> 0
A164: 45999 | B164: =Data_Entry!X254 -> 21450 | C164: =Data_Entry!AD254 -> 3.82 | D164: =B164/(24*I164) -> 0.21666667 | G164: =(F164-E164)*24*60 -> 0 | H164: =G164/60 -> 0 | I164: 4125 | K164: =I164*12 -> 49500 | L164: =J164*H164 -> 0 | M164: =(K164-L164)/K164 -> 1 | N164: =D164/M164 -> 0.21666667 | O164: =N164*I164*24 -> 21450 | P164: =O164-B164 -> 0
A165: 46000 | B165: =Data_Entry!X255 -> 23100 | C165: =Data_Entry!AD255 -> 4.13 | D165: =B165/(24*I165) -> 0.23333333 | G165: =(F165-E165)*24*60 -> 0 | H165: =G165/60 -> 0 | I165: 4125 | K165: =I165*12 -> 49500 | L165: =J165*H165 -> 0 | M165: =(K165-L165)/K165 -> 1 | N165: =D165/M165 -> 0.23333333 | O165: =N165*I165*24 -> 23100 | P165: =O165-B165 -> 0
A166: 46001 | B166: =Data_Entry!X256 -> 23250 | C166: =Data_Entry!AD256 -> 4.07 | D166: =B166/(24*I166) -> 0.23484848 | G166: =(F166-E166)*24*60 -> 0 | H166: =G166/60 -> 0 | I166: 4125 | K166: =I166*12 -> 49500 | L166: =J166*H166 -> 0 | M166: =(K166-L166)/K166 -> 1 | N166: =D166/M166 -> 0.23484848 | O166: =N166*I166*24 -> 23250 | P166: =O166-B166 -> 0
A167: 46002 | B167: =Data_Entry!X257 -> 22900 | C167: =Data_Entry!AD257 -> 4.12 | D167: =B167/(24*I167) -> 0.23131313 | G167: =(F167-E167)*24*60 -> 0 | H167: =G167/60 -> 0 | I167: 4125 | K167: =I167*12 -> 49500 | L167: =J167*H167 -> 0 | M167: =(K167-L167)/K167 -> 1 | N167: =D167/M167 -> 0.23131313 | O167: =N167*I167*24 -> 22900 | P167: =O167-B167 -> 0
... A172: 46007 | B172: =Data_Entry!X262 -> 21800 | C172: =Data_Entry!AD262 -> 3.75 | D172: =B172/(24*I172) -> 0.22020202 | G172: =(F172-E172)*24*60 -> 0 | H172: =G172/60 -> 0 | I172: 4125 | K172: =I172*12 -> 49500 | L172: =J172*H172 -> 0 | M172: =(K172-L172)/K172 -> 1 | N172: =D172/M172 -> 0.22020202 | O172: =N172*I172*24 -> 21800 | P172: =O172-B172 -> 0
A173: 46008 | B173: =Data_Entry!X263 -> 20150 | C173: =Data_Entry!AD263 -> 3.49 | D173: =B173/(24*I173) -> 0.20353535 | E173: 0.3125 | F173: 0.35347222 | G173: =(F173-E173)*24*60 -> 59 | H173: =G173/60 -> 0.98333333 | I173: 4125 | J173: 4125 | K173: =I173*12 -> 49500 | L173: =J173*H173 -> 4056.25 | M173: =(K173-L173)/K173 -> 0.91805556 | N173: =D173/M173 -> 0.22170265 | O173: =N173*I173*24 -> 21948.563 | P173: =O173-B173 -> 1798.5628
A174: 46009 | B174: =Data_Entry!X264 -> 20850 | C174: =Data_Entry!AD264 -> 3.74 | D174: =B174/(24*I174) -> 0.21060606 | G174: =(F174-E174)*24*60 -> 0 | H174: =G174/60 -> 0 | I174: 4125 | K174: =I174*12 -> 49500 | L174: =J174*H174 -> 0 | M174: =(K174-L174)/K174 -> 1 | N174: =D174/M174 -> 0.21060606 | O174: =N174*I174*24 -> 20850 | P174: =O174-B174 -> 0
A175: 46010 | B175: =Data_Entry!X265 -> 23050 | C175: =Data_Entry!AD265 -> 3.94 | D175: =B175/(24*I175) -> 0.23282828 | G175: =(F175-E175)*24*60 -> 0 | H175: =G175/60 -> 0 | I175: 4125 | K175: =I175*12 -> 49500 | L175: =J175*H175 -> 0 | M175: =(K175-L175)/K175 -> 1 | N175: =D175/M175 -> 0.23282828 | O175: =N175*I175*24 -> 23050 | P175: =O175-B175 -> 0
A176: 46011 | B176: =Data_Entry!X266 -> 22950 | C176: =Data_Entry!AD266 -> 4.1 | D176: =B176/(24*I176) -> 0.23181818 | G176: =(F176-E176)*24*60 -> 0 | H176: =G176/60 -> 0 | I176: 4125 | K176: =I176*12 -> 49500 | L176: =J176*H176 -> 0 | M176: =(K176-L176)/K176 -> 1 | N176: =D176/M176 -> 0.23181818 | O176: =N176*I176*24 -> 22950 | P176: =O176-B176 -> 0
A177: 46012 | B177: =Data_Entry!X267 -> 19700 | C177: =Data_Entry!AD267 -> 3.22 | D177: =B177/(24*I177) -> 0.1989899 | G177: =(F177-E177)*24*60 -> 0 | H177: =G177/60 -> 0 | I177: 4125 | K177: =I177*12 -> 49500 | L177: =J177*H177 -> 0 | M177: =(K177-L177)/K177 -> 1 | N177: =D177/M177 -> 0.1989899 | O177: =N177*I177*24 -> 19700 | P177: =O177-B177 -> 0
...

Sheet Sheet1

Sheet Sheet2

Sheet Sheet3

Sheet Sheet4

Sheet Sheet5
