Workbook

Sheet Budgeted_Data
A1: Plant Name | B1: Date | C1: Month | D1: Month | E1: Daily_Gen | F1: Daily_GTI | G1: Daily_GHI | H1: Ambt_Temp | I1: PR_% | J1: CUF_% | K1: TArray | L1: TArrWtd | M1: Connected_DC
A2: Devki_Galol | B2: 45747 | M2: 2411
A3: Devki_Galol | B3: 45748 | E3: 14287.348 | F3: 6.91332 | G3: 6.707771 | H3: 27.415 | I3: 0.85717156 | J3: 0.24691255 | K3: 0 | L3: 21.811708 | M3: 2411
A4: Devki_Galol | B4: 45749 | E4: 14905.571 | F4: 7.241431 | G4: 7.025458 | H4: 26.8775 | I4: 0.85374271 | J4: 0.25759662 | K4: 0 | L4: 22.152667 | M4: 2411
A5: Devki_Galol | B5: 45750 | E5: 15554.62 | F5: 7.635258 | G5: 7.411582 | H5: 28.30125 | I5: 0.84496453 | J5: 0.26881342 | K5: 0 | L5: 23.39775 | M5: 2411
A6: Devki_Galol | B6: 45751 | E6: 15886.128 | F6: 7.804122 | G6: 7.578766 | H6: 28.33 | I6: 0.84430002 | J6: 0.27454251 | K6: 0 | L6: 23.414625 | M6: 2411
A7: Devki_Galol | B7: 45752 | E7: 11752.222 | F7: 5.715388 | G7: 5.503698 | H7: 31.082917 | I7: 0.85285865 | J7: 0.20310075 | K7: 0 | L7: 22.630708 | M7: 2411
A8: Devki_Galol | B8: 45753 | E8: 7771.589 | F8: 3.734185 | G8: 3.586375 | H8: 30.53375 | I8: 0.86321064 | J8: 0.13430784 | K8: 0 | L8: 18.429417 | M8: 2411
A9: Devki_Galol | B9: 45754 | E9: 12872.497 | F9: 6.305604 | G9: 6.099538 | H9: 31.335 | I9: 0.8467182 | J9: 0.22246124 | K9: 0 | L9: 23.464917 | M9: 2411
A10: Devki_Galol | B10: 45755 | E10: 14069.94 | F10: 6.904297 | G10: 6.687158 | H10: 30.85375 | I10: 0.8452313 | J10: 0.24315533 | K10: 0 | L10: 23.794875 | M10: 2411
A11: Devki_Galol | B11: 45756 | E11: 15120.66 | F11: 7.448638 | G11: 7.215121 | H11: 30.165833 | I11: 0.8419701 | J11: 0.26131377 | K11: 0 | L11: 24.040958 | M11: 2411
A12: Devki_Galol | B12: 45757 | E12: 14350.56 | F12: 7.092072 | G12: 6.870152 | H12: 31.859167 | I12: 0.83926382 | J12: 0.24800498 | K12: 0 | L12: 24.6445 | M12: 2411
A13: Devki_Galol | B13: 45758 | E13: 15262.67 | F13: 7.611885 | G13: 7.375544 | H13: 32.392917 | I13: 0.83165095 | J13: 0.26376797 | K13: 0 | L13: 25.622375 | M13: 2411
A14: Devki_Galol | B14: 45759 | E14: 15211.54 | F14: 7.477686 | G14: 7.245707 | H14: 29.71 | I14: 0.84374021 | J14: 0.26288435 | K14: 0 | L14: 23.86675 | M14: 2411
... A366: Devki_Galol | B366: 46111 | E366: 14156.897 | F366: 6.93562 | G366: 6.725163 | H366: 29.551667 | I366: 0.84661425 | J366: 0.24465811 | K366: 0 | L366: 23.354625 | M366: 2411
A367: Devki_Galol | B367: 46112 | E367: 14820.857 | F367: 7.348117 | G367: 7.130108 | H367: 30.895833 | I367: 0.83656568 | J367: 0.2561326 | K367: 0 | L367: 24.667625

Sheet Data_Entry
B1: Month | C1: Date | D1: Plant_Up_Time | E1: Plant_Down_Time | F1: Inv_1 | G1: Inv_2 | H1: Inv_3 | I1: Inv_4 | J1: Inv_5 | K1: Inv_6 | L1: Inv_7 | M1: Total Inv Gen kWh | N1: ABT_Initial_Export | O1: ABT_Final_Export | P1: Total_Export | Q1: ABT_Initial_Import | R1: ABT_Final_Import | S1: Total_Import | T1: Net_Gen_kWh | U1: GHI (kwh/m2) | V1: GTI (kwh/m2) | W1: Ambt_Temp_Avg | X1: Module_Temp_Avg | Y1: Wtd_Module_Temp | Z1: Wind Speed | AA1: Rain_Gaug_MM | AB1: Weather_Condition
A2: 4 | B2: 45747 | C2: 45747 | M2: =SUM(F2:L2) -> 0 | P2: =MAX((O2-N2)*3000,0) -> 0 | S2: =MAX((R2-Q2)*3000,0) -> 0 | T2: =P2-S2 -> 0
A3: =A2+1 -> 5 | B3: 45748 | C3: 45748 | F3: 1907.18 | G3: 1939.32 | H3: 1904.51 | I3: 2007.77 | J3: 2023.7 | K3: 2022.23 | L3: 2004.7 | M3: =SUM(F3:L3) -> 13809.41 | N3: 106.77 | O3: 111.31 | P3: =MAX((O3-N3)*3000,0) -> 13620 | Q3: 2.2 | R3: 2.21 | S3: =MAX((R3-Q3)*3000,0) -> 30 | T3: =P3-S3 -> 13590 | V3: 5.54
A4: =A3+1 -> 6 | B4: 45749 | C4: 45749 | F4: 1957.32 | G4: 1993 | H4: 1956.83 | I4: 2061.56 | J4: 2070.05 | K4: 2066.26 | L4: 2061.12 | M4: =SUM(F4:L4) -> 14166.14 | N4: 111.31 | O4: 115.99 | P4: =MAX((O4-N4)*3000,0) -> 14040 | Q4: 2.21 | R4: 2.23 | S4: =MAX((R4-Q4)*3000,0) -> 60 | T4: =P4-S4 -> 13980 | V4: 5.58
A5: =A4+1 -> 7 | B5: 45750 | C5: 45750 | F5: 1875.34 | G5: 1915.98 | H5: 1879.63 | I5: 1980.41 | J5: 1990.28 | K5: 1989.18 | L5: 1992.85 | M5: =SUM(F5:L5) -> 13623.67 | N5: 115.99 | O5: 120.46 | P5: =MAX((O5-N5)*3000,0) -> 13410 | Q5: 2.23 | R5: 2.24 | S5: =MAX((R5-Q5)*3000,0) -> 30 | T5: =P5-S5 -> 13380 | V5: 5.37
A6: =A5+1 -> 8 | B6: 45751 | C6: 45751 | F6: 1902.7 | G6: 1935.04 | H6: 1901.8 | I6: 2009.4 | J6: 2021.08 | K6: 2009.01 | L6: 2014.18 | M6: =SUM(F6:L6) -> 13793.21 | N6: 120.46 | O6: 125.04 | P6: =MAX((O6-N6)*3000,0) -> 13740 | Q6: 2.24 | R6: 2.25 | S6: =MAX((R6-Q6)*3000,0) -> 30 | T6: =P6-S6 -> 13710 | V6: 5.41
A7: =A6+1 -> 9 | B7: 45752 | C7: 45752 | F7: 1948.19 | G7: 1975.14 | H7: 1946 | I7: 2050.1 | J7: 2061.63 | K7: 2056.9 | L7: 2058.73 | M7: =SUM(F7:L7) -> 14096.69 | N7: 125.04 | O7: 129.79 | P7: =MAX((O7-N7)*3000,0) -> 14250 | Q7: 2.25 | R7: 2.26 | S7: =MAX((R7-Q7)*3000,0) -> 30 | T7: =P7-S7 -> 14220 | V7: 5.52
A8: =A7+1 -> 10 | B8: 45753 | C8: 45753 | F8: 1971.04 | G8: 1999.88 | H8: 1970.16 | I8: 2074.85 | J8: 2085.24 | K8: 2070.8 | L8: 2082.29 | M8: =SUM(F8:L8) -> 14254.26 | N8: 129.79 | O8: 134.39 | P8: =MAX((O8-N8)*3000,0) -> 13800 | Q8: 2.26 | R8: 2.27 | S8: =MAX((R8-Q8)*3000,0) -> 30 | T8: =P8-S8 -> 13770 | V8: 5.56
A9: =A8+1 -> 11 | B9: 45754 | C9: 45754 | F9: 1920.52 | G9: 1964.16 | H9: 1923.6 | I9: 2036.21 | J9: 2074.93 | K9: 2027.7 | L9: 2047.38 | M9: =SUM(F9:L9) -> 13994.5 | N9: 134.39 | O9: 139 | P9: =MAX((O9-N9)*3000,0) -> 13830 | Q9: 2.27 | R9: 2.28 | S9: =MAX((R9-Q9)*3000,0) -> 30 | T9: =P9-S9 -> 13800 | V9: 5.45
A10: =A9+1 -> 12 | B10: 45755 | C10: 45755 | F10: 1903.77 | G10: 1964.92 | H10: 1901.96 | I10: 2034.49 | J10: 2053.74 | K10: 2009.58 | L10: 2054.45 | M10: =SUM(F10:L10) -> 13922.91 | N10: 139 | O10: 143.61 | P10: =MAX((O10-N10)*3000,0) -> 13830 | Q10: 2.28 | R10: 2.29 | S10: =MAX((R10-Q10)*3000,0) -> 30 | T10: =P10-S10 -> 13800 | V10: 5.49
A11: =A10+1 -> 13 | B11: 45756 | C11: 45756 | F11: 1897.6 | G11: 1946.4 | H11: 1892.3 | I11: 2009.2 | J11: 2028.25 | K11: 2003.95 | L11: 2029.3 | M11: =SUM(F11:L11) -> 13807 | N11: 143.61 | O11: 148.16 | P11: =MAX((O11-N11)*3000,0) -> 13650 | Q11: 2.29 | R11: 2.3 | S11: =MAX((R11-Q11)*3000,0) -> 30 | T11: =P11-S11 -> 13620 | V11: 5.44
A12: =A11+1 -> 14 | B12: 45757 | C12: 45757 | F12: 1921.95 | G12: 1971.76 | H12: 1911.8 | I12: 2037.4 | J12: 2057.6 | K12: 2024.87 | L12: 2057.3 | M12: =SUM(F12:L12) -> 13982.68 | N12: =O11 -> 148.16 | O12: 152.8 | P12: =MAX((O12-N12)*3000,0) -> 13920 | Q12: =R11 -> 2.3 | R12: 2.32 | S12: =MAX((R12-Q12)*3000,0) -> 60 | T12: =P12-S12 -> 13860 | V12: 5.55
A13: =A12+1 -> 15 | B13: 45758 | C13: 45758 | F13: 1930.15 | G13: 1976.35 | H13: 1920.76 | I13: 2047.35 | J13: 2065.2 | K13: 2025.05 | L13: 2060.1 | M13: =SUM(F13:L13) -> 14024.96 | N13: =O12 -> 152.8 | O13: 157.43 | P13: =MAX((O13-N13)*3000,0) -> 13890 | Q13: =R12 -> 2.32 | R13: 2.33 | S13: =MAX((R13-Q13)*3000,0) -> 30 | T13: =P13-S13 -> 13860 | V13: 5.45
A14: =A13+1 -> 16 | B14: 45759 | C14: 45759 | F14: 1932.2 | G14: 1981.9 | H14: 1917.1 | I14: 2046.3 | J14: 2061.39 | K14: 2027.4 | L14: 2065.25 | M14: =SUM(F14:L14) -> 14031.54 | N14: =O13 -> 157.43 | O14: 162.07 | P14: =MAX((O14-N14)*3000,0) -> 13920 | Q14: =R13 -> 2.33 | R14: 2.34 | S14: =MAX((R14-Q14)*3000,0) -> 30 | T14: =P14-S14 -> 13890 | V14: 2.05
A15: =A14+1 -> 17 | B15: 45760 | C15: 45760 | F15: 2030.2 | G15: 2077.84 | H15: 2018.4 | I15: 2147.62 | J15: 2166.85 | K15: 2120.31 | L15: 2161.95 | M15: =SUM(F15:L15) -> 14723.17 | N15: =O14 -> 162.07 | O15: 166.91 | P15: =MAX((O15-N15)*3000,0) -> 14520 | Q15: =R14 -> 2.34 | R15: 2.35 | S15: =MAX((R15-Q15)*3000,0) -> 30 | T15: =P15-S15 -> 14490 | V15: 5.82 | AB15: sunny
A16: =A15+1 -> 18 | B16: 45761 | C16: 45761 | F16: 2109.55 | G16: 2135.49 | H16: 2000.86 | I16: 2245.16 | J16: 2289.4 | K16: 2235.85 | L16: 2329.39 | M16: =SUM(F16:L16) -> 15345.7 | N16: =O15 -> 166.91 | O16: 171.77 | P16: =MAX((O16-N16)*3000,0) -> 14580 | Q16: =R15 -> 2.35 | R16: 2.36 | S16: =MAX((R16-Q16)*3000,0) -> 30 | T16: =P16-S16 -> 14550 | V16: 5.75 | AB16: sunny
A17: =A16+1 -> 19 | B17: 45762 | C17: 45762 | F17: 1991.64 | G17: 2031.13 | H17: 1980.62 | I17: 2104.3 | J17: 2120.45 | K17: 2100.17 | L17: 2120.05 | M17: =SUM(F17:L17) -> 14448.36 | N17: =O16 -> 171.77 | O17: 176.53 | P17: =MAX((O17-N17)*3000,0) -> 14280 | Q17: =R16 -> 2.36 | R17: 2.37 | S17: =MAX((R17-Q17)*3000,0) -> 30 | T17: =P17-S17 -> 14250 | V17: 5.78 | AB17: sunny
A18: =A17+1 -> 20 | B18: 45763 | C18: 45763 | F18: 1978.28 | G18: 2020.18 | H18: 1968.1 | I18: 2089.42 | J18: 2102.49 | K18: 2078.15 | L18: 2097.84 | M18: =SUM(F18:L18) -> 14334.46 | N18: =O17 -> 176.53 | O18: 181.27 | P18: =MAX((O18-N18)*3000,0) -> 14220 | Q18: =R17 -> 2.37 | R18: 2.38 | S18: =MAX((R18-Q18)*3000,0) -> 30 | T18: =P18-S18 -> 14190 | V18: 5.39 | W18: 32.04 | AB18: sunny
A19: =A18+1 -> 21 | B19: 45764 | C19: 45764 | F19: 2055.86 | G19: 2095.44 | H19: 2047.4 | I19: 2161.11 | J19: 2175.87 | K19: 2149.63 | L19: 2165.43 | M19: =SUM(F19:L19) -> 14850.74 | N19: =O18 -> 181.27 | O19: 186.17 | P19: =MAX((O19-N19)*3000,0) -> 14700 | Q19: =R18 -> 2.38 | R19: 2.39 | S19: =MAX((R19-Q19)*3000,0) -> 30 | T19: =P19-S19 -> 14670 | AB19: sunny
A20: =A19+1 -> 22 | B20: 45765 | C20: 45765 | F20: 2020.17 | G20: 2064.25 | H20: 2010.12 | I20: 2130.49 | J20: 2147.19 | K20: 2112.04 | L20: 2137.09 | M20: =SUM(F20:L20) -> 14621.35 | N20: =O19 -> 186.17 | O20: 191.01 | P20: =MAX((O20-N20)*3000,0) -> 14520 | Q20: =R19 -> 2.39 | R20: 2.4 | S20: =MAX((R20-Q20)*3000,0) -> 30 | T20: =P20-S20 -> 14490 | V20: 5.74 | W20: 32.57 | AB20: sunny
A21: =A20+1 -> 23 | B21: 45766 | C21: 45766 | F21: 2022.37 | G21: 2062.45 | H21: 2011.8 | I21: 2137.56 | J21: 2150.1 | K21: 2122.31 | L21: 2146.2 | M21: =SUM(F21:L21) -> 14652.79 | N21: =O20 -> 191.01 | O21: 195.84 | P21: =MAX((O21-N21)*3000,0) -> 14490 | Q21: =R20 -> 2.4 | R21: 2.41 | S21: =MAX((R21-Q21)*3000,0) -> 30 | T21: =P21-S21 -> 14460 | V21: 5.79 | W21: 32.54 | AB21: sunny
A22: =A21+1 -> 24 | B22: 45767 | C22: 45767 | F22: 2028.35 | G22: 2071.3 | H22: 2019.75 | I22: 2145.57 | J22: 2157.59 | K22: 2129.99 | L22: 2151.68 | M22: =SUM(F22:L22) -> 14704.23 | N22: =O21 -> 195.84 | O22: 200.7 | P22: =MAX((O22-N22)*3000,0) -> 14580 | Q22: =R21 -> 2.41 | R22: 2.42 | S22: =MAX((R22-Q22)*3000,0) -> 30 | T22: =P22-S22 -> 14550 | V22: 5.79 | W22: 32.54 | AB22: sunny
A23: =A22+1 -> 25 | B23: 45768 | C23: 45768 | F23: 1952.39 | G23: 1992.37 | H23: 1946.21 | I23: 2065.1 | J23: 2075.12 | K23: 2048.19 | L23: 2072.52 | M23: =SUM(F23:L23) -> 14151.9 | N23: =O22 -> 200.7 | O23: 205.37 | P23: =MAX((O23-N23)*3000,0) -> 14010 | Q23: =R22 -> 2.42 | R23: 2.43 | S23: =MAX((R23-Q23)*3000,0) -> 30 | T23: =P23-S23 -> 13980 | V23: 5.62 | W23: 33.86 | AB23: sunny
A24: =A23+1 -> 26 | B24: 45769 | C24: 45769 | F24: 1980.8 | G24: 2032.01 | H24: 1973.63 | I24: 2123.46 | J24: 2127.85 | K24: 2070.41 | L24: 2156.24 | M24: =SUM(F24:L24) -> 14464.4 | N24: =O23 -> 205.37 | O24: 210.15 | P24: =MAX((O24-N24)*3000,0) -> 14340 | Q24: =R23 -> 2.43 | R24: 2.45 | S24: =MAX((R24-Q24)*3000,0) -> 60 | T24: =P24-S24 -> 14280 | V24: 5.69 | W24: 35.88 | AB24: sunny
A25: =A24+1 -> 27 | B25: 45770 | C25: 45770 | F25: 1705.1 | G25: 1771.69 | H25: 1680.18 | I25: 1835.74 | J25: 1846.94 | K25: 1791.65 | L25: 1853.57 | M25: =SUM(F25:L25) -> 12484.87 | N25: =O24 -> 210.15 | O25: 214.24 | P25: =MAX((O25-N25)*3000,0) -> 12270 | Q25: =R24 -> 2.45 | R25: 2.46 | S25: =MAX((R25-Q25)*3000,0) -> 30 | T25: =P25-S25 -> 12240 | V25: 5.01 | W25: 35.88 | AB25: sunny
A26: =A25+1 -> 28 | B26: 45771 | C26: 45771 | F26: 1798.55 | G26: 1819.95 | H26: 1766.97 | I26: 1885.19 | J26: 1897.64 | K26: 1899.92 | L26: 1902.58 | M26: =SUM(F26:L26) -> 12970.8 | N26: =O25 -> 214.24 | O26: 218.55 | P26: =MAX((O26-N26)*3000,0) -> 12930 | Q26: =R25 -> 2.46 | R26: 2.47 | S26: =MAX((R26-Q26)*3000,0) -> 30 | T26: =P26-S26 -> 12900 | V26: 5.26 | W26: 32.75 | AB26: sunny
A27: =A26+1 -> 29 | B27: 45772 | C27: 45772 | F27: 2070.27 | G27: 2088.85 | H27: 2062.27 | I27: 2160.95 | J27: 2173.7 | K27: 2168.64 | L27: 2170.25 | M27: =SUM(F27:L27) -> 14894.93 | N27: =O26 -> 218.55 | O27: 223.48 | P27: =MAX((O27-N27)*3000,0) -> 14790 | Q27: =R26 -> 2.47 | R27: 2.48 | S27: =MAX((R27-Q27)*3000,0) -> 30 | T27: =P27-S27 -> 14760 | V27: 5.61 | W27: 31.86 | AB27: sunny
A28: =A27+1 -> 30 | B28: 45773 | C28: 45773 | F28: 2100.76 | G28: 2109.04 | H28: 2086.42 | I28: 2160.95 | J28: 2194.72 | K28: 2202.69 | L28: 2195.02 | M28: =SUM(F28:L28) -> 15049.6 | N28: =O27 -> 223.48 | O28: 228.46 | P28: =MAX((O28-N28)*3000,0) -> 14940 | Q28: =R27 -> 2.48 | R28: 2.49 | S28: =MAX((R28-Q28)*3000,0) -> 30 | T28: =P28-S28 -> 14910 | V28: 5.68 | W28: 32.49 | AB28: sunny
A29: =A28+1 -> 31 | B29: 45774 | C29: 45774 | F29: 2078.31 | G29: 2080.32 | H29: 2074.81 | I29: 2163.68 | J29: 2189.77 | K29: 2198.39 | L29: 2212.3 | M29: =SUM(F29:L29) -> 14997.58 | N29: =O28 -> 228.46 | O29: 233.33 | P29: =MAX((O29-N29)*3000,0) -> 14610 | Q29: =R28 -> 2.49 | R29: 2.5 | S29: =MAX((R29-Q29)*3000,0) -> 30 | T29: =P29-S29 -> 14580 | V29: 5.77 | W29: 33.49 | AB29: sunny
A30: =A29+1 -> 32 | B30: 45775 | C30: 45775 | D30: 0.29166667 | E30: 0.78125 | F30: 2044.8 | G30: 2058.59 | H30: 2034.1 | I30: 2130.79 | J30: 2144.31 | K30: 2141.63 | L30: 2139.16 | M30: =SUM(F30:L30) -> 14693.38 | N30: =O29 -> 233.33 | O30: 238.21 | P30: =MAX((O30-N30)*3000,0) -> 14640 | Q30: =R29 -> 2.5 | R30: 2.51 | S30: =MAX((R30-Q30)*3000,0) -> 30 | T30: =P30-S30 -> 14610 | V30: 5.74 | W30: 34.14 | AB30: sunny
A31: =A30+1 -> 33 | B31: 45776 | C31: 45776 | D31: 0.28125 | E31: 0.78125 | F31: 2079.11 | G31: 2082.8 | H31: 2064.31 | I31: 2148.1 | J31: 2166.33 | K31: 2152.19 | L31: 2154.55 | M31: =SUM(F31:L31) -> 14847.39 | N31: =O30 -> 238.21 | O31: 243.13 | P31: =MAX((O31-N31)*3000,0) -> 14760 | Q31: =R30 -> 2.51 | R31: 2.52 | S31: =MAX((R31-Q31)*3000,0) -> 30 | T31: =P31-S31 -> 14730 | V31: 5.55 | W31: 37.01 | AB31: sunny
A32: =A31+1 -> 34 | B32: 45777 | C32: 45777 | D32: 0.28125 | E32: 0.78125 | F32: 2053.26 | G32: 2060.77 | H32: 2035.98 | I32: 2138.23 | J32: 2150.81 | K32: 2141.18 | L32: 2140.5 | M32: =SUM(F32:L32) -> 14720.73 | N32: =O31 -> 243.13 | O32: 248.02 | P32: =MAX((O32-N32)*3000,0) -> 14670 | Q32: =R31 -> 2.52 | R32: 2.53 | S32: =MAX((R32-Q32)*3000,0) -> 30 | T32: =P32-S32 -> 14640 | V32: 5.7 | W32: 33.92 | AB32: sunny
A33: =A32+1 -> 35 | B33: 45778 | C33: 45778 | D33: 0.28125 | E33: 0.78125 | F33: 2084.71 | G33: 2095.72 | H33: 2067.82 | I33: 2170.77 | J33: 2184.2 | K33: 2165.94 | L33: 2173.35 | M33: =SUM(F33:L33) -> 14942.51 | N33: =O32 -> 248.02 | O33: 252.96 | P33: =MAX((O33-N33)*3000,0) -> 14820 | Q33: =R32 -> 2.53 | R33: 2.54 | S33: =MAX((R33-Q33)*3000,0) -> 30 | T33: =P33-S33 -> 14790 | V33: 5.76 | W33: 34.66 | AB33: sunny
A34: =A33+1 -> 36 | B34: 45779 | C34: 45779 | D34: 0.28125 | E34: 0.78194444 | F34: 2155.08 | G34: 2159.61 | H34: 2035.18 | I34: 2224.39 | J34: 2232.17 | K34: 2208.1 | L34: 2210.45 | M34: =SUM(F34:L34) -> 15224.98 | N34: =O33 -> 252.96 | O34: 257.98 | P34: =MAX((O34-N34)*3000,0) -> 15060 | Q34: =R33 -> 2.54 | R34: 2.55 | S34: =MAX((R34-Q34)*3000,0) -> 30 | T34: =P34-S34 -> 15030 | V34: 5.91 | W34: 34.33 | AB34: sunny
A35: =A34+1 -> 37 | B35: 45780 | C35: 45780 | D35: 0.28125 | E35: 0.78194444 | F35: 1995.5 | G35: 2000.39 | H35: 1980.27 | I35: 2069.52 | J35: 2073.16 | K35: 2066.69 | L35: 2063.53 | M35: =SUM(F35:L35) -> 14249.06 | N35: =O34 -> 257.98 | O35: 262.68 | P35: =MAX((O35-N35)*3000,0) -> 14100 | Q35: =R34 -> 2.55 | R35: 2.56 | S35: =MAX((R35-Q35)*3000,0) -> 30 | T35: =P35-S35 -> 14070 | V35: 5.5 | W35: 31.78 | AB35: sunny
A36: =A35+1 -> 38 | B36: 45781 | C36: 45781 | D36: 0.28125 | E36: 0.78125 | F36: 1750.09 | G36: 1750.71 | H36: 1733.4 | I36: 1816.52 | J36: 1821.93 | K36: 1816.66 | L36: 1821.7 | M36: =SUM(F36:L36) -> 12511.01 | N36: =O35 -> 262.68 | O36: 266.83 | P36: =MAX((O36-N36)*3000,0) -> 12450 | Q36: =R35 -> 2.56 | R36: 2.57 | S36: =MAX((R36-Q36)*3000,0) -> 30 | T36: =P36-S36 -> 12420 | V36: 5.16 | W36: 32.01 | AB36: sunny
A37: =A36+1 -> 39 | B37: 45782 | C37: 45782 | D37: 0.28125 | E37: 0.78125 | F37: 1633.36 | G37: 1643.32 | H37: 1615.21 | I37: 1701.11 | J37: 1700.02 | K37: 1682.68 | L37: 1695.72 | M37: =SUM(F37:L37) -> 11671.42 | N37: =O36 -> 266.83 | O37: 270.69 | P37: =MAX((O37-N37)*3000,0) -> 11580 | Q37: =R36 -> 2.57 | R37: 2.58 | S37: =MAX((R37-Q37)*3000,0) -> 30 | T37: =P37-S37 -> 11550 | V37: 4.23 | W37: 31.68 | AB37: mostly cloudy
A38: =A37+1 -> 40 | B38: 45783 | C38: 45783 | D38: 0.58333333 | E38: 0.79166667 | F38: 386.75 | G38: 389.76 | H38: 383.31 | I38: 404.43 | J38: 403.57 | K38: 399.1 | L38: 402.66 | M38: =SUM(F38:L38) -> 2769.58 | N38: =O37 -> 270.69 | O38: 271.63 | P38: =MAX((O38-N38)*3000,0) -> 2820 | Q38: =R37 -> 2.58 | R38: 2.59 | S38: =MAX((R38-Q38)*3000,0) -> 30 | T38: =P38-S38 -> 2790 | V38: 1.44 | W38: 30.36 | AB38: cloudy
A39: =A38+1 -> 41 | B39: 45784 | C39: 45784 | D39: 0.28125 | E39: 0.78125 | F39: 956.61 | G39: 988.23 | H39: 978.43 | I39: 1053.59 | J39: 1041.57 | K39: 1066.45 | L39: 1069.71 | M39: =SUM(F39:L39) -> 7154.59 | N39: =O38 -> 271.63 | O39: 273.99 | P39: =MAX((O39-N39)*3000,0) -> 7080 | Q39: =R38 -> 2.59 | R39: 2.6 | S39: =MAX((R39-Q39)*3000,0) -> 30 | T39: =P39-S39 -> 7050 | V39: 3.33 | W39: 28.95 | AB39: rainy
A40: =A39+1 -> 42 | B40: 45785 | C40: 45785 | D40: 0.28125 | E40: 0.79166667 | F40: 1410.35 | G40: 1419.42 | H40: 1398.2 | I40: 1474.59 | J40: 1475.25 | K40: 1473.4 | L40: 1479.5 | M40: =SUM(F40:L40) -> 10130.71 | N40: =O39 -> 273.99 | O40: 277.97 | P40: =MAX((O40-N40)*3000,0) -> 11940 | Q40: =R39 -> 2.6 | R40: 2.62 | S40: =MAX((R40-Q40)*3000,0) -> 60 | T40: =P40-S40 -> 11880 | V40: 4.03 | W40: 30.19 | AB40: rainy
A41: =A40+1 -> 43 | B41: 45786 | C41: 45786 | D41: 0.28125 | E41: 0.76041667 | F41: 1255.1 | G41: 1260.55 | H41: 1245.4 | I41: 1307.29 | J41: 1309.1 | K41: 1314.07 | L41: 1311.66 | M41: =SUM(F41:L41) -> 9003.17 | N41: =O40 -> 277.97 | O41: 280.9 | P41: =MAX((O41-N41)*3000,0) -> 8790 | Q41: =R40 -> 2.62 | R41: 2.63 | S41: =MAX((R41-Q41)*3000,0) -> 30 | T41: =P41-S41 -> 8760 | V41: 3.41 | W41: 29.47 | AB41: cloudy
... A44: =A43+1 -> 46 | B44: 45789 | C44: 45789 | D44: 0.28125 | E44: 0.78125 | F44: 1783.51 | G44: 1791.6 | H44: 1775.5 | I44: 1863.78 | J44: 1874.11 | K44: 1870.37 | L44: 1843.6 | M44: =SUM(F44:L44) -> 12802.47 | N44: =O43 -> 288.05 | O44: 292.29 | P44: =MAX((O44-N44)*3000,0) -> 12720 | Q44: =R43 -> 2.65 | R44: 2.66 | S44: =MAX((R44-Q44)*3000,0) -> 30 | T44: =P44-S44 -> 12690 | V44: 5.08 | W44: 31.8 | AB44: cloudy
A45: =A44+1 -> 47 | B45: 45790 | C45: 45790 | D45: 0.28125 | E45: 0.78125 | F45: 1927.39 | G45: 1930.35 | H45: 1922.86 | I45: 2005.43 | J45: 2020.04 | K45: 2032.81 | L45: 2028.81 | M45: =SUM(F45:L45) -> 13867.69 | N45: =O44 -> 292.29 | O45: 296.86 | P45: =MAX((O45-N45)*3000,0) -> 13710 | Q45: =R44 -> 2.66 | R45: 2.67 | S45: =MAX((R45-Q45)*3000,0) -> 30 | T45: =P45-S45 -> 13680 | AB45: cloudy
A46: =A45+1 -> 48 | B46: 45791 | C46: 45791 | F46: 2007.85 | G46: 2004.35 | H46: 2002.96 | I46: 2081.76 | J46: 2098.12 | K46: 2113.2 | L46: 2103.55 | M46: =SUM(F46:L46) -> 14411.79 | N46: =O45 -> 296.86 | O46: 301.62 | P46: =MAX((O46-N46)*3000,0) -> 14280 | Q46: =R45 -> 2.67 | R46: 2.68 | S46: =MAX((R46-Q46)*3000,0) -> 30 | T46: =P46-S46 -> 14250 | AB46: sunny
A47: =A46+1 -> 49 | B47: 45792 | C47: 45792 | F47: 1996.64 | G47: 2001.36 | H47: 1988.12 | I47: 2074.3 | J47: 2086.14 | K47: 2100.43 | L47: 2093.63 | M47: =SUM(F47:L47) -> 14340.62 | N47: =O46 -> 301.62 | O47: 306.37 | P47: =MAX((O47-N47)*3000,0) -> 14250 | Q47: =R46 -> 2.68 | R47: 2.69 | S47: =MAX((R47-Q47)*3000,0) -> 30 | T47: =P47-S47 -> 14220 | AB47: sunny
A48: =A47+1 -> 50 | B48: 45793 | C48: 45793 | D48: 0.27083333 | E48: 0.79166667 | F48: 2007.79 | G48: 2009.75 | H48: 1993.29 | I48: 2085.74 | J48: 2091.3 | K48: 2102.54 | L48: 2095.38 | M48: =SUM(F48:L48) -> 14385.79 | N48: =O47 -> 306.37 | O48: 311.13 | P48: =MAX((O48-N48)*3000,0) -> 14280 | Q48: =R47 -> 2.69 | R48: 2.7 | S48: =MAX((R48-Q48)*3000,0) -> 30 | T48: =P48-S48 -> 14250 | V48: 5.35 | W48: 32.48 | AB48: cloudy
A49: =A48+1 -> 51 | B49: 45794 | C49: 45794 | D49: 0.27083333 | E49: 0.79166667 | F49: 1917.51 | G49: 1920.53 | H49: 1919.45 | I49: 1997.27 | J49: 2006.11 | K49: 2019.89 | L49: 2012.33 | M49: =SUM(F49:L49) -> 13793.09 | N49: =O48 -> 311.13 | O49: 315.66 | P49: =MAX((O49-N49)*3000,0) -> 13590 | Q49: =R48 -> 2.7 | R49: 2.71 | S49: =MAX((R49-Q49)*3000,0) -> 30 | T49: =P49-S49 -> 13560 | V49: 5.2 | W49: 32.71 | AB49: sunny
A50: =A49+1 -> 52 | B50: 45795 | C50: 45795 | D50: 0.28125 | E50: 0.78125 | F50: 1865.09 | G50: 1822.8 | H50: 1799.89 | I50: 1890.87 | J50: 1894.11 | K50: 1864.91 | L50: 1853.28 | M50: =SUM(F50:L50) -> 12990.95 | N50: =O49 -> 315.66 | O50: 319.96 | P50: =MAX((O50-N50)*3000,0) -> 12900 | Q50: =R49 -> 2.71 | R50: 2.72 | S50: =MAX((R50-Q50)*3000,0) -> 30 | T50: =P50-S50 -> 12870 | V50: 5.65 | W50: 33.94 | AB50: sunny
A51: =A50+1 -> 53 | B51: 45796 | C51: 45796 | D51: 0.28125 | E51: 0.78125 | F51: 1906.48 | G51: 1914.89 | H51: 1891.43 | I51: 1987.36 | J51: 1995.43 | K51: 2000.83 | L51: 1997.49 | M51: =SUM(F51:L51) -> 13693.91 | N51: =O50 -> 319.96 | O51: 324.49 | P51: =MAX((O51-N51)*3000,0) -> 13590 | Q51: =R50 -> 2.72 | R51: 2.73 | S51: =MAX((R51-Q51)*3000,0) -> 30 | T51: =P51-S51 -> 13560 | V51: 5.43 | W51: 36 | AB51: sunny
A52: =A51+1 -> 54 | B52: 45797 | C52: 45797 | D52: 0.28125 | E52: 0.80208333 | F52: 1870.65 | G52: 1872.55 | H52: 1860.19 | I52: 1946.45 | J52: 1957.39 | K52: 1969.36 | L52: 1970.14 | M52: =SUM(F52:L52) -> 13446.73 | N52: =O51 -> 324.49 | O52: 328.92 | P52: =MAX((O52-N52)*3000,0) -> 13290 | Q52: =R51 -> 2.73 | R52: 2.74 | S52: =MAX((R52-Q52)*3000,0) -> 30 | T52: =P52-S52 -> 13260 | V52: 5.61 | W52: 36 | AB52: sunny
A53: =A52+1 -> 55 | B53: 45798 | C53: 45798 | D53: 0.28125 | E53: 0.79166667 | F53: 1014.89 | G53: 1017.18 | H53: 1005.76 | I53: 1056.3 | J53: 1061.22 | K53: 1062.48 | L53: 1063.54 | M53: =SUM(F53:L53) -> 7281.37 | N53: =O52 -> 328.92 | O53: 331.38 | P53: =MAX((O53-N53)*3000,0) -> 7380 | Q53: =R52 -> 2.74 | R53: 2.75 | S53: =MAX((R53-Q53)*3000,0) -> 30 | T53: =P53-S53 -> 7350 | V53: 3.17 | W53: 36 | AB53: cloudy
A54: =A53+1 -> 56 | B54: 45799 | C54: 45799 | D54: 0.27083333 | E54: 0.78125 | F54: 1699.08 | G54: 1707.43 | H54: 1699.46 | I54: 1782.23 | J54: 1790.25 | K54: 1801.13 | L54: 1795.83 | M54: =SUM(F54:L54) -> 12275.41 | N54: =O53 -> 331.38 | O54: 335.43 | P54: =MAX((O54-N54)*3000,0) -> 12150 | Q54: =R53 -> 2.75 | R54: 2.77 | S54: =MAX((R54-Q54)*3000,0) -> 60 | T54: =P54-S54 -> 12090 | V54: 5.41 | W54: 36 | AB54: sunny
A55: =A54+1 -> 57 | B55: 45800 | C55: 45800 | D55: 0.28125 | E55: 0.80208333 | F55: 1728.4 | G55: 1728.82 | H55: 1725.55 | I55: 1800.81 | J55: 1815.78 | K55: 1831.9 | L55: 1826.82 | M55: =SUM(F55:L55) -> 12458.08 | N55: =O54 -> 335.43 | O55: 339.57 | P55: =MAX((O55-N55)*3000,0) -> 12420 | Q55: =R54 -> 2.77 | R55: 2.78 | S55: =MAX((R55-Q55)*3000,0) -> 30 | T55: =P55-S55 -> 12390 | V55: 5.33 | W55: 36 | AB55: cloudy
A56: =A55+1 -> 58 | B56: 45801 | C56: 45801 | D56: 0.28125 | E56: 0.79166667 | F56: 1860.99 | G56: 1864.32 | H56: 1568.85 | I56: 1937.79 | J56: 1952.61 | K56: 1958.35 | L56: 1962.88 | M56: =SUM(F56:L56) -> 13105.79 | N56: =O55 -> 339.57 | O56: 343.9 | P56: =MAX((O56-N56)*3000,0) -> 12990 | Q56: =R55 -> 2.78 | R56: 2.79 | S56: =MAX((R56-Q56)*3000,0) -> 30 | T56: =P56-S56 -> 12960 | V56: 5.64 | W56: 33.38 | AB56: sunny
A57: =A56+1 -> 59 | B57: 45802 | C57: 45802 | D57: 0.28125 | E57: 0.79166667 | F57: 1922.89 | G57: 1925.23 | H57: 1880.65 | I57: 1994.65 | J57: 2006.55 | K57: 2012.26 | L57: 2008.11 | M57: =SUM(F57:L57) -> 13750.34 | N57: =O56 -> 343.9 | O57: 348.46 | P57: =MAX((O57-N57)*3000,0) -> 13680 | Q57: =R56 -> 2.79 | R57: 2.8 | S57: =MAX((R57-Q57)*3000,0) -> 30 | T57: =P57-S57 -> 13650 | V57: 5.61 | W57: 33.64 | AB57: sunny
A58: =A57+1 -> 60 | B58: 45803 | C58: 45803 | D58: 0.29166667 | E58: 0.79166667 | F58: 1445.61 | G58: 1452.47 | H58: 1438.01 | I58: 1508.79 | J58: 1520.45 | K58: 1522.42 | L58: 1525.42 | M58: =SUM(F58:L58) -> 10413.17 | N58: =O57 -> 348.46 | O58: 351.92 | P58: =MAX((O58-N58)*3000,0) -> 10380 | Q58: =R57 -> 2.8 | R58: 2.81 | S58: =MAX((R58-Q58)*3000,0) -> 30 | T58: =P58-S58 -> 10350 | V58: 4.33 | W58: 30 | AB58: cloudy
A59: =A58+1 -> 61 | B59: 45804 | C59: 45804 | D59: 0.28125 | E59: 0.78125 | F59: 831.6 | G59: 835.7 | H59: 824.87 | I59: 870.83 | J59: 875.35 | K59: 878.11 | L59: 878.8 | M59: =SUM(F59:L59) -> 5995.26 | N59: =O58 -> 351.92 | O59: 353.9 | P59: =MAX((O59-N59)*3000,0) -> 5940 | Q59: =R58 -> 2.81 | R59: 2.82 | S59: =MAX((R59-Q59)*3000,0) -> 30 | T59: =P59-S59 -> 5910 | V59: 2.58 | W59: 30 | AB59: cloudy
... A142: =A141+1 -> 144 | B142: 45887 | C142: 45887 | D142: 0.32291667 | E142: 0.78125 | F142: 1200.63 | G142: 1183.85 | H142: 1178.29 | I142: 1228.15 | J142: 1231.08 | K142: 1216.64 | L142: 1231.63 | M142: =SUM(F142:L142) -> 8470.27 | N142: =O141 -> 575.55 | O142: 578.36 | P142: =MAX((O142-N142)*3000,0) -> 8430 | Q142: =R141 -> 3.73 | R142: 3.75 | S142: =MAX((R142-Q142)*3000,0) -> 60 | T142: =P142-S142 -> 8370 | V142: 4 | W142: 0 | AB142: rainy
A143: =A142+1 -> 145 | B143: 45888 | C143: 45888 | F143: 1090.87 | G143: 1085.42 | H143: 1077.38 | I143: 1127.23 | J143: 1130.52 | K143: 1132.6 | L143: 1142.3 | M143: =SUM(F143:L143) -> 7786.32 | N143: =O142 -> 578.36 | O143: 580.93 | P143: =MAX((O143-N143)*3000,0) -> 7710 | Q143: =R142 -> 3.75 | R143: 3.76 | S143: =MAX((R143-Q143)*3000,0) -> 30 | T143: =P143-S143 -> 7680
A144: =A143+1 -> 146 | B144: 45889 | C144: 45889 | F144: 171.37 | G144: 165.42 | H144: 176.65 | I144: 180.85 | J144: 182.66 | K144: 183.78 | L144: 181.44 | M144: =SUM(F144:L144) -> 1242.17 | N144: =O143 -> 580.93 | O144: 581.3 | P144: =MAX((O144-N144)*3000,0) -> 1110 | Q144: =R143 -> 3.76 | R144: 3.78 | S144: =MAX((R144-Q144)*3000,0) -> 60 | T144: =P144-S144 -> 1050
A145: =A144+1 -> 147 | B145: 45890 | C145: 45890 | F145: 1573.81 | G145: 1570.21 | H145: 1566.31 | I145: 1640.23 | J145: 1641.54 | K145: 1637.02 | L145: 1644.3 | M145: =SUM(F145:L145) -> 11273.42 | N145: =O144 -> 581.3 | O145: 584.99 | P145: =MAX((O145-N145)*3000,0) -> 11070 | Q145: =R144 -> 3.78 | R145: 3.79 | S145: =MAX((R145-Q145)*3000,0) -> 30 | T145: =P145-S145 -> 11040
A146: =A145+1 -> 148 | B146: 45891 | C146: 45891 | F146: 1427.67 | G146: 1421.06 | H146: 1418.98 | I146: 1476.15 | J146: 1484.82 | K146: 1489.61 | L146: 1493.6 | M146: =SUM(F146:L146) -> 10211.89 | N146: =O145 -> 584.99 | O146: 588.37 | P146: =MAX((O146-N146)*3000,0) -> 10140 | Q146: =R145 -> 3.79 | R146: 3.8 | S146: =MAX((R146-Q146)*3000,0) -> 30 | T146: =P146-S146 -> 10110
A147: =A146+1 -> 149 | B147: 45892 | C147: 45892 | F147: 922.22 | G147: 921.86 | H147: 915.12 | I147: 957.7 | J147: 963.8 | K147: 64.86 | L147: 969.4 | M147: =SUM(F147:L147) -> 5714.96 | N147: =O146 -> 588.37 | O147: 590.56 | P147: =MAX((O147-N147)*3000,0) -> 6570 | Q147: =R146 -> 3.8 | R147: 3.81 | S147: =MAX((R147-Q147)*3000,0) -> 30 | T147: =P147-S147 -> 6540
A148: =A147+1 -> 150 | B148: 45893 | C148: 45893 | F148: 442.37 | G148: 444.21 | H148: 438.82 | I148: 460.43 | J148: 462.84 | K148: 463.93 | L148: 464.47 | M148: =SUM(F148:L148) -> 3177.07 | N148: =O147 -> 590.56 | O148: 591.59 | P148: =MAX((O148-N148)*3000,0) -> 3090 | Q148: =R147 -> 3.81 | R148: 3.82 | S148: =MAX((R148-Q148)*3000,0) -> 30 | T148: =P148-S148 -> 3060
A149: =A148+1 -> 151 | B149: 45894 | C149: 45894 | F149: 1011.11 | G149: 1009.96 | H149: 1001.53 | I149: 1059.87 | J149: 1061.08 | K149: 1062.41 | L149: 1067.35 | M149: =SUM(F149:L149) -> 7273.31 | N149: =O148 -> 591.59 | O149: 593.99 | P149: =MAX((O149-N149)*3000,0) -> 7200 | Q149: =R148 -> 3.82 | R149: 3.83 | S149: =MAX((R149-Q149)*3000,0) -> 30 | T149: =P149-S149 -> 7170
A150: =A149+1 -> 152 | B150: 45895 | C150: 45895 | F150: 837.46 | G150: 835.3 | H150: 828.16 | I150: 865.45 | J150: 875.36 | K150: 835.3 | L150: 877.46 | M150: =SUM(F150:L150) -> 5954.49 | N150: =O149 -> 593.99 | O150: 595.98 | P150: =MAX((O150-N150)*3000,0) -> 5970 | Q150: =R149 -> 3.83 | R150: 3.85 | S150: =MAX((R150-Q150)*3000,0) -> 60 | T150: =P150-S150 -> 5910
A151: =A150+1 -> 153 | B151: 45896 | C151: 45896 | F151: 1210.16 | G151: 1211.3 | H151: 1197.3 | I151: 1255.03 | J151: 1270.02 | K151: 1272.31 | L151: 1274.78 | M151: =SUM(F151:L151) -> 8690.9 | N151: =O150 -> 595.98 | O151: 598.85 | P151: =MAX((O151-N151)*3000,0) -> 8610 | Q151: =R150 -> 3.85 | R151: 3.86 | S151: =MAX((R151-Q151)*3000,0) -> 30 | T151: =P151-S151 -> 8580
A152: =A151+1 -> 154 | B152: 45897 | C152: 45897 | F152: 1202.48 | G152: 1199.74 | H152: 1191.04 | I152: 1249.15 | J152: 1264.55 | K152: 1258.46 | L152: 1273.23 | M152: =SUM(F152:L152) -> 8638.65 | N152: =O151 -> 598.85 | O152: 601.71 | P152: =MAX((O152-N152)*3000,0) -> 8580 | Q152: =R151 -> 3.86 | R152: 3.87 | S152: =MAX((R152-Q152)*3000,0) -> 30 | T152: =P152-S152 -> 8550
A153: =A152+1 -> 155 | B153: 45898 | C153: 45898 | F153: 976 | G153: 976.06 | H153: 961.3 | I153: 1009.54 | J153: 1018.35 | K153: 1025.02 | L153: 1024.4 | M153: =SUM(F153:L153) -> 6990.67 | N153: =O152 -> 601.71 | O153: 604.02 | P153: =MAX((O153-N153)*3000,0) -> 6930 | Q153: =R152 -> 3.87 | R153: 3.89 | S153: =MAX((R153-Q153)*3000,0) -> 60 | T153: =P153-S153 -> 6870
A154: =A153+1 -> 156 | B154: 45899 | C154: 45899 | F154: 1000.41 | G154: 1000.89 | H154: 991.85 | I154: 1046.39 | J154: 1047.52 | K154: 1048.13 | L154: 1045.28 | M154: =SUM(F154:L154) -> 7180.47 | N154: =O153 -> 604.02 | O154: 606.39 | P154: =MAX((O154-N154)*3000,0) -> 7110 | Q154: =R153 -> 3.89 | R154: 3.9 | S154: =MAX((R154-Q154)*3000,0) -> 30 | T154: =P154-S154 -> 7080
... A156: =A155+1 -> 158 | B156: 45901 | C156: 45901 | F156: 838.18 | G156: 837.18 | H156: 829.01 | I156: 867.26 | J156: 877.38 | K156: 880.51 | L156: 880.84 | M156: =SUM(F156:L156) -> 6010.36 | N156: =O155 -> 609.16 | O156: 611.19 | P156: =MAX((O156-N156)*3000,0) -> 6090 | Q156: =R155 -> 3.91 | R156: 3.92 | S156: =MAX((R156-Q156)*3000,0) -> 30 | T156: =P156-S156 -> 6060
A157: =A156+1 -> 159 | B157: 45902 | C157: 45902 | F157: 1372.37 | G157: 1357.89 | H157: 1362.1 | I157: 1407.4 | J157: 1425..63 | K157: 1435.63 | L157: 1429.63 | M157: =SUM(F157:L157) -> 8365.02 | N157: =O156 -> 611.19 | O157: 614.38 | P157: =MAX((O157-N157)*3000,0) -> 9570 | Q157: =R156 -> 3.92 | R157: 3.93 | S157: =MAX((R157-Q157)*3000,0) -> 30 | T157: =P157-S157 -> 9540
A158: =A157+1 -> 160 | B158: 45903 | C158: 45903 | F158: 1498.19 | G158: 1491.35 | H158: 1483.3 | I158: 1543.29 | J158: 1556.2 | K158: 1559.05 | L158: 1561.51 | M158: =SUM(F158:L158) -> 10692.89 | N158: =O157 -> 614.38 | O158: 617.9 | P158: =MAX((O158-N158)*3000,0) -> 10560 | Q158: =R157 -> 3.93 | R158: 3.94 | S158: =MAX((R158-Q158)*3000,0) -> 30 | T158: =P158-S158 -> 10530
A159: =A158+1 -> 161 | B159: 45904 | C159: 45904 | F159: 1054.99 | G159: 1059.37 | H159: 1043.09 | I159: 1088.89 | J159: 1103.52 | K159: 1110.58 | L159: 1111.111 | M159: =SUM(F159:L159) -> 7571.551 | N159: =O158 -> 617.9 | O159: 620.41 | P159: =MAX((O159-N159)*3000,0) -> 7530 | Q159: =R158 -> 3.94 | R159: 3.95 | S159: =MAX((R159-Q159)*3000,0) -> 30 | T159: =P159-S159 -> 7500
A160: =A159+1 -> 162 | B160: 45905 | C160: 45905 | F160: 687.79 | G160: 690.76 | H160: 680.01 | I160: 712.56 | J160: 723.89 | K160: 728.39 | L160: 728.91 | M160: =SUM(F160:L160) -> 4952.31 | N160: =O159 -> 620.41 | O160: 622.06 | P160: =MAX((O160-N160)*3000,0) -> 4950 | Q160: =R159 -> 3.95 | R160: 3.96 | S160: =MAX((R160-Q160)*3000,0) -> 30 | T160: =P160-S160 -> 4920
A161: =A160+1 -> 163 | B161: 45906 | C161: 45906 | F161: 345.01 | G161: 433.75 | H161: 427.06 | I161: 449.31 | J161: 456.66 | K161: 457.7 | L161: 458.12 | M161: =SUM(F161:L161) -> 3027.61 | N161: =O160 -> 622.06 | O161: 623.05 | P161: =MAX((O161-N161)*3000,0) -> 2970 | Q161: =R160 -> 3.96 | R161: 3.98 | S161: =MAX((R161-Q161)*3000,0) -> 60 | T161: =P161-S161 -> 2910
A162: =A161+1 -> 164 | B162: 45907 | C162: 45907 | F162: 78.48 | G162: 604.37 | H162: 599.53 | I162: 627.11 | J162: 632.54 | K162: 635.14 | L162: 634.11 | M162: =SUM(F162:L162) -> 3811.28 | N162: =O161 -> 623.05 | O162: 624.31 | P162: =MAX((O162-N162)*3000,0) -> 3780 | Q162: =R161 -> 3.98 | R162: 3.99 | S162: =MAX((R162-Q162)*3000,0) -> 30 | T162: =P162-S162 -> 3750
A163: =A162+1 -> 165 | B163: 45908 | C163: 45908 | F163: 638.44 | G163: 638.08 | H163: 630.98 | I163: 661.85 | J163: 664.81 | K163: 666.23 | L163: 666.86 | M163: =SUM(F163:L163) -> 4567.25 | N163: =O162 -> 624.31 | O163: 625.82 | P163: =MAX((O163-N163)*3000,0) -> 4530 | Q163: =R162 -> 3.99 | R163: 4 | S163: =MAX((R163-Q163)*3000,0) -> 30 | T163: =P163-S163 -> 4500
A164: =A163+1 -> 166 | B164: 45909 | C164: 45909 | F164: 1700.35 | G164: 1690.01 | H164: 1689.25 | I164: 1756.37 | J164: 1769.45 | K164: 1768.4 | L164: 1767.46 | M164: =SUM(F164:L164) -> 12141.29 | N164: =O163 -> 625.82 | O164: 629.82 | P164: =MAX((O164-N164)*3000,0) -> 12000 | Q164: =R163 -> 4 | R164: 4.01 | S164: =MAX((R164-Q164)*3000,0) -> 30 | T164: =P164-S164 -> 11970
A165: =A164+1 -> 167 | B165: 45910 | C165: 45910 | F165: 1701.76 | G165: 1699.02 | H165: 1696.45 | I165: 1779.69 | J165: 1781.76 | K165: 1782.04 | L165: 1780.85 | M165: =SUM(F165:L165) -> 12221.57 | N165: =O164 -> 629.82 | O165: 633.87 | P165: =MAX((O165-N165)*3000,0) -> 12150 | Q165: =R164 -> 4.01 | R165: 4.02 | S165: =MAX((R165-Q165)*3000,0) -> 30 | T165: =P165-S165 -> 12120
A166: =A165+1 -> 168 | B166: 45911 | C166: 45911 | F166: 1903.64 | G166: 1863.65 | H166: 1832.68 | I166: 1957.05 | J166: 1979.96 | K166: 1963.64 | L166: 1977.23 | M166: =SUM(F166:L166) -> 13477.85 | N166: =O165 -> 633.87 | O166: 638.29 | P166: =MAX((O166-N166)*3000,0) -> 13260 | Q166: =R165 -> 4.02 | R166: 4.04 | S166: =MAX((R166-Q166)*3000,0) -> 60 | T166: =P166-S166 -> 13200
A167: =A166+1 -> 169 | B167: 45912 | C167: 45912 | F167: 1441.41 | G167: 1413.33 | H167: 1429.64 | I167: 1461.21 | J167: 1480.86 | K167: 1474.29 | L167: 1472.87 | M167: =SUM(F167:L167) -> 10173.61 | N167: =O166 -> 638.29 | O167: 641.64 | P167: =MAX((O167-N167)*3000,0) -> 10050 | Q167: =R166 -> 4.04 | R167: 4.05 | S167: =MAX((R167-Q167)*3000,0) -> 30 | T167: =P167-S167 -> 10020
A168: =A167+1 -> 170 | B168: 45913 | C168: 45913 | F168: 1601.07 | G168: 1580.19 | H168: 1581.12 | I168: 1641.71 | J168: 1647.22 | K168: 1633.09 | L168: 1641.51 | M168: =SUM(F168:L168) -> 11325.91 | N168: =O167 -> 641.64 | O168: 645.37 | P168: =MAX((O168-N168)*3000,0) -> 11190 | Q168: =R167 -> 4.05 | R168: 4.06 | S168: =MAX((R168-Q168)*3000,0) -> 30 | T168: =P168-S168 -> 11160
A169: =A168+1 -> 171 | B169: 45914 | C169: 45914 | F169: 1000.85 | G169: 996.16 | H169: 995.89 | I169: 1047.29 | J169: 1053.12 | K169: 1046.39 | L169: 1041.84 | M169: =SUM(F169:L169) -> 7181.54 | N169: =O168 -> 645.37 | O169: 647.73 | P169: =MAX((O169-N169)*3000,0) -> 7080 | Q169: =R168 -> 4.06 | R169: 4.07 | S169: =MAX((R169-Q169)*3000,0) -> 30 | T169: =P169-S169 -> 7050
... A177: =A176+1 -> 179 | B177: 45922 | C177: 45922 | F177: 1050.74 | G177: 1044.61 | H177: 1055.53 | I177: 1109.89 | J177: 1121.85 | K177: 1111.07 | L177: 1129.61 | M177: =SUM(F177:L177) -> 7623.3 | N177: =O176 -> 673.38 | O177: 675.9 | P177: =MAX((O177-N177)*3000,0) -> 7560 | Q177: =R176 -> 4.15 | R177: 4.16 | S177: =MAX((R177-Q177)*3000,0) -> 30 | T177: =P177-S177 -> 7530
A178: =A177+1 -> 180 | B178: 45923 | C178: 45923 | D178: 0.29166667 | E178: 0.76041667 | F178: 1311.89 | G178: 1314.2 | H178: 1305.7 | I178: 1348.42 | J178: 1364.49 | K178: 1369.36 | L178: 1376.28 | M178: =SUM(F178:L178) -> 9390.34 | N178: =O177 -> 675.9 | O178: 678.95 | P178: =MAX((O178-N178)*3000,0) -> 9150 | Q178: =R177 -> 4.16 | R178: 4.17 | S178: =MAX((R178-Q178)*3000,0) -> 30 | T178: =P178-S178 -> 9120 | V178: 3.65 | W178: 30.41
A179: =A178+1 -> 181 | B179: 45924 | C179: 45924 | D179: 0.29166667 | E179: 0.76041667 | F179: 714.39 | G179: 719.61 | H179: 711.45 | I179: 729.71 | J179: 735.9 | K179: 744.86 | L179: 740.93 | M179: =SUM(F179:L179) -> 5096.85 | N179: =O178 -> 678.95 | O179: 680.66 | P179: =MAX((O179-N179)*3000,0) -> 5130 | Q179: =R178 -> 4.17 | R179: 4.18 | S179: =MAX((R179-Q179)*3000,0) -> 30 | T179: =P179-S179 -> 5100 | V179: 2.06 | W179: 0 | AB179: sunny
A180: =A179+1 -> 182 | B180: 45925 | C180: 45925 | D180: 0.29166667 | E180: 0.77083333 | F180: 1555.73 | G180: 1549.61 | H180: 1558.56 | I180: 1626.51 | J180: 1633.41 | K180: 1628.78 | L180: 1639.84 | M180: =SUM(F180:L180) -> 11192.44 | N180: =O179 -> 680.66 | O180: 684.35 | P180: =MAX((O180-N180)*3000,0) -> 11070 | Q180: =R179 -> 4.18 | R180: 4.2 | S180: =MAX((R180-Q180)*3000,0) -> 60 | T180: =P180-S180 -> 11010 | V180: 4.11 | W180: 0 | AB180: sunny
A181: =A180+1 -> 183 | B181: 45926 | C181: 45926 | D181: 0.29166667 | E181: 0.76041667 | F181: 1698.11 | G181: 1669.15 | H181: 1682.32 | I181: 1720.4 | J181: 1743.48 | K181: 1734.11 | L181: 1750.89 | M181: =SUM(F181:L181) -> 11998.46 | N181: =O180 -> 684.35 | O181: 688.3 | P181: =MAX((O181-N181)*3000,0) -> 11850 | Q181: =R180 -> 4.2 | R181: 4.21 | S181: =MAX((R181-Q181)*3000,0) -> 30 | T181: =P181-S181 -> 11820 | V181: 4.82 | W181: 0 | AB181: sunny
A182: =A181+1 -> 184 | B182: 45927 | C182: 45927 | D182: 0.29166667 | E182: 0.76041667 | F182: 1475.46 | G182: 1464.31 | H182: 1470.8 | I182: 1535.82 | J182: 1555.39 | K182: 1541.39 | L182: 1559.91 | M182: =SUM(F182:L182) -> 10603.08 | N182: =O181 -> 688.3 | O182: 691.79 | P182: =MAX((O182-N182)*3000,0) -> 10470 | Q182: =R181 -> 4.21 | R182: 4.22 | S182: =MAX((R182-Q182)*3000,0) -> 30 | T182: =P182-S182 -> 10440 | V182: 3.86 | W182: 0 | AB182: sunny
A183: =A182+1 -> 185 | B183: 45928 | C183: 45928 | D183: 0.29166667 | E183: 0.75 | F183: 609.47 | G183: 607.34 | H183: 599.6 | I183: 619.57 | J183: 630.48 | K183: 637.57 | L183: 638.11 | M183: =SUM(F183:L183) -> 4342.14 | N183: =O182 -> 691.79 | O183: 693.21 | P183: =MAX((O183-N183)*3000,0) -> 4260 | Q183: =R182 -> 4.22 | R183: 4.24 | S183: =MAX((R183-Q183)*3000,0) -> 60 | T183: =P183-S183 -> 4200 | V183: 1.75 | W183: 0 | AB183: cloudy
A184: =A183+1 -> 186 | B184: 45929 | C184: 45929 | D184: 0.39583333 | E184: 0.71875 | F184: 545.63 | G184: 554.86 | H184: 543.18 | I184: 565.36 | J184: 569.81 | K184: 570.31 | L184: 573.94 | M184: =SUM(F184:L184) -> 3923.09 | N184: =O183 -> 693.21 | O184: 694.53 | P184: =MAX((O184-N184)*3000,0) -> 3960 | Q184: =R183 -> 4.24 | R184: 4.25 | S184: =MAX((R184-Q184)*3000,0) -> 30 | T184: =P184-S184 -> 3930 | V184: 1.5 | W184: 0 | AB184: rainy
A185: =A184+1 -> 187 | B185: 45930 | C185: 45930 | D185: 0.29166667 | E185: 0.70833333 | F185: 504.35 | G185: 502.9 | H185: 499.17 | I185: 520.85 | J185: 525.77 | K185: 528.86 | L185: 529.78 | M185: =SUM(F185:L185) -> 3611.68 | N185: =O184 -> 694.53 | O185: 695.7 | P185: =MAX((O185-N185)*3000,0) -> 3510 | Q185: =R184 -> 4.25 | R185: 4.26 | S185: =MAX((R185-Q185)*3000,0) -> 30 | T185: =P185-S185 -> 3480 | V185: 1.23 | AB185: sunny
A186: =A185+1 -> 188 | B186: 45931 | C186: 45931 | D186: 0.28125 | E186: 0.75 | F186: 587.69 | G186: 584.15 | H186: 579.3 | I186: 604.21 | J186: 608.53 | K186: 611.2 | L186: 612.73 | M186: =SUM(F186:L186) -> 4187.81 | N186: =O185 -> 695.7 | O186: 697.09 | P186: =MAX((O186-N186)*3000,0) -> 4170 | Q186: =R185 -> 4.26 | R186: 4.27 | S186: =MAX((R186-Q186)*3000,0) -> 30 | T186: =P186-S186 -> 4140 | AB186: sunny
A187: =A186+1 -> 189 | B187: 45932 | C187: 45932 | D187: 0.32291667 | E187: 0.75 | F187: 690.26 | G187: 691.63 | H187: 686.9 | I187: 710.95 | J187: 721.28 | K187: 628.05 | L187: 728.84 | M187: =SUM(F187:L187) -> 4857.91 | N187: =O186 -> 697.09 | O187: 698.73 | P187: =MAX((O187-N187)*3000,0) -> 4920 | Q187: =R186 -> 4.27 | R187: 4.28 | S187: =MAX((R187-Q187)*3000,0) -> 30 | T187: =P187-S187 -> 4890 | AB187: sunny
A188: =A187+1 -> 190 | B188: 45933 | C188: 45933 | D188: 0.30208333 | E188: 0.75 | F188: 1539.21 | G188: 1534.83 | H188: 1530.09 | I188: 1601.61 | J188: 1607.34 | K188: 1609.35 | L188: 1616.33 | M188: =SUM(F188:L188) -> 11038.76 | N188: =O187 -> 698.73 | O188: 702.36 | P188: =MAX((O188-N188)*3000,0) -> 10890 | Q188: =R187 -> 4.28 | R188: 4.3 | S188: =MAX((R188-Q188)*3000,0) -> 60 | T188: =P188-S188 -> 10830 | V188: 4.33 | W188: 0 | AB188: sunny
A189: =A188+1 -> 191 | B189: 45934 | C189: 45934 | D189: 0.30208333 | E189: 0.75 | F189: 1681.98 | G189: 1679.47 | H189: 1690.98 | I189: 1727.02 | J189: 1757.05 | K189: 1770.87 | L189: 1778.2 | M189: =SUM(F189:L189) -> 12085.57 | N189: =O188 -> 702.36 | O189: 706.34 | P189: =MAX((O189-N189)*3000,0) -> 11940 | Q189: =R188 -> 4.3 | R189: 4.31 | S189: =MAX((R189-Q189)*3000,0) -> 30 | T189: =P189-S189 -> 11910 | V189: 5.15 | W189: 0 | AB189: sunny
A190: =A189+1 -> 192 | B190: 45935 | C190: 45935 | D190: 0.29166667 | E190: 0.75 | F190: 1699.81 | G190: 1695.63 | H190: 1712.23 | I190: 1749.62 | J190: 1771.03 | K190: 1774.25 | L190: 1773.85 | M190: =SUM(F190:L190) -> 12176.42 | N190: =O189 -> 706.34 | O190: 710.36 | P190: =MAX((O190-N190)*3000,0) -> 12060 | Q190: =R189 -> 4.31 | R190: 4.32 | S190: =MAX((R190-Q190)*3000,0) -> 30 | T190: =P190-S190 -> 12030 | V190: 4.6 | W190: 0 | AB190: sunny
A191: =A190+1 -> 193 | B191: 45936 | C191: 45936 | D191: 0.29166667 | E191: 0.76041667 | F191: 1713.34 | G191: 1694.88 | H191: 1709.67 | I191: 1726.5 | J191: 1765.81 | K191: 1780.57 | L191: 1775.75 | M191: =SUM(F191:L191) -> 12166.52 | N191: =O190 -> 710.36 | O191: 714.36 | P191: =MAX((O191-N191)*3000,0) -> 12000 | Q191: =R190 -> 4.32 | R191: 4.33 | S191: =MAX((R191-Q191)*3000,0) -> 30 | T191: =P191-S191 -> 11970 | V191: 4.83 | W191: 0 | AB191: sunny
A192: =A191+1 -> 194 | B192: 45937 | C192: 45937 | D192: 0.29166667 | E192: 0.75 | F192: 1812.1 | G192: 1806..57 | H192: 1806.87 | I192: 1835.74 | J192: 1877.23 | K192: 1897.92 | L192: 1890.35 | M192: =SUM(F192:L192) -> 11120.21 | N192: =O191 -> 714.36 | O192: 718.62 | P192: =MAX((O192-N192)*3000,0) -> 12780 | Q192: =R191 -> 4.33 | R192: 4.35 | S192: =MAX((R192-Q192)*3000,0) -> 60 | T192: =P192-S192 -> 12720 | V192: 5.09 | W192: 0 | AB192: sunny
...

Sheet Inverter_PR
A1: Inverter_Availability_Sheet
C2: 335.72 | D2: 335.72 | E2: 335.72 | F2: 350.98 | G2: 350.98 | H2: 350.98 | I2: 350.98
C3: Inv_1 | D3: Inv_2 | E3: Inv_3 | F3: Inv_4 | G3: Inv_5 | H3: Inv_6 | I3: Inv_7
A4: 45747 | B4: 45747
A5: 45748 | B5: 45748 | C5: =IFERROR((Data_Entry!F3/Data_Entry!$V3/C$2),"") -> 1.0254269 | D5: =IFERROR((Data_Entry!G3/Data_Entry!$V3/D$2),"") -> 1.0427075 | E5: =IFERROR((Data_Entry!H3/Data_Entry!$V3/E$2),"") -> 1.0239913 | F5: =IFERROR((Data_Entry!I3/Data_Entry!$V3/F$2),"") -> 1.0325755 | G5: =IFERROR((Data_Entry!J3/Data_Entry!$V3/G$2),"") -> 1.0407682 | H5: =IFERROR((Data_Entry!K3/Data_Entry!$V3/H$2),"") -> 1.0400122 | I5: =IFERROR((Data_Entry!L3/Data_Entry!$V3/I$2),"") -> 1.0309967
A6: 45749 | B6: 45749 | C6: =IFERROR((Data_Entry!F4/Data_Entry!$V4/C$2),"") -> 1.0448415 | D6: =IFERROR((Data_Entry!G4/Data_Entry!$V4/D$2),"") -> 1.0638879 | E6: =IFERROR((Data_Entry!H4/Data_Entry!$V4/E$2),"") -> 1.0445799 | F6: =IFERROR((Data_Entry!I4/Data_Entry!$V4/F$2),"") -> 1.0526389 | G6: =IFERROR((Data_Entry!J4/Data_Entry!$V4/G$2),"") -> 1.0569739 | H6: =IFERROR((Data_Entry!K4/Data_Entry!$V4/H$2),"") -> 1.0550387 | I6: =IFERROR((Data_Entry!L4/Data_Entry!$V4/I$2),"") -> 1.0524142
A7: 45750 | B7: 45750 | C7: =IFERROR((Data_Entry!F5/Data_Entry!$V5/C$2),"") -> 1.0402279 | D7: =IFERROR((Data_Entry!G5/Data_Entry!$V5/D$2),"") -> 1.0627705 | E7: =IFERROR((Data_Entry!H5/Data_Entry!$V5/E$2),"") -> 1.0426076 | F7: =IFERROR((Data_Entry!I5/Data_Entry!$V5/F$2),"") -> 1.0507477 | G7: =IFERROR((Data_Entry!J5/Data_Entry!$V5/G$2),"") -> 1.0559845 | H7: =IFERROR((Data_Entry!K5/Data_Entry!$V5/H$2),"") -> 1.0554008 | I7: =IFERROR((Data_Entry!L5/Data_Entry!$V5/I$2),"") -> 1.057348
A8: 45751 | B8: 45751 | C8: =IFERROR((Data_Entry!F6/Data_Entry!$V6/C$2),"") -> 1.0476008 | D8: =IFERROR((Data_Entry!G6/Data_Entry!$V6/D$2),"") -> 1.0654068 | E8: =IFERROR((Data_Entry!H6/Data_Entry!$V6/E$2),"") -> 1.0471053 | F8: =IFERROR((Data_Entry!I6/Data_Entry!$V6/F$2),"") -> 1.0582463 | G8: =IFERROR((Data_Entry!J6/Data_Entry!$V6/G$2),"") -> 1.0643976 | H8: =IFERROR((Data_Entry!K6/Data_Entry!$V6/H$2),"") -> 1.0580409 | I8: =IFERROR((Data_Entry!L6/Data_Entry!$V6/I$2),"") -> 1.0607637
A9: 45752 | B9: 45752 | C9: =IFERROR((Data_Entry!F7/Data_Entry!$V7/C$2),"") -> 1.0512718 | D9: =IFERROR((Data_Entry!G7/Data_Entry!$V7/D$2),"") -> 1.0658144 | E9: =IFERROR((Data_Entry!H7/Data_Entry!$V7/E$2),"") -> 1.0500901 | F9: =IFERROR((Data_Entry!I7/Data_Entry!$V7/F$2),"") -> 1.0581655 | G9: =IFERROR((Data_Entry!J7/Data_Entry!$V7/G$2),"") -> 1.0641167 | H9: =IFERROR((Data_Entry!K7/Data_Entry!$V7/H$2),"") -> 1.0616753 | I9: =IFERROR((Data_Entry!L7/Data_Entry!$V7/I$2),"") -> 1.0626199
A10: 45753 | B10: 45753 | C10: =IFERROR((Data_Entry!F8/Data_Entry!$V8/C$2),"") -> 1.0559502 | D10: =IFERROR((Data_Entry!G8/Data_Entry!$V8/D$2),"") -> 1.0714007 | E10: =IFERROR((Data_Entry!H8/Data_Entry!$V8/E$2),"") -> 1.0554787 | F10: =IFERROR((Data_Entry!I8/Data_Entry!$V8/F$2),"") -> 1.0632357 | G10: =IFERROR((Data_Entry!J8/Data_Entry!$V8/G$2),"") -> 1.0685599 | H10: =IFERROR((Data_Entry!K8/Data_Entry!$V8/H$2),"") -> 1.0611603 | I10: =IFERROR((Data_Entry!L8/Data_Entry!$V8/I$2),"") -> 1.0670482
A11: 45754 | B11: 45754 | C11: =IFERROR((Data_Entry!F9/Data_Entry!$V9/C$2),"") -> 1.0496515 | D11: =IFERROR((Data_Entry!G9/Data_Entry!$V9/D$2),"") -> 1.0735027 | E11: =IFERROR((Data_Entry!H9/Data_Entry!$V9/E$2),"") -> 1.0513348 | F11: =IFERROR((Data_Entry!I9/Data_Entry!$V9/F$2),"") -> 1.0644952 | G11: =IFERROR((Data_Entry!J9/Data_Entry!$V9/G$2),"") -> 1.0847373 | H11: =IFERROR((Data_Entry!K9/Data_Entry!$V9/H$2),"") -> 1.0600463 | I11: =IFERROR((Data_Entry!L9/Data_Entry!$V9/I$2),"") -> 1.0703346
A12: 45755 | B12: 45755 | C12: =IFERROR((Data_Entry!F10/Data_Entry!$V10/C$2),"") -> 1.0329158 | D12: =IFERROR((Data_Entry!G10/Data_Entry!$V10/D$2),"") -> 1.0660935 | E12: =IFERROR((Data_Entry!H10/Data_Entry!$V10/E$2),"") -> 1.0319338 | F12: =IFERROR((Data_Entry!I10/Data_Entry!$V10/F$2),"") -> 1.0558466 | G12: =IFERROR((Data_Entry!J10/Data_Entry!$V10/G$2),"") -> 1.0658369 | H12: =IFERROR((Data_Entry!K10/Data_Entry!$V10/H$2),"") -> 1.042919 | I12: =IFERROR((Data_Entry!L10/Data_Entry!$V10/I$2),"") -> 1.0662054
A13: 45756 | B13: 45756 | C13: =IFERROR((Data_Entry!F11/Data_Entry!$V11/C$2),"") -> 1.0390311 | D13: =IFERROR((Data_Entry!G11/Data_Entry!$V11/D$2),"") -> 1.0657516 | E13: =IFERROR((Data_Entry!H11/Data_Entry!$V11/E$2),"") -> 1.0361291 | F13: =IFERROR((Data_Entry!I11/Data_Entry!$V11/F$2),"") -> 1.0523056 | G13: =IFERROR((Data_Entry!J11/Data_Entry!$V11/G$2),"") -> 1.062283 | H13: =IFERROR((Data_Entry!K11/Data_Entry!$V11/H$2),"") -> 1.049556 | I13: =IFERROR((Data_Entry!L11/Data_Entry!$V11/I$2),"") -> 1.0628329
A14: 45757 | B14: 45757 | C14: =IFERROR((Data_Entry!F12/Data_Entry!$V12/C$2),"") -> 1.0315063 | D14: =IFERROR((Data_Entry!G12/Data_Entry!$V12/D$2),"") -> 1.0582392 | E14: =IFERROR((Data_Entry!H12/Data_Entry!$V12/E$2),"") -> 1.0260588 | F14: =IFERROR((Data_Entry!I12/Data_Entry!$V12/F$2),"") -> 1.045926 | G14: =IFERROR((Data_Entry!J12/Data_Entry!$V12/G$2),"") -> 1.0562959 | H14: =IFERROR((Data_Entry!K12/Data_Entry!$V12/H$2),"") -> 1.0394935 | I14: =IFERROR((Data_Entry!L12/Data_Entry!$V12/I$2),"") -> 1.0561419
A15: 45758 | B15: 45758 | C15: =IFERROR((Data_Entry!F13/Data_Entry!$V13/C$2),"") -> 1.0549147 | D15: =IFERROR((Data_Entry!G13/Data_Entry!$V13/D$2),"") -> 1.0801651 | E15: =IFERROR((Data_Entry!H13/Data_Entry!$V13/E$2),"") -> 1.0497826 | F15: =IFERROR((Data_Entry!I13/Data_Entry!$V13/F$2),"") -> 1.070319 | G15: =IFERROR((Data_Entry!J13/Data_Entry!$V13/G$2),"") -> 1.0796506 | H15: =IFERROR((Data_Entry!K13/Data_Entry!$V13/H$2),"") -> 1.0586609 | I15: =IFERROR((Data_Entry!L13/Data_Entry!$V13/I$2),"") -> 1.0769844
A16: 45759 | B16: 45759 | C16: =IFERROR((Data_Entry!F14/Data_Entry!$V14/C$2),"") -> 2.807508 | D16: =IFERROR((Data_Entry!G14/Data_Entry!$V14/D$2),"") -> 2.8797226 | E16: =IFERROR((Data_Entry!H14/Data_Entry!$V14/E$2),"") -> 2.7855675 | F16: =IFERROR((Data_Entry!I14/Data_Entry!$V14/F$2),"") -> 2.8440228 | G16: =IFERROR((Data_Entry!J14/Data_Entry!$V14/G$2),"") -> 2.8649954 | H16: =IFERROR((Data_Entry!K14/Data_Entry!$V14/H$2),"") -> 2.8177549 | I16: =IFERROR((Data_Entry!L14/Data_Entry!$V14/I$2),"") -> 2.8703602
... A70: 45813 | B70: 45813 | C70: =IFERROR((Data_Entry!F68/Data_Entry!$V68/C$2),"") -> 1.0172508 | D70: =IFERROR((Data_Entry!G68/Data_Entry!$V68/D$2),"") -> 1.0195076 | E70: =IFERROR((Data_Entry!H68/Data_Entry!$V68/E$2),"") -> 1.0070188 | F70: =IFERROR((Data_Entry!I68/Data_Entry!$V68/F$2),"") -> 1.0121333 | G70: =IFERROR((Data_Entry!J68/Data_Entry!$V68/G$2),"") -> 1.0166082 | H70: =IFERROR((Data_Entry!K68/Data_Entry!$V68/H$2),"") -> 1.0132371 | I70: =IFERROR((Data_Entry!L68/Data_Entry!$V68/I$2),"") -> 1.0180709
A71: 45814 | B71: 45814 | C71: =IFERROR((Data_Entry!F69/Data_Entry!$V69/C$2),"") -> 1.0073058 | D71: =IFERROR((Data_Entry!G69/Data_Entry!$V69/D$2),"") -> 1.0123181 | E71: =IFERROR((Data_Entry!I69/Data_Entry!$V69/E$2),"") -> 1.0503709 | F71: =IFERROR((Data_Entry!J69/Data_Entry!$V69/F$2),"") -> 1.0108815 | G71: =IFERROR((Data_Entry!K69/Data_Entry!$V69/G$2),"") -> 1.0043307 | H71: =IFERROR((Data_Entry!L69/Data_Entry!$V69/H$2),"") -> 1.0128096 | I71: =IFERROR((Data_Entry!#REF!/Data_Entry!$V69/I$2),"")
A72: 45815 | B72: 45815 | C72: =IFERROR((Data_Entry!F70/Data_Entry!$V70/C$2),"") -> 0.97047296 | D72: =IFERROR((Data_Entry!G70/Data_Entry!$V70/D$2),"") -> 0.97349668 | E72: =IFERROR((Data_Entry!H70/Data_Entry!$V70/E$2),"") -> 0.96415525 | F72: =IFERROR((Data_Entry!I70/Data_Entry!$V70/F$2),"") -> 0.96677723 | G72: =IFERROR((Data_Entry!J70/Data_Entry!$V70/G$2),"") -> 0.97285257 | H72: =IFERROR((Data_Entry!K70/Data_Entry!$V70/H$2),"") -> 0.96705191 | I72: =IFERROR((Data_Entry!L70/Data_Entry!$V70/I$2),"") -> 0.97377357
A73: 45816 | B73: 45816 | C73: =IFERROR((Data_Entry!F71/Data_Entry!$V71/C$2),"") -> 0.95181307 | D73: =IFERROR((Data_Entry!G71/Data_Entry!$V71/D$2),"") -> 0.95384123 | E73: =IFERROR((Data_Entry!H71/Data_Entry!$V71/E$2),"") -> 0.9469031 | F73: =IFERROR((Data_Entry!I71/Data_Entry!$V71/F$2),"") -> 0.94635717 | G73: =IFERROR((Data_Entry!J71/Data_Entry!$V71/G$2),"") -> 0.95059617 | H73: =IFERROR((Data_Entry!K71/Data_Entry!$V71/H$2),"") -> 0.94572595 | I73: =IFERROR((Data_Entry!L71/Data_Entry!$V71/I$2),"") -> 0.94983755
A74: 45817 | B74: 45817 | C74: =IFERROR((Data_Entry!F72/Data_Entry!$V72/C$2),"") -> 0.99383523 | D74: =IFERROR((Data_Entry!G72/Data_Entry!$V72/D$2),"") -> 0.9972294 | E74: =IFERROR((Data_Entry!H72/Data_Entry!$V72/E$2),"") -> 0.98482366 | F74: =IFERROR((Data_Entry!I72/Data_Entry!$V72/F$2),"") -> 0.98743704 | G74: =IFERROR((Data_Entry!J72/Data_Entry!$V72/G$2),"") -> 0.99178821 | H74: =IFERROR((Data_Entry!K72/Data_Entry!$V72/H$2),"") -> 0.98125869 | I74: =IFERROR((Data_Entry!L72/Data_Entry!$V72/I$2),"") -> 0.99192757
A75: 45818 | B75: 45818 | C75: =IFERROR((Data_Entry!F73/Data_Entry!$V73/C$2),"") -> 1.0467094 | D75: =IFERROR((Data_Entry!G73/Data_Entry!$V73/D$2),"") -> 1.0366603 | E75: =IFERROR((Data_Entry!H73/Data_Entry!$V73/E$2),"") -> 1.0358951 | F75: =IFERROR((Data_Entry!I73/Data_Entry!$V73/F$2),"") -> 1.0411249 | G75: =IFERROR((Data_Entry!J73/Data_Entry!$V73/G$2),"") -> 1.0449359 | H75: =IFERROR((Data_Entry!K73/Data_Entry!$V73/H$2),"") -> 1.0305993 | I75: =IFERROR((Data_Entry!L73/Data_Entry!$V73/I$2),"") -> 1.0467204
A76: 45819 | B76: 45819 | C76: =IFERROR((Data_Entry!F74/Data_Entry!$V74/C$2),"") -> 1.040158 | D76: =IFERROR((Data_Entry!G74/Data_Entry!$V74/D$2),"") -> 1.0555227 | E76: =IFERROR((Data_Entry!H74/Data_Entry!$V74/E$2),"") -> 1.0292886 | F76: =IFERROR((Data_Entry!I74/Data_Entry!$V74/F$2),"") -> 1.0613206 | G76: =IFERROR((Data_Entry!J74/Data_Entry!$V74/G$2),"") -> 0.99707059 | H76: =IFERROR((Data_Entry!K74/Data_Entry!$V74/H$2),"") -> 1.0271044 | I76: =IFERROR((Data_Entry!L74/Data_Entry!$V74/I$2),"") -> 1.0909819
A77: 45820 | B77: 45820 | C77: =IFERROR((Data_Entry!F75/Data_Entry!$V75/C$2),"") -> 0.97229545 | D77: =IFERROR((Data_Entry!G75/Data_Entry!$V75/D$2),"") -> 1.0024862 | E77: =IFERROR((Data_Entry!H75/Data_Entry!$V75/E$2),"") -> 0.96978106 | F77: =IFERROR((Data_Entry!I75/Data_Entry!$V75/F$2),"") -> 0.99420293 | G77: =IFERROR((Data_Entry!J75/Data_Entry!$V75/G$2),"") -> 1.0009913 | H77: =IFERROR((Data_Entry!K75/Data_Entry!$V75/H$2),"") -> 0.98996955 | I77: =IFERROR((Data_Entry!L75/Data_Entry!$V75/I$2),"") -> 1.003033
A78: 45821 | B78: 45821 | C78: =IFERROR((Data_Entry!F76/Data_Entry!$V76/C$2),"") -> 0.96503188 | D78: =IFERROR((Data_Entry!G76/Data_Entry!$V76/D$2),"") -> 0.97118006 | E78: =IFERROR((Data_Entry!H76/Data_Entry!$V76/E$2),"") -> 0.96066758 | F78: =IFERROR((Data_Entry!I76/Data_Entry!$V76/F$2),"") -> 0.96568446 | G78: =IFERROR((Data_Entry!J76/Data_Entry!$V76/G$2),"") -> 0.96970822 | H78: =IFERROR((Data_Entry!K76/Data_Entry!$V76/H$2),"") -> 0.97454942 | I78: =IFERROR((Data_Entry!L76/Data_Entry!$V76/I$2),"") -> 0.97450973
A79: 45822 | B79: 45822 | C79: =IFERROR((Data_Entry!F77/Data_Entry!$V77/C$2),"") -> 0.9629118 | D79: =IFERROR((Data_Entry!G77/Data_Entry!$V77/D$2),"") -> 0.96571051 | E79: =IFERROR((Data_Entry!H77/Data_Entry!$V77/E$2),"") -> 0.95519207 | F79: =IFERROR((Data_Entry!I77/Data_Entry!$V77/F$2),"") -> 0.95774094 | G79: =IFERROR((Data_Entry!J77/Data_Entry!$V77/G$2),"") -> 0.96031706 | H79: =IFERROR((Data_Entry!K77/Data_Entry!$V77/H$2),"") -> 0.95960477 | I79: =IFERROR((Data_Entry!L77/Data_Entry!$V77/I$2),"") -> 0.96285163
A80: 45823 | B80: 45823 | C80: =IFERROR((Data_Entry!F78/Data_Entry!$V78/C$2),"") -> 0.69826359 | D80: =IFERROR((Data_Entry!G78/Data_Entry!$V78/D$2),"") -> 0.70152315 | E80: =IFERROR((Data_Entry!H78/Data_Entry!$V78/E$2),"") -> 0.69278309 | F80: =IFERROR((Data_Entry!I78/Data_Entry!$V78/F$2),"") -> 0.69720197 | G80: =IFERROR((Data_Entry!J78/Data_Entry!$V78/G$2),"") -> 0.69892022 | H80: =IFERROR((Data_Entry!K78/Data_Entry!$V78/H$2),"") -> 0.69951379 | I80: =IFERROR((Data_Entry!L78/Data_Entry!$V78/I$2),"") -> 0.701357
A81: 45824 | B81: 45824 | C81: =IFERROR((Data_Entry!F79/Data_Entry!$V79/C$2),"") -> 1.2718932 | D81: =IFERROR((Data_Entry!G79/Data_Entry!$V79/D$2),"") -> 1.2310984 | E81: =IFERROR((Data_Entry!H79/Data_Entry!$V79/E$2),"") -> 1.2191189 | F81: =IFERROR((Data_Entry!I79/Data_Entry!$V79/F$2),"") -> 1.3083243 | G81: =IFERROR((Data_Entry!J79/Data_Entry!$V79/G$2),"") -> 1.3601048 | H81: =IFERROR((Data_Entry!K79/Data_Entry!$V79/H$2),"") -> 1.3836413 | I81: =IFERROR((Data_Entry!L79/Data_Entry!$V79/I$2),"") -> 1.3952857
A82: 45825 | B82: 45825 | C82: =IFERROR((Data_Entry!F80/Data_Entry!$V80/C$2),"") -> 1.0991302 | D82: =IFERROR((Data_Entry!G80/Data_Entry!$V80/D$2),"") -> 1.1054795 | E82: =IFERROR((Data_Entry!H80/Data_Entry!$V80/E$2),"") -> 1.0912524 | F82: =IFERROR((Data_Entry!I80/Data_Entry!$V80/F$2),"") -> 1.0897682 | G82: =IFERROR((Data_Entry!J80/Data_Entry!$V80/G$2),"") -> 1.0855694 | H82: =IFERROR((Data_Entry!K80/Data_Entry!$V80/H$2),"") -> 1.105776 | I82: =IFERROR((Data_Entry!L80/Data_Entry!$V80/I$2),"") -> 1.1033767
A83: 45826 | B83: 45826 | C83: =IFERROR((Data_Entry!F81/Data_Entry!$V81/C$2),"") -> 1.0934659 | D83: =IFERROR((Data_Entry!G81/Data_Entry!$V81/D$2),"") -> 1.0862145 | E83: =IFERROR((Data_Entry!H81/Data_Entry!$V81/E$2),"") -> 1.0827231 | F83: =IFERROR((Data_Entry!I81/Data_Entry!$V81/F$2),"") -> 1.0634392 | G83: =IFERROR((Data_Entry!J81/Data_Entry!$V81/G$2),"") -> 1.0493802 | H83: =IFERROR((Data_Entry!K81/Data_Entry!$V81/H$2),"") -> 1.055896 | I83: =IFERROR((Data_Entry!L81/Data_Entry!$V81/I$2),"") -> 1.0954573
... A98: 45841 | B98: 45841 | C98: =IFERROR((Data_Entry!F96/Data_Entry!$V96/C$2),"") -> 2.0326172 | D98: =IFERROR((Data_Entry!G96/Data_Entry!$V96/D$2),"") -> 2.0029031 | E98: =IFERROR((Data_Entry!H96/Data_Entry!$V96/E$2),"") -> 2.0010869 | F98: =IFERROR((Data_Entry!I96/Data_Entry!$V96/F$2),"") -> 2.0354158 | G98: =IFERROR((Data_Entry!J96/Data_Entry!$V96/G$2),"") -> 2.0193632 | H98: =IFERROR((Data_Entry!K96/Data_Entry!$V96/H$2),"") -> 2.0345819 | I98: =IFERROR((Data_Entry!L96/Data_Entry!$V96/I$2),"") -> 2.0315243
A99: 45842 | B99: 45842 | C99: =IFERROR((Data_Entry!F97/Data_Entry!$V97/C$2),"") -> 2.6621714 | D99: =IFERROR((Data_Entry!G97/Data_Entry!$V97/D$2),"") -> 2.6844422 | E99: =IFERROR((Data_Entry!H97/Data_Entry!$V97/E$2),"") -> 2.6699644 | F99: =IFERROR((Data_Entry!I97/Data_Entry!$V97/F$2),"") -> 2.6767244 | G99: =IFERROR((Data_Entry!K97/Data_Entry!$V97/G$2),"") -> 2.7080653 | H99: =IFERROR((Data_Entry!L97/Data_Entry!$V97/H$2),"") -> 2.7063756 | I99: =IFERROR((Data_Entry!#REF!/Data_Entry!$V97/I$2),"")
A100: 45843 | B100: 45843 | C100: =IFERROR((Data_Entry!F98/Data_Entry!$V98/C$2),"") -> 1.895015 | D100: =IFERROR((Data_Entry!G98/Data_Entry!$V98/D$2),"") -> 2.0921039 | E100: =IFERROR((Data_Entry!H98/Data_Entry!$V98/E$2),"") -> 2.0693777 | F100: =IFERROR((Data_Entry!I98/Data_Entry!$V98/F$2),"") -> 2.0818956 | G100: =IFERROR((Data_Entry!J98/Data_Entry!$V98/G$2),"") -> 2.0702087 | H100: =IFERROR((Data_Entry!K98/Data_Entry!$V98/H$2),"") -> 2.0946377 | I100: =IFERROR((Data_Entry!L98/Data_Entry!$V98/I$2),"") -> 2.0936088
A101: 45844 | B101: 45844 | C101: =IFERROR((Data_Entry!F99/Data_Entry!$V99/C$2),"") -> 5.830938 | D101: =IFERROR((Data_Entry!G99/Data_Entry!$V99/D$2),"") -> 5.8270905 | E101: =IFERROR((Data_Entry!H99/Data_Entry!$V99/E$2),"") -> 5.7862579 | F101: =IFERROR((Data_Entry!I99/Data_Entry!$V99/F$2),"") -> 5.7933619 | G101: =IFERROR((Data_Entry!J99/Data_Entry!$V99/G$2),"") -> 5.7892069 | H101: =IFERROR((Data_Entry!K99/Data_Entry!$V99/H$2),"") -> 5.8381176 | I101: =IFERROR((Data_Entry!L99/Data_Entry!$V99/I$2),"") -> 5.8320037
A102: 45845 | B102: 45845 | C102: =IFERROR((Data_Entry!F100/Data_Entry!$V100/C$2),"") -> 5.241802 | D102: =IFERROR((Data_Entry!G100/Data_Entry!$V100/D$2),"") -> 5.9054944 | E102: =IFERROR((Data_Entry!H100/Data_Entry!$V100/E$2),"") -> 5.8662201 | F102: =IFERROR((Data_Entry!I100/Data_Entry!$V100/F$2),"") -> 5.8941841 | G102: =IFERROR((Data_Entry!J100/Data_Entry!$V100/G$2),"") -> 5.874451 | H102: =IFERROR((Data_Entry!K100/Data_Entry!$V100/H$2),"") -> 5.934178 | I102: =IFERROR((Data_Entry!L100/Data_Entry!$V100/I$2),"") -> 5.9196156
A103: 45846 | B103: 45846 | C103: =IFERROR((Data_Entry!F101/Data_Entry!$V101/C$2),"") -> 8.5288501 | D103: =IFERROR((Data_Entry!G101/Data_Entry!$V101/D$2),"") -> 8.5426678 | E103: =IFERROR((Data_Entry!H101/Data_Entry!$V101/E$2),"") -> 8.5078339 | F103: =IFERROR((Data_Entry!I101/Data_Entry!$V101/F$2),"") -> 8.5212991 | G103: =IFERROR((Data_Entry!J101/Data_Entry!$V101/G$2),"") -> 8.5360989 | H103: =IFERROR((Data_Entry!K101/Data_Entry!$V101/H$2),"") -> 8.5667274 | I103: =IFERROR((Data_Entry!L101/Data_Entry!$V101/I$2),"") -> 8.5304797
A104: 45847 | B104: 45847 | C104: =IFERROR((Data_Entry!F102/Data_Entry!$V102/C$2),"") | D104: =IFERROR((Data_Entry!G102/Data_Entry!$V102/D$2),"") | E104: =IFERROR((Data_Entry!H102/Data_Entry!$V102/E$2),"") | F104: =IFERROR((Data_Entry!I102/Data_Entry!$V102/F$2),"") | G104: =IFERROR((Data_Entry!J102/Data_Entry!$V102/G$2),"") | H104: =IFERROR((Data_Entry!K102/Data_Entry!$V102/H$2),"") | I104: =IFERROR((Data_Entry!L102/Data_Entry!$V102/I$2),"")
A105: 45848 | B105: 45848 | C105: =IFERROR((Data_Entry!F103/Data_Entry!$V103/C$2),"") | D105: =IFERROR((Data_Entry!G103/Data_Entry!$V103/D$2),"") | E105: =IFERROR((Data_Entry!H103/Data_Entry!$V103/E$2),"") | F105: =IFERROR((Data_Entry!I103/Data_Entry!$V103/F$2),"") | G105: =IFERROR((Data_Entry!J103/Data_Entry!$V103/G$2),"") | H105: =IFERROR((Data_Entry!K103/Data_Entry!$V103/H$2),"") | I105: =IFERROR((Data_Entry!L103/Data_Entry!$V103/I$2),"")
A106: 45849 | B106: 45849 | C106: =IFERROR((Data_Entry!F104/Data_Entry!$V104/C$2),"") -> 1.7805802 | D106: =IFERROR((Data_Entry!G104/Data_Entry!$V104/D$2),"") -> 1.7860936 | E106: =IFERROR((Data_Entry!H104/Data_Entry!$V104/E$2),"") -> 1.7670375 | F106: =IFERROR((Data_Entry!I104/Data_Entry!$V104/F$2),"") -> 1.7711366 | G106: =IFERROR((Data_Entry!J104/Data_Entry!$V104/G$2),"") -> 1.7637748 | H106: =IFERROR((Data_Entry!K104/Data_Entry!$V104/H$2),"") -> 1.7888333 | I106: =IFERROR((Data_Entry!L104/Data_Entry!$V104/I$2),"") -> 1.7853648
A107: 45850 | B107: 45850 | C107: =IFERROR((Data_Entry!F105/Data_Entry!$V105/C$2),"") -> 1.1030836 | D107: =IFERROR((Data_Entry!G105/Data_Entry!$V105/D$2),"") -> 1.1030562 | E107: =IFERROR((Data_Entry!H105/Data_Entry!$V105/E$2),"") -> 1.091433 | F107: =IFERROR((Data_Entry!I105/Data_Entry!$V105/F$2),"") -> 1.091422 | G107: =IFERROR((Data_Entry!J105/Data_Entry!$V105/G$2),"") -> 1.0846693 | H107: =IFERROR((Data_Entry!K105/Data_Entry!$V105/H$2),"") -> 1.1004574 | I107: =IFERROR((Data_Entry!L105/Data_Entry!$V105/I$2),"") -> 1.09631
A108: 45851 | B108: 45851 | C108: =IFERROR((Data_Entry!F106/Data_Entry!$V106/C$2),"") -> 1.375606 | D108: =IFERROR((Data_Entry!G106/Data_Entry!$V106/D$2),"") -> 1.3632924 | E108: =IFERROR((Data_Entry!H106/Data_Entry!$V106/E$2),"") -> 1.3678757 | F108: =IFERROR((Data_Entry!I106/Data_Entry!$V106/F$2),"") -> 1.3553377 | G108: =IFERROR((Data_Entry!J106/Data_Entry!$V106/G$2),"") -> 1.3488592 | H108: =IFERROR((Data_Entry!K106/Data_Entry!$V106/H$2),"") -> 1.3685745 | I108: =IFERROR((Data_Entry!L106/Data_Entry!$V106/I$2),"") -> 1.3605781
A109: 45852 | B109: 45852 | C109: =IFERROR((Data_Entry!F107/Data_Entry!$V107/C$2),"") -> 1.2524614 | D109: =IFERROR((Data_Entry!G107/Data_Entry!$V107/D$2),"") -> 1.2464423 | E109: =IFERROR((Data_Entry!H107/Data_Entry!$V107/E$2),"") -> 1.2463718 | F109: =IFERROR((Data_Entry!I107/Data_Entry!$V107/F$2),"") -> 1.2379117 | G109: =IFERROR((Data_Entry!J107/Data_Entry!$V107/G$2),"") -> 1.2405754 | H109: =IFERROR((Data_Entry!K107/Data_Entry!$V107/H$2),"") -> 1.2462569 | I109: =IFERROR((Data_Entry!L107/Data_Entry!$V107/I$2),"") -> 1.2408704
A110: 45853 | B110: 45853 | C110: =IFERROR((Data_Entry!F108/Data_Entry!$V108/C$2),"") -> 1.2714613 | D110: =IFERROR((Data_Entry!G108/Data_Entry!$V108/D$2),"") -> 1.2760778 | E110: =IFERROR((Data_Entry!H108/Data_Entry!$V108/E$2),"") -> 1.2621563 | F110: =IFERROR((Data_Entry!I108/Data_Entry!$V108/F$2),"") -> 1.2670694 | G110: =IFERROR((Data_Entry!J108/Data_Entry!$V108/G$2),"") -> 1.268636 | H110: =IFERROR((Data_Entry!K108/Data_Entry!$V108/H$2),"") -> 1.2730518 | I110: =IFERROR((Data_Entry!L108/Data_Entry!$V108/I$2),"") -> 1.2736629
A111: 45854 | B111: 45854 | C111: =IFERROR((Data_Entry!F109/Data_Entry!$V109/C$2),"") -> 1.3857826 | D111: =IFERROR((Data_Entry!G109/Data_Entry!$V109/D$2),"") -> 1.3838178 | E111: =IFERROR((Data_Entry!H109/Data_Entry!$V109/E$2),"") -> 1.3689334 | F111: =IFERROR((Data_Entry!I109/Data_Entry!$V109/F$2),"") -> 1.3815791 | G111: =IFERROR((Data_Entry!J109/Data_Entry!$V109/G$2),"") -> 1.3822313 | H111: =IFERROR((Data_Entry!K109/Data_Entry!$V109/H$2),"") -> 1.3837846 | I111: =IFERROR((Data_Entry!L109/Data_Entry!$V109/I$2),"") -> 1.385089
... A252: 45995 | B252: 45995 | C252: =IFERROR((Data_Entry!F250/Data_Entry!$V250/C$2),"") -> 1.0769248 | D252: =IFERROR((Data_Entry!G250/Data_Entry!$V250/D$2),"") -> 1.1455894 | E252: =IFERROR((Data_Entry!H250/Data_Entry!$V250/E$2),"") -> 1.0754559 | F252: =IFERROR((Data_Entry!I250/Data_Entry!$V250/F$2),"") -> 1.1112447 | G252: =IFERROR((Data_Entry!J250/Data_Entry!$V250/G$2),"") -> 1.115819 | H252: =IFERROR((Data_Entry!K250/Data_Entry!$V250/H$2),"") -> 1.1141953 | I252: =IFERROR((Data_Entry!L250/Data_Entry!$V250/I$2),"") -> 1.1147495
A253: 45996 | B253: 45996 | C253: =IFERROR((Data_Entry!F251/Data_Entry!$W251/C$2),"") -> 0.15013287 | D253: =IFERROR((Data_Entry!G251/Data_Entry!$W251/D$2),"") -> 0.15940947 | E253: =IFERROR((Data_Entry!H251/Data_Entry!$W251/E$2),"") -> 0.14983112 | F253: =IFERROR((Data_Entry!I251/Data_Entry!$W251/F$2),"") -> 0.15555062 | G253: =IFERROR((Data_Entry!J251/Data_Entry!$W251/G$2),"") -> 0.15537129 | H253: =IFERROR((Data_Entry!K251/Data_Entry!$W251/H$2),"") -> 0.15495957 | I253: =IFERROR((Data_Entry!L251/Data_Entry!$W251/I$2),"") -> 0.15493728
A254: 45997 | B254: 45997 | C254: =IFERROR((Data_Entry!F252/Data_Entry!$W252/C$2),"") -> 0.14086313 | D254: =IFERROR((Data_Entry!G252/Data_Entry!$W252/D$2),"") -> 0.14810452 | E254: =IFERROR((Data_Entry!H252/Data_Entry!$W252/E$2),"") -> 0.14014888 | F254: =IFERROR((Data_Entry!I252/Data_Entry!$W252/F$2),"") -> 0.14555764 | G254: =IFERROR((Data_Entry!J252/Data_Entry!$W252/G$2),"") -> 0.14542818 | H254: =IFERROR((Data_Entry!K252/Data_Entry!$W252/H$2),"") -> 0.14526065 | I254: =IFERROR((Data_Entry!L252/Data_Entry!$W252/I$2),"") -> 0.14500173
A255: 45998 | B255: 45998 | C255: =IFERROR((Data_Entry!F253/Data_Entry!$V253/C$2),"") -> 1.0994039 | D255: =IFERROR((Data_Entry!G253/Data_Entry!$V253/D$2),"") -> 1.1719943 | E255: =IFERROR((Data_Entry!H253/Data_Entry!$V253/E$2),"") -> 1.0964721 | F255: =IFERROR((Data_Entry!I253/Data_Entry!$V253/F$2),"") -> 1.1342444 | G255: =IFERROR((Data_Entry!J253/Data_Entry!$V253/G$2),"") -> 1.1363234 | H255: =IFERROR((Data_Entry!K253/Data_Entry!$V253/H$2),"") -> 1.1348801 | I255: =IFERROR((Data_Entry!L253/Data_Entry!$V253/I$2),"") -> 1.132158
A256: 45999 | B256: 45999 | C256: =IFERROR((Data_Entry!F254/Data_Entry!$V254/C$2),"") -> 1.099333 | D256: =IFERROR((Data_Entry!G254/Data_Entry!$V254/D$2),"") -> 1.1716944 | E256: =IFERROR((Data_Entry!H254/Data_Entry!$V254/E$2),"") -> 1.0964089 | F256: =IFERROR((Data_Entry!I254/Data_Entry!$V254/F$2),"") -> 1.1336769 | G256: =IFERROR((Data_Entry!J254/Data_Entry!$V254/G$2),"") -> 1.1407625 | H256: =IFERROR((Data_Entry!K254/Data_Entry!$V254/H$2),"") -> 1.1354595 | I256: =IFERROR((Data_Entry!L254/Data_Entry!$V254/I$2),"") -> 1.1405462
A257: 46000 | B257: 46000 | C257: =IFERROR((Data_Entry!F255/Data_Entry!$V255/C$2),"") -> 1.1029455 | D257: =IFERROR((Data_Entry!G255/Data_Entry!$V255/D$2),"") -> 1.1696014 | E257: =IFERROR((Data_Entry!H255/Data_Entry!$V255/E$2),"") -> 1.0942764 | F257: =IFERROR((Data_Entry!I255/Data_Entry!$V255/F$2),"") -> 1.189523 | G257: =IFERROR((Data_Entry!J255/Data_Entry!$V255/G$2),"") -> 1.1639495 | H257: =IFERROR((Data_Entry!K255/Data_Entry!$V255/H$2),"") -> 1.1270277 | I257: =IFERROR((Data_Entry!L255/Data_Entry!$V255/I$2),"") -> 1.2322191
A258: 46001 | B258: 46001 | C258: =IFERROR((Data_Entry!F256/Data_Entry!$V256/C$2),"") -> 1.0432459 | D258: =IFERROR((Data_Entry!G256/Data_Entry!$V256/D$2),"") -> 1.208314 | E258: =IFERROR((Data_Entry!H256/Data_Entry!$V256/E$2),"") -> 1.0365182 | F258: =IFERROR((Data_Entry!I256/Data_Entry!$V256/F$2),"") -> 1.1488767 | G258: =IFERROR((Data_Entry!J256/Data_Entry!$V256/G$2),"") -> 1.1223992 | H258: =IFERROR((Data_Entry!K256/Data_Entry!$V256/H$2),"") -> 1.0716054 | I258: =IFERROR((Data_Entry!L256/Data_Entry!$V256/I$2),"") -> 1.1810936
A259: 46002 | B259: 46002 | C259: =IFERROR((Data_Entry!F257/Data_Entry!$V257/C$2),"") -> 1.1365629 | D259: =IFERROR((Data_Entry!G257/Data_Entry!$V257/D$2),"") -> 1.254485 | E259: =IFERROR((Data_Entry!H257/Data_Entry!$V257/E$2),"") -> 1.1298954 | F259: =IFERROR((Data_Entry!I257/Data_Entry!$V257/F$2),"") -> 1.2499794 | G259: =IFERROR((Data_Entry!J257/Data_Entry!$V257/G$2),"") -> 1.2342292 | H259: =IFERROR((Data_Entry!K257/Data_Entry!$V257/H$2),"") -> 1.18553 | I259: =IFERROR((Data_Entry!L257/Data_Entry!$V257/I$2),"") -> 1.2534524
A260: 46003 | B260: 46003 | C260: =IFERROR((Data_Entry!F258/Data_Entry!$V258/C$2),"") -> 1.1603043 | D260: =IFERROR((Data_Entry!G258/Data_Entry!$V258/D$2),"") -> 1.2400322 | E260: =IFERROR((Data_Entry!H258/Data_Entry!$V258/E$2),"") -> 1.1544331 | F260: =IFERROR((Data_Entry!I258/Data_Entry!$V258/F$2),"") -> 1.235295 | G260: =IFERROR((Data_Entry!J258/Data_Entry!$V258/G$2),"") -> 1.2193466 | H260: =IFERROR((Data_Entry!K258/Data_Entry!$V258/H$2),"") -> 1.2014209 | I260: =IFERROR((Data_Entry!L258/Data_Entry!$V258/I$2),"") -> 1.2346909
A261: 46004 | B261: 46004 | C261: =IFERROR((Data_Entry!F259/Data_Entry!$V259/C$2),"") -> 1.1607043 | D261: =IFERROR((Data_Entry!G259/Data_Entry!$V259/D$2),"") -> 1.2594747 | E261: =IFERROR((Data_Entry!H259/Data_Entry!$V259/E$2),"") -> 1.1579701 | F261: =IFERROR((Data_Entry!I259/Data_Entry!$V259/F$2),"") -> 1.2424132 | G261: =IFERROR((Data_Entry!J259/Data_Entry!$V259/G$2),"") -> 1.2258073 | H261: =IFERROR((Data_Entry!K259/Data_Entry!$V259/H$2),"") -> 1.2079893 | I261: =IFERROR((Data_Entry!L259/Data_Entry!$V259/I$2),"") -> 1.2407193
A262: 46005 | B262: 46005 | C262: =IFERROR((Data_Entry!F260/Data_Entry!$V260/C$2),"") -> 1.1619718 | D262: =IFERROR((Data_Entry!G260/Data_Entry!$V260/D$2),"") -> 1.243135 | E262: =IFERROR((Data_Entry!H260/Data_Entry!$V260/E$2),"") -> 1.1560526 | F262: =IFERROR((Data_Entry!I260/Data_Entry!$V260/F$2),"") -> 1.2395836 | G262: =IFERROR((Data_Entry!J260/Data_Entry!$V260/G$2),"") -> 1.2224522 | H262: =IFERROR((Data_Entry!K260/Data_Entry!$V260/H$2),"") -> 1.2048471 | I262: =IFERROR((Data_Entry!L260/Data_Entry!$V260/I$2),"") -> 1.236596
A263: 46006 | B263: 46006 | C263: =IFERROR((Data_Entry!F261/Data_Entry!$V261/C$2),"") -> 1.1539497 | D263: =IFERROR((Data_Entry!G261/Data_Entry!$V261/D$2),"") -> 1.2602088 | E263: =IFERROR((Data_Entry!H261/Data_Entry!$V261/E$2),"") -> 1.1497677 | F263: =IFERROR((Data_Entry!I261/Data_Entry!$V261/F$2),"") -> 1.2292691 | G263: =IFERROR((Data_Entry!J261/Data_Entry!$V261/G$2),"") -> 1.2140286 | H263: =IFERROR((Data_Entry!K261/Data_Entry!$V261/H$2),"") -> 1.1976157 | I263: =IFERROR((Data_Entry!L261/Data_Entry!$V261/I$2),"") -> 1.2332551
A264: 46007 | B264: 46007 | C264: =IFERROR((Data_Entry!F262/Data_Entry!$V262/C$2),"") -> 1.2217308 | D264: =IFERROR((Data_Entry!G262/Data_Entry!$V262/D$2),"") -> 1.3532593 | E264: =IFERROR((Data_Entry!H262/Data_Entry!$V262/E$2),"") -> 1.2163209 | F264: =IFERROR((Data_Entry!I262/Data_Entry!$V262/F$2),"") -> 1.304471 | G264: =IFERROR((Data_Entry!J262/Data_Entry!$V262/G$2),"") -> 1.2867138 | H264: =IFERROR((Data_Entry!K262/Data_Entry!$V262/H$2),"") -> 1.2670777 | I264: =IFERROR((Data_Entry!L262/Data_Entry!$V262/I$2),"") -> 1.3061882
A265: 46008 | B265: 46008 | C265: =IFERROR((Data_Entry!F263/Data_Entry!$V263/C$2),"") -> 1.1475542 | D265: =IFERROR((Data_Entry!G263/Data_Entry!$V263/D$2),"") -> 1.1699436 | E265: =IFERROR((Data_Entry!H263/Data_Entry!$V263/E$2),"") -> 1.1424691 | F265: =IFERROR((Data_Entry!I263/Data_Entry!$V263/F$2),"") -> 1.225936 | G265: =IFERROR((Data_Entry!J263/Data_Entry!$V263/G$2),"") -> 1.2133272 | H265: =IFERROR((Data_Entry!K263/Data_Entry!$V263/H$2),"") -> 1.1909983 | I265: =IFERROR((Data_Entry!L263/Data_Entry!$V263/I$2),"") -> 1.2263767
A266: 46009 | B266: 46009 | C266: =IFERROR((Data_Entry!F264/Data_Entry!$V264/C$2),"") -> 1.154623 | D266: =IFERROR((Data_Entry!G264/Data_Entry!$V264/D$2),"") -> 1.2326754 | E266: =IFERROR((Data_Entry!H264/Data_Entry!$V264/E$2),"") -> 1.1450082 | F266: =IFERROR((Data_Entry!I264/Data_Entry!$V264/F$2),"") -> 1.2280742 | G266: =IFERROR((Data_Entry!J264/Data_Entry!$V264/G$2),"") -> 1.2138131 | H266: =IFERROR((Data_Entry!K264/Data_Entry!$V264/H$2),"") -> 1.1962598 | I266: =IFERROR((Data_Entry!L264/Data_Entry!$V264/I$2),"") -> 1.2297776
... A369: 46112 | B369: 46112 | C369: =IFERROR((Data_Entry!F367/Data_Entry!$V367/C$2),"") -> 1.0434192 | D369: =IFERROR((Data_Entry!G367/Data_Entry!$V367/D$2),"") -> 1.0332721 | E369: =IFERROR((Data_Entry!H367/Data_Entry!$V367/E$2),"") -> 1.0363544 | F369: =IFERROR((Data_Entry!I367/Data_Entry!$V367/F$2),"") -> 1.0285904 | G369: =IFERROR((Data_Entry!J367/Data_Entry!$V367/G$2),"") -> 1.0318257 | H369: =IFERROR((Data_Entry!K367/Data_Entry!$V367/H$2),"") -> 1.0270667 | I369: =IFERROR((Data_Entry!L367/Data_Entry!$V367/I$2),"") -> 1.026524

Sheet DGR
A1: Daily_Generation_&_Performance_Report
A3: Inverter_No. | B3: ='E-Mail_Copy'!B4 -> 46178 | C3: =B3+1 -> 46179 | D3: =C3+1 -> 46180 | E3: =D3+1 -> 46181 | F3: =E3+1 -> 46182 | G3: =F3+1 -> 46183 | H3: =G3+1 -> 46184 | I3: =H3+1 -> 46185 | J3: =I3+1 -> 46186 | ... AF3: =AE3+1 -> 46208 | AG3: Total/Avg..
A4: Inv_1 | B4: =IFERROR(VLOOKUP(B$3,Data_Entry!$C:$AB,Data_Entry!$A2,0),"") -> 1580.3 | C4: =IFERROR(VLOOKUP(C$3,Data_Entry!$C:$AB,Data_Entry!$A2,0),"") -> 0 | D4: =IFERROR(VLOOKUP(D$3,Data_Entry!$C:$AB,Data_Entry!$A2,0),"") -> 0 | E4: =IFERROR(VLOOKUP(E$3,Data_Entry!$C:$AB,Data_Entry!$A2,0),"") -> 0 | F4: =IFERROR(VLOOKUP(F$3,Data_Entry!$C:$AB,Data_Entry!$A2,0),"") -> 0 | G4: =IFERROR(VLOOKUP(G$3,Data_Entry!$C:$AB,Data_Entry!$A2,0),"") -> 0 | H4: =IFERROR(VLOOKUP(H$3,Data_Entry!$C:$AB,Data_Entry!$A2,0),"") -> 0 | I4: =IFERROR(VLOOKUP(I$3,Data_Entry!$C:$AB,Data_Entry!$A2,0),"") -> 0 | ... AF4: =IFERROR(VLOOKUP(AF$3,Data_Entry!$C:$AB,Data_Entry!$A2,0),"") -> 0 | AG4: =IFERROR(SUM(B4:AF4),"") -> 1580.3
A5: Inv_2 | B5: =IFERROR(VLOOKUP(B$3,Data_Entry!$C:$AB,Data_Entry!$A3,0),"") -> 1583.54 | C5: =IFERROR(VLOOKUP(C$3,Data_Entry!$C:$AB,Data_Entry!$A3,0),"") -> 0 | D5: =IFERROR(VLOOKUP(D$3,Data_Entry!$C:$AB,Data_Entry!$A3,0),"") -> 0 | E5: =IFERROR(VLOOKUP(E$3,Data_Entry!$C:$AB,Data_Entry!$A3,0),"") -> 0 | F5: =IFERROR(VLOOKUP(F$3,Data_Entry!$C:$AB,Data_Entry!$A3,0),"") -> 0 | G5: =IFERROR(VLOOKUP(G$3,Data_Entry!$C:$AB,Data_Entry!$A3,0),"") -> 0 | H5: =IFERROR(VLOOKUP(H$3,Data_Entry!$C:$AB,Data_Entry!$A3,0),"") -> 0 | I5: =IFERROR(VLOOKUP(I$3,Data_Entry!$C:$AB,Data_Entry!$A3,0),"") -> 0 | ... AF5: =IFERROR(VLOOKUP(AF$3,Data_Entry!$C:$AB,Data_Entry!$A3,0),"") -> 0 | AG5: =IFERROR(SUM(B5:AF5),"") -> 1583.54
A6: Inv_3 | B6: =IFERROR(VLOOKUP(B$3,Data_Entry!$C:$AB,Data_Entry!$A4,0),"") -> 1563.5 | C6: =IFERROR(VLOOKUP(C$3,Data_Entry!$C:$AB,Data_Entry!$A4,0),"") -> 0 | D6: =IFERROR(VLOOKUP(D$3,Data_Entry!$C:$AB,Data_Entry!$A4,0),"") -> 0 | E6: =IFERROR(VLOOKUP(E$3,Data_Entry!$C:$AB,Data_Entry!$A4,0),"") -> 0 | F6: =IFERROR(VLOOKUP(F$3,Data_Entry!$C:$AB,Data_Entry!$A4,0),"") -> 0 | G6: =IFERROR(VLOOKUP(G$3,Data_Entry!$C:$AB,Data_Entry!$A4,0),"") -> 0 | H6: =IFERROR(VLOOKUP(H$3,Data_Entry!$C:$AB,Data_Entry!$A4,0),"") -> 0 | I6: =IFERROR(VLOOKUP(I$3,Data_Entry!$C:$AB,Data_Entry!$A4,0),"") -> 0 | ... AF6: =IFERROR(VLOOKUP(AF$3,Data_Entry!$C:$AB,Data_Entry!$A4,0),"") -> 0 | AG6: =IFERROR(SUM(B6:AF6),"") -> 1563.5
A7: Inv_4 | B7: =IFERROR(VLOOKUP(B$3,Data_Entry!$C:$AB,Data_Entry!$A5,0),"") -> 1643.94 | C7: =IFERROR(VLOOKUP(C$3,Data_Entry!$C:$AB,Data_Entry!$A5,0),"") -> 0 | D7: =IFERROR(VLOOKUP(D$3,Data_Entry!$C:$AB,Data_Entry!$A5,0),"") -> 0 | E7: =IFERROR(VLOOKUP(E$3,Data_Entry!$C:$AB,Data_Entry!$A5,0),"") -> 0 | F7: =IFERROR(VLOOKUP(F$3,Data_Entry!$C:$AB,Data_Entry!$A5,0),"") -> 0 | G7: =IFERROR(VLOOKUP(G$3,Data_Entry!$C:$AB,Data_Entry!$A5,0),"") -> 0 | H7: =IFERROR(VLOOKUP(H$3,Data_Entry!$C:$AB,Data_Entry!$A5,0),"") -> 0 | I7: =IFERROR(VLOOKUP(I$3,Data_Entry!$C:$AB,Data_Entry!$A5,0),"") -> 0 | ... AF7: =IFERROR(VLOOKUP(AF$3,Data_Entry!$C:$AB,Data_Entry!$A5,0),"") -> 0 | AG7: =IFERROR(SUM(B7:AF7),"") -> 1643.94
A8: Inv_5 | B8: =IFERROR(VLOOKUP(B$3,Data_Entry!$C:$AB,Data_Entry!$A6,0),"") -> 1663.13 | C8: =IFERROR(VLOOKUP(C$3,Data_Entry!$C:$AB,Data_Entry!$A6,0),"") -> 0 | D8: =IFERROR(VLOOKUP(D$3,Data_Entry!$C:$AB,Data_Entry!$A6,0),"") -> 0 | E8: =IFERROR(VLOOKUP(E$3,Data_Entry!$C:$AB,Data_Entry!$A6,0),"") -> 0 | F8: =IFERROR(VLOOKUP(F$3,Data_Entry!$C:$AB,Data_Entry!$A6,0),"") -> 0 | G8: =IFERROR(VLOOKUP(G$3,Data_Entry!$C:$AB,Data_Entry!$A6,0),"") -> 0 | H8: =IFERROR(VLOOKUP(H$3,Data_Entry!$C:$AB,Data_Entry!$A6,0),"") -> 0 | I8: =IFERROR(VLOOKUP(I$3,Data_Entry!$C:$AB,Data_Entry!$A6,0),"") -> 0 | ... AF8: =IFERROR(VLOOKUP(AF$3,Data_Entry!$C:$AB,Data_Entry!$A6,0),"") -> 0 | AG8: =IFERROR(SUM(B8:AF8),"") -> 1663.13
A9: Inv_6 | B9: =IFERROR(VLOOKUP(B$3,Data_Entry!$C:$AB,Data_Entry!$A7,0),"") -> 1653.37 | C9: =IFERROR(VLOOKUP(C$3,Data_Entry!$C:$AB,Data_Entry!$A7,0),"") -> 0 | D9: =IFERROR(VLOOKUP(D$3,Data_Entry!$C:$AB,Data_Entry!$A7,0),"") -> 0 | E9: =IFERROR(VLOOKUP(E$3,Data_Entry!$C:$AB,Data_Entry!$A7,0),"") -> 0 | F9: =IFERROR(VLOOKUP(F$3,Data_Entry!$C:$AB,Data_Entry!$A7,0),"") -> 0 | G9: =IFERROR(VLOOKUP(G$3,Data_Entry!$C:$AB,Data_Entry!$A7,0),"") -> 0 | H9: =IFERROR(VLOOKUP(H$3,Data_Entry!$C:$AB,Data_Entry!$A7,0),"") -> 0 | I9: =IFERROR(VLOOKUP(I$3,Data_Entry!$C:$AB,Data_Entry!$A7,0),"") -> 0 | ... AF9: =IFERROR(VLOOKUP(AF$3,Data_Entry!$C:$AB,Data_Entry!$A7,0),"") -> 0 | AG9: =IFERROR(SUM(B9:AF9),"") -> 1653.37
A10: Inv_7 | B10: =IFERROR(VLOOKUP(B$3,Data_Entry!$C:$AB,Data_Entry!$A8,0),"") -> 1662.44 | C10: =IFERROR(VLOOKUP(C$3,Data_Entry!$C:$AB,Data_Entry!$A8,0),"") -> 0 | D10: =IFERROR(VLOOKUP(D$3,Data_Entry!$C:$AB,Data_Entry!$A8,0),"") -> 0 | E10: =IFERROR(VLOOKUP(E$3,Data_Entry!$C:$AB,Data_Entry!$A8,0),"") -> 0 | F10: =IFERROR(VLOOKUP(F$3,Data_Entry!$C:$AB,Data_Entry!$A8,0),"") -> 0 | G10: =IFERROR(VLOOKUP(G$3,Data_Entry!$C:$AB,Data_Entry!$A8,0),"") -> 0 | H10: =IFERROR(VLOOKUP(H$3,Data_Entry!$C:$AB,Data_Entry!$A8,0),"") -> 0 | I10: =IFERROR(VLOOKUP(I$3,Data_Entry!$C:$AB,Data_Entry!$A8,0),"") -> 0 | ... AF10: =IFERROR(VLOOKUP(AF$3,Data_Entry!$C:$AB,Data_Entry!$A8,0),"") -> 0 | AG10: =IFERROR(SUM(B10:AF10),"") -> 1662.44
A11: Total_Inverter_(kWh) | B11: =SUM(B4:B10) -> 11350.22 | C11: =SUM(C4:C10) -> 0 | D11: =SUM(D4:D10) -> 0 | E11: =SUM(E4:E10) -> 0 | F11: =SUM(F4:F10) -> 0 | G11: =SUM(G4:G10) -> 0 | H11: =SUM(H4:H10) -> 0 | I11: =SUM(I4:I10) -> 0 | ... AG11: =SUM(AG4:AG10) -> 11350.22
A12: Total_ABT_Meter_Export_(kWh) | B12: =IFERROR(VLOOKUP(B$3,Data_Entry!$C:$AB,14,0)," ") -> 11310 | C12: =IFERROR(VLOOKUP(C$3,Data_Entry!$C:$AB,14,0)," ") -> 0 | D12: =IFERROR(VLOOKUP(D$3,Data_Entry!$C:$AB,14,0)," ") -> 0 | E12: =IFERROR(VLOOKUP(E$3,Data_Entry!$C:$AB,14,0)," ") -> 0 | F12: =IFERROR(VLOOKUP(F$3,Data_Entry!$C:$AB,14,0)," ") -> 0 | G12: =IFERROR(VLOOKUP(G$3,Data_Entry!$C:$AB,14,0)," ") -> 0 | H12: =IFERROR(VLOOKUP(H$3,Data_Entry!$C:$AB,14,0)," ") -> 0 | I12: =IFERROR(VLOOKUP(I$3,Data_Entry!$C:$AB,14,0)," ") -> 0 | ... AG12: =IFERROR(VLOOKUP(AG$3,Data_Entry!$C:$AB,14,0)," ")
A13: Total_ABT_Meter_Import_(kWh) | B13: =IFERROR(VLOOKUP(B$3,Data_Entry!$C:$AB,17,0)," ") -> 30 | C13: =IFERROR(VLOOKUP(C$3,Data_Entry!$C:$AB,17,0)," ") -> 0 | D13: =IFERROR(VLOOKUP(D$3,Data_Entry!$C:$AB,17,0)," ") -> 0 | E13: =IFERROR(VLOOKUP(E$3,Data_Entry!$C:$AB,17,0)," ") -> 0 | F13: =IFERROR(VLOOKUP(F$3,Data_Entry!$C:$AB,17,0)," ") -> 0 | G13: =IFERROR(VLOOKUP(G$3,Data_Entry!$C:$AB,17,0)," ") -> 0 | H13: =IFERROR(VLOOKUP(H$3,Data_Entry!$C:$AB,17,0)," ") -> 0 | I13: =IFERROR(VLOOKUP(I$3,Data_Entry!$C:$AB,17,0)," ") -> 0 | ... AG13: =IFERROR(VLOOKUP(AG$3,Data_Entry!$C:$AB,17,0)," ")
A14: Total_ABT_Meter_Net_(kWh) | B14: =IFERROR(VLOOKUP(B$3,Data_Entry!$C:$AB,18,0)," ") -> 11280 | C14: =IFERROR(VLOOKUP(C$3,Data_Entry!$C:$AB,18,0)," ") -> 0 | D14: =IFERROR(VLOOKUP(D$3,Data_Entry!$C:$AB,18,0)," ") -> 0 | E14: =IFERROR(VLOOKUP(E$3,Data_Entry!$C:$AB,18,0)," ") -> 0 | F14: =IFERROR(VLOOKUP(F$3,Data_Entry!$C:$AB,18,0)," ") -> 0 | G14: =IFERROR(VLOOKUP(G$3,Data_Entry!$C:$AB,18,0)," ") -> 0 | H14: =IFERROR(VLOOKUP(H$3,Data_Entry!$C:$AB,18,0)," ") -> 0 | I14: =IFERROR(VLOOKUP(I$3,Data_Entry!$C:$AB,18,0)," ") -> 0 | ... AG14: =IFERROR(VLOOKUP(AG$3,Data_Entry!$C:$AB,18,0)," ")
A15: GTI | B15: =IFERROR(VLOOKUP(B$3,Data_Entry!$C:$AB,20,0)," ") -> 4.71 | C15: =IFERROR(VLOOKUP(C$3,Data_Entry!$C:$AB,20,0)," ") -> 0 | D15: =IFERROR(VLOOKUP(D$3,Data_Entry!$C:$AB,20,0)," ") -> 0 | E15: =IFERROR(VLOOKUP(E$3,Data_Entry!$C:$AB,20,0)," ") -> 0 | F15: =IFERROR(VLOOKUP(F$3,Data_Entry!$C:$AB,20,0)," ") -> 0 | G15: =IFERROR(VLOOKUP(G$3,Data_Entry!$C:$AB,20,0)," ") -> 0 | H15: =IFERROR(VLOOKUP(H$3,Data_Entry!$C:$AB,20,0)," ") -> 0 | I15: =IFERROR(VLOOKUP(I$3,Data_Entry!$C:$AB,20,0)," ") -> 0 | ... AF15: =IFERROR(VLOOKUP(AF$3,Data_Entry!$C:$AB,20,0)," ") -> 0
A16: GHI | B16: =IFERROR(VLOOKUP(B$3,Data_Entry!$C:$AB,19,0)," ") -> 0 | C16: =IFERROR(VLOOKUP(C$3,Data_Entry!$C:$AB,19,0)," ") -> 0 | D16: =IFERROR(VLOOKUP(D$3,Data_Entry!$C:$AB,19,0)," ") -> 0 | E16: =IFERROR(VLOOKUP(E$3,Data_Entry!$C:$AB,19,0)," ") -> 0 | F16: =IFERROR(VLOOKUP(F$3,Data_Entry!$C:$AB,19,0)," ") -> 0 | G16: =IFERROR(VLOOKUP(G$3,Data_Entry!$C:$AB,19,0)," ") -> 0 | H16: =IFERROR(VLOOKUP(H$3,Data_Entry!$C:$AB,19,0)," ") -> 0 | I16: =IFERROR(VLOOKUP(I$3,Data_Entry!$C:$AB,19,0)," ") -> 0 | ... AF16: =IFERROR(VLOOKUP(AF$3,Data_Entry!$C:$AB,19,0)," ") -> 0
A17: Module_Temp. | B17: =IFERROR(VLOOKUP(B$3,Data_Entry!$C:$AB,23,0)," ") -> 0 | C17: =IFERROR(VLOOKUP(C$3,Data_Entry!$C:$AB,23,0)," ") -> 0 | D17: =IFERROR(VLOOKUP(D$3,Data_Entry!$C:$AB,23,0)," ") -> 0 | E17: =IFERROR(VLOOKUP(E$3,Data_Entry!$C:$AB,23,0)," ") -> 0 | F17: =IFERROR(VLOOKUP(F$3,Data_Entry!$C:$AB,23,0)," ") -> 0 | G17: =IFERROR(VLOOKUP(G$3,Data_Entry!$C:$AB,23,0)," ") -> 0 | H17: =IFERROR(VLOOKUP(H$3,Data_Entry!$C:$AB,23,0)," ") -> 0 | I17: =IFERROR(VLOOKUP(I$3,Data_Entry!$C:$AB,23,0)," ") -> 0 | ... AF17: =IFERROR(VLOOKUP(AF$3,Data_Entry!$C:$AB,23,0)," ") -> 0
A18: Ambt._Temp. | B18: =IFERROR(VLOOKUP(B$3,Data_Entry!$C:$AB,21,0)," ") -> 33.03 | C18: =IFERROR(VLOOKUP(C$3,Data_Entry!$C:$AB,21,0)," ") -> 0 | D18: =IFERROR(VLOOKUP(D$3,Data_Entry!$C:$AB,21,0)," ") -> 0 | E18: =IFERROR(VLOOKUP(E$3,Data_Entry!$C:$AB,21,0)," ") -> 0 | F18: =IFERROR(VLOOKUP(F$3,Data_Entry!$C:$AB,21,0)," ") -> 0 | G18: =IFERROR(VLOOKUP(G$3,Data_Entry!$C:$AB,21,0)," ") -> 0 | H18: =IFERROR(VLOOKUP(H$3,Data_Entry!$C:$AB,21,0)," ") -> 0 | I18: =IFERROR(VLOOKUP(I$3,Data_Entry!$C:$AB,21,0)," ") -> 0 | ... AF18: =IFERROR(VLOOKUP(AF$3,Data_Entry!$C:$AB,21,0)," ") -> 0
A19: Performance_Ratio_(%) | B19: =IFERROR(B12/B15/(Basic_Data!$G$10),"") -> 0.9959329 | C19: =IFERROR(C12/C15/(Basic_Data!$G$10),"") | D19: =IFERROR(D12/D15/(Basic_Data!$G$10),"") | E19: =IFERROR(E12/E15/(Basic_Data!$G$10),"") | F19: =IFERROR(F12/F15/(Basic_Data!$G$10),"") | G19: =IFERROR(G12/G15/(Basic_Data!$G$10),"") | H19: =IFERROR(H12/H15/(Basic_Data!$G$10),"") | I19: =IFERROR(I12/I15/(Basic_Data!$G$10),"") | ... AG19: =IFERROR(AG12/AG15/(Basic_Data!$G$10),"")
A20: Capacity_Utilization_Factor_(%) | B20: =IFERROR(B12/(Basic_Data!$F$10*24),"") -> 0.24480519 | C20: =IFERROR(C12/(Basic_Data!$F$10*24),"") -> 0 | D20: =IFERROR(D12/(Basic_Data!$F$10*24),"") -> 0 | E20: =IFERROR(E12/(Basic_Data!$F$10*24),"") -> 0 | F20: =IFERROR(F12/(Basic_Data!$F$10*24),"") -> 0 | G20: =IFERROR(G12/(Basic_Data!$F$10*24),"") -> 0 | H20: =IFERROR(H12/(Basic_Data!$F$10*24),"") -> 0 | I20: =IFERROR(I12/(Basic_Data!$F$10*24),"") -> 0 | ... AG20: =IFERROR(AG12/(Basic_Data!$F$10*24),"")
A21: Aux_Consumption_Line_Loss_(%) | B21: =IFERROR((B11-B12)/B11,"") -> 0.0035435436 | C21: =IFERROR((C11-C12)/C11,"") | D21: =IFERROR((D11-D12)/D11,"") | E21: =IFERROR((E11-E12)/E11,"") | F21: =IFERROR((F11-F12)/F11,"") | G21: =IFERROR((G11-G12)/G11,"") | H21: =IFERROR((H11-H12)/H11,"") | I21: =IFERROR((I11-I12)/I11,"") | ... AG21: =IFERROR((AG11-AG12)/AG11,"")

Sheet Invt_Analysis_Gen_Per_KW &_PR
A1: Daily_Generation_Per_KW_Performance_Analysis
B2: Inverter_No. | C2: =DGR!B3 -> 46178 | D2: =DGR!C3 -> 46179 | E2: =DGR!D3 -> 46180 | F2: =DGR!E3 -> 46181 | G2: =DGR!F3 -> 46182 | H2: =DGR!G3 -> 46183 | I2: =DGR!H3 -> 46184 | J2: =DGR!I3 -> 46185 | ... AH2: =DGR!AG3 -> Total/Avg..
B3: Inv_1 | C3: =IFERROR(VLOOKUP(C$2,Data_Entry!$C:$L,Data_Entry!$A2,0)/VLOOKUP($B3,Basic_Data!$E$2:$G$10,3,0),"") -> 4.7071965 | D3: =IFERROR(VLOOKUP(D$2,Data_Entry!$C:$L,Data_Entry!$A2,0)/VLOOKUP($B3,Basic_Data!$E$2:$G$10,3,0),"") -> 0 | E3: =IFERROR(VLOOKUP(E$2,Data_Entry!$C:$L,Data_Entry!$A2,0)/VLOOKUP($B3,Basic_Data!$E$2:$G$10,3,0),"") -> 0 | F3: =IFERROR(VLOOKUP(F$2,Data_Entry!$C:$L,Data_Entry!$A2,0)/VLOOKUP($B3,Basic_Data!$E$2:$G$10,3,0),"") -> 0 | G3: =IFERROR(VLOOKUP(G$2,Data_Entry!$C:$L,Data_Entry!$A2,0)/VLOOKUP($B3,Basic_Data!$E$2:$G$10,3,0),"") -> 0 | H3: =IFERROR(VLOOKUP(H$2,Data_Entry!$C:$L,Data_Entry!$A2,0)/VLOOKUP($B3,Basic_Data!$E$2:$G$10,3,0),"") -> 0 | I3: =IFERROR(VLOOKUP(I$2,Data_Entry!$C:$L,Data_Entry!$A2,0)/VLOOKUP($B3,Basic_Data!$E$2:$G$10,3,0),"") -> 0 | J3: =IFERROR(VLOOKUP(J$2,Data_Entry!$C:$L,Data_Entry!$A2,0)/VLOOKUP($B3,Basic_Data!$E$2:$G$10,3,0),"") -> 0 | ... AG3: =IFERROR(VLOOKUP(AG$2,Data_Entry!$C:$L,Data_Entry!$A2,0)/VLOOKUP($B3,Basic_Data!$E$2:$G$10,3,0),"") -> 0
B4: Inv_2 | C4: =IFERROR(VLOOKUP(C$2,Data_Entry!$C:$L,Data_Entry!$A3,0)/VLOOKUP($B4,Basic_Data!$E$2:$G$10,3,0),"") -> 4.7168474 | D4: =IFERROR(VLOOKUP(D$2,Data_Entry!$C:$L,Data_Entry!$A3,0)/VLOOKUP($B4,Basic_Data!$E$2:$G$10,3,0),"") -> 0 | E4: =IFERROR(VLOOKUP(E$2,Data_Entry!$C:$L,Data_Entry!$A3,0)/VLOOKUP($B4,Basic_Data!$E$2:$G$10,3,0),"") -> 0 | F4: =IFERROR(VLOOKUP(F$2,Data_Entry!$C:$L,Data_Entry!$A3,0)/VLOOKUP($B4,Basic_Data!$E$2:$G$10,3,0),"") -> 0 | G4: =IFERROR(VLOOKUP(G$2,Data_Entry!$C:$L,Data_Entry!$A3,0)/VLOOKUP($B4,Basic_Data!$E$2:$G$10,3,0),"") -> 0 | H4: =IFERROR(VLOOKUP(H$2,Data_Entry!$C:$L,Data_Entry!$A3,0)/VLOOKUP($B4,Basic_Data!$E$2:$G$10,3,0),"") -> 0 | I4: =IFERROR(VLOOKUP(I$2,Data_Entry!$C:$L,Data_Entry!$A3,0)/VLOOKUP($B4,Basic_Data!$E$2:$G$10,3,0),"") -> 0 | J4: =IFERROR(VLOOKUP(J$2,Data_Entry!$C:$L,Data_Entry!$A3,0)/VLOOKUP($B4,Basic_Data!$E$2:$G$10,3,0),"") -> 0 | ... AG4: =IFERROR(VLOOKUP(AG$2,Data_Entry!$C:$L,Data_Entry!$A3,0)/VLOOKUP($B4,Basic_Data!$E$2:$G$10,3,0),"") -> 0
B5: Inv_3 | C5: =IFERROR(VLOOKUP(C$2,Data_Entry!$C:$L,Data_Entry!$A4,0)/VLOOKUP($B5,Basic_Data!$E$2:$G$10,3,0),"") -> 4.6571548 | D5: =IFERROR(VLOOKUP(D$2,Data_Entry!$C:$L,Data_Entry!$A4,0)/VLOOKUP($B5,Basic_Data!$E$2:$G$10,3,0),"") -> 0 | E5: =IFERROR(VLOOKUP(E$2,Data_Entry!$C:$L,Data_Entry!$A4,0)/VLOOKUP($B5,Basic_Data!$E$2:$G$10,3,0),"") -> 0 | F5: =IFERROR(VLOOKUP(F$2,Data_Entry!$C:$L,Data_Entry!$A4,0)/VLOOKUP($B5,Basic_Data!$E$2:$G$10,3,0),"") -> 0 | G5: =IFERROR(VLOOKUP(G$2,Data_Entry!$C:$L,Data_Entry!$A4,0)/VLOOKUP($B5,Basic_Data!$E$2:$G$10,3,0),"") -> 0 | H5: =IFERROR(VLOOKUP(H$2,Data_Entry!$C:$L,Data_Entry!$A4,0)/VLOOKUP($B5,Basic_Data!$E$2:$G$10,3,0),"") -> 0 | I5: =IFERROR(VLOOKUP(I$2,Data_Entry!$C:$L,Data_Entry!$A4,0)/VLOOKUP($B5,Basic_Data!$E$2:$G$10,3,0),"") -> 0 | J5: =IFERROR(VLOOKUP(J$2,Data_Entry!$C:$L,Data_Entry!$A4,0)/VLOOKUP($B5,Basic_Data!$E$2:$G$10,3,0),"") -> 0 | ... AG5: =IFERROR(VLOOKUP(AG$2,Data_Entry!$C:$L,Data_Entry!$A4,0)/VLOOKUP($B5,Basic_Data!$E$2:$G$10,3,0),"") -> 0
B6: Inv_4 | C6: =IFERROR(VLOOKUP(C$2,Data_Entry!$C:$L,Data_Entry!$A5,0)/VLOOKUP($B6,Basic_Data!$E$2:$G$10,3,0),"") -> 4.6838566 | D6: =IFERROR(VLOOKUP(D$2,Data_Entry!$C:$L,Data_Entry!$A5,0)/VLOOKUP($B6,Basic_Data!$E$2:$G$10,3,0),"") -> 0 | E6: =IFERROR(VLOOKUP(E$2,Data_Entry!$C:$L,Data_Entry!$A5,0)/VLOOKUP($B6,Basic_Data!$E$2:$G$10,3,0),"") -> 0 | F6: =IFERROR(VLOOKUP(F$2,Data_Entry!$C:$L,Data_Entry!$A5,0)/VLOOKUP($B6,Basic_Data!$E$2:$G$10,3,0),"") -> 0 | G6: =IFERROR(VLOOKUP(G$2,Data_Entry!$C:$L,Data_Entry!$A5,0)/VLOOKUP($B6,Basic_Data!$E$2:$G$10,3,0),"") -> 0 | H6: =IFERROR(VLOOKUP(H$2,Data_Entry!$C:$L,Data_Entry!$A5,0)/VLOOKUP($B6,Basic_Data!$E$2:$G$10,3,0),"") -> 0 | I6: =IFERROR(VLOOKUP(I$2,Data_Entry!$C:$L,Data_Entry!$A5,0)/VLOOKUP($B6,Basic_Data!$E$2:$G$10,3,0),"") -> 0 | J6: =IFERROR(VLOOKUP(J$2,Data_Entry!$C:$L,Data_Entry!$A5,0)/VLOOKUP($B6,Basic_Data!$E$2:$G$10,3,0),"") -> 0 | ... AG6: =IFERROR(VLOOKUP(AG$2,Data_Entry!$C:$L,Data_Entry!$A5,0)/VLOOKUP($B6,Basic_Data!$E$2:$G$10,3,0),"") -> 0
B7: Inv_5 | C7: =IFERROR(VLOOKUP(C$2,Data_Entry!$C:$L,Data_Entry!$A6,0)/VLOOKUP($B7,Basic_Data!$E$2:$G$10,3,0),"") -> 4.7385321 | D7: =IFERROR(VLOOKUP(D$2,Data_Entry!$C:$L,Data_Entry!$A6,0)/VLOOKUP($B7,Basic_Data!$E$2:$G$10,3,0),"") -> 0 | E7: =IFERROR(VLOOKUP(E$2,Data_Entry!$C:$L,Data_Entry!$A6,0)/VLOOKUP($B7,Basic_Data!$E$2:$G$10,3,0),"") -> 0 | F7: =IFERROR(VLOOKUP(F$2,Data_Entry!$C:$L,Data_Entry!$A6,0)/VLOOKUP($B7,Basic_Data!$E$2:$G$10,3,0),"") -> 0 | G7: =IFERROR(VLOOKUP(G$2,Data_Entry!$C:$L,Data_Entry!$A6,0)/VLOOKUP($B7,Basic_Data!$E$2:$G$10,3,0),"") -> 0 | H7: =IFERROR(VLOOKUP(H$2,Data_Entry!$C:$L,Data_Entry!$A6,0)/VLOOKUP($B7,Basic_Data!$E$2:$G$10,3,0),"") -> 0 | I7: =IFERROR(VLOOKUP(I$2,Data_Entry!$C:$L,Data_Entry!$A6,0)/VLOOKUP($B7,Basic_Data!$E$2:$G$10,3,0),"") -> 0 | J7: =IFERROR(VLOOKUP(J$2,Data_Entry!$C:$L,Data_Entry!$A6,0)/VLOOKUP($B7,Basic_Data!$E$2:$G$10,3,0),"") -> 0 | ... AG7: =IFERROR(VLOOKUP(AG$2,Data_Entry!$C:$L,Data_Entry!$A6,0)/VLOOKUP($B7,Basic_Data!$E$2:$G$10,3,0),"") -> 0
B8: Inv_6 | C8: =IFERROR(VLOOKUP(C$2,Data_Entry!$C:$L,Data_Entry!$A7,0)/VLOOKUP($B8,Basic_Data!$E$2:$G$10,3,0),"") -> 4.7107243 | D8: =IFERROR(VLOOKUP(D$2,Data_Entry!$C:$L,Data_Entry!$A7,0)/VLOOKUP($B8,Basic_Data!$E$2:$G$10,3,0),"") -> 0 | E8: =IFERROR(VLOOKUP(E$2,Data_Entry!$C:$L,Data_Entry!$A7,0)/VLOOKUP($B8,Basic_Data!$E$2:$G$10,3,0),"") -> 0 | F8: =IFERROR(VLOOKUP(F$2,Data_Entry!$C:$L,Data_Entry!$A7,0)/VLOOKUP($B8,Basic_Data!$E$2:$G$10,3,0),"") -> 0 | G8: =IFERROR(VLOOKUP(G$2,Data_Entry!$C:$L,Data_Entry!$A7,0)/VLOOKUP($B8,Basic_Data!$E$2:$G$10,3,0),"") -> 0 | H8: =IFERROR(VLOOKUP(H$2,Data_Entry!$C:$L,Data_Entry!$A7,0)/VLOOKUP($B8,Basic_Data!$E$2:$G$10,3,0),"") -> 0 | I8: =IFERROR(VLOOKUP(I$2,Data_Entry!$C:$L,Data_Entry!$A7,0)/VLOOKUP($B8,Basic_Data!$E$2:$G$10,3,0),"") -> 0 | J8: =IFERROR(VLOOKUP(J$2,Data_Entry!$C:$L,Data_Entry!$A7,0)/VLOOKUP($B8,Basic_Data!$E$2:$G$10,3,0),"") -> 0 | ... AG8: =IFERROR(VLOOKUP(AG$2,Data_Entry!$C:$L,Data_Entry!$A7,0)/VLOOKUP($B8,Basic_Data!$E$2:$G$10,3,0),"") -> 0
B9: Inv_7 | C9: =IFERROR(VLOOKUP(C$2,Data_Entry!$C:$L,Data_Entry!$A8,0)/VLOOKUP($B9,Basic_Data!$E$2:$G$10,3,0),"") -> 4.7365662 | D9: =IFERROR(VLOOKUP(D$2,Data_Entry!$C:$L,Data_Entry!$A8,0)/VLOOKUP($B9,Basic_Data!$E$2:$G$10,3,0),"") -> 0 | E9: =IFERROR(VLOOKUP(E$2,Data_Entry!$C:$L,Data_Entry!$A8,0)/VLOOKUP($B9,Basic_Data!$E$2:$G$10,3,0),"") -> 0 | F9: =IFERROR(VLOOKUP(F$2,Data_Entry!$C:$L,Data_Entry!$A8,0)/VLOOKUP($B9,Basic_Data!$E$2:$G$10,3,0),"") -> 0 | G9: =IFERROR(VLOOKUP(G$2,Data_Entry!$C:$L,Data_Entry!$A8,0)/VLOOKUP($B9,Basic_Data!$E$2:$G$10,3,0),"") -> 0 | H9: =IFERROR(VLOOKUP(H$2,Data_Entry!$C:$L,Data_Entry!$A8,0)/VLOOKUP($B9,Basic_Data!$E$2:$G$10,3,0),"") -> 0 | I9: =IFERROR(VLOOKUP(I$2,Data_Entry!$C:$L,Data_Entry!$A8,0)/VLOOKUP($B9,Basic_Data!$E$2:$G$10,3,0),"") -> 0 | J9: =IFERROR(VLOOKUP(J$2,Data_Entry!$C:$L,Data_Entry!$A8,0)/VLOOKUP($B9,Basic_Data!$E$2:$G$10,3,0),"") -> 0 | ... AG9: =IFERROR(VLOOKUP(AG$2,Data_Entry!$C:$L,Data_Entry!$A8,0)/VLOOKUP($B9,Basic_Data!$E$2:$G$10,3,0),"") -> 0
B10: Avg_per_Kw | C10: =AVERAGE(C3:C9) -> 4.7072683 | D10: =AVERAGE(D3:D9) -> 0 | E10: =AVERAGE(E3:E9) -> 0 | F10: =AVERAGE(F3:F9) -> 0 | G10: =AVERAGE(G3:G9) -> 0 | H10: =AVERAGE(H3:H9) -> 0 | I10: =AVERAGE(I3:I9) -> 0 | J10: =AVERAGE(J3:J9) -> 0 | ... AH10: =AVERAGE(AH3:AH9) -> #DIV/0!
B13: Inverter_No. | C13: =DGR!B3 -> 46178 | D13: =DGR!C3 -> 46179 | E13: =DGR!D3 -> 46180 | F13: =DGR!E3 -> 46181 | G13: =DGR!F3 -> 46182 | H13: =DGR!G3 -> 46183 | I13: =DGR!H3 -> 46184 | J13: =DGR!I3 -> 46185 | ... AH13: =DGR!AG3 -> Total/Avg..
B14: Inv_1 | C14: =IFERROR(VLOOKUP(C$13,Data_Entry!$C:$M,Data_Entry!$A2,0)/VLOOKUP($B14,Basic_Data!$E$2:$G$9,3,0)/VLOOKUP(C$13,Data_Entry!$C:$V,20,0),"") -> 0.99940477 | D14: =IFERROR(VLOOKUP(D$13,Data_Entry!$C:$M,Data_Entry!$A2,0)/VLOOKUP($B14,Basic_Data!$E$2:$G$9,3,0)/VLOOKUP(D$13,Data_Entry!$C:$V,20,0),"") | E14: =IFERROR(VLOOKUP(E$13,Data_Entry!$C:$M,Data_Entry!$A2,0)/VLOOKUP($B14,Basic_Data!$E$2:$G$9,3,0)/VLOOKUP(E$13,Data_Entry!$C:$V,20,0),"") | F14: =IFERROR(VLOOKUP(F$13,Data_Entry!$C:$M,Data_Entry!$A2,0)/VLOOKUP($B14,Basic_Data!$E$2:$G$9,3,0)/VLOOKUP(F$13,Data_Entry!$C:$V,20,0),"") | G14: =IFERROR(VLOOKUP(G$13,Data_Entry!$C:$M,Data_Entry!$A2,0)/VLOOKUP($B14,Basic_Data!$E$2:$G$9,3,0)/VLOOKUP(G$13,Data_Entry!$C:$V,20,0),"") | H14: =IFERROR(VLOOKUP(H$13,Data_Entry!$C:$M,Data_Entry!$A2,0)/VLOOKUP($B14,Basic_Data!$E$2:$G$9,3,0)/VLOOKUP(H$13,Data_Entry!$C:$V,20,0),"") | I14: =IFERROR(VLOOKUP(I$13,Data_Entry!$C:$M,Data_Entry!$A2,0)/VLOOKUP($B14,Basic_Data!$E$2:$G$9,3,0)/VLOOKUP(I$13,Data_Entry!$C:$V,20,0),"") | J14: =IFERROR(VLOOKUP(J$13,Data_Entry!$C:$M,Data_Entry!$A2,0)/VLOOKUP($B14,Basic_Data!$E$2:$G$9,3,0)/VLOOKUP(J$13,Data_Entry!$C:$V,20,0),"") | ... AG14: =IFERROR(VLOOKUP(AG$13,Data_Entry!$C:$M,Data_Entry!$A2,0)/VLOOKUP($B14,Basic_Data!$E$2:$G$9,3,0)/VLOOKUP(AG$13,Data_Entry!$C:$V,20,0),"")
B15: Inv_2 | C15: =IFERROR(VLOOKUP(C$13,Data_Entry!$C:$M,Data_Entry!$A3,0)/VLOOKUP($B15,Basic_Data!$E$2:$G$9,3,0)/VLOOKUP(C$13,Data_Entry!$C:$V,20,0),"") -> 1.0014538 | D15: =IFERROR(VLOOKUP(D$13,Data_Entry!$C:$M,Data_Entry!$A3,0)/VLOOKUP($B15,Basic_Data!$E$2:$G$9,3,0)/VLOOKUP(D$13,Data_Entry!$C:$V,20,0),"") | E15: =IFERROR(VLOOKUP(E$13,Data_Entry!$C:$M,Data_Entry!$A3,0)/VLOOKUP($B15,Basic_Data!$E$2:$G$9,3,0)/VLOOKUP(E$13,Data_Entry!$C:$V,20,0),"") | F15: =IFERROR(VLOOKUP(F$13,Data_Entry!$C:$M,Data_Entry!$A3,0)/VLOOKUP($B15,Basic_Data!$E$2:$G$9,3,0)/VLOOKUP(F$13,Data_Entry!$C:$V,20,0),"") | G15: =IFERROR(VLOOKUP(G$13,Data_Entry!$C:$M,Data_Entry!$A3,0)/VLOOKUP($B15,Basic_Data!$E$2:$G$9,3,0)/VLOOKUP(G$13,Data_Entry!$C:$V,20,0),"") | H15: =IFERROR(VLOOKUP(H$13,Data_Entry!$C:$M,Data_Entry!$A3,0)/VLOOKUP($B15,Basic_Data!$E$2:$G$9,3,0)/VLOOKUP(H$13,Data_Entry!$C:$V,20,0),"") | I15: =IFERROR(VLOOKUP(I$13,Data_Entry!$C:$M,Data_Entry!$A3,0)/VLOOKUP($B15,Basic_Data!$E$2:$G$9,3,0)/VLOOKUP(I$13,Data_Entry!$C:$V,20,0),"") | J15: =IFERROR(VLOOKUP(J$13,Data_Entry!$C:$M,Data_Entry!$A3,0)/VLOOKUP($B15,Basic_Data!$E$2:$G$9,3,0)/VLOOKUP(J$13,Data_Entry!$C:$V,20,0),"") | ... AG15: =IFERROR(VLOOKUP(AG$13,Data_Entry!$C:$M,Data_Entry!$A3,0)/VLOOKUP($B15,Basic_Data!$E$2:$G$9,3,0)/VLOOKUP(AG$13,Data_Entry!$C:$V,20,0),"")
B16: Inv_3 | C16: =IFERROR(VLOOKUP(C$13,Data_Entry!$C:$M,Data_Entry!$A4,0)/VLOOKUP($B16,Basic_Data!$E$2:$G$9,3,0)/VLOOKUP(C$13,Data_Entry!$C:$V,20,0),"") -> 0.98878021 | D16: =IFERROR(VLOOKUP(D$13,Data_Entry!$C:$M,Data_Entry!$A4,0)/VLOOKUP($B16,Basic_Data!$E$2:$G$9,3,0)/VLOOKUP(D$13,Data_Entry!$C:$V,20,0),"") | E16: =IFERROR(VLOOKUP(E$13,Data_Entry!$C:$M,Data_Entry!$A4,0)/VLOOKUP($B16,Basic_Data!$E$2:$G$9,3,0)/VLOOKUP(E$13,Data_Entry!$C:$V,20,0),"") | F16: =IFERROR(VLOOKUP(F$13,Data_Entry!$C:$M,Data_Entry!$A4,0)/VLOOKUP($B16,Basic_Data!$E$2:$G$9,3,0)/VLOOKUP(F$13,Data_Entry!$C:$V,20,0),"") | G16: =IFERROR(VLOOKUP(G$13,Data_Entry!$C:$M,Data_Entry!$A4,0)/VLOOKUP($B16,Basic_Data!$E$2:$G$9,3,0)/VLOOKUP(G$13,Data_Entry!$C:$V,20,0),"") | H16: =IFERROR(VLOOKUP(H$13,Data_Entry!$C:$M,Data_Entry!$A4,0)/VLOOKUP($B16,Basic_Data!$E$2:$G$9,3,0)/VLOOKUP(H$13,Data_Entry!$C:$V,20,0),"") | I16: =IFERROR(VLOOKUP(I$13,Data_Entry!$C:$M,Data_Entry!$A4,0)/VLOOKUP($B16,Basic_Data!$E$2:$G$9,3,0)/VLOOKUP(I$13,Data_Entry!$C:$V,20,0),"") | J16: =IFERROR(VLOOKUP(J$13,Data_Entry!$C:$M,Data_Entry!$A4,0)/VLOOKUP($B16,Basic_Data!$E$2:$G$9,3,0)/VLOOKUP(J$13,Data_Entry!$C:$V,20,0),"") | ... AG16: =IFERROR(VLOOKUP(AG$13,Data_Entry!$C:$M,Data_Entry!$A4,0)/VLOOKUP($B16,Basic_Data!$E$2:$G$9,3,0)/VLOOKUP(AG$13,Data_Entry!$C:$V,20,0),"")
B17: Inv_4 | C17: =IFERROR(VLOOKUP(C$13,Data_Entry!$C:$M,Data_Entry!$A5,0)/VLOOKUP($B17,Basic_Data!$E$2:$G$9,3,0)/VLOOKUP(C$13,Data_Entry!$C:$V,20,0),"") -> 0.99444939 | D17: =IFERROR(VLOOKUP(D$13,Data_Entry!$C:$M,Data_Entry!$A5,0)/VLOOKUP($B17,Basic_Data!$E$2:$G$9,3,0)/VLOOKUP(D$13,Data_Entry!$C:$V,20,0),"") | E17: =IFERROR(VLOOKUP(E$13,Data_Entry!$C:$M,Data_Entry!$A5,0)/VLOOKUP($B17,Basic_Data!$E$2:$G$9,3,0)/VLOOKUP(E$13,Data_Entry!$C:$V,20,0),"") | F17: =IFERROR(VLOOKUP(F$13,Data_Entry!$C:$M,Data_Entry!$A5,0)/VLOOKUP($B17,Basic_Data!$E$2:$G$9,3,0)/VLOOKUP(F$13,Data_Entry!$C:$V,20,0),"") | G17: =IFERROR(VLOOKUP(G$13,Data_Entry!$C:$M,Data_Entry!$A5,0)/VLOOKUP($B17,Basic_Data!$E$2:$G$9,3,0)/VLOOKUP(G$13,Data_Entry!$C:$V,20,0),"") | H17: =IFERROR(VLOOKUP(H$13,Data_Entry!$C:$M,Data_Entry!$A5,0)/VLOOKUP($B17,Basic_Data!$E$2:$G$9,3,0)/VLOOKUP(H$13,Data_Entry!$C:$V,20,0),"") | I17: =IFERROR(VLOOKUP(I$13,Data_Entry!$C:$M,Data_Entry!$A5,0)/VLOOKUP($B17,Basic_Data!$E$2:$G$9,3,0)/VLOOKUP(I$13,Data_Entry!$C:$V,20,0),"") | J17: =IFERROR(VLOOKUP(J$13,Data_Entry!$C:$M,Data_Entry!$A5,0)/VLOOKUP($B17,Basic_Data!$E$2:$G$9,3,0)/VLOOKUP(J$13,Data_Entry!$C:$V,20,0),"") | ... AG17: =IFERROR(VLOOKUP(AG$13,Data_Entry!$C:$M,Data_Entry!$A5,0)/VLOOKUP($B17,Basic_Data!$E$2:$G$9,3,0)/VLOOKUP(AG$13,Data_Entry!$C:$V,20,0),"")
B18: Inv_5 | C18: =IFERROR(VLOOKUP(C$13,Data_Entry!$C:$M,Data_Entry!$A6,0)/VLOOKUP($B18,Basic_Data!$E$2:$G$9,3,0)/VLOOKUP(C$13,Data_Entry!$C:$V,20,0),"") -> 1.0060578 | D18: =IFERROR(VLOOKUP(D$13,Data_Entry!$C:$M,Data_Entry!$A6,0)/VLOOKUP($B18,Basic_Data!$E$2:$G$9,3,0)/VLOOKUP(D$13,Data_Entry!$C:$V,20,0),"") | E18: =IFERROR(VLOOKUP(E$13,Data_Entry!$C:$M,Data_Entry!$A6,0)/VLOOKUP($B18,Basic_Data!$E$2:$G$9,3,0)/VLOOKUP(E$13,Data_Entry!$C:$V,20,0),"") | F18: =IFERROR(VLOOKUP(F$13,Data_Entry!$C:$M,Data_Entry!$A6,0)/VLOOKUP($B18,Basic_Data!$E$2:$G$9,3,0)/VLOOKUP(F$13,Data_Entry!$C:$V,20,0),"") | G18: =IFERROR(VLOOKUP(G$13,Data_Entry!$C:$M,Data_Entry!$A6,0)/VLOOKUP($B18,Basic_Data!$E$2:$G$9,3,0)/VLOOKUP(G$13,Data_Entry!$C:$V,20,0),"") | H18: =IFERROR(VLOOKUP(H$13,Data_Entry!$C:$M,Data_Entry!$A6,0)/VLOOKUP($B18,Basic_Data!$E$2:$G$9,3,0)/VLOOKUP(H$13,Data_Entry!$C:$V,20,0),"") | I18: =IFERROR(VLOOKUP(I$13,Data_Entry!$C:$M,Data_Entry!$A6,0)/VLOOKUP($B18,Basic_Data!$E$2:$G$9,3,0)/VLOOKUP(I$13,Data_Entry!$C:$V,20,0),"") | J18: =IFERROR(VLOOKUP(J$13,Data_Entry!$C:$M,Data_Entry!$A6,0)/VLOOKUP($B18,Basic_Data!$E$2:$G$9,3,0)/VLOOKUP(J$13,Data_Entry!$C:$V,20,0),"") | ... AG18: =IFERROR(VLOOKUP(AG$13,Data_Entry!$C:$M,Data_Entry!$A6,0)/VLOOKUP($B18,Basic_Data!$E$2:$G$9,3,0)/VLOOKUP(AG$13,Data_Entry!$C:$V,20,0),"")
B19: Inv_6 | C19: =IFERROR(VLOOKUP(C$13,Data_Entry!$C:$M,Data_Entry!$A7,0)/VLOOKUP($B19,Basic_Data!$E$2:$G$9,3,0)/VLOOKUP(C$13,Data_Entry!$C:$V,20,0),"") -> 1.0001538 | D19: =IFERROR(VLOOKUP(D$13,Data_Entry!$C:$M,Data_Entry!$A7,0)/VLOOKUP($B19,Basic_Data!$E$2:$G$9,3,0)/VLOOKUP(D$13,Data_Entry!$C:$V,20,0),"") | E19: =IFERROR(VLOOKUP(E$13,Data_Entry!$C:$M,Data_Entry!$A7,0)/VLOOKUP($B19,Basic_Data!$E$2:$G$9,3,0)/VLOOKUP(E$13,Data_Entry!$C:$V,20,0),"") | F19: =IFERROR(VLOOKUP(F$13,Data_Entry!$C:$M,Data_Entry!$A7,0)/VLOOKUP($B19,Basic_Data!$E$2:$G$9,3,0)/VLOOKUP(F$13,Data_Entry!$C:$V,20,0),"") | G19: =IFERROR(VLOOKUP(G$13,Data_Entry!$C:$M,Data_Entry!$A7,0)/VLOOKUP($B19,Basic_Data!$E$2:$G$9,3,0)/VLOOKUP(G$13,Data_Entry!$C:$V,20,0),"") | H19: =IFERROR(VLOOKUP(H$13,Data_Entry!$C:$M,Data_Entry!$A7,0)/VLOOKUP($B19,Basic_Data!$E$2:$G$9,3,0)/VLOOKUP(H$13,Data_Entry!$C:$V,20,0),"") | I19: =IFERROR(VLOOKUP(I$13,Data_Entry!$C:$M,Data_Entry!$A7,0)/VLOOKUP($B19,Basic_Data!$E$2:$G$9,3,0)/VLOOKUP(I$13,Data_Entry!$C:$V,20,0),"") | J19: =IFERROR(VLOOKUP(J$13,Data_Entry!$C:$M,Data_Entry!$A7,0)/VLOOKUP($B19,Basic_Data!$E$2:$G$9,3,0)/VLOOKUP(J$13,Data_Entry!$C:$V,20,0),"") | ... AG19: =IFERROR(VLOOKUP(AG$13,Data_Entry!$C:$M,Data_Entry!$A7,0)/VLOOKUP($B19,Basic_Data!$E$2:$G$9,3,0)/VLOOKUP(AG$13,Data_Entry!$C:$V,20,0),"")
B20: Inv_7 | C20: =IFERROR(VLOOKUP(C$13,Data_Entry!$C:$M,Data_Entry!$A8,0)/VLOOKUP($B20,Basic_Data!$E$2:$G$9,3,0)/VLOOKUP(C$13,Data_Entry!$C:$V,20,0),"") -> 1.0056404 | D20: =IFERROR(VLOOKUP(D$13,Data_Entry!$C:$M,Data_Entry!$A8,0)/VLOOKUP($B20,Basic_Data!$E$2:$G$9,3,0)/VLOOKUP(D$13,Data_Entry!$C:$V,20,0),"") | E20: =IFERROR(VLOOKUP(E$13,Data_Entry!$C:$M,Data_Entry!$A8,0)/VLOOKUP($B20,Basic_Data!$E$2:$G$9,3,0)/VLOOKUP(E$13,Data_Entry!$C:$V,20,0),"") | F20: =IFERROR(VLOOKUP(F$13,Data_Entry!$C:$M,Data_Entry!$A8,0)/VLOOKUP($B20,Basic_Data!$E$2:$G$9,3,0)/VLOOKUP(F$13,Data_Entry!$C:$V,20,0),"") | G20: =IFERROR(VLOOKUP(G$13,Data_Entry!$C:$M,Data_Entry!$A8,0)/VLOOKUP($B20,Basic_Data!$E$2:$G$9,3,0)/VLOOKUP(G$13,Data_Entry!$C:$V,20,0),"") | H20: =IFERROR(VLOOKUP(H$13,Data_Entry!$C:$M,Data_Entry!$A8,0)/VLOOKUP($B20,Basic_Data!$E$2:$G$9,3,0)/VLOOKUP(H$13,Data_Entry!$C:$V,20,0),"") | I20: =IFERROR(VLOOKUP(I$13,Data_Entry!$C:$M,Data_Entry!$A8,0)/VLOOKUP($B20,Basic_Data!$E$2:$G$9,3,0)/VLOOKUP(I$13,Data_Entry!$C:$V,20,0),"") | J20: =IFERROR(VLOOKUP(J$13,Data_Entry!$C:$M,Data_Entry!$A8,0)/VLOOKUP($B20,Basic_Data!$E$2:$G$9,3,0)/VLOOKUP(J$13,Data_Entry!$C:$V,20,0),"") | ... AG20: =IFERROR(VLOOKUP(AG$13,Data_Entry!$C:$M,Data_Entry!$A8,0)/VLOOKUP($B20,Basic_Data!$E$2:$G$9,3,0)/VLOOKUP(AG$13,Data_Entry!$C:$V,20,0),"")
B21: Avg_PR% | C21: =AVERAGE(C14:C20) -> 0.99942001 | D21: =AVERAGE(D14:D20) -> #DIV/0! | E21: =AVERAGE(E14:E20) -> #DIV/0! | F21: =AVERAGE(F14:F20) -> #DIV/0! | G21: =AVERAGE(G14:G20) -> #DIV/0! | H21: =AVERAGE(H14:H20) -> #DIV/0! | I21: =AVERAGE(I14:I20) -> #DIV/0! | J21: =AVERAGE(J14:J20) -> #DIV/0! | ... AH21: =AVERAGE(AH14:AH20) -> #DIV/0!

Sheet Basic_Data
A2: Details_of_Plant | B2: Values | E2: Inverter_Name | F2: AC_Capacity_MW | G2: Connected_DC_MW | H2: No_Of_Module
A3: D.O.C(DD-MMM-YYY) | B3: 45726 | E3: Inv_1 | F3: 275 | G3: 335.72 | H3: =G3/0.545 -> 616 | I3: 2
A4: Plant_Name | B4: Devki Galol | E4: Inv_2 | F4: 275 | G4: 335.72 | H4: =G4/0.545 -> 616 | I4: 3
A5: Longitude_Of_Site | B5: 21.62 °N | E5: Inv_3 | F5: 275 | G5: 335.72 | H5: =G5/0.545 -> 616 | I5: 4
A6: Latitude_Of_Site | B6: 70.69 °E | E6: Inv_4 | F6: 275 | G6: 350.98 | H6: =G6/0.545 -> 644 | I6: 5
A7: DC_Capacity_(kWh) | B7: 2.411 | E7: Inv_5 | F7: 275 | G7: 350.98 | H7: =G7/0.545 -> 644 | I7: 6
A8: AC_Capacity_(kWh) | B8: 1.925 | E8: Inv_6 | F8: 275 | G8: 350.98 | H8: =G8/0.545 -> 644 | I8: 7
A9: Connected_DC_Capacity | B9: =SUM(G3:G94) -> 4822.16 | E9: Inv_7 | F9: 275 | G9: 350.98 | H9: =G9/0.545 -> 644 | I9: 8
A10: Multiplying_Factor_(MF) | B10: 3000 | E10: Total | F10: =SUM(F3:F9) -> 1925 | G10: =SUM(G3:G9) -> 2411.08 | H10: =SUM(H3:H9) -> 4424
A11: No._of_Power_Trafo. | B11: 1
A12: Power_Trafo._Make | B12: Gujrat_Trafo
A13: Inverter_Make | B13: Watt_power
A14: Inverter_Capacity | B14: 0.275
A15: No._of_Inverter | B15: 7
A16: Module_Make | B16: EMMVEE
A17: Module_Rating | B17: 545
A18: No._of_Strings/Table | B18: 158
A19: No._Of_Module_In_Table | B19: 28 for Bifacial
A20: Total_Module | B20: 4424
A21: Switch_Yard_Make_Vendors | B21: ABB
A22: Table_Configuration | B22: 2X28
A23: ABT Meter Make
A27: FY:Name | B27: From_FY | C27: To_FY
A28: 12-13 | B28: 41000 | C28: 41364 | D28: 365
A29: 13-14 | B29: 41365 | C29: 41729 | D29: 365
A30: 14-15 | B30: 41730 | C30: 42094 | D30: 365
A31: 15-16 | B31: 42095 | C31: 42460 | D31: 366
A32: 16-17 | B32: 42461 | C32: 42825 | D32: 365
A33: 17-18 | B33: 42826 | C33: 43190 | D33: 365
A34: 18-19 | B34: 43191 | C34: 43555 | D34: 365
A35: 19-20 | B35: 43556 | C35: 43921 | D35: 366
A36: 20-21 | B36: 43922 | C36: 44286 | D36: 365
A37: 21-22 | B37: 44287 | C37: 44651 | D37: 365
A38: 22-23 | B38: 44652 | C38: 45016 | D38: 365
A39: 23-24 | B39: 45017 | C39: 45382 | D39: 366
... A48: 32-33 | B48: 48305 | C48: 48669 | D48: 365

Sheet E-Mail_Copy
A1: Plant_Performance_of_Mandodara_GJ
B3: =DATE(YEAR(B4),MONTH(B4),1) -> 46174 | C3: =VLOOKUP(L3,Basic_Data!$A$28:$B$48,2,0) -> 45748 | L3: 25-26
A4: Date | B4: 46178 | C4: AC Capacity: | E4: =Basic_Data!F10 -> 1925 | F4: DC Capacity: | H4: =Basic_Data!G10 -> 2411.08 | I4: D.O.C.: | K4: =Basic_Data!B3 -> 45726
A5: Plant Name | C5: Daily | F5: MTD | I5: YTD
C6: Budgeted | D6: Actual | E6: Variation(%) | F6: Budgeted | G6: Actual | H6: Variation(%) | I6: Budgeted | J6: Actual | K6: Variation(%)
A7: Generation_MW | C7: =SUMIFS(Budgeted_Data!$E:$E,Budgeted_Data!$B:$B,'E-Mail_Copy'!$B$4) -> 0 | D7: =SUMIFS(Data_Entry!$T:$T,Data_Entry!$C:$C,'E-Mail_Copy'!$B$4) -> 11280 | E7: =(D7-C7)/C7 -> #DIV/0! | F7: =SUMIFS(Budgeted_Data!$E:$E,Budgeted_Data!$B:$B,">="&'E-Mail_Copy'!$B$3,Budgeted_Data!$B:$B,"<="&'E-Mail_Copy'!$B$4) -> 0 | G7: =SUMIFS(Data_Entry!$T:$T,Data_Entry!$C:$C,">="&'E-Mail_Copy'!$B$3,Data_Entry!$C:$C,"<="&'E-Mail_Copy'!$B$4) -> 57300 | H7: =(G7-F7)/F7 -> #DIV/0! | I7: =SUMIFS(Budgeted_Data!$E:$E,Budgeted_Data!$B:$B,">="&'E-Mail_Copy'!$C$3,Budgeted_Data!$B:$B,"<="&'E-Mail_Copy'!$B$4) -> 4242610.3 | J7: =SUMIFS(Data_Entry!$T:$T,Data_Entry!$C:$C,">="&'E-Mail_Copy'!$C$3,Data_Entry!$C:$C,"<="&'E-Mail_Copy'!$B$4) -> 4662923 | K7: =(J7-I7)/I7 -> 0.099069355
A8: GTI (Kwh/m2) | C8: =SUMIFS(Budgeted_Data!$F:$F,Budgeted_Data!$B:$B,'E-Mail_Copy'!$B$4) -> 0 | D8: =SUMIFS(Data_Entry!$V:$V,Data_Entry!$C:$C,'E-Mail_Copy'!B4) -> 4.71 | E8: =(D8-C8)/C8 -> #DIV/0! | F8: =SUMIFS(Budgeted_Data!$F:$F,Budgeted_Data!$B:$B,">="&'E-Mail_Copy'!$B$3,Budgeted_Data!$B:$B,"<="&'E-Mail_Copy'!$B$4) -> 0 | G8: =SUMIFS(Data_Entry!$V:$V,Data_Entry!$C:$C,">="&'E-Mail_Copy'!$B$3,Data_Entry!$C:$C,"<="&'E-Mail_Copy'!$B$4) -> 24.65 | H8: =(G8-F8)/F8 -> #DIV/0! | I8: =SUMIFS(Budgeted_Data!$F:$F,Budgeted_Data!$B:$B,">="&'E-Mail_Copy'!$C$3,Budgeted_Data!$B:$B,"<="&'E-Mail_Copy'!$B$4) -> 2080.1765 | J8: =SUMIFS(Data_Entry!$V:$V,Data_Entry!$C:$C,">="&'E-Mail_Copy'!$C$3,Data_Entry!$C:$C,"<="&'E-Mail_Copy'!$B$4) -> 1566.55 | K8: =(J8-I8)/I8 -> -0.24691485
A9: GHI (Kwh/m2) | C9: =SUMIFS(Budgeted_Data!$G:$G,Budgeted_Data!$B:$B,'E-Mail_Copy'!$B$4) -> 0 | D9: =SUMIFS(Data_Entry!$U:$U,Data_Entry!$C:$C,'E-Mail_Copy'!$B$4) -> 0 | E9: =(D9-C9)/C9 -> #DIV/0! | F9: =SUMIFS(Budgeted_Data!$G:$G,Budgeted_Data!$B:$B,">="&'E-Mail_Copy'!$B$3,Budgeted_Data!$B:$B,"<="&'E-Mail_Copy'!$B$4) -> 0 | G9: =SUMIFS(Data_Entry!$U:$U,Data_Entry!$C:$C,">="&'E-Mail_Copy'!$B$3,Data_Entry!$C:$C,"<="&'E-Mail_Copy'!$B$4) -> 0 | H9: =(G9-F9)/F9 -> #DIV/0! | I9: =SUMIFS(Budgeted_Data!$G:$G,Budgeted_Data!$B:$B,">="&'E-Mail_Copy'!$C$3,Budgeted_Data!$B:$B,"<="&'E-Mail_Copy'!$B$4) -> 2008.2427 | J9: =SUMIFS(Data_Entry!$U:$U,Data_Entry!$C:$C,">="&'E-Mail_Copy'!$C$3,Data_Entry!$C:$C,"<="&'E-Mail_Copy'!$B$4) -> 3.9 | K9: =(J9-I9)/I9 -> -0.998058
A10: PR_(%) | C10: =C7/C8/H4 -> #DIV/0! | D10: =D7/D8/H4 -> 0.99329116 | E10: =(D10-C10)/C10 -> #DIV/0! | F10: =F7/F8/H4/(B4-B3+1) -> #DIV/0! | G10: =G7/G8/H4/(B4-B3+1) -> 0.19282177 | H10: =(G10-F10)/F10 -> #DIV/0! | I10: =I7/I8/H4/(($B$4-$C$3)+1) -> 0.0019626555 | J10: =J7/J8/H4/(($B$4-$C$3)+1) -> 0.0028643435 | K10: =(J10-I10)/I10 -> 0.45942243
A11: CUF_(%) | C11: =C7/E4/24 -> 0 | D11: =D7/24/E4 -> 0.24415584 | E11: =(D11-C11)/C11 -> #DIV/0! | F11: =F7/24/E4/(B4-B3+1) -> 0 | G11: =G7/24/E4/(B4-B3+1) -> 0.24805195 | H11: =(G11-F11)/F11 -> #DIV/0! | I11: =I7/24/$E$4/(($B$4-$C$3)+1) -> 0.21306588 | J11: =J7/24/$E$4/(($B$4-$C$3)+1) -> 0.23417417 | K11: =(J11-I11)/I11 -> 0.099069355
A12: Wtd_Module_Temp | C12: =AVERAGEIFS(Budgeted_Data!$L:$L,Budgeted_Data!$B:$B,'E-Mail_Copy'!$B$4) -> #DIV/0! | D12: =AVERAGEIFS(Data_Entry!$Y:$Y,Data_Entry!$C:$C,'E-Mail_Copy'!$B$4) -> #DIV/0! | E12: =(D12-C12)/C12 -> #DIV/0! | F12: =AVERAGEIFS(Budgeted_Data!$L:$L,Budgeted_Data!$B:$B,">="&'E-Mail_Copy'!$B$3,Budgeted_Data!$B:$B,"<="&'E-Mail_Copy'!$B$4) -> #DIV/0! | G12: =AVERAGEIFS(Data_Entry!$Y:$Y,Data_Entry!$C:$C,">="&'E-Mail_Copy'!$B$3,Data_Entry!$C:$C,"<="&'E-Mail_Copy'!$B$4) -> #DIV/0! | H12: =(G12-F12)/F12 -> #DIV/0! | I12: =AVERAGEIFS(Budgeted_Data!$L:$L,Budgeted_Data!$B:$B,">="&'E-Mail_Copy'!$C$3,Budgeted_Data!$B:$B,"<="&'E-Mail_Copy'!$B$4) -> 20.137914 | J12: =AVERAGEIFS(Data_Entry!$Y:$Y,Data_Entry!$C:$C,">="&'E-Mail_Copy'!$C$3,Data_Entry!$C:$C,"<="&'E-Mail_Copy'!$B$4) -> #DIV/0! | K12: =(J12-I12)/I12 -> #DIV/0!
A13: Ambt._Temp_(0C) | C13: =AVERAGEIFS(Budgeted_Data!$H:$H,Budgeted_Data!$B:$B,'E-Mail_Copy'!$B$4) -> #DIV/0! | D13: =AVERAGEIFS(Data_Entry!$W:$W,Data_Entry!$C:$C,'E-Mail_Copy'!$B$4) -> 33.03 | E13: =(D13-C13)/C13 -> #DIV/0! | F13: =AVERAGEIFS(Budgeted_Data!$H:$H,Budgeted_Data!$B:$B,">="&'E-Mail_Copy'!$B$3,Budgeted_Data!$B:$B,"<="&'E-Mail_Copy'!$B$4) -> #DIV/0! | G13: =AVERAGEIFS(Data_Entry!$W:$W,Data_Entry!$C:$C,">="&'E-Mail_Copy'!$B$3,Data_Entry!$C:$C,"<="&'E-Mail_Copy'!$B$4) -> 33.098 | H13: =(G13-F13)/F13 -> #DIV/0! | I13: =AVERAGEIFS(Budgeted_Data!$H:$H,Budgeted_Data!$B:$B,">="&'E-Mail_Copy'!$C$3,Budgeted_Data!$B:$B,"<="&'E-Mail_Copy'!$B$4) -> 27.271039 | J13: =AVERAGEIFS(Data_Entry!$W:$W,Data_Entry!$C:$C,">="&'E-Mail_Copy'!$C$3,Data_Entry!$C:$C,"<="&'E-Mail_Copy'!$B$4) -> 26.990765 | K13: =(J13-I13)/I13 -> -0.010277342

Sheet Plant_Down_Time Details
A1: Plant_Down_Time Details
A2: Month | B2: Date | C2: Inverter_No | D2: String_No | E2: Down_Time_Start | F2: Down_Time_Stop | G2: Total_Down_Time | H2: Affected DC Capacity (in KW) | I2: Insolation*Capacity | J2: Generation Loss | K2: Revenue | L2: Component Name | M2: Fault Description | N2: Reason_Of_Down | O2: Purposed Action Plan | P2: Material Consumption Description | Q2: UOM | R2: Quantity | S2: Corrective_Action_Taken_By_Site_Team
A3: 45747 | B3: 45747
A4: 45748 | B4: 45748
A5: 45749 | B5: 45749
A6: 45750 | B6: 45750
A7: 45751 | B7: 45751
A8: 45752 | B8: 45752
A9: 45753 | B9: 45753
A10: 45754 | B10: 45754
A11: 45755 | B11: 45755
A12: 45756 | B12: 45756
A13: 45757 | B13: 45757
A14: 45758 | B14: 45758
... A25: 45769 | B25: 45769
A26: 45770 | B26: 45770 | C26: All inverter | D26: All string | E26: 0.48263889 | F26: 0.51736111 | G26: 0.034722222 | H26: 2411 | M26: Do wire burning | P26: used Do wire | S26: B phase Do wire replace
A27: 45771 | B27: 45771 | C27: All inverter | D27: All string | E27: 0.48958333 | F27: 0.52430556 | G27: 0.027777778 | H27: 2411 | M27: Do wire burning | P27: used Do wire | S27: B phase Do wire replace
A28: 45772 | B28: 45772
A29: 45773 | B29: 45773
A30: 45774 | B30: 45774
A31: 45775 | B31: 45775
A32: 45776 | B32: 45776
A33: 45777 | B33: 45777
A34: 45778 | B34: 45778
A35: 45779 | B35: 45779
A36: 45780 | B36: 45780
A37: 45781 | B37: 45781
A38: 45782 | B38: 45782
A39: 45783 | B39: 45783
... A86: 45830 | B86: 45830
A87: 45831 | B87: 45831 | C87: Inverter_No:02 | D87: 22 | E87: 0.28125 | F87: 0.79166667 | G87: =F87-E87 -> 0.51041667 | H87: 330 | L87: INVERTER | M87: INTERNAL | S87: Visit by wattpower team,
A88: 45832 | B88: 45832 | C88: Inverter_No:02 | D88: 22 | E88: 0.28125 | F88: 0.79166667 | G88: =F88-E88 -> 0.51041667 | H88: 330 | L88: INVERTER | M88: INTERNAL | S88: Visit by wattpower team,
A89: 45833 | B89: 45833 | C89: Inverter_No:02 | D89: 23 | E89: 0.28125 | F89: 0.79166667 | G89: =F89-E89 -> 0.51041667 | H89: 330 | L89: INVERTER | M89: INTERNAL | S89: Visit by wattpower team,
A90: 45834 | B90: 45834 | C90: Inverter_No:02 | D90: 24 | E90: 0.28125 | F90: 0.79166667 | G90: =F90-E90 -> 0.51041667 | H90: 330 | L90: INVERTER | M90: INTERNAL | S90: Visit by wattpower team,
A91: 45835 | B91: 45835 | C91: Inverter_No:02 | D91: 24 | E91: 0.28125 | F91: 0.79166667 | G91: =F91-E91 -> 0.51041667 | H91: 330 | L91: INVERTER | M91: INTERNAL | S91: Visit by wattpower team,
A92: 45836 | B92: 45836 | C92: Inverter_No:02 | D92: 24 | E92: 0.28125 | F92: 0.73611111 | G92: =F92-E92 -> 0.45486111 | H92: 330 | L92: INVERTER | M92: INTERNAL | S92: INSTALLED NEW INVERTER BY SITE TEAM
A93: 45837 | B93: 45837
A94: 45838 | B94: 45838 | C94: All inverter | D94: All string | E94: 0.63541667 | F94: 0.71875 | G94: =F94-E94 -> 0.083333333 | H94: 2411 | L94: 11 kv panel tripped | M94: over voltage & undar voltage | S94: aftar 11 kv panel manufactring person set relay
A95: 45839 | B95: 45839
A96: 45840 | B96: 45840
A97: 45841 | B97: 45841
A98: 45842 | B98: 45842
A99: 45843 | B99: 45843
A100: 45844 | B100: 45844
A101: 45845 | B101: 45845
A102: 45846 | B102: 45846
A103: 45847 | B103: 45847
A104: 45848 | B104: 45848
A105: 45849 | B105: 45849
A106: 45850 | B106: 45850
... A130: 45874 | B130: 45874
A131: 45875 | B131: 45875 | C131: All inverter | D131: All string | E131: 0.46527778 | F131: 0.49236111 | G131: =F131-E131 -> 0.027083333 | H131: 2411 | L131: DO wire | M131: over voltage | S131: resolved by site team
A132: 45876 | B132: 45876 | C132: All inverter | D132: All string | E132: 0.59027778 | F132: 0.6375 | G132: =F132-E132 -> 0.047222222 | H132: 2411 | L132: DO wire | M132: over voltage | S132: resolved by site team
A133: 45877 | B133: 45877 | G133: =F133-E133 -> 0
A134: 45878 | B134: 45878 | G134: =F134-E134 -> 0
A135: 45879 | B135: 45879 | G135: =F135-E135 -> 0
A136: 45880 | B136: 45880 | G136: =F136-E136 -> 0
A137: 45881 | B137: 45881 | G137: =F137-E137 -> 0
A138: 45882 | B138: 45882 | G138: =F138-E138 -> 0
A139: 45883 | B139: 45883 | G139: =F139-E139 -> 0
A140: 45884 | B140: 45884 | G140: =F140-E140 -> 0
A141: 45885 | B141: 45885 | G141: =F141-E141 -> 0
A142: 45886 | B142: 45886 | G142: =F142-E142 -> 0
A143: 45887 | B143: 45887 | G143: =F143-E143 -> 0
A144: 45888 | B144: 45888 | G144: =F144-E144 -> 0
... A162: 45906 | B162: 45906 | G162: =F162-E162 -> 0
A163: 45907 | B163: 45907 | C163: Inverter_No:01 | D163: 22 | E163: 0.29166667 | F163: 0.66666667 | G163: =F163-E163 -> 0.375 | H163: 330 | L163: arrey | M163: low insulation resistance | N163: arrey cable insulation damage | P163: 1 nos MC4 Connector | R163: 1 | S163: arry rectification by site team
A164: 45908 | B164: 45908 | G164: =F164-E164 -> 0
A165: 45909 | B165: 45909 | G165: =F165-E165 -> 0
A166: 45910 | B166: 45910 | G166: =F166-E166 -> 0
A167: 45911 | B167: 45911 | G167: =F167-E167 -> 0
A168: 45912 | B168: 45912 | G168: =F168-E168 -> 0
A169: 45913 | B169: 45913 | G169: =F169-E169 -> 0
A170: 45914 | B170: 45914 | G170: =F170-E170 -> 0
A171: 45915 | B171: 45915 | G171: =F171-E171 -> 0
A172: 45916 | B172: 45916 | G172: =F172-E172 -> 0
A173: 45917 | B173: 45917 | G173: =F173-E173 -> 0
A174: 45918 | B174: 45918 | G174: =F174-E174 -> 0
A175: 45919 | B175: 45919 | G175: =F175-E175 -> 0
... A209: 45953 | B209: 45953 | G209: =F209-E209 -> 0
A210: 45954 | B210: 45954 | C210: All inverter | D210: All string | E210: 0.35763889 | F210: 0.39930556 | G210: =F210-E210 -> 0.041666667 | H210: 2411 | L210: DP SWITCH | M210: Y phase HAVY Sparking | N210: loos conntect | S210: resoveld by site team
A211: 45955 | B211: 45955 | G211: =F211-E211 -> 0
A212: 45956 | B212: 45956 | G212: =F212-E212 -> 0
A213: 45957 | B213: 45957 | G213: =F213-E213 -> 0
A214: 45958 | B214: 45958 | G214: =F214-E214 -> 0
A215: 45959 | B215: 45959 | G215: =F215-E215 -> 0
A216: 45960 | B216: 45960 | G216: =F216-E216 -> 0
A217: 45961 | B217: 45961 | G217: =F217-E217 -> 0
A218: 45962 | B218: 45962 | G218: =F218-E218 -> 0
A219: 45963 | B219: 45963 | G219: =F219-E219 -> 0
A220: 45964 | B220: 45964 | G220: =F220-E220 -> 0
A221: 45965 | B221: 45965 | G221: =F221-E221 -> 0
A222: 45966 | B222: 45966 | G222: =F222-E222 -> 0
... A335: 46079 | B335: 46079 | G335: =F335-E335 -> 0
A336: 46080 | B336: 46080 | C336: All inverter | D336: All string | E336: 0.52986111 | F336: 0.78819444 | G336: =F336-E336 -> 0.25833333 | H336: 2411 | M336: brecker dummy tripped | N336: 11kv s/s site brecker issue
A337: 46081 | B337: 46081 | G337: =F337-E337 -> 0
A338: 46082 | B338: 46082 | G338: =F338-E338 -> 0
A339: 46083 | B339: 46083 | G339: =F339-E339 -> 0
A340: 46084 | B340: 46084 | G340: =F340-E340 -> 0
A341: 46085 | B341: 46085 | G341: =F341-E341 -> 0
...

Sheet Plant_Grid_Down_Time_Details
A1: Plant_Grid_Down_Time_Details
A3: Month | B3: Date | C3: Transformer_No. (T-1) | D3: Down_Time_Start | E3: Down_Time_Stop | F3: Total_Down_Time | G3: Comm. Insolation of the Period | H3: Module Temp of the Period | I3: Affected DC Capacity (in KW) | J3: Insolation*Capacity | K3: Generation Loss | L3: Revenue
B4: 45813 | C4: 1 | D4: 0.29166667 | E4: 0.58680556 | F4: =E4-D4 -> 0.29513889 | I4: 2411
B5: 45783 | C5: 1 | D5: 0.77430556 | E5: 0.7875 | F5: =E5-D5 -> 0.013194444 | I5: 2411 | M5: GETCO site s/s tripped
B6: 45838 | C6: 1 | D6: 0.47430556 | E6: 0.50347222 | F6: =E6-D6 -> 0.029166667 | I6: 2411 | M6: GETCO site s/s tripped
A7: 45887 | B7: 45888 | C7: 1 | D7: 0.41666667 | E7: 0.46180556 | F7: =E7-D7 -> 0.045138889 | I7: 2411 | M7: GETCO team Maintance work
A8: 268 | B8: 24/09/25 | C8: 1 | D8: 0.29166667 | E8: 0.52638889 | F8: =E8-D8 -> 0.23472222 | I8: 2411 | M8: GETCO site s/s IN OUTAGE
A9: 46082 | B9: 46082 | C9: 1 | D9: 0.34722222 | E9: 0.41666667 | F9: =E9-D9 -> 0.069444444 | I9: 2411 | M9: getco site 11kv panel kwh meter isueed
B10: 22/01/2026 | C10: 1 | D10: 0.41111111 | E10: 0.41527778 | F10: =E10-D10 -> 0.0041666667 | I10: 2411 | M10: s/s low voltage
A11: 31/01/2026 | B11: 31/01/2026 | C11: 1 | D11: 0.35416667 | E11: 0.4375 | F11: =E11-D11 -> 0.083333333 | I11: 2411 | M11: for getco s/s site 11 kv panle mechineal issued resoveld by joyti team(hitesh bhai visited)
B12: 31/01/2026 | C12: 1 | D12: 0.47916667 | E12: 0.50694444 | F12: =E12-D12 -> 0.027777778 | I12: 2411 | M12: again plant manully stopped for amp meter wiring checked by joyti team( hitesh bhai)
B13: 19/04/2026 | C13: 1 | D13: 0.29166667 | E13: 0.54236111 | F13: 0.25069444 | I13: 2411 | M13: substaation site planned outage

Sheet Module_Cleaning
C2: Water Consumption
A3: Months | B3: Date | C3: Tanker Qty | D3: Consumption (Capacity(Ltr)* Tanker) | E3: TDS (PPM) | F3: Cycle No. | G3: Invt. No | I3: Module | J3: Cleaned | K3: Before Cleaning PR% | L3: After Cleaning PR% | M3: Balance | N3: Remarks
A4: 45747 | B4: 45747
A5: 45748 | B5: 45748
A6: 45749 | B6: 45749
A7: 45750 | B7: 45750
A8: 45751 | B8: 45751
A9: 45752 | B9: 45752
A10: 45753 | B10: 45753
A11: 45754 | B11: 45754
A12: 45755 | B12: 45755
A13: 45756 | B13: 45756
A14: 45757 | B14: 45757
A15: 45758 | B15: 45758
A16: 45759 | B16: 45759 | H16: =IFERROR(VLOOKUP(G16,Basic_Data!$E$2:$I$9,5,0),"") | I16: =IFERROR(VLOOKUP($G16,Basic_Data!$E$2:$H$10,4,0),"") | K16: =IFERROR(VLOOKUP($B16-1,Inverter_PR!$B:$I,Module_Cleaning!H16,0),"") | L16: =IFERROR(VLOOKUP($B16+1,Inverter_PR!$B:$I,Module_Cleaning!H16,0),"") | M16: =IFERROR(I16-J16,"")
A17: 45760 | B17: 45760 | H17: =IFERROR(VLOOKUP(G17,Basic_Data!$E$2:$I$9,5,0),"") | I17: =IFERROR(VLOOKUP($G17,Basic_Data!$E$2:$H$10,4,0),"") | K17: =IFERROR(VLOOKUP($B17-1,Inverter_PR!$B:$I,Module_Cleaning!H17,0),"") | L17: =IFERROR(VLOOKUP($B17+1,Inverter_PR!$B:$I,Module_Cleaning!H17,0),"") | M17: =IFERROR(I17-J17,"")
A18: 45761 | B18: 45761 | H18: =IFERROR(VLOOKUP(G18,Basic_Data!$E$2:$I$9,5,0),"") | I18: =IFERROR(VLOOKUP($G18,Basic_Data!$E$2:$H$10,4,0),"") | K18: =IFERROR(VLOOKUP($B18-1,Inverter_PR!$B:$I,Module_Cleaning!H18,0),"") | L18: =IFERROR(VLOOKUP($B18+1,Inverter_PR!$B:$I,Module_Cleaning!H18,0),"") | M18: =IFERROR(I18-J18,"")
A19: 45762 | B19: 45762 | H19: =IFERROR(VLOOKUP(G19,Basic_Data!$E$2:$I$9,5,0),"") | I19: =IFERROR(VLOOKUP($G19,Basic_Data!$E$2:$H$10,4,0),"") | K19: =IFERROR(VLOOKUP($B19-1,Inverter_PR!$B:$I,Module_Cleaning!H19,0),"") | L19: =IFERROR(VLOOKUP($B19+1,Inverter_PR!$B:$I,Module_Cleaning!H19,0),"") | M19: =IFERROR(I19-J19,"")
A20: 45763 | B20: 45763 | H20: =IFERROR(VLOOKUP(G20,Basic_Data!$E$2:$I$9,5,0),"") | I20: =IFERROR(VLOOKUP($G20,Basic_Data!$E$2:$H$10,4,0),"") | K20: =IFERROR(VLOOKUP($B20-1,Inverter_PR!$B:$I,Module_Cleaning!H20,0),"") | L20: =IFERROR(VLOOKUP($B20+1,Inverter_PR!$B:$I,Module_Cleaning!H20,0),"") | M20: =IFERROR(I20-J20,"")
A21: 45764 | B21: 45764 | H21: =IFERROR(VLOOKUP(G21,Basic_Data!$E$2:$I$9,5,0),"") | I21: =IFERROR(VLOOKUP($G21,Basic_Data!$E$2:$H$10,4,0),"") | K21: =IFERROR(VLOOKUP($B21-1,Inverter_PR!$B:$I,Module_Cleaning!H21,0),"") | L21: =IFERROR(VLOOKUP($B21+1,Inverter_PR!$B:$I,Module_Cleaning!H21,0),"") | M21: =IFERROR(I21-J21,"")
A22: 45765 | B22: 45765 | H22: =IFERROR(VLOOKUP(G22,Basic_Data!$E$2:$I$9,5,0),"") | I22: =IFERROR(VLOOKUP($G22,Basic_Data!$E$2:$H$10,4,0),"") | K22: =IFERROR(VLOOKUP($B22-1,Inverter_PR!$B:$I,Module_Cleaning!H22,0),"") | L22: =IFERROR(VLOOKUP($B22+1,Inverter_PR!$B:$I,Module_Cleaning!H22,0),"") | M22: =IFERROR(I22-J22,"")
A23: 45766 | B23: 45766 | H23: =IFERROR(VLOOKUP(G23,Basic_Data!$E$2:$I$9,5,0),"") | I23: =IFERROR(VLOOKUP($G23,Basic_Data!$E$2:$H$10,4,0),"") | K23: =IFERROR(VLOOKUP($B23-1,Inverter_PR!$B:$I,Module_Cleaning!H23,0),"") | L23: =IFERROR(VLOOKUP($B23+1,Inverter_PR!$B:$I,Module_Cleaning!H23,0),"") | M23: =IFERROR(I23-J23,"")
A24: 45767 | B24: 45767 | H24: =IFERROR(VLOOKUP(G24,Basic_Data!$E$2:$I$9,5,0),"") | I24: =IFERROR(VLOOKUP($G24,Basic_Data!$E$2:$H$10,4,0),"") | K24: =IFERROR(VLOOKUP($B24-1,Inverter_PR!$B:$I,Module_Cleaning!H24,0),"") | L24: =IFERROR(VLOOKUP($B24+1,Inverter_PR!$B:$I,Module_Cleaning!H24,0),"") | M24: =IFERROR(I24-J24,"")
A25: 45768 | B25: 45768 | C25: 1 | D25: 2000 | F25: 2 | G25: Inv_7 | H25: =IFERROR(VLOOKUP(G25,Basic_Data!$E$2:$I$9,5,0),"") -> 8 | I25: =IFERROR(VLOOKUP($G25,Basic_Data!$E$2:$H$10,4,0),"") -> 644 | J25: 644 | K25: =IFERROR(VLOOKUP($B25-1,Inverter_PR!$B:$I,Module_Cleaning!H25,0),"") -> 1.0588069 | L25: =IFERROR(VLOOKUP($B25+1,Inverter_PR!$B:$I,Module_Cleaning!H25,0),"") -> 1.0796984 | M25: =IFERROR(I25-J25,"") -> 0 | N25: wet cleaning
A26: 45769 | B26: 45769 | C26: 2 | D26: 4000 | F26: 2 | G26: Inv_6 | H26: =IFERROR(VLOOKUP(G26,Basic_Data!$E$2:$I$9,5,0),"") -> 7 | I26: =IFERROR(VLOOKUP($G26,Basic_Data!$E$2:$H$10,4,0),"") -> 644 | J26: 644 | K26: =IFERROR(VLOOKUP($B26-1,Inverter_PR!$B:$I,Module_Cleaning!H26,0),"") -> 1.0383686 | L26: =IFERROR(VLOOKUP($B26+1,Inverter_PR!$B:$I,Module_Cleaning!H26,0),"") -> 1.0189036 | M26: =IFERROR(I26-J26,"") -> 0 | N26: wet cleaning
A27: 45799 | B27: 45769 | F27: 2 | G27: Inv_5 | I27: 644 | J27: 644 | N27: wet cleaning
A28: 45770 | B28: 45770 | C28: 2 | D28: 4000 | F28: 2 | G28: Inv_4 | H28: =IFERROR(VLOOKUP(G28,Basic_Data!$E$2:$I$9,5,0),"") -> 5 | I28: =IFERROR(VLOOKUP($G28,Basic_Data!$E$2:$H$10,4,0),"") -> 644 | J28: 644 | K28: =IFERROR(VLOOKUP($B28-1,Inverter_PR!$B:$I,Module_Cleaning!H28,0),"") -> 1.0632844 | L28: =IFERROR(VLOOKUP($B28+1,Inverter_PR!$B:$I,Module_Cleaning!H28,0),"") -> 1.0211441 | M28: =IFERROR(I28-J28,"") -> 0 | N28: wet cleaning
F29: 2 | G29: Inv_3 | I29: 616 | J29: 616 | N29: wet cleaning
A30: 45771 | B30: 45771 | C30: 2 | D30: 4000 | F30: 2 | G30: Inv_2 | H30: =IFERROR(VLOOKUP(G30,Basic_Data!$E$2:$I$9,5,0),"") -> 3 | I30: =IFERROR(VLOOKUP($G30,Basic_Data!$E$2:$H$10,4,0),"") -> 616 | J30: 616 | K30: =IFERROR(VLOOKUP($B30-1,Inverter_PR!$B:$I,Module_Cleaning!H30,0),"") -> 1.0533502 | L30: =IFERROR(VLOOKUP($B30+1,Inverter_PR!$B:$I,Module_Cleaning!H30,0),"") -> 1.109091 | M30: =IFERROR(I30-J30,"") -> 0 | N30: wet cleaning
F31: 2 | G31: Inv_1 | I31: 616 | J31: 616 | N31: wet cleaning
A32: 45772 | B32: 45772 | C32: 0 | D32: 0 | E32: 0 | F32: 0 | H32: 0 | I32: 0 | J32: 0 | K32: =IFERROR(VLOOKUP($B32-1,Inverter_PR!$B:$I,Module_Cleaning!H32,0),"") | L32: =IFERROR(VLOOKUP($B32+1,Inverter_PR!$B:$I,Module_Cleaning!H32,0),"") | M32: =IFERROR(I32-J32,"") -> 0 | N32: N0 cleaning
A33: 45773 | B33: 45773 | C33: 0 | D33: 0 | E33: 0 | F33: 0 | H33: =IFERROR(VLOOKUP(G33,Basic_Data!$E$2:$I$9,5,0),"") | I33: 0 | J33: 0 | K33: =IFERROR(VLOOKUP($B33-1,Inverter_PR!$B:$I,Module_Cleaning!H33,0),"") | L33: =IFERROR(VLOOKUP($B33+1,Inverter_PR!$B:$I,Module_Cleaning!H33,0),"") | M33: =IFERROR(I33-J33,"") -> 0 | N33: N0 cleaning
A34: 45774 | B34: 45774 | C34: 0 | D34: 0 | E34: 0 | F34: 0 | H34: =IFERROR(VLOOKUP(G34,Basic_Data!$E$2:$I$9,5,0),"") | I34: 0 | J34: 0 | K34: =IFERROR(VLOOKUP($B34-1,Inverter_PR!$B:$I,Module_Cleaning!H34,0),"") | L34: =IFERROR(VLOOKUP($B34+1,Inverter_PR!$B:$I,Module_Cleaning!H34,0),"") | M34: =IFERROR(I34-J34,"") -> 0 | N34: N0 cleaning
A35: 45775 | B35: 45775 | C35: 0 | D35: 0 | E35: 0 | F35: 0 | H35: =IFERROR(VLOOKUP(G35,Basic_Data!$E$2:$I$9,5,0),"") | I35: 0 | J35: 0 | K35: =IFERROR(VLOOKUP($B35-1,Inverter_PR!$B:$I,Module_Cleaning!H35,0),"") | L35: =IFERROR(VLOOKUP($B35+1,Inverter_PR!$B:$I,Module_Cleaning!H35,0),"") | M35: =IFERROR(I35-J35,"") -> 0 | N35: N0 cleaning
A36: 45776 | B36: 45776 | C36: 0 | D36: 0 | E36: 0 | F36: 0 | H36: =IFERROR(VLOOKUP(G36,Basic_Data!$E$2:$I$9,5,0),"") | I36: 0 | J36: 0 | K36: =IFERROR(VLOOKUP($B36-1,Inverter_PR!$B:$I,Module_Cleaning!H36,0),"") | L36: =IFERROR(VLOOKUP($B36+1,Inverter_PR!$B:$I,Module_Cleaning!H36,0),"") | M36: =IFERROR(I36-J36,"") -> 0 | N36: N0 cleaning
A37: 45777 | B37: 45777 | C37: 0 | D37: 0 | E37: 0 | F37: 0 | H37: =IFERROR(VLOOKUP(G37,Basic_Data!$E$2:$I$9,5,0),"") | I37: 0 | J37: 0 | K37: =IFERROR(VLOOKUP($B37-1,Inverter_PR!$B:$I,Module_Cleaning!H37,0),"") | L37: =IFERROR(VLOOKUP($B37+1,Inverter_PR!$B:$I,Module_Cleaning!H37,0),"") | M37: =IFERROR(I37-J37,"") -> 0 | N37: N0 cleaning
A38: 45778 | B38: 45778 | C38: 0 | D38: 0 | E38: 0 | F38: 0 | H38: =IFERROR(VLOOKUP(G38,Basic_Data!$E$2:$I$9,5,0),"") | I38: 0 | J38: 0 | K38: =IFERROR(VLOOKUP($B38-1,Inverter_PR!$B:$I,Module_Cleaning!H38,0),"") | L38: =IFERROR(VLOOKUP($B38+1,Inverter_PR!$B:$I,Module_Cleaning!H38,0),"") | M38: =IFERROR(I38-J38,"") -> 0 | N38: N0 cleaning
A39: 45779 | B39: 45779 | C39: 0 | D39: 0 | E39: 0 | F39: 0 | H39: =IFERROR(VLOOKUP(G39,Basic_Data!$E$2:$I$9,5,0),"") | I39: 0 | J39: 0 | K39: =IFERROR(VLOOKUP($B39-1,Inverter_PR!$B:$I,Module_Cleaning!H39,0),"") | L39: =IFERROR(VLOOKUP($B39+1,Inverter_PR!$B:$I,Module_Cleaning!H39,0),"") | M39: =IFERROR(I39-J39,"") -> 0 | N39: N0 cleaning
A40: 45780 | B40: 45780 | C40: 0 | D40: 0 | E40: 0 | F40: 0 | H40: =IFERROR(VLOOKUP(G40,Basic_Data!$E$2:$I$9,5,0),"") | I40: 0 | J40: 0 | K40: =IFERROR(VLOOKUP($B40-1,Inverter_PR!$B:$I,Module_Cleaning!H40,0),"") | L40: =IFERROR(VLOOKUP($B40+1,Inverter_PR!$B:$I,Module_Cleaning!H40,0),"") | M40: =IFERROR(I40-J40,"") -> 0 | N40: N0 cleaning
A41: 45781 | B41: 45781 | C41: 0 | E41: 0 | F41: 0 | H41: =IFERROR(VLOOKUP(G41,Basic_Data!$E$2:$I$9,5,0),"") | I41: 0 | J41: 0 | K41: =IFERROR(VLOOKUP($B41-1,Inverter_PR!$B:$I,Module_Cleaning!H41,0),"") | L41: =IFERROR(VLOOKUP($B41+1,Inverter_PR!$B:$I,Module_Cleaning!H41,0),"") | M41: =IFERROR(I41-J41,"") -> 0 | N41: N0 cleaning
A42: 45782 | B42: 45782 | C42: 0 | D42: 0 | E42: 0 | F42: 0 | H42: =IFERROR(VLOOKUP(G42,Basic_Data!$E$2:$I$9,5,0),"") | I42: 0 | J42: 0 | K42: 0 | L42: =IFERROR(VLOOKUP($B42+1,Inverter_PR!$B:$I,Module_Cleaning!H42,0),"") | M42: =IFERROR(I42-J42,"") -> 0 | N42: N0 cleaning
A43: 45783 | B43: 45783 | C43: 0 | D43: 0 | E43: 0 | F43: 0 | H43: =IFERROR(VLOOKUP(G43,Basic_Data!$E$2:$I$9,5,0),"") | I43: 0 | J43: 0 | K43: =IFERROR(VLOOKUP($B43-1,Inverter_PR!$B:$I,Module_Cleaning!H43,0),"") | L43: =IFERROR(VLOOKUP($B43+1,Inverter_PR!$B:$I,Module_Cleaning!H43,0),"") | M43: =IFERROR(I43-J43,"") -> 0 | N43: N0 cleaning
A44: 45784 | B44: 45784 | H44: =IFERROR(VLOOKUP(G44,Basic_Data!$E$2:$I$9,5,0),"") | I44: =IFERROR(VLOOKUP($G44,Basic_Data!$E$2:$H$10,4,0),"") | K44: =IFERROR(VLOOKUP($B44-1,Inverter_PR!$B:$I,Module_Cleaning!H44,0),"") | L44: =IFERROR(VLOOKUP($B44+1,Inverter_PR!$B:$I,Module_Cleaning!H44,0),"") | M44: =IFERROR(I44-J44,"") | N44: All module cleaned by rain
A45: 45785 | B45: 45785 | H45: =IFERROR(VLOOKUP(G45,Basic_Data!$E$2:$I$9,5,0),"") | I45: =IFERROR(VLOOKUP($G45,Basic_Data!$E$2:$H$10,4,0),"") | K45: =IFERROR(VLOOKUP($B45-1,Inverter_PR!$B:$I,Module_Cleaning!H45,0),"") | L45: =IFERROR(VLOOKUP($B45+1,Inverter_PR!$B:$I,Module_Cleaning!H45,0),"") | M45: =IFERROR(I45-J45,"") | N45: All module cleaned by rain
A46: 45786 | B46: 45786 | C46: 0 | D46: 0 | E46: 0 | F46: 0 | H46: =IFERROR(VLOOKUP(G46,Basic_Data!$E$2:$I$9,5,0),"") | I46: 0 | J46: 0 | K46: =IFERROR(VLOOKUP($B46-1,Inverter_PR!$B:$I,Module_Cleaning!H46,0),"") | L46: =IFERROR(VLOOKUP($B46+1,Inverter_PR!$B:$I,Module_Cleaning!H46,0),"") | M46: =IFERROR(I46-J46,"") -> 0 | N46: N0 cleaning
A47: 45787 | B47: 45787 | H47: =IFERROR(VLOOKUP(G47,Basic_Data!$E$2:$I$9,5,0),"") | I47: =IFERROR(VLOOKUP($G47,Basic_Data!$E$2:$H$10,4,0),"") | K47: =IFERROR(VLOOKUP($B47-1,Inverter_PR!$B:$I,Module_Cleaning!H47,0),"") | L47: =IFERROR(VLOOKUP($B47+1,Inverter_PR!$B:$I,Module_Cleaning!H47,0),"") | M47: =IFERROR(I47-J47,"") | N47: All module cleaned by rain
A48: 45788 | B48: 45788 | C48: 0 | D48: 0 | E48: 0 | F48: 0 | H48: =IFERROR(VLOOKUP(G48,Basic_Data!$E$2:$I$9,5,0),"") | I48: 0 | J48: 0 | K48: =IFERROR(VLOOKUP($B48-1,Inverter_PR!$B:$I,Module_Cleaning!H48,0),"") | L48: =IFERROR(VLOOKUP($B48+1,Inverter_PR!$B:$I,Module_Cleaning!H48,0),"") | M48: =IFERROR(I48-J48,"") -> 0 | N48: N0 cleaning
A49: 45789 | B49: 45789 | C49: 0 | D49: 0 | E49: 0 | F49: 0 | H49: =IFERROR(VLOOKUP(G49,Basic_Data!$E$2:$I$9,5,0),"") | I49: 0 | J49: 0 | K49: =IFERROR(VLOOKUP($B49-1,Inverter_PR!$B:$I,Module_Cleaning!H49,0),"") | L49: =IFERROR(VLOOKUP($B49+1,Inverter_PR!$B:$I,Module_Cleaning!H49,0),"") | M49: =IFERROR(I49-J49,"") -> 0 | N49: N0 cleaning
A50: 45790 | B50: 45790 | C50: 0 | D50: 0 | E50: 0 | F50: 0 | H50: =IFERROR(VLOOKUP(G50,Basic_Data!$E$2:$I$9,5,0),"") | I50: 0 | J50: 0 | K50: =IFERROR(VLOOKUP($B50-1,Inverter_PR!$B:$I,Module_Cleaning!H50,0),"") | L50: =IFERROR(VLOOKUP($B50+1,Inverter_PR!$B:$I,Module_Cleaning!H50,0),"") | M50: =IFERROR(I50-J50,"") -> 0 | N50: N0 cleaning
A51: 45791 | B51: 45791 | C51: 0 | D51: 0 | E51: 0 | F51: 0 | H51: =IFERROR(VLOOKUP(G51,Basic_Data!$E$2:$I$9,5,0),"") | I51: 0 | J51: 0 | K51: =IFERROR(VLOOKUP($B51-1,Inverter_PR!$B:$I,Module_Cleaning!H51,0),"") | L51: =IFERROR(VLOOKUP($B51+1,Inverter_PR!$B:$I,Module_Cleaning!H51,0),"") | M51: =IFERROR(I51-J51,"") -> 0 | N51: N0 cleaning
A52: 45792 | B52: 45792 | C52: 0 | D52: 0 | E52: 0 | F52: 0 | H52: =IFERROR(VLOOKUP(G52,Basic_Data!$E$2:$I$9,5,0),"") | I52: 0 | J52: 0 | K52: =IFERROR(VLOOKUP($B52-1,Inverter_PR!$B:$I,Module_Cleaning!H52,0),"") | L52: =IFERROR(VLOOKUP($B52+1,Inverter_PR!$B:$I,Module_Cleaning!H52,0),"") | M52: =IFERROR(I52-J52,"") -> 0 | N52: N0 cleaning
A53: 45793 | B53: 45793 | C53: 0 | D53: 0 | E53: 0 | F53: 0 | H53: =IFERROR(VLOOKUP(G53,Basic_Data!$E$2:$I$9,5,0),"") | I53: 0 | J53: 0 | K53: =IFERROR(VLOOKUP($B53-1,Inverter_PR!$B:$I,Module_Cleaning!H53,0),"") | L53: =IFERROR(VLOOKUP($B53+1,Inverter_PR!$B:$I,Module_Cleaning!H53,0),"") | M53: =IFERROR(I53-J53,"") -> 0 | N53: N0 cleaning
A54: 45794 | B54: 45794 | C54: 0 | D54: 0 | E54: 0 | F54: 0 | H54: =IFERROR(VLOOKUP(G54,Basic_Data!$E$2:$I$9,5,0),"") | I54: 0 | J54: 0 | K54: =IFERROR(VLOOKUP($B54-1,Inverter_PR!$B:$I,Module_Cleaning!H54,0),"") | L54: =IFERROR(VLOOKUP($B54+1,Inverter_PR!$B:$I,Module_Cleaning!H54,0),"") | M54: =IFERROR(I54-J54,"") -> 0 | N54: N0 cleaning
A55: 45795 | B55: 45795 | C55: 0 | D55: 0 | E55: 0 | F55: 0 | H55: =IFERROR(VLOOKUP(G55,Basic_Data!$E$2:$I$9,5,0),"") | I55: 0 | J55: 0 | K55: =IFERROR(VLOOKUP($B55-1,Inverter_PR!$B:$I,Module_Cleaning!H55,0),"") | L55: =IFERROR(VLOOKUP($B55+1,Inverter_PR!$B:$I,Module_Cleaning!H55,0),"") | M55: =IFERROR(I55-J55,"") -> 0 | N55: N0 cleaning
A56: 45796 | B56: 45796 | C56: 0 | D56: 0 | E56: 0 | F56: 0 | H56: =IFERROR(VLOOKUP(G56,Basic_Data!$E$2:$I$9,5,0),"") | I56: 0 | J56: 0 | K56: =IFERROR(VLOOKUP($B56-1,Inverter_PR!$B:$I,Module_Cleaning!H56,0),"") | L56: =IFERROR(VLOOKUP($B56+1,Inverter_PR!$B:$I,Module_Cleaning!H56,0),"") | M56: =IFERROR(I56-J56,"") -> 0 | N56: N0 cleaning
A57: 45797 | B57: 45797 | C57: 0 | D57: 0 | E57: 0 | F57: 0 | H57: =IFERROR(VLOOKUP(G57,Basic_Data!$E$2:$I$9,5,0),"") | I57: 0 | J57: 0 | K57: =IFERROR(VLOOKUP($B57-1,Inverter_PR!$B:$I,Module_Cleaning!H57,0),"") | L57: =IFERROR(VLOOKUP($B57+1,Inverter_PR!$B:$I,Module_Cleaning!H57,0),"") | M57: =IFERROR(I57-J57,"") -> 0 | N57: N0 cleaning
A58: 45798 | B58: 45798 | C58: 0 | D58: 0 | E58: 0 | F58: 0 | H58: =IFERROR(VLOOKUP(G58,Basic_Data!$E$2:$I$9,5,0),"") | I58: 0 | J58: 0 | K58: =IFERROR(VLOOKUP($B58-1,Inverter_PR!$B:$I,Module_Cleaning!H58,0),"") | L58: =IFERROR(VLOOKUP($B58+1,Inverter_PR!$B:$I,Module_Cleaning!H58,0),"") | M58: =IFERROR(I58-J58,"") -> 0 | N58: N0 cleaning
A59: 45799 | B59: 45799 | C59: 4 | D59: 4000 | F59: 1 | G59: Inv_1 | H59: =IFERROR(VLOOKUP(G59,Basic_Data!$E$2:$I$9,5,0),"") -> 2 | I59: =IFERROR(VLOOKUP($G59,Basic_Data!$E$2:$H$10,4,0),"") -> 616 | J59: 616 | K59: =IFERROR(VLOOKUP($B59-1,Inverter_PR!$B:$I,Module_Cleaning!H59,0),"") -> 0.95363569 | L59: =IFERROR(VLOOKUP($B59+1,Inverter_PR!$B:$I,Module_Cleaning!H59,0),"") -> 0.96591705 | M59: =IFERROR(I59-J59,"") -> 0 | N59: wet cleaning
A60: 45799 | B60: 45799 | F60: 1 | G60: Inv_2 | H60: 3 | I60: =IFERROR(VLOOKUP($G60,Basic_Data!$E$2:$H$10,4,0),"") -> 616 | J60: 616 | K60: =IFERROR(VLOOKUP($B60-1,Inverter_PR!$B:$I,Module_Cleaning!H60,0),"") -> 0.95578748 | L60: =IFERROR(VLOOKUP($B60+1,Inverter_PR!$B:$I,Module_Cleaning!H60,0),"") -> 0.96615177 | M60: =IFERROR(I60-J60,"") -> 0 | N60: wet cleaning
A61: 45799 | B61: 45799 | F61: 1 | G61: Inv_3 | H61: 4 | I61: =IFERROR(VLOOKUP($G61,Basic_Data!$E$2:$H$10,4,0),"") -> 616 | J61: 616 | K61: =IFERROR(VLOOKUP($B61-1,Inverter_PR!$B:$I,Module_Cleaning!H61,0),"") -> 0.94505674 | L61: =IFERROR(VLOOKUP($B61+1,Inverter_PR!$B:$I,Module_Cleaning!H61,0),"") -> 0.96432433 | M61: =IFERROR(I61-J61,"") -> 0 | N61: wet cleaning
A62: 45799 | B62: 45799 | F62: 1 | G62: Inv_4 | H62: 5 | I62: =IFERROR(VLOOKUP($G62,Basic_Data!$E$2:$H$10,4,0),"") -> 644 | J62: 644 | K62: =IFERROR(VLOOKUP($B62-1,Inverter_PR!$B:$I,Module_Cleaning!H62,0),"") -> 0.94939218 | L62: =IFERROR(VLOOKUP($B62+1,Inverter_PR!$B:$I,Module_Cleaning!H62,0),"") -> 0.96262761 | M62: =IFERROR(I62-J62,"") -> 0 | N62: wet cleaning
A63: 45800 | B63: 45800 | C63: 3 | D63: 3000 | E63: 0 | F63: 1 | G63: Inv_5 | H63: =IFERROR(VLOOKUP(G63,Basic_Data!$E$2:$I$9,5,0),"") -> 6 | I63: =IFERROR(VLOOKUP($G63,Basic_Data!$E$2:$H$10,4,0),"") -> 644 | J63: 644 | K63: =IFERROR(VLOOKUP($B63-1,Inverter_PR!$B:$I,Module_Cleaning!H63,0),"") -> 0.94283142 | L63: =IFERROR(VLOOKUP($B63+1,Inverter_PR!$B:$I,Module_Cleaning!H63,0),"") -> 0.98640221 | M63: =IFERROR(I63-J63,"") -> 0 | N63: wet cleaning
A64: 45800 | B64: 45800 | F64: 1 | G64: Inv_6 | H64: 7 | I64: =IFERROR(VLOOKUP($G64,Basic_Data!$E$2:$H$10,4,0),"") -> 644 | J64: 644 | K64: =IFERROR(VLOOKUP($B64-1,Inverter_PR!$B:$I,Module_Cleaning!H64,0),"") -> 0.94856135 | L64: =IFERROR(VLOOKUP($B64+1,Inverter_PR!$B:$I,Module_Cleaning!H64,0),"") -> 0.98930189 | M64: =IFERROR(I64-J64,"") -> 0 | N64: wet cleaning
A65: 45800 | B65: 45800 | F65: 1 | G65: Inv_7 | H65: 8 | I65: =IFERROR(VLOOKUP($G65,Basic_Data!$E$2:$H$10,4,0),"") -> 644 | J65: 644 | K65: =IFERROR(VLOOKUP($B65-1,Inverter_PR!$B:$I,Module_Cleaning!H65,0),"") -> 0.94577012 | L65: =IFERROR(VLOOKUP($B65+1,Inverter_PR!$B:$I,Module_Cleaning!H65,0),"") -> 0.99159032 | N65: wet cleaning
A66: 45801 | B66: 45801 | C66: 0 | D66: 0 | E66: 0 | F66: 0 | H66: =IFERROR(VLOOKUP(G66,Basic_Data!$E$2:$I$9,5,0),"") | I66: 0 | J66: 0 | K66: =IFERROR(VLOOKUP($B66-1,Inverter_PR!$B:$I,Module_Cleaning!H66,0),"") | L66: =IFERROR(VLOOKUP($B66+1,Inverter_PR!$B:$I,Module_Cleaning!H66,0),"") | M66: =IFERROR(I66-J66,"") -> 0 | N66: N0 cleaning
A67: 45802 | B67: 45802 | C67: 0 | D67: 0 | E67: 0 | F67: 0 | H67: =IFERROR(VLOOKUP(G67,Basic_Data!$E$2:$I$9,5,0),"") | I67: 0 | J67: 0 | K67: =IFERROR(VLOOKUP($B67-1,Inverter_PR!$B:$I,Module_Cleaning!H67,0),"") | L67: =IFERROR(VLOOKUP($B67+1,Inverter_PR!$B:$I,Module_Cleaning!H67,0),"") | M67: =IFERROR(I67-J67,"") -> 0 | N67: N0 cleaning
A68: 45803 | B68: 45803 | C68: 0 | D68: 0 | E68: 0 | F68: 0 | H68: =IFERROR(VLOOKUP(G68,Basic_Data!$E$2:$I$9,5,0),"") | I68: 0 | J68: 0 | K68: =IFERROR(VLOOKUP($B68-1,Inverter_PR!$B:$I,Module_Cleaning!H68,0),"") | L68: =IFERROR(VLOOKUP($B68+1,Inverter_PR!$B:$I,Module_Cleaning!H68,0),"") | M68: =IFERROR(I68-J68,"") -> 0 | N68: N0 cleaning
A69: 45804 | B69: 45804 | C69: 0 | D69: 0 | E69: 0 | F69: 0 | H69: =IFERROR(VLOOKUP(G69,Basic_Data!$E$2:$I$9,5,0),"") | I69: 0 | J69: 0 | K69: =IFERROR(VLOOKUP($B69-1,Inverter_PR!$B:$I,Module_Cleaning!H69,0),"") | L69: =IFERROR(VLOOKUP($B69+1,Inverter_PR!$B:$I,Module_Cleaning!H69,0),"") | M69: =IFERROR(I69-J69,"") -> 0 | N69: N0 cleaning
A70: 45805 | B70: 45805 | C70: 0 | D70: 0 | E70: 0 | F70: 0 | H70: =IFERROR(VLOOKUP(G70,Basic_Data!$E$2:$I$9,5,0),"") | I70: 0 | J70: 0 | K70: =IFERROR(VLOOKUP($B70-1,Inverter_PR!$B:$I,Module_Cleaning!H70,0),"") | L70: =IFERROR(VLOOKUP($B70+1,Inverter_PR!$B:$I,Module_Cleaning!H70,0),"") | M70: =IFERROR(I70-J70,"") -> 0 | N70: N0 cleaning
A71: 45806 | B71: 45806 | C71: 0 | D71: 0 | E71: 0 | F71: 0 | H71: =IFERROR(VLOOKUP(G71,Basic_Data!$E$2:$I$9,5,0),"") | I71: 0 | J71: 0 | K71: =IFERROR(VLOOKUP($B71-1,Inverter_PR!$B:$I,Module_Cleaning!H71,0),"") | L71: =IFERROR(VLOOKUP($B71+1,Inverter_PR!$B:$I,Module_Cleaning!H71,0),"") | M71: =IFERROR(I71-J71,"") -> 0 | N71: N0 cleaning
A72: 45807 | B72: 45807 | C72: 0 | D72: 0 | E72: 0 | F72: 0 | H72: =IFERROR(VLOOKUP(G72,Basic_Data!$E$2:$I$9,5,0),"") | I72: 0 | J72: 0 | K72: =IFERROR(VLOOKUP($B72-1,Inverter_PR!$B:$I,Module_Cleaning!H72,0),"") | L72: =IFERROR(VLOOKUP($B72+1,Inverter_PR!$B:$I,Module_Cleaning!H72,0),"") | M72: =IFERROR(I72-J72,"") -> 0 | N72: N0 cleaning
A73: 45808 | B73: 45808 | C73: 0 | D73: 0 | E73: 0 | F73: 0 | H73: =IFERROR(VLOOKUP(G73,Basic_Data!$E$2:$I$9,5,0),"") | I73: 0 | J73: 0 | K73: =IFERROR(VLOOKUP($B73-1,Inverter_PR!$B:$I,Module_Cleaning!H73,0),"") | L73: =IFERROR(VLOOKUP($B73+1,Inverter_PR!$B:$I,Module_Cleaning!H73,0),"") | M73: =IFERROR(I73-J73,"") -> 0 | N73: N0 cleaning
A74: 45809 | B74: 45809 | C74: 0 | D74: 0 | E74: 0 | F74: 0 | H74: =IFERROR(VLOOKUP(G74,Basic_Data!$E$2:$I$9,5,0),"") | I74: 0 | J74: 0 | K74: =IFERROR(VLOOKUP($B74-1,Inverter_PR!$B:$I,Module_Cleaning!H74,0),"") | L74: =IFERROR(VLOOKUP($B74+1,Inverter_PR!$B:$I,Module_Cleaning!H74,0),"") | M74: =IFERROR(I74-J74,"") -> 0 | N74: N0 cleaning
A75: 45810 | B75: 45810 | C75: 0 | D75: 0 | E75: 0 | F75: 0 | H75: =IFERROR(VLOOKUP(G75,Basic_Data!$E$2:$I$9,5,0),"") | I75: 0 | J75: 0 | K75: =IFERROR(VLOOKUP($B75-1,Inverter_PR!$B:$I,Module_Cleaning!H75,0),"") | L75: =IFERROR(VLOOKUP($B75+1,Inverter_PR!$B:$I,Module_Cleaning!H75,0),"") | M75: =IFERROR(I75-J75,"") -> 0 | N75: N0 cleaning
A76: 45811 | B76: 45811 | C76: 0 | D76: 0 | E76: 0 | F76: 0 | H76: =IFERROR(VLOOKUP(G76,Basic_Data!$E$2:$I$9,5,0),"") | I76: 0 | J76: 0 | K76: =IFERROR(VLOOKUP($B76-1,Inverter_PR!$B:$I,Module_Cleaning!H76,0),"") | L76: =IFERROR(VLOOKUP($B76+1,Inverter_PR!$B:$I,Module_Cleaning!H76,0),"") | M76: =IFERROR(I76-J76,"") -> 0 | N76: N0 cleaning
A77: 45812 | B77: 45812 | C77: 0 | D77: 0 | E77: 0 | F77: 0 | H77: =IFERROR(VLOOKUP(G77,Basic_Data!$E$2:$I$9,5,0),"") | I77: 0 | J77: 0 | K77: =IFERROR(VLOOKUP($B77-1,Inverter_PR!$B:$I,Module_Cleaning!H77,0),"") | L77: =IFERROR(VLOOKUP($B77+1,Inverter_PR!$B:$I,Module_Cleaning!H77,0),"") | M77: =IFERROR(I77-J77,"") -> 0 | N77: N0 cleaning
... A83: 45818 | B83: 45818 | C83: 0 | D83: 0 | E83: 0 | F83: 0 | H83: =IFERROR(VLOOKUP(G83,Basic_Data!$E$2:$I$9,5,0),"") | I83: 0 | J83: 0 | K83: =IFERROR(VLOOKUP($B83-1,Inverter_PR!$B:$I,Module_Cleaning!H83,0),"") | L83: =IFERROR(VLOOKUP($B83+1,Inverter_PR!$B:$I,Module_Cleaning!H83,0),"") | M83: =IFERROR(I83-J83,"") -> 0 | N83: N0 cleaning
A84: 45819 | B84: 45819 | C84: 3 | D84: 6000 | F84: 2 | G84: Inv_1 | H84: 2 | I84: 616 | J84: 616 | K84: 1.0588069 | L84: =IFERROR(VLOOKUP($B84+1,Inverter_PR!$B:$I,Module_Cleaning!H84,0),"") -> 0.97229545 | M84: 0 | N84: wet cleaning
A85: 45819 | B85: 45819 | F85: 2 | G85: Inv_2 | H85: 3 | I85: =IFERROR(VLOOKUP($G85,Basic_Data!$E$2:$H$10,4,0),"") -> 616 | J85: 616 | K85: =IFERROR(VLOOKUP($B85-1,Inverter_PR!$B:$I,Module_Cleaning!H85,0),"") -> 1.0366603 | L85: =IFERROR(VLOOKUP($B85+1,Inverter_PR!$B:$I,Module_Cleaning!H85,0),"") -> 1.0024862 | M85: 0 | N85: wet cleaning
A86: 45819 | B86: 45819 | F86: 2 | G86: Inv_3 | H86: 4 | I86: =IFERROR(VLOOKUP($G86,Basic_Data!$E$2:$H$10,4,0),"") -> 616 | J86: 616 | K86: =IFERROR(VLOOKUP($B86-1,Inverter_PR!$B:$I,Module_Cleaning!H86,0),"") -> 1.0358951 | L86: =IFERROR(VLOOKUP($B86+1,Inverter_PR!$B:$I,Module_Cleaning!H86,0),"") -> 0.96978106 | M86: 0 | N86: wet cleaning
A87: 45819 | B87: 45819 | F87: 2 | G87: Inv_4 | H87: 5 | I87: =IFERROR(VLOOKUP($G87,Basic_Data!$E$2:$H$10,4,0),"") -> 644 | J87: 644 | K87: =IFERROR(VLOOKUP($B87-1,Inverter_PR!$B:$I,Module_Cleaning!H87,0),"") -> 1.0411249 | L87: =IFERROR(VLOOKUP($B87+1,Inverter_PR!$B:$I,Module_Cleaning!H87,0),"") -> 0.99420293 | M87: 0 | N87: wet cleaning
A88: 45799 | B88: 45820 | C88: 3 | D88: 5000 | F88: 2 | G88: Inv_5 | H88: 6 | I88: 644 | J88: 644 | K88: =IFERROR(VLOOKUP($B88-1,Inverter_PR!$B:$I,Module_Cleaning!H88,0),"") -> 0.99707059 | L88: =IFERROR(VLOOKUP($B88+1,Inverter_PR!$B:$I,Module_Cleaning!H88,0),"") -> 0.96970822 | M88: 0 | N88: wet cleaning
A89: 45799 | B89: 45820 | F89: 2 | G89: Inv_6 | H89: 7 | I89: 644 | J89: 644 | K89: =IFERROR(VLOOKUP($B89-1,Inverter_PR!$B:$I,Module_Cleaning!H89,0),"") -> 1.0271044 | L89: =IFERROR(VLOOKUP($B89+1,Inverter_PR!$B:$I,Module_Cleaning!H89,0),"") -> 0.97454942 | M89: 0 | N89: wet cleaning
A90: 45799 | B90: 45820 | F90: 2 | G90: Inv_7 | H90: 8 | I90: 644 | J90: 644 | K90: =IFERROR(VLOOKUP($B90-1,Inverter_PR!$B:$I,Module_Cleaning!H90,0),"") -> 1.0909819 | L90: =IFERROR(VLOOKUP($B90+1,Inverter_PR!$B:$I,Module_Cleaning!H90,0),"") -> 0.97450973 | M90: 0 | N90: wet cleaning
A91: 45821 | B91: 45821 | C91: 0 | D91: 0 | E91: 0 | F91: 0 | H91: =IFERROR(VLOOKUP(G91,Basic_Data!$E$2:$I$9,5,0),"") | I91: 0 | J91: 0 | K91: 0 | L91: 0 | M91: =IFERROR(I91-J91,"") -> 0 | N91: N0 cleaning
A92: 45822 | B92: 45822 | C92: 0 | D92: 0 | E92: 0 | F92: 0 | H92: =IFERROR(VLOOKUP(G92,Basic_Data!$E$2:$I$9,5,0),"") | I92: 0 | J92: 0 | K92: 0 | L92: 0 | M92: =IFERROR(I92-J92,"") -> 0 | N92: N0 cleaning
A93: 45823 | B93: 45823 | C93: 0 | D93: 0 | E93: 0 | F93: 0 | H93: =IFERROR(VLOOKUP(G93,Basic_Data!$E$2:$I$9,5,0),"") | I93: 0 | J93: 0 | K93: 0 | L93: 0 | M93: =IFERROR(I93-J93,"") -> 0 | N93: All module cleaned by rain
A94: 45824 | B94: 45824 | C94: 0 | D94: 0 | E94: 0 | F94: 0 | H94: =IFERROR(VLOOKUP(G94,Basic_Data!$E$2:$I$9,5,0),"") | I94: 0 | J94: 0 | K94: 0 | L94: 0 | M94: =IFERROR(I94-J94,"") -> 0 | N94: All module cleaned by rain
A95: 45825 | B95: 45825 | C95: 0 | D95: 0 | E95: 0 | F95: 0 | H95: =IFERROR(VLOOKUP(G95,Basic_Data!$E$2:$I$9,5,0),"") | I95: 0 | J95: 0 | K95: 0 | L95: 0 | M95: =IFERROR(I95-J95,"") -> 0 | N95: All module cleaned by rain
A96: 45826 | B96: 45826 | C96: 0 | D96: 0 | E96: 0 | F96: 0 | H96: =IFERROR(VLOOKUP(G96,Basic_Data!$E$2:$I$9,5,0),"") | I96: 0 | J96: 0 | K96: 0 | L96: 0 | M96: =IFERROR(I96-J96,"") -> 0 | N96: N0 cleaning
A97: 45827 | B97: 45827 | C97: 0 | D97: 0 | E97: 0 | F97: 0 | H97: =IFERROR(VLOOKUP(G97,Basic_Data!$E$2:$I$9,5,0),"") | I97: 0 | J97: 0 | K97: 0 | L97: 0 | M97: =IFERROR(I97-J97,"") -> 0 | N97: N0 cleaning
A98: 45828 | B98: 45828 | C98: 0 | D98: 0 | E98: 0 | F98: 0 | H98: =IFERROR(VLOOKUP(G98,Basic_Data!$E$2:$I$9,5,0),"") | I98: 0 | J98: 0 | K98: 0 | L98: 0 | M98: =IFERROR(I98-J98,"") -> 0 | N98: N0 cleaning
A99: 45829 | B99: 45829 | C99: 0 | D99: 0 | E99: 0 | F99: 0 | H99: =IFERROR(VLOOKUP(G99,Basic_Data!$E$2:$I$9,5,0),"") | I99: 0 | J99: 0 | K99: 0 | L99: 0 | M99: =IFERROR(I99-J99,"") -> 0 | N99: N0 cleaning
A100: 45830 | B100: 45830 | C100: 0 | D100: 0 | E100: 0 | F100: 0 | H100: =IFERROR(VLOOKUP(G100,Basic_Data!$E$2:$I$9,5,0),"") | I100: 0 | J100: 0 | K100: 0 | L100: 0 | M100: =IFERROR(I100-J100,"") -> 0 | N100: All module cleaned by rain
A101: 45831 | B101: 45831 | C101: 0 | D101: 0 | E101: 0 | F101: 0 | H101: =IFERROR(VLOOKUP(G101,Basic_Data!$E$2:$I$9,5,0),"") | I101: 0 | J101: 0 | K101: 0 | L101: 0 | M101: =IFERROR(I101-J101,"") -> 0 | N101: All module cleaned by rain
A102: 45832 | B102: 45832 | C102: 0 | D102: 0 | E102: 0 | F102: 0 | H102: =IFERROR(VLOOKUP(G102,Basic_Data!$E$2:$I$9,5,0),"") | I102: 0 | J102: 0 | K102: 0 | L102: 0 | M102: =IFERROR(I102-J102,"") -> 0 | N102: All module cleaned by rain
... A150: 45880 | B150: 45880 | C150: 0 | D150: 0 | E150: 0 | F150: 0 | H150: =IFERROR(VLOOKUP(G150,Basic_Data!$E$2:$I$9,5,0),"") | I150: 0 | J150: 0 | K150: 0 | L150: 0 | M150: =IFERROR(I150-J150,"") -> 0 | N150: All module cleaned by rain
A151: 45881 | B151: 45881 | D151: 0 | E151: 0 | F151: 0 | H151: =IFERROR(VLOOKUP(G151,Basic_Data!$E$2:$I$9,5,0),"") | I151: 0 | J151: 0 | K151: 0 | L151: 0 | M151: =IFERROR(I151-J151,"") -> 0 | N151: N0 cleaning
A152: 45882 | B152: 45882 | D152: 0 | E152: 0 | F152: 0 | H152: =IFERROR(VLOOKUP(G152,Basic_Data!$E$2:$I$9,5,0),"") | I152: 0 | J152: 0 | K152: 0 | L152: 0 | M152: =IFERROR(I152-J152,"") -> 0 | N152: All module cleaned by rain
A153: 45883 | B153: 45883 | D153: 0 | E153: 0 | F153: 0 | H153: =IFERROR(VLOOKUP(G153,Basic_Data!$E$2:$I$9,5,0),"") | I153: 0 | J153: 0 | K153: 0 | L153: 0 | M153: =IFERROR(I153-J153,"") -> 0 | N153: All module cleaned by rain
...

Sheet WMS
A1: Months | B1: Date | C1: GHI | D1: GTI | E1: Module_Temp | F1: Amb_Temp | G1: Derect_Irr | H1: Diffused_Irr | I1: Wind_Speed | J1: Wind_derection | K1: Rain Gauge
A2: 45747 | B2: 45747
A3: 45748 | B3: 45748
A4: 45749 | B4: 45749
A5: 45750 | B5: 45750
A6: 45751 | B6: 45751
A7: 45752 | B7: 45752
A8: 45753 | B8: 45753
A9: 45754 | B9: 45754
A10: 45755 | B10: 45755
A11: 45756 | B11: 45756
A12: 45757 | B12: 45757 | D12: 5.55
A13: 45758 | B13: 45758 | D13: 5.45
A14: 45759 | B14: 45759 | D14: 5.82
A15: 45760 | B15: 45760 | D15: 5.82
A16: 45761 | B16: 45761 | D16: 5.75
A17: 45762 | B17: 45762 | D17: 5.78
A18: 45763 | B18: 45763 | D18: 5.39 | F18: 32.04
A19: 45764 | B19: 45764
A20: 45765 | B20: 45765 | D20: 5.74
A21: 45766 | B21: 45766 | D21: 5.79
A22: 45767 | B22: 45767 | D22: 5.79 | F22: 32.54
A23: 45768 | B23: 45768 | D23: 5.62 | F23: 33.86
A24: 45769 | B24: 45769 | D24: 5.69 | F24: 35.88
A25: 45770 | B25: 45770 | D25: 5.01 | F25: 35.88
A26: 45771 | B26: 45771 | D26: 5.26 | F26: 32.75
A27: 45772 | B27: 45772 | D27: 5.61 | F27: 31.86
A28: 45773 | B28: 45773 | D28: 5.68 | F28: 32.49
A29: 45774 | B29: 45774 | D29: 5.77 | F29: 33.49
A30: 45775 | B30: 45775 | D30: 5.74 | F30: 34.14
A31: 45776 | B31: 45776 | D31: 5.55 | F31: 37.01
A32: 45777 | B32: 45777 | D32: 5.7 | F32: 33.92
A33: 45778 | B33: 45778 | D33: 5.76 | F33: 34.66
... A44: 45789 | B44: 45789 | D44: 5.08 | F44: 31.8
A45: 45790 | B45: 45790
A46: 45791 | B46: 45791
A47: 45792 | B47: 45792
A48: 45793 | B48: 45793 | D48: 5.35 | F48: 32.48
A49: 45794 | B49: 45794 | D49: 5.2 | F49: 32.71
A50: 45795 | B50: 45795 | D50: 5.65 | F50: 33.94
A51: 45796 | B51: 45796 | D51: 5.43 | F51: 36
A52: 45797 | B52: 45797 | D52: 5.61 | F52: 36
A53: 45798 | B53: 45798 | D53: 3.17 | F53: 36
A54: 45799 | B54: 45799 | D54: 5.41 | F54: 36
A55: 45800 | B55: 45800 | D55: 5.33 | F55: 36
A56: 45801 | B56: 45801 | D56: 6.24 | F56: 33.38
A57: 45802 | B57: 45802 | D57: 5.61 | F57: 33.64
A58: 45803 | B58: 45803 | D58: 4.33 | F58: 30
A59: 45804 | B59: 45804 | D59: 2.58 | F59: 30
... A143: 45888 | B143: 45888 | D143: 1.5 | F143: 0
A144: 45889 | B144: 45889
A145: 45890 | B145: 45890
A146: 45891 | B146: 45891
A147: 45892 | B147: 45892
A148: 45893 | B148: 45893
A149: 45894 | B149: 45894
A150: 45895 | B150: 45895
A151: 45896 | B151: 45896
A152: 45897 | B152: 45897
A153: 45898 | B153: 45898
A154: 45899 | B154: 45899
A155: 45900 | B155: 45900
... A177: 45922 | B177: 45922
A178: 45923 | B178: 45923 | D178: 3.65 | E178: 30.41
A179: 45924 | B179: 45924 | D179: 2.06 | E179: 0
A180: 45925 | B180: 45925 | D180: 4.11 | E180: 0
A181: 45926 | B181: 45926 | D181: 4.82 | E181: 0
A182: 45927 | B182: 45927 | D182: 3.86 | E182: 0
A183: 45928 | B183: 45928 | D183: 1.75 | E183: 0
A184: 45929 | B184: 45929 | D184: 1.5
A185: 45930 | B185: 45930 | D185: 1.23
A186: 45931 | B186: 45931
A187: 45932 | B187: 45932
A188: 45933 | B188: 45933 | D188: 4.33 | E188: 0
A189: 45934 | B189: 45934 | D189: 5.15 | E189: 0
A190: 45935 | B190: 45935 | D190: 4.6 | E190: 0
A191: 45936 | B191: 45936 | D191: 4.83 | E191: 0
A192: 45937 | B192: 45937 | D192: 5.09 | E192: 0
A193: 45938 | B193: 45938 | D193: 4.85 | E193: 0
A194: 45939 | B194: 45939 | D194: 4.95 | E194: 0
A195: 45940 | B195: 45940 | D195: 3.92 | E195: 0
A196: 45941 | B196: 45941 | D196: 3.47 | E196: 0
A197: 45942 | B197: 45942 | D197: 3.56 | E197: 0
A198: 45943 | B198: 45943 | D198: 3.54 | E198: 0
A199: 45944 | B199: 45944 | D199: 3.55 | E199: 0
... A261: 46006 | B261: 46006 | D261: 4.01 | E261: 31
A262: 46007 | B262: 46007 | D262: 3.7
A263: 46008 | B263: 46008 | D263: 3.62
A264: 46009 | B264: 46009 | D264: 3.73
A265: 46010 | B265: 46010 | D265: 4.11
A266: 46011 | B266: 46011 | D266: 4.1
A267: 46012 | B267: 46012 | D267: 3.4
A268: 46013 | B268: 46013 | D268: 3.82
A269: 46014 | B269: 46014 | D269: 3.85 | E269: 26.75
A270: 46015 | B270: 46015 | D270: 3.91 | E270: 26.53
A271: 46016 | B271: 46016 | D271: 3.88 | E271: 26.07
A272: 46017 | B272: 46017 | D272: 3.74 | E272: 25.41
A273: 46018 | B273: 46018 | D273: 3.61 | E273: 25.97
A274: 46019 | B274: 46019 | D274: 3.63 | E274: 27.07
A275: 46020 | B275: 46020 | D275: 3.61 | E275: 26.9
...

Sheet Plant  Availiblity
A2: Date | B2: ABT Export Gen | C2: Total inevrter off | D2: GHI | E2: CUF% | F2: Out | G2: In | H2: Total Minute | I2: Outage Hrs. | J2: Plant Capacity | K2: Outage Capacity | L2: Plant Capacity Ratio | M2: Outage Ratio | N2: Plant Availiblity | O2: PA.C CUF | P2: total curtailment | Q2: P.A.C Generation | R2: PA Unit Lose
A3: 45839 | B3: =Data_Entry!T94 -> 8220 | C3: 0 | D3: =Data_Entry!V94 -> 3.07 | E3: =B3/(24*J3) -> 0.14205724 | F3: 0 | G3: 0 | H3: =(G3-F3)*24*60 -> 0 | I3: =H3/60 -> 0 | J3: 2411 | L3: =J3*12 -> 28932 | M3: =K3*I3 -> 0 | N3: =(L3-M3)/L3 -> 1 | O3: =E3/N3 -> 0.14205724 | Q3: =O3*J3*24 -> 8220 | R3: =Q3-B3 -> 0
A4: 45840 | B4: =Data_Entry!T95 -> 6720 | C4: 0 | D4: =Data_Entry!V95 -> 2.41 | E4: =B4/(24*J4) -> 0.11613438 | F4: 0 | G4: 0 | H4: =(G4-F4)*24*60 -> 0 | I4: =H4/60 -> 0 | J4: 2411 | L4: =J4*12 -> 28932 | M4: =K4*I4 -> 0 | N4: =(L4-M4)/L4 -> 1 | O4: =E4/N4 -> 0.11613438 | Q4: =O4*J4*24 -> 6720 | R4: =Q4-B4 -> 0
A5: 45841 | B5: =Data_Entry!T96 -> 1890 | C5: 0 | D5: =Data_Entry!V96 -> 0.41 | E5: =B5/(24*J5) -> 0.032662796 | F5: 0 | G5: 0 | H5: =(G5-F5)*24*60 -> 0 | I5: =H5/60 -> 0 | J5: 2411 | L5: =J5*12 -> 28932 | M5: =K5*I5 -> 0 | N5: =(L5-M5)/L5 -> 1 | O5: =E5/N5 -> 0.032662796 | Q5: =O5*J5*24 -> 1890 | R5: =Q5-B5 -> 0
A6: 45842 | B6: =Data_Entry!T97 -> 5520 | C6: 0 | D6: =Data_Entry!V97 -> 0.86 | E6: =B6/(24*J6) -> 0.095396101 | F6: 0 | G6: 0 | H6: =(G6-F6)*24*60 -> 0 | I6: =H6/60 -> 0 | J6: 2411 | L6: =J6*12 -> 28932 | M6: =K6*I6 -> 0 | N6: =(L6-M6)/L6 -> 1 | O6: =E6/N6 -> 0.095396101 | Q6: =O6*J6*24 -> 5520 | R6: =Q6-B6 -> 0
A7: 45843 | B7: =Data_Entry!T98 -> 5250 | C7: 0 | D7: =Data_Entry!V98 -> 1.08 | E7: =B7/(24*J7) -> 0.090729988 | F7: 0 | G7: 0 | H7: =(G7-F7)*24*60 -> 0 | I7: =H7/60 -> 0 | J7: 2411 | L7: =J7*12 -> 28932 | M7: =K7*I7 -> 0 | N7: =(L7-M7)/L7 -> 1 | O7: =E7/N7 -> 0.090729988 | Q7: =O7*J7*24 -> 5250 | R7: =Q7-B7 -> 0
A8: 45844 | B8: =Data_Entry!T99 -> 6690 | C8: 0 | D8: =Data_Entry!V99 -> 0.48 | E8: =B8/(24*J8) -> 0.11561593 | F8: 0 | G8: 0 | H8: =(G8-F8)*24*60 -> 0 | I8: =H8/60 -> 0 | J8: 2411 | L8: =J8*12 -> 28932 | M8: =K8*I8 -> 0 | N8: =(L8-M8)/L8 -> 1 | O8: =E8/N8 -> 0.11561593 | Q8: =O8*J8*24 -> 6690 | R8: =Q8-B8 -> 0
A9: 45845 | B9: =Data_Entry!T100 -> 3720 | C9: 0 | D9: =Data_Entry!V100 -> 0.27 | E9: =B9/(24*J9) -> 0.064288677 | F9: 0 | G9: 0 | H9: =(G9-F9)*24*60 -> 0 | I9: =H9/60 -> 0 | J9: 2411 | L9: =J9*12 -> 28932 | M9: =K9*I9 -> 0 | N9: =(L9-M9)/L9 -> 1 | O9: =E9/N9 -> 0.064288677 | Q9: =O9*J9*24 -> 3720 | R9: =Q9-B9 -> 0
A10: 45846 | B10: =Data_Entry!T101 -> 7350 | C10: 0 | D10: =Data_Entry!V101 -> 0.36 | E10: =B10/(24*J10) -> 0.12702198 | F10: 0 | G10: 0 | H10: =(G10-F10)*24*60 -> 0 | I10: =H10/60 -> 0 | J10: 2411 | L10: =J10*12 -> 28932 | M10: =K10*I10 -> 0 | N10: =(L10-M10)/L10 -> 1 | O10: =E10/N10 -> 0.12702198 | Q10: =O10*J10*24 -> 7350 | R10: =Q10-B10 -> 0
A11: 45847 | B11: =Data_Entry!T102 -> 10980 | C11: 0 | D11: =Data_Entry!V102 -> 0 | E11: =B11/(24*J11) -> 0.18975529 | F11: 0 | G11: 0 | H11: =(G11-F11)*24*60 -> 0 | I11: =H11/60 -> 0 | J11: 2411 | L11: =J11*12 -> 28932 | M11: =K11*I11 -> 0 | N11: =(L11-M11)/L11 -> 1 | O11: =E11/N11 -> 0.18975529 | Q11: =O11*J11*24 -> 10980 | R11: =Q11-B11 -> 0
A12: 45848 | B12: =Data_Entry!T103 -> 9870 | C12: 0 | D12: =Data_Entry!V103 -> 0 | E12: =B12/(24*J12) -> 0.17057238 | F12: 0 | G12: 0 | H12: =(G12-F12)*24*60 -> 0 | I12: =H12/60 -> 0 | J12: 2411 | L12: =J12*12 -> 28932 | M12: =K12*I12 -> 0 | N12: =(L12-M12)/L12 -> 1 | O12: =E12/N12 -> 0.17057238 | Q12: =O12*J12*24 -> 9870 | R12: =Q12-B12 -> 0
A13: 45849 | B13: =Data_Entry!T104 -> 6810 | C13: 0 | D13: =Data_Entry!V104 -> 1.61 | E13: =B13/(24*J13) -> 0.11768976 | F13: 0 | G13: 0 | H13: =(G13-F13)*24*60 -> 0 | I13: =H13/60 -> 0 | J13: 2411 | L13: =J13*12 -> 28932 | M13: =K13*I13 -> 0 | N13: =(L13-M13)/L13 -> 1 | O13: =E13/N13 -> 0.11768976 | Q13: =O13*J13*24 -> 6810 | R13: =Q13-B13 -> 0
A14: 45850 | B14: =Data_Entry!T105 -> 8340 | C14: 0 | D14: =Data_Entry!V105 -> 3.27 | E14: =B14/(24*J14) -> 0.14413107 | F14: 0 | G14: 0 | H14: =(G14-F14)*24*60 -> 0 | I14: =H14/60 -> 0 | J14: 2411 | L14: =J14*12 -> 28932 | M14: =K14*I14 -> 0 | N14: =(L14-M14)/L14 -> 1 | O14: =E14/N14 -> 0.14413107 | Q14: =O14*J14*24 -> 8340 | R14: =Q14-B14 -> 0
... A33: 45869 | B33: =Data_Entry!T124 -> 6000 | C33: 0 | D33: =Data_Entry!V124 -> 2.26 | E33: =B33/(24*J33) -> 0.10369141 | F33: 0 | G33: 0 | H33: =(G33-F33)*24*60 -> 0 | I33: =H33/60 -> 0 | J33: 2411 | L33: =J33*12 -> 28932 | M33: =K33*I33 -> 0 | N33: =(L33-M33)/L33 -> 1 | O33: =E33/N33 -> 0.10369141 | Q33: =O33*J33*24 -> 6000 | R33: =Q33-B33 -> 0
A35: 45870 | B35: =Data_Entry!T125 -> 7170 | C35: 0 | D35: =Data_Entry!V125 -> 3.01 | E35: =B35/(24*J35) -> 0.12391124 | F35: 0 | G35: 0 | H35: =(G35-F35)*24*60 -> 0 | I35: =H35/60 -> 0 | J35: 2411 | L35: =J35*12 -> 28932 | M35: =K35*I35 -> 0 | N35: =(L35-M35)/L35 -> 1 | O35: =E35/N35 -> 0.12391124 | Q35: =O35*J35*24 -> 7170 | R35: =Q35-B35 -> 0
A36: 45871 | B36: =Data_Entry!T126 -> 7620 | C36: 0 | D36: =Data_Entry!V126 -> 3.38 | E36: =B36/(24*J36) -> 0.1316881 | F36: 0 | G36: 0 | H36: =(G36-F36)*24*60 -> 0 | I36: =H36/60 -> 0 | J36: 2411 | L36: =J36*12 -> 28932 | M36: =K36*I36 -> 0 | N36: =(L36-M36)/L36 -> 1 | O36: =E36/N36 -> 0.1316881 | Q36: =O36*J36*24 -> 7620 | R36: =Q36-B36 -> 0
A37: 45872 | B37: =Data_Entry!T127 -> 7500 | C37: 0 | D37: =Data_Entry!V127 -> 3.8 | E37: =B37/(24*J37) -> 0.12961427 | F37: 0 | G37: 0 | H37: =(G37-F37)*24*60 -> 0 | I37: =H37/60 -> 0 | J37: 2411 | L37: =J37*12 -> 28932 | M37: =K37*I37 -> 0 | N37: =(L37-M37)/L37 -> 1 | O37: =E37/N37 -> 0.12961427 | Q37: =O37*J37*24 -> 7500 | R37: =Q37-B37 -> 0
A38: 45873 | B38: =Data_Entry!T128 -> 8730 | C38: 0 | D38: =Data_Entry!V128 -> 3.85 | E38: =B38/(24*J38) -> 0.15087101 | F38: 0 | G38: 0 | H38: =(G38-F38)*24*60 -> 0 | I38: =H38/60 -> 0 | J38: 2411 | L38: =J38*12 -> 28932 | M38: =K38*I38 -> 0 | N38: =(L38-M38)/L38 -> 1 | O38: =E38/N38 -> 0.15087101 | Q38: =O38*J38*24 -> 8730 | R38: =Q38-B38 -> 0
A39: 45874 | B39: =Data_Entry!T129 -> 9660 | C39: 0 | D39: =Data_Entry!V129 -> 3.78 | E39: =B39/(24*J39) -> 0.16694318 | F39: 0 | G39: 0 | H39: =(G39-F39)*24*60 -> 0 | I39: =H39/60 -> 0 | J39: 2411 | L39: =J39*12 -> 28932 | M39: =K39*I39 -> 0 | N39: =(L39-M39)/L39 -> 1 | O39: =E39/N39 -> 0.16694318 | Q39: =O39*J39*24 -> 9660 | R39: =Q39-B39 -> 0
A40: 45875 | B40: =Data_Entry!T130 -> 7980 | C40: 7 | D40: =Data_Entry!V130 -> 3.68 | E40: =B40/(24*J40) -> 0.13790958 | F40: 0.46527778 | G40: 0.49236111 | H40: =(G40-F40)*24*60 -> 39 | I40: =H40/60 -> 0.65 | J40: 2411 | K40: 2411 | L40: =J40*12 -> 28932 | M40: =K40*I40 -> 1567.15 | N40: =(L40-M40)/L40 -> 0.94583333 | O40: =E40/N40 -> 0.14580749 | Q40: =O40*J40*24 -> 8437.0044 | R40: =Q40-B40 -> 457.00441
A41: 45876 | B41: =Data_Entry!T131 -> 8850 | C41: 7 | D41: =Data_Entry!V131 -> 3.3 | E41: =B41/(24*J41) -> 0.15294484 | F41: 0.59027778 | G41: 0.6375 | H41: =(G41-F41)*24*60 -> 68 | I41: =H41/60 -> 1.1333333 | J41: 2411 | K41: 2411 | L41: =J41*12 -> 28932 | M41: =K41*I41 -> 2732.4667 | N41: =(L41-M41)/L41 -> 0.90555556 | O41: =E41/N41 -> 0.16889614 | Q41: =O41*J41*24 -> 9773.0061 | R41: =Q41-B41 -> 923.00613
A42: 45877 | B42: =Data_Entry!T132 -> 11070 | C42: 0 | D42: =Data_Entry!V132 -> 4.26 | E42: =B42/(24*J42) -> 0.19131066 | F42: 0 | G42: 0 | H42: =(G42-F42)*24*60 -> 0 | I42: =H42/60 -> 0 | J42: 2411 | L42: =J42*12 -> 28932 | M42: =K42*I42 -> 0 | N42: =(L42-M42)/L42 -> 1 | O42: =E42/N42 -> 0.19131066 | Q42: =O42*J42*24 -> 11070 | R42: =Q42-B42 -> 0
A43: 45878 | B43: =Data_Entry!T133 -> 8130 | C43: 0 | D43: =Data_Entry!V133 -> 3.37 | E43: =B43/(24*J43) -> 0.14050187 | F43: 0 | G43: 0 | H43: =(G43-F43)*24*60 -> 0 | I43: =H43/60 -> 0 | J43: 2411 | L43: =J43*12 -> 28932 | M43: =K43*I43 -> 0 | N43: =(L43-M43)/L43 -> 1 | O43: =E43/N43 -> 0.14050187 | Q43: =O43*J43*24 -> 8130 | R43: =Q43-B43 -> 0
A44: 45879 | B44: =Data_Entry!T134 -> 7830 | C44: 0 | D44: =Data_Entry!V134 -> 3.26 | E44: =B44/(24*J44) -> 0.1353173 | F44: 0 | G44: 0 | H44: =(G44-F44)*24*60 -> 0 | I44: =H44/60 -> 0 | J44: 2411 | L44: =J44*12 -> 28932 | M44: =K44*I44 -> 0 | N44: =(L44-M44)/L44 -> 1 | O44: =E44/N44 -> 0.1353173 | Q44: =O44*J44*24 -> 7830 | R44: =Q44-B44 -> 0
A45: 45880 | B45: =Data_Entry!T135 -> 9870 | C45: 0 | D45: =Data_Entry!V135 -> 3.95 | E45: =B45/(24*J45) -> 0.17057238 | F45: 0 | G45: 0 | H45: =(G45-F45)*24*60 -> 0 | I45: =H45/60 -> 0 | J45: 2411 | L45: =J45*12 -> 28932 | M45: =K45*I45 -> 0 | N45: =(L45-M45)/L45 -> 1 | O45: =E45/N45 -> 0.17057238 | Q45: =O45*J45*24 -> 9870 | R45: =Q45-B45 -> 0
A46: 45881 | B46: =Data_Entry!T136 -> 9960 | C46: 0 | D46: =Data_Entry!V136 -> 4.13 | E46: =B46/(24*J46) -> 0.17212775 | F46: 0 | G46: 0 | H46: =(G46-F46)*24*60 -> 0 | I46: =H46/60 -> 0 | J46: 2411 | L46: =J46*12 -> 28932 | M46: =K46*I46 -> 0 | N46: =(L46-M46)/L46 -> 1 | O46: =E46/N46 -> 0.17212775 | Q46: =O46*J46*24 -> 9960 | R46: =Q46-B46 -> 0
A47: 45882 | B47: =Data_Entry!T137 -> 8670 | C47: 0 | D47: =Data_Entry!V137 -> 3.79 | E47: =B47/(24*J47) -> 0.14983409 | F47: 0 | G47: 0 | H47: =(G47-F47)*24*60 -> 0 | I47: =H47/60 -> 0 | J47: 2411 | L47: =J47*12 -> 28932 | M47: =K47*I47 -> 0 | N47: =(L47-M47)/L47 -> 1 | O47: =E47/N47 -> 0.14983409 | Q47: =O47*J47*24 -> 8670 | R47: =Q47-B47 -> 0
A48: 45883 | B48: =Data_Entry!T138 -> 4050 | C48: 0 | D48: =Data_Entry!V138 -> 1.54 | E48: =B48/(24*J48) -> 0.069991705 | F48: 0 | G48: 0 | H48: =(G48-F48)*24*60 -> 0 | I48: =H48/60 -> 0 | J48: 2411 | L48: =J48*12 -> 28932 | M48: =K48*I48 -> 0 | N48: =(L48-M48)/L48 -> 1 | O48: =E48/N48 -> 0.069991705 | Q48: =O48*J48*24 -> 4050 | R48: =Q48-B48 -> 0
A49: 45884 | B49: =Data_Entry!T139 -> 8370 | C49: 0 | D49: =Data_Entry!V139 -> 3.34 | E49: =B49/(24*J49) -> 0.14464952 | F49: 0 | G49: 0 | H49: =(G49-F49)*24*60 -> 0 | I49: =H49/60 -> 0 | J49: 2411 | L49: =J49*12 -> 28932 | M49: =K49*I49 -> 0 | N49: =(L49-M49)/L49 -> 1 | O49: =E49/N49 -> 0.14464952 | Q49: =O49*J49*24 -> 8370 | R49: =Q49-B49 -> 0
A50: 45885 | B50: =Data_Entry!T140 -> 7440 | C50: 0 | D50: =Data_Entry!V140 -> 3.05 | E50: =B50/(24*J50) -> 0.12857735 | F50: 0 | G50: 0 | H50: =(G50-F50)*24*60 -> 0 | I50: =H50/60 -> 0 | J50: 2411 | L50: =J50*12 -> 28932 | M50: =K50*I50 -> 0 | N50: =(L50-M50)/L50 -> 1 | O50: =E50/N50 -> 0.12857735 | Q50: =O50*J50*24 -> 7440 | R50: =Q50-B50 -> 0
A51: 45886 | B51: =Data_Entry!T141 -> 7740 | C51: 0 | D51: =Data_Entry!V141 -> 3.32 | E51: =B51/(24*J51) -> 0.13376192 | F51: 0 | G51: 0 | H51: =(G51-F51)*24*60 -> 0 | I51: =H51/60 -> 0 | J51: 2411 | L51: =J51*12 -> 28932 | M51: =K51*I51 -> 0 | N51: =(L51-M51)/L51 -> 1 | O51: =E51/N51 -> 0.13376192 | Q51: =O51*J51*24 -> 7740 | R51: =Q51-B51 -> 0
A52: 45887 | B52: =Data_Entry!T142 -> 8370 | C52: 0 | D52: =Data_Entry!V142 -> 4 | E52: =B52/(24*J52) -> 0.14464952 | F52: 0 | G52: 0 | H52: =(G52-F52)*24*60 -> 0 | I52: =H52/60 -> 0 | J52: 2411 | L52: =J52*12 -> 28932 | M52: =K52*I52 -> 0 | N52: =(L52-M52)/L52 -> 1 | O52: =E52/N52 -> 0.14464952 | Q52: =O52*J52*24 -> 8370 | R52: =Q52-B52 -> 0
A53: 45888 | B53: =Data_Entry!T143 -> 7680 | C53: 0 | D53: =Data_Entry!V143 -> 0 | E53: =B53/(24*J53) -> 0.13272501 | F53: 0 | G53: 0 | H53: =(G53-F53)*24*60 -> 0 | I53: =H53/60 -> 0 | J53: 2411 | L53: =J53*12 -> 28932 | M53: =K53*I53 -> 0 | N53: =(L53-M53)/L53 -> 1 | O53: =E53/N53 -> 0.13272501 | Q53: =O53*J53*24 -> 7680 | R53: =Q53-B53 -> 0
... A71: 45906 | B71: =Data_Entry!T161 -> 2910 | C71: 0 | D71: =Data_Entry!V161 -> 0 | E71: =B71/(24*J71) -> 0.050290336 | F71: 0 | G71: 0 | H71: =(G71-F71)*24*60 -> 0 | I71: =H71/60 -> 0 | J71: 2411 | L71: =J71*12 -> 28932 | M71: =K71*I71 -> 0 | N71: =(L71-M71)/L71 -> 1 | O71: =E71/N71 -> 0.050290336 | Q71: =O71*J71*24 -> 2910 | R71: =Q71-B71 -> 0
A72: 45907 | B72: =Data_Entry!T162 -> 3750 | C72: 1 | D72: =Data_Entry!V162 -> 0 | E72: =B72/(24*J72) -> 0.064807134 | F72: 0.29166667 | G72: 0.66666667 | H72: =(G72-F72)*24*60 -> 540 | I72: =H72/60 -> 9 | J72: 2411 | K72: 330 | L72: =J72*12 -> 28932 | M72: =K72*I72 -> 2970 | N72: =(L72-M72)/L72 -> 0.8973455 | O72: =E72/N72 -> 0.072220938 | Q72: =O72*J72*24 -> 4178.9924 | R72: =Q72-B72 -> 428.99237
A73: 45908 | B73: =Data_Entry!T163 -> 4500 | C73: 0 | D73: =Data_Entry!V163 -> 0 | E73: =B73/(24*J73) -> 0.077768561 | F73: 0 | G73: 0 | H73: =(G73-F73)*24*60 -> 0 | I73: =H73/60 -> 0 | J73: 2411 | L73: =J73*12 -> 28932 | M73: =K73*I73 -> 0 | N73: =(L73-M73)/L73 -> 1 | O73: =E73/N73 -> 0.077768561 | Q73: =O73*J73*24 -> 4500 | R73: =Q73-B73 -> 0
A74: 45909 | B74: =Data_Entry!T164 -> 11970 | C74: 0 | D74: =Data_Entry!V164 -> 0 | E74: =B74/(24*J74) -> 0.20686437 | F74: 0 | G74: 0 | H74: =(G74-F74)*24*60 -> 0 | I74: =H74/60 -> 0 | J74: 2411 | L74: =J74*12 -> 28932 | M74: =K74*I74 -> 0 | N74: =(L74-M74)/L74 -> 1 | O74: =E74/N74 -> 0.20686437 | Q74: =O74*J74*24 -> 11970 | R74: =Q74-B74 -> 0
A75: 45910 | B75: =Data_Entry!T165 -> 12120 | C75: 0 | D75: =Data_Entry!V165 -> 0 | E75: =B75/(24*J75) -> 0.20945666 | F75: 0 | G75: 0 | H75: =(G75-F75)*24*60 -> 0 | I75: =H75/60 -> 0 | J75: 2411 | L75: =J75*12 -> 28932 | M75: =K75*I75 -> 0 | N75: =(L75-M75)/L75 -> 1 | O75: =E75/N75 -> 0.20945666 | Q75: =O75*J75*24 -> 12120 | R75: =Q75-B75 -> 0
A76: 45911 | B76: =Data_Entry!T166 -> 13200 | C76: 0 | D76: =Data_Entry!V166 -> 0 | E76: =B76/(24*J76) -> 0.22812111 | F76: 0 | G76: 0 | H76: =(G76-F76)*24*60 -> 0 | I76: =H76/60 -> 0 | J76: 2411 | L76: =J76*12 -> 28932 | M76: =K76*I76 -> 0 | N76: =(L76-M76)/L76 -> 1 | O76: =E76/N76 -> 0.22812111 | Q76: =O76*J76*24 -> 13200 | R76: =Q76-B76 -> 0
A77: 45912 | B77: =Data_Entry!T167 -> 10020 | C77: 0 | D77: =Data_Entry!V167 -> 0 | E77: =B77/(24*J77) -> 0.17316466 | F77: 0 | G77: 0 | H77: =(G77-F77)*24*60 -> 0 | I77: =H77/60 -> 0 | J77: 2411 | L77: =J77*12 -> 28932 | M77: =K77*I77 -> 0 | N77: =(L77-M77)/L77 -> 1 | O77: =E77/N77 -> 0.17316466 | Q77: =O77*J77*24 -> 10020 | R77: =Q77-B77 -> 0
A78: 45913 | B78: =Data_Entry!T168 -> 11160 | C78: 0 | D78: =Data_Entry!V168 -> 0 | E78: =B78/(24*J78) -> 0.19286603 | F78: 0 | G78: 0 | H78: =(G78-F78)*24*60 -> 0 | I78: =H78/60 -> 0 | J78: 2411 | L78: =J78*12 -> 28932 | M78: =K78*I78 -> 0 | N78: =(L78-M78)/L78 -> 1 | O78: =E78/N78 -> 0.19286603 | Q78: =O78*J78*24 -> 11160 | R78: =Q78-B78 -> 0
A79: 45914 | B79: =Data_Entry!T169 -> 7050 | C79: 0 | D79: =Data_Entry!V169 -> 0 | E79: =B79/(24*J79) -> 0.12183741 | F79: 0 | G79: 0 | H79: =(G79-F79)*24*60 -> 0 | I79: =H79/60 -> 0 | J79: 2411 | L79: =J79*12 -> 28932 | M79: =K79*I79 -> 0 | N79: =(L79-M79)/L79 -> 1 | O79: =E79/N79 -> 0.12183741 | Q79: =O79*J79*24 -> 7050 | R79: =Q79-B79 -> 0
A80: 45915 | B80: =Data_Entry!T170 -> 11040 | C80: 0 | D80: =Data_Entry!V170 -> 0 | E80: =B80/(24*J80) -> 0.1907922 | F80: 0 | G80: 0 | H80: =(G80-F80)*24*60 -> 0 | I80: =H80/60 -> 0 | J80: 2411 | L80: =J80*12 -> 28932 | M80: =K80*I80 -> 0 | N80: =(L80-M80)/L80 -> 1 | O80: =E80/N80 -> 0.1907922 | Q80: =O80*J80*24 -> 11040 | R80: =Q80-B80 -> 0
A81: 45916 | B81: =Data_Entry!T171 -> 11610 | C81: 0 | D81: =Data_Entry!V171 -> 0 | E81: =B81/(24*J81) -> 0.20064289 | F81: 0 | G81: 0 | H81: =(G81-F81)*24*60 -> 0 | I81: =H81/60 -> 0 | J81: 2411 | L81: =J81*12 -> 28932 | M81: =K81*I81 -> 0 | N81: =(L81-M81)/L81 -> 1 | O81: =E81/N81 -> 0.20064289 | Q81: =O81*J81*24 -> 11610 | R81: =Q81-B81 -> 0
A82: 45917 | B82: =Data_Entry!T172 -> 11850 | C82: 0 | D82: =Data_Entry!V172 -> 0 | E82: =B82/(24*J82) -> 0.20479054 | F82: 0 | G82: 0 | H82: =(G82-F82)*24*60 -> 0 | I82: =H82/60 -> 0 | J82: 2411 | L82: =J82*12 -> 28932 | M82: =K82*I82 -> 0 | N82: =(L82-M82)/L82 -> 1 | O82: =E82/N82 -> 0.20479054 | Q82: =O82*J82*24 -> 11850 | R82: =Q82-B82 -> 0
A83: 45918 | B83: =Data_Entry!T173 -> 10800 | C83: 0 | D83: =Data_Entry!V173 -> 0 | E83: =B83/(24*J83) -> 0.18664455 | F83: 0 | G83: 0 | H83: =(G83-F83)*24*60 -> 0 | I83: =H83/60 -> 0 | J83: 2411 | L83: =J83*12 -> 28932 | M83: =K83*I83 -> 0 | N83: =(L83-M83)/L83 -> 1 | O83: =E83/N83 -> 0.18664455 | Q83: =O83*J83*24 -> 10800 | R83: =Q83-B83 -> 0
A84: 45919 | B84: =Data_Entry!T174 -> 11550 | C84: 0 | D84: =Data_Entry!V174 -> 0 | E84: =B84/(24*J84) -> 0.19960597 | F84: 0 | G84: 0 | H84: =(G84-F84)*24*60 -> 0 | I84: =H84/60 -> 0 | J84: 2411 | L84: =J84*12 -> 28932 | M84: =K84*I84 -> 0 | N84: =(L84-M84)/L84 -> 1 | O84: =E84/N84 -> 0.19960597 | Q84: =O84*J84*24 -> 11550 | R84: =Q84-B84 -> 0
... A118: 45953 | B118: =Data_Entry!T208 -> 9780 | C118: 0 | D118: =Data_Entry!V208 -> 3.88 | E118: =B118/(24*J118) -> 0.16901701 | F118: 0 | G118: 0 | H118: =(G118-F118)*24*60 -> 0 | I118: =H118/60 -> 0 | J118: 2411 | L118: =J118*12 -> 28932 | M118: =K118*I118 -> 0 | N118: =(L118-M118)/L118 -> 1 | O118: =E118/N118 -> 0.16901701 | Q118: =O118*J118*24 -> 9780 | R118: =Q118-B118 -> 0
A119: 45954 | B119: =Data_Entry!T209 -> 9210 | C119: 7 | D119: =Data_Entry!V209 -> 3.94 | E119: =B119/(24*J119) -> 0.15916632 | F119: 0.35763889 | G119: 0.39930556 | H119: =(G119-F119)*24*60 -> 60 | I119: =H119/60 -> 1 | J119: 2411 | K119: 2411 | L119: =J119*12 -> 28932 | M119: =K119*I119 -> 2411 | N119: =(L119-M119)/L119 -> 0.91666667 | O119: =E119/N119 -> 0.17363599 | Q119: =O119*J119*24 -> 10047.273 | R119: =Q119-B119 -> 837.27273
A120: 45955 | B120: =Data_Entry!T210 -> 9000 | C120: 0 | D120: =Data_Entry!V210 -> 3.46 | E120: =B120/(24*J120) -> 0.15553712 | F120: 0 | G120: 0 | H120: =(G120-F120)*24*60 -> 0 | I120: =H120/60 -> 0 | J120: 2411 | L120: =J120*12 -> 28932 | M120: =K120*I120 -> 0 | N120: =(L120-M120)/L120 -> 1 | O120: =E120/N120 -> 0.15553712 | Q120: =O120*J120*24 -> 9000 | R120: =Q120-B120 -> 0
A121: 45956 | B121: =Data_Entry!T211 -> 1620 | C121: 0 | D121: =Data_Entry!V211 -> 0.69 | E121: =B121/(24*J121) -> 0.027996682 | F121: 0 | G121: 0 | H121: =(G121-F121)*24*60 -> 0 | I121: =H121/60 -> 0 | J121: 2411 | L121: =J121*12 -> 28932 | M121: =K121*I121 -> 0 | N121: =(L121-M121)/L121 -> 1 | O121: =E121/N121 -> 0.027996682 | Q121: =O121*J121*24 -> 1620 | R121: =Q121-B121 -> 0
A122: 45957 | B122: =Data_Entry!T212 -> 3570 | C122: 0 | D122: =Data_Entry!V212 -> 1.36 | E122: =B122/(24*J122) -> 0.061696392 | F122: 0 | G122: 0 | H122: =(G122-F122)*24*60 -> 0 | I122: =H122/60 -> 0 | J122: 2411 | L122: =J122*12 -> 28932 | M122: =K122*I122 -> 0 | N122: =(L122-M122)/L122 -> 1 | O122: =E122/N122 -> 0.061696392 | Q122: =O122*J122*24 -> 3570 | R122: =Q122-B122 -> 0
A123: 45958 | B123: =Data_Entry!T213 -> 1530 | C123: 0 | D123: =Data_Entry!V213 -> 0.56 | E123: =B123/(24*J123) -> 0.026441311 | F123: 0 | G123: 0 | H123: =(G123-F123)*24*60 -> 0 | I123: =H123/60 -> 0 | J123: 2411 | L123: =J123*12 -> 28932 | M123: =K123*I123 -> 0 | N123: =(L123-M123)/L123 -> 1 | O123: =E123/N123 -> 0.026441311 | Q123: =O123*J123*24 -> 1530 | R123: =Q123-B123 -> 0
A124: 45959 | B124: =Data_Entry!T214 -> 3240 | C124: 0 | D124: =Data_Entry!V214 -> 1.34 | E124: =B124/(24*J124) -> 0.055993364 | F124: 0 | G124: 0 | H124: =(G124-F124)*24*60 -> 0 | I124: =H124/60 -> 0 | J124: 2411 | L124: =J124*12 -> 28932 | M124: =K124*I124 -> 0 | N124: =(L124-M124)/L124 -> 1 | O124: =E124/N124 -> 0.055993364 | Q124: =O124*J124*24 -> 3240 | R124: =Q124-B124 -> 0
A125: 45960 | B125: =Data_Entry!T215 -> 4080 | C125: 0 | D125: =Data_Entry!V215 -> 1.62 | E125: =B125/(24*J125) -> 0.070510162 | F125: 0 | G125: 0 | H125: =(G125-F125)*24*60 -> 0 | I125: =H125/60 -> 0 | J125: 2411 | L125: =J125*12 -> 28932 | M125: =K125*I125 -> 0 | N125: =(L125-M125)/L125 -> 1 | O125: =E125/N125 -> 0.070510162 | Q125: =O125*J125*24 -> 4080 | R125: =Q125-B125 -> 0
A126: 45961 | B126: =Data_Entry!T216 -> 3900 | C126: 0 | D126: =Data_Entry!V216 -> 1.47 | E126: =B126/(24*J126) -> 0.067399419 | F126: 0 | G126: 0 | H126: =(G126-F126)*24*60 -> 0 | I126: =H126/60 -> 0 | J126: 2411 | L126: =J126*12 -> 28932 | M126: =K126*I126 -> 0 | N126: =(L126-M126)/L126 -> 1 | O126: =E126/N126 -> 0.067399419 | Q126: =O126*J126*24 -> 3900 | R126: =Q126-B126 -> 0
A127: 45962 | B127: =Data_Entry!T217 -> 6504 | C127: 0 | D127: =Data_Entry!V217 -> 2.54 | E127: =B127/(24*J127) -> 0.11240149 | F127: 0 | G127: 0 | H127: =(G127-F127)*24*60 -> 0 | I127: =H127/60 -> 0 | J127: 2411 | L127: =J127*12 -> 28932 | M127: =K127*I127 -> 0 | N127: =(L127-M127)/L127 -> 1 | O127: =E127/N127 -> 0.11240149 | Q127: =O127*J127*24 -> 6504 | R127: =Q127-B127 -> 0
A128: 45963 | B128: =Data_Entry!T218 -> 7716 | C128: 0 | D128: =Data_Entry!V218 -> 3.05 | E128: =B128/(24*J128) -> 0.13334716 | F128: 0 | G128: 0 | H128: =(G128-F128)*24*60 -> 0 | I128: =H128/60 -> 0 | J128: 2411 | L128: =J128*12 -> 28932 | M128: =K128*I128 -> 0 | N128: =(L128-M128)/L128 -> 1 | O128: =E128/N128 -> 0.13334716 | Q128: =O128*J128*24 -> 7716 | R128: =Q128-B128 -> 0
A129: 45964 | B129: =Data_Entry!T219 -> 11100 | C129: 0 | D129: =Data_Entry!V219 -> 4.05 | E129: =B129/(24*J129) -> 0.19182912 | F129: 0 | G129: 0 | H129: =(G129-F129)*24*60 -> 0 | I129: =H129/60 -> 0 | J129: 2411 | L129: =J129*12 -> 28932 | M129: =K129*I129 -> 0 | N129: =(L129-M129)/L129 -> 1 | O129: =E129/N129 -> 0.19182912 | Q129: =O129*J129*24 -> 11100 | R129: =Q129-B129 -> 0
A130: 45965 | B130: =Data_Entry!T220 -> 11490 | C130: 0 | D130: =Data_Entry!V220 -> 3.87 | E130: =B130/(24*J130) -> 0.19856906 | F130: 0 | G130: 0 | H130: =(G130-F130)*24*60 -> 0 | I130: =H130/60 -> 0 | J130: 2411 | L130: =J130*12 -> 28932 | M130: =K130*I130 -> 0 | N130: =(L130-M130)/L130 -> 1 | O130: =E130/N130 -> 0.19856906 | Q130: =O130*J130*24 -> 11490 | R130: =Q130-B130 -> 0
A131: 45966 | B131: =Data_Entry!T221 -> 12450 | C131: 0 | D131: =Data_Entry!V221 -> 4.47 | E131: =B131/(24*J131) -> 0.21515968 | F131: 0 | G131: 0 | H131: =(G131-F131)*24*60 -> 0 | I131: =H131/60 -> 0 | J131: 2411 | L131: =J131*12 -> 28932 | M131: =K131*I131 -> 0 | N131: =(L131-M131)/L131 -> 1 | O131: =E131/N131 -> 0.21515968 | Q131: =O131*J131*24 -> 12450 | R131: =Q131-B131 -> 0
... A160: 45995 | B160: =Data_Entry!T250 -> 9630 | C160: 0 | D160: =Data_Entry!V250 -> 3.65 | E160: =B160/(24*J160) -> 0.16642472 | F160: 0 | G160: 0 | H160: =(G160-F160)*24*60 -> 0 | I160: =H160/60 -> 0 | J160: 2411 | L160: =J160*12 -> 28932 | M160: =K160*I160 -> 0 | N160: =(L160-M160)/L160 -> 1 | O160: =E160/N160 -> 0.16642472 | Q160: =O160*J160*24 -> 9630 | R160: =Q160-B160 -> 0
A161: 45996 | B161: =Data_Entry!T251 -> 9840 | C161: 0 | D161: =Data_Entry!W251 -> 26.85 | E161: =B161/(24*J161) -> 0.17005392 | F161: 0 | G161: 0 | H161: =(G161-F161)*24*60 -> 0 | I161: =H161/60 -> 0 | J161: 2411 | L161: =J161*12 -> 28932 | M161: =K161*I161 -> 0 | N161: =(L161-M161)/L161 -> 1 | O161: =E161/N161 -> 0.17005392 | Q161: =O161*J161*24 -> 9840 | R161: =Q161-B161 -> 0
A162: 45997 | B162: =Data_Entry!T252 -> 9000 | C162: 0 | D162: =Data_Entry!W252 -> 26.19 | E162: =B162/(24*J162) -> 0.15553712 | F162: 0 | G162: 0 | H162: =(G162-F162)*24*60 -> 0 | I162: =H162/60 -> 0 | J162: 2411 | L162: =J162*12 -> 28932 | M162: =K162*I162 -> 0 | N162: =(L162-M162)/L162 -> 1 | O162: =E162/N162 -> 0.15553712 | Q162: =O162*J162*24 -> 9000 | R162: =Q162-B162 -> 0
A163: 45998 | B163: =Data_Entry!T253 -> 10260 | C163: 0 | D163: =Data_Entry!V253 -> 3.81 | E163: =B163/(24*J163) -> 0.17731232 | F163: 0 | G163: 0 | H163: =(G163-F163)*24*60 -> 0 | I163: =H163/60 -> 0 | J163: 2411 | L163: =J163*12 -> 28932 | M163: =K163*I163 -> 0 | N163: =(L163-M163)/L163 -> 1 | O163: =E163/N163 -> 0.17731232 | Q163: =O163*J163*24 -> 10260 | R163: =Q163-B163 -> 0
A164: 45999 | B164: =Data_Entry!T254 -> 10260 | C164: 0 | D164: =Data_Entry!V254 -> 3.82 | E164: =B164/(24*J164) -> 0.17731232 | F164: 0 | G164: 0 | H164: =(G164-F164)*24*60 -> 0 | I164: =H164/60 -> 0 | J164: 2411 | L164: =J164*12 -> 28932 | M164: =K164*I164 -> 0 | N164: =(L164-M164)/L164 -> 1 | O164: =E164/N164 -> 0.17731232 | Q164: =O164*J164*24 -> 10260 | R164: =Q164-B164 -> 0
A165: 46000 | B165: =Data_Entry!T255 -> 11340 | C165: 0 | D165: =Data_Entry!V255 -> 4.13 | E165: =B165/(24*J165) -> 0.19597677 | F165: 0 | G165: 0 | H165: =(G165-F165)*24*60 -> 0 | I165: =H165/60 -> 0 | J165: 2411 | L165: =J165*12 -> 28932 | M165: =K165*I165 -> 0 | N165: =(L165-M165)/L165 -> 1 | O165: =E165/N165 -> 0.19597677 | Q165: =O165*J165*24 -> 11340 | R165: =Q165-B165 -> 0
A166: 46001 | B166: =Data_Entry!T256 -> 9150 | C166: 0 | D166: =Data_Entry!V256 -> 3.48 | E166: =B166/(24*J166) -> 0.15812941 | F166: 0 | G166: 0 | H166: =(G166-F166)*24*60 -> 0 | I166: =H166/60 -> 0 | J166: 2411 | L166: =J166*12 -> 28932 | M166: =K166*I166 -> 0 | N166: =(L166-M166)/L166 -> 1 | O166: =E166/N166 -> 0.15812941 | Q166: =O166*J166*24 -> 9150 | R166: =Q166-B166 -> 0
A167: 46002 | B167: =Data_Entry!T257 -> 11790 | C167: 0 | D167: =Data_Entry!V257 -> 4.11 | E167: =B167/(24*J167) -> 0.20375363 | F167: 0 | G167: 0 | H167: =(G167-F167)*24*60 -> 0 | I167: =H167/60 -> 0 | J167: 2411 | L167: =J167*12 -> 28932 | M167: =K167*I167 -> 0 | N167: =(L167-M167)/L167 -> 1 | O167: =E167/N167 -> 0.20375363 | Q167: =O167*J167*24 -> 11790 | R167: =Q167-B167 -> 0
A168: 46003 | B168: =Data_Entry!T258 -> 11910 | C168: 0 | D168: =Data_Entry!V258 -> 4.15 | E168: =B168/(24*J168) -> 0.20582746 | F168: 0 | G168: 0 | H168: =(G168-F168)*24*60 -> 0 | I168: =H168/60 -> 0 | J168: 2411 | L168: =J168*12 -> 28932 | M168: =K168*I168 -> 0 | N168: =(L168-M168)/L168 -> 1 | O168: =E168/N168 -> 0.20582746 | Q168: =O168*J168*24 -> 11910 | R168: =Q168-B168 -> 0
A169: 46004 | B169: =Data_Entry!T259 -> 11580 | C169: 0 | D169: =Data_Entry!V259 -> 4.02 | E169: =B169/(24*J169) -> 0.20012443 | F169: 0 | G169: 0 | H169: =(G169-F169)*24*60 -> 0 | I169: =H169/60 -> 0 | J169: 2411 | L169: =J169*12 -> 28932 | M169: =K169*I169 -> 0 | N169: =(L169-M169)/L169 -> 1 | O169: =E169/N169 -> 0.20012443 | Q169: =O169*J169*24 -> 11580 | R169: =Q169-B169 -> 0
A170: 46005 | B170: =Data_Entry!T260 -> 11250 | C170: 0 | D170: =Data_Entry!V260 -> 3.91 | E170: =B170/(24*J170) -> 0.1944214 | F170: 0 | G170: 0 | H170: =(G170-F170)*24*60 -> 0 | I170: =H170/60 -> 0 | J170: 2411 | L170: =J170*12 -> 28932 | M170: =K170*I170 -> 0 | N170: =(L170-M170)/L170 -> 1 | O170: =E170/N170 -> 0.1944214 | Q170: =O170*J170*24 -> 11250 | R170: =Q170-B170 -> 0
A171: 46006 | B171: =Data_Entry!T261 -> 11460 | C171: 0 | D171: =Data_Entry!V261 -> 4.01 | E171: =B171/(24*J171) -> 0.1980506 | F171: 0 | G171: 0 | H171: =(G171-F171)*24*60 -> 0 | I171: =H171/60 -> 0 | J171: 2411 | L171: =J171*12 -> 28932 | M171: =K171*I171 -> 0 | N171: =(L171-M171)/L171 -> 1 | O171: =E171/N171 -> 0.1980506 | Q171: =O171*J171*24 -> 11460 | R171: =Q171-B171 -> 0
A172: 46007 | B172: =Data_Entry!T262 -> 11160 | C172: 0 | D172: =Data_Entry!V262 -> 3.7 | E172: =B172/(24*J172) -> 0.19286603 | F172: 0 | G172: 0 | H172: =(G172-F172)*24*60 -> 0 | I172: =H172/60 -> 0 | J172: 2411 | L172: =J172*12 -> 28932 | M172: =K172*I172 -> 0 | N172: =(L172-M172)/L172 -> 1 | O172: =E172/N172 -> 0.19286603 | Q172: =O172*J172*24 -> 11160 | R172: =Q172-B172 -> 0
A173: 46008 | B173: =Data_Entry!T263 -> 10380 | C173: 0 | D173: =Data_Entry!V263 -> 3.62 | E173: =B173/(24*J173) -> 0.17938615 | F173: 0 | G173: 0 | H173: =(G173-F173)*24*60 -> 0 | I173: =H173/60 -> 0 | J173: 2411 | L173: =J173*12 -> 28932 | M173: =K173*I173 -> 0 | N173: =(L173-M173)/L173 -> 1 | O173: =E173/N173 -> 0.17938615 | Q173: =O173*J173*24 -> 10380 | R173: =Q173-B173 -> 0
A174: 46009 | B174: =Data_Entry!T264 -> 10650 | C174: 0 | D174: =Data_Entry!V264 -> 3.73 | E174: =B174/(24*J174) -> 0.18405226 | F174: 0 | G174: 0 | H174: =(G174-F174)*24*60 -> 0 | I174: =H174/60 -> 0 | J174: 2411 | L174: =J174*12 -> 28932 | M174: =K174*I174 -> 0 | N174: =(L174-M174)/L174 -> 1 | O174: =E174/N174 -> 0.18405226 | Q174: =O174*J174*24 -> 10650 | R174: =Q174-B174 -> 0
... A213: 46048 | B213: =Data_Entry!T303 -> 11550 | C213: 0 | D213: =Data_Entry!V303 -> 3.88 | E213: =B213/(24*J213) -> 0.19960597 | F213: 0 | G213: 0 | H213: =(G213-F213)*24*60 -> 0 | I213: =H213/60 -> 0 | J213: 2411 | L213: =J213*12 -> 28932 | M213: =K213*I213 -> 0 | N213: =(L213-M213)/L213 -> 1 | O213: =E213/N213 -> 0.19960597 | Q213: =O213*J213*24 -> 11550 | R213: =Q213-B213 -> 0
A214: 46049 | B214: =Data_Entry!T304 -> 5910 | C214: 0 | D214: =Data_Entry!V304 -> 1.6 | E214: =B214/(24*J214) -> 0.10213604 | F214: 0.52986111 | G214: 0.78819444 | H214: =(G214-F214)*24*60 -> 372 | I214: =H214/60 -> 6.2 | J214: 2411 | K214: 2411 | L214: =J214*12 -> 28932 | M214: =K214*I214 -> 14948.2 | N214: =(L214-M214)/L214 -> 0.48333333 | O214: =E214/N214 -> 0.21131595 | Q214: =O214*J214*24 -> 12227.586 | R214: =Q214-B214 -> 6317.5862
A215: 46050 | B215: =Data_Entry!T305 -> 13560 | C215: 0 | D215: =Data_Entry!V305 -> 4.49 | E215: =B215/(24*J215) -> 0.2343426 | F215: 0.56944444 | G215: 0.59375 | H215: =(G215-F215)*24*60 -> 35 | I215: =H215/60 -> 0.58333333 | J215: 2411 | K215: 152.6 | L215: =J215*12 -> 28932 | M215: =K215*I215 -> 89.016667 | N215: =(L215-M215)/L215 -> 0.99692325 | O215: =E215/N215 -> 0.23506584 | P215: curtailment | Q215: =O215*J215*24 -> 13601.85 | R215: =Q215-B215 -> 41.849554
A216: 46051 | B216: =Data_Entry!T306 -> 12690 | C216: 0 | D216: =Data_Entry!V306 -> 4.29 | E216: =B216/(24*J216) -> 0.21930734 | F216: 0 | G216: 0 | H216: =(G216-F216)*24*60 -> 0 | I216: =H216/60 -> 0 | J216: 2411 | L216: =J216*12 -> 28932 | M216: =K216*I216 -> 0 | N216: =(L216-M216)/L216 -> 1 | O216: =E216/N216 -> 0.21930734 | Q216: =O216*J216*24 -> 12690 | R216: =Q216-B216 -> 0
A217: 46052 | B217: =Data_Entry!T307 -> 10500 | C217: 0 | D217: =Data_Entry!V307 -> 3.58 | E217: =B217/(24*J217) -> 0.18145998 | F217: 0 | G217: 0 | H217: =(G217-F217)*24*60 -> 0 | I217: =H217/60 -> 0 | J217: 2411 | L217: =J217*12 -> 28932 | M217: =K217*I217 -> 0 | N217: =(L217-M217)/L217 -> 1 | O217: =E217/N217 -> 0.18145998 | Q217: =O217*J217*24 -> 10500 | R217: =Q217-B217 -> 0
A218: 46053 | B218: =Data_Entry!T308 -> 6810 | C218: 0 | D218: =Data_Entry!V308 -> 2.86 | E218: =B218/(24*J218) -> 0.11768976 | F218: 0 | G218: 0 | H218: =(G218-F218)*24*60 -> 0 | I218: =H218/60 -> 0 | J218: 2411 | L218: =J218*12 -> 28932 | M218: =K218*I218 -> 0 | N218: =(L218-M218)/L218 -> 1 | O218: =E218/N218 -> 0.11768976 | Q218: =O218*J218*24 -> 6810 | R218: =Q218-B218 -> 0
A219: 46054 | B219: =Data_Entry!T309 -> 10050 | C219: 0 | D219: =Data_Entry!V309 -> 3.54 | E219: =B219/(24*J219) -> 0.17368312 | F219: 0 | G219: 0 | H219: =(G219-F219)*24*60 -> 0 | I219: =H219/60 -> 0 | J219: 2411 | L219: =J219*12 -> 28932 | M219: =K219*I219 -> 0 | N219: =(L219-M219)/L219 -> 1 | O219: =E219/N219 -> 0.17368312 | Q219: =O219*J219*24 -> 10050 | R219: =Q219-B219 -> 0
A220: 46055 | B220: =Data_Entry!T310 -> 9600 | C220: 0 | D220: =Data_Entry!V310 -> 3.5 | E220: =B220/(24*J220) -> 0.16590626 | F220: 0 | G220: 0 | H220: =(G220-F220)*24*60 -> 0 | I220: =H220/60 -> 0 | J220: 2411 | L220: =J220*12 -> 28932 | M220: =K220*I220 -> 0 | N220: =(L220-M220)/L220 -> 1 | O220: =E220/N220 -> 0.16590626 | Q220: =O220*J220*24 -> 9600 | R220: =Q220-B220 -> 0
A221: 46056 | B221: =Data_Entry!T311 -> 10380 | C221: 0 | D221: =Data_Entry!V311 -> 3.67 | E221: =B221/(24*J221) -> 0.17938615 | F221: 0 | G221: 0 | H221: =(G221-F221)*24*60 -> 0 | I221: =H221/60 -> 0 | J221: 2411 | L221: =J221*12 -> 28932 | M221: =K221*I221 -> 0 | N221: =(L221-M221)/L221 -> 1 | O221: =E221/N221 -> 0.17938615 | Q221: =O221*J221*24 -> 10380 | R221: =Q221-B221 -> 0
A222: 46057 | B222: =Data_Entry!T312 -> 10560 | C222: 0 | D222: =Data_Entry!V312 -> 3.74 | E222: =B222/(24*J222) -> 0.18249689 | F222: 0 | G222: 0 | H222: =(G222-F222)*24*60 -> 0 | I222: =H222/60 -> 0 | J222: 2411 | L222: =J222*12 -> 28932 | M222: =K222*I222 -> 0 | N222: =(L222-M222)/L222 -> 1 | O222: =E222/N222 -> 0.18249689 | Q222: =O222*J222*24 -> 10560 | R222: =Q222-B222 -> 0
A223: 46058 | B223: =Data_Entry!T313 -> 11430 | C223: 0 | D223: =Data_Entry!V313 -> 4.02 | E223: =B223/(24*J223) -> 0.19753214 | F223: 0 | G223: 0 | H223: =(G223-F223)*24*60 -> 0 | I223: =H223/60 -> 0 | J223: 2411 | L223: =J223*12 -> 28932 | M223: =K223*I223 -> 0 | N223: =(L223-M223)/L223 -> 1 | O223: =E223/N223 -> 0.19753214 | Q223: =O223*J223*24 -> 11430 | R223: =Q223-B223 -> 0
A224: 46059 | B224: =Data_Entry!T314 -> 12180 | C224: 0 | D224: =Data_Entry!V314 -> 4.2 | E224: =B224/(24*J224) -> 0.21049357 | F224: 0 | G224: 0 | H224: =(G224-F224)*24*60 -> 0 | I224: =H224/60 -> 0 | J224: 2411 | L224: =J224*12 -> 28932 | M224: =K224*I224 -> 0 | N224: =(L224-M224)/L224 -> 1 | O224: =E224/N224 -> 0.21049357 | Q224: =O224*J224*24 -> 12180 | R224: =Q224-B224 -> 0
A225: 46060 | B225: =Data_Entry!T315 -> 12180 | C225: 0 | D225: =Data_Entry!V315 -> 4.08 | E225: =B225/(24*J225) -> 0.21049357 | F225: 0 | G225: 0 | H225: =(G225-F225)*24*60 -> 0 | I225: =H225/60 -> 0 | J225: 2411 | L225: =J225*12 -> 28932 | M225: =K225*I225 -> 0 | N225: =(L225-M225)/L225 -> 1 | O225: =E225/N225 -> 0.21049357 | Q225: =O225*J225*24 -> 12180 | R225: =Q225-B225 -> 0
A226: 46061 | B226: =Data_Entry!T316 -> 11700 | C226: 0 | D226: =Data_Entry!V316 -> 4.05 | E226: =B226/(24*J226) -> 0.20219826 | F226: 0 | G226: 0 | H226: =(G226-F226)*24*60 -> 0 | I226: =H226/60 -> 0 | J226: 2411 | L226: =J226*12 -> 28932 | M226: =K226*I226 -> 0 | N226: =(L226-M226)/L226 -> 1 | O226: =E226/N226 -> 0.20219826 | Q226: =O226*J226*24 -> 11700 | R226: =Q226-B226 -> 0
A227: 46062 | B227: =Data_Entry!T317 -> 12720 | C227: 0 | D227: =Data_Entry!V317 -> 4.26 | E227: =B227/(24*J227) -> 0.2198258 | F227: 0 | G227: 0 | H227: =(G227-F227)*24*60 -> 0 | I227: =H227/60 -> 0 | J227: 2411 | L227: =J227*12 -> 28932 | M227: =K227*I227 -> 0 | N227: =(L227-M227)/L227 -> 1 | O227: =E227/N227 -> 0.2198258 | Q227: =O227*J227*24 -> 12720 | R227: =Q227-B227 -> 0
... A249: 46084 | B249: =Data_Entry!T339 -> 13020 | C249: 0 | D249: =Data_Entry!V339 -> 4.89 | E249: =B249/(24*J249) -> 0.22501037 | F249: 0 | G249: 0 | H249: =(G249-F249)*24*60 -> 0 | I249: =H249/60 -> 0 | J249: 2411 | L249: =J249*12 -> 28932 | M249: =K249*I249 -> 0 | N249: =(L249-M249)/L249 -> 1 | O249: =E249/N249 -> 0.22501037 | Q249: =O249*J249*24 -> 13020 | R249: =Q249-B249 -> 0
A250: 46085 | B250: =Data_Entry!T340 -> 12000 | C250: 0 | D250: =Data_Entry!V340 -> 4.68 | E250: =B250/(24*J250) -> 0.20738283 | F250: 0.5 | G250: 0.15277778 | H250: =(G250-F250)*24*60 -> -500 | I250: =H250/60 -> -8.3333333 | J250: 2411 | K250: 167.86 | L250: =J250*12 -> 28932 | M250: =K250*I250 -> -1398.8333 | N250: =(L250-M250)/L250 -> 1.048349 | O250: =E250/N250 -> 0.1978185 | P250: curtailment | Q250: =O250*J250*24 -> 11446.57 | R250: =Q250-B250 -> -553.43023
A251: 46086 | B251: =Data_Entry!T341 -> 13080 | C251: 0 | D251: =Data_Entry!V341 -> 4.84 | E251: =B251/(24*J251) -> 0.22604728 | F251: 0.45833333 | G251: 0.125 | H251: =(G251-F251)*24*60 -> -480 | I251: =H251/60 -> -8 | J251: 2411 | K251: 167.86 | L251: =J251*12 -> 28932 | M251: =K251*I251 -> -1342.88 | N251: =(L251-M251)/L251 -> 1.046415 | O251: =E251/N251 -> 0.21602067 | P251: curtailment | Q251: =O251*J251*24 -> 12499.82 | R251: =Q251-B251 -> -580.17969
A252: 46087 | B252: =Data_Entry!T342 -> 11820 | C252: 0 | D252: =Data_Entry!V342 -> 4.63 | E252: =B252/(24*J252) -> 0.20427209 | F252: 0 | G252: 0 | H252: =(G252-F252)*24*60 -> 0 | I252: =H252/60 -> 0 | J252: 2411 | L252: =J252*12 -> 28932 | M252: =K252*I252 -> 0 | N252: =(L252-M252)/L252 -> 1 | O252: =E252/N252 -> 0.20427209 | Q252: =O252*J252*24 -> 11820 | R252: =Q252-B252 -> 0
A253: 46088 | B253: =Data_Entry!T343 -> 13740 | C253: 0 | D253: =Data_Entry!V343 -> 4.99 | E253: =B253/(24*J253) -> 0.23745334 | F253: 0 | G253: 0 | H253: =(G253-F253)*24*60 -> 0 | I253: =H253/60 -> 0 | J253: 2411 | L253: =J253*12 -> 28932 | M253: =K253*I253 -> 0 | N253: =(L253-M253)/L253 -> 1 | O253: =E253/N253 -> 0.23745334 | Q253: =O253*J253*24 -> 13740 | R253: =Q253-B253 -> 0
A254: 46089 | B254: =Data_Entry!T344 -> 13470 | C254: 0 | D254: =Data_Entry!V344 -> 4.85 | E254: =B254/(24*J254) -> 0.23278723 | F254: 0 | G254: 0 | H254: =(G254-F254)*24*60 -> 0 | I254: =H254/60 -> 0 | J254: 2411 | L254: =J254*12 -> 28932 | M254: =K254*I254 -> 0 | N254: =(L254-M254)/L254 -> 1 | O254: =E254/N254 -> 0.23278723 | Q254: =O254*J254*24 -> 13470 | R254: =Q254-B254 -> 0
A255: 46090 | B255: =Data_Entry!T345 -> 13350 | C255: 0 | D255: =Data_Entry!V345 -> 4.91 | E255: =B255/(24*J255) -> 0.2307134 | F255: 0 | G255: 0 | H255: =(G255-F255)*24*60 -> 0 | I255: =H255/60 -> 0 | J255: 2411 | L255: =J255*12 -> 28932 | M255: =K255*I255 -> 0 | N255: =(L255-M255)/L255 -> 1 | O255: =E255/N255 -> 0.2307134 | Q255: =O255*J255*24 -> 13350 | R255: =Q255-B255 -> 0
A256: 46091 | B256: =Data_Entry!T346 -> 13260 | C256: 0 | D256: =Data_Entry!V346 -> 4.92 | E256: =B256/(24*J256) -> 0.22915803 | F256: 0 | G256: 0 | H256: =(G256-F256)*24*60 -> 0 | I256: =H256/60 -> 0 | J256: 2411 | L256: =J256*12 -> 28932 | M256: =K256*I256 -> 0 | N256: =(L256-M256)/L256 -> 1 | O256: =E256/N256 -> 0.22915803 | Q256: =O256*J256*24 -> 13260 | R256: =Q256-B256 -> 0
A257: 46092 | B257: =Data_Entry!T347 -> 13170 | C257: 0 | D257: =Data_Entry!V347 -> 4.89 | E257: =B257/(24*J257) -> 0.22760265 | F257: 0 | G257: 0 | H257: =(G257-F257)*24*60 -> 0 | I257: =H257/60 -> 0 | J257: 2411 | L257: =J257*12 -> 28932 | M257: =K257*I257 -> 0 | N257: =(L257-M257)/L257 -> 1 | O257: =E257/N257 -> 0.22760265 | Q257: =O257*J257*24 -> 13170 | R257: =Q257-B257 -> 0
...

Sheet Grid Availiblity
A1: Date | B1: ABT Export Gen | C1: GHI | D1: CUF% | E1: Out | F1: In | G1: Total Minute | H1: Outage Hrs. | I1: Plant Capacity | J1: Outage Capacity | K1: Plant Capacity Ratio | L1: Outage Ratio | M1: Grid Availiblity | N1: G.C CUF | O1: G.C Generation | P1: Grid Unit Lose
A2: 45839 | B2: =Data_Entry!T94 -> 8220 | C2: =Data_Entry!V94 -> 3.07 | D2: =B2/(24*I2) -> 0.14205724 | E2: 0 | F2: 0 | G2: =(F2-E2)*24*60 -> 0 | H2: =G2/60 -> 0 | I2: 2411 | K2: =I2*12 -> 28932 | L2: =J2*H2 -> 0 | M2: =(K2-L2)/K2 -> 1 | N2: =D2/M2 -> 0.14205724 | O2: =N2*I2*24 -> 8220 | P2: =O2-B2 -> 0
A3: 45840 | B3: =Data_Entry!T95 -> 6720 | C3: =Data_Entry!V95 -> 2.41 | D3: =B3/(24*I3) -> 0.11613438 | E3: 0 | F3: 0 | G3: =(F3-E3)*24*60 -> 0 | H3: =G3/60 -> 0 | I3: 2411 | K3: =I3*12 -> 28932 | L3: =J3*H3 -> 0 | M3: =(K3-L3)/K3 -> 1 | N3: =D3/M3 -> 0.11613438 | O3: =N3*I3*24 -> 6720 | P3: =O3-B3 -> 0
A4: 45841 | B4: =Data_Entry!T96 -> 1890 | C4: =Data_Entry!V96 -> 0.41 | D4: =B4/(24*I4) -> 0.032662796 | E4: 0 | F4: 0 | G4: =(F4-E4)*24*60 -> 0 | H4: =G4/60 -> 0 | I4: 2411 | K4: =I4*12 -> 28932 | L4: =J4*H4 -> 0 | M4: =(K4-L4)/K4 -> 1 | N4: =D4/M4 -> 0.032662796 | O4: =N4*I4*24 -> 1890 | P4: =O4-B4 -> 0
A5: 45842 | B5: =Data_Entry!T97 -> 5520 | C5: =Data_Entry!V97 -> 0.86 | D5: =B5/(24*I5) -> 0.095396101 | E5: 0 | F5: 0 | G5: =(F5-E5)*24*60 -> 0 | H5: =G5/60 -> 0 | I5: 2411 | K5: =I5*12 -> 28932 | L5: =J5*H5 -> 0 | M5: =(K5-L5)/K5 -> 1 | N5: =D5/M5 -> 0.095396101 | O5: =N5*I5*24 -> 5520 | P5: =O5-B5 -> 0
A6: 45843 | B6: =Data_Entry!T98 -> 5250 | C6: =Data_Entry!V98 -> 1.08 | D6: =B6/(24*I6) -> 0.090729988 | E6: 0 | F6: 0 | G6: =(F6-E6)*24*60 -> 0 | H6: =G6/60 -> 0 | I6: 2411 | K6: =I6*12 -> 28932 | L6: =J6*H6 -> 0 | M6: =(K6-L6)/K6 -> 1 | N6: =D6/M6 -> 0.090729988 | O6: =N6*I6*24 -> 5250 | P6: =O6-B6 -> 0
A7: 45844 | B7: =Data_Entry!T99 -> 6690 | C7: =Data_Entry!V99 -> 0.48 | D7: =B7/(24*I7) -> 0.11561593 | E7: 0 | F7: 0 | G7: =(F7-E7)*24*60 -> 0 | H7: =G7/60 -> 0 | I7: 2411 | K7: =I7*12 -> 28932 | L7: =J7*H7 -> 0 | M7: =(K7-L7)/K7 -> 1 | N7: =D7/M7 -> 0.11561593 | O7: =N7*I7*24 -> 6690 | P7: =O7-B7 -> 0
A8: 45845 | B8: =Data_Entry!T100 -> 3720 | C8: =Data_Entry!V100 -> 0.27 | D8: =B8/(24*I8) -> 0.064288677 | E8: 0 | F8: 0 | G8: =(F8-E8)*24*60 -> 0 | H8: =G8/60 -> 0 | I8: 2411 | K8: =I8*12 -> 28932 | L8: =J8*H8 -> 0 | M8: =(K8-L8)/K8 -> 1 | N8: =D8/M8 -> 0.064288677 | O8: =N8*I8*24 -> 3720 | P8: =O8-B8 -> 0
A9: 45846 | B9: =Data_Entry!T101 -> 7350 | C9: =Data_Entry!V101 -> 0.36 | D9: =B9/(24*I9) -> 0.12702198 | E9: 0 | F9: 0 | G9: =(F9-E9)*24*60 -> 0 | H9: =G9/60 -> 0 | I9: 2411 | K9: =I9*12 -> 28932 | L9: =J9*H9 -> 0 | M9: =(K9-L9)/K9 -> 1 | N9: =D9/M9 -> 0.12702198 | O9: =N9*I9*24 -> 7350 | P9: =O9-B9 -> 0
A10: 45847 | B10: =Data_Entry!T102 -> 10980 | C10: =Data_Entry!V102 -> 0 | D10: =B10/(24*I10) -> 0.18975529 | E10: 0 | F10: 0 | G10: =(F10-E10)*24*60 -> 0 | H10: =G10/60 -> 0 | I10: 2411 | K10: =I10*12 -> 28932 | L10: =J10*H10 -> 0 | M10: =(K10-L10)/K10 -> 1 | N10: =D10/M10 -> 0.18975529 | O10: =N10*I10*24 -> 10980 | P10: =O10-B10 -> 0
A11: 45848 | B11: =Data_Entry!T103 -> 9870 | C11: =Data_Entry!V103 -> 0 | D11: =B11/(24*I11) -> 0.17057238 | E11: 0 | F11: 0 | G11: =(F11-E11)*24*60 -> 0 | H11: =G11/60 -> 0 | I11: 2411 | K11: =I11*12 -> 28932 | L11: =J11*H11 -> 0 | M11: =(K11-L11)/K11 -> 1 | N11: =D11/M11 -> 0.17057238 | O11: =N11*I11*24 -> 9870 | P11: =O11-B11 -> 0
A12: 45849 | B12: =Data_Entry!T104 -> 6810 | C12: =Data_Entry!V104 -> 1.61 | D12: =B12/(24*I12) -> 0.11768976 | E12: 0 | F12: 0 | G12: =(F12-E12)*24*60 -> 0 | H12: =G12/60 -> 0 | I12: 2411 | K12: =I12*12 -> 28932 | L12: =J12*H12 -> 0 | M12: =(K12-L12)/K12 -> 1 | N12: =D12/M12 -> 0.11768976 | O12: =N12*I12*24 -> 6810 | P12: =O12-B12 -> 0
A13: 45850 | B13: =Data_Entry!T105 -> 8340 | C13: =Data_Entry!V105 -> 3.27 | D13: =B13/(24*I13) -> 0.14413107 | E13: 0 | F13: 0 | G13: =(F13-E13)*24*60 -> 0 | H13: =G13/60 -> 0 | I13: 2411 | K13: =I13*12 -> 28932 | L13: =J13*H13 -> 0 | M13: =(K13-L13)/K13 -> 1 | N13: =D13/M13 -> 0.14413107 | O13: =N13*I13*24 -> 8340 | P13: =O13-B13 -> 0
... A32: 45869 | B32: =Data_Entry!T124 -> 6000 | C32: =Data_Entry!V124 -> 2.26 | D32: =B32/(24*I32) -> 0.10369141 | E32: 0 | F32: 0 | G32: =(F32-E32)*24*60 -> 0 | H32: =G32/60 -> 0 | I32: 2411 | K32: =I32*12 -> 28932 | L32: =J32*H32 -> 0 | M32: =(K32-L32)/K32 -> 1 | N32: =D32/M32 -> 0.10369141 | O32: =N32*I32*24 -> 6000 | P32: =O32-B32 -> 0
A33: 45870 | B33: =Data_Entry!T125 -> 7170 | C33: =Data_Entry!V125 -> 3.01 | D33: =B33/(24*I33) -> 0.12391124 | E33: 0 | F33: 0 | G33: =(F33-E33)*24*60 -> 0 | H33: =G33/60 -> 0 | I33: 2411 | J33: 13000 | K33: =I33*12 -> 28932 | L33: =J33*H33 -> 0 | M33: =(K33-L33)/K33 -> 1 | N33: =D33/M33 -> 0.12391124 | O33: =N33*I33*24 -> 7170 | P33: =O33-B33 -> 0
A34: 45871 | B34: =Data_Entry!T126 -> 7620 | C34: =Data_Entry!V126 -> 3.38 | D34: =B34/(24*I34) -> 0.1316881 | E34: 0 | F34: 0 | G34: =(F34-E34)*24*60 -> 0 | H34: =G34/60 -> 0 | I34: 2411 | K34: =I34*12 -> 28932 | L34: =J34*H34 -> 0 | M34: =(K34-L34)/K34 -> 1 | N34: =D34/M34 -> 0.1316881 | O34: =N34*I34*24 -> 7620 | P34: =O34-B34 -> 0
A35: 45872 | B35: =Data_Entry!T127 -> 7500 | C35: =Data_Entry!V127 -> 3.8 | D35: =B35/(24*I35) -> 0.12961427 | E35: 0 | F35: 0 | G35: =(F35-E35)*24*60 -> 0 | H35: =G35/60 -> 0 | I35: 2411 | K35: =I35*12 -> 28932 | L35: =J35*H35 -> 0 | M35: =(K35-L35)/K35 -> 1 | N35: =D35/M35 -> 0.12961427 | O35: =N35*I35*24 -> 7500 | P35: =O35-B35 -> 0
A36: 45873 | B36: =Data_Entry!T128 -> 8730 | C36: =Data_Entry!V128 -> 3.85 | D36: =B36/(24*I36) -> 0.15087101 | E36: 0 | F36: 0 | G36: =(F36-E36)*24*60 -> 0 | H36: =G36/60 -> 0 | I36: 2411 | K36: =I36*12 -> 28932 | L36: =J36*H36 -> 0 | M36: =(K36-L36)/K36 -> 1 | N36: =D36/M36 -> 0.15087101 | O36: =N36*I36*24 -> 8730 | P36: =O36-B36 -> 0
A37: 45874 | B37: =Data_Entry!T129 -> 9660 | C37: =Data_Entry!V129 -> 3.78 | D37: =B37/(24*I37) -> 0.16694318 | E37: 0 | F37: 0 | G37: =(F37-E37)*24*60 -> 0 | H37: =G37/60 -> 0 | I37: 2411 | K37: =I37*12 -> 28932 | L37: =J37*H37 -> 0 | M37: =(K37-L37)/K37 -> 1 | N37: =D37/M37 -> 0.16694318 | O37: =N37*I37*24 -> 9660 | P37: =O37-B37 -> 0
A38: 45875 | B38: =Data_Entry!T130 -> 7980 | C38: =Data_Entry!V130 -> 3.68 | D38: =B38/(24*I38) -> 0.13790958 | E38: 0 | F38: 0 | G38: =(F38-E38)*24*60 -> 0 | H38: =G38/60 -> 0 | I38: 2411 | K38: =I38*12 -> 28932 | L38: =J38*H38 -> 0 | M38: =(K38-L38)/K38 -> 1 | N38: =D38/M38 -> 0.13790958 | O38: =N38*I38*24 -> 7980 | P38: =O38-B38 -> 0
A39: 45876 | B39: =Data_Entry!T131 -> 8850 | C39: =Data_Entry!V131 -> 3.3 | D39: =B39/(24*I39) -> 0.15294484 | E39: 0 | F39: 0 | G39: =(F39-E39)*24*60 -> 0 | H39: =G39/60 -> 0 | I39: 2411 | K39: =I39*12 -> 28932 | L39: =J39*H39 -> 0 | M39: =(K39-L39)/K39 -> 1 | N39: =D39/M39 -> 0.15294484 | O39: =N39*I39*24 -> 8850 | P39: =O39-B39 -> 0
A40: 45877 | B40: =Data_Entry!T132 -> 11070 | C40: =Data_Entry!V132 -> 4.26 | D40: =B40/(24*I40) -> 0.19131066 | E40: 0 | F40: 0 | G40: =(F40-E40)*24*60 -> 0 | H40: =G40/60 -> 0 | I40: 2411 | K40: =I40*12 -> 28932 | L40: =J40*H40 -> 0 | M40: =(K40-L40)/K40 -> 1 | N40: =D40/M40 -> 0.19131066 | O40: =N40*I40*24 -> 11070 | P40: =O40-B40 -> 0
A41: 45878 | B41: =Data_Entry!T133 -> 8130 | C41: =Data_Entry!V133 -> 3.37 | D41: =B41/(24*I41) -> 0.14050187 | E41: 0 | F41: 0 | G41: =(F41-E41)*24*60 -> 0 | H41: =G41/60 -> 0 | I41: 2411 | K41: =I41*12 -> 28932 | L41: =J41*H41 -> 0 | M41: =(K41-L41)/K41 -> 1 | N41: =D41/M41 -> 0.14050187 | O41: =N41*I41*24 -> 8130 | P41: =O41-B41 -> 0
A42: 45879 | B42: =Data_Entry!T134 -> 7830 | C42: =Data_Entry!V134 -> 3.26 | D42: =B42/(24*I42) -> 0.1353173 | E42: 0 | F42: 0 | G42: =(F42-E42)*24*60 -> 0 | H42: =G42/60 -> 0 | I42: 2411 | K42: =I42*12 -> 28932 | L42: =J42*H42 -> 0 | M42: =(K42-L42)/K42 -> 1 | N42: =D42/M42 -> 0.1353173 | O42: =N42*I42*24 -> 7830 | P42: =O42-B42 -> 0
A43: 45880 | B43: =Data_Entry!T135 -> 9870 | C43: =Data_Entry!V135 -> 3.95 | D43: =B43/(24*I43) -> 0.17057238 | E43: 0 | F43: 0 | G43: =(F43-E43)*24*60 -> 0 | H43: =G43/60 -> 0 | I43: 2411 | K43: =I43*12 -> 28932 | L43: =J43*H43 -> 0 | M43: =(K43-L43)/K43 -> 1 | N43: =D43/M43 -> 0.17057238 | O43: =N43*I43*24 -> 9870 | P43: =O43-B43 -> 0
A44: 45881 | B44: =Data_Entry!T136 -> 9960 | C44: =Data_Entry!V136 -> 4.13 | D44: =B44/(24*I44) -> 0.17212775 | E44: 0 | F44: 0 | G44: =(F44-E44)*24*60 -> 0 | H44: =G44/60 -> 0 | I44: 2411 | K44: =I44*12 -> 28932 | L44: =J44*H44 -> 0 | M44: =(K44-L44)/K44 -> 1 | N44: =D44/M44 -> 0.17212775 | O44: =N44*I44*24 -> 9960 | P44: =O44-B44 -> 0
A45: 45882 | B45: =Data_Entry!T137 -> 8670 | C45: =Data_Entry!V137 -> 3.79 | D45: =B45/(24*I45) -> 0.14983409 | E45: 0 | F45: 0 | G45: =(F45-E45)*24*60 -> 0 | H45: =G45/60 -> 0 | I45: 2411 | K45: =I45*12 -> 28932 | L45: =J45*H45 -> 0 | M45: =(K45-L45)/K45 -> 1 | N45: =D45/M45 -> 0.14983409 | O45: =N45*I45*24 -> 8670 | P45: =O45-B45 -> 0
... A49: 45886 | B49: =Data_Entry!T141 -> 7740 | C49: =Data_Entry!V141 -> 3.32 | D49: =B49/(24*I49) -> 0.13376192 | E49: 0 | F49: 0 | G49: =(F49-E49)*24*60 -> 0 | H49: =G49/60 -> 0 | I49: 2411 | K49: =I49*12 -> 28932 | L49: =J49*H49 -> 0 | M49: =(K49-L49)/K49 -> 1 | N49: =D49/M49 -> 0.13376192 | O49: =N49*I49*24 -> 7740 | P49: =O49-B49 -> 0
A50: 45887 | B50: =Data_Entry!T142 -> 8370 | C50: =Data_Entry!V142 -> 4 | D50: =B50/(24*I50) -> 0.14464952 | E50: 0.41666667 | F50: 0.46180556 | G50: =(F50-E50)*24*60 -> 65 | H50: =G50/60 -> 1.0833333 | I50: 2411 | J50: 2411 | K50: =I50*12 -> 28932 | L50: =J50*H50 -> 2611.9167 | M50: =(K50-L50)/K50 -> 0.90972222 | N50: =D50/M50 -> 0.15900406 | O50: =N50*I50*24 -> 9200.6107 | P50: =O50-B50 -> 830.61069
A51: 45888 | B51: =Data_Entry!T143 -> 7680 | C51: =Data_Entry!V143 -> 0 | D51: =B51/(24*I51) -> 0.13272501 | E51: 0 | F51: 0 | G51: =(F51-E51)*24*60 -> 0 | H51: =G51/60 -> 0 | I51: 2411 | K51: =I51*12 -> 28932 | L51: =J51*H51 -> 0 | M51: =(K51-L51)/K51 -> 1 | N51: =D51/M51 -> 0.13272501 | O51: =N51*I51*24 -> 7680 | P51: =O51-B51 -> 0
A52: 45889 | B52: =Data_Entry!T144 -> 1050 | C52: =Data_Entry!V144 -> 0 | D52: =B52/(24*I52) -> 0.018145998 | E52: 0 | F52: 0 | G52: =(F52-E52)*24*60 -> 0 | H52: =G52/60 -> 0 | I52: 2411 | K52: =I52*12 -> 28932 | L52: =J52*H52 -> 0 | M52: =(K52-L52)/K52 -> 1 | N52: =D52/M52 -> 0.018145998 | O52: =N52*I52*24 -> 1050 | P52: =O52-B52 -> 0
A53: 45890 | B53: =Data_Entry!T145 -> 11040 | C53: =Data_Entry!V145 -> 0 | D53: =B53/(24*I53) -> 0.1907922 | E53: 0 | F53: 0 | G53: =(F53-E53)*24*60 -> 0 | H53: =G53/60 -> 0 | I53: 2411 | K53: =I53*12 -> 28932 | L53: =J53*H53 -> 0 | M53: =(K53-L53)/K53 -> 1 | N53: =D53/M53 -> 0.1907922 | O53: =N53*I53*24 -> 11040 | P53: =O53-B53 -> 0
A54: 45891 | B54: =Data_Entry!T146 -> 10110 | C54: =Data_Entry!V146 -> 0 | D54: =B54/(24*I54) -> 0.17472003 | E54: 0 | F54: 0 | G54: =(F54-E54)*24*60 -> 0 | H54: =G54/60 -> 0 | I54: 2411 | K54: =I54*12 -> 28932 | L54: =J54*H54 -> 0 | M54: =(K54-L54)/K54 -> 1 | N54: =D54/M54 -> 0.17472003 | O54: =N54*I54*24 -> 10110 | P54: =O54-B54 -> 0
A55: 45892 | B55: =Data_Entry!T147 -> 6540 | C55: =Data_Entry!V147 -> 0 | D55: =B55/(24*I55) -> 0.11302364 | E55: 0 | F55: 0 | G55: =(F55-E55)*24*60 -> 0 | H55: =G55/60 -> 0 | I55: 2411 | K55: =I55*12 -> 28932 | L55: =J55*H55 -> 0 | M55: =(K55-L55)/K55 -> 1 | N55: =D55/M55 -> 0.11302364 | O55: =N55*I55*24 -> 6540 | P55: =O55-B55 -> 0
A56: 45893 | B56: =Data_Entry!T148 -> 3060 | C56: =Data_Entry!V148 -> 0 | D56: =B56/(24*I56) -> 0.052882621 | E56: 0 | F56: 0 | G56: =(F56-E56)*24*60 -> 0 | H56: =G56/60 -> 0 | I56: 2411 | K56: =I56*12 -> 28932 | L56: =J56*H56 -> 0 | M56: =(K56-L56)/K56 -> 1 | N56: =D56/M56 -> 0.052882621 | O56: =N56*I56*24 -> 3060 | P56: =O56-B56 -> 0
A57: 45894 | B57: =Data_Entry!T149 -> 7170 | C57: =Data_Entry!V149 -> 0 | D57: =B57/(24*I57) -> 0.12391124 | E57: 0 | F57: 0 | G57: =(F57-E57)*24*60 -> 0 | H57: =G57/60 -> 0 | I57: 2411 | K57: =I57*12 -> 28932 | L57: =J57*H57 -> 0 | M57: =(K57-L57)/K57 -> 1 | N57: =D57/M57 -> 0.12391124 | O57: =N57*I57*24 -> 7170 | P57: =O57-B57 -> 0
A58: 45895 | B58: =Data_Entry!T150 -> 5910 | C58: =Data_Entry!V150 -> 0 | D58: =B58/(24*I58) -> 0.10213604 | E58: 0 | F58: 0 | G58: =(F58-E58)*24*60 -> 0 | H58: =G58/60 -> 0 | I58: 2411 | K58: =I58*12 -> 28932 | L58: =J58*H58 -> 0 | M58: =(K58-L58)/K58 -> 1 | N58: =D58/M58 -> 0.10213604 | O58: =N58*I58*24 -> 5910 | P58: =O58-B58 -> 0
A59: 45896 | B59: =Data_Entry!T151 -> 8580 | C59: =Data_Entry!V151 -> 0 | D59: =B59/(24*I59) -> 0.14827872 | E59: 0 | F59: 0 | G59: =(F59-E59)*24*60 -> 0 | H59: =G59/60 -> 0 | I59: 2411 | K59: =I59*12 -> 28932 | L59: =J59*H59 -> 0 | M59: =(K59-L59)/K59 -> 1 | N59: =D59/M59 -> 0.14827872 | O59: =N59*I59*24 -> 8580 | P59: =O59-B59 -> 0
A60: 45897 | B60: =Data_Entry!T152 -> 8550 | C60: =Data_Entry!V152 -> 0 | D60: =B60/(24*I60) -> 0.14776027 | E60: 0 | F60: 0 | G60: =(F60-E60)*24*60 -> 0 | H60: =G60/60 -> 0 | I60: 2411 | K60: =I60*12 -> 28932 | L60: =J60*H60 -> 0 | M60: =(K60-L60)/K60 -> 1 | N60: =D60/M60 -> 0.14776027 | O60: =N60*I60*24 -> 8550 | P60: =O60-B60 -> 0
A61: 45898 | B61: =Data_Entry!T153 -> 6870 | C61: =Data_Entry!V153 -> 0 | D61: =B61/(24*I61) -> 0.11872667 | E61: 0 | F61: 0 | G61: =(F61-E61)*24*60 -> 0 | H61: =G61/60 -> 0 | I61: 2411 | K61: =I61*12 -> 28932 | L61: =J61*H61 -> 0 | M61: =(K61-L61)/K61 -> 1 | N61: =D61/M61 -> 0.11872667 | O61: =N61*I61*24 -> 6870 | P61: =O61-B61 -> 0
A62: 45899 | B62: =Data_Entry!T154 -> 7080 | C62: =Data_Entry!V154 -> 0 | D62: =B62/(24*I62) -> 0.12235587 | E62: 0 | F62: 0 | G62: =(F62-E62)*24*60 -> 0 | H62: =G62/60 -> 0 | I62: 2411 | K62: =I62*12 -> 28932 | L62: =J62*H62 -> 0 | M62: =(K62-L62)/K62 -> 1 | N62: =D62/M62 -> 0.12235587 | O62: =N62*I62*24 -> 7080 | P62: =O62-B62 -> 0
... A86: 45923 | B86: =Data_Entry!T178 -> 9120 | C86: =Data_Entry!V178 -> 3.65 | D86: =B86/(24*I86) -> 0.15761095 | E86: 0 | F86: 0 | G86: =(F86-E86)*24*60 -> 0 | H86: =G86/60 -> 0 | I86: 2411 | K86: =I86*12 -> 28932 | L86: =J86*H86 -> 0 | M86: =(K86-L86)/K86 -> 1 | N86: =D86/M86 -> 0.15761095 | O86: =N86*I86*24 -> 9120 | P86: =O86-B86 -> 0
A87: 45924 | B87: =Data_Entry!T179 -> 5100 | C87: =Data_Entry!V179 -> 2.06 | D87: =B87/(24*I87) -> 0.088137702 | E87: 0.29166667 | F87: 0.52638889 | G87: =(F87-E87)*24*60 -> 338 | H87: =G87/60 -> 5.6333333 | I87: 2411 | J87: 2411 | K87: =I87*12 -> 28932 | L87: =J87*H87 -> 13581.967 | M87: =(K87-L87)/K87 -> 0.53055556 | N87: =D87/M87 -> 0.16612342 | O87: =N87*I87*24 -> 9612.5654 | P87: =O87-B87 -> 4512.5654
A88: 45925 | B88: =Data_Entry!T180 -> 11010 | C88: =Data_Entry!V180 -> 4.11 | D88: =B88/(24*I88) -> 0.19027375 | E88: 0 | F88: 0 | G88: =(F88-E88)*24*60 -> 0 | H88: =G88/60 -> 0 | I88: 2411 | K88: =I88*12 -> 28932 | L88: =J88*H88 -> 0 | M88: =(K88-L88)/K88 -> 1 | N88: =D88/M88 -> 0.19027375 | O88: =N88*I88*24 -> 11010 | P88: =O88-B88 -> 0
A89: 45926 | B89: =Data_Entry!T181 -> 11820 | C89: =Data_Entry!V181 -> 4.82 | D89: =B89/(24*I89) -> 0.20427209 | E89: 0 | F89: 0 | G89: =(F89-E89)*24*60 -> 0 | H89: =G89/60 -> 0 | I89: 2411 | K89: =I89*12 -> 28932 | L89: =J89*H89 -> 0 | M89: =(K89-L89)/K89 -> 1 | N89: =D89/M89 -> 0.20427209 | O89: =N89*I89*24 -> 11820 | P89: =O89-B89 -> 0
A90: 45927 | B90: =Data_Entry!T182 -> 10440 | C90: =Data_Entry!V182 -> 3.86 | D90: =B90/(24*I90) -> 0.18042306 | E90: 0 | F90: 0 | G90: =(F90-E90)*24*60 -> 0 | H90: =G90/60 -> 0 | I90: 2411 | K90: =I90*12 -> 28932 | L90: =J90*H90 -> 0 | M90: =(K90-L90)/K90 -> 1 | N90: =D90/M90 -> 0.18042306 | O90: =N90*I90*24 -> 10440 | P90: =O90-B90 -> 0
A91: 45928 | B91: =Data_Entry!T183 -> 4200 | C91: =Data_Entry!V183 -> 1.75 | D91: =B91/(24*I91) -> 0.07258399 | E91: 0 | F91: 0 | G91: =(F91-E91)*24*60 -> 0 | H91: =G91/60 -> 0 | I91: 2411 | K91: =I91*12 -> 28932 | L91: =J91*H91 -> 0 | M91: =(K91-L91)/K91 -> 1 | N91: =D91/M91 -> 0.07258399 | O91: =N91*I91*24 -> 4200 | P91: =O91-B91 -> 0
A92: 45929 | B92: =Data_Entry!T184 -> 3930 | C92: =Data_Entry!V184 -> 1.5 | D92: =B92/(24*I92) -> 0.067917876 | E92: 0 | F92: 0 | G92: =(F92-E92)*24*60 -> 0 | H92: =G92/60 -> 0 | I92: 2411 | K92: =I92*12 -> 28932 | L92: =J92*H92 -> 0 | M92: =(K92-L92)/K92 -> 1 | N92: =D92/M92 -> 0.067917876 | O92: =N92*I92*24 -> 3930 | P92: =O92-B92 -> 0
